Workbook

Sheet OpeningDebtors
A1: Sales Date | B1: Customer Name | C1: Sales Invoice Number or reference | E1: Sales Description | G1: =SUM(G5:G300) -> 10800 | H1: =SUM(H5:H300) -> 1800 | I1: =SUM(I5:I300) -> 9000 | K1: For your information only. Enter How Paid e.g. Cash, Cheque etc., | L1: =SUM(L5:L300) -> 0 | M1: =SUM(M5:M300) -> 10800 | N1: =TODAY() -> 46295 | P1: =SUM(P5:P300) -> 0
G2: Sales Value including Vat | H2: =Apr!H2 -> 20 | I2: Sales Net of Vat | L2: Receipts from Customers | P2: Sub contractors only
H3: Vat Output | L3: Actual amount received | M3: Sales Value not yet received | N3: Number of Days Outstanding | P3: CIS Tax Deducted | Q3: CIS Certificate reference
B5: Acme Corp | C5: INV-0901 | G5: 7200 | H5: =IF(H$4>0,(IF(G5<>0,G5*H$4/100," ")),IF(G5<>0,G5*H$2/(100+H$2)," ")) -> 1200 | I5: =IF((G5<>0),G5-H5," ") -> 6000 | M5: =IF(G5<>0,G5-L5," ") -> 7200 | N5: =IF((G5-L5)<>0,N$1-A5," ") -> 46295
B6: Beta Systems | C6: INV-0902 | G6: 1200 | H6: =IF(H$4>0,(IF(G6<>0,G6*H$4/100," ")),IF(G6<>0,G6*H$2/(100+H$2)," ")) -> 200 | I6: =IF((G6<>0),G6-H6," ") -> 1000 | M6: =IF(G6<>0,G6-L6," ") -> 1200 | N6: =IF((G6-L6)<>0,N$1-A6," ") -> 46295
B7: Gamma Ltd | C7: INV-0903 | G7: 2400 | H7: =IF(H$4>0,(IF(G7<>0,G7*H$4/100," ")),IF(G7<>0,G7*H$2/(100+H$2)," ")) -> 400 | I7: =IF((G7<>0),G7-H7," ") -> 2000 | M7: =IF(G7<>0,G7-L7," ") -> 2400 | N7: =IF((G7-L7)<>0,N$1-A7," ") -> 46295
H8: =IF(H$4>0,(IF(G8<>0,G8*H$4/100," ")),IF(G8<>0,G8*H$2/(100+H$2)," ")) | I8: =IF((G8<>0),G8-H8," ") | M8: =IF(G8<>0,G8-L8," ") | N8: =IF((G8-L8)<>0,N$1-A8," ")
H9: =IF(H$4>0,(IF(G9<>0,G9*H$4/100," ")),IF(G9<>0,G9*H$2/(100+H$2)," ")) | I9: =IF((G9<>0),G9-H9," ") | M9: =IF(G9<>0,G9-L9," ") | N9: =IF((G9-L9)<>0,N$1-A9," ")
H10: =IF(H$4>0,(IF(G10<>0,G10*H$4/100," ")),IF(G10<>0,G10*H$2/(100+H$2)," ")) | I10: =IF((G10<>0),G10-H10," ") | M10: =IF(G10<>0,G10-L10," ") | N10: =IF((G10-L10)<>0,N$1-A10," ")
H11: =IF(H$4>0,(IF(G11<>0,G11*H$4/100," ")),IF(G11<>0,G11*H$2/(100+H$2)," ")) | I11: =IF((G11<>0),G11-H11," ") | M11: =IF(G11<>0,G11-L11," ") | N11: =IF((G11-L11)<>0,N$1-A11," ")
H12: =IF(H$4>0,(IF(G12<>0,G12*H$4/100," ")),IF(G12<>0,G12*H$2/(100+H$2)," ")) | I12: =IF((G12<>0),G12-H12," ") | M12: =IF(G12<>0,G12-L12," ") | N12: =IF((G12-L12)<>0,N$1-A12," ")
H13: =IF(H$4>0,(IF(G13<>0,G13*H$4/100," ")),IF(G13<>0,G13*H$2/(100+H$2)," ")) | I13: =IF((G13<>0),G13-H13," ") | M13: =IF(G13<>0,G13-L13," ") | N13: =IF((G13-L13)<>0,N$1-A13," ")
H14: =IF(H$4>0,(IF(G14<>0,G14*H$4/100," ")),IF(G14<>0,G14*H$2/(100+H$2)," ")) | I14: =IF((G14<>0),G14-H14," ") | M14: =IF(G14<>0,G14-L14," ") | N14: =IF((G14-L14)<>0,N$1-A14," ")
H15: =IF(H$4>0,(IF(G15<>0,G15*H$4/100," ")),IF(G15<>0,G15*H$2/(100+H$2)," ")) | I15: =IF((G15<>0),G15-H15," ") | M15: =IF(G15<>0,G15-L15," ") | N15: =IF((G15-L15)<>0,N$1-A15," ")
H16: =IF(H$4>0,(IF(G16<>0,G16*H$4/100," ")),IF(G16<>0,G16*H$2/(100+H$2)," ")) | I16: =IF((G16<>0),G16-H16," ") | M16: =IF(G16<>0,G16-L16," ") | N16: =IF((G16-L16)<>0,N$1-A16," ")
H17: =IF(H$4>0,(IF(G17<>0,G17*H$4/100," ")),IF(G17<>0,G17*H$2/(100+H$2)," ")) | I17: =IF((G17<>0),G17-H17," ") | M17: =IF(G17<>0,G17-L17," ") | N17: =IF((G17-L17)<>0,N$1-A17," ")
H18: =IF(H$4>0,(IF(G18<>0,G18*H$4/100," ")),IF(G18<>0,G18*H$2/(100+H$2)," ")) | I18: =IF((G18<>0),G18-H18," ") | M18: =IF(G18<>0,G18-L18," ") | N18: =IF((G18-L18)<>0,N$1-A18," ")
H19: =IF(H$4>0,(IF(G19<>0,G19*H$4/100," ")),IF(G19<>0,G19*H$2/(100+H$2)," ")) | I19: =IF((G19<>0),G19-H19," ") | M19: =IF(G19<>0,G19-L19," ") | N19: =IF((G19-L19)<>0,N$1-A19," ")
... H300: =IF(H$4>0,(IF(G300<>0,G300*H$4/100," ")),IF(G300<>0,G300*H$2/(100+H$2)," ")) | I300: =IF((G300<>0),G300-H300," ") | M300: =IF(G300<>0,G300-L300," ") | N300: =IF((G300-L300)<>0,N$1-A300," ")

Sheet Apr
A1: =G1-H1-SUM(P1:V1) -> 0 | B1: Check Total | C1: Sales Mileage | D1: =SUM(D5:D300) -> 0 | E1: Sales Description | F1: Enter Expense Code Letter | G1: =SUM(G5:G300) -> 33400 | H1: =SUM(H5:H300) -> 5566.6667 | I1: =SUM(I5:I300) -> 27833.333 | K1: For your information only. Enter How Paid e.g. Cash, Cheque etc., | L1: =SUM(L5:L300) -> 0 | M1: =SUM(M5:M300) -> 33400 | N1: =TODAY() -> 46295 | P1: =SUM(P5:P300) -> 25333.333 | Q1: =SUM(Q5:Q300) -> 1800 | R1: =SUM(R5:R300) -> 0 | S1: =SUM(S5:S300) -> 700 | T1: =SUM(T5:T300) -> 0 | U1: =SUM(U5:U300) -> 0 | V1: =SUM(V5:V300) -> 0 | W1: =SUM(W5:W300) -> 0 | X1: =W1 -> 0
A2: Sales Date | B2: Customer Name | C2: Sales Invoice Number or reference | D2: Sales Mileage | G2: Sales Value including Vat | H2: 20 | I2: Sales Net of Vat | L2: Receipts from Customers | P2: Sales Net of Vat | S2: Other Income | T2: Investment Grants | U2: Bad Debts written off | V2: =V1 -> 0 | W2: Sub contractors only
H3: Vat Output | L3: Actual amount received | M3: Sales Value not yet received | N3: Number of Days Outstanding | P3: Product A | Q3: Product B | R3: Product C | V3: Sale of Fixed Assets | W3: CIS Tax Deducted | X3: CIS Certificate reference
P4: A | Q4: B | R4: C | S4: D | T4: G | U4: O | V4: FS
A5: 46113 | B5: Beta Systems | C5: INV-1301 | E5: Software licence renewal | F5: b | G5: 1200 | H5: =IF(H$4>0,(IF(G5<>0,G5*H$4/100," ")),IF(G5<>0,G5*H$2/(100+H$2)," ")) -> 200 | I5: =IF((G5<>0),G5-H5," ") -> 1000 | M5: =IF(G5<>0,G5-L5," ") -> 1200 | N5: =IF((G5-L5)<>0,N$1-A5," ") -> 182 | P5: =IF((F5="a"),I5," ") | Q5: =IF((F5="b"),I5," ") -> 1000 | R5: =IF((F5="c"),I5," ") | S5: =IF((F5="d"),I5," ") | T5: =IF((F5="g"),I5," ") | U5: =IF((F5="o"),I5," ") | V5: =IF((F5="FS"),I5," ") | BZ5: 4001
A6: 46115 | B6: FreshField Ltd | C6: INV-2601 | E6: Software monitoring licence | F6: b | G6: 360 | H6: =IF(H$4>0,(IF(G6<>0,G6*H$4/100," ")),IF(G6<>0,G6*H$2/(100+H$2)," ")) -> 60 | I6: =IF((G6<>0),G6-H6," ") -> 300 | M6: =IF(G6<>0,G6-L6," ") -> 360 | N6: =IF((G6-L6)<>0,N$1-A6," ") -> 180 | P6: =IF((F6="a"),I6," ") | Q6: =IF((F6="b"),I6," ") -> 300 | R6: =IF((F6="c"),I6," ") | S6: =IF((F6="d"),I6," ") | T6: =IF((F6="g"),I6," ") | U6: =IF((F6="o"),I6," ") | V6: =IF((F6="FS"),I6," ") | BZ6: 4001
A7: 46117 | B7: CloudNine Ltd | C7: INV-1401 | E7: SaaS licence fee | F7: b | G7: 600 | H7: =IF(H$4>0,(IF(G7<>0,G7*H$4/100," ")),IF(G7<>0,G7*H$2/(100+H$2)," ")) -> 100 | I7: =IF((G7<>0),G7-H7," ") -> 500 | M7: =IF(G7<>0,G7-L7," ") -> 600 | N7: =IF((G7-L7)<>0,N$1-A7," ") -> 178 | P7: =IF((F7="a"),I7," ") | Q7: =IF((F7="b"),I7," ") -> 500 | R7: =IF((F7="c"),I7," ") | S7: =IF((F7="d"),I7," ") | T7: =IF((F7="g"),I7," ") | U7: =IF((F7="o"),I7," ") | V7: =IF((F7="FS"),I7," ") | BZ7: 4001
A8: 46120 | B8: Cedar Systems | C8: INV-2401 | E8: Managed services | F8: a | G8: 480 | H8: =IF(H$4>0,(IF(G8<>0,G8*H$4/100," ")),IF(G8<>0,G8*H$2/(100+H$2)," ")) -> 80 | I8: =IF((G8<>0),G8-H8," ") -> 400 | M8: =IF(G8<>0,G8-L8," ") -> 480 | N8: =IF((G8-L8)<>0,N$1-A8," ") -> 175 | P8: =IF((F8="a"),I8," ") -> 400 | Q8: =IF((F8="b"),I8," ") | R8: =IF((F8="c"),I8," ") | S8: =IF((F8="d"),I8," ") | T8: =IF((F8="g"),I8," ") | U8: =IF((F8="o"),I8," ") | V8: =IF((F8="FS"),I8," ") | BZ8: 4000
A9: 46122 | B9: Pinnacle Group | C9: INV-2201 | E9: Monthly support contract | F9: a | G9: 720 | H9: =IF(H$4>0,(IF(G9<>0,G9*H$4/100," ")),IF(G9<>0,G9*H$2/(100+H$2)," ")) -> 120 | I9: =IF((G9<>0),G9-H9," ") -> 600 | M9: =IF(G9<>0,G9-L9," ") -> 720 | N9: =IF((G9-L9)<>0,N$1-A9," ") -> 173 | P9: =IF((F9="a"),I9," ") -> 600 | Q9: =IF((F9="b"),I9," ") | R9: =IF((F9="c"),I9," ") | S9: =IF((F9="d"),I9," ") | T9: =IF((F9="g"),I9," ") | U9: =IF((F9="o"),I9," ") | V9: =IF((F9="FS"),I9," ") | BZ9: 4000
A10: 46127 | B10: Acme Corp | C10: INV-1001 | E10: IT consultancy services | F10: a | G10: 25000 | H10: =IF(H$4>0,(IF(G10<>0,G10*H$4/100," ")),IF(G10<>0,G10*H$2/(100+H$2)," ")) -> 4166.6667 | I10: =IF((G10<>0),G10-H10," ") -> 20833.333 | M10: =IF(G10<>0,G10-L10," ") -> 25000 | N10: =IF((G10-L10)<>0,N$1-A10," ") -> 168 | P10: =IF((F10="a"),I10," ") -> 20833.333 | Q10: =IF((F10="b"),I10," ") | R10: =IF((F10="c"),I10," ") | S10: =IF((F10="d"),I10," ") | T10: =IF((F10="g"),I10," ") | U10: =IF((F10="o"),I10," ") | V10: =IF((F10="FS"),I10," ") | BZ10: 4000
A11: 46130 | B11: TechStart Ltd | C11: INV-1101 | E11: IT consultancy retainer | F11: a | G11: 2400 | H11: =IF(H$4>0,(IF(G11<>0,G11*H$4/100," ")),IF(G11<>0,G11*H$2/(100+H$2)," ")) -> 400 | I11: =IF((G11<>0),G11-H11," ") -> 2000 | M11: =IF(G11<>0,G11-L11," ") -> 2400 | N11: =IF((G11-L11)<>0,N$1-A11," ") -> 165 | P11: =IF((F11="a"),I11," ") -> 2000 | Q11: =IF((F11="b"),I11," ") | R11: =IF((F11="c"),I11," ") | S11: =IF((F11="d"),I11," ") | T11: =IF((F11="g"),I11," ") | U11: =IF((F11="o"),I11," ") | V11: =IF((F11="FS"),I11," ") | BZ11: 4000
A12: 46132 | B12: DataFlow Inc | C12: INV-1201 | E12: Ad-hoc consultancy project | F12: a | G12: 1800 | H12: =IF(H$4>0,(IF(G12<>0,G12*H$4/100," ")),IF(G12<>0,G12*H$2/(100+H$2)," ")) -> 300 | I12: =IF((G12<>0),G12-H12," ") -> 1500 | M12: =IF(G12<>0,G12-L12," ") -> 1800 | N12: =IF((G12-L12)<>0,N$1-A12," ") -> 163 | P12: =IF((F12="a"),I12," ") -> 1500 | Q12: =IF((F12="b"),I12," ") | R12: =IF((F12="c"),I12," ") | S12: =IF((F12="d"),I12," ") | T12: =IF((F12="g"),I12," ") | U12: =IF((F12="o"),I12," ") | V12: =IF((F12="FS"),I12," ") | BZ12: 4000
A13: 46140 | B13: Horizon Analytics | C13: INV-2701 | E13: Data analytics commission | F13: d | G13: 840 | H13: =IF(H$4>0,(IF(G13<>0,G13*H$4/100," ")),IF(G13<>0,G13*H$2/(100+H$2)," ")) -> 140 | I13: =IF((G13<>0),G13-H13," ") -> 700 | M13: =IF(G13<>0,G13-L13," ") -> 840 | N13: =IF((G13-L13)<>0,N$1-A13," ") -> 155 | P13: =IF((F13="a"),I13," ") | Q13: =IF((F13="b"),I13," ") | R13: =IF((F13="c"),I13," ") | S13: =IF((F13="d"),I13," ") -> 700 | T13: =IF((F13="g"),I13," ") | U13: =IF((F13="o"),I13," ") | V13: =IF((F13="FS"),I13," ") | BZ13: 4003
H14: =IF(H$4>0,(IF(G14<>0,G14*H$4/100," ")),IF(G14<>0,G14*H$2/(100+H$2)," ")) | I14: =IF((G14<>0),G14-H14," ") | M14: =IF(G14<>0,G14-L14," ") | N14: =IF((G14-L14)<>0,N$1-A14," ") | P14: =IF((F14="a"),I14," ") | Q14: =IF((F14="b"),I14," ") | R14: =IF((F14="c"),I14," ") | S14: =IF((F14="d"),I14," ") | T14: =IF((F14="g"),I14," ") | U14: =IF((F14="o"),I14," ") | V14: =IF((F14="FS"),I14," ")
H15: =IF(H$4>0,(IF(G15<>0,G15*H$4/100," ")),IF(G15<>0,G15*H$2/(100+H$2)," ")) | I15: =IF((G15<>0),G15-H15," ") | M15: =IF(G15<>0,G15-L15," ") | N15: =IF((G15-L15)<>0,N$1-A15," ") | P15: =IF((F15="a"),I15," ") | Q15: =IF((F15="b"),I15," ") | R15: =IF((F15="c"),I15," ") | S15: =IF((F15="d"),I15," ") | T15: =IF((F15="g"),I15," ") | U15: =IF((F15="o"),I15," ") | V15: =IF((F15="FS"),I15," ")
H16: =IF(H$4>0,(IF(G16<>0,G16*H$4/100," ")),IF(G16<>0,G16*H$2/(100+H$2)," ")) | I16: =IF((G16<>0),G16-H16," ") | M16: =IF(G16<>0,G16-L16," ") | N16: =IF((G16-L16)<>0,N$1-A16," ") | P16: =IF((F16="a"),I16," ") | Q16: =IF((F16="b"),I16," ") | R16: =IF((F16="c"),I16," ") | S16: =IF((F16="d"),I16," ") | T16: =IF((F16="g"),I16," ") | U16: =IF((F16="o"),I16," ") | V16: =IF((F16="FS"),I16," ")
H17: =IF(H$4>0,(IF(G17<>0,G17*H$4/100," ")),IF(G17<>0,G17*H$2/(100+H$2)," ")) | I17: =IF((G17<>0),G17-H17," ") | M17: =IF(G17<>0,G17-L17," ") | N17: =IF((G17-L17)<>0,N$1-A17," ") | P17: =IF((F17="a"),I17," ") | Q17: =IF((F17="b"),I17," ") | R17: =IF((F17="c"),I17," ") | S17: =IF((F17="d"),I17," ") | T17: =IF((F17="g"),I17," ") | U17: =IF((F17="o"),I17," ") | V17: =IF((F17="FS"),I17," ")
H18: =IF(H$4>0,(IF(G18<>0,G18*H$4/100," ")),IF(G18<>0,G18*H$2/(100+H$2)," ")) | I18: =IF((G18<>0),G18-H18," ") | M18: =IF(G18<>0,G18-L18," ") | N18: =IF((G18-L18)<>0,N$1-A18," ") | P18: =IF((F18="a"),I18," ") | Q18: =IF((F18="b"),I18," ") | R18: =IF((F18="c"),I18," ") | S18: =IF((F18="d"),I18," ") | T18: =IF((F18="g"),I18," ") | U18: =IF((F18="o"),I18," ") | V18: =IF((F18="FS"),I18," ")
H19: =IF(H$4>0,(IF(G19<>0,G19*H$4/100," ")),IF(G19<>0,G19*H$2/(100+H$2)," ")) | I19: =IF((G19<>0),G19-H19," ") | M19: =IF(G19<>0,G19-L19," ") | N19: =IF((G19-L19)<>0,N$1-A19," ") | P19: =IF((F19="a"),I19," ") | Q19: =IF((F19="b"),I19," ") | R19: =IF((F19="c"),I19," ") | S19: =IF((F19="d"),I19," ") | T19: =IF((F19="g"),I19," ") | U19: =IF((F19="o"),I19," ") | V19: =IF((F19="FS"),I19," ")
H20: =IF(H$4>0,(IF(G20<>0,G20*H$4/100," ")),IF(G20<>0,G20*H$2/(100+H$2)," ")) | I20: =IF((G20<>0),G20-H20," ") | M20: =IF(G20<>0,G20-L20," ") | N20: =IF((G20-L20)<>0,N$1-A20," ") | P20: =IF((F20="a"),I20," ") | Q20: =IF((F20="b"),I20," ") | R20: =IF((F20="c"),I20," ") | S20: =IF((F20="d"),I20," ") | T20: =IF((F20="g"),I20," ") | U20: =IF((F20="o"),I20," ") | V20: =IF((F20="FS"),I20," ")
H21: =IF(H$4>0,(IF(G21<>0,G21*H$4/100," ")),IF(G21<>0,G21*H$2/(100+H$2)," ")) | I21: =IF((G21<>0),G21-H21," ") | M21: =IF(G21<>0,G21-L21," ") | N21: =IF((G21-L21)<>0,N$1-A21," ") | P21: =IF((F21="a"),I21," ") | Q21: =IF((F21="b"),I21," ") | R21: =IF((F21="c"),I21," ") | S21: =IF((F21="d"),I21," ") | T21: =IF((F21="g"),I21," ") | U21: =IF((F21="o"),I21," ") | V21: =IF((F21="FS"),I21," ")
H22: =IF(H$4>0,(IF(G22<>0,G22*H$4/100," ")),IF(G22<>0,G22*H$2/(100+H$2)," ")) | I22: =IF((G22<>0),G22-H22," ") | M22: =IF(G22<>0,G22-L22," ") | N22: =IF((G22-L22)<>0,N$1-A22," ") | P22: =IF((F22="a"),I22," ") | Q22: =IF((F22="b"),I22," ") | R22: =IF((F22="c"),I22," ") | S22: =IF((F22="d"),I22," ") | T22: =IF((F22="g"),I22," ") | U22: =IF((F22="o"),I22," ") | V22: =IF((F22="FS"),I22," ")
H23: =IF(H$4>0,(IF(G23<>0,G23*H$4/100," ")),IF(G23<>0,G23*H$2/(100+H$2)," ")) | I23: =IF((G23<>0),G23-H23," ") | M23: =IF(G23<>0,G23-L23," ") | N23: =IF((G23-L23)<>0,N$1-A23," ") | P23: =IF((F23="a"),I23," ") | Q23: =IF((F23="b"),I23," ") | R23: =IF((F23="c"),I23," ") | S23: =IF((F23="d"),I23," ") | T23: =IF((F23="g"),I23," ") | U23: =IF((F23="o"),I23," ") | V23: =IF((F23="FS"),I23," ")
H24: =IF(H$4>0,(IF(G24<>0,G24*H$4/100," ")),IF(G24<>0,G24*H$2/(100+H$2)," ")) | I24: =IF((G24<>0),G24-H24," ") | M24: =IF(G24<>0,G24-L24," ") | N24: =IF((G24-L24)<>0,N$1-A24," ") | P24: =IF((F24="a"),I24," ") | Q24: =IF((F24="b"),I24," ") | R24: =IF((F24="c"),I24," ") | S24: =IF((F24="d"),I24," ") | T24: =IF((F24="g"),I24," ") | U24: =IF((F24="o"),I24," ") | V24: =IF((F24="FS"),I24," ")
H25: =IF(H$4>0,(IF(G25<>0,G25*H$4/100," ")),IF(G25<>0,G25*H$2/(100+H$2)," ")) | I25: =IF((G25<>0),G25-H25," ") | M25: =IF(G25<>0,G25-L25," ") | N25: =IF((G25-L25)<>0,N$1-A25," ") | P25: =IF((F25="a"),I25," ") | Q25: =IF((F25="b"),I25," ") | R25: =IF((F25="c"),I25," ") | S25: =IF((F25="d"),I25," ") | T25: =IF((F25="g"),I25," ") | U25: =IF((F25="o"),I25," ") | V25: =IF((F25="FS"),I25," ")
... H69: =IF(H$4>0,(IF(G69<>0,G69*H$4/100," ")),IF(G69<>0,G69*H$2/(100+H$2)," ")) | I69: =IF((G69<>0),G69-H69," ") | M69: =IF(G69<>0,G69-L69," ") | N69: =IF((G69-L69)<>0,N$1-A69," ") | P69: =IF((F69="a"),I69," ") | Q69: =IF((F69="b"),I69," ") | R69: =IF((F69="c"),I69," ") | S69: =IF((F69="d"),I69," ") | T69: =IF((F69="g"),I69," ") | U69: =IF((F69="o"),I69," ") | V69: =IF((F69="FS"),I69," ")
F70: =IF((G70<>0),"Enter Letter"," ") | H70: =IF(H$4>0,(IF(G70<>0,G70*H$4/100," ")),IF(G70<>0,G70*H$2/(100+H$2)," ")) | I70: =IF((G70<>0),G70-H70," ") | M70: =IF(G70<>0,G70-L70," ") | N70: =IF((G70-L70)<>0,N$1-A70," ") | P70: =IF((F70="a"),I70," ") | Q70: =IF((F70="b"),I70," ") | R70: =IF((F70="c"),I70," ") | S70: =IF((F70="d"),I70," ") | T70: =IF((F70="g"),I70," ") | U70: =IF((F70="o"),I70," ") | V70: =IF((F70="FS"),I70," ")
F71: =IF((G71<>0),"Enter Letter"," ") | H71: =IF(H$4>0,(IF(G71<>0,G71*H$4/100," ")),IF(G71<>0,G71*H$2/(100+H$2)," ")) | I71: =IF((G71<>0),G71-H71," ") | M71: =IF(G71<>0,G71-L71," ") | N71: =IF((G71-L71)<>0,N$1-A71," ") | P71: =IF((F71="a"),I71," ") | Q71: =IF((F71="b"),I71," ") | R71: =IF((F71="c"),I71," ") | S71: =IF((F71="d"),I71," ") | T71: =IF((F71="g"),I71," ") | U71: =IF((F71="o"),I71," ") | V71: =IF((F71="FS"),I71," ")
F72: =IF((G72<>0),"Enter Letter"," ") | H72: =IF(H$4>0,(IF(G72<>0,G72*H$4/100," ")),IF(G72<>0,G72*H$2/(100+H$2)," ")) | I72: =IF((G72<>0),G72-H72," ") | M72: =IF(G72<>0,G72-L72," ") | N72: =IF((G72-L72)<>0,N$1-A72," ") | P72: =IF((F72="a"),I72," ") | Q72: =IF((F72="b"),I72," ") | R72: =IF((F72="c"),I72," ") | S72: =IF((F72="d"),I72," ") | T72: =IF((F72="g"),I72," ") | U72: =IF((F72="o"),I72," ") | V72: =IF((F72="FS"),I72," ")
F73: =IF((G73<>0),"Enter Letter"," ") | H73: =IF(H$4>0,(IF(G73<>0,G73*H$4/100," ")),IF(G73<>0,G73*H$2/(100+H$2)," ")) | I73: =IF((G73<>0),G73-H73," ") | M73: =IF(G73<>0,G73-L73," ") | N73: =IF((G73-L73)<>0,N$1-A73," ") | P73: =IF((F73="a"),I73," ") | Q73: =IF((F73="b"),I73," ") | R73: =IF((F73="c"),I73," ") | S73: =IF((F73="d"),I73," ") | T73: =IF((F73="g"),I73," ") | U73: =IF((F73="o"),I73," ") | V73: =IF((F73="FS"),I73," ")
F74: =IF((G74<>0),"Enter Letter"," ") | H74: =IF(H$4>0,(IF(G74<>0,G74*H$4/100," ")),IF(G74<>0,G74*H$2/(100+H$2)," ")) | I74: =IF((G74<>0),G74-H74," ") | M74: =IF(G74<>0,G74-L74," ") | N74: =IF((G74-L74)<>0,N$1-A74," ") | P74: =IF((F74="a"),I74," ") | Q74: =IF((F74="b"),I74," ") | R74: =IF((F74="c"),I74," ") | S74: =IF((F74="d"),I74," ") | T74: =IF((F74="g"),I74," ") | U74: =IF((F74="o"),I74," ") | V74: =IF((F74="FS"),I74," ")
F75: =IF((G75<>0),"Enter Letter"," ") | H75: =IF(H$4>0,(IF(G75<>0,G75*H$4/100," ")),IF(G75<>0,G75*H$2/(100+H$2)," ")) | I75: =IF((G75<>0),G75-H75," ") | M75: =IF(G75<>0,G75-L75," ") | N75: =IF((G75-L75)<>0,N$1-A75," ") | P75: =IF((F75="a"),I75," ") | Q75: =IF((F75="b"),I75," ") | R75: =IF((F75="c"),I75," ") | S75: =IF((F75="d"),I75," ") | T75: =IF((F75="g"),I75," ") | U75: =IF((F75="o"),I75," ") | V75: =IF((F75="FS"),I75," ")
F76: =IF((G76<>0),"Enter Letter"," ") | H76: =IF(H$4>0,(IF(G76<>0,G76*H$4/100," ")),IF(G76<>0,G76*H$2/(100+H$2)," ")) | I76: =IF((G76<>0),G76-H76," ") | M76: =IF(G76<>0,G76-L76," ") | N76: =IF((G76-L76)<>0,N$1-A76," ") | P76: =IF((F76="a"),I76," ") | Q76: =IF((F76="b"),I76," ") | R76: =IF((F76="c"),I76," ") | S76: =IF((F76="d"),I76," ") | T76: =IF((F76="g"),I76," ") | U76: =IF((F76="o"),I76," ") | V76: =IF((F76="FS"),I76," ")
F77: =IF((G77<>0),"Enter Letter"," ") | H77: =IF(H$4>0,(IF(G77<>0,G77*H$4/100," ")),IF(G77<>0,G77*H$2/(100+H$2)," ")) | I77: =IF((G77<>0),G77-H77," ") | M77: =IF(G77<>0,G77-L77," ") | N77: =IF((G77-L77)<>0,N$1-A77," ") | P77: =IF((F77="a"),I77," ") | Q77: =IF((F77="b"),I77," ") | R77: =IF((F77="c"),I77," ") | S77: =IF((F77="d"),I77," ") | T77: =IF((F77="g"),I77," ") | U77: =IF((F77="o"),I77," ") | V77: =IF((F77="FS"),I77," ")
F78: =IF((G78<>0),"Enter Letter"," ") | H78: =IF(H$4>0,(IF(G78<>0,G78*H$4/100," ")),IF(G78<>0,G78*H$2/(100+H$2)," ")) | I78: =IF((G78<>0),G78-H78," ") | M78: =IF(G78<>0,G78-L78," ") | N78: =IF((G78-L78)<>0,N$1-A78," ") | P78: =IF((F78="a"),I78," ") | Q78: =IF((F78="b"),I78," ") | R78: =IF((F78="c"),I78," ") | S78: =IF((F78="d"),I78," ") | T78: =IF((F78="g"),I78," ") | U78: =IF((F78="o"),I78," ") | V78: =IF((F78="FS"),I78," ")
F79: =IF((G79<>0),"Enter Letter"," ") | H79: =IF(H$4>0,(IF(G79<>0,G79*H$4/100," ")),IF(G79<>0,G79*H$2/(100+H$2)," ")) | I79: =IF((G79<>0),G79-H79," ") | M79: =IF(G79<>0,G79-L79," ") | N79: =IF((G79-L79)<>0,N$1-A79," ") | P79: =IF((F79="a"),I79," ") | Q79: =IF((F79="b"),I79," ") | R79: =IF((F79="c"),I79," ") | S79: =IF((F79="d"),I79," ") | T79: =IF((F79="g"),I79," ") | U79: =IF((F79="o"),I79," ") | V79: =IF((F79="FS"),I79," ")
F80: =IF((G80<>0),"Enter Letter"," ") | H80: =IF(H$4>0,(IF(G80<>0,G80*H$4/100," ")),IF(G80<>0,G80*H$2/(100+H$2)," ")) | I80: =IF((G80<>0),G80-H80," ") | M80: =IF(G80<>0,G80-L80," ") | N80: =IF((G80-L80)<>0,N$1-A80," ") | P80: =IF((F80="a"),I80," ") | Q80: =IF((F80="b"),I80," ") | R80: =IF((F80="c"),I80," ") | S80: =IF((F80="d"),I80," ") | T80: =IF((F80="g"),I80," ") | U80: =IF((F80="o"),I80," ") | V80: =IF((F80="FS"),I80," ")
F81: =IF((G81<>0),"Enter Letter"," ") | H81: =IF(H$4>0,(IF(G81<>0,G81*H$4/100," ")),IF(G81<>0,G81*H$2/(100+H$2)," ")) | I81: =IF((G81<>0),G81-H81," ") | M81: =IF(G81<>0,G81-L81," ") | N81: =IF((G81-L81)<>0,N$1-A81," ") | P81: =IF((F81="a"),I81," ") | Q81: =IF((F81="b"),I81," ") | R81: =IF((F81="c"),I81," ") | S81: =IF((F81="d"),I81," ") | T81: =IF((F81="g"),I81," ") | U81: =IF((F81="o"),I81," ") | V81: =IF((F81="FS"),I81," ")
... F300: =IF((G300<>0),"Enter Letter"," ") | H300: =IF(H$4>0,(IF(G300<>0,G300*H$4/100," ")),IF(G300<>0,G300*H$2/(100+H$2)," ")) | I300: =IF((G300<>0),G300-H300," ") | M300: =IF(G300<>0,G300-L300," ") | N300: =IF((G300-L300)<>0,N$1-A300," ") | P300: =IF((F300="a"),I300," ") | Q300: =IF((F300="b"),I300," ") | R300: =IF((F300="c"),I300," ") | S300: =IF((F300="d"),I300," ") | T300: =IF((F300="g"),I300," ") | U300: =IF((F300="o"),I300," ") | V300: =IF((F300="FS"),I300," ")

Sheet May
A1: =G1-H1-SUM(P1:V1) -> 0 | B1: Check Total | C1: Sales Mileage | D1: =SUM(D5:D300) -> 0 | E1: Sales Description | F1: Enter Expense Code Letter | G1: =SUM(G5:G300) -> 32920 | H1: =SUM(H5:H300) -> 5486.6667 | I1: =SUM(I5:I300) -> 27433.333 | K1: For your information only. Enter How Paid e.g. Cash, Cheque etc., | L1: =SUM(L5:L300) -> 0 | M1: =SUM(M5:M300) -> 32920 | N1: =TODAY() -> 46295 | P1: =SUM(P5:P300) -> 25633.333 | Q1: =SUM(Q5:Q300) -> 800 | R1: =SUM(R5:R300) -> 1000 | S1: =SUM(S5:S300) -> 0 | T1: =SUM(T5:T300) -> 0 | U1: =SUM(U5:U300) -> 0 | V1: =SUM(V5:V300) -> 0 | W1: =SUM(W5:W300) -> 0 | X1: =W1+Apr!X1 -> 0
A2: Sales Date | B2: Customer Name | C2: Sales Invoice Number or reference | D2: Sales Mileage | G2: Sales Value including Vat | H2: =Apr!H2 -> 20 | I2: Sales Net of Vat | L2: Receipts from Customers | P2: Sales Net of Vat | S2: Other Income | T2: Investment Grants | U2: Bad Debts written off | V2: =V1+Apr!V2 -> 0 | W2: Sub contractors only
H3: Vat Output | L3: Actual amount received | M3: Sales Value not yet received | N3: Number of Days Outstanding | P3: Product A | Q3: Product B | R3: Product C | V3: Sale of Fixed Assets | W3: CIS Tax Deducted | X3: CIS Certificate reference
H4: =Apr!H4 -> 0 | P4: A | Q4: B | R4: C | S4: D | T4: G | U4: O | V4: FS
A5: 46145 | B5: FreshField Ltd | C5: INV-2602 | E5: Software monitoring licence | F5: b | G5: 360 | H5: =IF(H$4>0,(IF(G5<>0,G5*H$4/100," ")),IF(G5<>0,G5*H$2/(100+H$2)," ")) -> 60 | I5: =IF((G5<>0),G5-H5," ") -> 300 | M5: =IF(G5<>0,G5-L5," ") -> 360 | N5: =IF((G5-L5)<>0,N$1-A5," ") -> 150 | P5: =IF((F5="a"),I5," ") | Q5: =IF((F5="b"),I5," ") -> 300 | R5: =IF((F5="c"),I5," ") | S5: =IF((F5="d"),I5," ") | T5: =IF((F5="g"),I5," ") | U5: =IF((F5="o"),I5," ") | V5: =IF((F5="FS"),I5," ") | BZ5: 4001
A6: 46147 | B6: CloudNine Ltd | C6: INV-1402 | E6: SaaS licence fee | F6: b | G6: 600 | H6: =IF(H$4>0,(IF(G6<>0,G6*H$4/100," ")),IF(G6<>0,G6*H$2/(100+H$2)," ")) -> 100 | I6: =IF((G6<>0),G6-H6," ") -> 500 | M6: =IF(G6<>0,G6-L6," ") -> 600 | N6: =IF((G6-L6)<>0,N$1-A6," ") -> 148 | P6: =IF((F6="a"),I6," ") | Q6: =IF((F6="b"),I6," ") -> 500 | R6: =IF((F6="c"),I6," ") | S6: =IF((F6="d"),I6," ") | T6: =IF((F6="g"),I6," ") | U6: =IF((F6="o"),I6," ") | V6: =IF((F6="FS"),I6," ") | BZ6: 4001
A7: 46150 | B7: Cedar Systems | C7: INV-2402 | E7: Managed services | F7: a | G7: 480 | H7: =IF(H$4>0,(IF(G7<>0,G7*H$4/100," ")),IF(G7<>0,G7*H$2/(100+H$2)," ")) -> 80 | I7: =IF((G7<>0),G7-H7," ") -> 400 | M7: =IF(G7<>0,G7-L7," ") -> 480 | N7: =IF((G7-L7)<>0,N$1-A7," ") -> 145 | P7: =IF((F7="a"),I7," ") -> 400 | Q7: =IF((F7="b"),I7," ") | R7: =IF((F7="c"),I7," ") | S7: =IF((F7="d"),I7," ") | T7: =IF((F7="g"),I7," ") | U7: =IF((F7="o"),I7," ") | V7: =IF((F7="FS"),I7," ") | BZ7: 4000
A8: 46152 | B8: Pinnacle Group | C8: INV-2202 | E8: Monthly support contract | F8: a | G8: 720 | H8: =IF(H$4>0,(IF(G8<>0,G8*H$4/100," ")),IF(G8<>0,G8*H$2/(100+H$2)," ")) -> 120 | I8: =IF((G8<>0),G8-H8," ") -> 600 | M8: =IF(G8<>0,G8-L8," ") -> 720 | N8: =IF((G8-L8)<>0,N$1-A8," ") -> 143 | P8: =IF((F8="a"),I8," ") -> 600 | Q8: =IF((F8="b"),I8," ") | R8: =IF((F8="c"),I8," ") | S8: =IF((F8="d"),I8," ") | T8: =IF((F8="g"),I8," ") | U8: =IF((F8="o"),I8," ") | V8: =IF((F8="FS"),I8," ") | BZ8: 4000
A9: 46154 | B9: QuickFix IT | C9: INV-2001 | E9: IT support consultancy | F9: a | G9: 960 | H9: =IF(H$4>0,(IF(G9<>0,G9*H$4/100," ")),IF(G9<>0,G9*H$2/(100+H$2)," ")) -> 160 | I9: =IF((G9<>0),G9-H9," ") -> 800 | M9: =IF(G9<>0,G9-L9," ") -> 960 | N9: =IF((G9-L9)<>0,N$1-A9," ") -> 141 | P9: =IF((F9="a"),I9," ") -> 800 | Q9: =IF((F9="b"),I9," ") | R9: =IF((F9="c"),I9," ") | S9: =IF((F9="d"),I9," ") | T9: =IF((F9="g"),I9," ") | U9: =IF((F9="o"),I9," ") | V9: =IF((F9="FS"),I9," ") | BZ9: 4000
A10: 46157 | B10: Acme Corp | C10: INV-1002 | E10: IT consultancy services | F10: a | G10: 25000 | H10: =IF(H$4>0,(IF(G10<>0,G10*H$4/100," ")),IF(G10<>0,G10*H$2/(100+H$2)," ")) -> 4166.6667 | I10: =IF((G10<>0),G10-H10," ") -> 20833.333 | M10: =IF(G10<>0,G10-L10," ") -> 25000 | N10: =IF((G10-L10)<>0,N$1-A10," ") -> 138 | P10: =IF((F10="a"),I10," ") -> 20833.333 | Q10: =IF((F10="b"),I10," ") | R10: =IF((F10="c"),I10," ") | S10: =IF((F10="d"),I10," ") | T10: =IF((F10="g"),I10," ") | U10: =IF((F10="o"),I10," ") | V10: =IF((F10="FS"),I10," ") | BZ10: 4000
A11: 46158 | B11: Summit Training | C11: INV-2801 | E11: Technical training delivery | F11: c | G11: 1200 | H11: =IF(H$4>0,(IF(G11<>0,G11*H$4/100," ")),IF(G11<>0,G11*H$2/(100+H$2)," ")) -> 200 | I11: =IF((G11<>0),G11-H11," ") -> 1000 | M11: =IF(G11<>0,G11-L11," ") -> 1200 | N11: =IF((G11-L11)<>0,N$1-A11," ") -> 137 | P11: =IF((F11="a"),I11," ") | Q11: =IF((F11="b"),I11," ") | R11: =IF((F11="c"),I11," ") -> 1000 | S11: =IF((F11="d"),I11," ") | T11: =IF((F11="g"),I11," ") | U11: =IF((F11="o"),I11," ") | V11: =IF((F11="FS"),I11," ") | BZ11: 4002
A12: 46160 | B12: TechStart Ltd | C12: INV-1102 | E12: IT consultancy retainer | F12: a | G12: 2400 | H12: =IF(H$4>0,(IF(G12<>0,G12*H$4/100," ")),IF(G12<>0,G12*H$2/(100+H$2)," ")) -> 400 | I12: =IF((G12<>0),G12-H12," ") -> 2000 | M12: =IF(G12<>0,G12-L12," ") -> 2400 | N12: =IF((G12-L12)<>0,N$1-A12," ") -> 135 | P12: =IF((F12="a"),I12," ") -> 2000 | Q12: =IF((F12="b"),I12," ") | R12: =IF((F12="c"),I12," ") | S12: =IF((F12="d"),I12," ") | T12: =IF((F12="g"),I12," ") | U12: =IF((F12="o"),I12," ") | V12: =IF((F12="FS"),I12," ") | BZ12: 4000
A13: 46167 | B13: Oakridge Partners | C13: INV-2501 | E13: Quarterly consulting engagement | F13: a | G13: 1200 | H13: =IF(H$4>0,(IF(G13<>0,G13*H$4/100," ")),IF(G13<>0,G13*H$2/(100+H$2)," ")) -> 200 | I13: =IF((G13<>0),G13-H13," ") -> 1000 | M13: =IF(G13<>0,G13-L13," ") -> 1200 | N13: =IF((G13-L13)<>0,N$1-A13," ") -> 128 | P13: =IF((F13="a"),I13," ") -> 1000 | Q13: =IF((F13="b"),I13," ") | R13: =IF((F13="c"),I13," ") | S13: =IF((F13="d"),I13," ") | T13: =IF((F13="g"),I13," ") | U13: =IF((F13="o"),I13," ") | V13: =IF((F13="FS"),I13," ") | BZ13: 4000
H14: =IF(H$4>0,(IF(G14<>0,G14*H$4/100," ")),IF(G14<>0,G14*H$2/(100+H$2)," ")) | I14: =IF((G14<>0),G14-H14," ") | M14: =IF(G14<>0,G14-L14," ") | N14: =IF((G14-L14)<>0,N$1-A14," ") | P14: =IF((F14="a"),I14," ") | Q14: =IF((F14="b"),I14," ") | R14: =IF((F14="c"),I14," ") | S14: =IF((F14="d"),I14," ") | T14: =IF((F14="g"),I14," ") | U14: =IF((F14="o"),I14," ") | V14: =IF((F14="FS"),I14," ")
H15: =IF(H$4>0,(IF(G15<>0,G15*H$4/100," ")),IF(G15<>0,G15*H$2/(100+H$2)," ")) | I15: =IF((G15<>0),G15-H15," ") | M15: =IF(G15<>0,G15-L15," ") | N15: =IF((G15-L15)<>0,N$1-A15," ") | P15: =IF((F15="a"),I15," ") | Q15: =IF((F15="b"),I15," ") | R15: =IF((F15="c"),I15," ") | S15: =IF((F15="d"),I15," ") | T15: =IF((F15="g"),I15," ") | U15: =IF((F15="o"),I15," ") | V15: =IF((F15="FS"),I15," ")
H16: =IF(H$4>0,(IF(G16<>0,G16*H$4/100," ")),IF(G16<>0,G16*H$2/(100+H$2)," ")) | I16: =IF((G16<>0),G16-H16," ") | M16: =IF(G16<>0,G16-L16," ") | N16: =IF((G16-L16)<>0,N$1-A16," ") | P16: =IF((F16="a"),I16," ") | Q16: =IF((F16="b"),I16," ") | R16: =IF((F16="c"),I16," ") | S16: =IF((F16="d"),I16," ") | T16: =IF((F16="g"),I16," ") | U16: =IF((F16="o"),I16," ") | V16: =IF((F16="FS"),I16," ")
H17: =IF(H$4>0,(IF(G17<>0,G17*H$4/100," ")),IF(G17<>0,G17*H$2/(100+H$2)," ")) | I17: =IF((G17<>0),G17-H17," ") | M17: =IF(G17<>0,G17-L17," ") | N17: =IF((G17-L17)<>0,N$1-A17," ") | P17: =IF((F17="a"),I17," ") | Q17: =IF((F17="b"),I17," ") | R17: =IF((F17="c"),I17," ") | S17: =IF((F17="d"),I17," ") | T17: =IF((F17="g"),I17," ") | U17: =IF((F17="o"),I17," ") | V17: =IF((F17="FS"),I17," ")
H18: =IF(H$4>0,(IF(G18<>0,G18*H$4/100," ")),IF(G18<>0,G18*H$2/(100+H$2)," ")) | I18: =IF((G18<>0),G18-H18," ") | M18: =IF(G18<>0,G18-L18," ") | N18: =IF((G18-L18)<>0,N$1-A18," ") | P18: =IF((F18="a"),I18," ") | Q18: =IF((F18="b"),I18," ") | R18: =IF((F18="c"),I18," ") | S18: =IF((F18="d"),I18," ") | T18: =IF((F18="g"),I18," ") | U18: =IF((F18="o"),I18," ") | V18: =IF((F18="FS"),I18," ")
H19: =IF(H$4>0,(IF(G19<>0,G19*H$4/100," ")),IF(G19<>0,G19*H$2/(100+H$2)," ")) | I19: =IF((G19<>0),G19-H19," ") | M19: =IF(G19<>0,G19-L19," ") | N19: =IF((G19-L19)<>0,N$1-A19," ") | P19: =IF((F19="a"),I19," ") | Q19: =IF((F19="b"),I19," ") | R19: =IF((F19="c"),I19," ") | S19: =IF((F19="d"),I19," ") | T19: =IF((F19="g"),I19," ") | U19: =IF((F19="o"),I19," ") | V19: =IF((F19="FS"),I19," ")
H20: =IF(H$4>0,(IF(G20<>0,G20*H$4/100," ")),IF(G20<>0,G20*H$2/(100+H$2)," ")) | I20: =IF((G20<>0),G20-H20," ") | M20: =IF(G20<>0,G20-L20," ") | N20: =IF((G20-L20)<>0,N$1-A20," ") | P20: =IF((F20="a"),I20," ") | Q20: =IF((F20="b"),I20," ") | R20: =IF((F20="c"),I20," ") | S20: =IF((F20="d"),I20," ") | T20: =IF((F20="g"),I20," ") | U20: =IF((F20="o"),I20," ") | V20: =IF((F20="FS"),I20," ")
H21: =IF(H$4>0,(IF(G21<>0,G21*H$4/100," ")),IF(G21<>0,G21*H$2/(100+H$2)," ")) | I21: =IF((G21<>0),G21-H21," ") | M21: =IF(G21<>0,G21-L21," ") | N21: =IF((G21-L21)<>0,N$1-A21," ") | P21: =IF((F21="a"),I21," ") | Q21: =IF((F21="b"),I21," ") | R21: =IF((F21="c"),I21," ") | S21: =IF((F21="d"),I21," ") | T21: =IF((F21="g"),I21," ") | U21: =IF((F21="o"),I21," ") | V21: =IF((F21="FS"),I21," ")
H22: =IF(H$4>0,(IF(G22<>0,G22*H$4/100," ")),IF(G22<>0,G22*H$2/(100+H$2)," ")) | I22: =IF((G22<>0),G22-H22," ") | M22: =IF(G22<>0,G22-L22," ") | N22: =IF((G22-L22)<>0,N$1-A22," ") | P22: =IF((F22="a"),I22," ") | Q22: =IF((F22="b"),I22," ") | R22: =IF((F22="c"),I22," ") | S22: =IF((F22="d"),I22," ") | T22: =IF((F22="g"),I22," ") | U22: =IF((F22="o"),I22," ") | V22: =IF((F22="FS"),I22," ")
H23: =IF(H$4>0,(IF(G23<>0,G23*H$4/100," ")),IF(G23<>0,G23*H$2/(100+H$2)," ")) | I23: =IF((G23<>0),G23-H23," ") | M23: =IF(G23<>0,G23-L23," ") | N23: =IF((G23-L23)<>0,N$1-A23," ") | P23: =IF((F23="a"),I23," ") | Q23: =IF((F23="b"),I23," ") | R23: =IF((F23="c"),I23," ") | S23: =IF((F23="d"),I23," ") | T23: =IF((F23="g"),I23," ") | U23: =IF((F23="o"),I23," ") | V23: =IF((F23="FS"),I23," ")
H24: =IF(H$4>0,(IF(G24<>0,G24*H$4/100," ")),IF(G24<>0,G24*H$2/(100+H$2)," ")) | I24: =IF((G24<>0),G24-H24," ") | M24: =IF(G24<>0,G24-L24," ") | N24: =IF((G24-L24)<>0,N$1-A24," ") | P24: =IF((F24="a"),I24," ") | Q24: =IF((F24="b"),I24," ") | R24: =IF((F24="c"),I24," ") | S24: =IF((F24="d"),I24," ") | T24: =IF((F24="g"),I24," ") | U24: =IF((F24="o"),I24," ") | V24: =IF((F24="FS"),I24," ")
H25: =IF(H$4>0,(IF(G25<>0,G25*H$4/100," ")),IF(G25<>0,G25*H$2/(100+H$2)," ")) | I25: =IF((G25<>0),G25-H25," ") | M25: =IF(G25<>0,G25-L25," ") | N25: =IF((G25-L25)<>0,N$1-A25," ") | P25: =IF((F25="a"),I25," ") | Q25: =IF((F25="b"),I25," ") | R25: =IF((F25="c"),I25," ") | S25: =IF((F25="d"),I25," ") | T25: =IF((F25="g"),I25," ") | U25: =IF((F25="o"),I25," ") | V25: =IF((F25="FS"),I25," ")
... H68: =IF(H$4>0,(IF(G68<>0,G68*H$4/100," ")),IF(G68<>0,G68*H$2/(100+H$2)," ")) | I68: =IF((G68<>0),G68-H68," ") | M68: =IF(G68<>0,G68-L68," ") | N68: =IF((G68-L68)<>0,N$1-A68," ") | P68: =IF((F68="a"),I68," ") | Q68: =IF((F68="b"),I68," ") | R68: =IF((F68="c"),I68," ") | S68: =IF((F68="d"),I68," ") | T68: =IF((F68="g"),I68," ") | U68: =IF((F68="o"),I68," ") | V68: =IF((F68="FS"),I68," ")
F69: =IF((G69<>0),"Enter Letter"," ") | H69: =IF(H$4>0,(IF(G69<>0,G69*H$4/100," ")),IF(G69<>0,G69*H$2/(100+H$2)," ")) | I69: =IF((G69<>0),G69-H69," ") | M69: =IF(G69<>0,G69-L69," ") | N69: =IF((G69-L69)<>0,N$1-A69," ") | P69: =IF((F69="a"),I69," ") | Q69: =IF((F69="b"),I69," ") | R69: =IF((F69="c"),I69," ") | S69: =IF((F69="d"),I69," ") | T69: =IF((F69="g"),I69," ") | U69: =IF((F69="o"),I69," ") | V69: =IF((F69="FS"),I69," ")
F70: =IF((G70<>0),"Enter Letter"," ") | H70: =IF(H$4>0,(IF(G70<>0,G70*H$4/100," ")),IF(G70<>0,G70*H$2/(100+H$2)," ")) | I70: =IF((G70<>0),G70-H70," ") | M70: =IF(G70<>0,G70-L70," ") | N70: =IF((G70-L70)<>0,N$1-A70," ") | P70: =IF((F70="a"),I70," ") | Q70: =IF((F70="b"),I70," ") | R70: =IF((F70="c"),I70," ") | S70: =IF((F70="d"),I70," ") | T70: =IF((F70="g"),I70," ") | U70: =IF((F70="o"),I70," ") | V70: =IF((F70="FS"),I70," ")
F71: =IF((G71<>0),"Enter Letter"," ") | H71: =IF(H$4>0,(IF(G71<>0,G71*H$4/100," ")),IF(G71<>0,G71*H$2/(100+H$2)," ")) | I71: =IF((G71<>0),G71-H71," ") | M71: =IF(G71<>0,G71-L71," ") | N71: =IF((G71-L71)<>0,N$1-A71," ") | P71: =IF((F71="a"),I71," ") | Q71: =IF((F71="b"),I71," ") | R71: =IF((F71="c"),I71," ") | S71: =IF((F71="d"),I71," ") | T71: =IF((F71="g"),I71," ") | U71: =IF((F71="o"),I71," ") | V71: =IF((F71="FS"),I71," ")
F72: =IF((G72<>0),"Enter Letter"," ") | H72: =IF(H$4>0,(IF(G72<>0,G72*H$4/100," ")),IF(G72<>0,G72*H$2/(100+H$2)," ")) | I72: =IF((G72<>0),G72-H72," ") | M72: =IF(G72<>0,G72-L72," ") | N72: =IF((G72-L72)<>0,N$1-A72," ") | P72: =IF((F72="a"),I72," ") | Q72: =IF((F72="b"),I72," ") | R72: =IF((F72="c"),I72," ") | S72: =IF((F72="d"),I72," ") | T72: =IF((F72="g"),I72," ") | U72: =IF((F72="o"),I72," ") | V72: =IF((F72="FS"),I72," ")
F73: =IF((G73<>0),"Enter Letter"," ") | H73: =IF(H$4>0,(IF(G73<>0,G73*H$4/100," ")),IF(G73<>0,G73*H$2/(100+H$2)," ")) | I73: =IF((G73<>0),G73-H73," ") | M73: =IF(G73<>0,G73-L73," ") | N73: =IF((G73-L73)<>0,N$1-A73," ") | P73: =IF((F73="a"),I73," ") | Q73: =IF((F73="b"),I73," ") | R73: =IF((F73="c"),I73," ") | S73: =IF((F73="d"),I73," ") | T73: =IF((F73="g"),I73," ") | U73: =IF((F73="o"),I73," ") | V73: =IF((F73="FS"),I73," ")
F74: =IF((G74<>0),"Enter Letter"," ") | H74: =IF(H$4>0,(IF(G74<>0,G74*H$4/100," ")),IF(G74<>0,G74*H$2/(100+H$2)," ")) | I74: =IF((G74<>0),G74-H74," ") | M74: =IF(G74<>0,G74-L74," ") | N74: =IF((G74-L74)<>0,N$1-A74," ") | P74: =IF((F74="a"),I74," ") | Q74: =IF((F74="b"),I74," ") | R74: =IF((F74="c"),I74," ") | S74: =IF((F74="d"),I74," ") | T74: =IF((F74="g"),I74," ") | U74: =IF((F74="o"),I74," ") | V74: =IF((F74="FS"),I74," ")
F75: =IF((G75<>0),"Enter Letter"," ") | H75: =IF(H$4>0,(IF(G75<>0,G75*H$4/100," ")),IF(G75<>0,G75*H$2/(100+H$2)," ")) | I75: =IF((G75<>0),G75-H75," ") | M75: =IF(G75<>0,G75-L75," ") | N75: =IF((G75-L75)<>0,N$1-A75," ") | P75: =IF((F75="a"),I75," ") | Q75: =IF((F75="b"),I75," ") | R75: =IF((F75="c"),I75," ") | S75: =IF((F75="d"),I75," ") | T75: =IF((F75="g"),I75," ") | U75: =IF((F75="o"),I75," ") | V75: =IF((F75="FS"),I75," ")
F76: =IF((G76<>0),"Enter Letter"," ") | H76: =IF(H$4>0,(IF(G76<>0,G76*H$4/100," ")),IF(G76<>0,G76*H$2/(100+H$2)," ")) | I76: =IF((G76<>0),G76-H76," ") | M76: =IF(G76<>0,G76-L76," ") | N76: =IF((G76-L76)<>0,N$1-A76," ") | P76: =IF((F76="a"),I76," ") | Q76: =IF((F76="b"),I76," ") | R76: =IF((F76="c"),I76," ") | S76: =IF((F76="d"),I76," ") | T76: =IF((F76="g"),I76," ") | U76: =IF((F76="o"),I76," ") | V76: =IF((F76="FS"),I76," ")
F77: =IF((G77<>0),"Enter Letter"," ") | H77: =IF(H$4>0,(IF(G77<>0,G77*H$4/100," ")),IF(G77<>0,G77*H$2/(100+H$2)," ")) | I77: =IF((G77<>0),G77-H77," ") | M77: =IF(G77<>0,G77-L77," ") | N77: =IF((G77-L77)<>0,N$1-A77," ") | P77: =IF((F77="a"),I77," ") | Q77: =IF((F77="b"),I77," ") | R77: =IF((F77="c"),I77," ") | S77: =IF((F77="d"),I77," ") | T77: =IF((F77="g"),I77," ") | U77: =IF((F77="o"),I77," ") | V77: =IF((F77="FS"),I77," ")
F78: =IF((G78<>0),"Enter Letter"," ") | H78: =IF(H$4>0,(IF(G78<>0,G78*H$4/100," ")),IF(G78<>0,G78*H$2/(100+H$2)," ")) | I78: =IF((G78<>0),G78-H78," ") | M78: =IF(G78<>0,G78-L78," ") | N78: =IF((G78-L78)<>0,N$1-A78," ") | P78: =IF((F78="a"),I78," ") | Q78: =IF((F78="b"),I78," ") | R78: =IF((F78="c"),I78," ") | S78: =IF((F78="d"),I78," ") | T78: =IF((F78="g"),I78," ") | U78: =IF((F78="o"),I78," ") | V78: =IF((F78="FS"),I78," ")
F79: =IF((G79<>0),"Enter Letter"," ") | H79: =IF(H$4>0,(IF(G79<>0,G79*H$4/100," ")),IF(G79<>0,G79*H$2/(100+H$2)," ")) | I79: =IF((G79<>0),G79-H79," ") | M79: =IF(G79<>0,G79-L79," ") | N79: =IF((G79-L79)<>0,N$1-A79," ") | P79: =IF((F79="a"),I79," ") | Q79: =IF((F79="b"),I79," ") | R79: =IF((F79="c"),I79," ") | S79: =IF((F79="d"),I79," ") | T79: =IF((F79="g"),I79," ") | U79: =IF((F79="o"),I79," ") | V79: =IF((F79="FS"),I79," ")
F80: =IF((G80<>0),"Enter Letter"," ") | H80: =IF(H$4>0,(IF(G80<>0,G80*H$4/100," ")),IF(G80<>0,G80*H$2/(100+H$2)," ")) | I80: =IF((G80<>0),G80-H80," ") | M80: =IF(G80<>0,G80-L80," ") | N80: =IF((G80-L80)<>0,N$1-A80," ") | P80: =IF((F80="a"),I80," ") | Q80: =IF((F80="b"),I80," ") | R80: =IF((F80="c"),I80," ") | S80: =IF((F80="d"),I80," ") | T80: =IF((F80="g"),I80," ") | U80: =IF((F80="o"),I80," ") | V80: =IF((F80="FS"),I80," ")
... F300: =IF((G300<>0),"Enter Letter"," ") | H300: =IF(H$4>0,(IF(G300<>0,G300*H$4/100," ")),IF(G300<>0,G300*H$2/(100+H$2)," ")) | I300: =IF((G300<>0),G300-H300," ") | M300: =IF(G300<>0,G300-L300," ") | N300: =IF((G300-L300)<>0,N$1-A300," ") | P300: =IF((F300="a"),I300," ") | Q300: =IF((F300="b"),I300," ") | R300: =IF((F300="c"),I300," ") | S300: =IF((F300="d"),I300," ") | T300: =IF((F300="g"),I300," ") | U300: =IF((F300="o"),I300," ") | V300: =IF((F300="FS"),I300," ")

Sheet Jun
A1: =G1-H1-SUM(P1:V1) -> 0 | B1: Check Total | C1: Sales Mileage | D1: =SUM(D5:D300) -> 0 | E1: Sales Description | F1: Enter Expense Code Letter | G1: =SUM(G5:G300) -> 35200 | H1: =SUM(H5:H300) -> 5866.6667 | I1: =SUM(I5:I300) -> 29333.333 | K1: For your information only. Enter How Paid e.g. Cash, Cheque etc., | L1: =SUM(L5:L300) -> 0 | M1: =SUM(M5:M300) -> 35200 | N1: =TODAY() -> 46295 | P1: =SUM(P5:P300) -> 26533.333 | Q1: =SUM(Q5:Q300) -> 800 | R1: =SUM(R5:R300) -> 2000 | S1: =SUM(S5:S300) -> 0 | T1: =SUM(T5:T300) -> 0 | U1: =SUM(U5:U300) -> 0 | V1: =SUM(V5:V300) -> 0 | W1: =SUM(W5:W300) -> 0 | X1: =W1+May!X1 -> 0
A2: Sales Date | B2: Customer Name | C2: Sales Invoice Number or reference | D2: Sales Mileage | G2: Sales Value including Vat | H2: =May!H2 -> 20 | I2: Sales Net of Vat | L2: Receipts from Customers | P2: Sales Net of Vat | S2: Other Income | T2: Investment Grants | U2: Bad Debts written off | V2: =V1+May!V2 -> 0 | W2: Sub contractors only
H3: Vat Output | L3: Actual amount received | M3: Sales Value not yet received | N3: Number of Days Outstanding | P3: Product A | Q3: Product B | R3: Product C | V3: Sale of Fixed Assets | W3: CIS Tax Deducted | X3: CIS Certificate reference
H4: =May!H4 -> 0 | P4: A | Q4: B | R4: C | S4: D | T4: G | U4: O | V4: FS
A5: 46176 | B5: FreshField Ltd | C5: INV-2603 | E5: Software monitoring licence | F5: b | G5: 360 | H5: =IF(H$4>0,(IF(G5<>0,G5*H$4/100," ")),IF(G5<>0,G5*H$2/(100+H$2)," ")) -> 60 | I5: =IF((G5<>0),G5-H5," ") -> 300 | M5: =IF(G5<>0,G5-L5," ") -> 360 | N5: =IF((G5-L5)<>0,N$1-A5," ") -> 119 | P5: =IF((F5="a"),I5," ") | Q5: =IF((F5="b"),I5," ") -> 300 | R5: =IF((F5="c"),I5," ") | S5: =IF((F5="d"),I5," ") | T5: =IF((F5="g"),I5," ") | U5: =IF((F5="o"),I5," ") | V5: =IF((F5="FS"),I5," ") | BZ5: 4001
A6: 46178 | B6: CloudNine Ltd | C6: INV-1403 | E6: SaaS licence fee | F6: b | G6: 600 | H6: =IF(H$4>0,(IF(G6<>0,G6*H$4/100," ")),IF(G6<>0,G6*H$2/(100+H$2)," ")) -> 100 | I6: =IF((G6<>0),G6-H6," ") -> 500 | M6: =IF(G6<>0,G6-L6," ") -> 600 | N6: =IF((G6-L6)<>0,N$1-A6," ") -> 117 | P6: =IF((F6="a"),I6," ") | Q6: =IF((F6="b"),I6," ") -> 500 | R6: =IF((F6="c"),I6," ") | S6: =IF((F6="d"),I6," ") | T6: =IF((F6="g"),I6," ") | U6: =IF((F6="o"),I6," ") | V6: =IF((F6="FS"),I6," ") | BZ6: 4001
A7: 46181 | B7: Cedar Systems | C7: INV-2403 | E7: Managed services | F7: a | G7: 480 | H7: =IF(H$4>0,(IF(G7<>0,G7*H$4/100," ")),IF(G7<>0,G7*H$2/(100+H$2)," ")) -> 80 | I7: =IF((G7<>0),G7-H7," ") -> 400 | M7: =IF(G7<>0,G7-L7," ") -> 480 | N7: =IF((G7-L7)<>0,N$1-A7," ") -> 114 | P7: =IF((F7="a"),I7," ") -> 400 | Q7: =IF((F7="b"),I7," ") | R7: =IF((F7="c"),I7," ") | S7: =IF((F7="d"),I7," ") | T7: =IF((F7="g"),I7," ") | U7: =IF((F7="o"),I7," ") | V7: =IF((F7="FS"),I7," ") | BZ7: 4000
A8: 46183 | B8: Pinnacle Group | C8: INV-2203 | E8: Monthly support contract | F8: a | G8: 720 | H8: =IF(H$4>0,(IF(G8<>0,G8*H$4/100," ")),IF(G8<>0,G8*H$2/(100+H$2)," ")) -> 120 | I8: =IF((G8<>0),G8-H8," ") -> 600 | M8: =IF(G8<>0,G8-L8," ") -> 720 | N8: =IF((G8-L8)<>0,N$1-A8," ") -> 112 | P8: =IF((F8="a"),I8," ") -> 600 | Q8: =IF((F8="b"),I8," ") | R8: =IF((F8="c"),I8," ") | S8: =IF((F8="d"),I8," ") | T8: =IF((F8="g"),I8," ") | U8: =IF((F8="o"),I8," ") | V8: =IF((F8="FS"),I8," ") | BZ8: 4000
A9: 46188 | B9: Acme Corp | C9: INV-1003 | E9: IT consultancy services | F9: a | G9: 25000 | H9: =IF(H$4>0,(IF(G9<>0,G9*H$4/100," ")),IF(G9<>0,G9*H$2/(100+H$2)," ")) -> 4166.6667 | I9: =IF((G9<>0),G9-H9," ") -> 20833.333 | M9: =IF(G9<>0,G9-L9," ") -> 25000 | N9: =IF((G9-L9)<>0,N$1-A9," ") -> 107 | P9: =IF((F9="a"),I9," ") -> 20833.333 | Q9: =IF((F9="b"),I9," ") | R9: =IF((F9="c"),I9," ") | S9: =IF((F9="d"),I9," ") | T9: =IF((F9="g"),I9," ") | U9: =IF((F9="o"),I9," ") | V9: =IF((F9="FS"),I9," ") | BZ9: 4000
A10: 46191 | B10: TechStart Ltd | C10: INV-1103 | E10: IT consultancy retainer | F10: a | G10: 2400 | H10: =IF(H$4>0,(IF(G10<>0,G10*H$4/100," ")),IF(G10<>0,G10*H$2/(100+H$2)," ")) -> 400 | I10: =IF((G10<>0),G10-H10," ") -> 2000 | M10: =IF(G10<>0,G10-L10," ") -> 2400 | N10: =IF((G10-L10)<>0,N$1-A10," ") -> 104 | P10: =IF((F10="a"),I10," ") -> 2000 | Q10: =IF((F10="b"),I10," ") | R10: =IF((F10="c"),I10," ") | S10: =IF((F10="d"),I10," ") | T10: =IF((F10="g"),I10," ") | U10: =IF((F10="o"),I10," ") | V10: =IF((F10="FS"),I10," ") | BZ10: 4000
A11: 46193 | B11: DataFlow Inc | C11: INV-1202 | E11: Ad-hoc consultancy project | F11: a | G11: 1800 | H11: =IF(H$4>0,(IF(G11<>0,G11*H$4/100," ")),IF(G11<>0,G11*H$2/(100+H$2)," ")) -> 300 | I11: =IF((G11<>0),G11-H11," ") -> 1500 | M11: =IF(G11<>0,G11-L11," ") -> 1800 | N11: =IF((G11-L11)<>0,N$1-A11," ") -> 102 | P11: =IF((F11="a"),I11," ") -> 1500 | Q11: =IF((F11="b"),I11," ") | R11: =IF((F11="c"),I11," ") | S11: =IF((F11="d"),I11," ") | T11: =IF((F11="g"),I11," ") | U11: =IF((F11="o"),I11," ") | V11: =IF((F11="FS"),I11," ") | BZ11: 4000
A12: 46193 | B12: Gamma Ltd | C12: INV-1501 | E12: Advanced DevOps training course | F12: c | G12: 2400 | H12: =IF(H$4>0,(IF(G12<>0,G12*H$4/100," ")),IF(G12<>0,G12*H$2/(100+H$2)," ")) -> 400 | I12: =IF((G12<>0),G12-H12," ") -> 2000 | M12: =IF(G12<>0,G12-L12," ") -> 2400 | N12: =IF((G12-L12)<>0,N$1-A12," ") -> 102 | P12: =IF((F12="a"),I12," ") | Q12: =IF((F12="b"),I12," ") | R12: =IF((F12="c"),I12," ") -> 2000 | S12: =IF((F12="d"),I12," ") | T12: =IF((F12="g"),I12," ") | U12: =IF((F12="o"),I12," ") | V12: =IF((F12="FS"),I12," ") | BZ12: 4002
A13: 46195 | B13: WidgetWorks | C13: INV-2101 | E13: Project consultancy | F13: a | G13: 1440 | H13: =IF(H$4>0,(IF(G13<>0,G13*H$4/100," ")),IF(G13<>0,G13*H$2/(100+H$2)," ")) -> 240 | I13: =IF((G13<>0),G13-H13," ") -> 1200 | M13: =IF(G13<>0,G13-L13," ") -> 1440 | N13: =IF((G13-L13)<>0,N$1-A13," ") -> 100 | P13: =IF((F13="a"),I13," ") -> 1200 | Q13: =IF((F13="b"),I13," ") | R13: =IF((F13="c"),I13," ") | S13: =IF((F13="d"),I13," ") | T13: =IF((F13="g"),I13," ") | U13: =IF((F13="o"),I13," ") | V13: =IF((F13="FS"),I13," ") | BZ13: 4000
H14: =IF(H$4>0,(IF(G14<>0,G14*H$4/100," ")),IF(G14<>0,G14*H$2/(100+H$2)," ")) | I14: =IF((G14<>0),G14-H14," ") | M14: =IF(G14<>0,G14-L14," ") | N14: =IF((G14-L14)<>0,N$1-A14," ") | P14: =IF((F14="a"),I14," ") | Q14: =IF((F14="b"),I14," ") | R14: =IF((F14="c"),I14," ") | S14: =IF((F14="d"),I14," ") | T14: =IF((F14="g"),I14," ") | U14: =IF((F14="o"),I14," ") | V14: =IF((F14="FS"),I14," ")
H15: =IF(H$4>0,(IF(G15<>0,G15*H$4/100," ")),IF(G15<>0,G15*H$2/(100+H$2)," ")) | I15: =IF((G15<>0),G15-H15," ") | M15: =IF(G15<>0,G15-L15," ") | N15: =IF((G15-L15)<>0,N$1-A15," ") | P15: =IF((F15="a"),I15," ") | Q15: =IF((F15="b"),I15," ") | R15: =IF((F15="c"),I15," ") | S15: =IF((F15="d"),I15," ") | T15: =IF((F15="g"),I15," ") | U15: =IF((F15="o"),I15," ") | V15: =IF((F15="FS"),I15," ")
H16: =IF(H$4>0,(IF(G16<>0,G16*H$4/100," ")),IF(G16<>0,G16*H$2/(100+H$2)," ")) | I16: =IF((G16<>0),G16-H16," ") | M16: =IF(G16<>0,G16-L16," ") | N16: =IF((G16-L16)<>0,N$1-A16," ") | P16: =IF((F16="a"),I16," ") | Q16: =IF((F16="b"),I16," ") | R16: =IF((F16="c"),I16," ") | S16: =IF((F16="d"),I16," ") | T16: =IF((F16="g"),I16," ") | U16: =IF((F16="o"),I16," ") | V16: =IF((F16="FS"),I16," ")
H17: =IF(H$4>0,(IF(G17<>0,G17*H$4/100," ")),IF(G17<>0,G17*H$2/(100+H$2)," ")) | I17: =IF((G17<>0),G17-H17," ") | M17: =IF(G17<>0,G17-L17," ") | N17: =IF((G17-L17)<>0,N$1-A17," ") | P17: =IF((F17="a"),I17," ") | Q17: =IF((F17="b"),I17," ") | R17: =IF((F17="c"),I17," ") | S17: =IF((F17="d"),I17," ") | T17: =IF((F17="g"),I17," ") | U17: =IF((F17="o"),I17," ") | V17: =IF((F17="FS"),I17," ")
H18: =IF(H$4>0,(IF(G18<>0,G18*H$4/100," ")),IF(G18<>0,G18*H$2/(100+H$2)," ")) | I18: =IF((G18<>0),G18-H18," ") | M18: =IF(G18<>0,G18-L18," ") | N18: =IF((G18-L18)<>0,N$1-A18," ") | P18: =IF((F18="a"),I18," ") | Q18: =IF((F18="b"),I18," ") | R18: =IF((F18="c"),I18," ") | S18: =IF((F18="d"),I18," ") | T18: =IF((F18="g"),I18," ") | U18: =IF((F18="o"),I18," ") | V18: =IF((F18="FS"),I18," ")
H19: =IF(H$4>0,(IF(G19<>0,G19*H$4/100," ")),IF(G19<>0,G19*H$2/(100+H$2)," ")) | I19: =IF((G19<>0),G19-H19," ") | M19: =IF(G19<>0,G19-L19," ") | N19: =IF((G19-L19)<>0,N$1-A19," ") | P19: =IF((F19="a"),I19," ") | Q19: =IF((F19="b"),I19," ") | R19: =IF((F19="c"),I19," ") | S19: =IF((F19="d"),I19," ") | T19: =IF((F19="g"),I19," ") | U19: =IF((F19="o"),I19," ") | V19: =IF((F19="FS"),I19," ")
H20: =IF(H$4>0,(IF(G20<>0,G20*H$4/100," ")),IF(G20<>0,G20*H$2/(100+H$2)," ")) | I20: =IF((G20<>0),G20-H20," ") | M20: =IF(G20<>0,G20-L20," ") | N20: =IF((G20-L20)<>0,N$1-A20," ") | P20: =IF((F20="a"),I20," ") | Q20: =IF((F20="b"),I20," ") | R20: =IF((F20="c"),I20," ") | S20: =IF((F20="d"),I20," ") | T20: =IF((F20="g"),I20," ") | U20: =IF((F20="o"),I20," ") | V20: =IF((F20="FS"),I20," ")
H21: =IF(H$4>0,(IF(G21<>0,G21*H$4/100," ")),IF(G21<>0,G21*H$2/(100+H$2)," ")) | I21: =IF((G21<>0),G21-H21," ") | M21: =IF(G21<>0,G21-L21," ") | N21: =IF((G21-L21)<>0,N$1-A21," ") | P21: =IF((F21="a"),I21," ") | Q21: =IF((F21="b"),I21," ") | R21: =IF((F21="c"),I21," ") | S21: =IF((F21="d"),I21," ") | T21: =IF((F21="g"),I21," ") | U21: =IF((F21="o"),I21," ") | V21: =IF((F21="FS"),I21," ")
H22: =IF(H$4>0,(IF(G22<>0,G22*H$4/100," ")),IF(G22<>0,G22*H$2/(100+H$2)," ")) | I22: =IF((G22<>0),G22-H22," ") | M22: =IF(G22<>0,G22-L22," ") | N22: =IF((G22-L22)<>0,N$1-A22," ") | P22: =IF((F22="a"),I22," ") | Q22: =IF((F22="b"),I22," ") | R22: =IF((F22="c"),I22," ") | S22: =IF((F22="d"),I22," ") | T22: =IF((F22="g"),I22," ") | U22: =IF((F22="o"),I22," ") | V22: =IF((F22="FS"),I22," ")
H23: =IF(H$4>0,(IF(G23<>0,G23*H$4/100," ")),IF(G23<>0,G23*H$2/(100+H$2)," ")) | I23: =IF((G23<>0),G23-H23," ") | M23: =IF(G23<>0,G23-L23," ") | N23: =IF((G23-L23)<>0,N$1-A23," ") | P23: =IF((F23="a"),I23," ") | Q23: =IF((F23="b"),I23," ") | R23: =IF((F23="c"),I23," ") | S23: =IF((F23="d"),I23," ") | T23: =IF((F23="g"),I23," ") | U23: =IF((F23="o"),I23," ") | V23: =IF((F23="FS"),I23," ")
H24: =IF(H$4>0,(IF(G24<>0,G24*H$4/100," ")),IF(G24<>0,G24*H$2/(100+H$2)," ")) | I24: =IF((G24<>0),G24-H24," ") | M24: =IF(G24<>0,G24-L24," ") | N24: =IF((G24-L24)<>0,N$1-A24," ") | P24: =IF((F24="a"),I24," ") | Q24: =IF((F24="b"),I24," ") | R24: =IF((F24="c"),I24," ") | S24: =IF((F24="d"),I24," ") | T24: =IF((F24="g"),I24," ") | U24: =IF((F24="o"),I24," ") | V24: =IF((F24="FS"),I24," ")
H25: =IF(H$4>0,(IF(G25<>0,G25*H$4/100," ")),IF(G25<>0,G25*H$2/(100+H$2)," ")) | I25: =IF((G25<>0),G25-H25," ") | M25: =IF(G25<>0,G25-L25," ") | N25: =IF((G25-L25)<>0,N$1-A25," ") | P25: =IF((F25="a"),I25," ") | Q25: =IF((F25="b"),I25," ") | R25: =IF((F25="c"),I25," ") | S25: =IF((F25="d"),I25," ") | T25: =IF((F25="g"),I25," ") | U25: =IF((F25="o"),I25," ") | V25: =IF((F25="FS"),I25," ")
... H68: =IF(H$4>0,(IF(G68<>0,G68*H$4/100," ")),IF(G68<>0,G68*H$2/(100+H$2)," ")) | I68: =IF((G68<>0),G68-H68," ") | M68: =IF(G68<>0,G68-L68," ") | N68: =IF((G68-L68)<>0,N$1-A68," ") | P68: =IF((F68="a"),I68," ") | Q68: =IF((F68="b"),I68," ") | R68: =IF((F68="c"),I68," ") | S68: =IF((F68="d"),I68," ") | T68: =IF((F68="g"),I68," ") | U68: =IF((F68="o"),I68," ") | V68: =IF((F68="FS"),I68," ")
F69: =IF((G69<>0),"Enter Letter"," ") | H69: =IF(H$4>0,(IF(G69<>0,G69*H$4/100," ")),IF(G69<>0,G69*H$2/(100+H$2)," ")) | I69: =IF((G69<>0),G69-H69," ") | M69: =IF(G69<>0,G69-L69," ") | N69: =IF((G69-L69)<>0,N$1-A69," ") | P69: =IF((F69="a"),I69," ") | Q69: =IF((F69="b"),I69," ") | R69: =IF((F69="c"),I69," ") | S69: =IF((F69="d"),I69," ") | T69: =IF((F69="g"),I69," ") | U69: =IF((F69="o"),I69," ") | V69: =IF((F69="FS"),I69," ")
F70: =IF((G70<>0),"Enter Letter"," ") | H70: =IF(H$4>0,(IF(G70<>0,G70*H$4/100," ")),IF(G70<>0,G70*H$2/(100+H$2)," ")) | I70: =IF((G70<>0),G70-H70," ") | M70: =IF(G70<>0,G70-L70," ") | N70: =IF((G70-L70)<>0,N$1-A70," ") | P70: =IF((F70="a"),I70," ") | Q70: =IF((F70="b"),I70," ") | R70: =IF((F70="c"),I70," ") | S70: =IF((F70="d"),I70," ") | T70: =IF((F70="g"),I70," ") | U70: =IF((F70="o"),I70," ") | V70: =IF((F70="FS"),I70," ")
F71: =IF((G71<>0),"Enter Letter"," ") | H71: =IF(H$4>0,(IF(G71<>0,G71*H$4/100," ")),IF(G71<>0,G71*H$2/(100+H$2)," ")) | I71: =IF((G71<>0),G71-H71," ") | M71: =IF(G71<>0,G71-L71," ") | N71: =IF((G71-L71)<>0,N$1-A71," ") | P71: =IF((F71="a"),I71," ") | Q71: =IF((F71="b"),I71," ") | R71: =IF((F71="c"),I71," ") | S71: =IF((F71="d"),I71," ") | T71: =IF((F71="g"),I71," ") | U71: =IF((F71="o"),I71," ") | V71: =IF((F71="FS"),I71," ")
F72: =IF((G72<>0),"Enter Letter"," ") | H72: =IF(H$4>0,(IF(G72<>0,G72*H$4/100," ")),IF(G72<>0,G72*H$2/(100+H$2)," ")) | I72: =IF((G72<>0),G72-H72," ") | M72: =IF(G72<>0,G72-L72," ") | N72: =IF((G72-L72)<>0,N$1-A72," ") | P72: =IF((F72="a"),I72," ") | Q72: =IF((F72="b"),I72," ") | R72: =IF((F72="c"),I72," ") | S72: =IF((F72="d"),I72," ") | T72: =IF((F72="g"),I72," ") | U72: =IF((F72="o"),I72," ") | V72: =IF((F72="FS"),I72," ")
F73: =IF((G73<>0),"Enter Letter"," ") | H73: =IF(H$4>0,(IF(G73<>0,G73*H$4/100," ")),IF(G73<>0,G73*H$2/(100+H$2)," ")) | I73: =IF((G73<>0),G73-H73," ") | M73: =IF(G73<>0,G73-L73," ") | N73: =IF((G73-L73)<>0,N$1-A73," ") | P73: =IF((F73="a"),I73," ") | Q73: =IF((F73="b"),I73," ") | R73: =IF((F73="c"),I73," ") | S73: =IF((F73="d"),I73," ") | T73: =IF((F73="g"),I73," ") | U73: =IF((F73="o"),I73," ") | V73: =IF((F73="FS"),I73," ")
F74: =IF((G74<>0),"Enter Letter"," ") | H74: =IF(H$4>0,(IF(G74<>0,G74*H$4/100," ")),IF(G74<>0,G74*H$2/(100+H$2)," ")) | I74: =IF((G74<>0),G74-H74," ") | M74: =IF(G74<>0,G74-L74," ") | N74: =IF((G74-L74)<>0,N$1-A74," ") | P74: =IF((F74="a"),I74," ") | Q74: =IF((F74="b"),I74," ") | R74: =IF((F74="c"),I74," ") | S74: =IF((F74="d"),I74," ") | T74: =IF((F74="g"),I74," ") | U74: =IF((F74="o"),I74," ") | V74: =IF((F74="FS"),I74," ")
F75: =IF((G75<>0),"Enter Letter"," ") | H75: =IF(H$4>0,(IF(G75<>0,G75*H$4/100," ")),IF(G75<>0,G75*H$2/(100+H$2)," ")) | I75: =IF((G75<>0),G75-H75," ") | M75: =IF(G75<>0,G75-L75," ") | N75: =IF((G75-L75)<>0,N$1-A75," ") | P75: =IF((F75="a"),I75," ") | Q75: =IF((F75="b"),I75," ") | R75: =IF((F75="c"),I75," ") | S75: =IF((F75="d"),I75," ") | T75: =IF((F75="g"),I75," ") | U75: =IF((F75="o"),I75," ") | V75: =IF((F75="FS"),I75," ")
F76: =IF((G76<>0),"Enter Letter"," ") | H76: =IF(H$4>0,(IF(G76<>0,G76*H$4/100," ")),IF(G76<>0,G76*H$2/(100+H$2)," ")) | I76: =IF((G76<>0),G76-H76," ") | M76: =IF(G76<>0,G76-L76," ") | N76: =IF((G76-L76)<>0,N$1-A76," ") | P76: =IF((F76="a"),I76," ") | Q76: =IF((F76="b"),I76," ") | R76: =IF((F76="c"),I76," ") | S76: =IF((F76="d"),I76," ") | T76: =IF((F76="g"),I76," ") | U76: =IF((F76="o"),I76," ") | V76: =IF((F76="FS"),I76," ")
F77: =IF((G77<>0),"Enter Letter"," ") | H77: =IF(H$4>0,(IF(G77<>0,G77*H$4/100," ")),IF(G77<>0,G77*H$2/(100+H$2)," ")) | I77: =IF((G77<>0),G77-H77," ") | M77: =IF(G77<>0,G77-L77," ") | N77: =IF((G77-L77)<>0,N$1-A77," ") | P77: =IF((F77="a"),I77," ") | Q77: =IF((F77="b"),I77," ") | R77: =IF((F77="c"),I77," ") | S77: =IF((F77="d"),I77," ") | T77: =IF((F77="g"),I77," ") | U77: =IF((F77="o"),I77," ") | V77: =IF((F77="FS"),I77," ")
F78: =IF((G78<>0),"Enter Letter"," ") | H78: =IF(H$4>0,(IF(G78<>0,G78*H$4/100," ")),IF(G78<>0,G78*H$2/(100+H$2)," ")) | I78: =IF((G78<>0),G78-H78," ") | M78: =IF(G78<>0,G78-L78," ") | N78: =IF((G78-L78)<>0,N$1-A78," ") | P78: =IF((F78="a"),I78," ") | Q78: =IF((F78="b"),I78," ") | R78: =IF((F78="c"),I78," ") | S78: =IF((F78="d"),I78," ") | T78: =IF((F78="g"),I78," ") | U78: =IF((F78="o"),I78," ") | V78: =IF((F78="FS"),I78," ")
F79: =IF((G79<>0),"Enter Letter"," ") | H79: =IF(H$4>0,(IF(G79<>0,G79*H$4/100," ")),IF(G79<>0,G79*H$2/(100+H$2)," ")) | I79: =IF((G79<>0),G79-H79," ") | M79: =IF(G79<>0,G79-L79," ") | N79: =IF((G79-L79)<>0,N$1-A79," ") | P79: =IF((F79="a"),I79," ") | Q79: =IF((F79="b"),I79," ") | R79: =IF((F79="c"),I79," ") | S79: =IF((F79="d"),I79," ") | T79: =IF((F79="g"),I79," ") | U79: =IF((F79="o"),I79," ") | V79: =IF((F79="FS"),I79," ")
F80: =IF((G80<>0),"Enter Letter"," ") | H80: =IF(H$4>0,(IF(G80<>0,G80*H$4/100," ")),IF(G80<>0,G80*H$2/(100+H$2)," ")) | I80: =IF((G80<>0),G80-H80," ") | M80: =IF(G80<>0,G80-L80," ") | N80: =IF((G80-L80)<>0,N$1-A80," ") | P80: =IF((F80="a"),I80," ") | Q80: =IF((F80="b"),I80," ") | R80: =IF((F80="c"),I80," ") | S80: =IF((F80="d"),I80," ") | T80: =IF((F80="g"),I80," ") | U80: =IF((F80="o"),I80," ") | V80: =IF((F80="FS"),I80," ")
... F300: =IF((G300<>0),"Enter Letter"," ") | H300: =IF(H$4>0,(IF(G300<>0,G300*H$4/100," ")),IF(G300<>0,G300*H$2/(100+H$2)," ")) | I300: =IF((G300<>0),G300-H300," ") | M300: =IF(G300<>0,G300-L300," ") | N300: =IF((G300-L300)<>0,N$1-A300," ") | P300: =IF((F300="a"),I300," ") | Q300: =IF((F300="b"),I300," ") | R300: =IF((F300="c"),I300," ") | S300: =IF((F300="d"),I300," ") | T300: =IF((F300="g"),I300," ") | U300: =IF((F300="o"),I300," ") | V300: =IF((F300="FS"),I300," ")

Sheet Jul
A1: =G1-H1-SUM(P1:V1) -> 0 | B1: Check Total | C1: Sales Mileage | D1: =SUM(D5:D300) -> 0 | E1: Sales Description | F1: Enter Expense Code Letter | G1: =SUM(G5:G300) -> 33760 | H1: =SUM(H5:H300) -> 5626.6667 | I1: =SUM(I5:I300) -> 28133.333 | K1: For your information only. Enter How Paid e.g. Cash, Cheque etc., | L1: =SUM(L5:L300) -> 0 | M1: =SUM(M5:M300) -> 33760 | N1: =TODAY() -> 46295 | P1: =SUM(P5:P300) -> 25633.333 | Q1: =SUM(Q5:Q300) -> 1800 | R1: =SUM(R5:R300) -> 0 | S1: =SUM(S5:S300) -> 700 | T1: =SUM(T5:T300) -> 0 | U1: =SUM(U5:U300) -> 0 | V1: =SUM(V5:V300) -> 0 | W1: =SUM(W5:W300) -> 0 | X1: =W1+Jun!X1 -> 0
A2: Sales Date | B2: Customer Name | C2: Sales Invoice Number or reference | D2: Sales Mileage | G2: Sales Value including Vat | H2: =Jun!H2 -> 20 | I2: Sales Net of Vat | L2: Receipts from Customers | P2: Sales Net of Vat | S2: Other Income | T2: Investment Grants | U2: Bad Debts written off | V2: =V1+Jun!V2 -> 0 | W2: Sub contractors only
H3: Vat Output | L3: Actual amount received | M3: Sales Value not yet received | N3: Number of Days Outstanding | P3: Product A | Q3: Product B | R3: Product C | V3: Sale of Fixed Assets | W3: CIS Tax Deducted | X3: CIS Certificate reference
H4: =Jun!H4 -> 0 | P4: A | Q4: B | R4: C | S4: D | T4: G | U4: O | V4: FS
A5: 46204 | B5: Beta Systems | C5: INV-1302 | E5: Software licence renewal | F5: b | G5: 1200 | H5: =IF(H$4>0,(IF(G5<>0,G5*H$4/100," ")),IF(G5<>0,G5*H$2/(100+H$2)," ")) -> 200 | I5: =IF((G5<>0),G5-H5," ") -> 1000 | M5: =IF(G5<>0,G5-L5," ") -> 1200 | N5: =IF((G5-L5)<>0,N$1-A5," ") -> 91 | P5: =IF((F5="a"),I5," ") | Q5: =IF((F5="b"),I5," ") -> 1000 | R5: =IF((F5="c"),I5," ") | S5: =IF((F5="d"),I5," ") | T5: =IF((F5="g"),I5," ") | U5: =IF((F5="o"),I5," ") | V5: =IF((F5="FS"),I5," ") | BZ5: 4001
A6: 46206 | B6: FreshField Ltd | C6: INV-2604 | E6: Software monitoring licence | F6: b | G6: 360 | H6: =IF(H$4>0,(IF(G6<>0,G6*H$4/100," ")),IF(G6<>0,G6*H$2/(100+H$2)," ")) -> 60 | I6: =IF((G6<>0),G6-H6," ") -> 300 | M6: =IF(G6<>0,G6-L6," ") -> 360 | N6: =IF((G6-L6)<>0,N$1-A6," ") -> 89 | P6: =IF((F6="a"),I6," ") | Q6: =IF((F6="b"),I6," ") -> 300 | R6: =IF((F6="c"),I6," ") | S6: =IF((F6="d"),I6," ") | T6: =IF((F6="g"),I6," ") | U6: =IF((F6="o"),I6," ") | V6: =IF((F6="FS"),I6," ") | BZ6: 4001
A7: 46208 | B7: CloudNine Ltd | C7: INV-1404 | E7: SaaS licence fee | F7: b | G7: 600 | H7: =IF(H$4>0,(IF(G7<>0,G7*H$4/100," ")),IF(G7<>0,G7*H$2/(100+H$2)," ")) -> 100 | I7: =IF((G7<>0),G7-H7," ") -> 500 | M7: =IF(G7<>0,G7-L7," ") -> 600 | N7: =IF((G7-L7)<>0,N$1-A7," ") -> 87 | P7: =IF((F7="a"),I7," ") | Q7: =IF((F7="b"),I7," ") -> 500 | R7: =IF((F7="c"),I7," ") | S7: =IF((F7="d"),I7," ") | T7: =IF((F7="g"),I7," ") | U7: =IF((F7="o"),I7," ") | V7: =IF((F7="FS"),I7," ") | BZ7: 4001
A8: 46211 | B8: Cedar Systems | C8: INV-2404 | E8: Managed services | F8: a | G8: 480 | H8: =IF(H$4>0,(IF(G8<>0,G8*H$4/100," ")),IF(G8<>0,G8*H$2/(100+H$2)," ")) -> 80 | I8: =IF((G8<>0),G8-H8," ") -> 400 | M8: =IF(G8<>0,G8-L8," ") -> 480 | N8: =IF((G8-L8)<>0,N$1-A8," ") -> 84 | P8: =IF((F8="a"),I8," ") -> 400 | Q8: =IF((F8="b"),I8," ") | R8: =IF((F8="c"),I8," ") | S8: =IF((F8="d"),I8," ") | T8: =IF((F8="g"),I8," ") | U8: =IF((F8="o"),I8," ") | V8: =IF((F8="FS"),I8," ") | BZ8: 4000
A9: 46213 | B9: Pinnacle Group | C9: INV-2204 | E9: Monthly support contract | F9: a | G9: 720 | H9: =IF(H$4>0,(IF(G9<>0,G9*H$4/100," ")),IF(G9<>0,G9*H$2/(100+H$2)," ")) -> 120 | I9: =IF((G9<>0),G9-H9," ") -> 600 | M9: =IF(G9<>0,G9-L9," ") -> 720 | N9: =IF((G9-L9)<>0,N$1-A9," ") -> 82 | P9: =IF((F9="a"),I9," ") -> 600 | Q9: =IF((F9="b"),I9," ") | R9: =IF((F9="c"),I9," ") | S9: =IF((F9="d"),I9," ") | T9: =IF((F9="g"),I9," ") | U9: =IF((F9="o"),I9," ") | V9: =IF((F9="FS"),I9," ") | BZ9: 4000
A10: 46217 | B10: NorthStar Digital | C10: INV-2301 | E10: Project delivery | F10: a | G10: 2160 | H10: =IF(H$4>0,(IF(G10<>0,G10*H$4/100," ")),IF(G10<>0,G10*H$2/(100+H$2)," ")) -> 360 | I10: =IF((G10<>0),G10-H10," ") -> 1800 | M10: =IF(G10<>0,G10-L10," ") -> 2160 | N10: =IF((G10-L10)<>0,N$1-A10," ") -> 78 | P10: =IF((F10="a"),I10," ") -> 1800 | Q10: =IF((F10="b"),I10," ") | R10: =IF((F10="c"),I10," ") | S10: =IF((F10="d"),I10," ") | T10: =IF((F10="g"),I10," ") | U10: =IF((F10="o"),I10," ") | V10: =IF((F10="FS"),I10," ") | BZ10: 4000
A11: 46218 | B11: Acme Corp | C11: INV-1004 | E11: IT consultancy services | F11: a | G11: 25000 | H11: =IF(H$4>0,(IF(G11<>0,G11*H$4/100," ")),IF(G11<>0,G11*H$2/(100+H$2)," ")) -> 4166.6667 | I11: =IF((G11<>0),G11-H11," ") -> 20833.333 | M11: =IF(G11<>0,G11-L11," ") -> 25000 | N11: =IF((G11-L11)<>0,N$1-A11," ") -> 77 | P11: =IF((F11="a"),I11," ") -> 20833.333 | Q11: =IF((F11="b"),I11," ") | R11: =IF((F11="c"),I11," ") | S11: =IF((F11="d"),I11," ") | T11: =IF((F11="g"),I11," ") | U11: =IF((F11="o"),I11," ") | V11: =IF((F11="FS"),I11," ") | BZ11: 4000
A12: 46221 | B12: TechStart Ltd | C12: INV-1104 | E12: IT consultancy retainer | F12: a | G12: 2400 | H12: =IF(H$4>0,(IF(G12<>0,G12*H$4/100," ")),IF(G12<>0,G12*H$2/(100+H$2)," ")) -> 400 | I12: =IF((G12<>0),G12-H12," ") -> 2000 | M12: =IF(G12<>0,G12-L12," ") -> 2400 | N12: =IF((G12-L12)<>0,N$1-A12," ") -> 74 | P12: =IF((F12="a"),I12," ") -> 2000 | Q12: =IF((F12="b"),I12," ") | R12: =IF((F12="c"),I12," ") | S12: =IF((F12="d"),I12," ") | T12: =IF((F12="g"),I12," ") | U12: =IF((F12="o"),I12," ") | V12: =IF((F12="FS"),I12," ") | BZ12: 4000
A13: 46231 | B13: Horizon Analytics | C13: INV-2702 | E13: Data analytics commission | F13: d | G13: 840 | H13: =IF(H$4>0,(IF(G13<>0,G13*H$4/100," ")),IF(G13<>0,G13*H$2/(100+H$2)," ")) -> 140 | I13: =IF((G13<>0),G13-H13," ") -> 700 | M13: =IF(G13<>0,G13-L13," ") -> 840 | N13: =IF((G13-L13)<>0,N$1-A13," ") -> 64 | P13: =IF((F13="a"),I13," ") | Q13: =IF((F13="b"),I13," ") | R13: =IF((F13="c"),I13," ") | S13: =IF((F13="d"),I13," ") -> 700 | T13: =IF((F13="g"),I13," ") | U13: =IF((F13="o"),I13," ") | V13: =IF((F13="FS"),I13," ") | BZ13: 4003
H14: =IF(H$4>0,(IF(G14<>0,G14*H$4/100," ")),IF(G14<>0,G14*H$2/(100+H$2)," ")) | I14: =IF((G14<>0),G14-H14," ") | M14: =IF(G14<>0,G14-L14," ") | N14: =IF((G14-L14)<>0,N$1-A14," ") | P14: =IF((F14="a"),I14," ") | Q14: =IF((F14="b"),I14," ") | R14: =IF((F14="c"),I14," ") | S14: =IF((F14="d"),I14," ") | T14: =IF((F14="g"),I14," ") | U14: =IF((F14="o"),I14," ") | V14: =IF((F14="FS"),I14," ")
H15: =IF(H$4>0,(IF(G15<>0,G15*H$4/100," ")),IF(G15<>0,G15*H$2/(100+H$2)," ")) | I15: =IF((G15<>0),G15-H15," ") | M15: =IF(G15<>0,G15-L15," ") | N15: =IF((G15-L15)<>0,N$1-A15," ") | P15: =IF((F15="a"),I15," ") | Q15: =IF((F15="b"),I15," ") | R15: =IF((F15="c"),I15," ") | S15: =IF((F15="d"),I15," ") | T15: =IF((F15="g"),I15," ") | U15: =IF((F15="o"),I15," ") | V15: =IF((F15="FS"),I15," ")
H16: =IF(H$4>0,(IF(G16<>0,G16*H$4/100," ")),IF(G16<>0,G16*H$2/(100+H$2)," ")) | I16: =IF((G16<>0),G16-H16," ") | M16: =IF(G16<>0,G16-L16," ") | N16: =IF((G16-L16)<>0,N$1-A16," ") | P16: =IF((F16="a"),I16," ") | Q16: =IF((F16="b"),I16," ") | R16: =IF((F16="c"),I16," ") | S16: =IF((F16="d"),I16," ") | T16: =IF((F16="g"),I16," ") | U16: =IF((F16="o"),I16," ") | V16: =IF((F16="FS"),I16," ")
H17: =IF(H$4>0,(IF(G17<>0,G17*H$4/100," ")),IF(G17<>0,G17*H$2/(100+H$2)," ")) | I17: =IF((G17<>0),G17-H17," ") | M17: =IF(G17<>0,G17-L17," ") | N17: =IF((G17-L17)<>0,N$1-A17," ") | P17: =IF((F17="a"),I17," ") | Q17: =IF((F17="b"),I17," ") | R17: =IF((F17="c"),I17," ") | S17: =IF((F17="d"),I17," ") | T17: =IF((F17="g"),I17," ") | U17: =IF((F17="o"),I17," ") | V17: =IF((F17="FS"),I17," ")
H18: =IF(H$4>0,(IF(G18<>0,G18*H$4/100," ")),IF(G18<>0,G18*H$2/(100+H$2)," ")) | I18: =IF((G18<>0),G18-H18," ") | M18: =IF(G18<>0,G18-L18," ") | N18: =IF((G18-L18)<>0,N$1-A18," ") | P18: =IF((F18="a"),I18," ") | Q18: =IF((F18="b"),I18," ") | R18: =IF((F18="c"),I18," ") | S18: =IF((F18="d"),I18," ") | T18: =IF((F18="g"),I18," ") | U18: =IF((F18="o"),I18," ") | V18: =IF((F18="FS"),I18," ")
H19: =IF(H$4>0,(IF(G19<>0,G19*H$4/100," ")),IF(G19<>0,G19*H$2/(100+H$2)," ")) | I19: =IF((G19<>0),G19-H19," ") | M19: =IF(G19<>0,G19-L19," ") | N19: =IF((G19-L19)<>0,N$1-A19," ") | P19: =IF((F19="a"),I19," ") | Q19: =IF((F19="b"),I19," ") | R19: =IF((F19="c"),I19," ") | S19: =IF((F19="d"),I19," ") | T19: =IF((F19="g"),I19," ") | U19: =IF((F19="o"),I19," ") | V19: =IF((F19="FS"),I19," ")
H20: =IF(H$4>0,(IF(G20<>0,G20*H$4/100," ")),IF(G20<>0,G20*H$2/(100+H$2)," ")) | I20: =IF((G20<>0),G20-H20," ") | M20: =IF(G20<>0,G20-L20," ") | N20: =IF((G20-L20)<>0,N$1-A20," ") | P20: =IF((F20="a"),I20," ") | Q20: =IF((F20="b"),I20," ") | R20: =IF((F20="c"),I20," ") | S20: =IF((F20="d"),I20," ") | T20: =IF((F20="g"),I20," ") | U20: =IF((F20="o"),I20," ") | V20: =IF((F20="FS"),I20," ")
F21: =IF((G21<>0),"Enter Letter"," ") | H21: =IF(H$4>0,(IF(G21<>0,G21*H$4/100," ")),IF(G21<>0,G21*H$2/(100+H$2)," ")) | I21: =IF((G21<>0),G21-H21," ") | M21: =IF(G21<>0,G21-L21," ") | N21: =IF((G21-L21)<>0,N$1-A21," ") | P21: =IF((F21="a"),I21," ") | Q21: =IF((F21="b"),I21," ") | R21: =IF((F21="c"),I21," ") | S21: =IF((F21="d"),I21," ") | T21: =IF((F21="g"),I21," ") | U21: =IF((F21="o"),I21," ") | V21: =IF((F21="FS"),I21," ")
F22: =IF((G22<>0),"Enter Letter"," ") | H22: =IF(H$4>0,(IF(G22<>0,G22*H$4/100," ")),IF(G22<>0,G22*H$2/(100+H$2)," ")) | I22: =IF((G22<>0),G22-H22," ") | M22: =IF(G22<>0,G22-L22," ") | N22: =IF((G22-L22)<>0,N$1-A22," ") | P22: =IF((F22="a"),I22," ") | Q22: =IF((F22="b"),I22," ") | R22: =IF((F22="c"),I22," ") | S22: =IF((F22="d"),I22," ") | T22: =IF((F22="g"),I22," ") | U22: =IF((F22="o"),I22," ") | V22: =IF((F22="FS"),I22," ")
H23: =IF(H$4>0,(IF(G23<>0,G23*H$4/100," ")),IF(G23<>0,G23*H$2/(100+H$2)," ")) | I23: =IF((G23<>0),G23-H23," ") | M23: =IF(G23<>0,G23-L23," ") | N23: =IF((G23-L23)<>0,N$1-A23," ") | P23: =IF((F23="a"),I23," ") | Q23: =IF((F23="b"),I23," ") | R23: =IF((F23="c"),I23," ") | S23: =IF((F23="d"),I23," ") | T23: =IF((F23="g"),I23," ") | U23: =IF((F23="o"),I23," ") | V23: =IF((F23="FS"),I23," ")
H24: =IF(H$4>0,(IF(G24<>0,G24*H$4/100," ")),IF(G24<>0,G24*H$2/(100+H$2)," ")) | I24: =IF((G24<>0),G24-H24," ") | M24: =IF(G24<>0,G24-L24," ") | N24: =IF((G24-L24)<>0,N$1-A24," ") | P24: =IF((F24="a"),I24," ") | Q24: =IF((F24="b"),I24," ") | R24: =IF((F24="c"),I24," ") | S24: =IF((F24="d"),I24," ") | T24: =IF((F24="g"),I24," ") | U24: =IF((F24="o"),I24," ") | V24: =IF((F24="FS"),I24," ")
H25: =IF(H$4>0,(IF(G25<>0,G25*H$4/100," ")),IF(G25<>0,G25*H$2/(100+H$2)," ")) | I25: =IF((G25<>0),G25-H25," ") | M25: =IF(G25<>0,G25-L25," ") | N25: =IF((G25-L25)<>0,N$1-A25," ") | P25: =IF((F25="a"),I25," ") | Q25: =IF((F25="b"),I25," ") | R25: =IF((F25="c"),I25," ") | S25: =IF((F25="d"),I25," ") | T25: =IF((F25="g"),I25," ") | U25: =IF((F25="o"),I25," ") | V25: =IF((F25="FS"),I25," ")
H26: =IF(H$4>0,(IF(G26<>0,G26*H$4/100," ")),IF(G26<>0,G26*H$2/(100+H$2)," ")) | I26: =IF((G26<>0),G26-H26," ") | M26: =IF(G26<>0,G26-L26," ") | N26: =IF((G26-L26)<>0,N$1-A26," ") | P26: =IF((F26="a"),I26," ") | Q26: =IF((F26="b"),I26," ") | R26: =IF((F26="c"),I26," ") | S26: =IF((F26="d"),I26," ") | T26: =IF((F26="g"),I26," ") | U26: =IF((F26="o"),I26," ") | V26: =IF((F26="FS"),I26," ")
H27: =IF(H$4>0,(IF(G27<>0,G27*H$4/100," ")),IF(G27<>0,G27*H$2/(100+H$2)," ")) | I27: =IF((G27<>0),G27-H27," ") | M27: =IF(G27<>0,G27-L27," ") | N27: =IF((G27-L27)<>0,N$1-A27," ") | P27: =IF((F27="a"),I27," ") | Q27: =IF((F27="b"),I27," ") | R27: =IF((F27="c"),I27," ") | S27: =IF((F27="d"),I27," ") | T27: =IF((F27="g"),I27," ") | U27: =IF((F27="o"),I27," ") | V27: =IF((F27="FS"),I27," ")
H28: =IF(H$4>0,(IF(G28<>0,G28*H$4/100," ")),IF(G28<>0,G28*H$2/(100+H$2)," ")) | I28: =IF((G28<>0),G28-H28," ") | M28: =IF(G28<>0,G28-L28," ") | N28: =IF((G28-L28)<>0,N$1-A28," ") | P28: =IF((F28="a"),I28," ") | Q28: =IF((F28="b"),I28," ") | R28: =IF((F28="c"),I28," ") | S28: =IF((F28="d"),I28," ") | T28: =IF((F28="g"),I28," ") | U28: =IF((F28="o"),I28," ") | V28: =IF((F28="FS"),I28," ")
H29: =IF(H$4>0,(IF(G29<>0,G29*H$4/100," ")),IF(G29<>0,G29*H$2/(100+H$2)," ")) | I29: =IF((G29<>0),G29-H29," ") | M29: =IF(G29<>0,G29-L29," ") | N29: =IF((G29-L29)<>0,N$1-A29," ") | P29: =IF((F29="a"),I29," ") | Q29: =IF((F29="b"),I29," ") | R29: =IF((F29="c"),I29," ") | S29: =IF((F29="d"),I29," ") | T29: =IF((F29="g"),I29," ") | U29: =IF((F29="o"),I29," ") | V29: =IF((F29="FS"),I29," ")
H30: =IF(H$4>0,(IF(G30<>0,G30*H$4/100," ")),IF(G30<>0,G30*H$2/(100+H$2)," ")) | I30: =IF((G30<>0),G30-H30," ") | M30: =IF(G30<>0,G30-L30," ") | N30: =IF((G30-L30)<>0,N$1-A30," ") | P30: =IF((F30="a"),I30," ") | Q30: =IF((F30="b"),I30," ") | R30: =IF((F30="c"),I30," ") | S30: =IF((F30="d"),I30," ") | T30: =IF((F30="g"),I30," ") | U30: =IF((F30="o"),I30," ") | V30: =IF((F30="FS"),I30," ")
H31: =IF(H$4>0,(IF(G31<>0,G31*H$4/100," ")),IF(G31<>0,G31*H$2/(100+H$2)," ")) | I31: =IF((G31<>0),G31-H31," ") | M31: =IF(G31<>0,G31-L31," ") | N31: =IF((G31-L31)<>0,N$1-A31," ") | P31: =IF((F31="a"),I31," ") | Q31: =IF((F31="b"),I31," ") | R31: =IF((F31="c"),I31," ") | S31: =IF((F31="d"),I31," ") | T31: =IF((F31="g"),I31," ") | U31: =IF((F31="o"),I31," ") | V31: =IF((F31="FS"),I31," ")
H32: =IF(H$4>0,(IF(G32<>0,G32*H$4/100," ")),IF(G32<>0,G32*H$2/(100+H$2)," ")) | I32: =IF((G32<>0),G32-H32," ") | M32: =IF(G32<>0,G32-L32," ") | N32: =IF((G32-L32)<>0,N$1-A32," ") | P32: =IF((F32="a"),I32," ") | Q32: =IF((F32="b"),I32," ") | R32: =IF((F32="c"),I32," ") | S32: =IF((F32="d"),I32," ") | T32: =IF((F32="g"),I32," ") | U32: =IF((F32="o"),I32," ") | V32: =IF((F32="FS"),I32," ")
H33: =IF(H$4>0,(IF(G33<>0,G33*H$4/100," ")),IF(G33<>0,G33*H$2/(100+H$2)," ")) | I33: =IF((G33<>0),G33-H33," ") | M33: =IF(G33<>0,G33-L33," ") | N33: =IF((G33-L33)<>0,N$1-A33," ") | P33: =IF((F33="a"),I33," ") | Q33: =IF((F33="b"),I33," ") | R33: =IF((F33="c"),I33," ") | S33: =IF((F33="d"),I33," ") | T33: =IF((F33="g"),I33," ") | U33: =IF((F33="o"),I33," ") | V33: =IF((F33="FS"),I33," ")
H34: =IF(H$4>0,(IF(G34<>0,G34*H$4/100," ")),IF(G34<>0,G34*H$2/(100+H$2)," ")) | I34: =IF((G34<>0),G34-H34," ") | M34: =IF(G34<>0,G34-L34," ") | N34: =IF((G34-L34)<>0,N$1-A34," ") | P34: =IF((F34="a"),I34," ") | Q34: =IF((F34="b"),I34," ") | R34: =IF((F34="c"),I34," ") | S34: =IF((F34="d"),I34," ") | T34: =IF((F34="g"),I34," ") | U34: =IF((F34="o"),I34," ") | V34: =IF((F34="FS"),I34," ")
... H68: =IF(H$4>0,(IF(G68<>0,G68*H$4/100," ")),IF(G68<>0,G68*H$2/(100+H$2)," ")) | I68: =IF((G68<>0),G68-H68," ") | M68: =IF(G68<>0,G68-L68," ") | N68: =IF((G68-L68)<>0,N$1-A68," ") | P68: =IF((F68="a"),I68," ") | Q68: =IF((F68="b"),I68," ") | R68: =IF((F68="c"),I68," ") | S68: =IF((F68="d"),I68," ") | T68: =IF((F68="g"),I68," ") | U68: =IF((F68="o"),I68," ") | V68: =IF((F68="FS"),I68," ")
F69: =IF((G69<>0),"Enter Letter"," ") | H69: =IF(H$4>0,(IF(G69<>0,G69*H$4/100," ")),IF(G69<>0,G69*H$2/(100+H$2)," ")) | I69: =IF((G69<>0),G69-H69," ") | M69: =IF(G69<>0,G69-L69," ") | N69: =IF((G69-L69)<>0,N$1-A69," ") | P69: =IF((F69="a"),I69," ") | Q69: =IF((F69="b"),I69," ") | R69: =IF((F69="c"),I69," ") | S69: =IF((F69="d"),I69," ") | T69: =IF((F69="g"),I69," ") | U69: =IF((F69="o"),I69," ") | V69: =IF((F69="FS"),I69," ")
F70: =IF((G70<>0),"Enter Letter"," ") | H70: =IF(H$4>0,(IF(G70<>0,G70*H$4/100," ")),IF(G70<>0,G70*H$2/(100+H$2)," ")) | I70: =IF((G70<>0),G70-H70," ") | M70: =IF(G70<>0,G70-L70," ") | N70: =IF((G70-L70)<>0,N$1-A70," ") | P70: =IF((F70="a"),I70," ") | Q70: =IF((F70="b"),I70," ") | R70: =IF((F70="c"),I70," ") | S70: =IF((F70="d"),I70," ") | T70: =IF((F70="g"),I70," ") | U70: =IF((F70="o"),I70," ") | V70: =IF((F70="FS"),I70," ")
F71: =IF((G71<>0),"Enter Letter"," ") | H71: =IF(H$4>0,(IF(G71<>0,G71*H$4/100," ")),IF(G71<>0,G71*H$2/(100+H$2)," ")) | I71: =IF((G71<>0),G71-H71," ") | M71: =IF(G71<>0,G71-L71," ") | N71: =IF((G71-L71)<>0,N$1-A71," ") | P71: =IF((F71="a"),I71," ") | Q71: =IF((F71="b"),I71," ") | R71: =IF((F71="c"),I71," ") | S71: =IF((F71="d"),I71," ") | T71: =IF((F71="g"),I71," ") | U71: =IF((F71="o"),I71," ") | V71: =IF((F71="FS"),I71," ")
F72: =IF((G72<>0),"Enter Letter"," ") | H72: =IF(H$4>0,(IF(G72<>0,G72*H$4/100," ")),IF(G72<>0,G72*H$2/(100+H$2)," ")) | I72: =IF((G72<>0),G72-H72," ") | M72: =IF(G72<>0,G72-L72," ") | N72: =IF((G72-L72)<>0,N$1-A72," ") | P72: =IF((F72="a"),I72," ") | Q72: =IF((F72="b"),I72," ") | R72: =IF((F72="c"),I72," ") | S72: =IF((F72="d"),I72," ") | T72: =IF((F72="g"),I72," ") | U72: =IF((F72="o"),I72," ") | V72: =IF((F72="FS"),I72," ")
F73: =IF((G73<>0),"Enter Letter"," ") | H73: =IF(H$4>0,(IF(G73<>0,G73*H$4/100," ")),IF(G73<>0,G73*H$2/(100+H$2)," ")) | I73: =IF((G73<>0),G73-H73," ") | M73: =IF(G73<>0,G73-L73," ") | N73: =IF((G73-L73)<>0,N$1-A73," ") | P73: =IF((F73="a"),I73," ") | Q73: =IF((F73="b"),I73," ") | R73: =IF((F73="c"),I73," ") | S73: =IF((F73="d"),I73," ") | T73: =IF((F73="g"),I73," ") | U73: =IF((F73="o"),I73," ") | V73: =IF((F73="FS"),I73," ")
F74: =IF((G74<>0),"Enter Letter"," ") | H74: =IF(H$4>0,(IF(G74<>0,G74*H$4/100," ")),IF(G74<>0,G74*H$2/(100+H$2)," ")) | I74: =IF((G74<>0),G74-H74," ") | M74: =IF(G74<>0,G74-L74," ") | N74: =IF((G74-L74)<>0,N$1-A74," ") | P74: =IF((F74="a"),I74," ") | Q74: =IF((F74="b"),I74," ") | R74: =IF((F74="c"),I74," ") | S74: =IF((F74="d"),I74," ") | T74: =IF((F74="g"),I74," ") | U74: =IF((F74="o"),I74," ") | V74: =IF((F74="FS"),I74," ")
F75: =IF((G75<>0),"Enter Letter"," ") | H75: =IF(H$4>0,(IF(G75<>0,G75*H$4/100," ")),IF(G75<>0,G75*H$2/(100+H$2)," ")) | I75: =IF((G75<>0),G75-H75," ") | M75: =IF(G75<>0,G75-L75," ") | N75: =IF((G75-L75)<>0,N$1-A75," ") | P75: =IF((F75="a"),I75," ") | Q75: =IF((F75="b"),I75," ") | R75: =IF((F75="c"),I75," ") | S75: =IF((F75="d"),I75," ") | T75: =IF((F75="g"),I75," ") | U75: =IF((F75="o"),I75," ") | V75: =IF((F75="FS"),I75," ")
F76: =IF((G76<>0),"Enter Letter"," ") | H76: =IF(H$4>0,(IF(G76<>0,G76*H$4/100," ")),IF(G76<>0,G76*H$2/(100+H$2)," ")) | I76: =IF((G76<>0),G76-H76," ") | M76: =IF(G76<>0,G76-L76," ") | N76: =IF((G76-L76)<>0,N$1-A76," ") | P76: =IF((F76="a"),I76," ") | Q76: =IF((F76="b"),I76," ") | R76: =IF((F76="c"),I76," ") | S76: =IF((F76="d"),I76," ") | T76: =IF((F76="g"),I76," ") | U76: =IF((F76="o"),I76," ") | V76: =IF((F76="FS"),I76," ")
F77: =IF((G77<>0),"Enter Letter"," ") | H77: =IF(H$4>0,(IF(G77<>0,G77*H$4/100," ")),IF(G77<>0,G77*H$2/(100+H$2)," ")) | I77: =IF((G77<>0),G77-H77," ") | M77: =IF(G77<>0,G77-L77," ") | N77: =IF((G77-L77)<>0,N$1-A77," ") | P77: =IF((F77="a"),I77," ") | Q77: =IF((F77="b"),I77," ") | R77: =IF((F77="c"),I77," ") | S77: =IF((F77="d"),I77," ") | T77: =IF((F77="g"),I77," ") | U77: =IF((F77="o"),I77," ") | V77: =IF((F77="FS"),I77," ")
F78: =IF((G78<>0),"Enter Letter"," ") | H78: =IF(H$4>0,(IF(G78<>0,G78*H$4/100," ")),IF(G78<>0,G78*H$2/(100+H$2)," ")) | I78: =IF((G78<>0),G78-H78," ") | M78: =IF(G78<>0,G78-L78," ") | N78: =IF((G78-L78)<>0,N$1-A78," ") | P78: =IF((F78="a"),I78," ") | Q78: =IF((F78="b"),I78," ") | R78: =IF((F78="c"),I78," ") | S78: =IF((F78="d"),I78," ") | T78: =IF((F78="g"),I78," ") | U78: =IF((F78="o"),I78," ") | V78: =IF((F78="FS"),I78," ")
F79: =IF((G79<>0),"Enter Letter"," ") | H79: =IF(H$4>0,(IF(G79<>0,G79*H$4/100," ")),IF(G79<>0,G79*H$2/(100+H$2)," ")) | I79: =IF((G79<>0),G79-H79," ") | M79: =IF(G79<>0,G79-L79," ") | N79: =IF((G79-L79)<>0,N$1-A79," ") | P79: =IF((F79="a"),I79," ") | Q79: =IF((F79="b"),I79," ") | R79: =IF((F79="c"),I79," ") | S79: =IF((F79="d"),I79," ") | T79: =IF((F79="g"),I79," ") | U79: =IF((F79="o"),I79," ") | V79: =IF((F79="FS"),I79," ")
F80: =IF((G80<>0),"Enter Letter"," ") | H80: =IF(H$4>0,(IF(G80<>0,G80*H$4/100," ")),IF(G80<>0,G80*H$2/(100+H$2)," ")) | I80: =IF((G80<>0),G80-H80," ") | M80: =IF(G80<>0,G80-L80," ") | N80: =IF((G80-L80)<>0,N$1-A80," ") | P80: =IF((F80="a"),I80," ") | Q80: =IF((F80="b"),I80," ") | R80: =IF((F80="c"),I80," ") | S80: =IF((F80="d"),I80," ") | T80: =IF((F80="g"),I80," ") | U80: =IF((F80="o"),I80," ") | V80: =IF((F80="FS"),I80," ")
... F300: =IF((G300<>0),"Enter Letter"," ") | H300: =IF(H$4>0,(IF(G300<>0,G300*H$4/100," ")),IF(G300<>0,G300*H$2/(100+H$2)," ")) | I300: =IF((G300<>0),G300-H300," ") | M300: =IF(G300<>0,G300-L300," ") | N300: =IF((G300-L300)<>0,N$1-A300," ") | P300: =IF((F300="a"),I300," ") | Q300: =IF((F300="b"),I300," ") | R300: =IF((F300="c"),I300," ") | S300: =IF((F300="d"),I300," ") | T300: =IF((F300="g"),I300," ") | U300: =IF((F300="o"),I300," ") | V300: =IF((F300="FS"),I300," ")

Sheet Aug
A1: =G1-H1-SUM(P1:V1) -> 0 | B1: Check Total | C1: Sales Mileage | D1: =SUM(D5:D300) -> 0 | E1: Sales Description | F1: Enter Expense Code Letter | G1: =SUM(G5:G300) -> 36020 | H1: =SUM(H5:H300) -> 6003.3333 | I1: =SUM(I5:I300) -> 30016.667 | K1: For your information only. Enter How Paid e.g. Cash, Cheque etc., | L1: =SUM(L5:L300) -> 0 | M1: =SUM(M5:M300) -> 36020 | N1: =TODAY() -> 46295 | P1: =SUM(P5:P300) -> 27133.333 | Q1: =SUM(Q5:Q300) -> 800 | R1: =SUM(R5:R300) -> 0 | S1: =SUM(S5:S300) -> 0 | T1: =SUM(T5:T300) -> 2083.3333 | U1: =SUM(U5:U300) -> 0 | V1: =SUM(V5:V300) -> 0 | W1: =SUM(W5:W300) -> 0 | X1: =W1+Jul!X1 -> 0
A2: Sales Date | B2: Customer Name | C2: Sales Invoice Number or reference | D2: Sales Mileage | G2: Sales Value including Vat | H2: =Jul!H2 -> 20 | I2: Sales Net of Vat | L2: Receipts from Customers | P2: Sales Net of Vat | S2: Other Income | T2: Investment Grants | U2: Bad Debts written off | V2: =V1+Jul!V2 -> 0 | W2: Sub contractors only
H3: Vat Output | L3: Actual amount received | M3: Sales Value not yet received | N3: Number of Days Outstanding | P3: Product A | Q3: Product B | R3: Product C | V3: Sale of Fixed Assets | W3: CIS Tax Deducted | X3: CIS Certificate reference
H4: =Jul!H4 -> 0 | P4: A | Q4: B | R4: C | S4: D | T4: G | U4: O | V4: FS
A5: 46235 | B5: Innovate UK | C5: INV-1701 | E5: Small business innovation grant | F5: g | G5: 2500 | H5: =IF(H$4>0,(IF(G5<>0,G5*H$4/100," ")),IF(G5<>0,G5*H$2/(100+H$2)," ")) -> 416.66667 | I5: =IF((G5<>0),G5-H5," ") -> 2083.3333 | M5: =IF(G5<>0,G5-L5," ") -> 2500 | N5: =IF((G5-L5)<>0,N$1-A5," ") -> 60 | P5: =IF((F5="a"),I5," ") | Q5: =IF((F5="b"),I5," ") | R5: =IF((F5="c"),I5," ") | S5: =IF((F5="d"),I5," ") | T5: =IF((F5="g"),I5," ") -> 2083.3333 | U5: =IF((F5="o"),I5," ") | V5: =IF((F5="FS"),I5," ") | BZ5: 4004
A6: 46237 | B6: FreshField Ltd | C6: INV-2605 | E6: Software monitoring licence | F6: b | G6: 360 | H6: =IF(H$4>0,(IF(G6<>0,G6*H$4/100," ")),IF(G6<>0,G6*H$2/(100+H$2)," ")) -> 60 | I6: =IF((G6<>0),G6-H6," ") -> 300 | M6: =IF(G6<>0,G6-L6," ") -> 360 | N6: =IF((G6-L6)<>0,N$1-A6," ") -> 58 | P6: =IF((F6="a"),I6," ") | Q6: =IF((F6="b"),I6," ") -> 300 | R6: =IF((F6="c"),I6," ") | S6: =IF((F6="d"),I6," ") | T6: =IF((F6="g"),I6," ") | U6: =IF((F6="o"),I6," ") | V6: =IF((F6="FS"),I6," ") | BZ6: 4001
A7: 46239 | B7: CloudNine Ltd | C7: INV-1405 | E7: SaaS licence fee | F7: b | G7: 600 | H7: =IF(H$4>0,(IF(G7<>0,G7*H$4/100," ")),IF(G7<>0,G7*H$2/(100+H$2)," ")) -> 100 | I7: =IF((G7<>0),G7-H7," ") -> 500 | M7: =IF(G7<>0,G7-L7," ") -> 600 | N7: =IF((G7-L7)<>0,N$1-A7," ") -> 56 | P7: =IF((F7="a"),I7," ") | Q7: =IF((F7="b"),I7," ") -> 500 | R7: =IF((F7="c"),I7," ") | S7: =IF((F7="d"),I7," ") | T7: =IF((F7="g"),I7," ") | U7: =IF((F7="o"),I7," ") | V7: =IF((F7="FS"),I7," ") | BZ7: 4001
A8: 46242 | B8: Cedar Systems | C8: INV-2405 | E8: Managed services | F8: a | G8: 480 | H8: =IF(H$4>0,(IF(G8<>0,G8*H$4/100," ")),IF(G8<>0,G8*H$2/(100+H$2)," ")) -> 80 | I8: =IF((G8<>0),G8-H8," ") -> 400 | M8: =IF(G8<>0,G8-L8," ") -> 480 | N8: =IF((G8-L8)<>0,N$1-A8," ") -> 53 | P8: =IF((F8="a"),I8," ") -> 400 | Q8: =IF((F8="b"),I8," ") | R8: =IF((F8="c"),I8," ") | S8: =IF((F8="d"),I8," ") | T8: =IF((F8="g"),I8," ") | U8: =IF((F8="o"),I8," ") | V8: =IF((F8="FS"),I8," ") | BZ8: 4000
A9: 46244 | B9: Pinnacle Group | C9: INV-2205 | E9: Monthly support contract | F9: a | G9: 720 | H9: =IF(H$4>0,(IF(G9<>0,G9*H$4/100," ")),IF(G9<>0,G9*H$2/(100+H$2)," ")) -> 120 | I9: =IF((G9<>0),G9-H9," ") -> 600 | M9: =IF(G9<>0,G9-L9," ") -> 720 | N9: =IF((G9-L9)<>0,N$1-A9," ") -> 51 | P9: =IF((F9="a"),I9," ") -> 600 | Q9: =IF((F9="b"),I9," ") | R9: =IF((F9="c"),I9," ") | S9: =IF((F9="d"),I9," ") | T9: =IF((F9="g"),I9," ") | U9: =IF((F9="o"),I9," ") | V9: =IF((F9="FS"),I9," ") | BZ9: 4000
A10: 46246 | B10: QuickFix IT | C10: INV-2002 | E10: IT support consultancy | F10: a | G10: 960 | H10: =IF(H$4>0,(IF(G10<>0,G10*H$4/100," ")),IF(G10<>0,G10*H$2/(100+H$2)," ")) -> 160 | I10: =IF((G10<>0),G10-H10," ") -> 800 | M10: =IF(G10<>0,G10-L10," ") -> 960 | N10: =IF((G10-L10)<>0,N$1-A10," ") -> 49 | P10: =IF((F10="a"),I10," ") -> 800 | Q10: =IF((F10="b"),I10," ") | R10: =IF((F10="c"),I10," ") | S10: =IF((F10="d"),I10," ") | T10: =IF((F10="g"),I10," ") | U10: =IF((F10="o"),I10," ") | V10: =IF((F10="FS"),I10," ") | BZ10: 4000
A11: 46249 | B11: Acme Corp | C11: INV-1005 | E11: IT consultancy services | F11: a | G11: 25000 | H11: =IF(H$4>0,(IF(G11<>0,G11*H$4/100," ")),IF(G11<>0,G11*H$2/(100+H$2)," ")) -> 4166.6667 | I11: =IF((G11<>0),G11-H11," ") -> 20833.333 | M11: =IF(G11<>0,G11-L11," ") -> 25000 | N11: =IF((G11-L11)<>0,N$1-A11," ") -> 46 | P11: =IF((F11="a"),I11," ") -> 20833.333 | Q11: =IF((F11="b"),I11," ") | R11: =IF((F11="c"),I11," ") | S11: =IF((F11="d"),I11," ") | T11: =IF((F11="g"),I11," ") | U11: =IF((F11="o"),I11," ") | V11: =IF((F11="FS"),I11," ") | BZ11: 4000
A12: 46252 | B12: TechStart Ltd | C12: INV-1105 | E12: IT consultancy retainer | F12: a | G12: 2400 | H12: =IF(H$4>0,(IF(G12<>0,G12*H$4/100," ")),IF(G12<>0,G12*H$2/(100+H$2)," ")) -> 400 | I12: =IF((G12<>0),G12-H12," ") -> 2000 | M12: =IF(G12<>0,G12-L12," ") -> 2400 | N12: =IF((G12-L12)<>0,N$1-A12," ") -> 43 | P12: =IF((F12="a"),I12," ") -> 2000 | Q12: =IF((F12="b"),I12," ") | R12: =IF((F12="c"),I12," ") | S12: =IF((F12="d"),I12," ") | T12: =IF((F12="g"),I12," ") | U12: =IF((F12="o"),I12," ") | V12: =IF((F12="FS"),I12," ") | BZ12: 4000
A13: 46254 | B13: DataFlow Inc | C13: INV-1203 | E13: Ad-hoc consultancy project | F13: a | G13: 1800 | H13: =IF(H$4>0,(IF(G13<>0,G13*H$4/100," ")),IF(G13<>0,G13*H$2/(100+H$2)," ")) -> 300 | I13: =IF((G13<>0),G13-H13," ") -> 1500 | M13: =IF(G13<>0,G13-L13," ") -> 1800 | N13: =IF((G13-L13)<>0,N$1-A13," ") -> 41 | P13: =IF((F13="a"),I13," ") -> 1500 | Q13: =IF((F13="b"),I13," ") | R13: =IF((F13="c"),I13," ") | S13: =IF((F13="d"),I13," ") | T13: =IF((F13="g"),I13," ") | U13: =IF((F13="o"),I13," ") | V13: =IF((F13="FS"),I13," ") | BZ13: 4000
A14: 46259 | B14: Oakridge Partners | C14: INV-2502 | E14: Quarterly consulting engagement | F14: a | G14: 1200 | H14: =IF(H$4>0,(IF(G14<>0,G14*H$4/100," ")),IF(G14<>0,G14*H$2/(100+H$2)," ")) -> 200 | I14: =IF((G14<>0),G14-H14," ") -> 1000 | M14: =IF(G14<>0,G14-L14," ") -> 1200 | N14: =IF((G14-L14)<>0,N$1-A14," ") -> 36 | P14: =IF((F14="a"),I14," ") -> 1000 | Q14: =IF((F14="b"),I14," ") | R14: =IF((F14="c"),I14," ") | S14: =IF((F14="d"),I14," ") | T14: =IF((F14="g"),I14," ") | U14: =IF((F14="o"),I14," ") | V14: =IF((F14="FS"),I14," ") | BZ14: 4000
H15: =IF(H$4>0,(IF(G15<>0,G15*H$4/100," ")),IF(G15<>0,G15*H$2/(100+H$2)," ")) | I15: =IF((G15<>0),G15-H15," ") | M15: =IF(G15<>0,G15-L15," ") | N15: =IF((G15-L15)<>0,N$1-A15," ") | P15: =IF((F15="a"),I15," ") | Q15: =IF((F15="b"),I15," ") | R15: =IF((F15="c"),I15," ") | S15: =IF((F15="d"),I15," ") | T15: =IF((F15="g"),I15," ") | U15: =IF((F15="o"),I15," ") | V15: =IF((F15="FS"),I15," ")
H16: =IF(H$4>0,(IF(G16<>0,G16*H$4/100," ")),IF(G16<>0,G16*H$2/(100+H$2)," ")) | I16: =IF((G16<>0),G16-H16," ") | M16: =IF(G16<>0,G16-L16," ") | N16: =IF((G16-L16)<>0,N$1-A16," ") | P16: =IF((F16="a"),I16," ") | Q16: =IF((F16="b"),I16," ") | R16: =IF((F16="c"),I16," ") | S16: =IF((F16="d"),I16," ") | T16: =IF((F16="g"),I16," ") | U16: =IF((F16="o"),I16," ") | V16: =IF((F16="FS"),I16," ")
H17: =IF(H$4>0,(IF(G17<>0,G17*H$4/100," ")),IF(G17<>0,G17*H$2/(100+H$2)," ")) | I17: =IF((G17<>0),G17-H17," ") | M17: =IF(G17<>0,G17-L17," ") | N17: =IF((G17-L17)<>0,N$1-A17," ") | P17: =IF((F17="a"),I17," ") | Q17: =IF((F17="b"),I17," ") | R17: =IF((F17="c"),I17," ") | S17: =IF((F17="d"),I17," ") | T17: =IF((F17="g"),I17," ") | U17: =IF((F17="o"),I17," ") | V17: =IF((F17="FS"),I17," ")
H18: =IF(H$4>0,(IF(G18<>0,G18*H$4/100," ")),IF(G18<>0,G18*H$2/(100+H$2)," ")) | I18: =IF((G18<>0),G18-H18," ") | M18: =IF(G18<>0,G18-L18," ") | N18: =IF((G18-L18)<>0,N$1-A18," ") | P18: =IF((F18="a"),I18," ") | Q18: =IF((F18="b"),I18," ") | R18: =IF((F18="c"),I18," ") | S18: =IF((F18="d"),I18," ") | T18: =IF((F18="g"),I18," ") | U18: =IF((F18="o"),I18," ") | V18: =IF((F18="FS"),I18," ")
H19: =IF(H$4>0,(IF(G19<>0,G19*H$4/100," ")),IF(G19<>0,G19*H$2/(100+H$2)," ")) | I19: =IF((G19<>0),G19-H19," ") | M19: =IF(G19<>0,G19-L19," ") | N19: =IF((G19-L19)<>0,N$1-A19," ") | P19: =IF((F19="a"),I19," ") | Q19: =IF((F19="b"),I19," ") | R19: =IF((F19="c"),I19," ") | S19: =IF((F19="d"),I19," ") | T19: =IF((F19="g"),I19," ") | U19: =IF((F19="o"),I19," ") | V19: =IF((F19="FS"),I19," ")
H20: =IF(H$4>0,(IF(G20<>0,G20*H$4/100," ")),IF(G20<>0,G20*H$2/(100+H$2)," ")) | I20: =IF((G20<>0),G20-H20," ") | M20: =IF(G20<>0,G20-L20," ") | N20: =IF((G20-L20)<>0,N$1-A20," ") | P20: =IF((F20="a"),I20," ") | Q20: =IF((F20="b"),I20," ") | R20: =IF((F20="c"),I20," ") | S20: =IF((F20="d"),I20," ") | T20: =IF((F20="g"),I20," ") | U20: =IF((F20="o"),I20," ") | V20: =IF((F20="FS"),I20," ")
H21: =IF(H$4>0,(IF(G21<>0,G21*H$4/100," ")),IF(G21<>0,G21*H$2/(100+H$2)," ")) | I21: =IF((G21<>0),G21-H21," ") | M21: =IF(G21<>0,G21-L21," ") | N21: =IF((G21-L21)<>0,N$1-A21," ") | P21: =IF((F21="a"),I21," ") | Q21: =IF((F21="b"),I21," ") | R21: =IF((F21="c"),I21," ") | S21: =IF((F21="d"),I21," ") | T21: =IF((F21="g"),I21," ") | U21: =IF((F21="o"),I21," ") | V21: =IF((F21="FS"),I21," ")
H22: =IF(H$4>0,(IF(G22<>0,G22*H$4/100," ")),IF(G22<>0,G22*H$2/(100+H$2)," ")) | I22: =IF((G22<>0),G22-H22," ") | M22: =IF(G22<>0,G22-L22," ") | N22: =IF((G22-L22)<>0,N$1-A22," ") | P22: =IF((F22="a"),I22," ") | Q22: =IF((F22="b"),I22," ") | R22: =IF((F22="c"),I22," ") | S22: =IF((F22="d"),I22," ") | T22: =IF((F22="g"),I22," ") | U22: =IF((F22="o"),I22," ") | V22: =IF((F22="FS"),I22," ")
H23: =IF(H$4>0,(IF(G23<>0,G23*H$4/100," ")),IF(G23<>0,G23*H$2/(100+H$2)," ")) | I23: =IF((G23<>0),G23-H23," ") | M23: =IF(G23<>0,G23-L23," ") | N23: =IF((G23-L23)<>0,N$1-A23," ") | P23: =IF((F23="a"),I23," ") | Q23: =IF((F23="b"),I23," ") | R23: =IF((F23="c"),I23," ") | S23: =IF((F23="d"),I23," ") | T23: =IF((F23="g"),I23," ") | U23: =IF((F23="o"),I23," ") | V23: =IF((F23="FS"),I23," ")
H24: =IF(H$4>0,(IF(G24<>0,G24*H$4/100," ")),IF(G24<>0,G24*H$2/(100+H$2)," ")) | I24: =IF((G24<>0),G24-H24," ") | M24: =IF(G24<>0,G24-L24," ") | N24: =IF((G24-L24)<>0,N$1-A24," ") | P24: =IF((F24="a"),I24," ") | Q24: =IF((F24="b"),I24," ") | R24: =IF((F24="c"),I24," ") | S24: =IF((F24="d"),I24," ") | T24: =IF((F24="g"),I24," ") | U24: =IF((F24="o"),I24," ") | V24: =IF((F24="FS"),I24," ")
H25: =IF(H$4>0,(IF(G25<>0,G25*H$4/100," ")),IF(G25<>0,G25*H$2/(100+H$2)," ")) | I25: =IF((G25<>0),G25-H25," ") | M25: =IF(G25<>0,G25-L25," ") | N25: =IF((G25-L25)<>0,N$1-A25," ") | P25: =IF((F25="a"),I25," ") | Q25: =IF((F25="b"),I25," ") | R25: =IF((F25="c"),I25," ") | S25: =IF((F25="d"),I25," ") | T25: =IF((F25="g"),I25," ") | U25: =IF((F25="o"),I25," ") | V25: =IF((F25="FS"),I25," ")
H26: =IF(H$4>0,(IF(G26<>0,G26*H$4/100," ")),IF(G26<>0,G26*H$2/(100+H$2)," ")) | I26: =IF((G26<>0),G26-H26," ") | M26: =IF(G26<>0,G26-L26," ") | N26: =IF((G26-L26)<>0,N$1-A26," ") | P26: =IF((F26="a"),I26," ") | Q26: =IF((F26="b"),I26," ") | R26: =IF((F26="c"),I26," ") | S26: =IF((F26="d"),I26," ") | T26: =IF((F26="g"),I26," ") | U26: =IF((F26="o"),I26," ") | V26: =IF((F26="FS"),I26," ")
... H68: =IF(H$4>0,(IF(G68<>0,G68*H$4/100," ")),IF(G68<>0,G68*H$2/(100+H$2)," ")) | I68: =IF((G68<>0),G68-H68," ") | M68: =IF(G68<>0,G68-L68," ") | N68: =IF((G68-L68)<>0,N$1-A68," ") | P68: =IF((F68="a"),I68," ") | Q68: =IF((F68="b"),I68," ") | R68: =IF((F68="c"),I68," ") | S68: =IF((F68="d"),I68," ") | T68: =IF((F68="g"),I68," ") | U68: =IF((F68="o"),I68," ") | V68: =IF((F68="FS"),I68," ")
F69: =IF((G69<>0),"Enter Letter"," ") | H69: =IF(H$4>0,(IF(G69<>0,G69*H$4/100," ")),IF(G69<>0,G69*H$2/(100+H$2)," ")) | I69: =IF((G69<>0),G69-H69," ") | M69: =IF(G69<>0,G69-L69," ") | N69: =IF((G69-L69)<>0,N$1-A69," ") | P69: =IF((F69="a"),I69," ") | Q69: =IF((F69="b"),I69," ") | R69: =IF((F69="c"),I69," ") | S69: =IF((F69="d"),I69," ") | T69: =IF((F69="g"),I69," ") | U69: =IF((F69="o"),I69," ") | V69: =IF((F69="FS"),I69," ")
F70: =IF((G70<>0),"Enter Letter"," ") | H70: =IF(H$4>0,(IF(G70<>0,G70*H$4/100," ")),IF(G70<>0,G70*H$2/(100+H$2)," ")) | I70: =IF((G70<>0),G70-H70," ") | M70: =IF(G70<>0,G70-L70," ") | N70: =IF((G70-L70)<>0,N$1-A70," ") | P70: =IF((F70="a"),I70," ") | Q70: =IF((F70="b"),I70," ") | R70: =IF((F70="c"),I70," ") | S70: =IF((F70="d"),I70," ") | T70: =IF((F70="g"),I70," ") | U70: =IF((F70="o"),I70," ") | V70: =IF((F70="FS"),I70," ")
F71: =IF((G71<>0),"Enter Letter"," ") | H71: =IF(H$4>0,(IF(G71<>0,G71*H$4/100," ")),IF(G71<>0,G71*H$2/(100+H$2)," ")) | I71: =IF((G71<>0),G71-H71," ") | M71: =IF(G71<>0,G71-L71," ") | N71: =IF((G71-L71)<>0,N$1-A71," ") | P71: =IF((F71="a"),I71," ") | Q71: =IF((F71="b"),I71," ") | R71: =IF((F71="c"),I71," ") | S71: =IF((F71="d"),I71," ") | T71: =IF((F71="g"),I71," ") | U71: =IF((F71="o"),I71," ") | V71: =IF((F71="FS"),I71," ")
F72: =IF((G72<>0),"Enter Letter"," ") | H72: =IF(H$4>0,(IF(G72<>0,G72*H$4/100," ")),IF(G72<>0,G72*H$2/(100+H$2)," ")) | I72: =IF((G72<>0),G72-H72," ") | M72: =IF(G72<>0,G72-L72," ") | N72: =IF((G72-L72)<>0,N$1-A72," ") | P72: =IF((F72="a"),I72," ") | Q72: =IF((F72="b"),I72," ") | R72: =IF((F72="c"),I72," ") | S72: =IF((F72="d"),I72," ") | T72: =IF((F72="g"),I72," ") | U72: =IF((F72="o"),I72," ") | V72: =IF((F72="FS"),I72," ")
F73: =IF((G73<>0),"Enter Letter"," ") | H73: =IF(H$4>0,(IF(G73<>0,G73*H$4/100," ")),IF(G73<>0,G73*H$2/(100+H$2)," ")) | I73: =IF((G73<>0),G73-H73," ") | M73: =IF(G73<>0,G73-L73," ") | N73: =IF((G73-L73)<>0,N$1-A73," ") | P73: =IF((F73="a"),I73," ") | Q73: =IF((F73="b"),I73," ") | R73: =IF((F73="c"),I73," ") | S73: =IF((F73="d"),I73," ") | T73: =IF((F73="g"),I73," ") | U73: =IF((F73="o"),I73," ") | V73: =IF((F73="FS"),I73," ")
F74: =IF((G74<>0),"Enter Letter"," ") | H74: =IF(H$4>0,(IF(G74<>0,G74*H$4/100," ")),IF(G74<>0,G74*H$2/(100+H$2)," ")) | I74: =IF((G74<>0),G74-H74," ") | M74: =IF(G74<>0,G74-L74," ") | N74: =IF((G74-L74)<>0,N$1-A74," ") | P74: =IF((F74="a"),I74," ") | Q74: =IF((F74="b"),I74," ") | R74: =IF((F74="c"),I74," ") | S74: =IF((F74="d"),I74," ") | T74: =IF((F74="g"),I74," ") | U74: =IF((F74="o"),I74," ") | V74: =IF((F74="FS"),I74," ")
F75: =IF((G75<>0),"Enter Letter"," ") | H75: =IF(H$4>0,(IF(G75<>0,G75*H$4/100," ")),IF(G75<>0,G75*H$2/(100+H$2)," ")) | I75: =IF((G75<>0),G75-H75," ") | M75: =IF(G75<>0,G75-L75," ") | N75: =IF((G75-L75)<>0,N$1-A75," ") | P75: =IF((F75="a"),I75," ") | Q75: =IF((F75="b"),I75," ") | R75: =IF((F75="c"),I75," ") | S75: =IF((F75="d"),I75," ") | T75: =IF((F75="g"),I75," ") | U75: =IF((F75="o"),I75," ") | V75: =IF((F75="FS"),I75," ")
F76: =IF((G76<>0),"Enter Letter"," ") | H76: =IF(H$4>0,(IF(G76<>0,G76*H$4/100," ")),IF(G76<>0,G76*H$2/(100+H$2)," ")) | I76: =IF((G76<>0),G76-H76," ") | M76: =IF(G76<>0,G76-L76," ") | N76: =IF((G76-L76)<>0,N$1-A76," ") | P76: =IF((F76="a"),I76," ") | Q76: =IF((F76="b"),I76," ") | R76: =IF((F76="c"),I76," ") | S76: =IF((F76="d"),I76," ") | T76: =IF((F76="g"),I76," ") | U76: =IF((F76="o"),I76," ") | V76: =IF((F76="FS"),I76," ")
F77: =IF((G77<>0),"Enter Letter"," ") | H77: =IF(H$4>0,(IF(G77<>0,G77*H$4/100," ")),IF(G77<>0,G77*H$2/(100+H$2)," ")) | I77: =IF((G77<>0),G77-H77," ") | M77: =IF(G77<>0,G77-L77," ") | N77: =IF((G77-L77)<>0,N$1-A77," ") | P77: =IF((F77="a"),I77," ") | Q77: =IF((F77="b"),I77," ") | R77: =IF((F77="c"),I77," ") | S77: =IF((F77="d"),I77," ") | T77: =IF((F77="g"),I77," ") | U77: =IF((F77="o"),I77," ") | V77: =IF((F77="FS"),I77," ")
F78: =IF((G78<>0),"Enter Letter"," ") | H78: =IF(H$4>0,(IF(G78<>0,G78*H$4/100," ")),IF(G78<>0,G78*H$2/(100+H$2)," ")) | I78: =IF((G78<>0),G78-H78," ") | M78: =IF(G78<>0,G78-L78," ") | N78: =IF((G78-L78)<>0,N$1-A78," ") | P78: =IF((F78="a"),I78," ") | Q78: =IF((F78="b"),I78," ") | R78: =IF((F78="c"),I78," ") | S78: =IF((F78="d"),I78," ") | T78: =IF((F78="g"),I78," ") | U78: =IF((F78="o"),I78," ") | V78: =IF((F78="FS"),I78," ")
F79: =IF((G79<>0),"Enter Letter"," ") | H79: =IF(H$4>0,(IF(G79<>0,G79*H$4/100," ")),IF(G79<>0,G79*H$2/(100+H$2)," ")) | I79: =IF((G79<>0),G79-H79," ") | M79: =IF(G79<>0,G79-L79," ") | N79: =IF((G79-L79)<>0,N$1-A79," ") | P79: =IF((F79="a"),I79," ") | Q79: =IF((F79="b"),I79," ") | R79: =IF((F79="c"),I79," ") | S79: =IF((F79="d"),I79," ") | T79: =IF((F79="g"),I79," ") | U79: =IF((F79="o"),I79," ") | V79: =IF((F79="FS"),I79," ")
F80: =IF((G80<>0),"Enter Letter"," ") | H80: =IF(H$4>0,(IF(G80<>0,G80*H$4/100," ")),IF(G80<>0,G80*H$2/(100+H$2)," ")) | I80: =IF((G80<>0),G80-H80," ") | M80: =IF(G80<>0,G80-L80," ") | N80: =IF((G80-L80)<>0,N$1-A80," ") | P80: =IF((F80="a"),I80," ") | Q80: =IF((F80="b"),I80," ") | R80: =IF((F80="c"),I80," ") | S80: =IF((F80="d"),I80," ") | T80: =IF((F80="g"),I80," ") | U80: =IF((F80="o"),I80," ") | V80: =IF((F80="FS"),I80," ")
... F300: =IF((G300<>0),"Enter Letter"," ") | H300: =IF(H$4>0,(IF(G300<>0,G300*H$4/100," ")),IF(G300<>0,G300*H$2/(100+H$2)," ")) | I300: =IF((G300<>0),G300-H300," ") | M300: =IF(G300<>0,G300-L300," ") | N300: =IF((G300-L300)<>0,N$1-A300," ") | P300: =IF((F300="a"),I300," ") | Q300: =IF((F300="b"),I300," ") | R300: =IF((F300="c"),I300," ") | S300: =IF((F300="d"),I300," ") | T300: =IF((F300="g"),I300," ") | U300: =IF((F300="o"),I300," ") | V300: =IF((F300="FS"),I300," ")

Sheet Sep
A1: =G1-H1-SUM(P1:V1) -> 0 | B1: Check Total | C1: Sales Mileage | D1: =SUM(D5:D300) -> 0 | E1: Sales Description | F1: Enter Expense Code Letter | G1: =SUM(G5:G300) -> 33760 | H1: =SUM(H5:H300) -> 5626.6667 | I1: =SUM(I5:I300) -> 28133.333 | K1: For your information only. Enter How Paid e.g. Cash, Cheque etc., | L1: =SUM(L5:L300) -> 0 | M1: =SUM(M5:M300) -> 33760 | N1: =TODAY() -> 46295 | P1: =SUM(P5:P300) -> 25033.333 | Q1: =SUM(Q5:Q300) -> 800 | R1: =SUM(R5:R300) -> 1800 | S1: =SUM(S5:S300) -> 500 | T1: =SUM(T5:T300) -> 0 | U1: =SUM(U5:U300) -> 0 | V1: =SUM(V5:V300) -> 0 | W1: =SUM(W5:W300) -> 0 | X1: =W1+Aug!X1 -> 0
A2: Sales Date | B2: Customer Name | C2: Sales Invoice Number or reference | D2: Sales Mileage | G2: Sales Value including Vat | H2: =Aug!H2 -> 20 | I2: Sales Net of Vat | L2: Receipts from Customers | P2: Sales Net of Vat | S2: Other Income | T2: Investment Grants | U2: Bad Debts written off | V2: =V1+Aug!V2 -> 0 | W2: Sub contractors only
H3: Vat Output | L3: Actual amount received | M3: Sales Value not yet received | N3: Number of Days Outstanding | P3: Product A | Q3: Product B | R3: Product C | V3: Sale of Fixed Assets | W3: CIS Tax Deducted | X3: CIS Certificate reference
H4: =Aug!H4 -> 0 | P4: A | Q4: B | R4: C | S4: D | T4: G | U4: O | V4: FS
A5: 46268 | B5: FreshField Ltd | C5: INV-2606 | E5: Software monitoring licence | F5: b | G5: 360 | H5: =IF(H$4>0,(IF(G5<>0,G5*H$4/100," ")),IF(G5<>0,G5*H$2/(100+H$2)," ")) -> 60 | I5: =IF((G5<>0),G5-H5," ") -> 300 | M5: =IF(G5<>0,G5-L5," ") -> 360 | N5: =IF((G5-L5)<>0,N$1-A5," ") -> 27 | P5: =IF((F5="a"),I5," ") | Q5: =IF((F5="b"),I5," ") -> 300 | R5: =IF((F5="c"),I5," ") | S5: =IF((F5="d"),I5," ") | T5: =IF((F5="g"),I5," ") | U5: =IF((F5="o"),I5," ") | V5: =IF((F5="FS"),I5," ") | BZ5: 4001
A6: 46270 | B6: CloudNine Ltd | C6: INV-1406 | E6: SaaS licence fee | F6: b | G6: 600 | H6: =IF(H$4>0,(IF(G6<>0,G6*H$4/100," ")),IF(G6<>0,G6*H$2/(100+H$2)," ")) -> 100 | I6: =IF((G6<>0),G6-H6," ") -> 500 | M6: =IF(G6<>0,G6-L6," ") -> 600 | N6: =IF((G6-L6)<>0,N$1-A6," ") -> 25 | P6: =IF((F6="a"),I6," ") | Q6: =IF((F6="b"),I6," ") -> 500 | R6: =IF((F6="c"),I6," ") | S6: =IF((F6="d"),I6," ") | T6: =IF((F6="g"),I6," ") | U6: =IF((F6="o"),I6," ") | V6: =IF((F6="FS"),I6," ") | BZ6: 4001
A7: 46273 | B7: Cedar Systems | C7: INV-2406 | E7: Managed services | F7: a | G7: 480 | H7: =IF(H$4>0,(IF(G7<>0,G7*H$4/100," ")),IF(G7<>0,G7*H$2/(100+H$2)," ")) -> 80 | I7: =IF((G7<>0),G7-H7," ") -> 400 | M7: =IF(G7<>0,G7-L7," ") -> 480 | N7: =IF((G7-L7)<>0,N$1-A7," ") -> 22 | P7: =IF((F7="a"),I7," ") -> 400 | Q7: =IF((F7="b"),I7," ") | R7: =IF((F7="c"),I7," ") | S7: =IF((F7="d"),I7," ") | T7: =IF((F7="g"),I7," ") | U7: =IF((F7="o"),I7," ") | V7: =IF((F7="FS"),I7," ") | BZ7: 4000
A8: 46275 | B8: Pinnacle Group | C8: INV-2206 | E8: Monthly support contract | F8: a | G8: 720 | H8: =IF(H$4>0,(IF(G8<>0,G8*H$4/100," ")),IF(G8<>0,G8*H$2/(100+H$2)," ")) -> 120 | I8: =IF((G8<>0),G8-H8," ") -> 600 | M8: =IF(G8<>0,G8-L8," ") -> 720 | N8: =IF((G8-L8)<>0,N$1-A8," ") -> 20 | P8: =IF((F8="a"),I8," ") -> 600 | Q8: =IF((F8="b"),I8," ") | R8: =IF((F8="c"),I8," ") | S8: =IF((F8="d"),I8," ") | T8: =IF((F8="g"),I8," ") | U8: =IF((F8="o"),I8," ") | V8: =IF((F8="FS"),I8," ") | BZ8: 4000
A9: 46280 | B9: Acme Corp | C9: INV-1006 | E9: IT consultancy services | F9: a | G9: 25000 | H9: =IF(H$4>0,(IF(G9<>0,G9*H$4/100," ")),IF(G9<>0,G9*H$2/(100+H$2)," ")) -> 4166.6667 | I9: =IF((G9<>0),G9-H9," ") -> 20833.333 | M9: =IF(G9<>0,G9-L9," ") -> 25000 | N9: =IF((G9-L9)<>0,N$1-A9," ") -> 15 | P9: =IF((F9="a"),I9," ") -> 20833.333 | Q9: =IF((F9="b"),I9," ") | R9: =IF((F9="c"),I9," ") | S9: =IF((F9="d"),I9," ") | T9: =IF((F9="g"),I9," ") | U9: =IF((F9="o"),I9," ") | V9: =IF((F9="FS"),I9," ") | BZ9: 4000
A10: 46281 | B10: Summit Training | C10: INV-2802 | E10: Technical training delivery | F10: c | G10: 1200 | H10: =IF(H$4>0,(IF(G10<>0,G10*H$4/100," ")),IF(G10<>0,G10*H$2/(100+H$2)," ")) -> 200 | I10: =IF((G10<>0),G10-H10," ") -> 1000 | M10: =IF(G10<>0,G10-L10," ") -> 1200 | N10: =IF((G10-L10)<>0,N$1-A10," ") -> 14 | P10: =IF((F10="a"),I10," ") | Q10: =IF((F10="b"),I10," ") | R10: =IF((F10="c"),I10," ") -> 1000 | S10: =IF((F10="d"),I10," ") | T10: =IF((F10="g"),I10," ") | U10: =IF((F10="o"),I10," ") | V10: =IF((F10="FS"),I10," ") | BZ10: 4002
A11: 46283 | B11: TechStart Ltd | C11: INV-1106 | E11: IT consultancy retainer | F11: a | G11: 2400 | H11: =IF(H$4>0,(IF(G11<>0,G11*H$4/100," ")),IF(G11<>0,G11*H$2/(100+H$2)," ")) -> 400 | I11: =IF((G11<>0),G11-H11," ") -> 2000 | M11: =IF(G11<>0,G11-L11," ") -> 2400 | N11: =IF((G11-L11)<>0,N$1-A11," ") -> 12 | P11: =IF((F11="a"),I11," ") -> 2000 | Q11: =IF((F11="b"),I11," ") | R11: =IF((F11="c"),I11," ") | S11: =IF((F11="d"),I11," ") | T11: =IF((F11="g"),I11," ") | U11: =IF((F11="o"),I11," ") | V11: =IF((F11="FS"),I11," ") | BZ11: 4000
A12: 46285 | B12: StartupHub | C12: INV-1504 | E12: Agile methodology workshop | F12: c | G12: 960 | H12: =IF(H$4>0,(IF(G12<>0,G12*H$4/100," ")),IF(G12<>0,G12*H$2/(100+H$2)," ")) -> 160 | I12: =IF((G12<>0),G12-H12," ") -> 800 | M12: =IF(G12<>0,G12-L12," ") -> 960 | N12: =IF((G12-L12)<>0,N$1-A12," ") -> 10 | P12: =IF((F12="a"),I12," ") | Q12: =IF((F12="b"),I12," ") | R12: =IF((F12="c"),I12," ") -> 800 | S12: =IF((F12="d"),I12," ") | T12: =IF((F12="g"),I12," ") | U12: =IF((F12="o"),I12," ") | V12: =IF((F12="FS"),I12," ") | BZ12: 4002
A13: 46287 | B13: WidgetWorks | C13: INV-2102 | E13: Project consultancy | F13: a | G13: 1440 | H13: =IF(H$4>0,(IF(G13<>0,G13*H$4/100," ")),IF(G13<>0,G13*H$2/(100+H$2)," ")) -> 240 | I13: =IF((G13<>0),G13-H13," ") -> 1200 | M13: =IF(G13<>0,G13-L13," ") -> 1440 | N13: =IF((G13-L13)<>0,N$1-A13," ") -> 8 | P13: =IF((F13="a"),I13," ") -> 1200 | Q13: =IF((F13="b"),I13," ") | R13: =IF((F13="c"),I13," ") | S13: =IF((F13="d"),I13," ") | T13: =IF((F13="g"),I13," ") | U13: =IF((F13="o"),I13," ") | V13: =IF((F13="FS"),I13," ") | BZ13: 4000
A14: 46290 | B14: Epsilon Partners | C14: INV-1601 | E14: Client referral commission | F14: d | G14: 600 | H14: =IF(H$4>0,(IF(G14<>0,G14*H$4/100," ")),IF(G14<>0,G14*H$2/(100+H$2)," ")) -> 100 | I14: =IF((G14<>0),G14-H14," ") -> 500 | M14: =IF(G14<>0,G14-L14," ") -> 600 | N14: =IF((G14-L14)<>0,N$1-A14," ") -> 5 | P14: =IF((F14="a"),I14," ") | Q14: =IF((F14="b"),I14," ") | R14: =IF((F14="c"),I14," ") | S14: =IF((F14="d"),I14," ") -> 500 | T14: =IF((F14="g"),I14," ") | U14: =IF((F14="o"),I14," ") | V14: =IF((F14="FS"),I14," ") | BZ14: 4003
H15: =IF(H$4>0,(IF(G15<>0,G15*H$4/100," ")),IF(G15<>0,G15*H$2/(100+H$2)," ")) | I15: =IF((G15<>0),G15-H15," ") | M15: =IF(G15<>0,G15-L15," ") | N15: =IF((G15-L15)<>0,N$1-A15," ") | P15: =IF((F15="a"),I15," ") | Q15: =IF((F15="b"),I15," ") | R15: =IF((F15="c"),I15," ") | S15: =IF((F15="d"),I15," ") | T15: =IF((F15="g"),I15," ") | U15: =IF((F15="o"),I15," ") | V15: =IF((F15="FS"),I15," ")
H16: =IF(H$4>0,(IF(G16<>0,G16*H$4/100," ")),IF(G16<>0,G16*H$2/(100+H$2)," ")) | I16: =IF((G16<>0),G16-H16," ") | M16: =IF(G16<>0,G16-L16," ") | N16: =IF((G16-L16)<>0,N$1-A16," ") | P16: =IF((F16="a"),I16," ") | Q16: =IF((F16="b"),I16," ") | R16: =IF((F16="c"),I16," ") | S16: =IF((F16="d"),I16," ") | T16: =IF((F16="g"),I16," ") | U16: =IF((F16="o"),I16," ") | V16: =IF((F16="FS"),I16," ")
H17: =IF(H$4>0,(IF(G17<>0,G17*H$4/100," ")),IF(G17<>0,G17*H$2/(100+H$2)," ")) | I17: =IF((G17<>0),G17-H17," ") | M17: =IF(G17<>0,G17-L17," ") | N17: =IF((G17-L17)<>0,N$1-A17," ") | P17: =IF((F17="a"),I17," ") | Q17: =IF((F17="b"),I17," ") | R17: =IF((F17="c"),I17," ") | S17: =IF((F17="d"),I17," ") | T17: =IF((F17="g"),I17," ") | U17: =IF((F17="o"),I17," ") | V17: =IF((F17="FS"),I17," ")
H18: =IF(H$4>0,(IF(G18<>0,G18*H$4/100," ")),IF(G18<>0,G18*H$2/(100+H$2)," ")) | I18: =IF((G18<>0),G18-H18," ") | M18: =IF(G18<>0,G18-L18," ") | N18: =IF((G18-L18)<>0,N$1-A18," ") | P18: =IF((F18="a"),I18," ") | Q18: =IF((F18="b"),I18," ") | R18: =IF((F18="c"),I18," ") | S18: =IF((F18="d"),I18," ") | T18: =IF((F18="g"),I18," ") | U18: =IF((F18="o"),I18," ") | V18: =IF((F18="FS"),I18," ")
H19: =IF(H$4>0,(IF(G19<>0,G19*H$4/100," ")),IF(G19<>0,G19*H$2/(100+H$2)," ")) | I19: =IF((G19<>0),G19-H19," ") | M19: =IF(G19<>0,G19-L19," ") | N19: =IF((G19-L19)<>0,N$1-A19," ") | P19: =IF((F19="a"),I19," ") | Q19: =IF((F19="b"),I19," ") | R19: =IF((F19="c"),I19," ") | S19: =IF((F19="d"),I19," ") | T19: =IF((F19="g"),I19," ") | U19: =IF((F19="o"),I19," ") | V19: =IF((F19="FS"),I19," ")
H20: =IF(H$4>0,(IF(G20<>0,G20*H$4/100," ")),IF(G20<>0,G20*H$2/(100+H$2)," ")) | I20: =IF((G20<>0),G20-H20," ") | M20: =IF(G20<>0,G20-L20," ") | N20: =IF((G20-L20)<>0,N$1-A20," ") | P20: =IF((F20="a"),I20," ") | Q20: =IF((F20="b"),I20," ") | R20: =IF((F20="c"),I20," ") | S20: =IF((F20="d"),I20," ") | T20: =IF((F20="g"),I20," ") | U20: =IF((F20="o"),I20," ") | V20: =IF((F20="FS"),I20," ")
H21: =IF(H$4>0,(IF(G21<>0,G21*H$4/100," ")),IF(G21<>0,G21*H$2/(100+H$2)," ")) | I21: =IF((G21<>0),G21-H21," ") | M21: =IF(G21<>0,G21-L21," ") | N21: =IF((G21-L21)<>0,N$1-A21," ") | P21: =IF((F21="a"),I21," ") | Q21: =IF((F21="b"),I21," ") | R21: =IF((F21="c"),I21," ") | S21: =IF((F21="d"),I21," ") | T21: =IF((F21="g"),I21," ") | U21: =IF((F21="o"),I21," ") | V21: =IF((F21="FS"),I21," ")
H22: =IF(H$4>0,(IF(G22<>0,G22*H$4/100," ")),IF(G22<>0,G22*H$2/(100+H$2)," ")) | I22: =IF((G22<>0),G22-H22," ") | M22: =IF(G22<>0,G22-L22," ") | N22: =IF((G22-L22)<>0,N$1-A22," ") | P22: =IF((F22="a"),I22," ") | Q22: =IF((F22="b"),I22," ") | R22: =IF((F22="c"),I22," ") | S22: =IF((F22="d"),I22," ") | T22: =IF((F22="g"),I22," ") | U22: =IF((F22="o"),I22," ") | V22: =IF((F22="FS"),I22," ")
H23: =IF(H$4>0,(IF(G23<>0,G23*H$4/100," ")),IF(G23<>0,G23*H$2/(100+H$2)," ")) | I23: =IF((G23<>0),G23-H23," ") | M23: =IF(G23<>0,G23-L23," ") | N23: =IF((G23-L23)<>0,N$1-A23," ") | P23: =IF((F23="a"),I23," ") | Q23: =IF((F23="b"),I23," ") | R23: =IF((F23="c"),I23," ") | S23: =IF((F23="d"),I23," ") | T23: =IF((F23="g"),I23," ") | U23: =IF((F23="o"),I23," ") | V23: =IF((F23="FS"),I23," ")
H24: =IF(H$4>0,(IF(G24<>0,G24*H$4/100," ")),IF(G24<>0,G24*H$2/(100+H$2)," ")) | I24: =IF((G24<>0),G24-H24," ") | M24: =IF(G24<>0,G24-L24," ") | N24: =IF((G24-L24)<>0,N$1-A24," ") | P24: =IF((F24="a"),I24," ") | Q24: =IF((F24="b"),I24," ") | R24: =IF((F24="c"),I24," ") | S24: =IF((F24="d"),I24," ") | T24: =IF((F24="g"),I24," ") | U24: =IF((F24="o"),I24," ") | V24: =IF((F24="FS"),I24," ")
H25: =IF(H$4>0,(IF(G25<>0,G25*H$4/100," ")),IF(G25<>0,G25*H$2/(100+H$2)," ")) | I25: =IF((G25<>0),G25-H25," ") | M25: =IF(G25<>0,G25-L25," ") | N25: =IF((G25-L25)<>0,N$1-A25," ") | P25: =IF((F25="a"),I25," ") | Q25: =IF((F25="b"),I25," ") | R25: =IF((F25="c"),I25," ") | S25: =IF((F25="d"),I25," ") | T25: =IF((F25="g"),I25," ") | U25: =IF((F25="o"),I25," ") | V25: =IF((F25="FS"),I25," ")
H26: =IF(H$4>0,(IF(G26<>0,G26*H$4/100," ")),IF(G26<>0,G26*H$2/(100+H$2)," ")) | I26: =IF((G26<>0),G26-H26," ") | M26: =IF(G26<>0,G26-L26," ") | N26: =IF((G26-L26)<>0,N$1-A26," ") | P26: =IF((F26="a"),I26," ") | Q26: =IF((F26="b"),I26," ") | R26: =IF((F26="c"),I26," ") | S26: =IF((F26="d"),I26," ") | T26: =IF((F26="g"),I26," ") | U26: =IF((F26="o"),I26," ") | V26: =IF((F26="FS"),I26," ")
... H68: =IF(H$4>0,(IF(G68<>0,G68*H$4/100," ")),IF(G68<>0,G68*H$2/(100+H$2)," ")) | I68: =IF((G68<>0),G68-H68," ") | M68: =IF(G68<>0,G68-L68," ") | N68: =IF((G68-L68)<>0,N$1-A68," ") | P68: =IF((F68="a"),I68," ") | Q68: =IF((F68="b"),I68," ") | R68: =IF((F68="c"),I68," ") | S68: =IF((F68="d"),I68," ") | T68: =IF((F68="g"),I68," ") | U68: =IF((F68="o"),I68," ") | V68: =IF((F68="FS"),I68," ")
F69: =IF((G69<>0),"Enter Letter"," ") | H69: =IF(H$4>0,(IF(G69<>0,G69*H$4/100," ")),IF(G69<>0,G69*H$2/(100+H$2)," ")) | I69: =IF((G69<>0),G69-H69," ") | M69: =IF(G69<>0,G69-L69," ") | N69: =IF((G69-L69)<>0,N$1-A69," ") | P69: =IF((F69="a"),I69," ") | Q69: =IF((F69="b"),I69," ") | R69: =IF((F69="c"),I69," ") | S69: =IF((F69="d"),I69," ") | T69: =IF((F69="g"),I69," ") | U69: =IF((F69="o"),I69," ") | V69: =IF((F69="FS"),I69," ")
F70: =IF((G70<>0),"Enter Letter"," ") | H70: =IF(H$4>0,(IF(G70<>0,G70*H$4/100," ")),IF(G70<>0,G70*H$2/(100+H$2)," ")) | I70: =IF((G70<>0),G70-H70," ") | M70: =IF(G70<>0,G70-L70," ") | N70: =IF((G70-L70)<>0,N$1-A70," ") | P70: =IF((F70="a"),I70," ") | Q70: =IF((F70="b"),I70," ") | R70: =IF((F70="c"),I70," ") | S70: =IF((F70="d"),I70," ") | T70: =IF((F70="g"),I70," ") | U70: =IF((F70="o"),I70," ") | V70: =IF((F70="FS"),I70," ")
F71: =IF((G71<>0),"Enter Letter"," ") | H71: =IF(H$4>0,(IF(G71<>0,G71*H$4/100," ")),IF(G71<>0,G71*H$2/(100+H$2)," ")) | I71: =IF((G71<>0),G71-H71," ") | M71: =IF(G71<>0,G71-L71," ") | N71: =IF((G71-L71)<>0,N$1-A71," ") | P71: =IF((F71="a"),I71," ") | Q71: =IF((F71="b"),I71," ") | R71: =IF((F71="c"),I71," ") | S71: =IF((F71="d"),I71," ") | T71: =IF((F71="g"),I71," ") | U71: =IF((F71="o"),I71," ") | V71: =IF((F71="FS"),I71," ")
F72: =IF((G72<>0),"Enter Letter"," ") | H72: =IF(H$4>0,(IF(G72<>0,G72*H$4/100," ")),IF(G72<>0,G72*H$2/(100+H$2)," ")) | I72: =IF((G72<>0),G72-H72," ") | M72: =IF(G72<>0,G72-L72," ") | N72: =IF((G72-L72)<>0,N$1-A72," ") | P72: =IF((F72="a"),I72," ") | Q72: =IF((F72="b"),I72," ") | R72: =IF((F72="c"),I72," ") | S72: =IF((F72="d"),I72," ") | T72: =IF((F72="g"),I72," ") | U72: =IF((F72="o"),I72," ") | V72: =IF((F72="FS"),I72," ")
F73: =IF((G73<>0),"Enter Letter"," ") | H73: =IF(H$4>0,(IF(G73<>0,G73*H$4/100," ")),IF(G73<>0,G73*H$2/(100+H$2)," ")) | I73: =IF((G73<>0),G73-H73," ") | M73: =IF(G73<>0,G73-L73," ") | N73: =IF((G73-L73)<>0,N$1-A73," ") | P73: =IF((F73="a"),I73," ") | Q73: =IF((F73="b"),I73," ") | R73: =IF((F73="c"),I73," ") | S73: =IF((F73="d"),I73," ") | T73: =IF((F73="g"),I73," ") | U73: =IF((F73="o"),I73," ") | V73: =IF((F73="FS"),I73," ")
F74: =IF((G74<>0),"Enter Letter"," ") | H74: =IF(H$4>0,(IF(G74<>0,G74*H$4/100," ")),IF(G74<>0,G74*H$2/(100+H$2)," ")) | I74: =IF((G74<>0),G74-H74," ") | M74: =IF(G74<>0,G74-L74," ") | N74: =IF((G74-L74)<>0,N$1-A74," ") | P74: =IF((F74="a"),I74," ") | Q74: =IF((F74="b"),I74," ") | R74: =IF((F74="c"),I74," ") | S74: =IF((F74="d"),I74," ") | T74: =IF((F74="g"),I74," ") | U74: =IF((F74="o"),I74," ") | V74: =IF((F74="FS"),I74," ")
F75: =IF((G75<>0),"Enter Letter"," ") | H75: =IF(H$4>0,(IF(G75<>0,G75*H$4/100," ")),IF(G75<>0,G75*H$2/(100+H$2)," ")) | I75: =IF((G75<>0),G75-H75," ") | M75: =IF(G75<>0,G75-L75," ") | N75: =IF((G75-L75)<>0,N$1-A75," ") | P75: =IF((F75="a"),I75," ") | Q75: =IF((F75="b"),I75," ") | R75: =IF((F75="c"),I75," ") | S75: =IF((F75="d"),I75," ") | T75: =IF((F75="g"),I75," ") | U75: =IF((F75="o"),I75," ") | V75: =IF((F75="FS"),I75," ")
F76: =IF((G76<>0),"Enter Letter"," ") | H76: =IF(H$4>0,(IF(G76<>0,G76*H$4/100," ")),IF(G76<>0,G76*H$2/(100+H$2)," ")) | I76: =IF((G76<>0),G76-H76," ") | M76: =IF(G76<>0,G76-L76," ") | N76: =IF((G76-L76)<>0,N$1-A76," ") | P76: =IF((F76="a"),I76," ") | Q76: =IF((F76="b"),I76," ") | R76: =IF((F76="c"),I76," ") | S76: =IF((F76="d"),I76," ") | T76: =IF((F76="g"),I76," ") | U76: =IF((F76="o"),I76," ") | V76: =IF((F76="FS"),I76," ")
F77: =IF((G77<>0),"Enter Letter"," ") | H77: =IF(H$4>0,(IF(G77<>0,G77*H$4/100," ")),IF(G77<>0,G77*H$2/(100+H$2)," ")) | I77: =IF((G77<>0),G77-H77," ") | M77: =IF(G77<>0,G77-L77," ") | N77: =IF((G77-L77)<>0,N$1-A77," ") | P77: =IF((F77="a"),I77," ") | Q77: =IF((F77="b"),I77," ") | R77: =IF((F77="c"),I77," ") | S77: =IF((F77="d"),I77," ") | T77: =IF((F77="g"),I77," ") | U77: =IF((F77="o"),I77," ") | V77: =IF((F77="FS"),I77," ")
F78: =IF((G78<>0),"Enter Letter"," ") | H78: =IF(H$4>0,(IF(G78<>0,G78*H$4/100," ")),IF(G78<>0,G78*H$2/(100+H$2)," ")) | I78: =IF((G78<>0),G78-H78," ") | M78: =IF(G78<>0,G78-L78," ") | N78: =IF((G78-L78)<>0,N$1-A78," ") | P78: =IF((F78="a"),I78," ") | Q78: =IF((F78="b"),I78," ") | R78: =IF((F78="c"),I78," ") | S78: =IF((F78="d"),I78," ") | T78: =IF((F78="g"),I78," ") | U78: =IF((F78="o"),I78," ") | V78: =IF((F78="FS"),I78," ")
F79: =IF((G79<>0),"Enter Letter"," ") | H79: =IF(H$4>0,(IF(G79<>0,G79*H$4/100," ")),IF(G79<>0,G79*H$2/(100+H$2)," ")) | I79: =IF((G79<>0),G79-H79," ") | M79: =IF(G79<>0,G79-L79," ") | N79: =IF((G79-L79)<>0,N$1-A79," ") | P79: =IF((F79="a"),I79," ") | Q79: =IF((F79="b"),I79," ") | R79: =IF((F79="c"),I79," ") | S79: =IF((F79="d"),I79," ") | T79: =IF((F79="g"),I79," ") | U79: =IF((F79="o"),I79," ") | V79: =IF((F79="FS"),I79," ")
F80: =IF((G80<>0),"Enter Letter"," ") | H80: =IF(H$4>0,(IF(G80<>0,G80*H$4/100," ")),IF(G80<>0,G80*H$2/(100+H$2)," ")) | I80: =IF((G80<>0),G80-H80," ") | M80: =IF(G80<>0,G80-L80," ") | N80: =IF((G80-L80)<>0,N$1-A80," ") | P80: =IF((F80="a"),I80," ") | Q80: =IF((F80="b"),I80," ") | R80: =IF((F80="c"),I80," ") | S80: =IF((F80="d"),I80," ") | T80: =IF((F80="g"),I80," ") | U80: =IF((F80="o"),I80," ") | V80: =IF((F80="FS"),I80," ")
... F300: =IF((G300<>0),"Enter Letter"," ") | H300: =IF(H$4>0,(IF(G300<>0,G300*H$4/100," ")),IF(G300<>0,G300*H$2/(100+H$2)," ")) | I300: =IF((G300<>0),G300-H300," ") | M300: =IF(G300<>0,G300-L300," ") | N300: =IF((G300-L300)<>0,N$1-A300," ") | P300: =IF((F300="a"),I300," ") | Q300: =IF((F300="b"),I300," ") | R300: =IF((F300="c"),I300," ") | S300: =IF((F300="d"),I300," ") | T300: =IF((F300="g"),I300," ") | U300: =IF((F300="o"),I300," ") | V300: =IF((F300="FS"),I300," ")

Sheet Oct
A1: =G1-H1-SUM(P1:V1) -> 0 | B1: Check Total | C1: Sales Mileage | D1: =SUM(D5:D300) -> 0 | E1: Sales Description | F1: Enter Expense Code Letter | G1: =SUM(G5:G300) -> 50560 | H1: =SUM(H5:H300) -> 8426.6667 | I1: =SUM(I5:I300) -> 42133.333 | K1: For your information only. Enter How Paid e.g. Cash, Cheque etc., | L1: =SUM(L5:L300) -> 0 | M1: =SUM(M5:M300) -> 50560 | N1: =TODAY() -> 46295 | P1: =SUM(P5:P300) -> 27133.333 | Q1: =SUM(Q5:Q300) -> 1800 | R1: =SUM(R5:R300) -> 0 | S1: =SUM(S5:S300) -> 700 | T1: =SUM(T5:T300) -> 0 | U1: =SUM(U5:U300) -> 0 | V1: =SUM(V5:V300) -> 12500 | W1: =SUM(W5:W300) -> 0 | X1: =W1+Sep!X1 -> 0
A2: Sales Date | B2: Customer Name | C2: Sales Invoice Number or reference | D2: Sales Mileage | G2: Sales Value including Vat | H2: =Sep!H2 -> 20 | I2: Sales Net of Vat | L2: Receipts from Customers | P2: Sales Net of Vat | S2: Other Income | T2: Investment Grants | U2: Bad Debts written off | V2: =V1+Sep!V2 -> 12500 | W2: Sub contractors only
H3: Vat Output | L3: Actual amount received | M3: Sales Value not yet received | N3: Number of Days Outstanding | P3: Product A | Q3: Product B | R3: Product C | V3: Sale of Fixed Assets | W3: CIS Tax Deducted | X3: CIS Certificate reference
H4: =Sep!H4 -> 0 | P4: A | Q4: B | R4: C | S4: D | T4: G | U4: O | V4: FS
A5: 46296 | B5: Beta Systems | C5: INV-1303 | E5: Software licence renewal | F5: b | G5: 1200 | H5: =IF(H$4>0,(IF(G5<>0,G5*H$4/100," ")),IF(G5<>0,G5*H$2/(100+H$2)," ")) -> 200 | I5: =IF((G5<>0),G5-H5," ") -> 1000 | M5: =IF(G5<>0,G5-L5," ") -> 1200 | N5: =IF((G5-L5)<>0,N$1-A5," ") -> -1 | P5: =IF((F5="a"),I5," ") | Q5: =IF((F5="b"),I5," ") -> 1000 | R5: =IF((F5="c"),I5," ") | S5: =IF((F5="d"),I5," ") | T5: =IF((F5="g"),I5," ") | U5: =IF((F5="o"),I5," ") | V5: =IF((F5="FS"),I5," ") | BZ5: 4001
A6: 46298 | B6: FreshField Ltd | C6: INV-2607 | E6: Software monitoring licence | F6: b | G6: 360 | H6: =IF(H$4>0,(IF(G6<>0,G6*H$4/100," ")),IF(G6<>0,G6*H$2/(100+H$2)," ")) -> 60 | I6: =IF((G6<>0),G6-H6," ") -> 300 | M6: =IF(G6<>0,G6-L6," ") -> 360 | N6: =IF((G6-L6)<>0,N$1-A6," ") -> -3 | P6: =IF((F6="a"),I6," ") | Q6: =IF((F6="b"),I6," ") -> 300 | R6: =IF((F6="c"),I6," ") | S6: =IF((F6="d"),I6," ") | T6: =IF((F6="g"),I6," ") | U6: =IF((F6="o"),I6," ") | V6: =IF((F6="FS"),I6," ") | BZ6: 4001
A7: 46300 | B7: CloudNine Ltd | C7: INV-1407 | E7: SaaS licence fee | F7: b | G7: 600 | H7: =IF(H$4>0,(IF(G7<>0,G7*H$4/100," ")),IF(G7<>0,G7*H$2/(100+H$2)," ")) -> 100 | I7: =IF((G7<>0),G7-H7," ") -> 500 | M7: =IF(G7<>0,G7-L7," ") -> 600 | N7: =IF((G7-L7)<>0,N$1-A7," ") -> -5 | P7: =IF((F7="a"),I7," ") | Q7: =IF((F7="b"),I7," ") -> 500 | R7: =IF((F7="c"),I7," ") | S7: =IF((F7="d"),I7," ") | T7: =IF((F7="g"),I7," ") | U7: =IF((F7="o"),I7," ") | V7: =IF((F7="FS"),I7," ") | BZ7: 4001
A8: 46303 | B8: Cedar Systems | C8: INV-2407 | E8: Managed services | F8: a | G8: 480 | H8: =IF(H$4>0,(IF(G8<>0,G8*H$4/100," ")),IF(G8<>0,G8*H$2/(100+H$2)," ")) -> 80 | I8: =IF((G8<>0),G8-H8," ") -> 400 | M8: =IF(G8<>0,G8-L8," ") -> 480 | N8: =IF((G8-L8)<>0,N$1-A8," ") -> -8 | P8: =IF((F8="a"),I8," ") -> 400 | Q8: =IF((F8="b"),I8," ") | R8: =IF((F8="c"),I8," ") | S8: =IF((F8="d"),I8," ") | T8: =IF((F8="g"),I8," ") | U8: =IF((F8="o"),I8," ") | V8: =IF((F8="FS"),I8," ") | BZ8: 4000
A9: 46305 | B9: Private buyer | C9: INV-1901 | E9: Disposal of company van | F9: fs | G9: 15000 | H9: =IF(H$4>0,(IF(G9<>0,G9*H$4/100," ")),IF(G9<>0,G9*H$2/(100+H$2)," ")) -> 2500 | I9: =IF((G9<>0),G9-H9," ") -> 12500 | M9: =IF(G9<>0,G9-L9," ") -> 15000 | N9: =IF((G9-L9)<>0,N$1-A9," ") -> -10 | P9: =IF((F9="a"),I9," ") | Q9: =IF((F9="b"),I9," ") | R9: =IF((F9="c"),I9," ") | S9: =IF((F9="d"),I9," ") | T9: =IF((F9="g"),I9," ") | U9: =IF((F9="o"),I9," ") | V9: =IF((F9="FS"),I9," ") -> 12500 | BZ9: 4006
A10: 46305 | B10: Pinnacle Group | C10: INV-2207 | E10: Monthly support contract | F10: a | G10: 720 | H10: =IF(H$4>0,(IF(G10<>0,G10*H$4/100," ")),IF(G10<>0,G10*H$2/(100+H$2)," ")) -> 120 | I10: =IF((G10<>0),G10-H10," ") -> 600 | M10: =IF(G10<>0,G10-L10," ") -> 720 | N10: =IF((G10-L10)<>0,N$1-A10," ") -> -10 | P10: =IF((F10="a"),I10," ") -> 600 | Q10: =IF((F10="b"),I10," ") | R10: =IF((F10="c"),I10," ") | S10: =IF((F10="d"),I10," ") | T10: =IF((F10="g"),I10," ") | U10: =IF((F10="o"),I10," ") | V10: =IF((F10="FS"),I10," ") | BZ10: 4000
A11: 46309 | B11: NorthStar Digital | C11: INV-2302 | E11: Project delivery | F11: a | G11: 2160 | H11: =IF(H$4>0,(IF(G11<>0,G11*H$4/100," ")),IF(G11<>0,G11*H$2/(100+H$2)," ")) -> 360 | I11: =IF((G11<>0),G11-H11," ") -> 1800 | M11: =IF(G11<>0,G11-L11," ") -> 2160 | N11: =IF((G11-L11)<>0,N$1-A11," ") -> -14 | P11: =IF((F11="a"),I11," ") -> 1800 | Q11: =IF((F11="b"),I11," ") | R11: =IF((F11="c"),I11," ") | S11: =IF((F11="d"),I11," ") | T11: =IF((F11="g"),I11," ") | U11: =IF((F11="o"),I11," ") | V11: =IF((F11="FS"),I11," ") | BZ11: 4000
A12: 46310 | B12: Acme Corp | C12: INV-1007 | E12: IT consultancy services | F12: a | G12: 25000 | H12: =IF(H$4>0,(IF(G12<>0,G12*H$4/100," ")),IF(G12<>0,G12*H$2/(100+H$2)," ")) -> 4166.6667 | I12: =IF((G12<>0),G12-H12," ") -> 20833.333 | M12: =IF(G12<>0,G12-L12," ") -> 25000 | N12: =IF((G12-L12)<>0,N$1-A12," ") -> -15 | P12: =IF((F12="a"),I12," ") -> 20833.333 | Q12: =IF((F12="b"),I12," ") | R12: =IF((F12="c"),I12," ") | S12: =IF((F12="d"),I12," ") | T12: =IF((F12="g"),I12," ") | U12: =IF((F12="o"),I12," ") | V12: =IF((F12="FS"),I12," ") | BZ12: 4000
A13: 46313 | B13: TechStart Ltd | C13: INV-1107 | E13: IT consultancy retainer | F13: a | G13: 2400 | H13: =IF(H$4>0,(IF(G13<>0,G13*H$4/100," ")),IF(G13<>0,G13*H$2/(100+H$2)," ")) -> 400 | I13: =IF((G13<>0),G13-H13," ") -> 2000 | M13: =IF(G13<>0,G13-L13," ") -> 2400 | N13: =IF((G13-L13)<>0,N$1-A13," ") -> -18 | P13: =IF((F13="a"),I13," ") -> 2000 | Q13: =IF((F13="b"),I13," ") | R13: =IF((F13="c"),I13," ") | S13: =IF((F13="d"),I13," ") | T13: =IF((F13="g"),I13," ") | U13: =IF((F13="o"),I13," ") | V13: =IF((F13="FS"),I13," ") | BZ13: 4000
A14: 46315 | B14: DataFlow Inc | C14: INV-1204 | E14: Ad-hoc consultancy project | F14: a | G14: 1800 | H14: =IF(H$4>0,(IF(G14<>0,G14*H$4/100," ")),IF(G14<>0,G14*H$2/(100+H$2)," ")) -> 300 | I14: =IF((G14<>0),G14-H14," ") -> 1500 | M14: =IF(G14<>0,G14-L14," ") -> 1800 | N14: =IF((G14-L14)<>0,N$1-A14," ") -> -20 | P14: =IF((F14="a"),I14," ") -> 1500 | Q14: =IF((F14="b"),I14," ") | R14: =IF((F14="c"),I14," ") | S14: =IF((F14="d"),I14," ") | T14: =IF((F14="g"),I14," ") | U14: =IF((F14="o"),I14," ") | V14: =IF((F14="FS"),I14," ") | BZ14: 4000
A15: 46323 | B15: Horizon Analytics | C15: INV-2703 | E15: Data analytics commission | F15: d | G15: 840 | H15: =IF(H$4>0,(IF(G15<>0,G15*H$4/100," ")),IF(G15<>0,G15*H$2/(100+H$2)," ")) -> 140 | I15: =IF((G15<>0),G15-H15," ") -> 700 | M15: =IF(G15<>0,G15-L15," ") -> 840 | N15: =IF((G15-L15)<>0,N$1-A15," ") -> -28 | P15: =IF((F15="a"),I15," ") | Q15: =IF((F15="b"),I15," ") | R15: =IF((F15="c"),I15," ") | S15: =IF((F15="d"),I15," ") -> 700 | T15: =IF((F15="g"),I15," ") | U15: =IF((F15="o"),I15," ") | V15: =IF((F15="FS"),I15," ") | BZ15: 4003
H16: =IF(H$4>0,(IF(G16<>0,G16*H$4/100," ")),IF(G16<>0,G16*H$2/(100+H$2)," ")) | I16: =IF((G16<>0),G16-H16," ") | M16: =IF(G16<>0,G16-L16," ") | N16: =IF((G16-L16)<>0,N$1-A16," ") | P16: =IF((F16="a"),I16," ") | Q16: =IF((F16="b"),I16," ") | R16: =IF((F16="c"),I16," ") | S16: =IF((F16="d"),I16," ") | T16: =IF((F16="g"),I16," ") | U16: =IF((F16="o"),I16," ") | V16: =IF((F16="FS"),I16," ")
H17: =IF(H$4>0,(IF(G17<>0,G17*H$4/100," ")),IF(G17<>0,G17*H$2/(100+H$2)," ")) | I17: =IF((G17<>0),G17-H17," ") | M17: =IF(G17<>0,G17-L17," ") | N17: =IF((G17-L17)<>0,N$1-A17," ") | P17: =IF((F17="a"),I17," ") | Q17: =IF((F17="b"),I17," ") | R17: =IF((F17="c"),I17," ") | S17: =IF((F17="d"),I17," ") | T17: =IF((F17="g"),I17," ") | U17: =IF((F17="o"),I17," ") | V17: =IF((F17="FS"),I17," ")
H18: =IF(H$4>0,(IF(G18<>0,G18*H$4/100," ")),IF(G18<>0,G18*H$2/(100+H$2)," ")) | I18: =IF((G18<>0),G18-H18," ") | M18: =IF(G18<>0,G18-L18," ") | N18: =IF((G18-L18)<>0,N$1-A18," ") | P18: =IF((F18="a"),I18," ") | Q18: =IF((F18="b"),I18," ") | R18: =IF((F18="c"),I18," ") | S18: =IF((F18="d"),I18," ") | T18: =IF((F18="g"),I18," ") | U18: =IF((F18="o"),I18," ") | V18: =IF((F18="FS"),I18," ")
H19: =IF(H$4>0,(IF(G19<>0,G19*H$4/100," ")),IF(G19<>0,G19*H$2/(100+H$2)," ")) | I19: =IF((G19<>0),G19-H19," ") | M19: =IF(G19<>0,G19-L19," ") | N19: =IF((G19-L19)<>0,N$1-A19," ") | P19: =IF((F19="a"),I19," ") | Q19: =IF((F19="b"),I19," ") | R19: =IF((F19="c"),I19," ") | S19: =IF((F19="d"),I19," ") | T19: =IF((F19="g"),I19," ") | U19: =IF((F19="o"),I19," ") | V19: =IF((F19="FS"),I19," ")
H20: =IF(H$4>0,(IF(G20<>0,G20*H$4/100," ")),IF(G20<>0,G20*H$2/(100+H$2)," ")) | I20: =IF((G20<>0),G20-H20," ") | M20: =IF(G20<>0,G20-L20," ") | N20: =IF((G20-L20)<>0,N$1-A20," ") | P20: =IF((F20="a"),I20," ") | Q20: =IF((F20="b"),I20," ") | R20: =IF((F20="c"),I20," ") | S20: =IF((F20="d"),I20," ") | T20: =IF((F20="g"),I20," ") | U20: =IF((F20="o"),I20," ") | V20: =IF((F20="FS"),I20," ")
H21: =IF(H$4>0,(IF(G21<>0,G21*H$4/100," ")),IF(G21<>0,G21*H$2/(100+H$2)," ")) | I21: =IF((G21<>0),G21-H21," ") | M21: =IF(G21<>0,G21-L21," ") | N21: =IF((G21-L21)<>0,N$1-A21," ") | P21: =IF((F21="a"),I21," ") | Q21: =IF((F21="b"),I21," ") | R21: =IF((F21="c"),I21," ") | S21: =IF((F21="d"),I21," ") | T21: =IF((F21="g"),I21," ") | U21: =IF((F21="o"),I21," ") | V21: =IF((F21="FS"),I21," ")
H22: =IF(H$4>0,(IF(G22<>0,G22*H$4/100," ")),IF(G22<>0,G22*H$2/(100+H$2)," ")) | I22: =IF((G22<>0),G22-H22," ") | M22: =IF(G22<>0,G22-L22," ") | N22: =IF((G22-L22)<>0,N$1-A22," ") | P22: =IF((F22="a"),I22," ") | Q22: =IF((F22="b"),I22," ") | R22: =IF((F22="c"),I22," ") | S22: =IF((F22="d"),I22," ") | T22: =IF((F22="g"),I22," ") | U22: =IF((F22="o"),I22," ") | V22: =IF((F22="FS"),I22," ")
H23: =IF(H$4>0,(IF(G23<>0,G23*H$4/100," ")),IF(G23<>0,G23*H$2/(100+H$2)," ")) | I23: =IF((G23<>0),G23-H23," ") | M23: =IF(G23<>0,G23-L23," ") | N23: =IF((G23-L23)<>0,N$1-A23," ") | P23: =IF((F23="a"),I23," ") | Q23: =IF((F23="b"),I23," ") | R23: =IF((F23="c"),I23," ") | S23: =IF((F23="d"),I23," ") | T23: =IF((F23="g"),I23," ") | U23: =IF((F23="o"),I23," ") | V23: =IF((F23="FS"),I23," ")
H24: =IF(H$4>0,(IF(G24<>0,G24*H$4/100," ")),IF(G24<>0,G24*H$2/(100+H$2)," ")) | I24: =IF((G24<>0),G24-H24," ") | M24: =IF(G24<>0,G24-L24," ") | N24: =IF((G24-L24)<>0,N$1-A24," ") | P24: =IF((F24="a"),I24," ") | Q24: =IF((F24="b"),I24," ") | R24: =IF((F24="c"),I24," ") | S24: =IF((F24="d"),I24," ") | T24: =IF((F24="g"),I24," ") | U24: =IF((F24="o"),I24," ") | V24: =IF((F24="FS"),I24," ")
H25: =IF(H$4>0,(IF(G25<>0,G25*H$4/100," ")),IF(G25<>0,G25*H$2/(100+H$2)," ")) | I25: =IF((G25<>0),G25-H25," ") | M25: =IF(G25<>0,G25-L25," ") | N25: =IF((G25-L25)<>0,N$1-A25," ") | P25: =IF((F25="a"),I25," ") | Q25: =IF((F25="b"),I25," ") | R25: =IF((F25="c"),I25," ") | S25: =IF((F25="d"),I25," ") | T25: =IF((F25="g"),I25," ") | U25: =IF((F25="o"),I25," ") | V25: =IF((F25="FS"),I25," ")
H26: =IF(H$4>0,(IF(G26<>0,G26*H$4/100," ")),IF(G26<>0,G26*H$2/(100+H$2)," ")) | I26: =IF((G26<>0),G26-H26," ") | M26: =IF(G26<>0,G26-L26," ") | N26: =IF((G26-L26)<>0,N$1-A26," ") | P26: =IF((F26="a"),I26," ") | Q26: =IF((F26="b"),I26," ") | R26: =IF((F26="c"),I26," ") | S26: =IF((F26="d"),I26," ") | T26: =IF((F26="g"),I26," ") | U26: =IF((F26="o"),I26," ") | V26: =IF((F26="FS"),I26," ")
H27: =IF(H$4>0,(IF(G27<>0,G27*H$4/100," ")),IF(G27<>0,G27*H$2/(100+H$2)," ")) | I27: =IF((G27<>0),G27-H27," ") | M27: =IF(G27<>0,G27-L27," ") | N27: =IF((G27-L27)<>0,N$1-A27," ") | P27: =IF((F27="a"),I27," ") | Q27: =IF((F27="b"),I27," ") | R27: =IF((F27="c"),I27," ") | S27: =IF((F27="d"),I27," ") | T27: =IF((F27="g"),I27," ") | U27: =IF((F27="o"),I27," ") | V27: =IF((F27="FS"),I27," ")
... H68: =IF(H$4>0,(IF(G68<>0,G68*H$4/100," ")),IF(G68<>0,G68*H$2/(100+H$2)," ")) | I68: =IF((G68<>0),G68-H68," ") | M68: =IF(G68<>0,G68-L68," ") | N68: =IF((G68-L68)<>0,N$1-A68," ") | P68: =IF((F68="a"),I68," ") | Q68: =IF((F68="b"),I68," ") | R68: =IF((F68="c"),I68," ") | S68: =IF((F68="d"),I68," ") | T68: =IF((F68="g"),I68," ") | U68: =IF((F68="o"),I68," ") | V68: =IF((F68="FS"),I68," ")
F69: =IF((G69<>0),"Enter Letter"," ") | H69: =IF(H$4>0,(IF(G69<>0,G69*H$4/100," ")),IF(G69<>0,G69*H$2/(100+H$2)," ")) | I69: =IF((G69<>0),G69-H69," ") | M69: =IF(G69<>0,G69-L69," ") | N69: =IF((G69-L69)<>0,N$1-A69," ") | P69: =IF((F69="a"),I69," ") | Q69: =IF((F69="b"),I69," ") | R69: =IF((F69="c"),I69," ") | S69: =IF((F69="d"),I69," ") | T69: =IF((F69="g"),I69," ") | U69: =IF((F69="o"),I69," ") | V69: =IF((F69="FS"),I69," ")
F70: =IF((G70<>0),"Enter Letter"," ") | H70: =IF(H$4>0,(IF(G70<>0,G70*H$4/100," ")),IF(G70<>0,G70*H$2/(100+H$2)," ")) | I70: =IF((G70<>0),G70-H70," ") | M70: =IF(G70<>0,G70-L70," ") | N70: =IF((G70-L70)<>0,N$1-A70," ") | P70: =IF((F70="a"),I70," ") | Q70: =IF((F70="b"),I70," ") | R70: =IF((F70="c"),I70," ") | S70: =IF((F70="d"),I70," ") | T70: =IF((F70="g"),I70," ") | U70: =IF((F70="o"),I70," ") | V70: =IF((F70="FS"),I70," ")
F71: =IF((G71<>0),"Enter Letter"," ") | H71: =IF(H$4>0,(IF(G71<>0,G71*H$4/100," ")),IF(G71<>0,G71*H$2/(100+H$2)," ")) | I71: =IF((G71<>0),G71-H71," ") | M71: =IF(G71<>0,G71-L71," ") | N71: =IF((G71-L71)<>0,N$1-A71," ") | P71: =IF((F71="a"),I71," ") | Q71: =IF((F71="b"),I71," ") | R71: =IF((F71="c"),I71," ") | S71: =IF((F71="d"),I71," ") | T71: =IF((F71="g"),I71," ") | U71: =IF((F71="o"),I71," ") | V71: =IF((F71="FS"),I71," ")
F72: =IF((G72<>0),"Enter Letter"," ") | H72: =IF(H$4>0,(IF(G72<>0,G72*H$4/100," ")),IF(G72<>0,G72*H$2/(100+H$2)," ")) | I72: =IF((G72<>0),G72-H72," ") | M72: =IF(G72<>0,G72-L72," ") | N72: =IF((G72-L72)<>0,N$1-A72," ") | P72: =IF((F72="a"),I72," ") | Q72: =IF((F72="b"),I72," ") | R72: =IF((F72="c"),I72," ") | S72: =IF((F72="d"),I72," ") | T72: =IF((F72="g"),I72," ") | U72: =IF((F72="o"),I72," ") | V72: =IF((F72="FS"),I72," ")
F73: =IF((G73<>0),"Enter Letter"," ") | H73: =IF(H$4>0,(IF(G73<>0,G73*H$4/100," ")),IF(G73<>0,G73*H$2/(100+H$2)," ")) | I73: =IF((G73<>0),G73-H73," ") | M73: =IF(G73<>0,G73-L73," ") | N73: =IF((G73-L73)<>0,N$1-A73," ") | P73: =IF((F73="a"),I73," ") | Q73: =IF((F73="b"),I73," ") | R73: =IF((F73="c"),I73," ") | S73: =IF((F73="d"),I73," ") | T73: =IF((F73="g"),I73," ") | U73: =IF((F73="o"),I73," ") | V73: =IF((F73="FS"),I73," ")
F74: =IF((G74<>0),"Enter Letter"," ") | H74: =IF(H$4>0,(IF(G74<>0,G74*H$4/100," ")),IF(G74<>0,G74*H$2/(100+H$2)," ")) | I74: =IF((G74<>0),G74-H74," ") | M74: =IF(G74<>0,G74-L74," ") | N74: =IF((G74-L74)<>0,N$1-A74," ") | P74: =IF((F74="a"),I74," ") | Q74: =IF((F74="b"),I74," ") | R74: =IF((F74="c"),I74," ") | S74: =IF((F74="d"),I74," ") | T74: =IF((F74="g"),I74," ") | U74: =IF((F74="o"),I74," ") | V74: =IF((F74="FS"),I74," ")
F75: =IF((G75<>0),"Enter Letter"," ") | H75: =IF(H$4>0,(IF(G75<>0,G75*H$4/100," ")),IF(G75<>0,G75*H$2/(100+H$2)," ")) | I75: =IF((G75<>0),G75-H75," ") | M75: =IF(G75<>0,G75-L75," ") | N75: =IF((G75-L75)<>0,N$1-A75," ") | P75: =IF((F75="a"),I75," ") | Q75: =IF((F75="b"),I75," ") | R75: =IF((F75="c"),I75," ") | S75: =IF((F75="d"),I75," ") | T75: =IF((F75="g"),I75," ") | U75: =IF((F75="o"),I75," ") | V75: =IF((F75="FS"),I75," ")
F76: =IF((G76<>0),"Enter Letter"," ") | H76: =IF(H$4>0,(IF(G76<>0,G76*H$4/100," ")),IF(G76<>0,G76*H$2/(100+H$2)," ")) | I76: =IF((G76<>0),G76-H76," ") | M76: =IF(G76<>0,G76-L76," ") | N76: =IF((G76-L76)<>0,N$1-A76," ") | P76: =IF((F76="a"),I76," ") | Q76: =IF((F76="b"),I76," ") | R76: =IF((F76="c"),I76," ") | S76: =IF((F76="d"),I76," ") | T76: =IF((F76="g"),I76," ") | U76: =IF((F76="o"),I76," ") | V76: =IF((F76="FS"),I76," ")
F77: =IF((G77<>0),"Enter Letter"," ") | H77: =IF(H$4>0,(IF(G77<>0,G77*H$4/100," ")),IF(G77<>0,G77*H$2/(100+H$2)," ")) | I77: =IF((G77<>0),G77-H77," ") | M77: =IF(G77<>0,G77-L77," ") | N77: =IF((G77-L77)<>0,N$1-A77," ") | P77: =IF((F77="a"),I77," ") | Q77: =IF((F77="b"),I77," ") | R77: =IF((F77="c"),I77," ") | S77: =IF((F77="d"),I77," ") | T77: =IF((F77="g"),I77," ") | U77: =IF((F77="o"),I77," ") | V77: =IF((F77="FS"),I77," ")
F78: =IF((G78<>0),"Enter Letter"," ") | H78: =IF(H$4>0,(IF(G78<>0,G78*H$4/100," ")),IF(G78<>0,G78*H$2/(100+H$2)," ")) | I78: =IF((G78<>0),G78-H78," ") | M78: =IF(G78<>0,G78-L78," ") | N78: =IF((G78-L78)<>0,N$1-A78," ") | P78: =IF((F78="a"),I78," ") | Q78: =IF((F78="b"),I78," ") | R78: =IF((F78="c"),I78," ") | S78: =IF((F78="d"),I78," ") | T78: =IF((F78="g"),I78," ") | U78: =IF((F78="o"),I78," ") | V78: =IF((F78="FS"),I78," ")
F79: =IF((G79<>0),"Enter Letter"," ") | H79: =IF(H$4>0,(IF(G79<>0,G79*H$4/100," ")),IF(G79<>0,G79*H$2/(100+H$2)," ")) | I79: =IF((G79<>0),G79-H79," ") | M79: =IF(G79<>0,G79-L79," ") | N79: =IF((G79-L79)<>0,N$1-A79," ") | P79: =IF((F79="a"),I79," ") | Q79: =IF((F79="b"),I79," ") | R79: =IF((F79="c"),I79," ") | S79: =IF((F79="d"),I79," ") | T79: =IF((F79="g"),I79," ") | U79: =IF((F79="o"),I79," ") | V79: =IF((F79="FS"),I79," ")
F80: =IF((G80<>0),"Enter Letter"," ") | H80: =IF(H$4>0,(IF(G80<>0,G80*H$4/100," ")),IF(G80<>0,G80*H$2/(100+H$2)," ")) | I80: =IF((G80<>0),G80-H80," ") | M80: =IF(G80<>0,G80-L80," ") | N80: =IF((G80-L80)<>0,N$1-A80," ") | P80: =IF((F80="a"),I80," ") | Q80: =IF((F80="b"),I80," ") | R80: =IF((F80="c"),I80," ") | S80: =IF((F80="d"),I80," ") | T80: =IF((F80="g"),I80," ") | U80: =IF((F80="o"),I80," ") | V80: =IF((F80="FS"),I80," ")
... F300: =IF((G300<>0),"Enter Letter"," ") | H300: =IF(H$4>0,(IF(G300<>0,G300*H$4/100," ")),IF(G300<>0,G300*H$2/(100+H$2)," ")) | I300: =IF((G300<>0),G300-H300," ") | M300: =IF(G300<>0,G300-L300," ") | N300: =IF((G300-L300)<>0,N$1-A300," ") | P300: =IF((F300="a"),I300," ") | Q300: =IF((F300="b"),I300," ") | R300: =IF((F300="c"),I300," ") | S300: =IF((F300="d"),I300," ") | T300: =IF((F300="g"),I300," ") | U300: =IF((F300="o"),I300," ") | V300: =IF((F300="FS"),I300," ")

Sheet Nov
A1: =G1-H1-SUM(P1:V1) -> 0 | B1: Check Total | C1: Sales Mileage | D1: =SUM(D5:D300) -> 0 | E1: Sales Description | F1: Enter Expense Code Letter | G1: =SUM(G5:G300) -> 35320 | H1: =SUM(H5:H300) -> 5886.6667 | I1: =SUM(I5:I300) -> 29433.333 | K1: For your information only. Enter How Paid e.g. Cash, Cheque etc., | L1: =SUM(L5:L300) -> 0 | M1: =SUM(M5:M300) -> 35320 | N1: =TODAY() -> 46295 | P1: =SUM(P5:P300) -> 25633.333 | Q1: =SUM(Q5:Q300) -> 800 | R1: =SUM(R5:R300) -> 3000 | S1: =SUM(S5:S300) -> 0 | T1: =SUM(T5:T300) -> 0 | U1: =SUM(U5:U300) -> 0 | V1: =SUM(V5:V300) -> 0 | W1: =SUM(W5:W300) -> 0 | X1: =W1+Oct!X1 -> 0
A2: Sales Date | B2: Customer Name | C2: Sales Invoice Number or reference | D2: Sales Mileage | G2: Sales Value including Vat | H2: =Oct!H2 -> 20 | I2: Sales Net of Vat | L2: Receipts from Customers | P2: Sales Net of Vat | S2: Other Income | T2: Investment Grants | U2: Bad Debts written off | V2: =V1+Oct!V2 -> 12500 | W2: Sub contractors only
H3: Vat Output | L3: Actual amount received | M3: Sales Value not yet received | N3: Number of Days Outstanding | P3: Product A | Q3: Product B | R3: Product C | V3: Sale of Fixed Assets | W3: CIS Tax Deducted | X3: CIS Certificate reference
H4: =Oct!H4 -> 0 | P4: A | Q4: B | R4: C | S4: D | T4: G | U4: O | V4: FS
A5: 46329 | B5: FreshField Ltd | C5: INV-2608 | E5: Software monitoring licence | F5: b | G5: 360 | H5: =IF(H$4>0,(IF(G5<>0,G5*H$4/100," ")),IF(G5<>0,G5*H$2/(100+H$2)," ")) -> 60 | I5: =IF((G5<>0),G5-H5," ") -> 300 | M5: =IF(G5<>0,G5-L5," ") -> 360 | N5: =IF((G5-L5)<>0,N$1-A5," ") -> -34 | P5: =IF((F5="a"),I5," ") | Q5: =IF((F5="b"),I5," ") -> 300 | R5: =IF((F5="c"),I5," ") | S5: =IF((F5="d"),I5," ") | T5: =IF((F5="g"),I5," ") | U5: =IF((F5="o"),I5," ") | V5: =IF((F5="FS"),I5," ") | BZ5: 4001
A6: 46331 | B6: CloudNine Ltd | C6: INV-1408 | E6: SaaS licence fee | F6: b | G6: 600 | H6: =IF(H$4>0,(IF(G6<>0,G6*H$4/100," ")),IF(G6<>0,G6*H$2/(100+H$2)," ")) -> 100 | I6: =IF((G6<>0),G6-H6," ") -> 500 | M6: =IF(G6<>0,G6-L6," ") -> 600 | N6: =IF((G6-L6)<>0,N$1-A6," ") -> -36 | P6: =IF((F6="a"),I6," ") | Q6: =IF((F6="b"),I6," ") -> 500 | R6: =IF((F6="c"),I6," ") | S6: =IF((F6="d"),I6," ") | T6: =IF((F6="g"),I6," ") | U6: =IF((F6="o"),I6," ") | V6: =IF((F6="FS"),I6," ") | BZ6: 4001
A7: 46334 | B7: Cedar Systems | C7: INV-2408 | E7: Managed services | F7: a | G7: 480 | H7: =IF(H$4>0,(IF(G7<>0,G7*H$4/100," ")),IF(G7<>0,G7*H$2/(100+H$2)," ")) -> 80 | I7: =IF((G7<>0),G7-H7," ") -> 400 | M7: =IF(G7<>0,G7-L7," ") -> 480 | N7: =IF((G7-L7)<>0,N$1-A7," ") -> -39 | P7: =IF((F7="a"),I7," ") -> 400 | Q7: =IF((F7="b"),I7," ") | R7: =IF((F7="c"),I7," ") | S7: =IF((F7="d"),I7," ") | T7: =IF((F7="g"),I7," ") | U7: =IF((F7="o"),I7," ") | V7: =IF((F7="FS"),I7," ") | BZ7: 4000
A8: 46336 | B8: Pinnacle Group | C8: INV-2208 | E8: Monthly support contract | F8: a | G8: 720 | H8: =IF(H$4>0,(IF(G8<>0,G8*H$4/100," ")),IF(G8<>0,G8*H$2/(100+H$2)," ")) -> 120 | I8: =IF((G8<>0),G8-H8," ") -> 600 | M8: =IF(G8<>0,G8-L8," ") -> 720 | N8: =IF((G8-L8)<>0,N$1-A8," ") -> -41 | P8: =IF((F8="a"),I8," ") -> 600 | Q8: =IF((F8="b"),I8," ") | R8: =IF((F8="c"),I8," ") | S8: =IF((F8="d"),I8," ") | T8: =IF((F8="g"),I8," ") | U8: =IF((F8="o"),I8," ") | V8: =IF((F8="FS"),I8," ") | BZ8: 4000
A9: 46338 | B9: QuickFix IT | C9: INV-2003 | E9: IT support consultancy | F9: a | G9: 960 | H9: =IF(H$4>0,(IF(G9<>0,G9*H$4/100," ")),IF(G9<>0,G9*H$2/(100+H$2)," ")) -> 160 | I9: =IF((G9<>0),G9-H9," ") -> 800 | M9: =IF(G9<>0,G9-L9," ") -> 960 | N9: =IF((G9-L9)<>0,N$1-A9," ") -> -43 | P9: =IF((F9="a"),I9," ") -> 800 | Q9: =IF((F9="b"),I9," ") | R9: =IF((F9="c"),I9," ") | S9: =IF((F9="d"),I9," ") | T9: =IF((F9="g"),I9," ") | U9: =IF((F9="o"),I9," ") | V9: =IF((F9="FS"),I9," ") | BZ9: 4000
A10: 46341 | B10: Acme Corp | C10: INV-1008 | E10: IT consultancy services | F10: a | G10: 25000 | H10: =IF(H$4>0,(IF(G10<>0,G10*H$4/100," ")),IF(G10<>0,G10*H$2/(100+H$2)," ")) -> 4166.6667 | I10: =IF((G10<>0),G10-H10," ") -> 20833.333 | M10: =IF(G10<>0,G10-L10," ") -> 25000 | N10: =IF((G10-L10)<>0,N$1-A10," ") -> -46 | P10: =IF((F10="a"),I10," ") -> 20833.333 | Q10: =IF((F10="b"),I10," ") | R10: =IF((F10="c"),I10," ") | S10: =IF((F10="d"),I10," ") | T10: =IF((F10="g"),I10," ") | U10: =IF((F10="o"),I10," ") | V10: =IF((F10="FS"),I10," ") | BZ10: 4000
A11: 46344 | B11: TechStart Ltd | C11: INV-1108 | E11: IT consultancy retainer | F11: a | G11: 2400 | H11: =IF(H$4>0,(IF(G11<>0,G11*H$4/100," ")),IF(G11<>0,G11*H$2/(100+H$2)," ")) -> 400 | I11: =IF((G11<>0),G11-H11," ") -> 2000 | M11: =IF(G11<>0,G11-L11," ") -> 2400 | N11: =IF((G11-L11)<>0,N$1-A11," ") -> -49 | P11: =IF((F11="a"),I11," ") -> 2000 | Q11: =IF((F11="b"),I11," ") | R11: =IF((F11="c"),I11," ") | S11: =IF((F11="d"),I11," ") | T11: =IF((F11="g"),I11," ") | U11: =IF((F11="o"),I11," ") | V11: =IF((F11="FS"),I11," ") | BZ11: 4000
A12: 46346 | B12: Delta PLC | C12: INV-1502 | E12: Cloud architecture workshop | F12: c | G12: 3600 | H12: =IF(H$4>0,(IF(G12<>0,G12*H$4/100," ")),IF(G12<>0,G12*H$2/(100+H$2)," ")) -> 600 | I12: =IF((G12<>0),G12-H12," ") -> 3000 | M12: =IF(G12<>0,G12-L12," ") -> 3600 | N12: =IF((G12-L12)<>0,N$1-A12," ") -> -51 | P12: =IF((F12="a"),I12," ") | Q12: =IF((F12="b"),I12," ") | R12: =IF((F12="c"),I12," ") -> 3000 | S12: =IF((F12="d"),I12," ") | T12: =IF((F12="g"),I12," ") | U12: =IF((F12="o"),I12," ") | V12: =IF((F12="FS"),I12," ") | BZ12: 4002
A13: 46351 | B13: Oakridge Partners | C13: INV-2503 | E13: Quarterly consulting engagement | F13: a | G13: 1200 | H13: =IF(H$4>0,(IF(G13<>0,G13*H$4/100," ")),IF(G13<>0,G13*H$2/(100+H$2)," ")) -> 200 | I13: =IF((G13<>0),G13-H13," ") -> 1000 | M13: =IF(G13<>0,G13-L13," ") -> 1200 | N13: =IF((G13-L13)<>0,N$1-A13," ") -> -56 | P13: =IF((F13="a"),I13," ") -> 1000 | Q13: =IF((F13="b"),I13," ") | R13: =IF((F13="c"),I13," ") | S13: =IF((F13="d"),I13," ") | T13: =IF((F13="g"),I13," ") | U13: =IF((F13="o"),I13," ") | V13: =IF((F13="FS"),I13," ") | BZ13: 4000
H14: =IF(H$4>0,(IF(G14<>0,G14*H$4/100," ")),IF(G14<>0,G14*H$2/(100+H$2)," ")) | I14: =IF((G14<>0),G14-H14," ") | M14: =IF(G14<>0,G14-L14," ") | N14: =IF((G14-L14)<>0,N$1-A14," ") | P14: =IF((F14="a"),I14," ") | Q14: =IF((F14="b"),I14," ") | R14: =IF((F14="c"),I14," ") | S14: =IF((F14="d"),I14," ") | T14: =IF((F14="g"),I14," ") | U14: =IF((F14="o"),I14," ") | V14: =IF((F14="FS"),I14," ")
H15: =IF(H$4>0,(IF(G15<>0,G15*H$4/100," ")),IF(G15<>0,G15*H$2/(100+H$2)," ")) | I15: =IF((G15<>0),G15-H15," ") | M15: =IF(G15<>0,G15-L15," ") | N15: =IF((G15-L15)<>0,N$1-A15," ") | P15: =IF((F15="a"),I15," ") | Q15: =IF((F15="b"),I15," ") | R15: =IF((F15="c"),I15," ") | S15: =IF((F15="d"),I15," ") | T15: =IF((F15="g"),I15," ") | U15: =IF((F15="o"),I15," ") | V15: =IF((F15="FS"),I15," ")
H16: =IF(H$4>0,(IF(G16<>0,G16*H$4/100," ")),IF(G16<>0,G16*H$2/(100+H$2)," ")) | I16: =IF((G16<>0),G16-H16," ") | M16: =IF(G16<>0,G16-L16," ") | N16: =IF((G16-L16)<>0,N$1-A16," ") | P16: =IF((F16="a"),I16," ") | Q16: =IF((F16="b"),I16," ") | R16: =IF((F16="c"),I16," ") | S16: =IF((F16="d"),I16," ") | T16: =IF((F16="g"),I16," ") | U16: =IF((F16="o"),I16," ") | V16: =IF((F16="FS"),I16," ")
H17: =IF(H$4>0,(IF(G17<>0,G17*H$4/100," ")),IF(G17<>0,G17*H$2/(100+H$2)," ")) | I17: =IF((G17<>0),G17-H17," ") | M17: =IF(G17<>0,G17-L17," ") | N17: =IF((G17-L17)<>0,N$1-A17," ") | P17: =IF((F17="a"),I17," ") | Q17: =IF((F17="b"),I17," ") | R17: =IF((F17="c"),I17," ") | S17: =IF((F17="d"),I17," ") | T17: =IF((F17="g"),I17," ") | U17: =IF((F17="o"),I17," ") | V17: =IF((F17="FS"),I17," ")
H18: =IF(H$4>0,(IF(G18<>0,G18*H$4/100," ")),IF(G18<>0,G18*H$2/(100+H$2)," ")) | I18: =IF((G18<>0),G18-H18," ") | M18: =IF(G18<>0,G18-L18," ") | N18: =IF((G18-L18)<>0,N$1-A18," ") | P18: =IF((F18="a"),I18," ") | Q18: =IF((F18="b"),I18," ") | R18: =IF((F18="c"),I18," ") | S18: =IF((F18="d"),I18," ") | T18: =IF((F18="g"),I18," ") | U18: =IF((F18="o"),I18," ") | V18: =IF((F18="FS"),I18," ")
H19: =IF(H$4>0,(IF(G19<>0,G19*H$4/100," ")),IF(G19<>0,G19*H$2/(100+H$2)," ")) | I19: =IF((G19<>0),G19-H19," ") | M19: =IF(G19<>0,G19-L19," ") | N19: =IF((G19-L19)<>0,N$1-A19," ") | P19: =IF((F19="a"),I19," ") | Q19: =IF((F19="b"),I19," ") | R19: =IF((F19="c"),I19," ") | S19: =IF((F19="d"),I19," ") | T19: =IF((F19="g"),I19," ") | U19: =IF((F19="o"),I19," ") | V19: =IF((F19="FS"),I19," ")
H20: =IF(H$4>0,(IF(G20<>0,G20*H$4/100," ")),IF(G20<>0,G20*H$2/(100+H$2)," ")) | I20: =IF((G20<>0),G20-H20," ") | M20: =IF(G20<>0,G20-L20," ") | N20: =IF((G20-L20)<>0,N$1-A20," ") | P20: =IF((F20="a"),I20," ") | Q20: =IF((F20="b"),I20," ") | R20: =IF((F20="c"),I20," ") | S20: =IF((F20="d"),I20," ") | T20: =IF((F20="g"),I20," ") | U20: =IF((F20="o"),I20," ") | V20: =IF((F20="FS"),I20," ")
H21: =IF(H$4>0,(IF(G21<>0,G21*H$4/100," ")),IF(G21<>0,G21*H$2/(100+H$2)," ")) | I21: =IF((G21<>0),G21-H21," ") | M21: =IF(G21<>0,G21-L21," ") | N21: =IF((G21-L21)<>0,N$1-A21," ") | P21: =IF((F21="a"),I21," ") | Q21: =IF((F21="b"),I21," ") | R21: =IF((F21="c"),I21," ") | S21: =IF((F21="d"),I21," ") | T21: =IF((F21="g"),I21," ") | U21: =IF((F21="o"),I21," ") | V21: =IF((F21="FS"),I21," ")
H22: =IF(H$4>0,(IF(G22<>0,G22*H$4/100," ")),IF(G22<>0,G22*H$2/(100+H$2)," ")) | I22: =IF((G22<>0),G22-H22," ") | M22: =IF(G22<>0,G22-L22," ") | N22: =IF((G22-L22)<>0,N$1-A22," ") | P22: =IF((F22="a"),I22," ") | Q22: =IF((F22="b"),I22," ") | R22: =IF((F22="c"),I22," ") | S22: =IF((F22="d"),I22," ") | T22: =IF((F22="g"),I22," ") | U22: =IF((F22="o"),I22," ") | V22: =IF((F22="FS"),I22," ")
H23: =IF(H$4>0,(IF(G23<>0,G23*H$4/100," ")),IF(G23<>0,G23*H$2/(100+H$2)," ")) | I23: =IF((G23<>0),G23-H23," ") | M23: =IF(G23<>0,G23-L23," ") | N23: =IF((G23-L23)<>0,N$1-A23," ") | P23: =IF((F23="a"),I23," ") | Q23: =IF((F23="b"),I23," ") | R23: =IF((F23="c"),I23," ") | S23: =IF((F23="d"),I23," ") | T23: =IF((F23="g"),I23," ") | U23: =IF((F23="o"),I23," ") | V23: =IF((F23="FS"),I23," ")
H24: =IF(H$4>0,(IF(G24<>0,G24*H$4/100," ")),IF(G24<>0,G24*H$2/(100+H$2)," ")) | I24: =IF((G24<>0),G24-H24," ") | M24: =IF(G24<>0,G24-L24," ") | N24: =IF((G24-L24)<>0,N$1-A24," ") | P24: =IF((F24="a"),I24," ") | Q24: =IF((F24="b"),I24," ") | R24: =IF((F24="c"),I24," ") | S24: =IF((F24="d"),I24," ") | T24: =IF((F24="g"),I24," ") | U24: =IF((F24="o"),I24," ") | V24: =IF((F24="FS"),I24," ")
H25: =IF(H$4>0,(IF(G25<>0,G25*H$4/100," ")),IF(G25<>0,G25*H$2/(100+H$2)," ")) | I25: =IF((G25<>0),G25-H25," ") | M25: =IF(G25<>0,G25-L25," ") | N25: =IF((G25-L25)<>0,N$1-A25," ") | P25: =IF((F25="a"),I25," ") | Q25: =IF((F25="b"),I25," ") | R25: =IF((F25="c"),I25," ") | S25: =IF((F25="d"),I25," ") | T25: =IF((F25="g"),I25," ") | U25: =IF((F25="o"),I25," ") | V25: =IF((F25="FS"),I25," ")
... H68: =IF(H$4>0,(IF(G68<>0,G68*H$4/100," ")),IF(G68<>0,G68*H$2/(100+H$2)," ")) | I68: =IF((G68<>0),G68-H68," ") | M68: =IF(G68<>0,G68-L68," ") | N68: =IF((G68-L68)<>0,N$1-A68," ") | P68: =IF((F68="a"),I68," ") | Q68: =IF((F68="b"),I68," ") | R68: =IF((F68="c"),I68," ") | S68: =IF((F68="d"),I68," ") | T68: =IF((F68="g"),I68," ") | U68: =IF((F68="o"),I68," ") | V68: =IF((F68="FS"),I68," ")
F69: =IF((G69<>0),"Enter Letter"," ") | H69: =IF(H$4>0,(IF(G69<>0,G69*H$4/100," ")),IF(G69<>0,G69*H$2/(100+H$2)," ")) | I69: =IF((G69<>0),G69-H69," ") | M69: =IF(G69<>0,G69-L69," ") | N69: =IF((G69-L69)<>0,N$1-A69," ") | P69: =IF((F69="a"),I69," ") | Q69: =IF((F69="b"),I69," ") | R69: =IF((F69="c"),I69," ") | S69: =IF((F69="d"),I69," ") | T69: =IF((F69="g"),I69," ") | U69: =IF((F69="o"),I69," ") | V69: =IF((F69="FS"),I69," ")
F70: =IF((G70<>0),"Enter Letter"," ") | H70: =IF(H$4>0,(IF(G70<>0,G70*H$4/100," ")),IF(G70<>0,G70*H$2/(100+H$2)," ")) | I70: =IF((G70<>0),G70-H70," ") | M70: =IF(G70<>0,G70-L70," ") | N70: =IF((G70-L70)<>0,N$1-A70," ") | P70: =IF((F70="a"),I70," ") | Q70: =IF((F70="b"),I70," ") | R70: =IF((F70="c"),I70," ") | S70: =IF((F70="d"),I70," ") | T70: =IF((F70="g"),I70," ") | U70: =IF((F70="o"),I70," ") | V70: =IF((F70="FS"),I70," ")
F71: =IF((G71<>0),"Enter Letter"," ") | H71: =IF(H$4>0,(IF(G71<>0,G71*H$4/100," ")),IF(G71<>0,G71*H$2/(100+H$2)," ")) | I71: =IF((G71<>0),G71-H71," ") | M71: =IF(G71<>0,G71-L71," ") | N71: =IF((G71-L71)<>0,N$1-A71," ") | P71: =IF((F71="a"),I71," ") | Q71: =IF((F71="b"),I71," ") | R71: =IF((F71="c"),I71," ") | S71: =IF((F71="d"),I71," ") | T71: =IF((F71="g"),I71," ") | U71: =IF((F71="o"),I71," ") | V71: =IF((F71="FS"),I71," ")
F72: =IF((G72<>0),"Enter Letter"," ") | H72: =IF(H$4>0,(IF(G72<>0,G72*H$4/100," ")),IF(G72<>0,G72*H$2/(100+H$2)," ")) | I72: =IF((G72<>0),G72-H72," ") | M72: =IF(G72<>0,G72-L72," ") | N72: =IF((G72-L72)<>0,N$1-A72," ") | P72: =IF((F72="a"),I72," ") | Q72: =IF((F72="b"),I72," ") | R72: =IF((F72="c"),I72," ") | S72: =IF((F72="d"),I72," ") | T72: =IF((F72="g"),I72," ") | U72: =IF((F72="o"),I72," ") | V72: =IF((F72="FS"),I72," ")
F73: =IF((G73<>0),"Enter Letter"," ") | H73: =IF(H$4>0,(IF(G73<>0,G73*H$4/100," ")),IF(G73<>0,G73*H$2/(100+H$2)," ")) | I73: =IF((G73<>0),G73-H73," ") | M73: =IF(G73<>0,G73-L73," ") | N73: =IF((G73-L73)<>0,N$1-A73," ") | P73: =IF((F73="a"),I73," ") | Q73: =IF((F73="b"),I73," ") | R73: =IF((F73="c"),I73," ") | S73: =IF((F73="d"),I73," ") | T73: =IF((F73="g"),I73," ") | U73: =IF((F73="o"),I73," ") | V73: =IF((F73="FS"),I73," ")
F74: =IF((G74<>0),"Enter Letter"," ") | H74: =IF(H$4>0,(IF(G74<>0,G74*H$4/100," ")),IF(G74<>0,G74*H$2/(100+H$2)," ")) | I74: =IF((G74<>0),G74-H74," ") | M74: =IF(G74<>0,G74-L74," ") | N74: =IF((G74-L74)<>0,N$1-A74," ") | P74: =IF((F74="a"),I74," ") | Q74: =IF((F74="b"),I74," ") | R74: =IF((F74="c"),I74," ") | S74: =IF((F74="d"),I74," ") | T74: =IF((F74="g"),I74," ") | U74: =IF((F74="o"),I74," ") | V74: =IF((F74="FS"),I74," ")
F75: =IF((G75<>0),"Enter Letter"," ") | H75: =IF(H$4>0,(IF(G75<>0,G75*H$4/100," ")),IF(G75<>0,G75*H$2/(100+H$2)," ")) | I75: =IF((G75<>0),G75-H75," ") | M75: =IF(G75<>0,G75-L75," ") | N75: =IF((G75-L75)<>0,N$1-A75," ") | P75: =IF((F75="a"),I75," ") | Q75: =IF((F75="b"),I75," ") | R75: =IF((F75="c"),I75," ") | S75: =IF((F75="d"),I75," ") | T75: =IF((F75="g"),I75," ") | U75: =IF((F75="o"),I75," ") | V75: =IF((F75="FS"),I75," ")
F76: =IF((G76<>0),"Enter Letter"," ") | H76: =IF(H$4>0,(IF(G76<>0,G76*H$4/100," ")),IF(G76<>0,G76*H$2/(100+H$2)," ")) | I76: =IF((G76<>0),G76-H76," ") | M76: =IF(G76<>0,G76-L76," ") | N76: =IF((G76-L76)<>0,N$1-A76," ") | P76: =IF((F76="a"),I76," ") | Q76: =IF((F76="b"),I76," ") | R76: =IF((F76="c"),I76," ") | S76: =IF((F76="d"),I76," ") | T76: =IF((F76="g"),I76," ") | U76: =IF((F76="o"),I76," ") | V76: =IF((F76="FS"),I76," ")
F77: =IF((G77<>0),"Enter Letter"," ") | H77: =IF(H$4>0,(IF(G77<>0,G77*H$4/100," ")),IF(G77<>0,G77*H$2/(100+H$2)," ")) | I77: =IF((G77<>0),G77-H77," ") | M77: =IF(G77<>0,G77-L77," ") | N77: =IF((G77-L77)<>0,N$1-A77," ") | P77: =IF((F77="a"),I77," ") | Q77: =IF((F77="b"),I77," ") | R77: =IF((F77="c"),I77," ") | S77: =IF((F77="d"),I77," ") | T77: =IF((F77="g"),I77," ") | U77: =IF((F77="o"),I77," ") | V77: =IF((F77="FS"),I77," ")
F78: =IF((G78<>0),"Enter Letter"," ") | H78: =IF(H$4>0,(IF(G78<>0,G78*H$4/100," ")),IF(G78<>0,G78*H$2/(100+H$2)," ")) | I78: =IF((G78<>0),G78-H78," ") | M78: =IF(G78<>0,G78-L78," ") | N78: =IF((G78-L78)<>0,N$1-A78," ") | P78: =IF((F78="a"),I78," ") | Q78: =IF((F78="b"),I78," ") | R78: =IF((F78="c"),I78," ") | S78: =IF((F78="d"),I78," ") | T78: =IF((F78="g"),I78," ") | U78: =IF((F78="o"),I78," ") | V78: =IF((F78="FS"),I78," ")
F79: =IF((G79<>0),"Enter Letter"," ") | H79: =IF(H$4>0,(IF(G79<>0,G79*H$4/100," ")),IF(G79<>0,G79*H$2/(100+H$2)," ")) | I79: =IF((G79<>0),G79-H79," ") | M79: =IF(G79<>0,G79-L79," ") | N79: =IF((G79-L79)<>0,N$1-A79," ") | P79: =IF((F79="a"),I79," ") | Q79: =IF((F79="b"),I79," ") | R79: =IF((F79="c"),I79," ") | S79: =IF((F79="d"),I79," ") | T79: =IF((F79="g"),I79," ") | U79: =IF((F79="o"),I79," ") | V79: =IF((F79="FS"),I79," ")
F80: =IF((G80<>0),"Enter Letter"," ") | H80: =IF(H$4>0,(IF(G80<>0,G80*H$4/100," ")),IF(G80<>0,G80*H$2/(100+H$2)," ")) | I80: =IF((G80<>0),G80-H80," ") | M80: =IF(G80<>0,G80-L80," ") | N80: =IF((G80-L80)<>0,N$1-A80," ") | P80: =IF((F80="a"),I80," ") | Q80: =IF((F80="b"),I80," ") | R80: =IF((F80="c"),I80," ") | S80: =IF((F80="d"),I80," ") | T80: =IF((F80="g"),I80," ") | U80: =IF((F80="o"),I80," ") | V80: =IF((F80="FS"),I80," ")
... F300: =IF((G300<>0),"Enter Letter"," ") | H300: =IF(H$4>0,(IF(G300<>0,G300*H$4/100," ")),IF(G300<>0,G300*H$2/(100+H$2)," ")) | I300: =IF((G300<>0),G300-H300," ") | M300: =IF(G300<>0,G300-L300," ") | N300: =IF((G300-L300)<>0,N$1-A300," ") | P300: =IF((F300="a"),I300," ") | Q300: =IF((F300="b"),I300," ") | R300: =IF((F300="c"),I300," ") | S300: =IF((F300="d"),I300," ") | T300: =IF((F300="g"),I300," ") | U300: =IF((F300="o"),I300," ") | V300: =IF((F300="FS"),I300," ")

Sheet Dec
A1: =G1-H1-SUM(P1:V1) -> 0 | B1: Check Total | C1: Sales Mileage | D1: =SUM(D5:D300) -> 0 | E1: Sales Description | F1: Enter Expense Code Letter | G1: =SUM(G5:G300) -> 32800 | H1: =SUM(H5:H300) -> 5466.6667 | I1: =SUM(I5:I300) -> 27333.333 | K1: For your information only. Enter How Paid e.g. Cash, Cheque etc., | L1: =SUM(L5:L300) -> 0 | M1: =SUM(M5:M300) -> 32800 | N1: =TODAY() -> 46295 | P1: =SUM(P5:P300) -> 26533.333 | Q1: =SUM(Q5:Q300) -> 800 | R1: =SUM(R5:R300) -> 0 | S1: =SUM(S5:S300) -> 0 | T1: =SUM(T5:T300) -> 0 | U1: =SUM(U5:U300) -> 0 | V1: =SUM(V5:V300) -> 0 | W1: =SUM(W5:W300) -> 0 | X1: =W1+Nov!X1 -> 0
A2: Sales Date | B2: Customer Name | C2: Sales Invoice Number or reference | D2: Sales Mileage | G2: Sales Value including Vat | H2: =Nov!H2 -> 20 | I2: Sales Net of Vat | L2: Receipts from Customers | P2: Sales Net of Vat | S2: Other Income | T2: Investment Grants | U2: Bad Debts written off | V2: =V1+Nov!V2 -> 12500 | W2: Sub contractors only
H3: Vat Output | L3: Actual amount received | M3: Sales Value not yet received | N3: Number of Days Outstanding | P3: Product A | Q3: Product B | R3: Product C | V3: Sale of Fixed Assets | W3: CIS Tax Deducted | X3: CIS Certificate reference
H4: =Nov!H4 -> 0 | P4: A | Q4: B | R4: C | S4: D | T4: G | U4: O | V4: FS
A5: 46359 | B5: FreshField Ltd | C5: INV-2609 | E5: Software monitoring licence | F5: b | G5: 360 | H5: =IF(H$4>0,(IF(G5<>0,G5*H$4/100," ")),IF(G5<>0,G5*H$2/(100+H$2)," ")) -> 60 | I5: =IF((G5<>0),G5-H5," ") -> 300 | M5: =IF(G5<>0,G5-L5," ") -> 360 | N5: =IF((G5-L5)<>0,N$1-A5," ") -> -64 | P5: =IF((F5="a"),I5," ") | Q5: =IF((F5="b"),I5," ") -> 300 | R5: =IF((F5="c"),I5," ") | S5: =IF((F5="d"),I5," ") | T5: =IF((F5="g"),I5," ") | U5: =IF((F5="o"),I5," ") | V5: =IF((F5="FS"),I5," ") | BZ5: 4001
A6: 46361 | B6: CloudNine Ltd | C6: INV-1409 | E6: SaaS licence fee | F6: b | G6: 600 | H6: =IF(H$4>0,(IF(G6<>0,G6*H$4/100," ")),IF(G6<>0,G6*H$2/(100+H$2)," ")) -> 100 | I6: =IF((G6<>0),G6-H6," ") -> 500 | M6: =IF(G6<>0,G6-L6," ") -> 600 | N6: =IF((G6-L6)<>0,N$1-A6," ") -> -66 | P6: =IF((F6="a"),I6," ") | Q6: =IF((F6="b"),I6," ") -> 500 | R6: =IF((F6="c"),I6," ") | S6: =IF((F6="d"),I6," ") | T6: =IF((F6="g"),I6," ") | U6: =IF((F6="o"),I6," ") | V6: =IF((F6="FS"),I6," ") | BZ6: 4001
A7: 46364 | B7: Cedar Systems | C7: INV-2409 | E7: Managed services | F7: a | G7: 480 | H7: =IF(H$4>0,(IF(G7<>0,G7*H$4/100," ")),IF(G7<>0,G7*H$2/(100+H$2)," ")) -> 80 | I7: =IF((G7<>0),G7-H7," ") -> 400 | M7: =IF(G7<>0,G7-L7," ") -> 480 | N7: =IF((G7-L7)<>0,N$1-A7," ") -> -69 | P7: =IF((F7="a"),I7," ") -> 400 | Q7: =IF((F7="b"),I7," ") | R7: =IF((F7="c"),I7," ") | S7: =IF((F7="d"),I7," ") | T7: =IF((F7="g"),I7," ") | U7: =IF((F7="o"),I7," ") | V7: =IF((F7="FS"),I7," ") | BZ7: 4000
A8: 46366 | B8: Pinnacle Group | C8: INV-2209 | E8: Monthly support contract | F8: a | G8: 720 | H8: =IF(H$4>0,(IF(G8<>0,G8*H$4/100," ")),IF(G8<>0,G8*H$2/(100+H$2)," ")) -> 120 | I8: =IF((G8<>0),G8-H8," ") -> 600 | M8: =IF(G8<>0,G8-L8," ") -> 720 | N8: =IF((G8-L8)<>0,N$1-A8," ") -> -71 | P8: =IF((F8="a"),I8," ") -> 600 | Q8: =IF((F8="b"),I8," ") | R8: =IF((F8="c"),I8," ") | S8: =IF((F8="d"),I8," ") | T8: =IF((F8="g"),I8," ") | U8: =IF((F8="o"),I8," ") | V8: =IF((F8="FS"),I8," ") | BZ8: 4000
A9: 46371 | B9: Acme Corp | C9: INV-1009 | E9: IT consultancy services | F9: a | G9: 25000 | H9: =IF(H$4>0,(IF(G9<>0,G9*H$4/100," ")),IF(G9<>0,G9*H$2/(100+H$2)," ")) -> 4166.6667 | I9: =IF((G9<>0),G9-H9," ") -> 20833.333 | M9: =IF(G9<>0,G9-L9," ") -> 25000 | N9: =IF((G9-L9)<>0,N$1-A9," ") -> -76 | P9: =IF((F9="a"),I9," ") -> 20833.333 | Q9: =IF((F9="b"),I9," ") | R9: =IF((F9="c"),I9," ") | S9: =IF((F9="d"),I9," ") | T9: =IF((F9="g"),I9," ") | U9: =IF((F9="o"),I9," ") | V9: =IF((F9="FS"),I9," ") | BZ9: 4000
A10: 46374 | B10: TechStart Ltd | C10: INV-1109 | E10: IT consultancy retainer | F10: a | G10: 2400 | H10: =IF(H$4>0,(IF(G10<>0,G10*H$4/100," ")),IF(G10<>0,G10*H$2/(100+H$2)," ")) -> 400 | I10: =IF((G10<>0),G10-H10," ") -> 2000 | M10: =IF(G10<>0,G10-L10," ") -> 2400 | N10: =IF((G10-L10)<>0,N$1-A10," ") -> -79 | P10: =IF((F10="a"),I10," ") -> 2000 | Q10: =IF((F10="b"),I10," ") | R10: =IF((F10="c"),I10," ") | S10: =IF((F10="d"),I10," ") | T10: =IF((F10="g"),I10," ") | U10: =IF((F10="o"),I10," ") | V10: =IF((F10="FS"),I10," ") | BZ10: 4000
A11: 46376 | B11: DataFlow Inc | C11: INV-1205 | E11: Ad-hoc consultancy project | F11: a | G11: 1800 | H11: =IF(H$4>0,(IF(G11<>0,G11*H$4/100," ")),IF(G11<>0,G11*H$2/(100+H$2)," ")) -> 300 | I11: =IF((G11<>0),G11-H11," ") -> 1500 | M11: =IF(G11<>0,G11-L11," ") -> 1800 | N11: =IF((G11-L11)<>0,N$1-A11," ") -> -81 | P11: =IF((F11="a"),I11," ") -> 1500 | Q11: =IF((F11="b"),I11," ") | R11: =IF((F11="c"),I11," ") | S11: =IF((F11="d"),I11," ") | T11: =IF((F11="g"),I11," ") | U11: =IF((F11="o"),I11," ") | V11: =IF((F11="FS"),I11," ") | BZ11: 4000
A12: 46378 | B12: WidgetWorks | C12: INV-2103 | E12: Project consultancy | F12: a | G12: 1440 | H12: =IF(H$4>0,(IF(G12<>0,G12*H$4/100," ")),IF(G12<>0,G12*H$2/(100+H$2)," ")) -> 240 | I12: =IF((G12<>0),G12-H12," ") -> 1200 | M12: =IF(G12<>0,G12-L12," ") -> 1440 | N12: =IF((G12-L12)<>0,N$1-A12," ") -> -83 | P12: =IF((F12="a"),I12," ") -> 1200 | Q12: =IF((F12="b"),I12," ") | R12: =IF((F12="c"),I12," ") | S12: =IF((F12="d"),I12," ") | T12: =IF((F12="g"),I12," ") | U12: =IF((F12="o"),I12," ") | V12: =IF((F12="FS"),I12," ") | BZ12: 4000
H13: =IF(H$4>0,(IF(G13<>0,G13*H$4/100," ")),IF(G13<>0,G13*H$2/(100+H$2)," ")) | I13: =IF((G13<>0),G13-H13," ") | M13: =IF(G13<>0,G13-L13," ") | N13: =IF((G13-L13)<>0,N$1-A13," ") | P13: =IF((F13="a"),I13," ") | Q13: =IF((F13="b"),I13," ") | R13: =IF((F13="c"),I13," ") | S13: =IF((F13="d"),I13," ") | T13: =IF((F13="g"),I13," ") | U13: =IF((F13="o"),I13," ") | V13: =IF((F13="FS"),I13," ")
H14: =IF(H$4>0,(IF(G14<>0,G14*H$4/100," ")),IF(G14<>0,G14*H$2/(100+H$2)," ")) | I14: =IF((G14<>0),G14-H14," ") | M14: =IF(G14<>0,G14-L14," ") | N14: =IF((G14-L14)<>0,N$1-A14," ") | P14: =IF((F14="a"),I14," ") | Q14: =IF((F14="b"),I14," ") | R14: =IF((F14="c"),I14," ") | S14: =IF((F14="d"),I14," ") | T14: =IF((F14="g"),I14," ") | U14: =IF((F14="o"),I14," ") | V14: =IF((F14="FS"),I14," ")
H15: =IF(H$4>0,(IF(G15<>0,G15*H$4/100," ")),IF(G15<>0,G15*H$2/(100+H$2)," ")) | I15: =IF((G15<>0),G15-H15," ") | M15: =IF(G15<>0,G15-L15," ") | N15: =IF((G15-L15)<>0,N$1-A15," ") | P15: =IF((F15="a"),I15," ") | Q15: =IF((F15="b"),I15," ") | R15: =IF((F15="c"),I15," ") | S15: =IF((F15="d"),I15," ") | T15: =IF((F15="g"),I15," ") | U15: =IF((F15="o"),I15," ") | V15: =IF((F15="FS"),I15," ")
H16: =IF(H$4>0,(IF(G16<>0,G16*H$4/100," ")),IF(G16<>0,G16*H$2/(100+H$2)," ")) | I16: =IF((G16<>0),G16-H16," ") | M16: =IF(G16<>0,G16-L16," ") | N16: =IF((G16-L16)<>0,N$1-A16," ") | P16: =IF((F16="a"),I16," ") | Q16: =IF((F16="b"),I16," ") | R16: =IF((F16="c"),I16," ") | S16: =IF((F16="d"),I16," ") | T16: =IF((F16="g"),I16," ") | U16: =IF((F16="o"),I16," ") | V16: =IF((F16="FS"),I16," ")
H17: =IF(H$4>0,(IF(G17<>0,G17*H$4/100," ")),IF(G17<>0,G17*H$2/(100+H$2)," ")) | I17: =IF((G17<>0),G17-H17," ") | M17: =IF(G17<>0,G17-L17," ") | N17: =IF((G17-L17)<>0,N$1-A17," ") | P17: =IF((F17="a"),I17," ") | Q17: =IF((F17="b"),I17," ") | R17: =IF((F17="c"),I17," ") | S17: =IF((F17="d"),I17," ") | T17: =IF((F17="g"),I17," ") | U17: =IF((F17="o"),I17," ") | V17: =IF((F17="FS"),I17," ")
H18: =IF(H$4>0,(IF(G18<>0,G18*H$4/100," ")),IF(G18<>0,G18*H$2/(100+H$2)," ")) | I18: =IF((G18<>0),G18-H18," ") | M18: =IF(G18<>0,G18-L18," ") | N18: =IF((G18-L18)<>0,N$1-A18," ") | P18: =IF((F18="a"),I18," ") | Q18: =IF((F18="b"),I18," ") | R18: =IF((F18="c"),I18," ") | S18: =IF((F18="d"),I18," ") | T18: =IF((F18="g"),I18," ") | U18: =IF((F18="o"),I18," ") | V18: =IF((F18="FS"),I18," ")
H19: =IF(H$4>0,(IF(G19<>0,G19*H$4/100," ")),IF(G19<>0,G19*H$2/(100+H$2)," ")) | I19: =IF((G19<>0),G19-H19," ") | M19: =IF(G19<>0,G19-L19," ") | N19: =IF((G19-L19)<>0,N$1-A19," ") | P19: =IF((F19="a"),I19," ") | Q19: =IF((F19="b"),I19," ") | R19: =IF((F19="c"),I19," ") | S19: =IF((F19="d"),I19," ") | T19: =IF((F19="g"),I19," ") | U19: =IF((F19="o"),I19," ") | V19: =IF((F19="FS"),I19," ")
H20: =IF(H$4>0,(IF(G20<>0,G20*H$4/100," ")),IF(G20<>0,G20*H$2/(100+H$2)," ")) | I20: =IF((G20<>0),G20-H20," ") | M20: =IF(G20<>0,G20-L20," ") | N20: =IF((G20-L20)<>0,N$1-A20," ") | P20: =IF((F20="a"),I20," ") | Q20: =IF((F20="b"),I20," ") | R20: =IF((F20="c"),I20," ") | S20: =IF((F20="d"),I20," ") | T20: =IF((F20="g"),I20," ") | U20: =IF((F20="o"),I20," ") | V20: =IF((F20="FS"),I20," ")
H21: =IF(H$4>0,(IF(G21<>0,G21*H$4/100," ")),IF(G21<>0,G21*H$2/(100+H$2)," ")) | I21: =IF((G21<>0),G21-H21," ") | M21: =IF(G21<>0,G21-L21," ") | N21: =IF((G21-L21)<>0,N$1-A21," ") | P21: =IF((F21="a"),I21," ") | Q21: =IF((F21="b"),I21," ") | R21: =IF((F21="c"),I21," ") | S21: =IF((F21="d"),I21," ") | T21: =IF((F21="g"),I21," ") | U21: =IF((F21="o"),I21," ") | V21: =IF((F21="FS"),I21," ")
H22: =IF(H$4>0,(IF(G22<>0,G22*H$4/100," ")),IF(G22<>0,G22*H$2/(100+H$2)," ")) | I22: =IF((G22<>0),G22-H22," ") | M22: =IF(G22<>0,G22-L22," ") | N22: =IF((G22-L22)<>0,N$1-A22," ") | P22: =IF((F22="a"),I22," ") | Q22: =IF((F22="b"),I22," ") | R22: =IF((F22="c"),I22," ") | S22: =IF((F22="d"),I22," ") | T22: =IF((F22="g"),I22," ") | U22: =IF((F22="o"),I22," ") | V22: =IF((F22="FS"),I22," ")
H23: =IF(H$4>0,(IF(G23<>0,G23*H$4/100," ")),IF(G23<>0,G23*H$2/(100+H$2)," ")) | I23: =IF((G23<>0),G23-H23," ") | M23: =IF(G23<>0,G23-L23," ") | N23: =IF((G23-L23)<>0,N$1-A23," ") | P23: =IF((F23="a"),I23," ") | Q23: =IF((F23="b"),I23," ") | R23: =IF((F23="c"),I23," ") | S23: =IF((F23="d"),I23," ") | T23: =IF((F23="g"),I23," ") | U23: =IF((F23="o"),I23," ") | V23: =IF((F23="FS"),I23," ")
H24: =IF(H$4>0,(IF(G24<>0,G24*H$4/100," ")),IF(G24<>0,G24*H$2/(100+H$2)," ")) | I24: =IF((G24<>0),G24-H24," ") | M24: =IF(G24<>0,G24-L24," ") | N24: =IF((G24-L24)<>0,N$1-A24," ") | P24: =IF((F24="a"),I24," ") | Q24: =IF((F24="b"),I24," ") | R24: =IF((F24="c"),I24," ") | S24: =IF((F24="d"),I24," ") | T24: =IF((F24="g"),I24," ") | U24: =IF((F24="o"),I24," ") | V24: =IF((F24="FS"),I24," ")
... H68: =IF(H$4>0,(IF(G68<>0,G68*H$4/100," ")),IF(G68<>0,G68*H$2/(100+H$2)," ")) | I68: =IF((G68<>0),G68-H68," ") | M68: =IF(G68<>0,G68-L68," ") | N68: =IF((G68-L68)<>0,N$1-A68," ") | P68: =IF((F68="a"),I68," ") | Q68: =IF((F68="b"),I68," ") | R68: =IF((F68="c"),I68," ") | S68: =IF((F68="d"),I68," ") | T68: =IF((F68="g"),I68," ") | U68: =IF((F68="o"),I68," ") | V68: =IF((F68="FS"),I68," ")
F69: =IF((G69<>0),"Enter Letter"," ") | H69: =IF(H$4>0,(IF(G69<>0,G69*H$4/100," ")),IF(G69<>0,G69*H$2/(100+H$2)," ")) | I69: =IF((G69<>0),G69-H69," ") | M69: =IF(G69<>0,G69-L69," ") | N69: =IF((G69-L69)<>0,N$1-A69," ") | P69: =IF((F69="a"),I69," ") | Q69: =IF((F69="b"),I69," ") | R69: =IF((F69="c"),I69," ") | S69: =IF((F69="d"),I69," ") | T69: =IF((F69="g"),I69," ") | U69: =IF((F69="o"),I69," ") | V69: =IF((F69="FS"),I69," ")
F70: =IF((G70<>0),"Enter Letter"," ") | H70: =IF(H$4>0,(IF(G70<>0,G70*H$4/100," ")),IF(G70<>0,G70*H$2/(100+H$2)," ")) | I70: =IF((G70<>0),G70-H70," ") | M70: =IF(G70<>0,G70-L70," ") | N70: =IF((G70-L70)<>0,N$1-A70," ") | P70: =IF((F70="a"),I70," ") | Q70: =IF((F70="b"),I70," ") | R70: =IF((F70="c"),I70," ") | S70: =IF((F70="d"),I70," ") | T70: =IF((F70="g"),I70," ") | U70: =IF((F70="o"),I70," ") | V70: =IF((F70="FS"),I70," ")
F71: =IF((G71<>0),"Enter Letter"," ") | H71: =IF(H$4>0,(IF(G71<>0,G71*H$4/100," ")),IF(G71<>0,G71*H$2/(100+H$2)," ")) | I71: =IF((G71<>0),G71-H71," ") | M71: =IF(G71<>0,G71-L71," ") | N71: =IF((G71-L71)<>0,N$1-A71," ") | P71: =IF((F71="a"),I71," ") | Q71: =IF((F71="b"),I71," ") | R71: =IF((F71="c"),I71," ") | S71: =IF((F71="d"),I71," ") | T71: =IF((F71="g"),I71," ") | U71: =IF((F71="o"),I71," ") | V71: =IF((F71="FS"),I71," ")
F72: =IF((G72<>0),"Enter Letter"," ") | H72: =IF(H$4>0,(IF(G72<>0,G72*H$4/100," ")),IF(G72<>0,G72*H$2/(100+H$2)," ")) | I72: =IF((G72<>0),G72-H72," ") | M72: =IF(G72<>0,G72-L72," ") | N72: =IF((G72-L72)<>0,N$1-A72," ") | P72: =IF((F72="a"),I72," ") | Q72: =IF((F72="b"),I72," ") | R72: =IF((F72="c"),I72," ") | S72: =IF((F72="d"),I72," ") | T72: =IF((F72="g"),I72," ") | U72: =IF((F72="o"),I72," ") | V72: =IF((F72="FS"),I72," ")
F73: =IF((G73<>0),"Enter Letter"," ") | H73: =IF(H$4>0,(IF(G73<>0,G73*H$4/100," ")),IF(G73<>0,G73*H$2/(100+H$2)," ")) | I73: =IF((G73<>0),G73-H73," ") | M73: =IF(G73<>0,G73-L73," ") | N73: =IF((G73-L73)<>0,N$1-A73," ") | P73: =IF((F73="a"),I73," ") | Q73: =IF((F73="b"),I73," ") | R73: =IF((F73="c"),I73," ") | S73: =IF((F73="d"),I73," ") | T73: =IF((F73="g"),I73," ") | U73: =IF((F73="o"),I73," ") | V73: =IF((F73="FS"),I73," ")
F74: =IF((G74<>0),"Enter Letter"," ") | H74: =IF(H$4>0,(IF(G74<>0,G74*H$4/100," ")),IF(G74<>0,G74*H$2/(100+H$2)," ")) | I74: =IF((G74<>0),G74-H74," ") | M74: =IF(G74<>0,G74-L74," ") | N74: =IF((G74-L74)<>0,N$1-A74," ") | P74: =IF((F74="a"),I74," ") | Q74: =IF((F74="b"),I74," ") | R74: =IF((F74="c"),I74," ") | S74: =IF((F74="d"),I74," ") | T74: =IF((F74="g"),I74," ") | U74: =IF((F74="o"),I74," ") | V74: =IF((F74="FS"),I74," ")
F75: =IF((G75<>0),"Enter Letter"," ") | H75: =IF(H$4>0,(IF(G75<>0,G75*H$4/100," ")),IF(G75<>0,G75*H$2/(100+H$2)," ")) | I75: =IF((G75<>0),G75-H75," ") | M75: =IF(G75<>0,G75-L75," ") | N75: =IF((G75-L75)<>0,N$1-A75," ") | P75: =IF((F75="a"),I75," ") | Q75: =IF((F75="b"),I75," ") | R75: =IF((F75="c"),I75," ") | S75: =IF((F75="d"),I75," ") | T75: =IF((F75="g"),I75," ") | U75: =IF((F75="o"),I75," ") | V75: =IF((F75="FS"),I75," ")
F76: =IF((G76<>0),"Enter Letter"," ") | H76: =IF(H$4>0,(IF(G76<>0,G76*H$4/100," ")),IF(G76<>0,G76*H$2/(100+H$2)," ")) | I76: =IF((G76<>0),G76-H76," ") | M76: =IF(G76<>0,G76-L76," ") | N76: =IF((G76-L76)<>0,N$1-A76," ") | P76: =IF((F76="a"),I76," ") | Q76: =IF((F76="b"),I76," ") | R76: =IF((F76="c"),I76," ") | S76: =IF((F76="d"),I76," ") | T76: =IF((F76="g"),I76," ") | U76: =IF((F76="o"),I76," ") | V76: =IF((F76="FS"),I76," ")
F77: =IF((G77<>0),"Enter Letter"," ") | H77: =IF(H$4>0,(IF(G77<>0,G77*H$4/100," ")),IF(G77<>0,G77*H$2/(100+H$2)," ")) | I77: =IF((G77<>0),G77-H77," ") | M77: =IF(G77<>0,G77-L77," ") | N77: =IF((G77-L77)<>0,N$1-A77," ") | P77: =IF((F77="a"),I77," ") | Q77: =IF((F77="b"),I77," ") | R77: =IF((F77="c"),I77," ") | S77: =IF((F77="d"),I77," ") | T77: =IF((F77="g"),I77," ") | U77: =IF((F77="o"),I77," ") | V77: =IF((F77="FS"),I77," ")
F78: =IF((G78<>0),"Enter Letter"," ") | H78: =IF(H$4>0,(IF(G78<>0,G78*H$4/100," ")),IF(G78<>0,G78*H$2/(100+H$2)," ")) | I78: =IF((G78<>0),G78-H78," ") | M78: =IF(G78<>0,G78-L78," ") | N78: =IF((G78-L78)<>0,N$1-A78," ") | P78: =IF((F78="a"),I78," ") | Q78: =IF((F78="b"),I78," ") | R78: =IF((F78="c"),I78," ") | S78: =IF((F78="d"),I78," ") | T78: =IF((F78="g"),I78," ") | U78: =IF((F78="o"),I78," ") | V78: =IF((F78="FS"),I78," ")
F79: =IF((G79<>0),"Enter Letter"," ") | H79: =IF(H$4>0,(IF(G79<>0,G79*H$4/100," ")),IF(G79<>0,G79*H$2/(100+H$2)," ")) | I79: =IF((G79<>0),G79-H79," ") | M79: =IF(G79<>0,G79-L79," ") | N79: =IF((G79-L79)<>0,N$1-A79," ") | P79: =IF((F79="a"),I79," ") | Q79: =IF((F79="b"),I79," ") | R79: =IF((F79="c"),I79," ") | S79: =IF((F79="d"),I79," ") | T79: =IF((F79="g"),I79," ") | U79: =IF((F79="o"),I79," ") | V79: =IF((F79="FS"),I79," ")
F80: =IF((G80<>0),"Enter Letter"," ") | H80: =IF(H$4>0,(IF(G80<>0,G80*H$4/100," ")),IF(G80<>0,G80*H$2/(100+H$2)," ")) | I80: =IF((G80<>0),G80-H80," ") | M80: =IF(G80<>0,G80-L80," ") | N80: =IF((G80-L80)<>0,N$1-A80," ") | P80: =IF((F80="a"),I80," ") | Q80: =IF((F80="b"),I80," ") | R80: =IF((F80="c"),I80," ") | S80: =IF((F80="d"),I80," ") | T80: =IF((F80="g"),I80," ") | U80: =IF((F80="o"),I80," ") | V80: =IF((F80="FS"),I80," ")
... F300: =IF((G300<>0),"Enter Letter"," ") | H300: =IF(H$4>0,(IF(G300<>0,G300*H$4/100," ")),IF(G300<>0,G300*H$2/(100+H$2)," ")) | I300: =IF((G300<>0),G300-H300," ") | M300: =IF(G300<>0,G300-L300," ") | N300: =IF((G300-L300)<>0,N$1-A300," ") | P300: =IF((F300="a"),I300," ") | Q300: =IF((F300="b"),I300," ") | R300: =IF((F300="c"),I300," ") | S300: =IF((F300="d"),I300," ") | T300: =IF((F300="g"),I300," ") | U300: =IF((F300="o"),I300," ") | V300: =IF((F300="FS"),I300," ")

Sheet Jan
A1: =G1-H1-SUM(P1:V1) -> 0 | B1: Check Total | C1: Sales Mileage | D1: =SUM(D5:D300) -> 0 | E1: Sales Description | F1: Enter Expense Code Letter | G1: =SUM(G5:G300) -> 35440 | H1: =SUM(H5:H300) -> 5906.6667 | I1: =SUM(I5:I300) -> 29533.333 | K1: For your information only. Enter How Paid e.g. Cash, Cheque etc., | L1: =SUM(L5:L300) -> 0 | M1: =SUM(M5:M300) -> 35440 | N1: =TODAY() -> 46295 | P1: =SUM(P5:P300) -> 25633.333 | Q1: =SUM(Q5:Q300) -> 1800 | R1: =SUM(R5:R300) -> 1000 | S1: =SUM(S5:S300) -> 1100 | T1: =SUM(T5:T300) -> 0 | U1: =SUM(U5:U300) -> 0 | V1: =SUM(V5:V300) -> 0 | W1: =SUM(W5:W300) -> 0 | X1: =W1+Dec!X1 -> 0
A2: Sales Date | B2: Customer Name | C2: Sales Invoice Number or reference | D2: Sales Mileage | G2: Sales Value including Vat | H2: =Dec!H2 -> 20 | I2: Sales Net of Vat | L2: Receipts from Customers | P2: Sales Net of Vat | S2: Other Income | T2: Investment Grants | U2: Bad Debts written off | V2: =V1+Dec!V2 -> 12500 | W2: Sub contractors only
H3: Vat Output | L3: Actual amount received | M3: Sales Value not yet received | N3: Number of Days Outstanding | P3: Product A | Q3: Product B | R3: Product C | V3: Sale of Fixed Assets | W3: CIS Tax Deducted | X3: CIS Certificate reference
H4: =Dec!H4 -> 0 | P4: A | Q4: B | R4: C | S4: D | T4: G | U4: O | V4: FS
A5: 46388 | B5: Beta Systems | C5: INV-1304 | E5: Software licence renewal | F5: b | G5: 1200 | H5: =IF(H$4>0,(IF(G5<>0,G5*H$4/100," ")),IF(G5<>0,G5*H$2/(100+H$2)," ")) -> 200 | I5: =IF((G5<>0),G5-H5," ") -> 1000 | M5: =IF(G5<>0,G5-L5," ") -> 1200 | N5: =IF((G5-L5)<>0,N$1-A5," ") -> -93 | P5: =IF((F5="a"),I5," ") | Q5: =IF((F5="b"),I5," ") -> 1000 | R5: =IF((F5="c"),I5," ") | S5: =IF((F5="d"),I5," ") | T5: =IF((F5="g"),I5," ") | U5: =IF((F5="o"),I5," ") | V5: =IF((F5="FS"),I5," ") | BZ5: 4001
A6: 46390 | B6: FreshField Ltd | C6: INV-2610 | E6: Software monitoring licence | F6: b | G6: 360 | H6: =IF(H$4>0,(IF(G6<>0,G6*H$4/100," ")),IF(G6<>0,G6*H$2/(100+H$2)," ")) -> 60 | I6: =IF((G6<>0),G6-H6," ") -> 300 | M6: =IF(G6<>0,G6-L6," ") -> 360 | N6: =IF((G6-L6)<>0,N$1-A6," ") -> -95 | P6: =IF((F6="a"),I6," ") | Q6: =IF((F6="b"),I6," ") -> 300 | R6: =IF((F6="c"),I6," ") | S6: =IF((F6="d"),I6," ") | T6: =IF((F6="g"),I6," ") | U6: =IF((F6="o"),I6," ") | V6: =IF((F6="FS"),I6," ") | BZ6: 4001
A7: 46392 | B7: CloudNine Ltd | C7: INV-1410 | E7: SaaS licence fee | F7: b | G7: 600 | H7: =IF(H$4>0,(IF(G7<>0,G7*H$4/100," ")),IF(G7<>0,G7*H$2/(100+H$2)," ")) -> 100 | I7: =IF((G7<>0),G7-H7," ") -> 500 | M7: =IF(G7<>0,G7-L7," ") -> 600 | N7: =IF((G7-L7)<>0,N$1-A7," ") -> -97 | P7: =IF((F7="a"),I7," ") | Q7: =IF((F7="b"),I7," ") -> 500 | R7: =IF((F7="c"),I7," ") | S7: =IF((F7="d"),I7," ") | T7: =IF((F7="g"),I7," ") | U7: =IF((F7="o"),I7," ") | V7: =IF((F7="FS"),I7," ") | BZ7: 4001
A8: 46395 | B8: Cedar Systems | C8: INV-2410 | E8: Managed services | F8: a | G8: 480 | H8: =IF(H$4>0,(IF(G8<>0,G8*H$4/100," ")),IF(G8<>0,G8*H$2/(100+H$2)," ")) -> 80 | I8: =IF((G8<>0),G8-H8," ") -> 400 | M8: =IF(G8<>0,G8-L8," ") -> 480 | N8: =IF((G8-L8)<>0,N$1-A8," ") -> -100 | P8: =IF((F8="a"),I8," ") -> 400 | Q8: =IF((F8="b"),I8," ") | R8: =IF((F8="c"),I8," ") | S8: =IF((F8="d"),I8," ") | T8: =IF((F8="g"),I8," ") | U8: =IF((F8="o"),I8," ") | V8: =IF((F8="FS"),I8," ") | BZ8: 4000
A9: 46397 | B9: Pinnacle Group | C9: INV-2210 | E9: Monthly support contract | F9: a | G9: 720 | H9: =IF(H$4>0,(IF(G9<>0,G9*H$4/100," ")),IF(G9<>0,G9*H$2/(100+H$2)," ")) -> 120 | I9: =IF((G9<>0),G9-H9," ") -> 600 | M9: =IF(G9<>0,G9-L9," ") -> 720 | N9: =IF((G9-L9)<>0,N$1-A9," ") -> -102 | P9: =IF((F9="a"),I9," ") -> 600 | Q9: =IF((F9="b"),I9," ") | R9: =IF((F9="c"),I9," ") | S9: =IF((F9="d"),I9," ") | T9: =IF((F9="g"),I9," ") | U9: =IF((F9="o"),I9," ") | V9: =IF((F9="FS"),I9," ") | BZ9: 4000
A10: 46401 | B10: NorthStar Digital | C10: INV-2303 | E10: Project delivery | F10: a | G10: 2160 | H10: =IF(H$4>0,(IF(G10<>0,G10*H$4/100," ")),IF(G10<>0,G10*H$2/(100+H$2)," ")) -> 360 | I10: =IF((G10<>0),G10-H10," ") -> 1800 | M10: =IF(G10<>0,G10-L10," ") -> 2160 | N10: =IF((G10-L10)<>0,N$1-A10," ") -> -106 | P10: =IF((F10="a"),I10," ") -> 1800 | Q10: =IF((F10="b"),I10," ") | R10: =IF((F10="c"),I10," ") | S10: =IF((F10="d"),I10," ") | T10: =IF((F10="g"),I10," ") | U10: =IF((F10="o"),I10," ") | V10: =IF((F10="FS"),I10," ") | BZ10: 4000
A11: 46402 | B11: Acme Corp | C11: INV-1010 | E11: IT consultancy services | F11: a | G11: 25000 | H11: =IF(H$4>0,(IF(G11<>0,G11*H$4/100," ")),IF(G11<>0,G11*H$2/(100+H$2)," ")) -> 4166.6667 | I11: =IF((G11<>0),G11-H11," ") -> 20833.333 | M11: =IF(G11<>0,G11-L11," ") -> 25000 | N11: =IF((G11-L11)<>0,N$1-A11," ") -> -107 | P11: =IF((F11="a"),I11," ") -> 20833.333 | Q11: =IF((F11="b"),I11," ") | R11: =IF((F11="c"),I11," ") | S11: =IF((F11="d"),I11," ") | T11: =IF((F11="g"),I11," ") | U11: =IF((F11="o"),I11," ") | V11: =IF((F11="FS"),I11," ") | BZ11: 4000
A12: 46403 | B12: Summit Training | C12: INV-2803 | E12: Technical training delivery | F12: c | G12: 1200 | H12: =IF(H$4>0,(IF(G12<>0,G12*H$4/100," ")),IF(G12<>0,G12*H$2/(100+H$2)," ")) -> 200 | I12: =IF((G12<>0),G12-H12," ") -> 1000 | M12: =IF(G12<>0,G12-L12," ") -> 1200 | N12: =IF((G12-L12)<>0,N$1-A12," ") -> -108 | P12: =IF((F12="a"),I12," ") | Q12: =IF((F12="b"),I12," ") | R12: =IF((F12="c"),I12," ") -> 1000 | S12: =IF((F12="d"),I12," ") | T12: =IF((F12="g"),I12," ") | U12: =IF((F12="o"),I12," ") | V12: =IF((F12="FS"),I12," ") | BZ12: 4002
A13: 46405 | B13: TechStart Ltd | C13: INV-1110 | E13: IT consultancy retainer | F13: a | G13: 2400 | H13: =IF(H$4>0,(IF(G13<>0,G13*H$4/100," ")),IF(G13<>0,G13*H$2/(100+H$2)," ")) -> 400 | I13: =IF((G13<>0),G13-H13," ") -> 2000 | M13: =IF(G13<>0,G13-L13," ") -> 2400 | N13: =IF((G13-L13)<>0,N$1-A13," ") -> -110 | P13: =IF((F13="a"),I13," ") -> 2000 | Q13: =IF((F13="b"),I13," ") | R13: =IF((F13="c"),I13," ") | S13: =IF((F13="d"),I13," ") | T13: =IF((F13="g"),I13," ") | U13: =IF((F13="o"),I13," ") | V13: =IF((F13="FS"),I13," ") | BZ13: 4000
A14: 46412 | B14: Lambda Corp | C14: INV-1602 | E14: Client referral commission | F14: d | G14: 480 | H14: =IF(H$4>0,(IF(G14<>0,G14*H$4/100," ")),IF(G14<>0,G14*H$2/(100+H$2)," ")) -> 80 | I14: =IF((G14<>0),G14-H14," ") -> 400 | M14: =IF(G14<>0,G14-L14," ") -> 480 | N14: =IF((G14-L14)<>0,N$1-A14," ") -> -117 | P14: =IF((F14="a"),I14," ") | Q14: =IF((F14="b"),I14," ") | R14: =IF((F14="c"),I14," ") | S14: =IF((F14="d"),I14," ") -> 400 | T14: =IF((F14="g"),I14," ") | U14: =IF((F14="o"),I14," ") | V14: =IF((F14="FS"),I14," ") | BZ14: 4003
A15: 46415 | B15: Horizon Analytics | C15: INV-2704 | E15: Data analytics commission | F15: d | G15: 840 | H15: =IF(H$4>0,(IF(G15<>0,G15*H$4/100," ")),IF(G15<>0,G15*H$2/(100+H$2)," ")) -> 140 | I15: =IF((G15<>0),G15-H15," ") -> 700 | M15: =IF(G15<>0,G15-L15," ") -> 840 | N15: =IF((G15-L15)<>0,N$1-A15," ") -> -120 | P15: =IF((F15="a"),I15," ") | Q15: =IF((F15="b"),I15," ") | R15: =IF((F15="c"),I15," ") | S15: =IF((F15="d"),I15," ") -> 700 | T15: =IF((F15="g"),I15," ") | U15: =IF((F15="o"),I15," ") | V15: =IF((F15="FS"),I15," ") | BZ15: 4003
H16: =IF(H$4>0,(IF(G16<>0,G16*H$4/100," ")),IF(G16<>0,G16*H$2/(100+H$2)," ")) | I16: =IF((G16<>0),G16-H16," ") | M16: =IF(G16<>0,G16-L16," ") | N16: =IF((G16-L16)<>0,N$1-A16," ") | P16: =IF((F16="a"),I16," ") | Q16: =IF((F16="b"),I16," ") | R16: =IF((F16="c"),I16," ") | S16: =IF((F16="d"),I16," ") | T16: =IF((F16="g"),I16," ") | U16: =IF((F16="o"),I16," ") | V16: =IF((F16="FS"),I16," ")
H17: =IF(H$4>0,(IF(G17<>0,G17*H$4/100," ")),IF(G17<>0,G17*H$2/(100+H$2)," ")) | I17: =IF((G17<>0),G17-H17," ") | M17: =IF(G17<>0,G17-L17," ") | N17: =IF((G17-L17)<>0,N$1-A17," ") | P17: =IF((F17="a"),I17," ") | Q17: =IF((F17="b"),I17," ") | R17: =IF((F17="c"),I17," ") | S17: =IF((F17="d"),I17," ") | T17: =IF((F17="g"),I17," ") | U17: =IF((F17="o"),I17," ") | V17: =IF((F17="FS"),I17," ")
H18: =IF(H$4>0,(IF(G18<>0,G18*H$4/100," ")),IF(G18<>0,G18*H$2/(100+H$2)," ")) | I18: =IF((G18<>0),G18-H18," ") | M18: =IF(G18<>0,G18-L18," ") | N18: =IF((G18-L18)<>0,N$1-A18," ") | P18: =IF((F18="a"),I18," ") | Q18: =IF((F18="b"),I18," ") | R18: =IF((F18="c"),I18," ") | S18: =IF((F18="d"),I18," ") | T18: =IF((F18="g"),I18," ") | U18: =IF((F18="o"),I18," ") | V18: =IF((F18="FS"),I18," ")
H19: =IF(H$4>0,(IF(G19<>0,G19*H$4/100," ")),IF(G19<>0,G19*H$2/(100+H$2)," ")) | I19: =IF((G19<>0),G19-H19," ") | M19: =IF(G19<>0,G19-L19," ") | N19: =IF((G19-L19)<>0,N$1-A19," ") | P19: =IF((F19="a"),I19," ") | Q19: =IF((F19="b"),I19," ") | R19: =IF((F19="c"),I19," ") | S19: =IF((F19="d"),I19," ") | T19: =IF((F19="g"),I19," ") | U19: =IF((F19="o"),I19," ") | V19: =IF((F19="FS"),I19," ")
H20: =IF(H$4>0,(IF(G20<>0,G20*H$4/100," ")),IF(G20<>0,G20*H$2/(100+H$2)," ")) | I20: =IF((G20<>0),G20-H20," ") | M20: =IF(G20<>0,G20-L20," ") | N20: =IF((G20-L20)<>0,N$1-A20," ") | P20: =IF((F20="a"),I20," ") | Q20: =IF((F20="b"),I20," ") | R20: =IF((F20="c"),I20," ") | S20: =IF((F20="d"),I20," ") | T20: =IF((F20="g"),I20," ") | U20: =IF((F20="o"),I20," ") | V20: =IF((F20="FS"),I20," ")
H21: =IF(H$4>0,(IF(G21<>0,G21*H$4/100," ")),IF(G21<>0,G21*H$2/(100+H$2)," ")) | I21: =IF((G21<>0),G21-H21," ") | M21: =IF(G21<>0,G21-L21," ") | N21: =IF((G21-L21)<>0,N$1-A21," ") | P21: =IF((F21="a"),I21," ") | Q21: =IF((F21="b"),I21," ") | R21: =IF((F21="c"),I21," ") | S21: =IF((F21="d"),I21," ") | T21: =IF((F21="g"),I21," ") | U21: =IF((F21="o"),I21," ") | V21: =IF((F21="FS"),I21," ")
H22: =IF(H$4>0,(IF(G22<>0,G22*H$4/100," ")),IF(G22<>0,G22*H$2/(100+H$2)," ")) | I22: =IF((G22<>0),G22-H22," ") | M22: =IF(G22<>0,G22-L22," ") | N22: =IF((G22-L22)<>0,N$1-A22," ") | P22: =IF((F22="a"),I22," ") | Q22: =IF((F22="b"),I22," ") | R22: =IF((F22="c"),I22," ") | S22: =IF((F22="d"),I22," ") | T22: =IF((F22="g"),I22," ") | U22: =IF((F22="o"),I22," ") | V22: =IF((F22="FS"),I22," ")
H23: =IF(H$4>0,(IF(G23<>0,G23*H$4/100," ")),IF(G23<>0,G23*H$2/(100+H$2)," ")) | I23: =IF((G23<>0),G23-H23," ") | M23: =IF(G23<>0,G23-L23," ") | N23: =IF((G23-L23)<>0,N$1-A23," ") | P23: =IF((F23="a"),I23," ") | Q23: =IF((F23="b"),I23," ") | R23: =IF((F23="c"),I23," ") | S23: =IF((F23="d"),I23," ") | T23: =IF((F23="g"),I23," ") | U23: =IF((F23="o"),I23," ") | V23: =IF((F23="FS"),I23," ")
H24: =IF(H$4>0,(IF(G24<>0,G24*H$4/100," ")),IF(G24<>0,G24*H$2/(100+H$2)," ")) | I24: =IF((G24<>0),G24-H24," ") | M24: =IF(G24<>0,G24-L24," ") | N24: =IF((G24-L24)<>0,N$1-A24," ") | P24: =IF((F24="a"),I24," ") | Q24: =IF((F24="b"),I24," ") | R24: =IF((F24="c"),I24," ") | S24: =IF((F24="d"),I24," ") | T24: =IF((F24="g"),I24," ") | U24: =IF((F24="o"),I24," ") | V24: =IF((F24="FS"),I24," ")
H25: =IF(H$4>0,(IF(G25<>0,G25*H$4/100," ")),IF(G25<>0,G25*H$2/(100+H$2)," ")) | I25: =IF((G25<>0),G25-H25," ") | M25: =IF(G25<>0,G25-L25," ") | N25: =IF((G25-L25)<>0,N$1-A25," ") | P25: =IF((F25="a"),I25," ") | Q25: =IF((F25="b"),I25," ") | R25: =IF((F25="c"),I25," ") | S25: =IF((F25="d"),I25," ") | T25: =IF((F25="g"),I25," ") | U25: =IF((F25="o"),I25," ") | V25: =IF((F25="FS"),I25," ")
H26: =IF(H$4>0,(IF(G26<>0,G26*H$4/100," ")),IF(G26<>0,G26*H$2/(100+H$2)," ")) | I26: =IF((G26<>0),G26-H26," ") | M26: =IF(G26<>0,G26-L26," ") | N26: =IF((G26-L26)<>0,N$1-A26," ") | P26: =IF((F26="a"),I26," ") | Q26: =IF((F26="b"),I26," ") | R26: =IF((F26="c"),I26," ") | S26: =IF((F26="d"),I26," ") | T26: =IF((F26="g"),I26," ") | U26: =IF((F26="o"),I26," ") | V26: =IF((F26="FS"),I26," ")
H27: =IF(H$4>0,(IF(G27<>0,G27*H$4/100," ")),IF(G27<>0,G27*H$2/(100+H$2)," ")) | I27: =IF((G27<>0),G27-H27," ") | M27: =IF(G27<>0,G27-L27," ") | N27: =IF((G27-L27)<>0,N$1-A27," ") | P27: =IF((F27="a"),I27," ") | Q27: =IF((F27="b"),I27," ") | R27: =IF((F27="c"),I27," ") | S27: =IF((F27="d"),I27," ") | T27: =IF((F27="g"),I27," ") | U27: =IF((F27="o"),I27," ") | V27: =IF((F27="FS"),I27," ")
... H68: =IF(H$4>0,(IF(G68<>0,G68*H$4/100," ")),IF(G68<>0,G68*H$2/(100+H$2)," ")) | I68: =IF((G68<>0),G68-H68," ") | M68: =IF(G68<>0,G68-L68," ") | N68: =IF((G68-L68)<>0,N$1-A68," ") | P68: =IF((F68="a"),I68," ") | Q68: =IF((F68="b"),I68," ") | R68: =IF((F68="c"),I68," ") | S68: =IF((F68="d"),I68," ") | T68: =IF((F68="g"),I68," ") | U68: =IF((F68="o"),I68," ") | V68: =IF((F68="FS"),I68," ")
F69: =IF((G69<>0),"Enter Letter"," ") | H69: =IF(H$4>0,(IF(G69<>0,G69*H$4/100," ")),IF(G69<>0,G69*H$2/(100+H$2)," ")) | I69: =IF((G69<>0),G69-H69," ") | M69: =IF(G69<>0,G69-L69," ") | N69: =IF((G69-L69)<>0,N$1-A69," ") | P69: =IF((F69="a"),I69," ") | Q69: =IF((F69="b"),I69," ") | R69: =IF((F69="c"),I69," ") | S69: =IF((F69="d"),I69," ") | T69: =IF((F69="g"),I69," ") | U69: =IF((F69="o"),I69," ") | V69: =IF((F69="FS"),I69," ")
F70: =IF((G70<>0),"Enter Letter"," ") | H70: =IF(H$4>0,(IF(G70<>0,G70*H$4/100," ")),IF(G70<>0,G70*H$2/(100+H$2)," ")) | I70: =IF((G70<>0),G70-H70," ") | M70: =IF(G70<>0,G70-L70," ") | N70: =IF((G70-L70)<>0,N$1-A70," ") | P70: =IF((F70="a"),I70," ") | Q70: =IF((F70="b"),I70," ") | R70: =IF((F70="c"),I70," ") | S70: =IF((F70="d"),I70," ") | T70: =IF((F70="g"),I70," ") | U70: =IF((F70="o"),I70," ") | V70: =IF((F70="FS"),I70," ")
F71: =IF((G71<>0),"Enter Letter"," ") | H71: =IF(H$4>0,(IF(G71<>0,G71*H$4/100," ")),IF(G71<>0,G71*H$2/(100+H$2)," ")) | I71: =IF((G71<>0),G71-H71," ") | M71: =IF(G71<>0,G71-L71," ") | N71: =IF((G71-L71)<>0,N$1-A71," ") | P71: =IF((F71="a"),I71," ") | Q71: =IF((F71="b"),I71," ") | R71: =IF((F71="c"),I71," ") | S71: =IF((F71="d"),I71," ") | T71: =IF((F71="g"),I71," ") | U71: =IF((F71="o"),I71," ") | V71: =IF((F71="FS"),I71," ")
F72: =IF((G72<>0),"Enter Letter"," ") | H72: =IF(H$4>0,(IF(G72<>0,G72*H$4/100," ")),IF(G72<>0,G72*H$2/(100+H$2)," ")) | I72: =IF((G72<>0),G72-H72," ") | M72: =IF(G72<>0,G72-L72," ") | N72: =IF((G72-L72)<>0,N$1-A72," ") | P72: =IF((F72="a"),I72," ") | Q72: =IF((F72="b"),I72," ") | R72: =IF((F72="c"),I72," ") | S72: =IF((F72="d"),I72," ") | T72: =IF((F72="g"),I72," ") | U72: =IF((F72="o"),I72," ") | V72: =IF((F72="FS"),I72," ")
F73: =IF((G73<>0),"Enter Letter"," ") | H73: =IF(H$4>0,(IF(G73<>0,G73*H$4/100," ")),IF(G73<>0,G73*H$2/(100+H$2)," ")) | I73: =IF((G73<>0),G73-H73," ") | M73: =IF(G73<>0,G73-L73," ") | N73: =IF((G73-L73)<>0,N$1-A73," ") | P73: =IF((F73="a"),I73," ") | Q73: =IF((F73="b"),I73," ") | R73: =IF((F73="c"),I73," ") | S73: =IF((F73="d"),I73," ") | T73: =IF((F73="g"),I73," ") | U73: =IF((F73="o"),I73," ") | V73: =IF((F73="FS"),I73," ")
F74: =IF((G74<>0),"Enter Letter"," ") | H74: =IF(H$4>0,(IF(G74<>0,G74*H$4/100," ")),IF(G74<>0,G74*H$2/(100+H$2)," ")) | I74: =IF((G74<>0),G74-H74," ") | M74: =IF(G74<>0,G74-L74," ") | N74: =IF((G74-L74)<>0,N$1-A74," ") | P74: =IF((F74="a"),I74," ") | Q74: =IF((F74="b"),I74," ") | R74: =IF((F74="c"),I74," ") | S74: =IF((F74="d"),I74," ") | T74: =IF((F74="g"),I74," ") | U74: =IF((F74="o"),I74," ") | V74: =IF((F74="FS"),I74," ")
F75: =IF((G75<>0),"Enter Letter"," ") | H75: =IF(H$4>0,(IF(G75<>0,G75*H$4/100," ")),IF(G75<>0,G75*H$2/(100+H$2)," ")) | I75: =IF((G75<>0),G75-H75," ") | M75: =IF(G75<>0,G75-L75," ") | N75: =IF((G75-L75)<>0,N$1-A75," ") | P75: =IF((F75="a"),I75," ") | Q75: =IF((F75="b"),I75," ") | R75: =IF((F75="c"),I75," ") | S75: =IF((F75="d"),I75," ") | T75: =IF((F75="g"),I75," ") | U75: =IF((F75="o"),I75," ") | V75: =IF((F75="FS"),I75," ")
F76: =IF((G76<>0),"Enter Letter"," ") | H76: =IF(H$4>0,(IF(G76<>0,G76*H$4/100," ")),IF(G76<>0,G76*H$2/(100+H$2)," ")) | I76: =IF((G76<>0),G76-H76," ") | M76: =IF(G76<>0,G76-L76," ") | N76: =IF((G76-L76)<>0,N$1-A76," ") | P76: =IF((F76="a"),I76," ") | Q76: =IF((F76="b"),I76," ") | R76: =IF((F76="c"),I76," ") | S76: =IF((F76="d"),I76," ") | T76: =IF((F76="g"),I76," ") | U76: =IF((F76="o"),I76," ") | V76: =IF((F76="FS"),I76," ")
F77: =IF((G77<>0),"Enter Letter"," ") | H77: =IF(H$4>0,(IF(G77<>0,G77*H$4/100," ")),IF(G77<>0,G77*H$2/(100+H$2)," ")) | I77: =IF((G77<>0),G77-H77," ") | M77: =IF(G77<>0,G77-L77," ") | N77: =IF((G77-L77)<>0,N$1-A77," ") | P77: =IF((F77="a"),I77," ") | Q77: =IF((F77="b"),I77," ") | R77: =IF((F77="c"),I77," ") | S77: =IF((F77="d"),I77," ") | T77: =IF((F77="g"),I77," ") | U77: =IF((F77="o"),I77," ") | V77: =IF((F77="FS"),I77," ")
F78: =IF((G78<>0),"Enter Letter"," ") | H78: =IF(H$4>0,(IF(G78<>0,G78*H$4/100," ")),IF(G78<>0,G78*H$2/(100+H$2)," ")) | I78: =IF((G78<>0),G78-H78," ") | M78: =IF(G78<>0,G78-L78," ") | N78: =IF((G78-L78)<>0,N$1-A78," ") | P78: =IF((F78="a"),I78," ") | Q78: =IF((F78="b"),I78," ") | R78: =IF((F78="c"),I78," ") | S78: =IF((F78="d"),I78," ") | T78: =IF((F78="g"),I78," ") | U78: =IF((F78="o"),I78," ") | V78: =IF((F78="FS"),I78," ")
F79: =IF((G79<>0),"Enter Letter"," ") | H79: =IF(H$4>0,(IF(G79<>0,G79*H$4/100," ")),IF(G79<>0,G79*H$2/(100+H$2)," ")) | I79: =IF((G79<>0),G79-H79," ") | M79: =IF(G79<>0,G79-L79," ") | N79: =IF((G79-L79)<>0,N$1-A79," ") | P79: =IF((F79="a"),I79," ") | Q79: =IF((F79="b"),I79," ") | R79: =IF((F79="c"),I79," ") | S79: =IF((F79="d"),I79," ") | T79: =IF((F79="g"),I79," ") | U79: =IF((F79="o"),I79," ") | V79: =IF((F79="FS"),I79," ")
F80: =IF((G80<>0),"Enter Letter"," ") | H80: =IF(H$4>0,(IF(G80<>0,G80*H$4/100," ")),IF(G80<>0,G80*H$2/(100+H$2)," ")) | I80: =IF((G80<>0),G80-H80," ") | M80: =IF(G80<>0,G80-L80," ") | N80: =IF((G80-L80)<>0,N$1-A80," ") | P80: =IF((F80="a"),I80," ") | Q80: =IF((F80="b"),I80," ") | R80: =IF((F80="c"),I80," ") | S80: =IF((F80="d"),I80," ") | T80: =IF((F80="g"),I80," ") | U80: =IF((F80="o"),I80," ") | V80: =IF((F80="FS"),I80," ")
... F300: =IF((G300<>0),"Enter Letter"," ") | H300: =IF(H$4>0,(IF(G300<>0,G300*H$4/100," ")),IF(G300<>0,G300*H$2/(100+H$2)," ")) | I300: =IF((G300<>0),G300-H300," ") | M300: =IF(G300<>0,G300-L300," ") | N300: =IF((G300-L300)<>0,N$1-A300," ") | P300: =IF((F300="a"),I300," ") | Q300: =IF((F300="b"),I300," ") | R300: =IF((F300="c"),I300," ") | S300: =IF((F300="d"),I300," ") | T300: =IF((F300="g"),I300," ") | U300: =IF((F300="o"),I300," ") | V300: =IF((F300="FS"),I300," ")

Sheet Feb
A1: =G1-H1-SUM(P1:V1) -> 0 | B1: Check Total | C1: Sales Mileage | D1: =SUM(D5:D300) -> 0 | E1: Sales Description | F1: Enter Expense Code Letter | G1: =SUM(G5:G300) -> 34360 | H1: =SUM(H5:H300) -> 5726.6667 | I1: =SUM(I5:I300) -> 28633.333 | K1: For your information only. Enter How Paid e.g. Cash, Cheque etc., | L1: =SUM(L5:L300) -> 0 | M1: =SUM(M5:M300) -> 34360 | N1: =TODAY() -> 46295 | P1: =SUM(P5:P300) -> 26333.333 | Q1: =SUM(Q5:Q300) -> 800 | R1: =SUM(R5:R300) -> 1500 | S1: =SUM(S5:S300) -> 0 | T1: =SUM(T5:T300) -> 0 | U1: =SUM(U5:U300) -> 0 | V1: =SUM(V5:V300) -> 0 | W1: =SUM(W5:W300) -> 0 | X1: =W1+Jan!X1 -> 0
A2: Sales Date | B2: Customer Name | C2: Sales Invoice Number or reference | D2: Sales Mileage | G2: Sales Value including Vat | H2: =Jan!H2 -> 20 | I2: Sales Net of Vat | L2: Receipts from Customers | P2: Sales Net of Vat | S2: Other Income | T2: Investment Grants | U2: Bad Debts written off | V2: =V1+Jan!V2 -> 12500 | W2: Sub contractors only
H3: Vat Output | L3: Actual amount received | M3: Sales Value not yet received | N3: Number of Days Outstanding | P3: Product A | Q3: Product B | R3: Product C | V3: Sale of Fixed Assets | W3: CIS Tax Deducted | X3: CIS Certificate reference
H4: =Jan!H4 -> 0 | P4: A | Q4: B | R4: C | S4: D | T4: G | U4: O | V4: FS
A5: 46421 | B5: FreshField Ltd | C5: INV-2611 | E5: Software monitoring licence | F5: b | G5: 360 | H5: =IF(H$4>0,(IF(G5<>0,G5*H$4/100," ")),IF(G5<>0,G5*H$2/(100+H$2)," ")) -> 60 | I5: =IF((G5<>0),G5-H5," ") -> 300 | M5: =IF(G5<>0,G5-L5," ") -> 360 | N5: =IF((G5-L5)<>0,N$1-A5," ") -> -126 | P5: =IF((F5="a"),I5," ") | Q5: =IF((F5="b"),I5," ") -> 300 | R5: =IF((F5="c"),I5," ") | S5: =IF((F5="d"),I5," ") | T5: =IF((F5="g"),I5," ") | U5: =IF((F5="o"),I5," ") | V5: =IF((F5="FS"),I5," ") | BZ5: 4001
A6: 46423 | B6: CloudNine Ltd | C6: INV-1411 | E6: SaaS licence fee | F6: b | G6: 600 | H6: =IF(H$4>0,(IF(G6<>0,G6*H$4/100," ")),IF(G6<>0,G6*H$2/(100+H$2)," ")) -> 100 | I6: =IF((G6<>0),G6-H6," ") -> 500 | M6: =IF(G6<>0,G6-L6," ") -> 600 | N6: =IF((G6-L6)<>0,N$1-A6," ") -> -128 | P6: =IF((F6="a"),I6," ") | Q6: =IF((F6="b"),I6," ") -> 500 | R6: =IF((F6="c"),I6," ") | S6: =IF((F6="d"),I6," ") | T6: =IF((F6="g"),I6," ") | U6: =IF((F6="o"),I6," ") | V6: =IF((F6="FS"),I6," ") | BZ6: 4001
A7: 46426 | B7: Cedar Systems | C7: INV-2411 | E7: Managed services | F7: a | G7: 480 | H7: =IF(H$4>0,(IF(G7<>0,G7*H$4/100," ")),IF(G7<>0,G7*H$2/(100+H$2)," ")) -> 80 | I7: =IF((G7<>0),G7-H7," ") -> 400 | M7: =IF(G7<>0,G7-L7," ") -> 480 | N7: =IF((G7-L7)<>0,N$1-A7," ") -> -131 | P7: =IF((F7="a"),I7," ") -> 400 | Q7: =IF((F7="b"),I7," ") | R7: =IF((F7="c"),I7," ") | S7: =IF((F7="d"),I7," ") | T7: =IF((F7="g"),I7," ") | U7: =IF((F7="o"),I7," ") | V7: =IF((F7="FS"),I7," ") | BZ7: 4000
A8: 46428 | B8: Pinnacle Group | C8: INV-2211 | E8: Monthly support contract | F8: a | G8: 720 | H8: =IF(H$4>0,(IF(G8<>0,G8*H$4/100," ")),IF(G8<>0,G8*H$2/(100+H$2)," ")) -> 120 | I8: =IF((G8<>0),G8-H8," ") -> 600 | M8: =IF(G8<>0,G8-L8," ") -> 720 | N8: =IF((G8-L8)<>0,N$1-A8," ") -> -133 | P8: =IF((F8="a"),I8," ") -> 600 | Q8: =IF((F8="b"),I8," ") | R8: =IF((F8="c"),I8," ") | S8: =IF((F8="d"),I8," ") | T8: =IF((F8="g"),I8," ") | U8: =IF((F8="o"),I8," ") | V8: =IF((F8="FS"),I8," ") | BZ8: 4000
A9: 46433 | B9: Acme Corp | C9: INV-1011 | E9: IT consultancy services | F9: a | G9: 25000 | H9: =IF(H$4>0,(IF(G9<>0,G9*H$4/100," ")),IF(G9<>0,G9*H$2/(100+H$2)," ")) -> 4166.6667 | I9: =IF((G9<>0),G9-H9," ") -> 20833.333 | M9: =IF(G9<>0,G9-L9," ") -> 25000 | N9: =IF((G9-L9)<>0,N$1-A9," ") -> -138 | P9: =IF((F9="a"),I9," ") -> 20833.333 | Q9: =IF((F9="b"),I9," ") | R9: =IF((F9="c"),I9," ") | S9: =IF((F9="d"),I9," ") | T9: =IF((F9="g"),I9," ") | U9: =IF((F9="o"),I9," ") | V9: =IF((F9="FS"),I9," ") | BZ9: 4000
A10: 46436 | B10: TechStart Ltd | C10: INV-1111 | E10: IT consultancy retainer | F10: a | G10: 2400 | H10: =IF(H$4>0,(IF(G10<>0,G10*H$4/100," ")),IF(G10<>0,G10*H$2/(100+H$2)," ")) -> 400 | I10: =IF((G10<>0),G10-H10," ") -> 2000 | M10: =IF(G10<>0,G10-L10," ") -> 2400 | N10: =IF((G10-L10)<>0,N$1-A10," ") -> -141 | P10: =IF((F10="a"),I10," ") -> 2000 | Q10: =IF((F10="b"),I10," ") | R10: =IF((F10="c"),I10," ") | S10: =IF((F10="d"),I10," ") | T10: =IF((F10="g"),I10," ") | U10: =IF((F10="o"),I10," ") | V10: =IF((F10="FS"),I10," ") | BZ10: 4000
A11: 46438 | B11: DataFlow Inc | C11: INV-1206 | E11: Ad-hoc consultancy project | F11: a | G11: 1800 | H11: =IF(H$4>0,(IF(G11<>0,G11*H$4/100," ")),IF(G11<>0,G11*H$2/(100+H$2)," ")) -> 300 | I11: =IF((G11<>0),G11-H11," ") -> 1500 | M11: =IF(G11<>0,G11-L11," ") -> 1800 | N11: =IF((G11-L11)<>0,N$1-A11," ") -> -143 | P11: =IF((F11="a"),I11," ") -> 1500 | Q11: =IF((F11="b"),I11," ") | R11: =IF((F11="c"),I11," ") | S11: =IF((F11="d"),I11," ") | T11: =IF((F11="g"),I11," ") | U11: =IF((F11="o"),I11," ") | V11: =IF((F11="FS"),I11," ") | BZ11: 4000
A12: 46438 | B12: MegaCorp | C12: INV-1503 | E12: Security awareness training | F12: c | G12: 1800 | H12: =IF(H$4>0,(IF(G12<>0,G12*H$4/100," ")),IF(G12<>0,G12*H$2/(100+H$2)," ")) -> 300 | I12: =IF((G12<>0),G12-H12," ") -> 1500 | M12: =IF(G12<>0,G12-L12," ") -> 1800 | N12: =IF((G12-L12)<>0,N$1-A12," ") -> -143 | P12: =IF((F12="a"),I12," ") | Q12: =IF((F12="b"),I12," ") | R12: =IF((F12="c"),I12," ") -> 1500 | S12: =IF((F12="d"),I12," ") | T12: =IF((F12="g"),I12," ") | U12: =IF((F12="o"),I12," ") | V12: =IF((F12="FS"),I12," ") | BZ12: 4002
A13: 46443 | B13: Oakridge Partners | C13: INV-2504 | E13: Quarterly consulting engagement | F13: a | G13: 1200 | H13: =IF(H$4>0,(IF(G13<>0,G13*H$4/100," ")),IF(G13<>0,G13*H$2/(100+H$2)," ")) -> 200 | I13: =IF((G13<>0),G13-H13," ") -> 1000 | M13: =IF(G13<>0,G13-L13," ") -> 1200 | N13: =IF((G13-L13)<>0,N$1-A13," ") -> -148 | P13: =IF((F13="a"),I13," ") -> 1000 | Q13: =IF((F13="b"),I13," ") | R13: =IF((F13="c"),I13," ") | S13: =IF((F13="d"),I13," ") | T13: =IF((F13="g"),I13," ") | U13: =IF((F13="o"),I13," ") | V13: =IF((F13="FS"),I13," ") | BZ13: 4000
H14: =IF(H$4>0,(IF(G14<>0,G14*H$4/100," ")),IF(G14<>0,G14*H$2/(100+H$2)," ")) | I14: =IF((G14<>0),G14-H14," ") | M14: =IF(G14<>0,G14-L14," ") | N14: =IF((G14-L14)<>0,N$1-A14," ") | P14: =IF((F14="a"),I14," ") | Q14: =IF((F14="b"),I14," ") | R14: =IF((F14="c"),I14," ") | S14: =IF((F14="d"),I14," ") | T14: =IF((F14="g"),I14," ") | U14: =IF((F14="o"),I14," ") | V14: =IF((F14="FS"),I14," ")
H15: =IF(H$4>0,(IF(G15<>0,G15*H$4/100," ")),IF(G15<>0,G15*H$2/(100+H$2)," ")) | I15: =IF((G15<>0),G15-H15," ") | M15: =IF(G15<>0,G15-L15," ") | N15: =IF((G15-L15)<>0,N$1-A15," ") | P15: =IF((F15="a"),I15," ") | Q15: =IF((F15="b"),I15," ") | R15: =IF((F15="c"),I15," ") | S15: =IF((F15="d"),I15," ") | T15: =IF((F15="g"),I15," ") | U15: =IF((F15="o"),I15," ") | V15: =IF((F15="FS"),I15," ")
H16: =IF(H$4>0,(IF(G16<>0,G16*H$4/100," ")),IF(G16<>0,G16*H$2/(100+H$2)," ")) | I16: =IF((G16<>0),G16-H16," ") | M16: =IF(G16<>0,G16-L16," ") | N16: =IF((G16-L16)<>0,N$1-A16," ") | P16: =IF((F16="a"),I16," ") | Q16: =IF((F16="b"),I16," ") | R16: =IF((F16="c"),I16," ") | S16: =IF((F16="d"),I16," ") | T16: =IF((F16="g"),I16," ") | U16: =IF((F16="o"),I16," ") | V16: =IF((F16="FS"),I16," ")
H17: =IF(H$4>0,(IF(G17<>0,G17*H$4/100," ")),IF(G17<>0,G17*H$2/(100+H$2)," ")) | I17: =IF((G17<>0),G17-H17," ") | M17: =IF(G17<>0,G17-L17," ") | N17: =IF((G17-L17)<>0,N$1-A17," ") | P17: =IF((F17="a"),I17," ") | Q17: =IF((F17="b"),I17," ") | R17: =IF((F17="c"),I17," ") | S17: =IF((F17="d"),I17," ") | T17: =IF((F17="g"),I17," ") | U17: =IF((F17="o"),I17," ") | V17: =IF((F17="FS"),I17," ")
H18: =IF(H$4>0,(IF(G18<>0,G18*H$4/100," ")),IF(G18<>0,G18*H$2/(100+H$2)," ")) | I18: =IF((G18<>0),G18-H18," ") | M18: =IF(G18<>0,G18-L18," ") | N18: =IF((G18-L18)<>0,N$1-A18," ") | P18: =IF((F18="a"),I18," ") | Q18: =IF((F18="b"),I18," ") | R18: =IF((F18="c"),I18," ") | S18: =IF((F18="d"),I18," ") | T18: =IF((F18="g"),I18," ") | U18: =IF((F18="o"),I18," ") | V18: =IF((F18="FS"),I18," ")
H19: =IF(H$4>0,(IF(G19<>0,G19*H$4/100," ")),IF(G19<>0,G19*H$2/(100+H$2)," ")) | I19: =IF((G19<>0),G19-H19," ") | M19: =IF(G19<>0,G19-L19," ") | N19: =IF((G19-L19)<>0,N$1-A19," ") | P19: =IF((F19="a"),I19," ") | Q19: =IF((F19="b"),I19," ") | R19: =IF((F19="c"),I19," ") | S19: =IF((F19="d"),I19," ") | T19: =IF((F19="g"),I19," ") | U19: =IF((F19="o"),I19," ") | V19: =IF((F19="FS"),I19," ")
H20: =IF(H$4>0,(IF(G20<>0,G20*H$4/100," ")),IF(G20<>0,G20*H$2/(100+H$2)," ")) | I20: =IF((G20<>0),G20-H20," ") | M20: =IF(G20<>0,G20-L20," ") | N20: =IF((G20-L20)<>0,N$1-A20," ") | P20: =IF((F20="a"),I20," ") | Q20: =IF((F20="b"),I20," ") | R20: =IF((F20="c"),I20," ") | S20: =IF((F20="d"),I20," ") | T20: =IF((F20="g"),I20," ") | U20: =IF((F20="o"),I20," ") | V20: =IF((F20="FS"),I20," ")
H21: =IF(H$4>0,(IF(G21<>0,G21*H$4/100," ")),IF(G21<>0,G21*H$2/(100+H$2)," ")) | I21: =IF((G21<>0),G21-H21," ") | M21: =IF(G21<>0,G21-L21," ") | N21: =IF((G21-L21)<>0,N$1-A21," ") | P21: =IF((F21="a"),I21," ") | Q21: =IF((F21="b"),I21," ") | R21: =IF((F21="c"),I21," ") | S21: =IF((F21="d"),I21," ") | T21: =IF((F21="g"),I21," ") | U21: =IF((F21="o"),I21," ") | V21: =IF((F21="FS"),I21," ")
H22: =IF(H$4>0,(IF(G22<>0,G22*H$4/100," ")),IF(G22<>0,G22*H$2/(100+H$2)," ")) | I22: =IF((G22<>0),G22-H22," ") | M22: =IF(G22<>0,G22-L22," ") | N22: =IF((G22-L22)<>0,N$1-A22," ") | P22: =IF((F22="a"),I22," ") | Q22: =IF((F22="b"),I22," ") | R22: =IF((F22="c"),I22," ") | S22: =IF((F22="d"),I22," ") | T22: =IF((F22="g"),I22," ") | U22: =IF((F22="o"),I22," ") | V22: =IF((F22="FS"),I22," ")
H23: =IF(H$4>0,(IF(G23<>0,G23*H$4/100," ")),IF(G23<>0,G23*H$2/(100+H$2)," ")) | I23: =IF((G23<>0),G23-H23," ") | M23: =IF(G23<>0,G23-L23," ") | N23: =IF((G23-L23)<>0,N$1-A23," ") | P23: =IF((F23="a"),I23," ") | Q23: =IF((F23="b"),I23," ") | R23: =IF((F23="c"),I23," ") | S23: =IF((F23="d"),I23," ") | T23: =IF((F23="g"),I23," ") | U23: =IF((F23="o"),I23," ") | V23: =IF((F23="FS"),I23," ")
H24: =IF(H$4>0,(IF(G24<>0,G24*H$4/100," ")),IF(G24<>0,G24*H$2/(100+H$2)," ")) | I24: =IF((G24<>0),G24-H24," ") | M24: =IF(G24<>0,G24-L24," ") | N24: =IF((G24-L24)<>0,N$1-A24," ") | P24: =IF((F24="a"),I24," ") | Q24: =IF((F24="b"),I24," ") | R24: =IF((F24="c"),I24," ") | S24: =IF((F24="d"),I24," ") | T24: =IF((F24="g"),I24," ") | U24: =IF((F24="o"),I24," ") | V24: =IF((F24="FS"),I24," ")
H25: =IF(H$4>0,(IF(G25<>0,G25*H$4/100," ")),IF(G25<>0,G25*H$2/(100+H$2)," ")) | I25: =IF((G25<>0),G25-H25," ") | M25: =IF(G25<>0,G25-L25," ") | N25: =IF((G25-L25)<>0,N$1-A25," ") | P25: =IF((F25="a"),I25," ") | Q25: =IF((F25="b"),I25," ") | R25: =IF((F25="c"),I25," ") | S25: =IF((F25="d"),I25," ") | T25: =IF((F25="g"),I25," ") | U25: =IF((F25="o"),I25," ") | V25: =IF((F25="FS"),I25," ")
... H68: =IF(H$4>0,(IF(G68<>0,G68*H$4/100," ")),IF(G68<>0,G68*H$2/(100+H$2)," ")) | I68: =IF((G68<>0),G68-H68," ") | M68: =IF(G68<>0,G68-L68," ") | N68: =IF((G68-L68)<>0,N$1-A68," ") | P68: =IF((F68="a"),I68," ") | Q68: =IF((F68="b"),I68," ") | R68: =IF((F68="c"),I68," ") | S68: =IF((F68="d"),I68," ") | T68: =IF((F68="g"),I68," ") | U68: =IF((F68="o"),I68," ") | V68: =IF((F68="FS"),I68," ")
F69: =IF((G69<>0),"Enter Letter"," ") | H69: =IF(H$4>0,(IF(G69<>0,G69*H$4/100," ")),IF(G69<>0,G69*H$2/(100+H$2)," ")) | I69: =IF((G69<>0),G69-H69," ") | M69: =IF(G69<>0,G69-L69," ") | N69: =IF((G69-L69)<>0,N$1-A69," ") | P69: =IF((F69="a"),I69," ") | Q69: =IF((F69="b"),I69," ") | R69: =IF((F69="c"),I69," ") | S69: =IF((F69="d"),I69," ") | T69: =IF((F69="g"),I69," ") | U69: =IF((F69="o"),I69," ") | V69: =IF((F69="FS"),I69," ")
F70: =IF((G70<>0),"Enter Letter"," ") | H70: =IF(H$4>0,(IF(G70<>0,G70*H$4/100," ")),IF(G70<>0,G70*H$2/(100+H$2)," ")) | I70: =IF((G70<>0),G70-H70," ") | M70: =IF(G70<>0,G70-L70," ") | N70: =IF((G70-L70)<>0,N$1-A70," ") | P70: =IF((F70="a"),I70," ") | Q70: =IF((F70="b"),I70," ") | R70: =IF((F70="c"),I70," ") | S70: =IF((F70="d"),I70," ") | T70: =IF((F70="g"),I70," ") | U70: =IF((F70="o"),I70," ") | V70: =IF((F70="FS"),I70," ")
F71: =IF((G71<>0),"Enter Letter"," ") | H71: =IF(H$4>0,(IF(G71<>0,G71*H$4/100," ")),IF(G71<>0,G71*H$2/(100+H$2)," ")) | I71: =IF((G71<>0),G71-H71," ") | M71: =IF(G71<>0,G71-L71," ") | N71: =IF((G71-L71)<>0,N$1-A71," ") | P71: =IF((F71="a"),I71," ") | Q71: =IF((F71="b"),I71," ") | R71: =IF((F71="c"),I71," ") | S71: =IF((F71="d"),I71," ") | T71: =IF((F71="g"),I71," ") | U71: =IF((F71="o"),I71," ") | V71: =IF((F71="FS"),I71," ")
F72: =IF((G72<>0),"Enter Letter"," ") | H72: =IF(H$4>0,(IF(G72<>0,G72*H$4/100," ")),IF(G72<>0,G72*H$2/(100+H$2)," ")) | I72: =IF((G72<>0),G72-H72," ") | M72: =IF(G72<>0,G72-L72," ") | N72: =IF((G72-L72)<>0,N$1-A72," ") | P72: =IF((F72="a"),I72," ") | Q72: =IF((F72="b"),I72," ") | R72: =IF((F72="c"),I72," ") | S72: =IF((F72="d"),I72," ") | T72: =IF((F72="g"),I72," ") | U72: =IF((F72="o"),I72," ") | V72: =IF((F72="FS"),I72," ")
F73: =IF((G73<>0),"Enter Letter"," ") | H73: =IF(H$4>0,(IF(G73<>0,G73*H$4/100," ")),IF(G73<>0,G73*H$2/(100+H$2)," ")) | I73: =IF((G73<>0),G73-H73," ") | M73: =IF(G73<>0,G73-L73," ") | N73: =IF((G73-L73)<>0,N$1-A73," ") | P73: =IF((F73="a"),I73," ") | Q73: =IF((F73="b"),I73," ") | R73: =IF((F73="c"),I73," ") | S73: =IF((F73="d"),I73," ") | T73: =IF((F73="g"),I73," ") | U73: =IF((F73="o"),I73," ") | V73: =IF((F73="FS"),I73," ")
F74: =IF((G74<>0),"Enter Letter"," ") | H74: =IF(H$4>0,(IF(G74<>0,G74*H$4/100," ")),IF(G74<>0,G74*H$2/(100+H$2)," ")) | I74: =IF((G74<>0),G74-H74," ") | M74: =IF(G74<>0,G74-L74," ") | N74: =IF((G74-L74)<>0,N$1-A74," ") | P74: =IF((F74="a"),I74," ") | Q74: =IF((F74="b"),I74," ") | R74: =IF((F74="c"),I74," ") | S74: =IF((F74="d"),I74," ") | T74: =IF((F74="g"),I74," ") | U74: =IF((F74="o"),I74," ") | V74: =IF((F74="FS"),I74," ")
F75: =IF((G75<>0),"Enter Letter"," ") | H75: =IF(H$4>0,(IF(G75<>0,G75*H$4/100," ")),IF(G75<>0,G75*H$2/(100+H$2)," ")) | I75: =IF((G75<>0),G75-H75," ") | M75: =IF(G75<>0,G75-L75," ") | N75: =IF((G75-L75)<>0,N$1-A75," ") | P75: =IF((F75="a"),I75," ") | Q75: =IF((F75="b"),I75," ") | R75: =IF((F75="c"),I75," ") | S75: =IF((F75="d"),I75," ") | T75: =IF((F75="g"),I75," ") | U75: =IF((F75="o"),I75," ") | V75: =IF((F75="FS"),I75," ")
F76: =IF((G76<>0),"Enter Letter"," ") | H76: =IF(H$4>0,(IF(G76<>0,G76*H$4/100," ")),IF(G76<>0,G76*H$2/(100+H$2)," ")) | I76: =IF((G76<>0),G76-H76," ") | M76: =IF(G76<>0,G76-L76," ") | N76: =IF((G76-L76)<>0,N$1-A76," ") | P76: =IF((F76="a"),I76," ") | Q76: =IF((F76="b"),I76," ") | R76: =IF((F76="c"),I76," ") | S76: =IF((F76="d"),I76," ") | T76: =IF((F76="g"),I76," ") | U76: =IF((F76="o"),I76," ") | V76: =IF((F76="FS"),I76," ")
F77: =IF((G77<>0),"Enter Letter"," ") | H77: =IF(H$4>0,(IF(G77<>0,G77*H$4/100," ")),IF(G77<>0,G77*H$2/(100+H$2)," ")) | I77: =IF((G77<>0),G77-H77," ") | M77: =IF(G77<>0,G77-L77," ") | N77: =IF((G77-L77)<>0,N$1-A77," ") | P77: =IF((F77="a"),I77," ") | Q77: =IF((F77="b"),I77," ") | R77: =IF((F77="c"),I77," ") | S77: =IF((F77="d"),I77," ") | T77: =IF((F77="g"),I77," ") | U77: =IF((F77="o"),I77," ") | V77: =IF((F77="FS"),I77," ")
F78: =IF((G78<>0),"Enter Letter"," ") | H78: =IF(H$4>0,(IF(G78<>0,G78*H$4/100," ")),IF(G78<>0,G78*H$2/(100+H$2)," ")) | I78: =IF((G78<>0),G78-H78," ") | M78: =IF(G78<>0,G78-L78," ") | N78: =IF((G78-L78)<>0,N$1-A78," ") | P78: =IF((F78="a"),I78," ") | Q78: =IF((F78="b"),I78," ") | R78: =IF((F78="c"),I78," ") | S78: =IF((F78="d"),I78," ") | T78: =IF((F78="g"),I78," ") | U78: =IF((F78="o"),I78," ") | V78: =IF((F78="FS"),I78," ")
F79: =IF((G79<>0),"Enter Letter"," ") | H79: =IF(H$4>0,(IF(G79<>0,G79*H$4/100," ")),IF(G79<>0,G79*H$2/(100+H$2)," ")) | I79: =IF((G79<>0),G79-H79," ") | M79: =IF(G79<>0,G79-L79," ") | N79: =IF((G79-L79)<>0,N$1-A79," ") | P79: =IF((F79="a"),I79," ") | Q79: =IF((F79="b"),I79," ") | R79: =IF((F79="c"),I79," ") | S79: =IF((F79="d"),I79," ") | T79: =IF((F79="g"),I79," ") | U79: =IF((F79="o"),I79," ") | V79: =IF((F79="FS"),I79," ")
F80: =IF((G80<>0),"Enter Letter"," ") | H80: =IF(H$4>0,(IF(G80<>0,G80*H$4/100," ")),IF(G80<>0,G80*H$2/(100+H$2)," ")) | I80: =IF((G80<>0),G80-H80," ") | M80: =IF(G80<>0,G80-L80," ") | N80: =IF((G80-L80)<>0,N$1-A80," ") | P80: =IF((F80="a"),I80," ") | Q80: =IF((F80="b"),I80," ") | R80: =IF((F80="c"),I80," ") | S80: =IF((F80="d"),I80," ") | T80: =IF((F80="g"),I80," ") | U80: =IF((F80="o"),I80," ") | V80: =IF((F80="FS"),I80," ")
... F300: =IF((G300<>0),"Enter Letter"," ") | H300: =IF(H$4>0,(IF(G300<>0,G300*H$4/100," ")),IF(G300<>0,G300*H$2/(100+H$2)," ")) | I300: =IF((G300<>0),G300-H300," ") | M300: =IF(G300<>0,G300-L300," ") | N300: =IF((G300-L300)<>0,N$1-A300," ") | P300: =IF((F300="a"),I300," ") | Q300: =IF((F300="b"),I300," ") | R300: =IF((F300="c"),I300," ") | S300: =IF((F300="d"),I300," ") | T300: =IF((F300="g"),I300," ") | U300: =IF((F300="o"),I300," ") | V300: =IF((F300="FS"),I300," ")

Sheet Mar
A1: =G1-H1-SUM(P1:V1) -> 0 | B1: Check Total | C1: Sales Mileage | D1: =SUM(D5:D300) -> 0 | E1: Sales Description | F1: Enter Expense Code Letter | G1: =SUM(G5:G300) -> 31360 | H1: =SUM(H5:H300) -> 5226.6667 | I1: =SUM(I5:I300) -> 26133.333 | K1: For your information only. Enter How Paid e.g. Cash, Cheque etc., | L1: =SUM(L5:L300) -> 0 | M1: =SUM(M5:M300) -> 31360 | N1: =TODAY() -> 46295 | P1: =SUM(P5:P300) -> 25033.333 | Q1: =SUM(Q5:Q300) -> 800 | R1: =SUM(R5:R300) -> 0 | S1: =SUM(S5:S300) -> 0 | T1: =SUM(T5:T300) -> 0 | U1: =SUM(U5:U300) -> 300 | V1: =SUM(V5:V300) -> 0 | W1: =SUM(W5:W300) -> 0 | X1: =W1+Feb!X1 -> 0
A2: Sales Date | B2: Customer Name | C2: Sales Invoice Number or reference | D2: Sales Mileage | G2: Sales Value including Vat | H2: =Feb!H2 -> 20 | I2: Sales Net of Vat | L2: Receipts from Customers | P2: Sales Net of Vat | S2: Other Income | T2: Investment Grants | U2: Bad Debts written off | V2: =V1+Feb!V2 -> 12500 | W2: Sub contractors only
H3: Vat Output | L3: Actual amount received | M3: Sales Value not yet received | N3: Number of Days Outstanding | P3: Product A | Q3: Product B | R3: Product C | V3: Sale of Fixed Assets | W3: CIS Tax Deducted | X3: CIS Certificate reference
H4: =Feb!H4 -> 0 | P4: A | Q4: B | R4: C | S4: D | T4: G | U4: O | V4: FS
A5: 46449 | B5: FreshField Ltd | C5: INV-2612 | E5: Software monitoring licence | F5: b | G5: 360 | H5: =IF(H$4>0,(IF(G5<>0,G5*H$4/100," ")),IF(G5<>0,G5*H$2/(100+H$2)," ")) -> 60 | I5: =IF((G5<>0),G5-H5," ") -> 300 | M5: =IF(G5<>0,G5-L5," ") -> 360 | N5: =IF((G5-L5)<>0,N$1-A5," ") -> -154 | P5: =IF((F5="a"),I5," ") | Q5: =IF((F5="b"),I5," ") -> 300 | R5: =IF((F5="c"),I5," ") | S5: =IF((F5="d"),I5," ") | T5: =IF((F5="g"),I5," ") | U5: =IF((F5="o"),I5," ") | V5: =IF((F5="FS"),I5," ") | BZ5: 4001
A6: 46451 | B6: CloudNine Ltd | C6: INV-1412 | E6: SaaS licence fee | F6: b | G6: 600 | H6: =IF(H$4>0,(IF(G6<>0,G6*H$4/100," ")),IF(G6<>0,G6*H$2/(100+H$2)," ")) -> 100 | I6: =IF((G6<>0),G6-H6," ") -> 500 | M6: =IF(G6<>0,G6-L6," ") -> 600 | N6: =IF((G6-L6)<>0,N$1-A6," ") -> -156 | P6: =IF((F6="a"),I6," ") | Q6: =IF((F6="b"),I6," ") -> 500 | R6: =IF((F6="c"),I6," ") | S6: =IF((F6="d"),I6," ") | T6: =IF((F6="g"),I6," ") | U6: =IF((F6="o"),I6," ") | V6: =IF((F6="FS"),I6," ") | BZ6: 4001
A7: 46454 | B7: Cedar Systems | C7: INV-2412 | E7: Managed services | F7: a | G7: 480 | H7: =IF(H$4>0,(IF(G7<>0,G7*H$4/100," ")),IF(G7<>0,G7*H$2/(100+H$2)," ")) -> 80 | I7: =IF((G7<>0),G7-H7," ") -> 400 | M7: =IF(G7<>0,G7-L7," ") -> 480 | N7: =IF((G7-L7)<>0,N$1-A7," ") -> -159 | P7: =IF((F7="a"),I7," ") -> 400 | Q7: =IF((F7="b"),I7," ") | R7: =IF((F7="c"),I7," ") | S7: =IF((F7="d"),I7," ") | T7: =IF((F7="g"),I7," ") | U7: =IF((F7="o"),I7," ") | V7: =IF((F7="FS"),I7," ") | BZ7: 4000
A8: 46456 | B8: Pinnacle Group | C8: INV-2212 | E8: Monthly support contract | F8: a | G8: 720 | H8: =IF(H$4>0,(IF(G8<>0,G8*H$4/100," ")),IF(G8<>0,G8*H$2/(100+H$2)," ")) -> 120 | I8: =IF((G8<>0),G8-H8," ") -> 600 | M8: =IF(G8<>0,G8-L8," ") -> 720 | N8: =IF((G8-L8)<>0,N$1-A8," ") -> -161 | P8: =IF((F8="a"),I8," ") -> 600 | Q8: =IF((F8="b"),I8," ") | R8: =IF((F8="c"),I8," ") | S8: =IF((F8="d"),I8," ") | T8: =IF((F8="g"),I8," ") | U8: =IF((F8="o"),I8," ") | V8: =IF((F8="FS"),I8," ") | BZ8: 4000
A9: 46461 | B9: Acme Corp | C9: INV-1012 | E9: IT consultancy services | F9: a | G9: 25000 | H9: =IF(H$4>0,(IF(G9<>0,G9*H$4/100," ")),IF(G9<>0,G9*H$2/(100+H$2)," ")) -> 4166.6667 | I9: =IF((G9<>0),G9-H9," ") -> 20833.333 | M9: =IF(G9<>0,G9-L9," ") -> 25000 | N9: =IF((G9-L9)<>0,N$1-A9," ") -> -166 | P9: =IF((F9="a"),I9," ") -> 20833.333 | Q9: =IF((F9="b"),I9," ") | R9: =IF((F9="c"),I9," ") | S9: =IF((F9="d"),I9," ") | T9: =IF((F9="g"),I9," ") | U9: =IF((F9="o"),I9," ") | V9: =IF((F9="FS"),I9," ") | BZ9: 4000
A10: 46464 | B10: TechStart Ltd | C10: INV-1112 | E10: IT consultancy retainer | F10: a | G10: 2400 | H10: =IF(H$4>0,(IF(G10<>0,G10*H$4/100," ")),IF(G10<>0,G10*H$2/(100+H$2)," ")) -> 400 | I10: =IF((G10<>0),G10-H10," ") -> 2000 | M10: =IF(G10<>0,G10-L10," ") -> 2400 | N10: =IF((G10-L10)<>0,N$1-A10," ") -> -169 | P10: =IF((F10="a"),I10," ") -> 2000 | Q10: =IF((F10="b"),I10," ") | R10: =IF((F10="c"),I10," ") | S10: =IF((F10="d"),I10," ") | T10: =IF((F10="g"),I10," ") | U10: =IF((F10="o"),I10," ") | V10: =IF((F10="FS"),I10," ") | BZ10: 4000
A11: 46468 | B11: WidgetWorks | C11: INV-2104 | E11: Project consultancy | F11: a | G11: 1440 | H11: =IF(H$4>0,(IF(G11<>0,G11*H$4/100," ")),IF(G11<>0,G11*H$2/(100+H$2)," ")) -> 240 | I11: =IF((G11<>0),G11-H11," ") -> 1200 | M11: =IF(G11<>0,G11-L11," ") -> 1440 | N11: =IF((G11-L11)<>0,N$1-A11," ") -> -173 | P11: =IF((F11="a"),I11," ") -> 1200 | Q11: =IF((F11="b"),I11," ") | R11: =IF((F11="c"),I11," ") | S11: =IF((F11="d"),I11," ") | T11: =IF((F11="g"),I11," ") | U11: =IF((F11="o"),I11," ") | V11: =IF((F11="FS"),I11," ") | BZ11: 4000
A12: 46477 | B12: Zeta Corp | C12: CN-1801 | E12: Bad debt written off | F12: o | G12: 360 | H12: =IF(H$4>0,(IF(G12<>0,G12*H$4/100," ")),IF(G12<>0,G12*H$2/(100+H$2)," ")) -> 60 | I12: =IF((G12<>0),G12-H12," ") -> 300 | M12: =IF(G12<>0,G12-L12," ") -> 360 | N12: =IF((G12-L12)<>0,N$1-A12," ") -> -182 | P12: =IF((F12="a"),I12," ") | Q12: =IF((F12="b"),I12," ") | R12: =IF((F12="c"),I12," ") | S12: =IF((F12="d"),I12," ") | T12: =IF((F12="g"),I12," ") | U12: =IF((F12="o"),I12," ") -> 300 | V12: =IF((F12="FS"),I12," ") | BZ12: 4005
H13: =IF(H$4>0,(IF(G13<>0,G13*H$4/100," ")),IF(G13<>0,G13*H$2/(100+H$2)," ")) | I13: =IF((G13<>0),G13-H13," ") | M13: =IF(G13<>0,G13-L13," ") | N13: =IF((G13-L13)<>0,N$1-A13," ") | P13: =IF((F13="a"),I13," ") | Q13: =IF((F13="b"),I13," ") | R13: =IF((F13="c"),I13," ") | S13: =IF((F13="d"),I13," ") | T13: =IF((F13="g"),I13," ") | U13: =IF((F13="o"),I13," ") | V13: =IF((F13="FS"),I13," ")
H14: =IF(H$4>0,(IF(G14<>0,G14*H$4/100," ")),IF(G14<>0,G14*H$2/(100+H$2)," ")) | I14: =IF((G14<>0),G14-H14," ") | M14: =IF(G14<>0,G14-L14," ") | N14: =IF((G14-L14)<>0,N$1-A14," ") | P14: =IF((F14="a"),I14," ") | Q14: =IF((F14="b"),I14," ") | R14: =IF((F14="c"),I14," ") | S14: =IF((F14="d"),I14," ") | T14: =IF((F14="g"),I14," ") | U14: =IF((F14="o"),I14," ") | V14: =IF((F14="FS"),I14," ")
H15: =IF(H$4>0,(IF(G15<>0,G15*H$4/100," ")),IF(G15<>0,G15*H$2/(100+H$2)," ")) | I15: =IF((G15<>0),G15-H15," ") | M15: =IF(G15<>0,G15-L15," ") | N15: =IF((G15-L15)<>0,N$1-A15," ") | P15: =IF((F15="a"),I15," ") | Q15: =IF((F15="b"),I15," ") | R15: =IF((F15="c"),I15," ") | S15: =IF((F15="d"),I15," ") | T15: =IF((F15="g"),I15," ") | U15: =IF((F15="o"),I15," ") | V15: =IF((F15="FS"),I15," ")
