Workbook

Sheet Employee
W2: =Admin!B2 -> 45753 | X2: 1
B3: BUSINESS DETAILS | H3: DIY Accounting Payslip Generator | Q3: www.diyaccounting.co.uk | W3: =Admin!B3 -> 45754 | X3: =X2+1 -> 2
W4: =Admin!B4 -> 45755 | X4: =X3+1 -> 3
B5: Business name | H5: Complete Employee details below and add calculated tax and wages to the monthly sheets (Apr22, May22, etc…), then switch to the Payslips sheet to generate payslips by selecting W or M (weekly/monthly) and the week or month number. | V5: M | W5: =Admin!B5 -> 45756 | X5: =X4+1 -> 4
B6: Address line 1 | V6: F | W6: =Admin!B6 -> 45757 | X6: =X5+1 -> 5
B7: City | V7: W | W7: =Admin!B7 -> 45758 | X7: =X6+1 -> 6
V8: M | W8: =Admin!B8 -> 45759 | X8: =X7+1 -> 7
B9: Post code | K9: Financial tax year | M9: =Admin!B2 -> 45753 | O9: =Admin!I1 -> 46117 | W9: =Admin!B9 -> 45760 | X9: =X8+1 -> 8
V10: D | W10: =Admin!B10 -> 45761 | X10: =X9+1 -> 9
W11: =Admin!B11 -> 45762 | X11: =X10+1 -> 10
V12: W1 | W12: =Admin!B12 -> 45763 | X12: =X11+1 -> 11
B13: EMPLOYEE DETAILS 01 | H13: * Bank details are optional | K13: NATIONAL INSURANCE | V13: M1 | W13: =Admin!B13 -> 45764 | X13: =X12+1 -> 12
W14: =Admin!B14 -> 45765 | X14: =X13+1 -> 13
B15: Employee surname use Capitals | H15: *Account name | K15: National Insurance number | W15: =Admin!B15 -> 45766 | X15: =X14+1 -> 14
B16: Employee forename(s) | W16: =Admin!B16 -> 45767 | X16: =X15+1 -> 15
H17: *Account number | W17: =Admin!B17 -> 45768 | X17: =X16+1 -> 16
W18: =Admin!B18 -> 45769 | X18: =X17+1 -> 17
H19: *Bank name | W19: =Admin!B19 -> 45770 | X19: =X18+1 -> 18
W20: =Admin!B20 -> 45771 | X20: =X19+1 -> 19
H21: *Sort code | W21: =Admin!B21 -> 45772 | X21: =X20+1 -> 20
W22: =Admin!B22 -> 45773 | X22: =X21+1 -> 21
F23: Wk/Mth no | W23: =Admin!B23 -> 45774 | X23: =X22+1 -> 22
B24: ="Starting date (existing = " & TEXT(M9,"dd/mm/yy") & ")" -> Starting date (existing = 06/04/25) | F24: =IF(D24=0," ",IF(D28="W",LOOKUP(D24,Admin!B:B,Admin!C:C),IF(D28="M",LOOKUP(D24,Admin!B:B,Admin!D:D),LOOKUP(D24,Admin!B:B,Admin!C:C)))) | Q24: =IF(O24>0,"Enter Date"," ") | S24: =IF(Q24=" "," ",IF(D28="W",LOOKUP(Q24,Admin!B:B,Admin!C:C),IF(D28="m",LOOKUP(Q24,Admin!B:B,Admin!D:D),"Check D28"))) | W24: =Admin!B24 -> 45775 | X24: =X23+1 -> 23
W25: =Admin!B25 -> 45776 | X25: =X24+1 -> 24
B26: Leaving date (dd/mm/yyyy) | F26: =IF(D24=0," ",IF(D26=0," ",IF(D28="W",LOOKUP(D26,Admin!B:B,Admin!C:C),IF(D28="M",LOOKUP(D26,Admin!B:B,Admin!D:D),LOOKUP(D26,Admin!B:B,Admin!C:C))))) | W26: =Admin!B26 -> 45777 | X26: =X25+1 -> 25
Q27: =IF(M27>0,D24," ") | S27: =IF(Q27=" "," ",IF(D28="W",LOOKUP(Q27,Admin!B:B,Admin!C:C),IF(D28="m",LOOKUP(Q27,Admin!B:B,Admin!D:D),"Check D28"))) | W27: =Admin!B27 -> 45778 | X27: =X26+1 -> 26
B28: Paid monthly or weekly? | F28: =IF(D30="D","Enter M for Director","Enter M or W for Employee") -> Enter M or W for Employee | Q28: =IF(M28>0,"Enter Date"," ") | S28: =IF(Q28=" "," ",IF(D28="W",LOOKUP(Q28,Admin!B:B,Admin!C:C),IF(D28="m",LOOKUP(Q28,Admin!B:B,Admin!D:D),"Check D28"))) | W28: =Admin!B28 -> 45779 | X28: =X27+1 -> 27
B29: Payroll number | D29: 1 | Q29: =IF(M29>0,"Enter Date"," ") | S29: =IF(Q29=" "," ",IF(D28="W",LOOKUP(Q29,Admin!B:B,Admin!C:C),IF(D28="m",LOOKUP(Q29,Admin!B:B,Admin!D:D),"Check D28"))) | W29: =Admin!B29 -> 45780 | X29: =X28+1 -> 28
B30: Limited Companies Only | F30: Enter D for Director | Q30: =IF(M30>0,"Enter Date"," ") | S30: =IF(Q30=" "," ",IF(D28="W",LOOKUP(Q30,Admin!B:B,Admin!C:C),IF(D28="m",LOOKUP(Q30,Admin!B:B,Admin!D:D),"Check D28"))) | W30: =Admin!B30 -> 45781 | X30: =X29+1 -> 29
W31: =Admin!B31 -> 45782 | X31: =X30+1 -> 30
W32: =Admin!B32 -> 45783 | X32: =X31+1 -> 31
W33: =Admin!B33 -> 45784 | X33: =X32+1 -> 32
Q34: =IF(O34="Y","Enter Date"," ") | W34: =Admin!B34 -> 45785 | X34: =X33+1 -> 33
W35: =Admin!B35 -> 45786 | X35: =X34+1 -> 34
W36: =Admin!B36 -> 45787 | X36: =X35+1 -> 35
W37: =Admin!B37 -> 45788 | X37: =X36+1 -> 36
W38: =Admin!B38 -> 45789 | X38: =X37+1 -> 37
B39: EMPLOYEE DETAILS 02 | H39: * Bank details are optional | K39: NATIONAL INSURANCE | W39: =Admin!B39 -> 45790 | X39: =X38+1 -> 38
W40: =Admin!B40 -> 45791 | X40: =X39+1 -> 39
B41: Employee surname | H41: *Account name | K41: National Insurance number | W41: =Admin!B41 -> 45792 | X41: =X40+1 -> 40
B42: Employee forename(s) | W42: =Admin!B42 -> 45793 | X42: =X41+1 -> 41
H43: *Account number | W43: =Admin!B43 -> 45794 | X43: =X42+1 -> 42
W44: =Admin!B44 -> 45795 | X44: =X43+1 -> 43
H45: *Bank name | W45: =Admin!B45 -> 45796 | X45: =X44+1 -> 44
W46: =Admin!B46 -> 45797 | X46: =X45+1 -> 45
H47: *Sort code | W47: =Admin!B47 -> 45798 | X47: =X46+1 -> 46
W48: =Admin!B48 -> 45799 | X48: =X47+1 -> 47
F49: Wk/Mth no | W49: =Admin!B49 -> 45800 | X49: =X48+1 -> 48
B50: =B24 -> Starting date (existing = 06/04/25) | F50: =IF(D50=0," ",IF(D54="W",LOOKUP(D50,Admin!B:B,Admin!C:C),IF(D54="M",LOOKUP(D50,Admin!B:B,Admin!D:D),LOOKUP(D50,Admin!B:B,Admin!C:C)))) | W50: =Admin!B50 -> 45801 | X50: =X49+1 -> 49
W51: =Admin!B51 -> 45802 | X51: =X50+1 -> 50
B52: Leaving date (dd/mm/yyyy) | F52: =IF(D50=0," ",IF(D52=0," ",IF(D54="W",LOOKUP(D52,Admin!B:B,Admin!C:C),IF(D54="M",LOOKUP(D52,Admin!B:B,Admin!D:D),LOOKUP(D52,Admin!B:B,Admin!C:C))))) | W52: =Admin!B52 -> 45803 | X52: =X51+1 -> 51
W53: =Admin!B53 -> 45804 | X53: =X52+1 -> 52
B54: Paid monthly or weekly? | F54: =IF(D56="D","Enter M for Director","Enter M or W for Employee") -> Enter M or W for Employee | W54: =Admin!B54 -> 45805 | X54: 53
B55: Payroll number | D55: 2 | W55: =Admin!B55 -> 45806
B56: Limited Companies Only | F56: Enter D for Director | W56: =Admin!B56 -> 45807
W57: =Admin!B57 -> 45808
W58: =Admin!B58 -> 45809
W59: =Admin!B59 -> 45810
W60: =Admin!B60 -> 45811
W61: =Admin!B61 -> 45812
W62: =Admin!B62 -> 45813
W63: =Admin!B63 -> 45814
W64: =Admin!B64 -> 45815
B65: EMPLOYEE DETAILS 03 | H65: * Bank details are optional | K65: NATIONAL INSURANCE | W65: =Admin!B65 -> 45816
W66: =Admin!B66 -> 45817
B67: Employee surname | H67: *Account name | K67: National Insurance number | W67: =Admin!B67 -> 45818
B68: Employee forename(s) | W68: =Admin!B68 -> 45819
H69: *Account number | W69: =Admin!B69 -> 45820
W70: =Admin!B70 -> 45821
H71: *Bank name | W71: =Admin!B71 -> 45822
W72: =Admin!B72 -> 45823
H73: *Sort code | W73: =Admin!B73 -> 45824
W74: =Admin!B74 -> 45825
F75: Wk/Mth no | W75: =Admin!B75 -> 45826
B76: =B24 -> Starting date (existing = 06/04/25) | F76: =IF(D76=0," ",IF(D80="W",LOOKUP(D76,Admin!B:B,Admin!C:C),IF(D80="M",LOOKUP(D76,Admin!B:B,Admin!D:D),LOOKUP(D76,Admin!B:B,Admin!C:C)))) | W76: =Admin!B76 -> 45827
W77: =Admin!B77 -> 45828
B78: Leaving date (dd/mm/yyyy) | F78: =IF(D76=0," ",IF(D78=0," ",IF(D80="W",LOOKUP(D78,Admin!B:B,Admin!C:C),IF(D80="M",LOOKUP(D78,Admin!B:B,Admin!D:D),LOOKUP(D78,Admin!B:B,Admin!C:C))))) | W78: =Admin!B78 -> 45829
W79: =Admin!B79 -> 45830
B80: Paid monthly or weekly? | F80: =IF(D82="D","Enter M for Director","Enter M or W for Employee") -> Enter M or W for Employee | W80: =Admin!B80 -> 45831
B81: Payroll number | D81: 3 | W81: =Admin!B81 -> 45832
B82: Limited Companies Only | F82: Enter D for Director | W82: =Admin!B82 -> 45833
W83: =Admin!B83 -> 45834
W84: =Admin!B84 -> 45835
W85: =Admin!B85 -> 45836
W86: =Admin!B86 -> 45837
W87: =Admin!B87 -> 45838
W88: =Admin!B88 -> 45839
W89: =Admin!B89 -> 45840
W90: =Admin!B90 -> 45841
B91: EMPLOYEE DETAILS 04 | H91: * Bank details are optional | K91: NATIONAL INSURANCE | W91: =Admin!B91 -> 45842
W92: =Admin!B92 -> 45843
B93: Employee surname | H93: *Account name | K93: National Insurance number | W93: =Admin!B93 -> 45844
B94: Employee forename(s) | W94: =Admin!B94 -> 45845
B95: Address line 1 | H95: *Account number | W95: =Admin!B95 -> 45846
W96: =Admin!B96 -> 45847
H97: *Bank name | W97: =Admin!B97 -> 45848
W98: =Admin!B98 -> 45849
H99: *Sort code | W99: =Admin!B99 -> 45850
W100: =Admin!B100 -> 45851
F101: Wk/Mth no | W101: =Admin!B101 -> 45852
...

Sheet Jun
B1: www.diyaccounting.co.uk | G1: =SUM(AD60:AG60)+SUM(AE62:AG62) -> 0 | I1: Monthly Totals | M1: =M16+M26+M36+M46+M56 -> 0 | N1: =N16+N26+N36+N46+N56 -> 0 | O1: =O16+O26+O36+O46+O56 -> 0 | P1: =P16+P26+P36+P46+P56 -> 0 | Q1: =Q16+Q26+Q36+Q46+Q56 -> 0 | R1: =R16+R26+R36+R46+R56 -> 0 | T1: =T16+T26+T36+T46+T56 -> 0 | V1: YEAR TO DATE | AD1: Statutory Payments & NIC Recovered
I2: Sub Totals Directors | M2: =M65 -> 0 | N2: =N65 -> 0 | O2: =O65 -> 0 | P2: =P65 -> 0 | Q2: =Q65 -> 0 | R2: =R65 -> 0 | S2: =S65 -> 0 | T2: =T65 -> 0
B3: Dir Ref | C3: NIC Table | D3: Tax Code | E3: Pay No | F3: Employee Name | G3: SSP | H3: Statutory Pay | I3: Basic hours | J3: Hourly rate | K3: Basic wages | L3: Overtime Bonus Gratuities | M3: GROSS WAGES | N3: Income Tax | O3: Employees National Insurance | P3: Student Loans | Q3: Other Deductions | R3: NET PAY | T3: Employers National Insurance | V3: Gross Wages | W3: Income Tax | X3: Employees National Insurance | Y3: Student Loan deductions | Z3: Other Deductions | AA3: Net Pay | AC3: Employers National Insurance | AD3: Statutory Sick Pay Recovered | AE3: Statutory Maternity Pay Recovered | AF3: Statutory Paternity Pay Recovered | AG3: Statutory Adoption Pay Recovered
G4: SMP
G5: SPP
G6: SAP
B8: WEEKLY PAYROLL | O8: Date Wages paid
B9: Week number | E9: 1 | H9: Wages Tax Period | K9: =Admin!B2 -> 45753 | L9: - | M9: =K9+(7-WEEKDAY(K9, 2)) -> 45753
B11: =IF(E11=" "," ",IF(Employee!F$24>E$9," ",IF(Employee!F$26<E$9," ",Employee!D$30))) | E11: =IF(Employee!D$28="m"," ",IF(Employee!F$24>E$9," ",IF(Employee!F$26<E$9," ",Employee!D$29))) | F11: =IF(E11=" "," ",IF(Employee!F$24>E$9," ",IF(Employee!F$26<E$9," ",Employee!D$15))) | H11: 0 | I11: 0 | J11: 0 | K11: =I11*J11 -> 0 | L11: 0 | M11: =IF(E11=" "," ",IF((H11+K11+L11)>0,H11+K11+L11," ")) | N11: 0 | O11: 0 | P11: 0 | Q11: 0 | R11: =IF(M11=" "," ",IF(M11=0," ",M11-SUM(N11:Q11))) | T11: 0 | V11: =IF(Employee!H$34=E$9,Employee!D$34+SUM(M11)+0,SUM(M11)+0) -> 0 | W11: =IF(Employee!H$34=E$9,Employee!D$35+SUM(N11)+0,SUM(N11)+0) -> 0 | X11: =IF(O11=" ",0,O11) -> 0 | Y11: =IF(P11=" ",0,P11) -> 0 | Z11: =IF(Q11=" ",0,Q11) -> 0 | AA11: =IF(R11=" ",0,R11) -> 0 | AC11: =IF(T11=" ",0,T11) -> 0 | AD11: =IF(G11="SSP",H11,0) -> 0 | AE11: =IF(G11="SMP",H11,0) -> 0 | AF11: =IF(G11="SPP",H11,0) -> 0 | AG11: =IF(G11="SAP",H11,0) -> 0
B12: =IF(E12=" "," ",IF(Employee!F$50>E$9," ",IF(Employee!F$52<E$9," ",Employee!D$56))) | E12: =IF(Employee!D$54="m"," ",IF(Employee!F$50>E$9," ",IF(Employee!F$52<E$9," ",Employee!D$55))) | F12: =IF(E12=" "," ",IF(Employee!F$50>E$9," ",IF(Employee!F$52<E$9," ",Employee!D$41))) | H12: 0 | I12: 0 | J12: 0 | K12: =I12*J12 -> 0 | L12: 0 | M12: =IF(E12=" "," ",IF((H12+K12+L12)>0,H12+K12+L12," ")) | N12: 0 | O12: 0 | P12: 0 | Q12: 0 | R12: =IF(M12=" "," ",IF(M12=0," ",M12-SUM(N12:Q12))) | T12: 0 | V12: =IF(Employee!H$60=E$9,Employee!D$60+SUM(M12)+0,SUM(M12)+0) -> 0 | W12: =IF(Employee!H$60=E$9,Employee!D$61+SUM(N12)+0,SUM(N12)+0) -> 0 | X12: =IF(O12=" ",0,O12) -> 0 | Y12: =IF(P12=" ",0,P12) -> 0 | Z12: =IF(Q12=" ",0,Q12) -> 0 | AA12: =IF(R12=" ",0,R12) -> 0 | AC12: =IF(T12=" ",0,T12) -> 0 | AD12: =IF(G12="SSP",H12,0) -> 0 | AE12: =IF(G12="SMP",H12,0) -> 0 | AF12: =IF(G12="SPP",H12,0) -> 0 | AG12: =IF(G12="SAP",H12,0) -> 0
B13: =IF(E13=" "," ",IF(Employee!F$76>E$9," ",IF(Employee!F$78<E$9," ",Employee!D$82))) | E13: =IF(Employee!D$80="m"," ",IF(Employee!F$76>E$9," ",IF(Employee!F$78<E$9," ",Employee!D$81))) | F13: =IF(E13=" "," ",IF(Employee!F$76>E$9," ",IF(Employee!F$78<E$9," ",Employee!D$67))) | H13: 0 | I13: 0 | J13: 0 | K13: =I13*J13 -> 0 | L13: 0 | M13: =IF(E13=" "," ",IF((H13+K13+L13)>0,H13+K13+L13," ")) | N13: 0 | O13: 0 | P13: 0 | Q13: 0 | R13: =IF(M13=" "," ",IF(M13=0," ",M13-SUM(N13:Q13))) | T13: 0 | V13: =IF(Employee!H$86=E$9,Employee!D$86+SUM(M13)+0,SUM(M13)+0) -> 0 | W13: =IF(Employee!H$86=E$9,Employee!D$87+SUM(N13)+0,SUM(N13)+0) -> 0 | X13: =IF(O13=" ",0,O13) -> 0 | Y13: =IF(P13=" ",0,P13) -> 0 | Z13: =IF(Q13=" ",0,Q13) -> 0 | AA13: =IF(R13=" ",0,R13) -> 0 | AC13: =IF(T13=" ",0,T13) -> 0 | AD13: =IF(G13="SSP",H13,0) -> 0 | AE13: =IF(G13="SMP",H13,0) -> 0 | AF13: =IF(G13="SPP",H13,0) -> 0 | AG13: =IF(G13="SAP",H13,0) -> 0
B14: =IF(E14=" "," ",IF(Employee!F$102>E$9," ",IF(Employee!F$104<E$9," ",Employee!D$108))) | E14: =IF(Employee!D$106="m"," ",IF(Employee!F$102>E$9," ",IF(Employee!F$104<E$9," ",Employee!D$107))) | F14: =IF(E14=" "," ",IF(Employee!F$102>E$9," ",IF(Employee!F$104<E$9," ",Employee!D$93))) | H14: 0 | I14: 0 | J14: 0 | K14: =I14*J14 -> 0 | L14: 0 | M14: =IF(E14=" "," ",IF((H14+K14+L14)>0,H14+K14+L14," ")) | N14: 0 | O14: 0 | P14: 0 | Q14: 0 | R14: =IF(M14=" "," ",IF(M14=0," ",M14-SUM(N14:Q14))) | T14: 0 | V14: =IF(Employee!H$112=E$9,Employee!D$112+SUM(M14)+0,SUM(M14)+0) -> 0 | W14: =IF(Employee!H$112=E$9,Employee!D$113+SUM(N14)+0,SUM(N14)+0) -> 0 | X14: =IF(O14=" ",0,O14) -> 0 | Y14: =IF(P14=" ",0,P14) -> 0 | Z14: =IF(Q14=" ",0,Q14) -> 0 | AA14: =IF(R14=" ",0,R14) -> 0 | AC14: =IF(T14=" ",0,T14) -> 0 | AD14: =IF(G14="SSP",H14,0) -> 0 | AE14: =IF(G14="SMP",H14,0) -> 0 | AF14: =IF(G14="SPP",H14,0) -> 0 | AG14: =IF(G14="SAP",H14,0) -> 0
B15: =IF(E15=" "," ",IF(Employee!F$128>E$9," ",IF(Employee!F$130<E$9," ",Employee!D$134))) | E15: =IF(Employee!D$132="m"," ",IF(Employee!F$128>E$9," ",IF(Employee!F$130<E$9," ",Employee!D$133))) | F15: =IF(E15=" "," ",IF(Employee!F$128>E$9," ",IF(Employee!F$130<E$9," ",Employee!D$119))) | H15: 0 | I15: 0 | J15: 0 | K15: =I15*J15 -> 0 | L15: 0 | M15: =IF(E15=" "," ",IF((H15+K15+L15)>0,H15+K15+L15," ")) | N15: 0 | O15: 0 | P15: 0 | Q15: 0 | R15: =IF(M15=" "," ",IF(M15=0," ",M15-SUM(N15:Q15))) | T15: 0 | V15: =IF(Employee!H$138=E$9,Employee!D$138+SUM(M15)+0,SUM(M15)+0) -> 0 | W15: =IF(Employee!H$138=E$9,Employee!D$139+SUM(N15)+0,SUM(N15)+0) -> 0 | X15: =IF(O15=" ",0,O15) -> 0 | Y15: =IF(P15=" ",0,P15) -> 0 | Z15: =IF(Q15=" ",0,Q15) -> 0 | AA15: =IF(R15=" ",0,R15) -> 0 | AC15: =IF(T15=" ",0,T15) -> 0 | AD15: =IF(G15="SSP",H15,0) -> 0 | AE15: =IF(G15="SMP",H15,0) -> 0 | AF15: =IF(G15="SPP",H15,0) -> 0 | AG15: =IF(G15="SAP",H15,0) -> 0
F16: Payroll Total | M16: =SUM(M11:M15) -> 0 | N16: =SUM(N11:N15) -> 0 | O16: =SUM(O11:O15) -> 0 | P16: =SUM(P11:P15) -> 0 | Q16: =SUM(Q11:Q15) -> 0 | R16: =SUM(R11:R15) -> 0 | T16: =SUM(T11:T15) -> 0
B18: WEEKLY PAYROLL | O18: Date Wages paid
B19: Week number | E19: 2 | H19: Date Wages paid | K19: =M9+1 -> 45754 | L19: - | M19: =K19+6 -> 45760 | O19: One Click to repeat previous week Enter Y
B21: =IF(E21=" "," ",IF(Employee!F$24>E$19," ",IF(Employee!F$26<E$19," ",Employee!D$30))) | E21: =IF(Employee!D$28="m"," ",IF(Employee!F$24>E$19," ",IF(Employee!F$26<E$19," ",Employee!D$29))) | F21: =IF(E21=" "," ",IF(Employee!F$24>E$19," ",IF(Employee!F$26<E$19," ",Employee!D$15))) | H21: =IF(T$19="Y",H11,0) -> 0 | I21: 0 | J21: 0 | K21: =IF(T$19="Y",K11,I21*J21) -> 0 | L21: =IF(T$19="Y",L11,0) -> 0 | M21: =IF(E21=" "," ",IF(T$19="Y",M11,IF((H21+K21+L21)>0,H21+K21+L21," "))) | N21: 0 | O21: 0 | P21: 0 | Q21: 0 | R21: =IF(M21=" "," ",IF(M21=0," ",M21-SUM(N21:Q21))) | T21: 0 | V21: =IF(Employee!H$34=E$19,Employee!D$34+SUM(M21)+V11,SUM(M21)+V11) -> 0 | W21: =IF(Employee!H$34=E$19,Employee!D$35+SUM(N21)+W11,SUM(N21)+W11) -> 0 | X21: =IF(O21=" ",X11,O21+X11) -> 0 | Y21: =IF(P21=0,Y11,P21+Y11) -> 0 | Z21: =IF(Q21=0,Z11,Q21+Z11) -> 0 | AA21: =IF(R21=" ",AA11,AA11+R21) -> 0 | AC21: =IF(T21=" ",AC11,T21+AC11) -> 0 | AD21: =IF(G21="SSP",H21,0) -> 0 | AE21: =IF(G21="SMP",H21,0) -> 0 | AF21: =IF(G21="SPP",H21,0) -> 0 | AG21: =IF(G21="SAP",H21,0) -> 0
B22: =IF(E22=" "," ",IF(Employee!F$50>E$19," ",IF(Employee!F$52<E$19," ",Employee!D$56))) | E22: =IF(Employee!D$54="m"," ",IF(Employee!F$50>E$19," ",IF(Employee!F$52<E$19," ",Employee!D$55))) | F22: =IF(E22=" "," ",IF(Employee!F$50>E$19," ",IF(Employee!F$52<E$19," ",Employee!D$41))) | H22: =IF(T$19="Y",H12,0) -> 0 | I22: =IF(T$19="Y",I12,0) -> 0 | J22: =IF(T$19="Y",J12,0) -> 0 | K22: =IF(T$19="Y",K12,I22*J22) -> 0 | L22: =IF(T$19="Y",L12,0) -> 0 | M22: =IF(E22=" "," ",IF(T$19="Y",M12,IF((H22+K22+L22)>0,H22+K22+L22," "))) | N22: 0 | O22: 0 | P22: 0 | Q22: 0 | R22: =IF(M22=" "," ",IF(M22=0," ",M22-SUM(N22:Q22))) | T22: 0 | V22: =IF(Employee!H$60=E$19,Employee!D$60+SUM(M22)+V12,SUM(M22)+V12) -> 0 | W22: =IF(Employee!H$60=E$19,Employee!D$61+SUM(N22)+W12,SUM(N22)+W12) -> 0 | X22: =IF(O22=" ",X12,O22+X12) -> 0 | Y22: =IF(P22=0,Y12,P22+Y12) -> 0 | Z22: =IF(Q22=0,Z12,Q22+Z12) -> 0 | AA22: =IF(R22=" ",AA12,AA12+R22) -> 0 | AC22: =IF(T22=" ",AC12,T22+AC12) -> 0 | AD22: =IF(G22="SSP",H22,0) -> 0 | AE22: =IF(G22="SMP",H22,0) -> 0 | AF22: =IF(G22="SPP",H22,0) -> 0 | AG22: =IF(G22="SAP",H22,0) -> 0
B23: =IF(E23=" "," ",IF(Employee!F$76>E$19," ",IF(Employee!F$78<E$19," ",Employee!D$82))) | E23: =IF(Employee!D$80="m"," ",IF(Employee!F$76>E$19," ",IF(Employee!F$78<E$19," ",Employee!D$81))) | F23: =IF(E23=" "," ",IF(Employee!F$76>E$19," ",IF(Employee!F$78<E$19," ",Employee!D$67))) | H23: =IF(T$19="Y",H13,0) -> 0 | I23: =IF(T$19="Y",I13,0) -> 0 | J23: =IF(T$19="Y",J13,0) -> 0 | K23: =IF(T$19="Y",K13,I23*J23) -> 0 | L23: =IF(T$19="Y",L13,0) -> 0 | M23: =IF(E23=" "," ",IF(T$19="Y",M13,IF((H23+K23+L23)>0,H23+K23+L23," "))) | N23: 0 | O23: 0 | P23: 0 | Q23: 0 | R23: =IF(M23=" "," ",IF(M23=0," ",M23-SUM(N23:Q23))) | T23: 0 | V23: =IF(Employee!H$86=E$19,Employee!D$86+SUM(M23)+V13,SUM(M23)+V13) -> 0 | W23: =IF(Employee!H$86=E$19,Employee!D$87+SUM(N23)+W13,SUM(N23)+W13) -> 0 | X23: =IF(O23=" ",X13,O23+X13) -> 0 | Y23: =IF(P23=0,Y13,P23+Y13) -> 0 | Z23: =IF(Q23=0,Z13,Q23+Z13) -> 0 | AA23: =IF(R23=" ",AA13,AA13+R23) -> 0 | AC23: =IF(T23=" ",AC13,T23+AC13) -> 0 | AD23: =IF(G23="SSP",H23,0) -> 0 | AE23: =IF(G23="SMP",H23,0) -> 0 | AF23: =IF(G23="SPP",H23,0) -> 0 | AG23: =IF(G23="SAP",H23,0) -> 0
B24: =IF(E24=" "," ",IF(Employee!F$102>E$19," ",IF(Employee!F$104<E$19," ",Employee!D$108))) | E24: =IF(Employee!D$106="m"," ",IF(Employee!F$102>E$19," ",IF(Employee!F$104<E$19," ",Employee!D$107))) | F24: =IF(E24=" "," ",IF(Employee!F$102>E$19," ",IF(Employee!F$104<E$19," ",Employee!D$93))) | H24: =IF(T$19="Y",H14,0) -> 0 | I24: =IF(T$19="Y",I14,0) -> 0 | J24: =IF(T$19="Y",J14,0) -> 0 | K24: =IF(T$19="Y",K14,I24*J24) -> 0 | L24: =IF(T$19="Y",L14,0) -> 0 | M24: =IF(E24=" "," ",IF(T$19="Y",M14,IF((H24+K24+L24)>0,H24+K24+L24," "))) | N24: 0 | O24: 0 | P24: 0 | Q24: 0 | R24: =IF(M24=" "," ",IF(M24=0," ",M24-SUM(N24:Q24))) | T24: 0 | V24: =IF(Employee!H$112=E$19,Employee!D$112+SUM(M24)+V14,SUM(M24)+V14) -> 0 | W24: =IF(Employee!H$112=E$19,Employee!D$113+SUM(N24)+W14,SUM(N24)+W14) -> 0 | X24: =IF(O24=" ",X14,O24+X14) -> 0 | Y24: =IF(P24=0,Y14,P24+Y14) -> 0 | Z24: =IF(Q24=0,Z14,Q24+Z14) -> 0 | AA24: =IF(R24=" ",AA14,AA14+R24) -> 0 | AC24: =IF(T24=" ",AC14,T24+AC14) -> 0 | AD24: =IF(G24="SSP",H24,0) -> 0 | AE24: =IF(G24="SMP",H24,0) -> 0 | AF24: =IF(G24="SPP",H24,0) -> 0 | AG24: =IF(G24="SAP",H24,0) -> 0
B25: =IF(E25=" "," ",IF(Employee!F$128>E$19," ",IF(Employee!F$130<E$19," ",Employee!D$134))) | E25: =IF(Employee!D$132="m"," ",IF(Employee!F$128>E$19," ",IF(Employee!F$130<E$19," ",Employee!D$133))) | F25: =IF(E25=" "," ",IF(Employee!F$128>E$19," ",IF(Employee!F$130<E$19," ",Employee!D$119))) | H25: =IF(T$19="Y",H15,0) -> 0 | I25: =IF(T$19="Y",I15,0) -> 0 | J25: =IF(T$19="Y",J15,0) -> 0 | K25: =IF(T$19="Y",K15,I25*J25) -> 0 | L25: =IF(T$19="Y",L15,0) -> 0 | M25: =IF(E25=" "," ",IF(T$19="Y",M15,IF((H25+K25+L25)>0,H25+K25+L25," "))) | N25: 0 | O25: 0 | P25: 0 | Q25: 0 | R25: =IF(M25=" "," ",IF(M25=0," ",M25-SUM(N25:Q25))) | T25: 0 | V25: =IF(Employee!H$138=E$19,Employee!D$138+SUM(M25)+V15,SUM(M25)+V15) -> 0 | W25: =IF(Employee!H$138=E$19,Employee!D$139+SUM(N25)+W15,SUM(N25)+W15) -> 0 | X25: =IF(O25=" ",X15,O25+X15) -> 0 | Y25: =IF(P25=0,Y15,P25+Y15) -> 0 | Z25: =IF(Q25=0,Z15,Q25+Z15) -> 0 | AA25: =IF(R25=" ",AA15,AA15+R25) -> 0 | AC25: =IF(T25=" ",AC15,T25+AC15) -> 0 | AD25: =IF(G25="SSP",H25,0) -> 0 | AE25: =IF(G25="SMP",H25,0) -> 0 | AF25: =IF(G25="SPP",H25,0) -> 0 | AG25: =IF(G25="SAP",H25,0) -> 0
F26: Payroll Total | M26: =SUM(M21:M25) -> 0 | N26: =SUM(N21:N25) -> 0 | O26: =SUM(O21:O25) -> 0 | P26: =SUM(P21:P25) -> 0 | Q26: =SUM(Q21:Q25) -> 0 | R26: =SUM(R21:R25) -> 0 | T26: =SUM(T21:T25) -> 0
B28: WEEKLY PAYROLL | O28: Date Wages paid
B29: Week number | E29: 3 | H29: Date Wages paid | K29: =M19+1 -> 45761 | L29: - | M29: =K29+6 -> 45767 | O29: One Click to repeat previous week Enter Y
B31: =IF(E31=" "," ",IF(Employee!F$24>E$29," ",IF(Employee!F$26<E$29," ",Employee!D$30))) | E31: =IF(Employee!D$28="m"," ",IF(Employee!F$24>E$29," ",IF(Employee!F$26<E$29," ",Employee!D$29))) | F31: =IF(E31=" "," ",IF(Employee!F$24>E$29," ",IF(Employee!F$26<E$29," ",Employee!D$15))) | H31: =IF(T$29="Y",H21,0) -> 0 | I31: 0 | J31: 0 | K31: =IF(T$29="Y",K21,I31*J31) -> 0 | L31: =IF(T$29="Y",L21,0) -> 0 | M31: =IF(E31=" "," ",IF(T$29="Y",M21,IF((H31+K31+L31)>0,H31+K31+L31," "))) | N31: 0 | O31: 0 | P31: 0 | Q31: 0 | R31: =IF(M31=" "," ",IF(M31=0," ",M31-SUM(N31:Q31))) | T31: 0 | V31: =IF(Employee!H$34=E$29,Employee!D$34+SUM(M31)+V21,SUM(M31)+V21) -> 0 | W31: =IF(Employee!H$34=E$29,Employee!D$35+SUM(N31)+W21,SUM(N31)+W21) -> 0 | X31: =IF(O31=" ",X21,O31+X21) -> 0 | Y31: =IF(P31=0,Y21,P31+Y21) -> 0 | Z31: =IF(Q31=0,Z21,Q31+Z21) -> 0 | AA31: =IF(R31=" ",AA21,AA21+R31) -> 0 | AC31: =IF(T31=" ",AC21,T31+AC21) -> 0 | AD31: =IF(G31="SSP",H31,0) -> 0 | AE31: =IF(G31="SMP",H31,0) -> 0 | AF31: =IF(G31="SPP",H31,0) -> 0 | AG31: =IF(G31="SAP",H31,0) -> 0
B32: =IF(E32=" "," ",IF(Employee!F$50>E$29," ",IF(Employee!F$52<E$29," ",Employee!D$56))) | E32: =IF(Employee!D$54="m"," ",IF(Employee!F$50>E$29," ",IF(Employee!F$52<E$29," ",Employee!D$55))) | F32: =IF(E32=" "," ",IF(Employee!F$50>E$29," ",IF(Employee!F$52<E$29," ",Employee!D$41))) | H32: =IF(T$29="Y",H22,0) -> 0 | I32: =IF(T$29="Y",I22,0) -> 0 | J32: =IF(T$29="Y",J22,0) -> 0 | K32: =IF(T$29="Y",K22,I32*J32) -> 0 | L32: =IF(T$29="Y",L22,0) -> 0 | M32: =IF(E32=" "," ",IF(T$29="Y",M22,IF((H32+K32+L32)>0,H32+K32+L32," "))) | N32: 0 | O32: 0 | P32: 0 | Q32: 0 | R32: =IF(M32=" "," ",IF(M32=0," ",M32-SUM(N32:Q32))) | T32: 0 | V32: =IF(Employee!H$60=E$29,Employee!D$60+SUM(M32)+V22,SUM(M32)+V22) -> 0 | W32: =IF(Employee!H$60=E$29,Employee!D$61+SUM(N32)+W22,SUM(N32)+W22) -> 0 | X32: =IF(O32=" ",X22,O32+X22) -> 0 | Y32: =IF(P32=0,Y22,P32+Y22) -> 0 | Z32: =IF(Q32=0,Z22,Q32+Z22) -> 0 | AA32: =IF(R32=" ",AA22,AA22+R32) -> 0 | AC32: =IF(T32=" ",AC22,T32+AC22) -> 0 | AD32: =IF(G32="SSP",H32,0) -> 0 | AE32: =IF(G32="SMP",H32,0) -> 0 | AF32: =IF(G32="SPP",H32,0) -> 0 | AG32: =IF(G32="SAP",H32,0) -> 0
B33: =IF(E33=" "," ",IF(Employee!F$76>E$29," ",IF(Employee!F$78<E$29," ",Employee!D$82))) | E33: =IF(Employee!D$80="m"," ",IF(Employee!F$76>E$29," ",IF(Employee!F$78<E$29," ",Employee!D$81))) | F33: =IF(E33=" "," ",IF(Employee!F$76>E$29," ",IF(Employee!F$78<E$29," ",Employee!D$67))) | H33: =IF(T$29="Y",H23,0) -> 0 | I33: =IF(T$29="Y",I23,0) -> 0 | J33: =IF(T$29="Y",J23,0) -> 0 | K33: =IF(T$29="Y",K23,I33*J33) -> 0 | L33: =IF(T$29="Y",L23,0) -> 0 | M33: =IF(E33=" "," ",IF(T$29="Y",M23,IF((H33+K33+L33)>0,H33+K33+L33," "))) | N33: 0 | O33: 0 | P33: 0 | Q33: 0 | R33: =IF(M33=" "," ",IF(M33=0," ",M33-SUM(N33:Q33))) | T33: 0 | V33: =IF(Employee!H$86=E$29,Employee!D$86+SUM(M33)+V23,SUM(M33)+V23) -> 0 | W33: =IF(Employee!H$86=E$29,Employee!D$87+SUM(N33)+W23,SUM(N33)+W23) -> 0 | X33: =IF(O33=" ",X23,O33+X23) -> 0 | Y33: =IF(P33=0,Y23,P33+Y23) -> 0 | Z33: =IF(Q33=0,Z23,Q33+Z23) -> 0 | AA33: =IF(R33=" ",AA23,AA23+R33) -> 0 | AC33: =IF(T33=" ",AC23,T33+AC23) -> 0 | AD33: =IF(G33="SSP",H33,0) -> 0 | AE33: =IF(G33="SMP",H33,0) -> 0 | AF33: =IF(G33="SPP",H33,0) -> 0 | AG33: =IF(G33="SAP",H33,0) -> 0
B34: =IF(E34=" "," ",IF(Employee!F$102>E$29," ",IF(Employee!F$104<E$29," ",Employee!D$108))) | E34: =IF(Employee!D$106="m"," ",IF(Employee!F$102>E$29," ",IF(Employee!F$104<E$29," ",Employee!D$107))) | F34: =IF(E34=" "," ",IF(Employee!F$102>E$29," ",IF(Employee!F$104<E$29," ",Employee!D$93))) | H34: =IF(T$29="Y",H24,0) -> 0 | I34: =IF(T$29="Y",I24,0) -> 0 | J34: =IF(T$29="Y",J24,0) -> 0 | K34: =IF(T$29="Y",K24,I34*J34) -> 0 | L34: =IF(T$29="Y",L24,0) -> 0 | M34: =IF(E34=" "," ",IF(T$29="Y",M24,IF((H34+K34+L34)>0,H34+K34+L34," "))) | N34: 0 | O34: 0 | P34: 0 | Q34: 0 | R34: =IF(M34=" "," ",IF(M34=0," ",M34-SUM(N34:Q34))) | T34: 0 | V34: =IF(Employee!H$112=E$29,Employee!D$112+SUM(M34)+V24,SUM(M34)+V24) -> 0 | W34: =IF(Employee!H$112=E$29,Employee!D$113+SUM(N34)+W24,SUM(N34)+W24) -> 0 | X34: =IF(O34=" ",X24,O34+X24) -> 0 | Y34: =IF(P34=0,Y24,P34+Y24) -> 0 | Z34: =IF(Q34=0,Z24,Q34+Z24) -> 0 | AA34: =IF(R34=" ",AA24,AA24+R34) -> 0 | AC34: =IF(T34=" ",AC24,T34+AC24) -> 0 | AD34: =IF(G34="SSP",H34,0) -> 0 | AE34: =IF(G34="SMP",H34,0) -> 0 | AF34: =IF(G34="SPP",H34,0) -> 0 | AG34: =IF(G34="SAP",H34,0) -> 0
B35: =IF(E35=" "," ",IF(Employee!F$128>E$29," ",IF(Employee!F$130<E$29," ",Employee!D$134))) | E35: =IF(Employee!D$132="m"," ",IF(Employee!F$128>E$29," ",IF(Employee!F$130<E$29," ",Employee!D$133))) | F35: =IF(E35=" "," ",IF(Employee!F$128>E$29," ",IF(Employee!F$130<E$29," ",Employee!D$119))) | H35: =IF(T$29="Y",H25,0) -> 0 | I35: =IF(T$29="Y",I25,0) -> 0 | J35: =IF(T$29="Y",J25,0) -> 0 | K35: =IF(T$29="Y",K25,I35*J35) -> 0 | L35: =IF(T$29="Y",L25,0) -> 0 | M35: =IF(E35=" "," ",IF(T$29="Y",M25,IF((H35+K35+L35)>0,H35+K35+L35," "))) | N35: 0 | O35: 0 | P35: 0 | Q35: 0 | R35: =IF(M35=" "," ",IF(M35=0," ",M35-SUM(N35:Q35))) | T35: 0 | V35: =IF(Employee!H$138=E$29,Employee!D$138+SUM(M35)+V25,SUM(M35)+V25) -> 0 | W35: =IF(Employee!H$138=E$29,Employee!D$139+SUM(N35)+W25,SUM(N35)+W25) -> 0 | X35: =IF(O35=" ",X25,O35+X25) -> 0 | Y35: =IF(P35=0,Y25,P35+Y25) -> 0 | Z35: =IF(Q35=0,Z25,Q35+Z25) -> 0 | AA35: =IF(R35=" ",AA25,AA25+R35) -> 0 | AC35: =IF(T35=" ",AC25,T35+AC25) -> 0 | AD35: =IF(G35="SSP",H35,0) -> 0 | AE35: =IF(G35="SMP",H35,0) -> 0 | AF35: =IF(G35="SPP",H35,0) -> 0 | AG35: =IF(G35="SAP",H35,0) -> 0
F36: Payroll Total | M36: =SUM(M31:M35) -> 0 | N36: =SUM(N31:N35) -> 0 | O36: =SUM(O31:O35) -> 0 | P36: =SUM(P31:P35) -> 0 | Q36: =SUM(Q31:Q35) -> 0 | R36: =SUM(R31:R35) -> 0 | T36: =SUM(T31:T35) -> 0
B38: WEEKLY PAYROLL | O38: Date Wages paid
B39: Week number | E39: 4 | H39: Date Wages paid | K39: =M29+1 -> 45768 | L39: - | M39: =K39+6 -> 45774 | O39: One Click to repeat previous week Enter Y
B41: =IF(E41=" "," ",IF(Employee!F$24>E$39," ",IF(Employee!F$26<E$39," ",Employee!D$30))) | E41: =IF(Employee!D$28="m"," ",IF(Employee!F$24>E$39," ",IF(Employee!F$26<E$39," ",Employee!D$29))) | F41: =IF(E41=" "," ",IF(Employee!F$24>E$39," ",IF(Employee!F$26<E$39," ",Employee!D$15))) | H41: =IF(T$39="Y",H31,0) -> 0 | I41: 0 | J41: 0 | K41: =IF(T$39="Y",K31,I41*J41) -> 0 | L41: =IF(T$39="Y",L31,0) -> 0 | M41: =IF(E41=" "," ",IF(T$39="Y",M31,IF((H41+K41+L41)>0,H41+K41+L41," "))) | N41: 0 | O41: 0 | P41: 0 | Q41: 0 | R41: =IF(M41=" "," ",IF(M41=0," ",M41-SUM(N41:Q41))) | T41: 0 | V41: =IF(Employee!H$34=E$39,Employee!D$34+SUM(M41)+V31,SUM(M41)+V31) -> 0 | W41: =IF(Employee!H$34=E$39,Employee!D$35+SUM(N41)+W31,SUM(N41)+W31) -> 0 | X41: =IF(O41=" ",X31,O41+X31) -> 0 | Y41: =IF(P41=0,Y31,P41+Y31) -> 0 | Z41: =IF(Q41=0,Z31,Q41+Z31) -> 0 | AA41: =IF(R41=" ",AA31,AA31+R41) -> 0 | AC41: =IF(T41=" ",AC31,T41+AC31) -> 0 | AD41: =IF(G41="SSP",H41,0) -> 0 | AE41: =IF(G41="SMP",H41,0) -> 0 | AF41: =IF(G41="SPP",H41,0) -> 0 | AG41: =IF(G41="SAP",H41,0) -> 0
B42: =IF(E42=" "," ",IF(Employee!F$50>E$39," ",IF(Employee!F$52<E$39," ",Employee!D$56))) | E42: =IF(Employee!D$54="m"," ",IF(Employee!F$50>E$39," ",IF(Employee!F$52<E$39," ",Employee!D$55))) | F42: =IF(E42=" "," ",IF(Employee!F$50>E$39," ",IF(Employee!F$52<E$39," ",Employee!D$41))) | H42: =IF(T$39="Y",H32,0) -> 0 | I42: =IF(T$39="Y",I32,0) -> 0 | J42: =IF(T$39="Y",J32,0) -> 0 | K42: =IF(T$39="Y",K32,I42*J42) -> 0 | L42: =IF(T$39="Y",L32,0) -> 0 | M42: =IF(E42=" "," ",IF(T$39="Y",M32,IF((H42+K42+L42)>0,H42+K42+L42," "))) | N42: 0 | O42: 0 | P42: 0 | Q42: 0 | R42: =IF(M42=" "," ",IF(M42=0," ",M42-SUM(N42:Q42))) | T42: 0 | V42: =IF(Employee!H$60=E$39,Employee!D$60+SUM(M42)+V32,SUM(M42)+V32) -> 0 | W42: =IF(Employee!H$60=E$39,Employee!D$61+SUM(N42)+W32,SUM(N42)+W32) -> 0 | X42: =IF(O42=" ",X32,O42+X32) -> 0 | Y42: =IF(P42=0,Y32,P42+Y32) -> 0 | Z42: =IF(Q42=0,Z32,Q42+Z32) -> 0 | AA42: =IF(R42=" ",AA32,AA32+R42) -> 0 | AC42: =IF(T42=" ",AC32,T42+AC32) -> 0 | AD42: =IF(G42="SSP",H42,0) -> 0 | AE42: =IF(G42="SMP",H42,0) -> 0 | AF42: =IF(G42="SPP",H42,0) -> 0 | AG42: =IF(G42="SAP",H42,0) -> 0
B43: =IF(E43=" "," ",IF(Employee!F$76>E$39," ",IF(Employee!F$78<E$39," ",Employee!D$82))) | E43: =IF(Employee!D$80="m"," ",IF(Employee!F$76>E$39," ",IF(Employee!F$78<E$39," ",Employee!D$81))) | F43: =IF(E43=" "," ",IF(Employee!F$76>E$39," ",IF(Employee!F$78<E$39," ",Employee!D$67))) | H43: =IF(T$39="Y",H33,0) -> 0 | I43: =IF(T$39="Y",I33,0) -> 0 | J43: =IF(T$39="Y",J33,0) -> 0 | K43: =IF(T$39="Y",K33,I43*J43) -> 0 | L43: =IF(T$39="Y",L33,0) -> 0 | M43: =IF(E43=" "," ",IF(T$39="Y",M33,IF((H43+K43+L43)>0,H43+K43+L43," "))) | N43: 0 | O43: 0 | P43: 0 | Q43: 0 | R43: =IF(M43=" "," ",IF(M43=0," ",M43-SUM(N43:Q43))) | T43: 0 | V43: =IF(Employee!H$86=E$39,Employee!D$86+SUM(M43)+V33,SUM(M43)+V33) -> 0 | W43: =IF(Employee!H$86=E$39,Employee!D$87+SUM(N43)+W33,SUM(N43)+W33) -> 0 | X43: =IF(O43=" ",X33,O43+X33) -> 0 | Y43: =IF(P43=0,Y33,P43+Y33) -> 0 | Z43: =IF(Q43=0,Z33,Q43+Z33) -> 0 | AA43: =IF(R43=" ",AA33,AA33+R43) -> 0 | AC43: =IF(T43=" ",AC33,T43+AC33) -> 0 | AD43: =IF(G43="SSP",H43,0) -> 0 | AE43: =IF(G43="SMP",H43,0) -> 0 | AF43: =IF(G43="SPP",H43,0) -> 0 | AG43: =IF(G43="SAP",H43,0) -> 0
B44: =IF(E44=" "," ",IF(Employee!F$102>E$39," ",IF(Employee!F$104<E$39," ",Employee!D$108))) | E44: =IF(Employee!D$106="m"," ",IF(Employee!F$102>E$39," ",IF(Employee!F$104<E$39," ",Employee!D$107))) | F44: =IF(E44=" "," ",IF(Employee!F$102>E$39," ",IF(Employee!F$104<E$39," ",Employee!D$93))) | H44: =IF(T$39="Y",H34,0) -> 0 | I44: =IF(T$39="Y",I34,0) -> 0 | J44: =IF(T$39="Y",J34,0) -> 0 | K44: =IF(T$39="Y",K34,I44*J44) -> 0 | L44: =IF(T$39="Y",L34,0) -> 0 | M44: =IF(E44=" "," ",IF(T$39="Y",M34,IF((H44+K44+L44)>0,H44+K44+L44," "))) | N44: 0 | O44: 0 | P44: 0 | Q44: 0 | R44: =IF(M44=" "," ",IF(M44=0," ",M44-SUM(N44:Q44))) | T44: 0 | V44: =IF(Employee!H$112=E$39,Employee!D$112+SUM(M44)+V34,SUM(M44)+V34) -> 0 | W44: =IF(Employee!H$112=E$39,Employee!D$113+SUM(N44)+W34,SUM(N44)+W34) -> 0 | X44: =IF(O44=" ",X34,O44+X34) -> 0 | Y44: =IF(P44=0,Y34,P44+Y34) -> 0 | Z44: =IF(Q44=0,Z34,Q44+Z34) -> 0 | AA44: =IF(R44=" ",AA34,AA34+R44) -> 0 | AC44: =IF(T44=" ",AC34,T44+AC34) -> 0 | AD44: =IF(G44="SSP",H44,0) -> 0 | AE44: =IF(G44="SMP",H44,0) -> 0 | AF44: =IF(G44="SPP",H44,0) -> 0 | AG44: =IF(G44="SAP",H44,0) -> 0
B45: =IF(E45=" "," ",IF(Employee!F$128>E$39," ",IF(Employee!F$130<E$39," ",Employee!D$134))) | E45: =IF(Employee!D$132="m"," ",IF(Employee!F$128>E$39," ",IF(Employee!F$130<E$39," ",Employee!D$133))) | F45: =IF(E45=" "," ",IF(Employee!F$128>E$39," ",IF(Employee!F$130<E$39," ",Employee!D$119))) | H45: =IF(T$39="Y",H35,0) -> 0 | I45: =IF(T$39="Y",I35,0) -> 0 | J45: =IF(T$39="Y",J35,0) -> 0 | K45: =IF(T$39="Y",K35,I45*J45) -> 0 | L45: =IF(T$39="Y",L35,0) -> 0 | M45: =IF(E45=" "," ",IF(T$39="Y",M35,IF((H45+K45+L45)>0,H45+K45+L45," "))) | N45: 0 | O45: 0 | P45: 0 | Q45: 0 | R45: =IF(M45=" "," ",IF(M45=0," ",M45-SUM(N45:Q45))) | T45: 0 | V45: =IF(Employee!H$138=E$39,Employee!D$138+SUM(M45)+V35,SUM(M45)+V35) -> 0 | W45: =IF(Employee!H$138=E$39,Employee!D$139+SUM(N45)+W35,SUM(N45)+W35) -> 0 | X45: =IF(O45=" ",X35,O45+X35) -> 0 | Y45: =IF(P45=0,Y35,P45+Y35) -> 0 | Z45: =IF(Q45=0,Z35,Q45+Z35) -> 0 | AA45: =IF(R45=" ",AA35,AA35+R45) -> 0 | AC45: =IF(T45=" ",AC35,T45+AC35) -> 0 | AD45: =IF(G45="SSP",H45,0) -> 0 | AE45: =IF(G45="SMP",H45,0) -> 0 | AF45: =IF(G45="SPP",H45,0) -> 0 | AG45: =IF(G45="SAP",H45,0) -> 0
F46: Payroll Total | M46: =SUM(M41:M45) -> 0 | N46: =SUM(N41:N45) -> 0 | O46: =SUM(O41:O45) -> 0 | P46: =SUM(P41:P45) -> 0 | Q46: =SUM(Q41:Q45) -> 0 | R46: =SUM(R41:R45) -> 0 | T46: =SUM(T41:T45) -> 0
B48: MONTHLY PAYROLL | O48: Date Wages paid
B49: Month number | E49: 1 | H49: Date Wages paid | K49: =DATE(2024,6,1) -> 45444 | L49: - | M49: =DATE(2024,6,30) -> 45473 | O49: One Click to repeat previous month | T49: Month 1
B51: =IF(E51=" "," ",IF(Employee!F$24>E$49," ",IF(Employee!F$26<E$49," ",Employee!D$30))) | E51: =IF(Employee!D$28="w"," ",IF(Employee!F$24>E$49," ",IF(Employee!F$26<E$49," ",Employee!D$29))) | F51: =IF(E51=" "," ",IF(Employee!F$24>E$49," ",IF(Employee!F$26<E$49," ",Employee!D$15))) | H51: 0 | I51: 0 | J51: 0 | K51: =I51*J51 -> 0 | L51: 0 | M51: =IF(E51=" "," ",IF((H51+K51+L51)>0,H51+K51+L51," ")) | N51: 0 | O51: 0 | P51: 0 | Q51: 0 | R51: =IF(M51=" "," ",IF(M51=0," ",M51-SUM(N51:Q51))) | T51: 0 | V51: =IF(Employee!H$35=E$49,Employee!D$34+SUM(M51)+0,SUM(M51)+0) -> 0 | W51: =IF(Employee!H$35=E$49,Employee!D$35+SUM(N51)+0,SUM(N51)+0) -> 0 | X51: =IF(O51=" ",0,O51) -> 0 | Y51: =IF(P51=" ",0,P51) -> 0 | Z51: =IF(Q51=" ",0,Q51) -> 0 | AA51: =IF(R51=" ",0,R51) -> 0 | AC51: =IF(T51=" ",0,T51) -> 0 | AD51: =IF(G51="SSP",H51,0) -> 0 | AE51: =IF(G51="SMP",H51,0) -> 0 | AF51: =IF(G51="SPP",H51,0) -> 0 | AG51: =IF(G51="SAP",H51,0) -> 0
B52: =IF(E52=" "," ",IF(Employee!F$50>E$49," ",IF(Employee!F$52<E$49," ",Employee!D$56))) | E52: =IF(Employee!D$54="w"," ",IF(Employee!F$50>E$49," ",IF(Employee!F$52<E$49," ",Employee!D$55))) | F52: =IF(E52=" "," ",IF(Employee!F$50>E$49," ",IF(Employee!F$52<E$49," ",Employee!D$41))) | H52: 0 | I52: 0 | J52: 0 | K52: =I52*J52 -> 0 | L52: 0 | M52: =IF(E52=" "," ",IF((H52+K52+L52)>0,H52+K52+L52," ")) | N52: 0 | O52: 0 | P52: 0 | Q52: 0 | R52: =IF(M52=" "," ",IF(M52=0," ",M52-SUM(N52:Q52))) | T52: 0 | V52: =IF(Employee!H$61=E$49,Employee!D$60+SUM(M52)+0,SUM(M52)+0) -> 0 | W52: =IF(Employee!H$61=E$49,Employee!D$61+SUM(N52)+0,SUM(N52)+0) -> 0 | X52: =IF(O52=" ",0,O52) -> 0 | Y52: =IF(P52=" ",0,P52) -> 0 | Z52: =IF(Q52=" ",0,Q52) -> 0 | AA52: =IF(R52=" ",0,R52) -> 0 | AC52: =IF(T52=" ",0,T52) -> 0 | AD52: =IF(G52="SSP",H52,0) -> 0 | AE52: =IF(G52="SMP",H52,0) -> 0 | AF52: =IF(G52="SPP",H52,0) -> 0 | AG52: =IF(G52="SAP",H52,0) -> 0
B53: =IF(E53=" "," ",IF(Employee!F$76>E$49," ",IF(Employee!F$78<E$49," ",Employee!D$82))) | E53: =IF(Employee!D$80="w"," ",IF(Employee!F$76>E$49," ",IF(Employee!F$78<E$49," ",Employee!D$81))) | F53: =IF(E53=" "," ",IF(Employee!F$76>E$49," ",IF(Employee!F$78<E$49," ",Employee!D$67))) | H53: 0 | I53: 0 | J53: 0 | K53: =I53*J53 -> 0 | L53: 0 | M53: =IF(E53=" "," ",IF((H53+K53+L53)>0,H53+K53+L53," ")) | N53: 0 | O53: 0 | P53: 0 | Q53: 0 | R53: =IF(M53=" "," ",IF(M53=0," ",M53-SUM(N53:Q53))) | T53: 0 | V53: =IF(Employee!H$87=E$49,Employee!D$86+SUM(M53)+0,SUM(M53)+0) -> 0 | W53: =IF(Employee!H$87=E$49,Employee!D$87+SUM(N53)+0,SUM(N53)+0) -> 0 | X53: =IF(O53=" ",0,O53) -> 0 | Y53: =IF(P53=" ",0,P53) -> 0 | Z53: =IF(Q53=" ",0,Q53) -> 0 | AA53: =IF(R53=" ",0,R53) -> 0 | AC53: =IF(T53=" ",0,T53) -> 0 | AD53: =IF(G53="SSP",H53,0) -> 0 | AE53: =IF(G53="SMP",H53,0) -> 0 | AF53: =IF(G53="SPP",H53,0) -> 0 | AG53: =IF(G53="SAP",H53,0) -> 0
B54: =IF(E54=" "," ",IF(Employee!F$102>E$49," ",IF(Employee!F$104<E$49," ",Employee!D$108))) | E54: =IF(Employee!D$106="w"," ",IF(Employee!F$102>E$49," ",IF(Employee!F$104<E$49," ",Employee!D$107))) | F54: =IF(E54=" "," ",IF(Employee!F$102>E$49," ",IF(Employee!F$104<E$49," ",Employee!D$93))) | H54: 0 | I54: 0 | J54: 0 | K54: =I54*J54 -> 0 | L54: 0 | M54: =IF(E54=" "," ",IF((H54+K54+L54)>0,H54+K54+L54," ")) | N54: 0 | O54: 0 | P54: 0 | Q54: 0 | R54: =IF(M54=" "," ",IF(M54=0," ",M54-SUM(N54:Q54))) | T54: 0 | V54: =IF(Employee!H$113=E$49,Employee!D$112+SUM(M54)+0,SUM(M54)+0) -> 0 | W54: =IF(Employee!H$113=E$49,Employee!D$113+SUM(N54)+0,SUM(N54)+0) -> 0 | X54: =IF(O54=" ",0,O54) -> 0 | Y54: =IF(P54=" ",0,P54) -> 0 | Z54: =IF(Q54=" ",0,Q54) -> 0 | AA54: =IF(R54=" ",0,R54) -> 0 | AC54: =IF(T54=" ",0,T54) -> 0 | AD54: =IF(G54="SSP",H54,0) -> 0 | AE54: =IF(G54="SMP",H54,0) -> 0 | AF54: =IF(G54="SPP",H54,0) -> 0 | AG54: =IF(G54="SAP",H54,0) -> 0
B55: =IF(E55=" "," ",IF(Employee!F$128>E$49," ",IF(Employee!F$130<E$49," ",Employee!D$134))) | E55: =IF(Employee!D$132="w"," ",IF(Employee!F$128>E$49," ",IF(Employee!F$130<E$49," ",Employee!D$133))) | F55: =IF(E55=" "," ",IF(Employee!F$128>E$49," ",IF(Employee!F$130<E$49," ",Employee!D$119))) | H55: 0 | I55: 0 | J55: 0 | K55: =I55*J55 -> 0 | L55: 0 | M55: =IF(E55=" "," ",IF((H55+K55+L55)>0,H55+K55+L55," ")) | N55: 0 | O55: 0 | P55: 0 | Q55: 0 | R55: =IF(M55=" "," ",IF(M55=0," ",M55-SUM(N55:Q55))) | T55: 0 | V55: =IF(Employee!H$139=E$49,Employee!D$138+SUM(M55)+0,SUM(M55)+0) -> 0 | W55: =IF(Employee!H$139=E$49,Employee!D$139+SUM(N55)+0,SUM(N55)+0) -> 0 | X55: =IF(O55=" ",0,O55) -> 0 | Y55: =IF(P55=" ",0,P55) -> 0 | Z55: =IF(Q55=" ",0,Q55) -> 0 | AA55: =IF(R55=" ",0,R55) -> 0 | AC55: =IF(T55=" ",0,T55) -> 0 | AD55: =IF(G55="SSP",H55,0) -> 0 | AE55: =IF(G55="SMP",H55,0) -> 0 | AF55: =IF(G55="SPP",H55,0) -> 0 | AG55: =IF(G55="SAP",H55,0) -> 0
F56: Payroll Total | M56: =SUM(M51:M55) -> 0 | N56: =SUM(N51:N55) -> 0 | O56: =SUM(O51:O55) -> 0 | P56: =SUM(P51:P55) -> 0 | Q56: =SUM(Q51:Q55) -> 0 | R56: =SUM(R51:R55) -> 0 | T56: =SUM(T51:T55) -> 0
AD58: =SUM(AD11:AD56) -> 0 | AE58: =SUM(AE11:AE56) -> 0 | AF58: =SUM(AF11:AF56) -> 0 | AG58: =SUM(AG11:AG56) -> 0
F59: Directors | M59: Directors Wages Limited Companies Only
F60: =IF(B51="D",Employee!D15," ") | M60: =IF(B51="D",M51," ") | N60: =IF(B51="D",N51," ") | O60: =IF(B51="D",O51," ") | P60: =IF(B51="D",P51," ") | Q60: =IF(B51="D",Q51," ") | R60: =IF(B51="D",R51," ") | T60: =IF(B51="D",T51," ") | AD60: =IF((AD58-(O1+T1)*0.13)>0,AD58-(Q1+T1)*0.13,0) -> 0 | AE60: =AE58 -> 0 | AF60: =AF58 -> 0 | AG60: =AG58 -> 0
F61: =IF(B52="D",Employee!D41," ") | M61: =IF(B52="D",M52," ") | N61: =IF(B52="D",N52," ") | O61: =IF(B52="D",O52," ") | P61: =IF(B52="D",P52," ") | Q61: =IF(B52="D",Q52," ") | R61: =IF(B52="D",R52," ") | T61: =IF(B52="D",T52," ")
F62: =IF(B53="D",Employee!D67," ") | M62: =IF(B53="D",M53," ") | N62: =IF(B53="D",N53," ") | O62: =IF(B53="D",O53," ") | P62: =IF(B53="D",P53," ") | Q62: =IF(B53="D",Q53," ") | R62: =IF(B53="D",R53," ") | T62: =IF(B53="D",T53," ") | AE62: =AE60*0.045 -> 0 | AF62: =AF60*0.045 -> 0 | AG62: =AG60*0.045 -> 0
F63: =IF(B54="D",Employee!D93," ") | M63: =IF(B54="D",M54," ") | N63: =IF(B54="D",N54," ") | O63: =IF(B54="D",O54," ") | P63: =IF(B54="D",P54," ") | Q63: =IF(B54="D",Q54," ") | R63: =IF(B54="D",R54," ") | T63: =IF(B54="D",T54," ")
F64: =IF(B55="D",Employee!D119," ") | M64: =IF(B55="D",M55," ") | N64: =IF(B55="D",N55," ") | O64: =IF(B55="D",O55," ") | P64: =IF(B55="D",P55," ") | Q64: =IF(B55="D",Q55," ") | R64: =IF(B55="D",R55," ") | T64: =IF(B55="D",T55," ")
F65: Director Totals | M65: =SUM(M60:M64) -> 0 | N65: =SUM(N60:N64) -> 0 | O65: =SUM(O60:O64) -> 0 | P65: =SUM(P60:P64) -> 0 | Q65: =SUM(Q60:Q64) -> 0 | R65: =SUM(R60:R64) -> 0 | T65: =SUM(T60:T64) -> 0 | AD65: =AD60 -> 0 | AE65: =AE60 -> 0 | AF65: =AF60 -> 0 | AG65: =AG60 -> 0
AE67: =AE62 -> 0 | AF67: =AF62 -> 0 | AG67: =AG62 -> 0

Sheet Jul
B1: www.diyaccounting.co.uk | G1: =SUM(AD60:AG60)+SUM(AE62:AG62) -> 0 | I1: Monthly Totals | M1: =M16+M26+M36+M46+M56 -> 0 | N1: =N16+N26+N36+N46+N56 -> 0 | O1: =O16+O26+O36+O46+O56 -> 0 | P1: =P16+P26+P36+P46+P56 -> 0 | Q1: =Q16+Q26+Q36+Q46+Q56 -> 0 | R1: =R16+R26+R36+R46+R56 -> 0 | T1: =T16+T26+T36+T46+T56 -> 0 | V1: YEAR TO DATE | AD1: Statutory Payments & NIC Recovered
I2: Sub Totals Directors | M2: =M65 -> 0 | N2: =N65 -> 0 | O2: =O65 -> 0 | P2: =P65 -> 0 | Q2: =Q65 -> 0 | R2: =R65 -> 0 | S2: =S65 -> 0 | T2: =T65 -> 0
B3: Dir Ref | C3: NIC Table | D3: Tax Code | E3: Pay No | F3: Employee Name | G3: SSP | H3: =Jun!H3:H6 -> Statutory Pay | I3: =Jun!I3:I6 -> Basic hours | J3: =Jun!J3:J6 -> Hourly rate | K3: =Jun!K3:K6 -> Basic wages | L3: =Jun!L3:L6 -> Overtime Bonus Gratuities | M3: =Jun!M3:M6 -> GROSS WAGES | N3: =Jun!N3:N6 -> Income Tax | O3: =Jun!O3:O6 -> Employees National Insurance | ... R3: =Jun!R3:R6 -> NET PAY | T3: =Jun!T3:T6 -> Employers National Insurance | V3: Gross Wages | W3: Income Tax | X3: Employees National Insurance | Y3: Student Loan deductions | Z3: Other Deductions | AA3: Net Pay | AC3: Employers National Insurance | AD3: Statutory Sick Pay Recovered | AE3: Statutory Maternity Pay Recovered | AF3: Statutory Paternity Pay Recovered | AG3: Statutory Adoption Pay Recovered
G4: SMP
G5: SPP
G6: SAP
B8: WEEKLY PAYROLL | O8: Date Wages paid
B9: Week number | E9: 5 | H9: Date Wages paid | K9: =Jun!M39+1 -> 45775 | L9: - | M9: =K9+6 -> 45781 | O9: One Click to repeat previous week Enter Y
B11: =IF(E11=" "," ",IF(Employee!F$24>E$9," ",IF(Employee!F$26<E$9," ",Employee!D$30))) | E11: =IF(Employee!D$28="m"," ",IF(Employee!F$24>E$9," ",IF(Employee!F$26<E$9," ",Employee!D$29))) | F11: =IF(E11=" "," ",IF(Employee!F$24>E$9," ",IF(Employee!F$26<E$9," ",Employee!D$15))) | H11: =IF(T$9="Y",Jun!H41,0) -> 0 | I11: =IF(T$9="Y",Jun!I41,0) -> 0 | J11: =IF(T$9="Y",Jun!J41,0) -> 0 | K11: =IF(T$9="Y",Jun!K41,I11*J11) -> 0 | L11: =IF(T$9="Y",Jun!L41,0) -> 0 | M11: =IF(E11=" "," ",IF(T$9="Y",Jun!M41,IF((H11+K11+L11)>0,H11+K11+L11," "))) | N11: 0 | O11: 0 | P11: 0 | Q11: 0 | R11: =IF(M11=" "," ",IF(M11=0," ",M11-SUM(N11:Q11))) | T11: 0 | V11: =IF(Employee!H$34=E$9,Employee!D$34+SUM(M11)+Jun!V41,SUM(M11)+Jun!V41) -> 0 | W11: =IF(Employee!H$34=E$9,Employee!D$35+SUM(N11)+Jun!W41,SUM(N11)+Jun!W41) -> 0 | X11: =IF(O11=" ",Jun!X41,O11+Jun!X41) -> 0 | Y11: =IF(P11=" ",Jun!Y41,P11+Jun!Y41) -> 0 | Z11: =IF(Q11=" ",Jun!Z41,Q11+Jun!Z41) -> 0 | AA11: =IF(R11=" ",Jun!AA41,R11+Jun!AA41) -> 0 | AC11: =IF(T11=" ",Jun!AC41,T11+Jun!AC41) -> 0 | AD11: =IF(G11="SSP",H11,0) -> 0 | AE11: =IF(G11="SMP",H11,0) -> 0 | AF11: =IF(G11="SPP",H11,0) -> 0 | AG11: =IF(G11="SAP",H11,0) -> 0
B12: =IF(E12=" "," ",IF(Employee!F$50>E$9," ",IF(Employee!F$52<E$9," ",Employee!D$56))) | E12: =IF(Employee!D$54="m"," ",IF(Employee!F$50>E$9," ",IF(Employee!F$52<E$9," ",Employee!D$55))) | F12: =IF(E12=" "," ",IF(Employee!F$50>E$9," ",IF(Employee!F$52<E$9," ",Employee!D$41))) | H12: =IF(T$9="Y",Jun!H42,0) -> 0 | I12: =IF(T$9="Y",Jun!I42,0) -> 0 | J12: =IF(T$9="Y",Jun!J42,0) -> 0 | K12: =IF(T$9="Y",Jun!K42,I12*J12) -> 0 | L12: =IF(T$9="Y",Jun!L42,0) -> 0 | M12: =IF(E12=" "," ",IF(T$9="Y",Jun!M42,IF((H12+K12+L12)>0,H12+K12+L12," "))) | N12: 0 | O12: 0 | P12: 0 | Q12: 0 | R12: =IF(M12=" "," ",IF(M12=0," ",M12-SUM(N12:Q12))) | T12: 0 | V12: =IF(Employee!H$60=E$9,Employee!D$60+SUM(M12)+Jun!V42,SUM(M12)+Jun!V42) -> 0 | W12: =IF(Employee!H$60=E$9,Employee!D$61+SUM(N12)+Jun!W42,SUM(N12)+Jun!W42) -> 0 | X12: =IF(O12=" ",Jun!X42,O12+Jun!X42) -> 0 | Y12: =IF(P12=" ",Jun!Y42,P12+Jun!Y42) -> 0 | Z12: =IF(Q12=" ",Jun!Z42,Q12+Jun!Z42) -> 0 | AA12: =IF(R12=" ",Jun!AA42,R12+Jun!AA42) -> 0 | AC12: =IF(T12=" ",Jun!AC42,T12+Jun!AC42) -> 0 | AD12: =IF(G12="SSP",H12,0) -> 0 | AE12: =IF(G12="SMP",H12,0) -> 0 | AF12: =IF(G12="SPP",H12,0) -> 0 | AG12: =IF(G12="SAP",H12,0) -> 0
B13: =IF(E13=" "," ",IF(Employee!F$76>E$9," ",IF(Employee!F$78<E$9," ",Employee!D$82))) | E13: =IF(Employee!D$80="m"," ",IF(Employee!F$76>E$9," ",IF(Employee!F$78<E$9," ",Employee!D$81))) | F13: =IF(E13=" "," ",IF(Employee!F$76>E$9," ",IF(Employee!F$78<E$9," ",Employee!D$67))) | H13: =IF(T$9="Y",Jun!H43,0) -> 0 | I13: =IF(T$9="Y",Jun!I43,0) -> 0 | J13: =IF(T$9="Y",Jun!J43,0) -> 0 | K13: =IF(T$9="Y",Jun!K43,I13*J13) -> 0 | L13: =IF(T$9="Y",Jun!L43,0) -> 0 | M13: =IF(E13=" "," ",IF(T$9="Y",Jun!M43,IF((H13+K13+L13)>0,H13+K13+L13," "))) | N13: 0 | O13: 0 | P13: 0 | Q13: 0 | R13: =IF(M13=" "," ",IF(M13=0," ",M13-SUM(N13:Q13))) | T13: 0 | V13: =IF(Employee!H$86=E$9,Employee!D$86+SUM(M13)+Jun!V43,SUM(M13)+Jun!V43) -> 0 | W13: =IF(Employee!H$86=E$9,Employee!D$87+SUM(N13)+Jun!W43,SUM(N13)+Jun!W43) -> 0 | X13: =IF(O13=" ",Jun!X43,O13+Jun!X43) -> 0 | Y13: =IF(P13=" ",Jun!Y43,P13+Jun!Y43) -> 0 | Z13: =IF(Q13=" ",Jun!Z43,Q13+Jun!Z43) -> 0 | AA13: =IF(R13=" ",Jun!AA43,R13+Jun!AA43) -> 0 | AC13: =IF(T13=" ",Jun!AC43,T13+Jun!AC43) -> 0 | AD13: =IF(G13="SSP",H13,0) -> 0 | AE13: =IF(G13="SMP",H13,0) -> 0 | AF13: =IF(G13="SPP",H13,0) -> 0 | AG13: =IF(G13="SAP",H13,0) -> 0
B14: =IF(E14=" "," ",IF(Employee!F$102>E$9," ",IF(Employee!F$104<E$9," ",Employee!D$108))) | E14: =IF(Employee!D$106="m"," ",IF(Employee!F$102>E$9," ",IF(Employee!F$104<E$9," ",Employee!D$107))) | F14: =IF(E14=" "," ",IF(Employee!F$102>E$9," ",IF(Employee!F$104<E$9," ",Employee!D$93))) | H14: =IF(T$9="Y",Jun!H44,0) -> 0 | I14: =IF(T$9="Y",Jun!I44,0) -> 0 | J14: =IF(T$9="Y",Jun!J44,0) -> 0 | K14: =IF(T$9="Y",Jun!K44,I14*J14) -> 0 | L14: =IF(T$9="Y",Jun!L44,0) -> 0 | M14: =IF(E14=" "," ",IF(T$9="Y",Jun!M44,IF((H14+K14+L14)>0,H14+K14+L14," "))) | N14: 0 | O14: 0 | P14: 0 | Q14: 0 | R14: =IF(M14=" "," ",IF(M14=0," ",M14-SUM(N14:Q14))) | T14: 0 | V14: =IF(Employee!H$112=E$9,Employee!D$112+SUM(M14)+Jun!V44,SUM(M14)+Jun!V44) -> 0 | W14: =IF(Employee!H$112=E$9,Employee!D$113+SUM(N14)+Jun!W44,SUM(N14)+Jun!W44) -> 0 | X14: =IF(O14=" ",Jun!X44,O14+Jun!X44) -> 0 | Y14: =IF(P14=" ",Jun!Y44,P14+Jun!Y44) -> 0 | Z14: =IF(Q14=" ",Jun!Z44,Q14+Jun!Z44) -> 0 | AA14: =IF(R14=" ",Jun!AA44,R14+Jun!AA44) -> 0 | AC14: =IF(T14=" ",Jun!AC44,T14+Jun!AC44) -> 0 | AD14: =IF(G14="SSP",H14,0) -> 0 | AE14: =IF(G14="SMP",H14,0) -> 0 | AF14: =IF(G14="SPP",H14,0) -> 0 | AG14: =IF(G14="SAP",H14,0) -> 0
B15: =IF(E15=" "," ",IF(Employee!F$128>E$9," ",IF(Employee!F$130<E$9," ",Employee!D$134))) | E15: =IF(Employee!D$132="m"," ",IF(Employee!F$128>E$9," ",IF(Employee!F$130<E$9," ",Employee!D$133))) | F15: =IF(E15=" "," ",IF(Employee!F$128>E$9," ",IF(Employee!F$130<E$9," ",Employee!D$119))) | H15: =IF(T$9="Y",Jun!H45,0) -> 0 | I15: =IF(T$9="Y",Jun!I45,0) -> 0 | J15: =IF(T$9="Y",Jun!J45,0) -> 0 | K15: =IF(T$9="Y",Jun!K45,I15*J15) -> 0 | L15: =IF(T$9="Y",Jun!L45,0) -> 0 | M15: =IF(E15=" "," ",IF(T$9="Y",Jun!M45,IF((H15+K15+L15)>0,H15+K15+L15," "))) | N15: 0 | O15: 0 | P15: 0 | Q15: 0 | R15: =IF(M15=" "," ",IF(M15=0," ",M15-SUM(N15:Q15))) | T15: 0 | V15: =IF(Employee!H$138=E$9,Employee!D$138+SUM(M15)+Jun!V45,SUM(M15)+Jun!V45) -> 0 | W15: =IF(Employee!H$138=E$9,Employee!D$139+SUM(N15)+Jun!W45,SUM(N15)+Jun!W45) -> 0 | X15: =IF(O15=" ",Jun!X45,O15+Jun!X45) -> 0 | Y15: =IF(P15=" ",Jun!Y45,P15+Jun!Y45) -> 0 | Z15: =IF(Q15=" ",Jun!Z45,Q15+Jun!Z45) -> 0 | AA15: =IF(R15=" ",Jun!AA45,R15+Jun!AA45) -> 0 | AC15: =IF(T15=" ",Jun!AC45,T15+Jun!AC45) -> 0 | AD15: =IF(G15="SSP",H15,0) -> 0 | AE15: =IF(G15="SMP",H15,0) -> 0 | AF15: =IF(G15="SPP",H15,0) -> 0 | AG15: =IF(G15="SAP",H15,0) -> 0
F16: Payroll Total | M16: =SUM(M11:M15) -> 0 | N16: =SUM(N11:N15) -> 0 | O16: =SUM(O11:O15) -> 0 | P16: =SUM(P11:P15) -> 0 | Q16: =SUM(Q11:Q15) -> 0 | R16: =SUM(R11:R15) -> 0 | T16: =SUM(T11:T15) -> 0
B18: WEEKLY PAYROLL | O18: Date Wages paid
B19: Week number | E19: 6 | H19: Date Wages paid | K19: =M9+1 -> 45782 | L19: - | M19: =K19+6 -> 45788 | O19: One Click to repeat previous week Enter Y
B21: =IF(E21=" "," ",IF(Employee!F$24>E$19," ",IF(Employee!F$26<E$19," ",Employee!D$30))) | E21: =IF(Employee!D$28="m"," ",IF(Employee!F$24>E$19," ",IF(Employee!F$26<E$19," ",Employee!D$29))) | F21: =IF(E21=" "," ",IF(Employee!F$24>E$19," ",IF(Employee!F$26<E$19," ",Employee!D$15))) | H21: =IF(T$19="Y",H11,0) -> 0 | I21: =IF(T$19="Y",I11,0) -> 0 | J21: =IF(T$19="Y",J11,0) -> 0 | K21: =IF(T$19="Y",K11,I21*J21) -> 0 | L21: =IF(T$19="Y",L11,0) -> 0 | M21: =IF(E21=" "," ",IF(T$19="Y",M11,IF((H21+K21+L21)>0,H21+K21+L21," "))) | N21: 0 | O21: 0 | P21: 0 | Q21: 0 | R21: =IF(M21=" "," ",IF(M21=0," ",M21-SUM(N21:Q21))) | T21: 0 | V21: =IF(Employee!H$34=E$19,Employee!D$34+SUM(M21)+V11,SUM(M21)+V11) -> 0 | W21: =IF(Employee!H$34=E$19,Employee!D$35+SUM(N21)+W11,SUM(N21)+W11) -> 0 | X21: =IF(O21=" ",X11,O21+X11) -> 0 | Y21: =IF(P21=0,Y11,P21+Y11) -> 0 | Z21: =IF(Q21=0,Z11,Q21+Z11) -> 0 | AA21: =IF(R21=" ",AA11,AA11+R21) -> 0 | AC21: =IF(T21=" ",AC11,T21+AC11) -> 0 | AD21: =IF(G21="SSP",H21,0) -> 0 | AE21: =IF(G21="SMP",H21,0) -> 0 | AF21: =IF(G21="SPP",H21,0) -> 0 | AG21: =IF(G21="SAP",H21,0) -> 0
B22: =IF(E22=" "," ",IF(Employee!F$50>E$19," ",IF(Employee!F$52<E$19," ",Employee!D$56))) | E22: =IF(Employee!D$54="m"," ",IF(Employee!F$50>E$19," ",IF(Employee!F$52<E$19," ",Employee!D$55))) | F22: =IF(E22=" "," ",IF(Employee!F$50>E$19," ",IF(Employee!F$52<E$19," ",Employee!D$41))) | H22: =IF(T$19="Y",H12,0) -> 0 | I22: =IF(T$19="Y",I12,0) -> 0 | J22: =IF(T$19="Y",J12,0) -> 0 | K22: =IF(T$19="Y",K12,I22*J22) -> 0 | L22: =IF(T$19="Y",L12,0) -> 0 | M22: =IF(E22=" "," ",IF(T$19="Y",M12,IF((H22+K22+L22)>0,H22+K22+L22," "))) | N22: 0 | O22: 0 | P22: 0 | Q22: 0 | R22: =IF(M22=" "," ",IF(M22=0," ",M22-SUM(N22:Q22))) | T22: 0 | V22: =IF(Employee!H$60=E$19,Employee!D$60+SUM(M22)+V12,SUM(M22)+V12) -> 0 | W22: =IF(Employee!H$60=E$19,Employee!D$61+SUM(N22)+W12,SUM(N22)+W12) -> 0 | X22: =IF(O22=" ",X12,O22+X12) -> 0 | Y22: =IF(P22=0,Y12,P22+Y12) -> 0 | Z22: =IF(Q22=0,Z12,Q22+Z12) -> 0 | AA22: =IF(R22=" ",AA12,AA12+R22) -> 0 | AC22: =IF(T22=" ",AC12,T22+AC12) -> 0 | AD22: =IF(G22="SSP",H22,0) -> 0 | AE22: =IF(G22="SMP",H22,0) -> 0 | AF22: =IF(G22="SPP",H22,0) -> 0 | AG22: =IF(G22="SAP",H22,0) -> 0
B23: =IF(E23=" "," ",IF(Employee!F$76>E$19," ",IF(Employee!F$78<E$19," ",Employee!D$82))) | E23: =IF(Employee!D$80="m"," ",IF(Employee!F$76>E$19," ",IF(Employee!F$78<E$19," ",Employee!D$81))) | F23: =IF(E23=" "," ",IF(Employee!F$76>E$19," ",IF(Employee!F$78<E$19," ",Employee!D$67))) | H23: =IF(T$19="Y",H13,0) -> 0 | I23: =IF(T$19="Y",I13,0) -> 0 | J23: =IF(T$19="Y",J13,0) -> 0 | K23: =IF(T$19="Y",K13,I23*J23) -> 0 | L23: =IF(T$19="Y",L13,0) -> 0 | M23: =IF(E23=" "," ",IF(T$19="Y",M13,IF((H23+K23+L23)>0,H23+K23+L23," "))) | N23: 0 | O23: 0 | P23: 0 | Q23: 0 | R23: =IF(M23=" "," ",IF(M23=0," ",M23-SUM(N23:Q23))) | T23: 0 | V23: =IF(Employee!H$86=E$19,Employee!D$86+SUM(M23)+V13,SUM(M23)+V13) -> 0 | W23: =IF(Employee!H$86=E$19,Employee!D$87+SUM(N23)+W13,SUM(N23)+W13) -> 0 | X23: =IF(O23=" ",X13,O23+X13) -> 0 | Y23: =IF(P23=0,Y13,P23+Y13) -> 0 | Z23: =IF(Q23=0,Z13,Q23+Z13) -> 0 | AA23: =IF(R23=" ",AA13,AA13+R23) -> 0 | AC23: =IF(T23=" ",AC13,T23+AC13) -> 0 | AD23: =IF(G23="SSP",H23,0) -> 0 | AE23: =IF(G23="SMP",H23,0) -> 0 | AF23: =IF(G23="SPP",H23,0) -> 0 | AG23: =IF(G23="SAP",H23,0) -> 0
B24: =IF(E24=" "," ",IF(Employee!F$102>E$19," ",IF(Employee!F$104<E$19," ",Employee!D$108))) | E24: =IF(Employee!D$106="m"," ",IF(Employee!F$102>E$19," ",IF(Employee!F$104<E$19," ",Employee!D$107))) | F24: =IF(E24=" "," ",IF(Employee!F$102>E$19," ",IF(Employee!F$104<E$19," ",Employee!D$93))) | H24: =IF(T$19="Y",H14,0) -> 0 | I24: =IF(T$19="Y",I14,0) -> 0 | J24: =IF(T$19="Y",J14,0) -> 0 | K24: =IF(T$19="Y",K14,I24*J24) -> 0 | L24: =IF(T$19="Y",L14,0) -> 0 | M24: =IF(E24=" "," ",IF(T$19="Y",M14,IF((H24+K24+L24)>0,H24+K24+L24," "))) | N24: 0 | O24: 0 | P24: 0 | Q24: 0 | R24: =IF(M24=" "," ",IF(M24=0," ",M24-SUM(N24:Q24))) | T24: 0 | V24: =IF(Employee!H$112=E$19,Employee!D$112+SUM(M24)+V14,SUM(M24)+V14) -> 0 | W24: =IF(Employee!H$112=E$19,Employee!D$113+SUM(N24)+W14,SUM(N24)+W14) -> 0 | X24: =IF(O24=" ",X14,O24+X14) -> 0 | Y24: =IF(P24=0,Y14,P24+Y14) -> 0 | Z24: =IF(Q24=0,Z14,Q24+Z14) -> 0 | AA24: =IF(R24=" ",AA14,AA14+R24) -> 0 | AC24: =IF(T24=" ",AC14,T24+AC14) -> 0 | AD24: =IF(G24="SSP",H24,0) -> 0 | AE24: =IF(G24="SMP",H24,0) -> 0 | AF24: =IF(G24="SPP",H24,0) -> 0 | AG24: =IF(G24="SAP",H24,0) -> 0
B25: =IF(E25=" "," ",IF(Employee!F$128>E$19," ",IF(Employee!F$130<E$19," ",Employee!D$134))) | E25: =IF(Employee!D$132="m"," ",IF(Employee!F$128>E$19," ",IF(Employee!F$130<E$19," ",Employee!D$133))) | F25: =IF(E25=" "," ",IF(Employee!F$128>E$19," ",IF(Employee!F$130<E$19," ",Employee!D$119))) | H25: =IF(T$19="Y",H15,0) -> 0 | I25: =IF(T$19="Y",I15,0) -> 0 | J25: =IF(T$19="Y",J15,0) -> 0 | K25: =IF(T$19="Y",K15,I25*J25) -> 0 | L25: =IF(T$19="Y",L15,0) -> 0 | M25: =IF(E25=" "," ",IF(T$19="Y",M15,IF((H25+K25+L25)>0,H25+K25+L25," "))) | N25: 0 | O25: 0 | P25: 0 | Q25: 0 | R25: =IF(M25=" "," ",IF(M25=0," ",M25-SUM(N25:Q25))) | T25: 0 | V25: =IF(Employee!H$138=E$19,Employee!D$138+SUM(M25)+V15,SUM(M25)+V15) -> 0 | W25: =IF(Employee!H$138=E$19,Employee!D$139+SUM(N25)+W15,SUM(N25)+W15) -> 0 | X25: =IF(O25=" ",X15,O25+X15) -> 0 | Y25: =IF(P25=0,Y15,P25+Y15) -> 0 | Z25: =IF(Q25=0,Z15,Q25+Z15) -> 0 | AA25: =IF(R25=" ",AA15,AA15+R25) -> 0 | AC25: =IF(T25=" ",AC15,T25+AC15) -> 0 | AD25: =IF(G25="SSP",H25,0) -> 0 | AE25: =IF(G25="SMP",H25,0) -> 0 | AF25: =IF(G25="SPP",H25,0) -> 0 | AG25: =IF(G25="SAP",H25,0) -> 0
F26: Payroll Total | M26: =SUM(M21:M25) -> 0 | N26: =SUM(N21:N25) -> 0 | O26: =SUM(O21:O25) -> 0 | P26: =SUM(P21:P25) -> 0 | Q26: =SUM(Q21:Q25) -> 0 | R26: =SUM(R21:R25) -> 0 | T26: =SUM(T21:T25) -> 0
B28: WEEKLY PAYROLL | O28: Date Wages paid
B29: Week number | E29: 7 | H29: Date Wages paid | K29: =M19+1 -> 45789 | L29: - | M29: =K29+6 -> 45795 | O29: One Click to repeat previous week Enter Y
B31: =IF(E31=" "," ",IF(Employee!F$24>E$29," ",IF(Employee!F$26<E$29," ",Employee!D$30))) | E31: =IF(Employee!D$28="m"," ",IF(Employee!F$24>E$29," ",IF(Employee!F$26<E$29," ",Employee!D$29))) | F31: =IF(E31=" "," ",IF(Employee!F$24>E$29," ",IF(Employee!F$26<E$29," ",Employee!D$15))) | H31: =IF(T$29="Y",H21,0) -> 0 | I31: =IF(T$29="Y",I21,0) -> 0 | J31: =IF(T$29="Y",J21,0) -> 0 | K31: =IF(T$29="Y",K21,I31*J31) -> 0 | L31: =IF(T$29="Y",L21,0) -> 0 | M31: =IF(E31=" "," ",IF(T$29="Y",M21,IF((H31+K31+L31)>0,H31+K31+L31," "))) | N31: 0 | O31: 0 | P31: 0 | Q31: 0 | R31: =IF(M31=" "," ",IF(M31=0," ",M31-SUM(N31:Q31))) | T31: 0 | V31: =IF(Employee!H$34=E$29,Employee!D$34+SUM(M31)+V21,SUM(M31)+V21) -> 0 | W31: =IF(Employee!H$34=E$29,Employee!D$35+SUM(N31)+W21,SUM(N31)+W21) -> 0 | X31: =IF(O31=" ",X21,O31+X21) -> 0 | Y31: =IF(P31=0,Y21,P31+Y21) -> 0 | Z31: =IF(Q31=0,Z21,Q31+Z21) -> 0 | AA31: =IF(R31=" ",AA21,AA21+R31) -> 0 | AC31: =IF(T31=" ",AC21,T31+AC21) -> 0 | AD31: =IF(G31="SSP",H31,0) -> 0 | AE31: =IF(G31="SMP",H31,0) -> 0 | AF31: =IF(G31="SPP",H31,0) -> 0 | AG31: =IF(G31="SAP",H31,0) -> 0
B32: =IF(E32=" "," ",IF(Employee!F$50>E$29," ",IF(Employee!F$52<E$29," ",Employee!D$56))) | E32: =IF(Employee!D$54="m"," ",IF(Employee!F$50>E$29," ",IF(Employee!F$52<E$29," ",Employee!D$55))) | F32: =IF(E32=" "," ",IF(Employee!F$50>E$29," ",IF(Employee!F$52<E$29," ",Employee!D$41))) | H32: =IF(T$29="Y",H22,0) -> 0 | I32: =IF(T$29="Y",I22,0) -> 0 | J32: =IF(T$29="Y",J22,0) -> 0 | K32: =IF(T$29="Y",K22,I32*J32) -> 0 | L32: =IF(T$29="Y",L22,0) -> 0 | M32: =IF(E32=" "," ",IF(T$29="Y",M22,IF((H32+K32+L32)>0,H32+K32+L32," "))) | N32: 0 | O32: 0 | P32: 0 | Q32: 0 | R32: =IF(M32=" "," ",IF(M32=0," ",M32-SUM(N32:Q32))) | T32: 0 | V32: =IF(Employee!H$60=E$29,Employee!D$60+SUM(M32)+V22,SUM(M32)+V22) -> 0 | W32: =IF(Employee!H$60=E$29,Employee!D$61+SUM(N32)+W22,SUM(N32)+W22) -> 0 | X32: =IF(O32=" ",X22,O32+X22) -> 0 | Y32: =IF(P32=0,Y22,P32+Y22) -> 0 | Z32: =IF(Q32=0,Z22,Q32+Z22) -> 0 | AA32: =IF(R32=" ",AA22,AA22+R32) -> 0 | AC32: =IF(T32=" ",AC22,T32+AC22) -> 0 | AD32: =IF(G32="SSP",H32,0) -> 0 | AE32: =IF(G32="SMP",H32,0) -> 0 | AF32: =IF(G32="SPP",H32,0) -> 0 | AG32: =IF(G32="SAP",H32,0) -> 0
B33: =IF(E33=" "," ",IF(Employee!F$76>E$29," ",IF(Employee!F$78<E$29," ",Employee!D$82))) | E33: =IF(Employee!D$80="m"," ",IF(Employee!F$76>E$29," ",IF(Employee!F$78<E$29," ",Employee!D$81))) | F33: =IF(E33=" "," ",IF(Employee!F$76>E$29," ",IF(Employee!F$78<E$29," ",Employee!D$67))) | H33: =IF(T$29="Y",H23,0) -> 0 | I33: =IF(T$29="Y",I23,0) -> 0 | J33: =IF(T$29="Y",J23,0) -> 0 | K33: =IF(T$29="Y",K23,I33*J33) -> 0 | L33: =IF(T$29="Y",L23,0) -> 0 | M33: =IF(E33=" "," ",IF(T$29="Y",M23,IF((H33+K33+L33)>0,H33+K33+L33," "))) | N33: 0 | O33: 0 | P33: 0 | Q33: 0 | R33: =IF(M33=" "," ",IF(M33=0," ",M33-SUM(N33:Q33))) | T33: 0 | V33: =IF(Employee!H$86=E$29,Employee!D$86+SUM(M33)+V23,SUM(M33)+V23) -> 0 | W33: =IF(Employee!H$86=E$29,Employee!D$87+SUM(N33)+W23,SUM(N33)+W23) -> 0 | X33: =IF(O33=" ",X23,O33+X23) -> 0 | Y33: =IF(P33=0,Y23,P33+Y23) -> 0 | Z33: =IF(Q33=0,Z23,Q33+Z23) -> 0 | AA33: =IF(R33=" ",AA23,AA23+R33) -> 0 | AC33: =IF(T33=" ",AC23,T33+AC23) -> 0 | AD33: =IF(G33="SSP",H33,0) -> 0 | AE33: =IF(G33="SMP",H33,0) -> 0 | AF33: =IF(G33="SPP",H33,0) -> 0 | AG33: =IF(G33="SAP",H33,0) -> 0
B34: =IF(E34=" "," ",IF(Employee!F$102>E$29," ",IF(Employee!F$104<E$29," ",Employee!D$108))) | E34: =IF(Employee!D$106="m"," ",IF(Employee!F$102>E$29," ",IF(Employee!F$104<E$29," ",Employee!D$107))) | F34: =IF(E34=" "," ",IF(Employee!F$102>E$29," ",IF(Employee!F$104<E$29," ",Employee!D$93))) | H34: =IF(T$29="Y",H24,0) -> 0 | I34: =IF(T$29="Y",I24,0) -> 0 | J34: =IF(T$29="Y",J24,0) -> 0 | K34: =IF(T$29="Y",K24,I34*J34) -> 0 | L34: =IF(T$29="Y",L24,0) -> 0 | M34: =IF(E34=" "," ",IF(T$29="Y",M24,IF((H34+K34+L34)>0,H34+K34+L34," "))) | N34: 0 | O34: 0 | P34: 0 | Q34: 0 | R34: =IF(M34=" "," ",IF(M34=0," ",M34-SUM(N34:Q34))) | T34: 0 | V34: =IF(Employee!H$112=E$29,Employee!D$112+SUM(M34)+V24,SUM(M34)+V24) -> 0 | W34: =IF(Employee!H$112=E$29,Employee!D$113+SUM(N34)+W24,SUM(N34)+W24) -> 0 | X34: =IF(O34=" ",X24,O34+X24) -> 0 | Y34: =IF(P34=0,Y24,P34+Y24) -> 0 | Z34: =IF(Q34=0,Z24,Q34+Z24) -> 0 | AA34: =IF(R34=" ",AA24,AA24+R34) -> 0 | AC34: =IF(T34=" ",AC24,T34+AC24) -> 0 | AD34: =IF(G34="SSP",H34,0) -> 0 | AE34: =IF(G34="SMP",H34,0) -> 0 | AF34: =IF(G34="SPP",H34,0) -> 0 | AG34: =IF(G34="SAP",H34,0) -> 0
B35: =IF(E35=" "," ",IF(Employee!F$128>E$29," ",IF(Employee!F$130<E$29," ",Employee!D$134))) | E35: =IF(Employee!D$132="m"," ",IF(Employee!F$128>E$29," ",IF(Employee!F$130<E$29," ",Employee!D$133))) | F35: =IF(E35=" "," ",IF(Employee!F$128>E$29," ",IF(Employee!F$130<E$29," ",Employee!D$119))) | H35: =IF(T$29="Y",H25,0) -> 0 | I35: =IF(T$29="Y",I25,0) -> 0 | J35: =IF(T$29="Y",J25,0) -> 0 | K35: =IF(T$29="Y",K25,I35*J35) -> 0 | L35: =IF(T$29="Y",L25,0) -> 0 | M35: =IF(E35=" "," ",IF(T$29="Y",M25,IF((H35+K35+L35)>0,H35+K35+L35," "))) | N35: 0 | O35: 0 | P35: 0 | Q35: 0 | R35: =IF(M35=" "," ",IF(M35=0," ",M35-SUM(N35:Q35))) | T35: 0 | V35: =IF(Employee!H$138=E$29,Employee!D$138+SUM(M35)+V25,SUM(M35)+V25) -> 0 | W35: =IF(Employee!H$138=E$29,Employee!D$139+SUM(N35)+W25,SUM(N35)+W25) -> 0 | X35: =IF(O35=" ",X25,O35+X25) -> 0 | Y35: =IF(P35=0,Y25,P35+Y25) -> 0 | Z35: =IF(Q35=0,Z25,Q35+Z25) -> 0 | AA35: =IF(R35=" ",AA25,AA25+R35) -> 0 | AC35: =IF(T35=" ",AC25,T35+AC25) -> 0 | AD35: =IF(G35="SSP",H35,0) -> 0 | AE35: =IF(G35="SMP",H35,0) -> 0 | AF35: =IF(G35="SPP",H35,0) -> 0 | AG35: =IF(G35="SAP",H35,0) -> 0
F36: Payroll Total | M36: =SUM(M31:M35) -> 0 | N36: =SUM(N31:N35) -> 0 | O36: =SUM(O31:O35) -> 0 | P36: =SUM(P31:P35) -> 0 | Q36: =SUM(Q31:Q35) -> 0 | R36: =SUM(R31:R35) -> 0 | T36: =SUM(T31:T35) -> 0
B38: WEEKLY PAYROLL | O38: Date Wages paid
B39: Week number | E39: 8 | H39: Date Wages paid | K39: =M29+1 -> 45796 | L39: - | M39: =K39+6 -> 45802 | O39: One Click to repeat previous week Enter Y
B41: =IF(E41=" "," ",IF(Employee!F$24>E$39," ",IF(Employee!F$26<E$39," ",Employee!D$30))) | E41: =IF(Employee!D$28="m"," ",IF(Employee!F$24>E$39," ",IF(Employee!F$26<E$39," ",Employee!D$29))) | F41: =IF(E41=" "," ",IF(Employee!F$24>E$39," ",IF(Employee!F$26<E$39," ",Employee!D$15))) | H41: =IF(T$39="Y",H31,0) -> 0 | I41: =IF(T$39="Y",I31,0) -> 0 | J41: =IF(T$39="Y",J31,0) -> 0 | K41: =IF(T$39="Y",K31,I41*J41) -> 0 | L41: =IF(T$39="Y",L31,0) -> 0 | M41: =IF(E41=" "," ",IF(T$39="Y",M31,IF((H41+K41+L41)>0,H41+K41+L41," "))) | N41: 0 | O41: 0 | P41: 0 | Q41: 0 | R41: =IF(M41=" "," ",IF(M41=0," ",M41-SUM(N41:Q41))) | T41: 0 | V41: =IF(Employee!H$34=E$39,Employee!D$34+SUM(M41)+V31,SUM(M41)+V31) -> 0 | W41: =IF(Employee!H$34=E$39,Employee!D$35+SUM(N41)+W31,SUM(N41)+W31) -> 0 | X41: =IF(O41=" ",X31,O41+X31) -> 0 | Y41: =IF(P41=0,Y31,P41+Y31) -> 0 | Z41: =IF(Q41=0,Z31,Q41+Z31) -> 0 | AA41: =IF(R41=" ",AA31,AA31+R41) -> 0 | AC41: =IF(T41=" ",AC31,T41+AC31) -> 0 | AD41: =IF(G41="SSP",H41,0) -> 0 | AE41: =IF(G41="SMP",H41,0) -> 0 | AF41: =IF(G41="SPP",H41,0) -> 0 | AG41: =IF(G41="SAP",H41,0) -> 0
B42: =IF(E42=" "," ",IF(Employee!F$50>E$39," ",IF(Employee!F$52<E$39," ",Employee!D$56))) | E42: =IF(Employee!D$54="m"," ",IF(Employee!F$50>E$39," ",IF(Employee!F$52<E$39," ",Employee!D$55))) | F42: =IF(E42=" "," ",IF(Employee!F$50>E$39," ",IF(Employee!F$52<E$39," ",Employee!D$41))) | H42: =IF(T$39="Y",H32,0) -> 0 | I42: =IF(T$39="Y",I32,0) -> 0 | J42: =IF(T$39="Y",J32,0) -> 0 | K42: =IF(T$39="Y",K32,I42*J42) -> 0 | L42: =IF(T$39="Y",L32,0) -> 0 | M42: =IF(E42=" "," ",IF(T$39="Y",M32,IF((H42+K42+L42)>0,H42+K42+L42," "))) | N42: 0 | O42: 0 | P42: 0 | Q42: 0 | R42: =IF(M42=" "," ",IF(M42=0," ",M42-SUM(N42:Q42))) | T42: 0 | V42: =IF(Employee!H$60=E$39,Employee!D$60+SUM(M42)+V32,SUM(M42)+V32) -> 0 | W42: =IF(Employee!H$60=E$39,Employee!D$61+SUM(N42)+W32,SUM(N42)+W32) -> 0 | X42: =IF(O42=" ",X32,O42+X32) -> 0 | Y42: =IF(P42=0,Y32,P42+Y32) -> 0 | Z42: =IF(Q42=0,Z32,Q42+Z32) -> 0 | AA42: =IF(R42=" ",AA32,AA32+R42) -> 0 | AC42: =IF(T42=" ",AC32,T42+AC32) -> 0 | AD42: =IF(G42="SSP",H42,0) -> 0 | AE42: =IF(G42="SMP",H42,0) -> 0 | AF42: =IF(G42="SPP",H42,0) -> 0 | AG42: =IF(G42="SAP",H42,0) -> 0
B43: =IF(E43=" "," ",IF(Employee!F$76>E$39," ",IF(Employee!F$78<E$39," ",Employee!D$82))) | E43: =IF(Employee!D$80="m"," ",IF(Employee!F$76>E$39," ",IF(Employee!F$78<E$39," ",Employee!D$81))) | F43: =IF(E43=" "," ",IF(Employee!F$76>E$39," ",IF(Employee!F$78<E$39," ",Employee!D$67))) | H43: =IF(T$39="Y",H33,0) -> 0 | I43: =IF(T$39="Y",I33,0) -> 0 | J43: =IF(T$39="Y",J33,0) -> 0 | K43: =IF(T$39="Y",K33,I43*J43) -> 0 | L43: =IF(T$39="Y",L33,0) -> 0 | M43: =IF(E43=" "," ",IF(T$39="Y",M33,IF((H43+K43+L43)>0,H43+K43+L43," "))) | N43: 0 | O43: 0 | P43: 0 | Q43: 0 | R43: =IF(M43=" "," ",IF(M43=0," ",M43-SUM(N43:Q43))) | T43: 0 | V43: =IF(Employee!H$86=E$39,Employee!D$86+SUM(M43)+V33,SUM(M43)+V33) -> 0 | W43: =IF(Employee!H$86=E$39,Employee!D$87+SUM(N43)+W33,SUM(N43)+W33) -> 0 | X43: =IF(O43=" ",X33,O43+X33) -> 0 | Y43: =IF(P43=0,Y33,P43+Y33) -> 0 | Z43: =IF(Q43=0,Z33,Q43+Z33) -> 0 | AA43: =IF(R43=" ",AA33,AA33+R43) -> 0 | AC43: =IF(T43=" ",AC33,T43+AC33) -> 0 | AD43: =IF(G43="SSP",H43,0) -> 0 | AE43: =IF(G43="SMP",H43,0) -> 0 | AF43: =IF(G43="SPP",H43,0) -> 0 | AG43: =IF(G43="SAP",H43,0) -> 0
B44: =IF(E44=" "," ",IF(Employee!F$102>E$39," ",IF(Employee!F$104<E$39," ",Employee!D$108))) | E44: =IF(Employee!D$106="m"," ",IF(Employee!F$102>E$39," ",IF(Employee!F$104<E$39," ",Employee!D$107))) | F44: =IF(E44=" "," ",IF(Employee!F$102>E$39," ",IF(Employee!F$104<E$39," ",Employee!D$93))) | H44: =IF(T$39="Y",H34,0) -> 0 | I44: =IF(T$39="Y",I34,0) -> 0 | J44: =IF(T$39="Y",J34,0) -> 0 | K44: =IF(T$39="Y",K34,I44*J44) -> 0 | L44: =IF(T$39="Y",L34,0) -> 0 | M44: =IF(E44=" "," ",IF(T$39="Y",M34,IF((H44+K44+L44)>0,H44+K44+L44," "))) | N44: 0 | O44: 0 | P44: 0 | Q44: 0 | R44: =IF(M44=" "," ",IF(M44=0," ",M44-SUM(N44:Q44))) | T44: 0 | V44: =IF(Employee!H$112=E$39,Employee!D$112+SUM(M44)+V34,SUM(M44)+V34) -> 0 | W44: =IF(Employee!H$112=E$39,Employee!D$113+SUM(N44)+W34,SUM(N44)+W34) -> 0 | X44: =IF(O44=" ",X34,O44+X34) -> 0 | Y44: =IF(P44=0,Y34,P44+Y34) -> 0 | Z44: =IF(Q44=0,Z34,Q44+Z34) -> 0 | AA44: =IF(R44=" ",AA34,AA34+R44) -> 0 | AC44: =IF(T44=" ",AC34,T44+AC34) -> 0 | AD44: =IF(G44="SSP",H44,0) -> 0 | AE44: =IF(G44="SMP",H44,0) -> 0 | AF44: =IF(G44="SPP",H44,0) -> 0 | AG44: =IF(G44="SAP",H44,0) -> 0
B45: =IF(E45=" "," ",IF(Employee!F$128>E$39," ",IF(Employee!F$130<E$39," ",Employee!D$134))) | E45: =IF(Employee!D$132="m"," ",IF(Employee!F$128>E$39," ",IF(Employee!F$130<E$39," ",Employee!D$133))) | F45: =IF(E45=" "," ",IF(Employee!F$128>E$39," ",IF(Employee!F$130<E$39," ",Employee!D$119))) | H45: =IF(T$39="Y",H35,0) -> 0 | I45: =IF(T$39="Y",I35,0) -> 0 | J45: =IF(T$39="Y",J35,0) -> 0 | K45: =IF(T$39="Y",K35,I45*J45) -> 0 | L45: =IF(T$39="Y",L35,0) -> 0 | M45: =IF(E45=" "," ",IF(T$39="Y",M35,IF((H45+K45+L45)>0,H45+K45+L45," "))) | N45: 0 | O45: 0 | P45: 0 | Q45: 0 | R45: =IF(M45=" "," ",IF(M45=0," ",M45-SUM(N45:Q45))) | T45: 0 | V45: =IF(Employee!H$138=E$39,Employee!D$138+SUM(M45)+V35,SUM(M45)+V35) -> 0 | W45: =IF(Employee!H$138=E$39,Employee!D$139+SUM(N45)+W35,SUM(N45)+W35) -> 0 | X45: =IF(O45=" ",X35,O45+X35) -> 0 | Y45: =IF(P45=0,Y35,P45+Y35) -> 0 | Z45: =IF(Q45=0,Z35,Q45+Z35) -> 0 | AA45: =IF(R45=" ",AA35,AA35+R45) -> 0 | AC45: =IF(T45=" ",AC35,T45+AC35) -> 0 | AD45: =IF(G45="SSP",H45,0) -> 0 | AE45: =IF(G45="SMP",H45,0) -> 0 | AF45: =IF(G45="SPP",H45,0) -> 0 | AG45: =IF(G45="SAP",H45,0) -> 0
F46: Payroll Total | M46: =SUM(M41:M45) -> 0 | N46: =SUM(N41:N45) -> 0 | O46: =SUM(O41:O45) -> 0 | P46: =SUM(P41:P45) -> 0 | Q46: =SUM(Q41:Q45) -> 0 | R46: =SUM(R41:R45) -> 0 | T46: =SUM(T41:T45) -> 0
B48: MONTHLY PAYROLL | O48: Date Wages paid
B49: Month number | E49: 2 | H49: Date Wages paid | K49: =DATE(2024,7,1) -> 45474 | L49: - | M49: =DATE(2024,7,31) -> 45504 | O49: One Click to repeat previous month Enter Y
B51: =IF(E51=" "," ",IF(Employee!F$24>E$49," ",IF(Employee!F$26<E$49," ",Employee!D$30))) | E51: =IF(Employee!D$28="w"," ",IF(Employee!F$24>E$49," ",IF(Employee!F$26<E$49," ",Employee!D$29))) | F51: =IF(E51=" "," ",IF(Employee!F$24>E$49," ",IF(Employee!F$26<E$49," ",Employee!D$15))) | H51: =IF(T$49="Y",Jun!H51,0) -> 0 | I51: =IF(T$49="Y",Jun!I51,0) -> 0 | J51: =IF(T$49="Y",Jun!J51,0) -> 0 | K51: =IF(T$49="Y",Jun!K51,I51*J51) -> 0 | L51: =IF(T$49="Y",Jun!L51,0) -> 0 | M51: =IF(E51=" "," ",IF(T$49="Y",Jun!M51,IF((H51+K51+L51)>0,H51+K51+L51," "))) | N51: 0 | O51: 0 | P51: 0 | Q51: 0 | R51: =IF(M51=" "," ",IF(M51=0," ",M51-SUM(N51:Q51))) | T51: 0 | V51: =IF(Employee!H$35=E$49,Employee!D$34+SUM(M51)+Jun!V51,SUM(M51)+Jun!V51) -> 0 | W51: =IF(Employee!H$35=E$49,Employee!D$35+SUM(N51)+Jun!W51,SUM(N51)+Jun!W51) -> 0 | X51: =IF(O51=" ",Jun!X51,O51+Jun!X51) -> 0 | Y51: =IF(P51=" ",Jun!Y51,P51+Jun!Y51) -> 0 | Z51: =IF(Q51=" ",Jun!Z51,Q51+Jun!Z51) -> 0 | AA51: =IF(R51=" ",Jun!AA51,R51+Jun!AA51) -> 0 | AC51: =IF(T51=" ",Jun!AC51,T51+Jun!AC51) -> 0 | AD51: =IF(G51="SSP",H51,0) -> 0 | AE51: =IF(G51="SMP",H51,0) -> 0 | AF51: =IF(G51="SPP",H51,0) -> 0 | AG51: =IF(G51="SAP",H51,0) -> 0
B52: =IF(E52=" "," ",IF(Employee!F$50>E$49," ",IF(Employee!F$52<E$49," ",Employee!D$56))) | E52: =IF(Employee!D$54="w"," ",IF(Employee!F$50>E$49," ",IF(Employee!F$52<E$49," ",Employee!D$55))) | F52: =IF(E52=" "," ",IF(Employee!F$50>E$49," ",IF(Employee!F$52<E$49," ",Employee!D$41))) | H52: =IF(T$49="Y",Jun!H52,0) -> 0 | I52: =IF(T$49="Y",Jun!I52,0) -> 0 | J52: =IF(T$49="Y",Jun!J52,0) -> 0 | K52: =IF(T$49="Y",Jun!K52,I52*J52) -> 0 | L52: =IF(T$49="Y",Jun!L52,0) -> 0 | M52: =IF(E52=" "," ",IF(T$49="Y",Jun!M52,IF((H52+K52+L52)>0,H52+K52+L52," "))) | N52: 0 | O52: 0 | P52: 0 | Q52: 0 | R52: =IF(M52=" "," ",IF(M52=0," ",M52-SUM(N52:Q52))) | T52: 0 | V52: =IF(Employee!H$61=E$49,Employee!D$60+SUM(M52)+Jun!V52,SUM(M52)+Jun!V52) -> 0 | W52: =IF(Employee!H$61=E$49,Employee!D$61+SUM(N52)+Jun!W52,SUM(N52)+Jun!W52) -> 0 | X52: =IF(O52=" ",Jun!X52,O52+Jun!X52) -> 0 | Y52: =IF(P52=" ",Jun!Y52,P52+Jun!Y52) -> 0 | Z52: =IF(Q52=" ",Jun!Z52,Q52+Jun!Z52) -> 0 | AA52: =IF(R52=" ",Jun!AA52,R52+Jun!AA52) -> 0 | AC52: =IF(T52=" ",Jun!AC52,T52+Jun!AC52) -> 0 | AD52: =IF(G52="SSP",H52,0) -> 0 | AE52: =IF(G52="SMP",H52,0) -> 0 | AF52: =IF(G52="SPP",H52,0) -> 0 | AG52: =IF(G52="SAP",H52,0) -> 0
B53: =IF(E53=" "," ",IF(Employee!F$76>E$49," ",IF(Employee!F$78<E$49," ",Employee!D$82))) | E53: =IF(Employee!D$80="w"," ",IF(Employee!F$76>E$49," ",IF(Employee!F$78<E$49," ",Employee!D$81))) | F53: =IF(E53=" "," ",IF(Employee!F$76>E$49," ",IF(Employee!F$78<E$49," ",Employee!D$67))) | H53: =IF(T$49="Y",Jun!H53,0) -> 0 | I53: =IF(T$49="Y",Jun!I53,0) -> 0 | J53: =IF(T$49="Y",Jun!J53,0) -> 0 | K53: =IF(T$49="Y",Jun!K53,I53*J53) -> 0 | L53: =IF(T$49="Y",Jun!L53,0) -> 0 | M53: =IF(E53=" "," ",IF(T$49="Y",Jun!M53,IF((H53+K53+L53)>0,H53+K53+L53," "))) | N53: 0 | O53: 0 | P53: 0 | Q53: 0 | R53: =IF(M53=" "," ",IF(M53=0," ",M53-SUM(N53:Q53))) | T53: 0 | V53: =IF(Employee!H$87=E$49,Employee!D$86+SUM(M53)+Jun!V53,SUM(M53)+Jun!V53) -> 0 | W53: =IF(Employee!H$87=E$49,Employee!D$7+SUM(N53)+Jun!W53,SUM(N53)+Jun!W53) -> 0 | X53: =IF(O53=" ",Jun!X53,O53+Jun!X53) -> 0 | Y53: =IF(P53=" ",Jun!Y53,P53+Jun!Y53) -> 0 | Z53: =IF(Q53=" ",Jun!Z53,Q53+Jun!Z53) -> 0 | AA53: =IF(R53=" ",Jun!AA53,R53+Jun!AA53) -> 0 | AC53: =IF(T53=" ",Jun!AC53,T53+Jun!AC53) -> 0 | AD53: =IF(G53="SSP",H53,0) -> 0 | AE53: =IF(G53="SMP",H53,0) -> 0 | AF53: =IF(G53="SPP",H53,0) -> 0 | AG53: =IF(G53="SAP",H53,0) -> 0
B54: =IF(E54=" "," ",IF(Employee!F$102>E$49," ",IF(Employee!F$104<E$49," ",Employee!D$108))) | E54: =IF(Employee!D$106="w"," ",IF(Employee!F$102>E$49," ",IF(Employee!F$104<E$49," ",Employee!D$107))) | F54: =IF(E54=" "," ",IF(Employee!F$102>E$49," ",IF(Employee!F$104<E$49," ",Employee!D$93))) | H54: =IF(T$49="Y",Jun!H54,0) -> 0 | I54: =IF(T$49="Y",Jun!I54,0) -> 0 | J54: =IF(T$49="Y",Jun!J54,0) -> 0 | K54: =IF(T$49="Y",Jun!K54,I54*J54) -> 0 | L54: =IF(T$49="Y",Jun!L54,0) -> 0 | M54: =IF(E54=" "," ",IF(T$49="Y",Jun!M54,IF((H54+K54+L54)>0,H54+K54+L54," "))) | N54: 0 | O54: 0 | P54: 0 | Q54: 0 | R54: =IF(M54=" "," ",IF(M54=0," ",M54-SUM(N54:Q54))) | T54: 0 | V54: =IF(Employee!H$113=E$49,Employee!D$112+SUM(M54)+Jun!V54,SUM(M54)+Jun!V54) -> 0 | W54: =IF(Employee!H$113=E$49,Employee!D$113+SUM(N54)+Jun!W54,SUM(N54)+Jun!W54) -> 0 | X54: =IF(O54=" ",Jun!X54,O54+Jun!X54) -> 0 | Y54: =IF(P54=" ",Jun!Y54,P54+Jun!Y54) -> 0 | Z54: =IF(Q54=" ",Jun!Z54,Q54+Jun!Z54) -> 0 | AA54: =IF(R54=" ",Jun!AA54,R54+Jun!AA54) -> 0 | AC54: =IF(T54=" ",Jun!AC54,T54+Jun!AC54) -> 0 | AD54: =IF(G54="SSP",H54,0) -> 0 | AE54: =IF(G54="SMP",H54,0) -> 0 | AF54: =IF(G54="SPP",H54,0) -> 0 | AG54: =IF(G54="SAP",H54,0) -> 0
B55: =IF(E55=" "," ",IF(Employee!F$128>E$49," ",IF(Employee!F$130<E$49," ",Employee!D$134))) | E55: =IF(Employee!D$132="w"," ",IF(Employee!F$128>E$49," ",IF(Employee!F$130<E$49," ",Employee!D$133))) | F55: =IF(E55=" "," ",IF(Employee!F$128>E$49," ",IF(Employee!F$130<E$49," ",Employee!D$119))) | H55: =IF(T$49="Y",Jun!H55,0) -> 0 | I55: =IF(T$49="Y",Jun!I55,0) -> 0 | J55: =IF(T$49="Y",Jun!J55,0) -> 0 | K55: =IF(T$49="Y",Jun!K55,I55*J55) -> 0 | L55: =IF(T$49="Y",Jun!L55,0) -> 0 | M55: =IF(E55=" "," ",IF(T$49="Y",Jun!M55,IF((H55+K55+L55)>0,H55+K55+L55," "))) | N55: 0 | O55: 0 | P55: 0 | Q55: 0 | R55: =IF(M55=" "," ",IF(M55=0," ",M55-SUM(N55:Q55))) | T55: 0 | V55: =IF(Employee!H$139=E$49,Employee!D$138+SUM(M55)+Jun!V55,SUM(M55)+Jun!V55) -> 0 | W55: =IF(Employee!H$139=E$49,Employee!D$139+SUM(N55)+Jun!W55,SUM(N55)+Jun!W55) -> 0 | X55: =IF(O55=" ",Jun!X55,O55+Jun!X55) -> 0 | Y55: =IF(P55=" ",Jun!Y55,P55+Jun!Y55) -> 0 | Z55: =IF(Q55=" ",Jun!Z55,Q55+Jun!Z55) -> 0 | AA55: =IF(R55=" ",Jun!AA55,R55+Jun!AA55) -> 0 | AC55: =IF(T55=" ",Jun!AC55,T55+Jun!AC55) -> 0 | AD55: =IF(G55="SSP",H55,0) -> 0 | AE55: =IF(G55="SMP",H55,0) -> 0 | AF55: =IF(G55="SPP",H55,0) -> 0 | AG55: =IF(G55="SAP",H55,0) -> 0
F56: Payroll Total | M56: =SUM(M51:M55) -> 0 | N56: =SUM(N51:N55) -> 0 | O56: =SUM(O51:O55) -> 0 | P56: =SUM(P51:P55) -> 0 | Q56: =SUM(Q51:Q55) -> 0 | R56: =SUM(R51:R55) -> 0 | T56: =SUM(T51:T55) -> 0
AD58: =SUM(AD11:AD56) -> 0 | AE58: =SUM(AE11:AE56) -> 0 | AF58: =SUM(AF11:AF56) -> 0 | AG58: =SUM(AG11:AG56) -> 0
F59: Directors | M59: Directors Wages Limited Companies Only
F60: =IF(B51="D",Employee!D15," ") | M60: =IF(B51="D",M51," ") | N60: =IF(B51="D",N51," ") | O60: =IF(B51="D",O51," ") | P60: =IF(B51="D",P51," ") | Q60: =IF(B51="D",Q51," ") | R60: =IF(B51="D",R51," ") | T60: =IF(B51="D",T51," ") | AD60: =IF((AD58-(O1+T1)*0.13)>0,AD58-(Q1+T1)*0.13,0) -> 0 | AE60: =AE58 -> 0 | AF60: =AF58 -> 0 | AG60: =AG58 -> 0
F61: =IF(B52="D",Employee!D41," ") | M61: =IF(B52="D",M52," ") | N61: =IF(B52="D",N52," ") | O61: =IF(B52="D",O52," ") | P61: =IF(B52="D",P52," ") | Q61: =IF(B52="D",Q52," ") | R61: =IF(B52="D",R52," ") | T61: =IF(B52="D",T52," ")
F62: =IF(B53="D",Employee!D67," ") | M62: =IF(B53="D",M53," ") | N62: =IF(B53="D",N53," ") | O62: =IF(B53="D",O53," ") | P62: =IF(B53="D",P53," ") | Q62: =IF(B53="D",Q53," ") | R62: =IF(B53="D",R53," ") | T62: =IF(B53="D",T53," ") | AE62: =AE60*0.045 -> 0 | AF62: =AF60*0.045 -> 0 | AG62: =AG60*0.045 -> 0
F63: =IF(B54="D",Employee!D93," ") | M63: =IF(B54="D",M54," ") | N63: =IF(B54="D",N54," ") | O63: =IF(B54="D",O54," ") | P63: =IF(B54="D",P54," ") | Q63: =IF(B54="D",Q54," ") | R63: =IF(B54="D",R54," ") | T63: =IF(B54="D",T54," ")
F64: =IF(B55="D",Employee!D119," ") | M64: =IF(B55="D",M55," ") | N64: =IF(B55="D",N55," ") | O64: =IF(B55="D",O55," ") | P64: =IF(B55="D",P55," ") | Q64: =IF(B55="D",Q55," ") | R64: =IF(B55="D",R55," ") | T64: =IF(B55="D",T55," ")
F65: Director Totals | M65: =SUM(M60:M64) -> 0 | N65: =SUM(N60:N64) -> 0 | O65: =SUM(O60:O64) -> 0 | P65: =SUM(P60:P64) -> 0 | Q65: =SUM(Q60:Q64) -> 0 | R65: =SUM(R60:R64) -> 0 | T65: =SUM(T60:T64) -> 0 | AD65: =AD60+Jun!AD65 -> 0 | AE65: =AE60+Jun!AE65 -> 0 | AF65: =AF60+Jun!AF65 -> 0 | AG65: =AG60+Jun!AG65 -> 0
AE67: =AE62+Jun!AE67 -> 0 | AF67: =AF62+Jun!AF67 -> 0 | AG67: =AG62+Jun!AG67 -> 0

Sheet Aug
B1: www.diyaccounting.co.uk | G1: =SUM(AD70:AG70)+SUM(AE72:AG72) -> 0 | I1: Monthly Totals | M1: =M16+M26+M36+M46+M56+M66 -> 0 | N1: =N16+N26+N36+N46+N56+N66 -> 0 | O1: =O16+O26+O36+O46+O56+O66 -> 0 | P1: =P16+P26+P36+P46+P56+P66 -> 0 | Q1: =Q16+Q26+Q36+Q46+Q56+Q66 -> 0 | R1: =R16+R26+R36+R46+R56+R66 -> 0 | T1: =T16+T26+T36+T46+T56+T66 -> 0 | V1: YEAR TO DATE | AD1: Statutory Payments & NIC Recovered
I2: Sub Totals Directors | M2: =M75 -> 0 | N2: =N75 -> 0 | O2: =O75 -> 0 | P2: =P75 -> 0 | Q2: =Q75 -> 0 | R2: =R75 -> 0 | S2: =S65 -> 0 | T2: =T75 -> 0
B3: Dir Ref | C3: NIC Table | D3: Tax Code | E3: Pay No | F3: Employee Name | G3: SSP | H3: =Jun!H3:H6 -> Statutory Pay | I3: =Jun!I3:I6 -> Basic hours | J3: =Jun!J3:J6 -> Hourly rate | K3: =Jun!K3:K6 -> Basic wages | L3: =Jun!L3:L6 -> Overtime Bonus Gratuities | M3: =Jun!M3:M6 -> GROSS WAGES | N3: =Jun!N3:N6 -> Income Tax | O3: =Jun!O3:O6 -> Employees National Insurance | ... R3: =Jun!R3:R6 -> NET PAY | T3: =Jun!T3:T6 -> Employers National Insurance | V3: Gross Wages | W3: Income Tax | X3: Employees National Insurance | Y3: Student Loan deductions | Z3: Other Deductions | AA3: Net Pay | AC3: Employers National Insurance | AD3: Statutory Sick Pay Recovered | AE3: Statutory Maternity Pay Recovered | AF3: Statutory Paternity Pay Recovered | AG3: Statutory Adoption Pay Recovered
G4: SMP
G5: SPP
G6: SAP
B8: WEEKLY PAYROLL | O8: Date Wages paid
B9: Week number | E9: 9 | H9: Date Wages paid | K9: =Jul!M39+1 -> 45803 | L9: - | M9: =K9+6 -> 45809 | O9: One Click to repeat previous week Enter Y
B11: =IF(E11=" "," ",IF(Employee!F$24>E$9," ",IF(Employee!F$26<E$9," ",Employee!D$30))) | E11: =IF(Employee!D$28="m"," ",IF(Employee!F$24>E$9," ",IF(Employee!F$26<E$9," ",Employee!D$29))) | F11: =IF(E11=" "," ",IF(Employee!F$24>E$9," ",IF(Employee!F$26<E$9," ",Employee!D$15))) | H11: =IF(T$9="Y",Jul!H41,0) -> 0 | I11: =IF(T$9="Y",Jul!I41,0) -> 0 | J11: =IF(T$9="Y",Jul!J41,0) -> 0 | K11: =IF(T$9="Y",Jul!K41,I11*J11) -> 0 | L11: =IF(T$9="Y",Jul!L41,0) -> 0 | M11: =IF(E11=" "," ",IF(T$9="Y",Jul!M41,IF((H11+K11+L11)>0,H11+K11+L11," "))) | N11: 0 | O11: 0 | P11: 0 | Q11: 0 | R11: =IF(M11=" "," ",IF(M11=0," ",M11-SUM(N11:Q11))) | T11: 0 | V11: =IF(Employee!H$34=E$9,Employee!D$34+SUM(M11)+Jul!V41,SUM(M11)+Jul!V41) -> 0 | W11: =IF(Employee!H$34=E$9,Employee!D$35+SUM(N11)+Jul!W41,SUM(N11)+Jul!W41) -> 0 | X11: =IF(O11=" ",Jul!X41,O11+Jul!X41) -> 0 | Y11: =IF(P11=" ",Jul!Y41,P11+Jul!Y41) -> 0 | Z11: =IF(Q11=" ",Jul!Z41,Q11+Jul!Z41) -> 0 | AA11: =IF(R11=" ",Jul!AA41,R11+Jul!AA41) -> 0 | AC11: =IF(T11=" ",Jul!AC41,T11+Jul!AC41) -> 0 | AD11: =IF(G11="SSP",H11,0) -> 0 | AE11: =IF(G11="SMP",H11,0) -> 0 | AF11: =IF(G11="SPP",H11,0) -> 0 | AG11: =IF(G11="SAP",H11,0) -> 0
B12: =IF(E12=" "," ",IF(Employee!F$50>E$9," ",IF(Employee!F$52<E$9," ",Employee!D$56))) | E12: =IF(Employee!D$54="m"," ",IF(Employee!F$50>E$9," ",IF(Employee!F$52<E$9," ",Employee!D$55))) | F12: =IF(E12=" "," ",IF(Employee!F$50>E$9," ",IF(Employee!F$52<E$9," ",Employee!D$41))) | H12: =IF(T$9="Y",Jul!H42,0) -> 0 | I12: =IF(T$9="Y",Jul!I42,0) -> 0 | J12: =IF(T$9="Y",Jul!J42,0) -> 0 | K12: =IF(T$9="Y",Jul!K42,I12*J12) -> 0 | L12: =IF(T$9="Y",Jul!L42,0) -> 0 | M12: =IF(E12=" "," ",IF(T$9="Y",Jul!M42,IF((H12+K12+L12)>0,H12+K12+L12," "))) | N12: 0 | O12: 0 | P12: 0 | Q12: 0 | R12: =IF(M12=" "," ",IF(M12=0," ",M12-SUM(N12:Q12))) | T12: 0 | V12: =IF(Employee!H$60=E$9,Employee!D$60+SUM(M12)+Jul!V42,SUM(M12)+Jul!V42) -> 0 | W12: =IF(Employee!H$60=E$9,Employee!D$61+SUM(N12)+Jul!W42,SUM(N12)+Jul!W42) -> 0 | X12: =IF(O12=" ",Jul!X42,O12+Jul!X42) -> 0 | Y12: =IF(P12=" ",Jul!Y42,P12+Jul!Y42) -> 0 | Z12: =IF(Q12=" ",Jul!Z42,Q12+Jul!Z42) -> 0 | AA12: =IF(R12=" ",Jul!AA42,R12+Jul!AA42) -> 0 | AC12: =IF(T12=" ",Jul!AC42,T12+Jul!AC42) -> 0 | AD12: =IF(G12="SSP",H12,0) -> 0 | AE12: =IF(G12="SMP",H12,0) -> 0 | AF12: =IF(G12="SPP",H12,0) -> 0 | AG12: =IF(G12="SAP",H12,0) -> 0
B13: =IF(E13=" "," ",IF(Employee!F$76>E$9," ",IF(Employee!F$78<E$9," ",Employee!D$82))) | E13: =IF(Employee!D$80="m"," ",IF(Employee!F$76>E$9," ",IF(Employee!F$78<E$9," ",Employee!D$81))) | F13: =IF(E13=" "," ",IF(Employee!F$76>E$9," ",IF(Employee!F$78<E$9," ",Employee!D$67))) | H13: =IF(T$9="Y",Jul!H43,0) -> 0 | I13: =IF(T$9="Y",Jul!I43,0) -> 0 | J13: =IF(T$9="Y",Jul!J43,0) -> 0 | K13: =IF(T$9="Y",Jul!K43,I13*J13) -> 0 | L13: =IF(T$9="Y",Jul!L43,0) -> 0 | M13: =IF(E13=" "," ",IF(T$9="Y",Jul!M43,IF((H13+K13+L13)>0,H13+K13+L13," "))) | N13: 0 | O13: 0 | P13: 0 | Q13: 0 | R13: =IF(M13=" "," ",IF(M13=0," ",M13-SUM(N13:Q13))) | T13: 0 | V13: =IF(Employee!H$86=E$9,Employee!D$86+SUM(M13)+Jul!V43,SUM(M13)+Jul!V43) -> 0 | W13: =IF(Employee!H$86=E$9,Employee!D$87+SUM(N13)+Jul!W43,SUM(N13)+Jul!W43) -> 0 | X13: =IF(O13=" ",Jul!X43,O13+Jul!X43) -> 0 | Y13: =IF(P13=" ",Jul!Y43,P13+Jul!Y43) -> 0 | Z13: =IF(Q13=" ",Jul!Z43,Q13+Jul!Z43) -> 0 | AA13: =IF(R13=" ",Jul!AA43,R13+Jul!AA43) -> 0 | AC13: =IF(T13=" ",Jul!AC43,T13+Jul!AC43) -> 0 | AD13: =IF(G13="SSP",H13,0) -> 0 | AE13: =IF(G13="SMP",H13,0) -> 0 | AF13: =IF(G13="SPP",H13,0) -> 0 | AG13: =IF(G13="SAP",H13,0) -> 0
B14: =IF(E14=" "," ",IF(Employee!F$102>E$9," ",IF(Employee!F$104<E$9," ",Employee!D$108))) | E14: =IF(Employee!D$106="m"," ",IF(Employee!F$102>E$9," ",IF(Employee!F$104<E$9," ",Employee!D$107))) | F14: =IF(E14=" "," ",IF(Employee!F$102>E$9," ",IF(Employee!F$104<E$9," ",Employee!D$93))) | H14: =IF(T$9="Y",Jul!H44,0) -> 0 | I14: =IF(T$9="Y",Jul!I44,0) -> 0 | J14: =IF(T$9="Y",Jul!J44,0) -> 0 | K14: =IF(T$9="Y",Jul!K44,I14*J14) -> 0 | L14: =IF(T$9="Y",Jul!L44,0) -> 0 | M14: =IF(E14=" "," ",IF(T$9="Y",Jul!M44,IF((H14+K14+L14)>0,H14+K14+L14," "))) | N14: 0 | O14: 0 | P14: 0 | Q14: 0 | R14: =IF(M14=" "," ",IF(M14=0," ",M14-SUM(N14:Q14))) | T14: 0 | V14: =IF(Employee!H$112=E$9,Employee!D$112+SUM(M14)+Jul!V44,SUM(M14)+Jul!V44) -> 0 | W14: =IF(Employee!H$112=E$9,Employee!D$113+SUM(N14)+Jul!W44,SUM(N14)+Jul!W44) -> 0 | X14: =IF(O14=" ",Jul!X44,O14+Jul!X44) -> 0 | Y14: =IF(P14=" ",Jul!Y44,P14+Jul!Y44) -> 0 | Z14: =IF(Q14=" ",Jul!Z44,Q14+Jul!Z44) -> 0 | AA14: =IF(R14=" ",Jul!AA44,R14+Jul!AA44) -> 0 | AC14: =IF(T14=" ",Jul!AC44,T14+Jul!AC44) -> 0 | AD14: =IF(G14="SSP",H14,0) -> 0 | AE14: =IF(G14="SMP",H14,0) -> 0 | AF14: =IF(G14="SPP",H14,0) -> 0 | AG14: =IF(G14="SAP",H14,0) -> 0
B15: =IF(E15=" "," ",IF(Employee!F$128>E$9," ",IF(Employee!F$130<E$9," ",Employee!D$134))) | E15: =IF(Employee!D$132="m"," ",IF(Employee!F$128>E$9," ",IF(Employee!F$130<E$9," ",Employee!D$133))) | F15: =IF(E15=" "," ",IF(Employee!F$128>E$9," ",IF(Employee!F$130<E$9," ",Employee!D$119))) | H15: =IF(T$9="Y",Jul!H45,0) -> 0 | I15: =IF(T$9="Y",Jul!I45,0) -> 0 | J15: =IF(T$9="Y",Jul!J45,0) -> 0 | K15: =IF(T$9="Y",Jul!K45,I15*J15) -> 0 | L15: =IF(T$9="Y",Jul!L45,0) -> 0 | M15: =IF(E15=" "," ",IF(T$9="Y",Jul!M45,IF((H15+K15+L15)>0,H15+K15+L15," "))) | N15: 0 | O15: 0 | P15: 0 | Q15: 0 | R15: =IF(M15=" "," ",IF(M15=0," ",M15-SUM(N15:Q15))) | T15: 0 | V15: =IF(Employee!H$138=E$9,Employee!D$138+SUM(M15)+Jul!V45,SUM(M15)+Jul!V45) -> 0 | W15: =IF(Employee!H$138=E$9,Employee!D$139+SUM(N15)+Jul!W45,SUM(N15)+Jul!W45) -> 0 | X15: =IF(O15=" ",Jul!X45,O15+Jul!X45) -> 0 | Y15: =IF(P15=" ",Jul!Y45,P15+Jul!Y45) -> 0 | Z15: =IF(Q15=" ",Jul!Z45,Q15+Jul!Z45) -> 0 | AA15: =IF(R15=" ",Jul!AA45,R15+Jul!AA45) -> 0 | AC15: =IF(T15=" ",Jul!AC45,T15+Jul!AC45) -> 0 | AD15: =IF(G15="SSP",H15,0) -> 0 | AE15: =IF(G15="SMP",H15,0) -> 0 | AF15: =IF(G15="SPP",H15,0) -> 0 | AG15: =IF(G15="SAP",H15,0) -> 0
F16: Payroll Total | M16: =SUM(M11:M15) -> 0 | N16: =SUM(N11:N15) -> 0 | O16: =SUM(O11:O15) -> 0 | P16: =SUM(P11:P15) -> 0 | Q16: =SUM(Q11:Q15) -> 0 | R16: =SUM(R11:R15) -> 0 | T16: =SUM(T11:T15) -> 0
B18: WEEKLY PAYROLL | O18: Date Wages paid
B19: Week number | E19: 10 | H19: Date Wages paid | K19: =M9+1 -> 45810 | L19: - | M19: =K19+6 -> 45816 | O19: One Click to repeat previous week Enter Y
B21: =IF(E21=" "," ",IF(Employee!F$24>E$19," ",IF(Employee!F$26<E$19," ",Employee!D$30))) | E21: =IF(Employee!D$28="m"," ",IF(Employee!F$24>E$19," ",IF(Employee!F$26<E$19," ",Employee!D$29))) | F21: =IF(E21=" "," ",IF(Employee!F$24>E$19," ",IF(Employee!F$26<E$19," ",Employee!D$15))) | H21: =IF(T$19="Y",H11,0) -> 0 | I21: =IF(T$19="Y",I11,0) -> 0 | J21: =IF(T$19="Y",J11,0) -> 0 | K21: =IF(T$19="Y",K11,I21*J21) -> 0 | L21: =IF(T$19="Y",L11,0) -> 0 | M21: =IF(E21=" "," ",IF(T$19="Y",M11,IF((H21+K21+L21)>0,H21+K21+L21," "))) | N21: 0 | O21: 0 | P21: 0 | Q21: 0 | R21: =IF(M21=" "," ",IF(M21=0," ",M21-SUM(N21:Q21))) | T21: 0 | V21: =IF(Employee!H$34=E$19,Employee!D$34+SUM(M21)+V11,SUM(M21)+V11) -> 0 | W21: =IF(Employee!H$34=E$19,Employee!D$35+SUM(N21)+W11,SUM(N21)+W11) -> 0 | X21: =IF(O21=" ",X11,O21+X11) -> 0 | Y21: =IF(P21=0,Y11,P21+Y11) -> 0 | Z21: =IF(Q21=0,Z11,Q21+Z11) -> 0 | AA21: =IF(R21=" ",AA11,AA11+R21) -> 0 | AC21: =IF(T21=" ",AC11,T21+AC11) -> 0 | AD21: =IF(G21="SSP",H21,0) -> 0 | AE21: =IF(G21="SMP",H21,0) -> 0 | AF21: =IF(G21="SPP",H21,0) -> 0 | AG21: =IF(G21="SAP",H21,0) -> 0
B22: =IF(E22=" "," ",IF(Employee!F$50>E$19," ",IF(Employee!F$52<E$19," ",Employee!D$56))) | E22: =IF(Employee!D$54="m"," ",IF(Employee!F$50>E$19," ",IF(Employee!F$52<E$19," ",Employee!D$55))) | F22: =IF(E22=" "," ",IF(Employee!F$50>E$19," ",IF(Employee!F$52<E$19," ",Employee!D$41))) | H22: =IF(T$19="Y",H12,0) -> 0 | I22: =IF(T$19="Y",I12,0) -> 0 | J22: =IF(T$19="Y",J12,0) -> 0 | K22: =IF(T$19="Y",K12,I22*J22) -> 0 | L22: =IF(T$19="Y",L12,0) -> 0 | M22: =IF(E22=" "," ",IF(T$19="Y",M12,IF((H22+K22+L22)>0,H22+K22+L22," "))) | N22: 0 | O22: 0 | P22: 0 | Q22: 0 | R22: =IF(M22=" "," ",IF(M22=0," ",M22-SUM(N22:Q22))) | T22: 0 | V22: =IF(Employee!H$60=E$19,Employee!D$60+SUM(M22)+V12,SUM(M22)+V12) -> 0 | W22: =IF(Employee!H$60=E$19,Employee!D$61+SUM(N22)+W12,SUM(N22)+W12) -> 0 | X22: =IF(O22=" ",X12,O22+X12) -> 0 | Y22: =IF(P22=0,Y12,P22+Y12) -> 0 | Z22: =IF(Q22=0,Z12,Q22+Z12) -> 0 | AA22: =IF(R22=" ",AA12,AA12+R22) -> 0 | AC22: =IF(T22=" ",AC12,T22+AC12) -> 0 | AD22: =IF(G22="SSP",H22,0) -> 0 | AE22: =IF(G22="SMP",H22,0) -> 0 | AF22: =IF(G22="SPP",H22,0) -> 0 | AG22: =IF(G22="SAP",H22,0) -> 0
B23: =IF(E23=" "," ",IF(Employee!F$76>E$19," ",IF(Employee!F$78<E$19," ",Employee!D$82))) | E23: =IF(Employee!D$80="m"," ",IF(Employee!F$76>E$19," ",IF(Employee!F$78<E$19," ",Employee!D$81))) | F23: =IF(E23=" "," ",IF(Employee!F$76>E$19," ",IF(Employee!F$78<E$19," ",Employee!D$67))) | H23: =IF(T$19="Y",H13,0) -> 0 | I23: =IF(T$19="Y",I13,0) -> 0 | J23: =IF(T$19="Y",J13,0) -> 0 | K23: =IF(T$19="Y",K13,I23*J23) -> 0 | L23: =IF(T$19="Y",L13,0) -> 0 | M23: =IF(E23=" "," ",IF(T$19="Y",M13,IF((H23+K23+L23)>0,H23+K23+L23," "))) | N23: 0 | O23: 0 | P23: 0 | Q23: 0 | R23: =IF(M23=" "," ",IF(M23=0," ",M23-SUM(N23:Q23))) | T23: 0 | V23: =IF(Employee!H$86=E$19,Employee!D$86+SUM(M23)+V13,SUM(M23)+V13) -> 0 | W23: =IF(Employee!H$86=E$19,Employee!D$87+SUM(N23)+W13,SUM(N23)+W13) -> 0 | X23: =IF(O23=" ",X13,O23+X13) -> 0 | Y23: =IF(P23=0,Y13,P23+Y13) -> 0 | Z23: =IF(Q23=0,Z13,Q23+Z13) -> 0 | AA23: =IF(R23=" ",AA13,AA13+R23) -> 0 | AC23: =IF(T23=" ",AC13,T23+AC13) -> 0 | AD23: =IF(G23="SSP",H23,0) -> 0 | AE23: =IF(G23="SMP",H23,0) -> 0 | AF23: =IF(G23="SPP",H23,0) -> 0 | AG23: =IF(G23="SAP",H23,0) -> 0
B24: =IF(E24=" "," ",IF(Employee!F$102>E$19," ",IF(Employee!F$104<E$19," ",Employee!D$108))) | E24: =IF(Employee!D$106="m"," ",IF(Employee!F$102>E$19," ",IF(Employee!F$104<E$19," ",Employee!D$107))) | F24: =IF(E24=" "," ",IF(Employee!F$102>E$19," ",IF(Employee!F$104<E$19," ",Employee!D$93))) | H24: =IF(T$19="Y",H14,0) -> 0 | I24: =IF(T$19="Y",I14,0) -> 0 | J24: =IF(T$19="Y",J14,0) -> 0 | K24: =IF(T$19="Y",K14,I24*J24) -> 0 | L24: =IF(T$19="Y",L14,0) -> 0 | M24: =IF(E24=" "," ",IF(T$19="Y",M14,IF((H24+K24+L24)>0,H24+K24+L24," "))) | N24: 0 | O24: 0 | P24: 0 | Q24: 0 | R24: =IF(M24=" "," ",IF(M24=0," ",M24-SUM(N24:Q24))) | T24: 0 | V24: =IF(Employee!H$112=E$19,Employee!D$112+SUM(M24)+V14,SUM(M24)+V14) -> 0 | W24: =IF(Employee!H$112=E$19,Employee!D$113+SUM(N24)+W14,SUM(N24)+W14) -> 0 | X24: =IF(O24=" ",X14,O24+X14) -> 0 | Y24: =IF(P24=0,Y14,P24+Y14) -> 0 | Z24: =IF(Q24=0,Z14,Q24+Z14) -> 0 | AA24: =IF(R24=" ",AA14,AA14+R24) -> 0 | AC24: =IF(T24=" ",AC14,T24+AC14) -> 0 | AD24: =IF(G24="SSP",H24,0) -> 0 | AE24: =IF(G24="SMP",H24,0) -> 0 | AF24: =IF(G24="SPP",H24,0) -> 0 | AG24: =IF(G24="SAP",H24,0) -> 0
B25: =IF(E25=" "," ",IF(Employee!F$128>E$19," ",IF(Employee!F$130<E$19," ",Employee!D$134))) | E25: =IF(Employee!D$132="m"," ",IF(Employee!F$128>E$19," ",IF(Employee!F$130<E$19," ",Employee!D$133))) | F25: =IF(E25=" "," ",IF(Employee!F$128>E$19," ",IF(Employee!F$130<E$19," ",Employee!D$119))) | H25: =IF(T$19="Y",H15,0) -> 0 | I25: =IF(T$19="Y",I15,0) -> 0 | J25: =IF(T$19="Y",J15,0) -> 0 | K25: =IF(T$19="Y",K15,I25*J25) -> 0 | L25: =IF(T$19="Y",L15,0) -> 0 | M25: =IF(E25=" "," ",IF(T$19="Y",M15,IF((H25+K25+L25)>0,H25+K25+L25," "))) | N25: 0 | O25: 0 | P25: 0 | Q25: 0 | R25: =IF(M25=" "," ",IF(M25=0," ",M25-SUM(N25:Q25))) | T25: 0 | V25: =IF(Employee!H$138=E$19,Employee!D$138+SUM(M25)+V15,SUM(M25)+V15) -> 0 | W25: =IF(Employee!H$138=E$19,Employee!D$139+SUM(N25)+W15,SUM(N25)+W15) -> 0 | X25: =IF(O25=" ",X15,O25+X15) -> 0 | Y25: =IF(P25=0,Y15,P25+Y15) -> 0 | Z25: =IF(Q25=0,Z15,Q25+Z15) -> 0 | AA25: =IF(R25=" ",AA15,AA15+R25) -> 0 | AC25: =IF(T25=" ",AC15,T25+AC15) -> 0 | AD25: =IF(G25="SSP",H25,0) -> 0 | AE25: =IF(G25="SMP",H25,0) -> 0 | AF25: =IF(G25="SPP",H25,0) -> 0 | AG25: =IF(G25="SAP",H25,0) -> 0
F26: Payroll Total | M26: =SUM(M21:M25) -> 0 | N26: =SUM(N21:N25) -> 0 | O26: =SUM(O21:O25) -> 0 | P26: =SUM(P21:P25) -> 0 | Q26: =SUM(Q21:Q25) -> 0 | R26: =SUM(R21:R25) -> 0 | T26: =SUM(T21:T25) -> 0
B28: WEEKLY PAYROLL | O28: Date Wages paid
B29: Week number | E29: 11 | H29: Date Wages paid | K29: =M19+1 -> 45817 | L29: - | M29: =K29+6 -> 45823 | O29: One Click to repeat previous week Enter Y
B31: =IF(E31=" "," ",IF(Employee!F$24>E$29," ",IF(Employee!F$26<E$29," ",Employee!D$30))) | E31: =IF(Employee!D$28="m"," ",IF(Employee!F$24>E$29," ",IF(Employee!F$26<E$29," ",Employee!D$29))) | F31: =IF(E31=" "," ",IF(Employee!F$24>E$29," ",IF(Employee!F$26<E$29," ",Employee!D$15))) | H31: =IF(T$29="Y",H21,0) -> 0 | I31: =IF(T$29="Y",I21,0) -> 0 | J31: =IF(T$29="Y",J21,0) -> 0 | K31: =IF(T$29="Y",K21,I31*J31) -> 0 | L31: =IF(T$29="Y",L21,0) -> 0 | M31: =IF(E31=" "," ",IF(T$29="Y",M21,IF((H31+K31+L31)>0,H31+K31+L31," "))) | N31: 0 | O31: 0 | P31: 0 | Q31: 0 | R31: =IF(M31=" "," ",IF(M31=0," ",M31-SUM(N31:Q31))) | T31: 0 | V31: =IF(Employee!H$34=E$29,Employee!D$34+SUM(M31)+V21,SUM(M31)+V21) -> 0 | W31: =IF(Employee!H$34=E$29,Employee!D$35+SUM(N31)+W21,SUM(N31)+W21) -> 0 | X31: =IF(O31=" ",X21,O31+X21) -> 0 | Y31: =IF(P31=0,Y21,P31+Y21) -> 0 | Z31: =IF(Q31=0,Z21,Q31+Z21) -> 0 | AA31: =IF(R31=" ",AA21,AA21+R31) -> 0 | AC31: =IF(T31=" ",AC21,T31+AC21) -> 0 | AD31: =IF(G31="SSP",H31,0) -> 0 | AE31: =IF(G31="SMP",H31,0) -> 0 | AF31: =IF(G31="SPP",H31,0) -> 0 | AG31: =IF(G31="SAP",H31,0) -> 0
B32: =IF(E32=" "," ",IF(Employee!F$50>E$29," ",IF(Employee!F$52<E$29," ",Employee!D$56))) | E32: =IF(Employee!D$54="m"," ",IF(Employee!F$50>E$29," ",IF(Employee!F$52<E$29," ",Employee!D$55))) | F32: =IF(E32=" "," ",IF(Employee!F$50>E$29," ",IF(Employee!F$52<E$29," ",Employee!D$41))) | H32: =IF(T$29="Y",H22,0) -> 0 | I32: =IF(T$29="Y",I22,0) -> 0 | J32: =IF(T$29="Y",J22,0) -> 0 | K32: =IF(T$29="Y",K22,I32*J32) -> 0 | L32: =IF(T$29="Y",L22,0) -> 0 | M32: =IF(E32=" "," ",IF(T$29="Y",M22,IF((H32+K32+L32)>0,H32+K32+L32," "))) | N32: 0 | O32: 0 | P32: 0 | Q32: 0 | R32: =IF(M32=" "," ",IF(M32=0," ",M32-SUM(N32:Q32))) | T32: 0 | V32: =IF(Employee!H$60=E$29,Employee!D$60+SUM(M32)+V22,SUM(M32)+V22) -> 0 | W32: =IF(Employee!H$60=E$29,Employee!D$61+SUM(N32)+W22,SUM(N32)+W22) -> 0 | X32: =IF(O32=" ",X22,O32+X22) -> 0 | Y32: =IF(P32=0,Y22,P32+Y22) -> 0 | Z32: =IF(Q32=0,Z22,Q32+Z22) -> 0 | AA32: =IF(R32=" ",AA22,AA22+R32) -> 0 | AC32: =IF(T32=" ",AC22,T32+AC22) -> 0 | AD32: =IF(G32="SSP",H32,0) -> 0 | AE32: =IF(G32="SMP",H32,0) -> 0 | AF32: =IF(G32="SPP",H32,0) -> 0 | AG32: =IF(G32="SAP",H32,0) -> 0
B33: =IF(E33=" "," ",IF(Employee!F$76>E$29," ",IF(Employee!F$78<E$29," ",Employee!D$82))) | E33: =IF(Employee!D$80="m"," ",IF(Employee!F$76>E$29," ",IF(Employee!F$78<E$29," ",Employee!D$81))) | F33: =IF(E33=" "," ",IF(Employee!F$76>E$29," ",IF(Employee!F$78<E$29," ",Employee!D$67))) | H33: =IF(T$29="Y",H23,0) -> 0 | I33: =IF(T$29="Y",I23,0) -> 0 | J33: =IF(T$29="Y",J23,0) -> 0 | K33: =IF(T$29="Y",K23,I33*J33) -> 0 | L33: =IF(T$29="Y",L23,0) -> 0 | M33: =IF(E33=" "," ",IF(T$29="Y",M23,IF((H33+K33+L33)>0,H33+K33+L33," "))) | N33: 0 | O33: 0 | P33: 0 | Q33: 0 | R33: =IF(M33=" "," ",IF(M33=0," ",M33-SUM(N33:Q33))) | T33: 0 | V33: =IF(Employee!H$86=E$29,Employee!D$86+SUM(M33)+V23,SUM(M33)+V23) -> 0 | W33: =IF(Employee!H$86=E$29,Employee!D$87+SUM(N33)+W23,SUM(N33)+W23) -> 0 | X33: =IF(O33=" ",X23,O33+X23) -> 0 | Y33: =IF(P33=0,Y23,P33+Y23) -> 0 | Z33: =IF(Q33=0,Z23,Q33+Z23) -> 0 | AA33: =IF(R33=" ",AA23,AA23+R33) -> 0 | AC33: =IF(T33=" ",AC23,T33+AC23) -> 0 | AD33: =IF(G33="SSP",H33,0) -> 0 | AE33: =IF(G33="SMP",H33,0) -> 0 | AF33: =IF(G33="SPP",H33,0) -> 0 | AG33: =IF(G33="SAP",H33,0) -> 0
B34: =IF(E34=" "," ",IF(Employee!F$102>E$29," ",IF(Employee!F$104<E$29," ",Employee!D$108))) | E34: =IF(Employee!D$106="m"," ",IF(Employee!F$102>E$29," ",IF(Employee!F$104<E$29," ",Employee!D$107))) | F34: =IF(E34=" "," ",IF(Employee!F$102>E$29," ",IF(Employee!F$104<E$29," ",Employee!D$93))) | H34: =IF(T$29="Y",H24,0) -> 0 | I34: =IF(T$29="Y",I24,0) -> 0 | J34: =IF(T$29="Y",J24,0) -> 0 | K34: =IF(T$29="Y",K24,I34*J34) -> 0 | L34: =IF(T$29="Y",L24,0) -> 0 | M34: =IF(E34=" "," ",IF(T$29="Y",M24,IF((H34+K34+L34)>0,H34+K34+L34," "))) | N34: 0 | O34: 0 | P34: 0 | Q34: 0 | R34: =IF(M34=" "," ",IF(M34=0," ",M34-SUM(N34:Q34))) | T34: 0 | V34: =IF(Employee!H$112=E$29,Employee!D$112+SUM(M34)+V24,SUM(M34)+V24) -> 0 | W34: =IF(Employee!H$112=E$29,Employee!D$113+SUM(N34)+W24,SUM(N34)+W24) -> 0 | X34: =IF(O34=" ",X24,O34+X24) -> 0 | Y34: =IF(P34=0,Y24,P34+Y24) -> 0 | Z34: =IF(Q34=0,Z24,Q34+Z24) -> 0 | AA34: =IF(R34=" ",AA24,AA24+R34) -> 0 | AC34: =IF(T34=" ",AC24,T34+AC24) -> 0 | AD34: =IF(G34="SSP",H34,0) -> 0 | AE34: =IF(G34="SMP",H34,0) -> 0 | AF34: =IF(G34="SPP",H34,0) -> 0 | AG34: =IF(G34="SAP",H34,0) -> 0
B35: =IF(E35=" "," ",IF(Employee!F$128>E$29," ",IF(Employee!F$130<E$29," ",Employee!D$134))) | E35: =IF(Employee!D$132="m"," ",IF(Employee!F$128>E$29," ",IF(Employee!F$130<E$29," ",Employee!D$133))) | F35: =IF(E35=" "," ",IF(Employee!F$128>E$29," ",IF(Employee!F$130<E$29," ",Employee!D$119))) | H35: =IF(T$29="Y",H25,0) -> 0 | I35: =IF(T$29="Y",I25,0) -> 0 | J35: =IF(T$29="Y",J25,0) -> 0 | K35: =IF(T$29="Y",K25,I35*J35) -> 0 | L35: =IF(T$29="Y",L25,0) -> 0 | M35: =IF(E35=" "," ",IF(T$29="Y",M25,IF((H35+K35+L35)>0,H35+K35+L35," "))) | N35: 0 | O35: 0 | P35: 0 | Q35: 0 | R35: =IF(M35=" "," ",IF(M35=0," ",M35-SUM(N35:Q35))) | T35: 0 | V35: =IF(Employee!H$138=E$29,Employee!D$138+SUM(M35)+V25,SUM(M35)+V25) -> 0 | W35: =IF(Employee!H$138=E$29,Employee!D$139+SUM(N35)+W25,SUM(N35)+W25) -> 0 | X35: =IF(O35=" ",X25,O35+X25) -> 0 | Y35: =IF(P35=0,Y25,P35+Y25) -> 0 | Z35: =IF(Q35=0,Z25,Q35+Z25) -> 0 | AA35: =IF(R35=" ",AA25,AA25+R35) -> 0 | AC35: =IF(T35=" ",AC25,T35+AC25) -> 0 | AD35: =IF(G35="SSP",H35,0) -> 0 | AE35: =IF(G35="SMP",H35,0) -> 0 | AF35: =IF(G35="SPP",H35,0) -> 0 | AG35: =IF(G35="SAP",H35,0) -> 0
F36: Payroll Total | M36: =SUM(M31:M35) -> 0 | N36: =SUM(N31:N35) -> 0 | O36: =SUM(O31:O35) -> 0 | P36: =SUM(P31:P35) -> 0 | Q36: =SUM(Q31:Q35) -> 0 | R36: =SUM(R31:R35) -> 0 | T36: =SUM(T31:T35) -> 0
B38: WEEKLY PAYROLL | O38: Date Wages paid
B39: Week number | E39: 12 | H39: Date Wages paid | K39: =M29+1 -> 45824 | L39: - | M39: =K39+6 -> 45830 | O39: One Click to repeat previous week Enter Y
B41: =IF(E41=" "," ",IF(Employee!F$24>E$39," ",IF(Employee!F$26<E$39," ",Employee!D$30))) | E41: =IF(Employee!D$28="m"," ",IF(Employee!F$24>E$39," ",IF(Employee!F$26<E$39," ",Employee!D$29))) | F41: =IF(E41=" "," ",IF(Employee!F$24>E$39," ",IF(Employee!F$26<E$39," ",Employee!D$15))) | H41: =IF(T$39="Y",H31,0) -> 0 | I41: =IF(T$39="Y",I31,0) -> 0 | J41: =IF(T$39="Y",J31,0) -> 0 | K41: =IF(T$39="Y",K31,I41*J41) -> 0 | L41: =IF(T$39="Y",L31,0) -> 0 | M41: =IF(E41=" "," ",IF(T$39="Y",M31,IF((H41+K41+L41)>0,H41+K41+L41," "))) | N41: 0 | O41: 0 | P41: 0 | Q41: 0 | R41: =IF(M41=" "," ",IF(M41=0," ",M41-SUM(N41:Q41))) | T41: 0 | V41: =IF(Employee!H$34=E$39,Employee!D$34+SUM(M41)+V31,SUM(M41)+V31) -> 0 | W41: =IF(Employee!H$34=E$39,Employee!D$35+SUM(N41)+W31,SUM(N41)+W31) -> 0 | X41: =IF(O41=" ",X31,O41+X31) -> 0 | Y41: =IF(P41=0,Y31,P41+Y31) -> 0 | Z41: =IF(Q41=0,Z31,Q41+Z31) -> 0 | AA41: =IF(R41=" ",AA31,AA31+R41) -> 0 | AC41: =IF(T41=" ",AC31,T41+AC31) -> 0 | AD41: =IF(G41="SSP",H41,0) -> 0 | AE41: =IF(G41="SMP",H41,0) -> 0 | AF41: =IF(G41="SPP",H41,0) -> 0 | AG41: =IF(G41="SAP",H41,0) -> 0
B42: =IF(E42=" "," ",IF(Employee!F$50>E$39," ",IF(Employee!F$52<E$39," ",Employee!D$56))) | E42: =IF(Employee!D$54="m"," ",IF(Employee!F$50>E$39," ",IF(Employee!F$52<E$39," ",Employee!D$55))) | F42: =IF(E42=" "," ",IF(Employee!F$50>E$39," ",IF(Employee!F$52<E$39," ",Employee!D$41))) | H42: =IF(T$39="Y",H32,0) -> 0 | I42: =IF(T$39="Y",I32,0) -> 0 | J42: =IF(T$39="Y",J32,0) -> 0 | K42: =IF(T$39="Y",K32,I42*J42) -> 0 | L42: =IF(T$39="Y",L32,0) -> 0 | M42: =IF(E42=" "," ",IF(T$39="Y",M32,IF((H42+K42+L42)>0,H42+K42+L42," "))) | N42: 0 | O42: 0 | P42: 0 | Q42: 0 | R42: =IF(M42=" "," ",IF(M42=0," ",M42-SUM(N42:Q42))) | T42: 0 | V42: =IF(Employee!H$60=E$39,Employee!D$60+SUM(M42)+V32,SUM(M42)+V32) -> 0 | W42: =IF(Employee!H$60=E$39,Employee!D$61+SUM(N42)+W32,SUM(N42)+W32) -> 0 | X42: =IF(O42=" ",X32,O42+X32) -> 0 | Y42: =IF(P42=0,Y32,P42+Y32) -> 0 | Z42: =IF(Q42=0,Z32,Q42+Z32) -> 0 | AA42: =IF(R42=" ",AA32,AA32+R42) -> 0 | AC42: =IF(T42=" ",AC32,T42+AC32) -> 0 | AD42: =IF(G42="SSP",H42,0) -> 0 | AE42: =IF(G42="SMP",H42,0) -> 0 | AF42: =IF(G42="SPP",H42,0) -> 0 | AG42: =IF(G42="SAP",H42,0) -> 0
B43: =IF(E43=" "," ",IF(Employee!F$76>E$39," ",IF(Employee!F$78<E$39," ",Employee!D$82))) | E43: =IF(Employee!D$80="m"," ",IF(Employee!F$76>E$39," ",IF(Employee!F$78<E$39," ",Employee!D$81))) | F43: =IF(E43=" "," ",IF(Employee!F$76>E$39," ",IF(Employee!F$78<E$39," ",Employee!D$67))) | H43: =IF(T$39="Y",H33,0) -> 0 | I43: =IF(T$39="Y",I33,0) -> 0 | J43: =IF(T$39="Y",J33,0) -> 0 | K43: =IF(T$39="Y",K33,I43*J43) -> 0 | L43: =IF(T$39="Y",L33,0) -> 0 | M43: =IF(E43=" "," ",IF(T$39="Y",M33,IF((H43+K43+L43)>0,H43+K43+L43," "))) | N43: 0 | O43: 0 | P43: 0 | Q43: 0 | R43: =IF(M43=" "," ",IF(M43=0," ",M43-SUM(N43:Q43))) | T43: 0 | V43: =IF(Employee!H$86=E$39,Employee!D$86+SUM(M43)+V33,SUM(M43)+V33) -> 0 | W43: =IF(Employee!H$86=E$39,Employee!D$87+SUM(N43)+W33,SUM(N43)+W33) -> 0 | X43: =IF(O43=" ",X33,O43+X33) -> 0 | Y43: =IF(P43=0,Y33,P43+Y33) -> 0 | Z43: =IF(Q43=0,Z33,Q43+Z33) -> 0 | AA43: =IF(R43=" ",AA33,AA33+R43) -> 0 | AC43: =IF(T43=" ",AC33,T43+AC33) -> 0 | AD43: =IF(G43="SSP",H43,0) -> 0 | AE43: =IF(G43="SMP",H43,0) -> 0 | AF43: =IF(G43="SPP",H43,0) -> 0 | AG43: =IF(G43="SAP",H43,0) -> 0
B44: =IF(E44=" "," ",IF(Employee!F$102>E$39," ",IF(Employee!F$104<E$39," ",Employee!D$108))) | E44: =IF(Employee!D$106="m"," ",IF(Employee!F$102>E$39," ",IF(Employee!F$104<E$39," ",Employee!D$107))) | F44: =IF(E44=" "," ",IF(Employee!F$102>E$39," ",IF(Employee!F$104<E$39," ",Employee!D$93))) | H44: =IF(T$39="Y",H34,0) -> 0 | I44: =IF(T$39="Y",I34,0) -> 0 | J44: =IF(T$39="Y",J34,0) -> 0 | K44: =IF(T$39="Y",K34,I44*J44) -> 0 | L44: =IF(T$39="Y",L34,0) -> 0 | M44: =IF(E44=" "," ",IF(T$39="Y",M34,IF((H44+K44+L44)>0,H44+K44+L44," "))) | N44: 0 | O44: 0 | P44: 0 | Q44: 0 | R44: =IF(M44=" "," ",IF(M44=0," ",M44-SUM(N44:Q44))) | T44: 0 | V44: =IF(Employee!H$112=E$39,Employee!D$112+SUM(M44)+V34,SUM(M44)+V34) -> 0 | W44: =IF(Employee!H$112=E$39,Employee!D$113+SUM(N44)+W34,SUM(N44)+W34) -> 0 | X44: =IF(O44=" ",X34,O44+X34) -> 0 | Y44: =IF(P44=0,Y34,P44+Y34) -> 0 | Z44: =IF(Q44=0,Z34,Q44+Z34) -> 0 | AA44: =IF(R44=" ",AA34,AA34+R44) -> 0 | AC44: =IF(T44=" ",AC34,T44+AC34) -> 0 | AD44: =IF(G44="SSP",H44,0) -> 0 | AE44: =IF(G44="SMP",H44,0) -> 0 | AF44: =IF(G44="SPP",H44,0) -> 0 | AG44: =IF(G44="SAP",H44,0) -> 0
B45: =IF(E45=" "," ",IF(Employee!F$128>E$39," ",IF(Employee!F$130<E$39," ",Employee!D$134))) | E45: =IF(Employee!D$132="m"," ",IF(Employee!F$128>E$39," ",IF(Employee!F$130<E$39," ",Employee!D$133))) | F45: =IF(E45=" "," ",IF(Employee!F$128>E$39," ",IF(Employee!F$130<E$39," ",Employee!D$119))) | H45: =IF(T$39="Y",H35,0) -> 0 | I45: =IF(T$39="Y",I35,0) -> 0 | J45: =IF(T$39="Y",J35,0) -> 0 | K45: =IF(T$39="Y",K35,I45*J45) -> 0 | L45: =IF(T$39="Y",L35,0) -> 0 | M45: =IF(E45=" "," ",IF(T$39="Y",M35,IF((H45+K45+L45)>0,H45+K45+L45," "))) | N45: 0 | O45: 0 | P45: 0 | Q45: 0 | R45: =IF(M45=" "," ",IF(M45=0," ",M45-SUM(N45:Q45))) | T45: 0 | V45: =IF(Employee!H$138=E$39,Employee!D$138+SUM(M45)+V35,SUM(M45)+V35) -> 0 | W45: =IF(Employee!H$138=E$39,Employee!D$139+SUM(N45)+W35,SUM(N45)+W35) -> 0 | X45: =IF(O45=" ",X35,O45+X35) -> 0 | Y45: =IF(P45=0,Y35,P45+Y35) -> 0 | Z45: =IF(Q45=0,Z35,Q45+Z35) -> 0 | AA45: =IF(R45=" ",AA35,AA35+R45) -> 0 | AC45: =IF(T45=" ",AC35,T45+AC35) -> 0 | AD45: =IF(G45="SSP",H45,0) -> 0 | AE45: =IF(G45="SMP",H45,0) -> 0 | AF45: =IF(G45="SPP",H45,0) -> 0 | AG45: =IF(G45="SAP",H45,0) -> 0
F46: Payroll Total | M46: =SUM(M41:M45) -> 0 | N46: =SUM(N41:N45) -> 0 | O46: =SUM(O41:O45) -> 0 | P46: =SUM(P41:P45) -> 0 | Q46: =SUM(Q41:Q45) -> 0 | R46: =SUM(R41:R45) -> 0 | T46: =SUM(T41:T45) -> 0
B48: WEEKLY PAYROLL | O48: Date Wages paid
B49: Week number | E49: 13 | H49: Date Wages paid | K49: =M39+1 -> 45831 | L49: - | M49: =K49+6 -> 45837 | O49: One Click to repeat previous week Enter Y
B51: =IF(E51=" "," ",IF(Employee!F$24>E$39," ",IF(Employee!F$26<E$39," ",Employee!D$30))) | E51: =IF(Employee!D$28="m"," ",IF(Employee!F$24>E$39," ",IF(Employee!F$26<E$39," ",Employee!D$29))) | F51: =IF(E51=" "," ",IF(Employee!F$24>E$39," ",IF(Employee!F$26<E$39," ",Employee!D$15))) | H51: =IF(T$39="Y",H41,0) -> 0 | I51: =IF(T$39="Y",I41,0) -> 0 | J51: =IF(T$39="Y",J41,0) -> 0 | K51: =IF(T$39="Y",K41,I51*J51) -> 0 | L51: =IF(T$39="Y",L41,0) -> 0 | M51: =IF(E51=" "," ",IF(T$39="Y",M41,IF((H51+K51+L51)>0,H51+K51+L51," "))) | N51: 0 | O51: 0 | P51: 0 | Q51: 0 | R51: =IF(M51=" "," ",IF(M51=0," ",M51-SUM(N51:Q51))) | T51: 0 | V51: =IF(Employee!H$34=E$49,Employee!D$34+SUM(M51)+V41,SUM(M51)+V41) -> 0 | W51: =IF(Employee!H$34=E$49,Employee!D$35+SUM(N51)+W41,SUM(N51)+W41) -> 0 | X51: =IF(O51=" ",X41,O51+X41) -> 0 | Y51: =IF(P51=0,Y41,P51+Y41) -> 0 | Z51: =IF(Q51=0,Z41,Q51+Z41) -> 0 | AA51: =IF(R51=" ",AA41,AA41+R51) -> 0 | AC51: =IF(T51=" ",AC41,T51+AC41) -> 0 | AD51: =IF(G51="SSP",H51,0) -> 0 | AE51: =IF(G51="SMP",H51,0) -> 0 | AF51: =IF(G51="SPP",H51,0) -> 0 | AG51: =IF(G51="SAP",H51,0) -> 0
B52: =IF(E52=" "," ",IF(Employee!F$50>E$39," ",IF(Employee!F$52<E$39," ",Employee!D$56))) | E52: =IF(Employee!D$54="m"," ",IF(Employee!F$50>E$39," ",IF(Employee!F$52<E$39," ",Employee!D$55))) | F52: =IF(E52=" "," ",IF(Employee!F$50>E$39," ",IF(Employee!F$52<E$39," ",Employee!D$41))) | H52: =IF(T$39="Y",H42,0) -> 0 | I52: =IF(T$39="Y",I42,0) -> 0 | J52: =IF(T$39="Y",J42,0) -> 0 | K52: =IF(T$39="Y",K42,I52*J52) -> 0 | L52: =IF(T$39="Y",L42,0) -> 0 | M52: =IF(E52=" "," ",IF(T$39="Y",M42,IF((H52+K52+L52)>0,H52+K52+L52," "))) | N52: 0 | O52: 0 | P52: 0 | Q52: 0 | R52: =IF(M52=" "," ",IF(M52=0," ",M52-SUM(N52:Q52))) | T52: 0 | V52: =IF(Employee!H$60=E$49,Employee!D$60+SUM(M52)+V42,SUM(M52)+V42) -> 0 | W52: =IF(Employee!H$60=E$49,Employee!D$61+SUM(N52)+W42,SUM(N52)+W42) -> 0 | X52: =IF(O52=" ",X42,O52+X42) -> 0 | Y52: =IF(P52=0,Y42,P52+Y42) -> 0 | Z52: =IF(Q52=0,Z42,Q52+Z42) -> 0 | AA52: =IF(R52=" ",AA42,AA42+R52) -> 0 | AC52: =IF(T52=" ",AC42,T52+AC42) -> 0 | AD52: =IF(G52="SSP",H52,0) -> 0 | AE52: =IF(G52="SMP",H52,0) -> 0 | AF52: =IF(G52="SPP",H52,0) -> 0 | AG52: =IF(G52="SAP",H52,0) -> 0
B53: =IF(E53=" "," ",IF(Employee!F$76>E$39," ",IF(Employee!F$78<E$39," ",Employee!D$82))) | E53: =IF(Employee!D$80="m"," ",IF(Employee!F$76>E$39," ",IF(Employee!F$78<E$39," ",Employee!D$81))) | F53: =IF(E53=" "," ",IF(Employee!F$76>E$39," ",IF(Employee!F$78<E$39," ",Employee!D$67))) | H53: =IF(T$39="Y",H43,0) -> 0 | I53: =IF(T$39="Y",I43,0) -> 0 | J53: =IF(T$39="Y",J43,0) -> 0 | K53: =IF(T$39="Y",K43,I53*J53) -> 0 | L53: =IF(T$39="Y",L43,0) -> 0 | M53: =IF(E53=" "," ",IF(T$39="Y",M43,IF((H53+K53+L53)>0,H53+K53+L53," "))) | N53: 0 | O53: 0 | P53: 0 | Q53: 0 | R53: =IF(M53=" "," ",IF(M53=0," ",M53-SUM(N53:Q53))) | T53: 0 | V53: =IF(Employee!H$86=E$49,Employee!D$86+SUM(M53)+V43,SUM(M53)+V43) -> 0 | W53: =IF(Employee!H$86=E$49,Employee!D$87+SUM(N53)+W43,SUM(N53)+W43) -> 0 | X53: =IF(O53=" ",X43,O53+X43) -> 0 | Y53: =IF(P53=0,Y43,P53+Y43) -> 0 | Z53: =IF(Q53=0,Z43,Q53+Z43) -> 0 | AA53: =IF(R53=" ",AA43,AA43+R53) -> 0 | AC53: =IF(T53=" ",AC43,T53+AC43) -> 0 | AD53: =IF(G53="SSP",H53,0) -> 0 | AE53: =IF(G53="SMP",H53,0) -> 0 | AF53: =IF(G53="SPP",H53,0) -> 0 | AG53: =IF(G53="SAP",H53,0) -> 0
B54: =IF(E54=" "," ",IF(Employee!F$102>E$39," ",IF(Employee!F$104<E$39," ",Employee!D$108))) | E54: =IF(Employee!D$106="m"," ",IF(Employee!F$102>E$39," ",IF(Employee!F$104<E$39," ",Employee!D$107))) | F54: =IF(E54=" "," ",IF(Employee!F$102>E$39," ",IF(Employee!F$104<E$39," ",Employee!D$93))) | H54: =IF(T$39="Y",H44,0) -> 0 | I54: =IF(T$39="Y",I44,0) -> 0 | J54: =IF(T$39="Y",J44,0) -> 0 | K54: =IF(T$39="Y",K44,I54*J54) -> 0 | L54: =IF(T$39="Y",L44,0) -> 0 | M54: =IF(E54=" "," ",IF(T$39="Y",M44,IF((H54+K54+L54)>0,H54+K54+L54," "))) | N54: 0 | O54: 0 | P54: 0 | Q54: 0 | R54: =IF(M54=" "," ",IF(M54=0," ",M54-SUM(N54:Q54))) | T54: 0 | V54: =IF(Employee!H$112=E$49,Employee!D$112+SUM(M54)+V44,SUM(M54)+V44) -> 0 | W54: =IF(Employee!H$112=E$49,Employee!D$113+SUM(N54)+W44,SUM(N54)+W44) -> 0 | X54: =IF(O54=" ",X44,O54+X44) -> 0 | Y54: =IF(P54=0,Y44,P54+Y44) -> 0 | Z54: =IF(Q54=0,Z44,Q54+Z44) -> 0 | AA54: =IF(R54=" ",AA44,AA44+R54) -> 0 | AC54: =IF(T54=" ",AC44,T54+AC44) -> 0 | AD54: =IF(G54="SSP",H54,0) -> 0 | AE54: =IF(G54="SMP",H54,0) -> 0 | AF54: =IF(G54="SPP",H54,0) -> 0 | AG54: =IF(G54="SAP",H54,0) -> 0
B55: =IF(E55=" "," ",IF(Employee!F$128>E$39," ",IF(Employee!F$130<E$39," ",Employee!D$134))) | E55: =IF(Employee!D$132="m"," ",IF(Employee!F$128>E$39," ",IF(Employee!F$130<E$39," ",Employee!D$133))) | F55: =IF(E55=" "," ",IF(Employee!F$128>E$39," ",IF(Employee!F$130<E$39," ",Employee!D$119))) | H55: =IF(T$39="Y",H45,0) -> 0 | I55: =IF(T$39="Y",I45,0) -> 0 | J55: =IF(T$39="Y",J45,0) -> 0 | K55: =IF(T$39="Y",K45,I55*J55) -> 0 | L55: =IF(T$39="Y",L45,0) -> 0 | M55: =IF(E55=" "," ",IF(T$39="Y",M45,IF((H55+K55+L55)>0,H55+K55+L55," "))) | N55: 0 | O55: 0 | P55: 0 | Q55: 0 | R55: =IF(M55=" "," ",IF(M55=0," ",M55-SUM(N55:Q55))) | T55: 0 | V55: =IF(Employee!H$138=E$49,Employee!D$138+SUM(M55)+V45,SUM(M55)+V45) -> 0 | W55: =IF(Employee!H$138=E$49,Employee!D$139+SUM(N55)+W45,SUM(N55)+W45) -> 0 | X55: =IF(O55=" ",X45,O55+X45) -> 0 | Y55: =IF(P55=0,Y45,P55+Y45) -> 0 | Z55: =IF(Q55=0,Z45,Q55+Z45) -> 0 | AA55: =IF(R55=" ",AA45,AA45+R55) -> 0 | AC55: =IF(T55=" ",AC45,T55+AC45) -> 0 | AD55: =IF(G55="SSP",H55,0) -> 0 | AE55: =IF(G55="SMP",H55,0) -> 0 | AF55: =IF(G55="SPP",H55,0) -> 0 | AG55: =IF(G55="SAP",H55,0) -> 0
F56: Payroll Total | M56: =SUM(M51:M55) -> 0 | N56: =SUM(N51:N55) -> 0 | O56: =SUM(O51:O55) -> 0 | P56: =SUM(P51:P55) -> 0 | Q56: =SUM(Q51:Q55) -> 0 | R56: =SUM(R51:R55) -> 0 | T56: =SUM(T51:T55) -> 0
B58: MONTHLY PAYROLL | O58: Date Wages paid
B59: Month number | E59: 3 | H59: Date Wages paid | K59: =DATE(2024,8,1) -> 45505 | L59: - | M59: =DATE(2024,8,31) -> 45535 | O59: One Click to repeat previous month Enter Y
B61: =IF(E61=" "," ",IF(Employee!F$24>E$59," ",IF(Employee!F$26<E$59," ",Employee!D$30))) | E61: =IF(Employee!D$28="w"," ",IF(Employee!F$24>E$59," ",IF(Employee!F$26<E$59," ",Employee!D$29))) | F61: =IF(E61=" "," ",IF(Employee!F$24>E$59," ",IF(Employee!F$26<E$59," ",Employee!D$15))) | H61: =IF(T$59="Y",Jul!H51,0) -> 0 | I61: =IF(T$59="Y",Jul!I51,0) -> 0 | J61: =IF(T$59="Y",Jul!J51,0) -> 0 | K61: =IF(T$59="Y",Jul!K51,I61*J61) -> 0 | L61: =IF(T$59="Y",Jul!L51,0) -> 0 | M61: =IF(E61=" "," ",IF(T$59="Y",Jul!M51,IF((H61+K61+L61)>0,H61+K61+L61," "))) | N61: 0 | O61: 0 | P61: 0 | Q61: 0 | R61: =IF(M61=" "," ",IF(M61=0," ",M61-SUM(N61:Q61))) | T61: 0 | V61: =IF(Employee!H$35=E$59,Employee!D$34+SUM(M61)+Jul!V51,SUM(M61)+Jul!V51) -> 0 | W61: =IF(Employee!H$35=E$59,Employee!D$35+SUM(N61)+Jul!W51,SUM(N61)+Jul!W51) -> 0 | X61: =IF(O61=" ",Jul!X51,O61+Jul!X51) -> 0 | Y61: =IF(P61=" ",Jul!Y51,P61+Jul!Y51) -> 0 | Z61: =IF(Q61=" ",Jul!Z51,Q61+Jul!Z51) -> 0 | AA61: =IF(R61=" ",Jul!AA51,R61+Jul!AA51) -> 0 | AC61: =IF(T61=" ",Jul!AC51,T61+Jul!AC51) -> 0 | AD61: =IF(G61="SSP",H61,0) -> 0 | AE61: =IF(G61="SMP",H61,0) -> 0 | AF61: =IF(G61="SPP",H61,0) -> 0 | AG61: =IF(G61="SAP",H61,0) -> 0
B62: =IF(E62=" "," ",IF(Employee!F$50>E$59," ",IF(Employee!F$52<E$59," ",Employee!D$56))) | E62: =IF(Employee!D$54="w"," ",IF(Employee!F$50>E$59," ",IF(Employee!F$52<E$59," ",Employee!D$55))) | F62: =IF(E62=" "," ",IF(Employee!F$50>E$59," ",IF(Employee!F$52<E$59," ",Employee!D$41))) | H62: =IF(T$59="Y",Jul!H52,0) -> 0 | I62: =IF(T$59="Y",Jul!I52,0) -> 0 | J62: =IF(T$59="Y",Jul!J52,0) -> 0 | K62: =IF(T$59="Y",Jul!K52,I62*J62) -> 0 | L62: =IF(T$59="Y",Jul!L52,0) -> 0 | M62: =IF(E62=" "," ",IF(T$59="Y",Jul!M52,IF((H62+K62+L62)>0,H62+K62+L62," "))) | N62: 0 | O62: 0 | P62: 0 | Q62: 0 | R62: =IF(M62=" "," ",IF(M62=0," ",M62-SUM(N62:Q62))) | T62: 0 | V62: =IF(Employee!H$61=E$59,Employee!D$60+SUM(M62)+Jul!V52,SUM(M62)+Jul!V52) -> 0 | W62: =IF(Employee!H$61=E$59,Employee!D$61+SUM(N62)+Jul!W52,SUM(N62)+Jul!W52) -> 0 | X62: =IF(O62=" ",Jul!X52,O62+Jul!X52) -> 0 | Y62: =IF(P62=" ",Jul!Y52,P62+Jul!Y52) -> 0 | Z62: =IF(Q62=" ",Jul!Z52,Q62+Jul!Z52) -> 0 | AA62: =IF(R62=" ",Jul!AA52,R62+Jul!AA52) -> 0 | AC62: =IF(T62=" ",Jul!AC52,T62+Jul!AC52) -> 0 | AD62: =IF(G62="SSP",H62,0) -> 0 | AE62: =IF(G62="SMP",H62,0) -> 0 | AF62: =IF(G62="SPP",H62,0) -> 0 | AG62: =IF(G62="SAP",H62,0) -> 0
B63: =IF(E63=" "," ",IF(Employee!F$76>E$59," ",IF(Employee!F$78<E$59," ",Employee!D$82))) | E63: =IF(Employee!D$80="w"," ",IF(Employee!F$76>E$59," ",IF(Employee!F$78<E$59," ",Employee!D$81))) | F63: =IF(E63=" "," ",IF(Employee!F$76>E$59," ",IF(Employee!F$78<E$59," ",Employee!D$67))) | H63: =IF(T$59="Y",Jul!H53,0) -> 0 | I63: =IF(T$59="Y",Jul!I53,0) -> 0 | J63: =IF(T$59="Y",Jul!J53,0) -> 0 | K63: =IF(T$59="Y",Jul!K53,I63*J63) -> 0 | L63: =IF(T$59="Y",Jul!L53,0) -> 0 | M63: =IF(E63=" "," ",IF(T$59="Y",Jul!M53,IF((H63+K63+L63)>0,H63+K63+L63," "))) | N63: 0 | O63: 0 | P63: 0 | Q63: 0 | R63: =IF(M63=" "," ",IF(M63=0," ",M63-SUM(N63:Q63))) | T63: 0 | V63: =IF(Employee!H$87=E$59,Employee!D$86+SUM(M63)+Jul!V53,SUM(M63)+Jul!V53) -> 0 | W63: =IF(Employee!H$87=E$59,Employee!D$87+SUM(N63)+Jul!W53,SUM(N63)+Jul!W53) -> 0 | X63: =IF(O63=" ",Jul!X53,O63+Jul!X53) -> 0 | Y63: =IF(P63=" ",Jul!Y53,P63+Jul!Y53) -> 0 | Z63: =IF(Q63=" ",Jul!Z53,Q63+Jul!Z53) -> 0 | AA63: =IF(R63=" ",Jul!AA53,R63+Jul!AA53) -> 0 | AC63: =IF(T63=" ",Jul!AC53,T63+Jul!AC53) -> 0 | AD63: =IF(G63="SSP",H63,0) -> 0 | AE63: =IF(G63="SMP",H63,0) -> 0 | AF63: =IF(G63="SPP",H63,0) -> 0 | AG63: =IF(G63="SAP",H63,0) -> 0
B64: =IF(E64=" "," ",IF(Employee!F$102>E$59," ",IF(Employee!F$104<E$59," ",Employee!D$108))) | E64: =IF(Employee!D$106="w"," ",IF(Employee!F$102>E$59," ",IF(Employee!F$104<E$59," ",Employee!D$107))) | F64: =IF(E64=" "," ",IF(Employee!F$102>E$59," ",IF(Employee!F$104<E$59," ",Employee!D$93))) | H64: =IF(T$59="Y",Jul!H54,0) -> 0 | I64: =IF(T$59="Y",Jul!I54,0) -> 0 | J64: =IF(T$59="Y",Jul!J54,0) -> 0 | K64: =IF(T$59="Y",Jul!K54,I64*J64) -> 0 | L64: =IF(T$59="Y",Jul!L54,0) -> 0 | M64: =IF(E64=" "," ",IF(T$59="Y",Jul!M54,IF((H64+K64+L64)>0,H64+K64+L64," "))) | N64: 0 | O64: 0 | P64: 0 | Q64: 0 | R64: =IF(M64=" "," ",IF(M64=0," ",M64-SUM(N64:Q64))) | T64: 0 | V64: =IF(Employee!H$113=E$59,Employee!D$112+SUM(M64)+Jul!V54,SUM(M64)+Jul!V54) -> 0 | W64: =IF(Employee!H$113=E$59,Employee!D$113+SUM(N64)+Jul!W54,SUM(N64)+Jul!W54) -> 0 | X64: =IF(O64=" ",Jul!X54,O64+Jul!X54) -> 0 | Y64: =IF(P64=" ",Jul!Y54,P64+Jul!Y54) -> 0 | Z64: =IF(Q64=" ",Jul!Z54,Q64+Jul!Z54) -> 0 | AA64: =IF(R64=" ",Jul!AA54,R64+Jul!AA54) -> 0 | AC64: =IF(T64=" ",Jul!AC54,T64+Jul!AC54) -> 0 | AD64: =IF(G64="SSP",H64,0) -> 0 | AE64: =IF(G64="SMP",H64,0) -> 0 | AF64: =IF(G64="SPP",H64,0) -> 0 | AG64: =IF(G64="SAP",H64,0) -> 0
B65: =IF(E65=" "," ",IF(Employee!F$128>E$59," ",IF(Employee!F$130<E$59," ",Employee!D$134))) | E65: =IF(Employee!D$132="w"," ",IF(Employee!F$128>E$59," ",IF(Employee!F$130<E$59," ",Employee!D$133))) | F65: =IF(E65=" "," ",IF(Employee!F$128>E$59," ",IF(Employee!F$130<E$59," ",Employee!D$119))) | H65: =IF(T$59="Y",Jul!H55,0) -> 0 | I65: =IF(T$59="Y",Jul!I55,0) -> 0 | J65: =IF(T$59="Y",Jul!J55,0) -> 0 | K65: =IF(T$59="Y",Jul!K55,I65*J65) -> 0 | L65: =IF(T$59="Y",Jul!L55,0) -> 0 | M65: =IF(E65=" "," ",IF(T$59="Y",Jul!M55,IF((H65+K65+L65)>0,H65+K65+L65," "))) | N65: 0 | O65: 0 | P65: 0 | Q65: 0 | R65: =IF(M65=" "," ",IF(M65=0," ",M65-SUM(N65:Q65))) | T65: 0 | V65: =IF(Employee!H$139=E$59,Employee!D$138+SUM(M65)+Jul!V55,SUM(M65)+Jul!V55) -> 0 | W65: =IF(Employee!H$139=E$59,Employee!D$139+SUM(N65)+Jul!W55,SUM(N65)+Jul!W55) -> 0 | X65: =IF(O65=" ",Jul!X55,O65+Jul!X55) -> 0 | Y65: =IF(P65=" ",Jul!Y55,P65+Jul!Y55) -> 0 | Z65: =IF(Q65=" ",Jul!Z55,Q65+Jul!Z55) -> 0 | AA65: =IF(R65=" ",Jul!AA55,R65+Jul!AA55) -> 0 | AC65: =IF(T65=" ",Jul!AC55,T65+Jul!AC55) -> 0 | AD65: =IF(G65="SSP",H65,0) -> 0 | AE65: =IF(G65="SMP",H65,0) -> 0 | AF65: =IF(G65="SPP",H65,0) -> 0 | AG65: =IF(G65="SAP",H65,0) -> 0
F66: Payroll Total | M66: =SUM(M61:M65) -> 0 | N66: =SUM(N61:N65) -> 0 | O66: =SUM(O61:O65) -> 0 | P66: =SUM(P61:P65) -> 0 | Q66: =SUM(Q61:Q65) -> 0 | R66: =SUM(R61:R65) -> 0 | T66: =SUM(T61:T65) -> 0
AD68: =SUM(AD11:AD66) -> 0 | AE68: =SUM(AE11:AE66) -> 0 | AF68: =SUM(AF11:AF66) -> 0 | AG68: =SUM(AG11:AG66) -> 0
F69: Directors | M69: Directors Wages Limited Companies Only
F70: =IF(B61="D",Employee!D15," ") | M70: =IF(B61="D",M61," ") | N70: =IF(B61="D",N61," ") | O70: =IF(B61="D",O61," ") | P70: =IF(B61="D",P61," ") | Q70: =IF(B61="D",Q61," ") | R70: =IF(B61="D",R61," ") | T70: =IF(B61="D",T61," ") | AD70: =IF((AD68-(O1+T1)*0.13)>0,AD68-(Q1+T1)*0.13,0) -> 0 | AE70: =AE68 -> 0 | AF70: =AF68 -> 0 | AG70: =AG68 -> 0
F71: =IF(B62="D",Employee!D41," ") | M71: =IF(B62="D",M62," ") | N71: =IF(B62="D",N62," ") | O71: =IF(B62="D",O62," ") | P71: =IF(B62="D",P62," ") | Q71: =IF(B62="D",Q62," ") | R71: =IF(B62="D",R62," ") | T71: =IF(B62="D",T62," ")
F72: =IF(B63="D",Employee!D67," ") | M72: =IF(B63="D",M63," ") | N72: =IF(B63="D",N63," ") | O72: =IF(B63="D",O63," ") | P72: =IF(B63="D",P63," ") | Q72: =IF(B63="D",Q63," ") | R72: =IF(B63="D",R63," ") | T72: =IF(B63="D",T63," ") | AE72: =AE70*0.045 -> 0 | AF72: =AF70*0.045 -> 0 | AG72: =AG70*0.045 -> 0
F73: =IF(B64="D",Employee!D93," ") | M73: =IF(B64="D",M64," ") | N73: =IF(B64="D",N64," ") | O73: =IF(B64="D",O64," ") | P73: =IF(B64="D",P64," ") | Q73: =IF(B64="D",Q64," ") | R73: =IF(B64="D",R64," ") | T73: =IF(B64="D",T64," ")
F74: =IF(B65="D",Employee!D119," ") | M74: =IF(B65="D",M65," ") | N74: =IF(B65="D",N65," ") | O74: =IF(B65="D",O65," ") | P74: =IF(B65="D",P65," ") | Q74: =IF(B65="D",Q65," ") | R74: =IF(B65="D",R65," ") | T74: =IF(B65="D",T65," ")
F75: Director Totals | M75: =SUM(M70:M74) -> 0 | N75: =SUM(N70:N74) -> 0 | O75: =SUM(O70:O74) -> 0 | P75: =SUM(P70:P74) -> 0 | Q75: =SUM(Q70:Q74) -> 0 | R75: =SUM(R70:R74) -> 0 | T75: =SUM(T70:T74) -> 0 | AD75: =AD70+Jul!AD65 -> 0 | AE75: =AE70+Jul!AE65 -> 0 | AF75: =AF70+Jul!AF65 -> 0 | AG75: =AG70+Jul!AG65 -> 0
AE77: =AE72+Jul!AE67 -> 0 | AF77: =AF72+Jul!AF67 -> 0 | AG77: =AG72+Jul!AG67 -> 0

Sheet Sep
B1: www.diyaccounting.co.uk | G1: =SUM(AD60:AG60)+SUM(AE62:AG62) -> 0 | I1: Monthly Totals | M1: =M16+M26+M36+M46+M56 -> 0 | N1: =N16+N26+N36+N46+N56 -> 0 | O1: =O16+O26+O36+O46+O56 -> 0 | P1: =P16+P26+P36+P46+P56 -> 0 | Q1: =Q16+Q26+Q36+Q46+Q56 -> 0 | R1: =R16+R26+R36+R46+R56 -> 0 | T1: =T16+T26+T36+T46+T56 -> 0 | V1: YEAR TO DATE | AD1: Statutory Payments & NIC Recovered
I2: Sub Totals Directors | M2: =M65 -> 0 | N2: =N65 -> 0 | O2: =O65 -> 0 | P2: =P65 -> 0 | Q2: =Q65 -> 0 | R2: =R65 -> 0 | S2: =S65 -> 0 | T2: =T65 -> 0
B3: Dir Ref | C3: NIC Table | D3: Tax Code | E3: Pay No | F3: Employee Name | G3: SSP | H3: =Jun!H3:H6 -> Statutory Pay | I3: =Jun!I3:I6 -> Basic hours | J3: =Jun!J3:J6 -> Hourly rate | K3: =Jun!K3:K6 -> Basic wages | L3: =Jun!L3:L6 -> Overtime Bonus Gratuities | M3: =Jun!M3:M6 -> GROSS WAGES | N3: =Jun!N3:N6 -> Income Tax | O3: =Jun!O3:O6 -> Employees National Insurance | ... R3: =Jun!R3:R6 -> NET PAY | T3: =Jun!T3:T6 -> Employers National Insurance | V3: Gross Wages | W3: Income Tax | X3: Employees National Insurance | Y3: Student Loan deductions | Z3: Other Deductions | AA3: Net Pay | AC3: Employers National Insurance | AD3: Statutory Sick Pay Recovered | AE3: Statutory Maternity Pay Recovered | AF3: Statutory Paternity Pay Recovered | AG3: Statutory Adoption Pay Recovered
G4: SMP
G5: SPP
G6: SAP
B8: WEEKLY PAYROLL | O8: Date Wages paid
B9: Week number | E9: 14 | H9: Date Wages paid | K9: =Admin!B91 -> 45842 | L9: - | M9: =K9+6 -> 45848 | O9: One Click to repeat previous week Enter Y
B11: =IF(E11=" "," ",IF(Employee!F$24>E$9," ",IF(Employee!F$26<E$9," ",Employee!D$30))) | E11: =IF(Employee!D$28="m"," ",IF(Employee!F$24>E$9," ",IF(Employee!F$26<E$9," ",Employee!D$29))) | F11: =IF(E11=" "," ",IF(Employee!F$24>E$9," ",IF(Employee!F$26<E$9," ",Employee!D$15))) | H11: =IF(T$9="Y",Aug!H41,0) -> 0 | I11: =IF(T$9="Y",Aug!I41,0) -> 0 | J11: =IF(T$9="Y",Aug!J41,0) -> 0 | K11: =IF(T$9="Y",Aug!K41,I11*J11) -> 0 | L11: =IF(T$9="Y",Aug!L41,0) -> 0 | M11: =IF(E11=" "," ",IF(T$9="Y",Aug!M41,IF((H11+K11+L11)>0,H11+K11+L11," "))) | N11: 0 | O11: 0 | P11: 0 | Q11: 0 | R11: =IF(M11=" "," ",IF(M11=0," ",M11-SUM(N11:Q11))) | T11: 0 | V11: =IF(Employee!H$34=E$9,Employee!D$34+SUM(M11)+Aug!V51,SUM(M11)+Aug!V51) -> 0 | W11: =IF(Employee!H$34=E$9,Employee!D$35+SUM(N11)+Aug!W51,SUM(N11)+Aug!W51) -> 0 | X11: =IF(O11=" ",Aug!X51,O11+Aug!X51) -> 0 | Y11: =IF(P11=" ",Aug!Y51,P11+Aug!Y51) -> 0 | Z11: =IF(Q11=" ",Aug!Z51,Q11+Aug!Z51) -> 0 | AA11: =IF(R11=" ",Aug!AA51,R11+Aug!AA51) -> 0 | AC11: =IF(T11=" ",Aug!AC51,T11+Aug!AC51) -> 0 | AD11: =IF(G11="SSP",H11,0) -> 0 | AE11: =IF(G11="SMP",H11,0) -> 0 | AF11: =IF(G11="SPP",H11,0) -> 0 | AG11: =IF(G11="SAP",H11,0) -> 0
B12: =IF(E12=" "," ",IF(Employee!F$50>E$9," ",IF(Employee!F$52<E$9," ",Employee!D$56))) | E12: =IF(Employee!D$54="m"," ",IF(Employee!F$50>E$9," ",IF(Employee!F$52<E$9," ",Employee!D$55))) | F12: =IF(E12=" "," ",IF(Employee!F$50>E$9," ",IF(Employee!F$52<E$9," ",Employee!D$41))) | H12: =IF(T$9="Y",Aug!H42,0) -> 0 | I12: =IF(T$9="Y",Aug!I42,0) -> 0 | J12: =IF(T$9="Y",Aug!J42,0) -> 0 | K12: =IF(T$9="Y",Aug!K42,I12*J12) -> 0 | L12: =IF(T$9="Y",Aug!L42,0) -> 0 | M12: =IF(E12=" "," ",IF(T$9="Y",Aug!M42,IF((H12+K12+L12)>0,H12+K12+L12," "))) | N12: 0 | O12: 0 | P12: 0 | Q12: 0 | R12: =IF(M12=" "," ",IF(M12=0," ",M12-SUM(N12:Q12))) | T12: 0 | V12: =IF(Employee!H$60=E$9,Employee!D$60+SUM(M12)+Aug!V52,SUM(M12)+Aug!V52) -> 0 | W12: =IF(Employee!H$60=E$9,Employee!D$61+SUM(N12)+Aug!W52,SUM(N12)+Aug!W52) -> 0 | X12: =IF(O12=" ",Aug!X52,O12+Aug!X52) -> 0 | Y12: =IF(P12=" ",Aug!Y52,P12+Aug!Y52) -> 0 | Z12: =IF(Q12=" ",Aug!Z52,Q12+Aug!Z52) -> 0 | AA12: =IF(R12=" ",Aug!AA52,R12+Aug!AA52) -> 0 | AC12: =IF(T12=" ",Aug!AC52,T12+Aug!AC52) -> 0 | AD12: =IF(G12="SSP",H12,0) -> 0 | AE12: =IF(G12="SMP",H12,0) -> 0 | AF12: =IF(G12="SPP",H12,0) -> 0 | AG12: =IF(G12="SAP",H12,0) -> 0
B13: =IF(E13=" "," ",IF(Employee!F$76>E$9," ",IF(Employee!F$78<E$9," ",Employee!D$82))) | E13: =IF(Employee!D$80="m"," ",IF(Employee!F$76>E$9," ",IF(Employee!F$78<E$9," ",Employee!D$81))) | F13: =IF(E13=" "," ",IF(Employee!F$76>E$9," ",IF(Employee!F$78<E$9," ",Employee!D$67))) | H13: =IF(T$9="Y",Aug!H43,0) -> 0 | I13: =IF(T$9="Y",Aug!I43,0) -> 0 | J13: =IF(T$9="Y",Aug!J43,0) -> 0 | K13: =IF(T$9="Y",Aug!K43,I13*J13) -> 0 | L13: =IF(T$9="Y",Aug!L43,0) -> 0 | M13: =IF(E13=" "," ",IF(T$9="Y",Aug!M43,IF((H13+K13+L13)>0,H13+K13+L13," "))) | N13: 0 | O13: 0 | P13: 0 | Q13: 0 | R13: =IF(M13=" "," ",IF(M13=0," ",M13-SUM(N13:Q13))) | T13: 0 | V13: =IF(Employee!H$86=E$9,Employee!D$86+SUM(M13)+Aug!V53,SUM(M13)+Aug!V53) -> 0 | W13: =IF(Employee!H$86=E$9,Employee!D$87+SUM(N13)+Aug!W53,SUM(N13)+Aug!W53) -> 0 | X13: =IF(O13=" ",Aug!X53,O13+Aug!X53) -> 0 | Y13: =IF(P13=" ",Aug!Y53,P13+Aug!Y53) -> 0 | Z13: =IF(Q13=" ",Aug!Z53,Q13+Aug!Z53) -> 0 | AA13: =IF(R13=" ",Aug!AA53,R13+Aug!AA53) -> 0 | AC13: =IF(T13=" ",Aug!AC53,T13+Aug!AC53) -> 0 | AD13: =IF(G13="SSP",H13,0) -> 0 | AE13: =IF(G13="SMP",H13,0) -> 0 | AF13: =IF(G13="SPP",H13,0) -> 0 | AG13: =IF(G13="SAP",H13,0) -> 0
B14: =IF(E14=" "," ",IF(Employee!F$102>E$9," ",IF(Employee!F$104<E$9," ",Employee!D$108))) | E14: =IF(Employee!D$106="m"," ",IF(Employee!F$102>E$9," ",IF(Employee!F$104<E$9," ",Employee!D$107))) | F14: =IF(E14=" "," ",IF(Employee!F$102>E$9," ",IF(Employee!F$104<E$9," ",Employee!D$93))) | H14: =IF(T$9="Y",Aug!H44,0) -> 0 | I14: =IF(T$9="Y",Aug!I44,0) -> 0 | J14: =IF(T$9="Y",Aug!J44,0) -> 0 | K14: =IF(T$9="Y",Aug!K44,I14*J14) -> 0 | L14: =IF(T$9="Y",Aug!L44,0) -> 0 | M14: =IF(E14=" "," ",IF(T$9="Y",Aug!M44,IF((H14+K14+L14)>0,H14+K14+L14," "))) | N14: 0 | O14: 0 | P14: 0 | Q14: 0 | R14: =IF(M14=" "," ",IF(M14=0," ",M14-SUM(N14:Q14))) | T14: 0 | V14: =IF(Employee!H$112=E$9,Employee!D$112+SUM(M14)+Aug!V54,SUM(M14)+Aug!V54) -> 0 | W14: =IF(Employee!H$112=E$9,Employee!D$113+SUM(N14)+Aug!W54,SUM(N14)+Aug!W54) -> 0 | X14: =IF(O14=" ",Aug!X54,O14+Aug!X54) -> 0 | Y14: =IF(P14=" ",Aug!Y54,P14+Aug!Y54) -> 0 | Z14: =IF(Q14=" ",Aug!Z54,Q14+Aug!Z54) -> 0 | AA14: =IF(R14=" ",Aug!AA54,R14+Aug!AA54) -> 0 | AC14: =IF(T14=" ",Aug!AC54,T14+Aug!AC54) -> 0 | AD14: =IF(G14="SSP",H14,0) -> 0 | AE14: =IF(G14="SMP",H14,0) -> 0 | AF14: =IF(G14="SPP",H14,0) -> 0 | AG14: =IF(G14="SAP",H14,0) -> 0
B15: =IF(E15=" "," ",IF(Employee!F$128>E$9," ",IF(Employee!F$130<E$9," ",Employee!D$134))) | E15: =IF(Employee!D$132="m"," ",IF(Employee!F$128>E$9," ",IF(Employee!F$130<E$9," ",Employee!D$133))) | F15: =IF(E15=" "," ",IF(Employee!F$128>E$9," ",IF(Employee!F$130<E$9," ",Employee!D$119))) | H15: =IF(T$9="Y",Aug!H45,0) -> 0 | I15: =IF(T$9="Y",Aug!I45,0) -> 0 | J15: =IF(T$9="Y",Aug!J45,0) -> 0 | K15: =IF(T$9="Y",Aug!K45,I15*J15) -> 0 | L15: =IF(T$9="Y",Aug!L45,0) -> 0 | M15: =IF(E15=" "," ",IF(T$9="Y",Aug!M45,IF((H15+K15+L15)>0,H15+K15+L15," "))) | N15: 0 | O15: 0 | P15: 0 | Q15: 0 | R15: =IF(M15=" "," ",IF(M15=0," ",M15-SUM(N15:Q15))) | T15: 0 | V15: =IF(Employee!H$138=E$9,Employee!D$138+SUM(M15)+Aug!V55,SUM(M15)+Aug!V55) -> 0 | W15: =IF(Employee!H$138=E$9,Employee!D$139+SUM(N15)+Aug!W55,SUM(N15)+Aug!W55) -> 0 | X15: =IF(O15=" ",Aug!X55,O15+Aug!X55) -> 0 | Y15: =IF(P15=" ",Aug!Y55,P15+Aug!Y55) -> 0 | Z15: =IF(Q15=" ",Aug!Z55,Q15+Aug!Z55) -> 0 | AA15: =IF(R15=" ",Aug!AA55,R15+Aug!AA55) -> 0 | AC15: =IF(T15=" ",Aug!AC55,T15+Aug!AC55) -> 0 | AD15: =IF(G15="SSP",H15,0) -> 0 | AE15: =IF(G15="SMP",H15,0) -> 0 | AF15: =IF(G15="SPP",H15,0) -> 0 | AG15: =IF(G15="SAP",H15,0) -> 0
F16: Payroll Total | M16: =SUM(M11:M15) -> 0 | N16: =SUM(N11:N15) -> 0 | O16: =SUM(O11:O15) -> 0 | P16: =SUM(P11:P15) -> 0 | Q16: =SUM(Q11:Q15) -> 0 | R16: =SUM(R11:R15) -> 0 | T16: =SUM(T11:T15) -> 0
B18: WEEKLY PAYROLL | O18: Date Wages paid
B19: Week number | E19: 15 | H19: Date Wages paid | K19: =M9+1 -> 45849 | L19: - | M19: =K19+6 -> 45855 | O19: One Click to repeat previous week Enter Y
B21: =IF(E21=" "," ",IF(Employee!F$24>E$19," ",IF(Employee!F$26<E$19," ",Employee!D$30))) | E21: =IF(Employee!D$28="m"," ",IF(Employee!F$24>E$19," ",IF(Employee!F$26<E$19," ",Employee!D$29))) | F21: =IF(E21=" "," ",IF(Employee!F$24>E$19," ",IF(Employee!F$26<E$19," ",Employee!D$15))) | H21: =IF(T$19="Y",H11,0) -> 0 | I21: =IF(T$19="Y",I11,0) -> 0 | J21: =IF(T$19="Y",J11,0) -> 0 | K21: =IF(T$19="Y",K11,I21*J21) -> 0 | L21: =IF(T$19="Y",L11,0) -> 0 | M21: =IF(E21=" "," ",IF(T$19="Y",M11,IF((H21+K21+L21)>0,H21+K21+L21," "))) | N21: 0 | O21: 0 | P21: 0 | Q21: 0 | R21: =IF(M21=" "," ",IF(M21=0," ",M21-SUM(N21:Q21))) | T21: 0 | V21: =IF(Employee!H$34=E$19,Employee!D$34+SUM(M21)+V11,SUM(M21)+V11) -> 0 | W21: =IF(Employee!H$34=E$19,Employee!D$35+SUM(N21)+W11,SUM(N21)+W11) -> 0 | X21: =IF(O21=" ",X11,O21+X11) -> 0 | Y21: =IF(P21=0,Y11,P21+Y11) -> 0 | Z21: =IF(Q21=0,Z11,Q21+Z11) -> 0 | AA21: =IF(R21=" ",AA11,AA11+R21) -> 0 | AC21: =IF(T21=" ",AC11,T21+AC11) -> 0 | AD21: =IF(G21="SSP",H21,0) -> 0 | AE21: =IF(G21="SMP",H21,0) -> 0 | AF21: =IF(G21="SPP",H21,0) -> 0 | AG21: =IF(G21="SAP",H21,0) -> 0
B22: =IF(E22=" "," ",IF(Employee!F$50>E$19," ",IF(Employee!F$52<E$19," ",Employee!D$56))) | E22: =IF(Employee!D$54="m"," ",IF(Employee!F$50>E$19," ",IF(Employee!F$52<E$19," ",Employee!D$55))) | F22: =IF(E22=" "," ",IF(Employee!F$50>E$19," ",IF(Employee!F$52<E$19," ",Employee!D$41))) | H22: =IF(T$19="Y",H12,0) -> 0 | I22: =IF(T$19="Y",I12,0) -> 0 | J22: =IF(T$19="Y",J12,0) -> 0 | K22: =IF(T$19="Y",K12,I22*J22) -> 0 | L22: =IF(T$19="Y",L12,0) -> 0 | M22: =IF(E22=" "," ",IF(T$19="Y",M12,IF((H22+K22+L22)>0,H22+K22+L22," "))) | N22: 0 | O22: 0 | P22: 0 | Q22: 0 | R22: =IF(M22=" "," ",IF(M22=0," ",M22-SUM(N22:Q22))) | T22: 0 | V22: =IF(Employee!H$60=E$19,Employee!D$60+SUM(M22)+V12,SUM(M22)+V12) -> 0 | W22: =IF(Employee!H$60=E$19,Employee!D$61+SUM(N22)+W12,SUM(N22)+W12) -> 0 | X22: =IF(O22=" ",X12,O22+X12) -> 0 | Y22: =IF(P22=0,Y12,P22+Y12) -> 0 | Z22: =IF(Q22=0,Z12,Q22+Z12) -> 0 | AA22: =IF(R22=" ",AA12,AA12+R22) -> 0 | AC22: =IF(T22=" ",AC12,T22+AC12) -> 0 | AD22: =IF(G22="SSP",H22,0) -> 0 | AE22: =IF(G22="SMP",H22,0) -> 0 | AF22: =IF(G22="SPP",H22,0) -> 0 | AG22: =IF(G22="SAP",H22,0) -> 0
B23: =IF(E23=" "," ",IF(Employee!F$76>E$19," ",IF(Employee!F$78<E$19," ",Employee!D$82))) | E23: =IF(Employee!D$80="m"," ",IF(Employee!F$76>E$19," ",IF(Employee!F$78<E$19," ",Employee!D$81))) | F23: =IF(E23=" "," ",IF(Employee!F$76>E$19," ",IF(Employee!F$78<E$19," ",Employee!D$67))) | H23: =IF(T$19="Y",H13,0) -> 0 | I23: =IF(T$19="Y",I13,0) -> 0 | J23: =IF(T$19="Y",J13,0) -> 0 | K23: =IF(T$19="Y",K13,I23*J23) -> 0 | L23: =IF(T$19="Y",L13,0) -> 0 | M23: =IF(E23=" "," ",IF(T$19="Y",M13,IF((H23+K23+L23)>0,H23+K23+L23," "))) | N23: 0 | O23: 0 | P23: 0 | Q23: 0 | R23: =IF(M23=" "," ",IF(M23=0," ",M23-SUM(N23:Q23))) | T23: 0 | V23: =IF(Employee!H$86=E$19,Employee!D$86+SUM(M23)+V13,SUM(M23)+V13) -> 0 | W23: =IF(Employee!H$86=E$19,Employee!D$87+SUM(N23)+W13,SUM(N23)+W13) -> 0 | X23: =IF(O23=" ",X13,O23+X13) -> 0 | Y23: =IF(P23=0,Y13,P23+Y13) -> 0 | Z23: =IF(Q23=0,Z13,Q23+Z13) -> 0 | AA23: =IF(R23=" ",AA13,AA13+R23) -> 0 | AC23: =IF(T23=" ",AC13,T23+AC13) -> 0 | AD23: =IF(G23="SSP",H23,0) -> 0 | AE23: =IF(G23="SMP",H23,0) -> 0 | AF23: =IF(G23="SPP",H23,0) -> 0 | AG23: =IF(G23="SAP",H23,0) -> 0
B24: =IF(E24=" "," ",IF(Employee!F$102>E$19," ",IF(Employee!F$104<E$19," ",Employee!D$108))) | E24: =IF(Employee!D$106="m"," ",IF(Employee!F$102>E$19," ",IF(Employee!F$104<E$19," ",Employee!D$107))) | F24: =IF(E24=" "," ",IF(Employee!F$102>E$19," ",IF(Employee!F$104<E$19," ",Employee!D$93))) | H24: =IF(T$19="Y",H14,0) -> 0 | I24: =IF(T$19="Y",I14,0) -> 0 | J24: =IF(T$19="Y",J14,0) -> 0 | K24: =IF(T$19="Y",K14,I24*J24) -> 0 | L24: =IF(T$19="Y",L14,0) -> 0 | M24: =IF(E24=" "," ",IF(T$19="Y",M14,IF((H24+K24+L24)>0,H24+K24+L24," "))) | N24: 0 | O24: 0 | P24: 0 | Q24: 0 | R24: =IF(M24=" "," ",IF(M24=0," ",M24-SUM(N24:Q24))) | T24: 0 | V24: =IF(Employee!H$112=E$19,Employee!D$112+SUM(M24)+V14,SUM(M24)+V14) -> 0 | W24: =IF(Employee!H$112=E$19,Employee!D$113+SUM(N24)+W14,SUM(N24)+W14) -> 0 | X24: =IF(O24=" ",X14,O24+X14) -> 0 | Y24: =IF(P24=0,Y14,P24+Y14) -> 0 | Z24: =IF(Q24=0,Z14,Q24+Z14) -> 0 | AA24: =IF(R24=" ",AA14,AA14+R24) -> 0 | AC24: =IF(T24=" ",AC14,T24+AC14) -> 0 | AD24: =IF(G24="SSP",H24,0) -> 0 | AE24: =IF(G24="SMP",H24,0) -> 0 | AF24: =IF(G24="SPP",H24,0) -> 0 | AG24: =IF(G24="SAP",H24,0) -> 0
B25: =IF(E25=" "," ",IF(Employee!F$128>E$19," ",IF(Employee!F$130<E$19," ",Employee!D$134))) | E25: =IF(Employee!D$132="m"," ",IF(Employee!F$128>E$19," ",IF(Employee!F$130<E$19," ",Employee!D$133))) | F25: =IF(E25=" "," ",IF(Employee!F$128>E$19," ",IF(Employee!F$130<E$19," ",Employee!D$119))) | H25: =IF(T$19="Y",H15,0) -> 0 | I25: =IF(T$19="Y",I15,0) -> 0 | J25: =IF(T$19="Y",J15,0) -> 0 | K25: =IF(T$19="Y",K15,I25*J25) -> 0 | L25: =IF(T$19="Y",L15,0) -> 0 | M25: =IF(E25=" "," ",IF(T$19="Y",M15,IF((H25+K25+L25)>0,H25+K25+L25," "))) | N25: 0 | O25: 0 | P25: 0 | Q25: 0 | R25: =IF(M25=" "," ",IF(M25=0," ",M25-SUM(N25:Q25))) | T25: 0 | V25: =IF(Employee!H$138=E$19,Employee!D$138+SUM(M25)+V15,SUM(M25)+V15) -> 0 | W25: =IF(Employee!H$138=E$19,Employee!D$139+SUM(N25)+W15,SUM(N25)+W15) -> 0 | X25: =IF(O25=" ",X15,O25+X15) -> 0 | Y25: =IF(P25=0,Y15,P25+Y15) -> 0 | Z25: =IF(Q25=0,Z15,Q25+Z15) -> 0 | AA25: =IF(R25=" ",AA15,AA15+R25) -> 0 | AC25: =IF(T25=" ",AC15,T25+AC15) -> 0 | AD25: =IF(G25="SSP",H25,0) -> 0 | AE25: =IF(G25="SMP",H25,0) -> 0 | AF25: =IF(G25="SPP",H25,0) -> 0 | AG25: =IF(G25="SAP",H25,0) -> 0
F26: Payroll Total | M26: =SUM(M21:M25) -> 0 | N26: =SUM(N21:N25) -> 0 | O26: =SUM(O21:O25) -> 0 | P26: =SUM(P21:P25) -> 0 | Q26: =SUM(Q21:Q25) -> 0 | R26: =SUM(R21:R25) -> 0 | T26: =SUM(T21:T25) -> 0
B28: WEEKLY PAYROLL | O28: Date Wages paid
B29: Week number | E29: 16 | H29: Date Wages paid | K29: =M19+1 -> 45856 | L29: - | M29: =K29+6 -> 45862 | O29: One Click to repeat previous week Enter Y
B31: =IF(E31=" "," ",IF(Employee!F$24>E$29," ",IF(Employee!F$26<E$29," ",Employee!D$30))) | E31: =IF(Employee!D$28="m"," ",IF(Employee!F$24>E$29," ",IF(Employee!F$26<E$29," ",Employee!D$29))) | F31: =IF(E31=" "," ",IF(Employee!F$24>E$29," ",IF(Employee!F$26<E$29," ",Employee!D$15))) | H31: =IF(T$29="Y",H21,0) -> 0 | I31: =IF(T$29="Y",I21,0) -> 0 | J31: =IF(T$29="Y",J21,0) -> 0 | K31: =IF(T$29="Y",K21,I31*J31) -> 0 | L31: =IF(T$29="Y",L21,0) -> 0 | M31: =IF(E31=" "," ",IF(T$29="Y",M21,IF((H31+K31+L31)>0,H31+K31+L31," "))) | N31: 0 | O31: 0 | P31: 0 | Q31: 0 | R31: =IF(M31=" "," ",IF(M31=0," ",M31-SUM(N31:Q31))) | T31: 0 | V31: =IF(Employee!H$34=E$29,Employee!D$34+SUM(M31)+V21,SUM(M31)+V21) -> 0 | W31: =IF(Employee!H$34=E$29,Employee!D$35+SUM(N31)+W21,SUM(N31)+W21) -> 0 | X31: =IF(O31=" ",X21,O31+X21) -> 0 | Y31: =IF(P31=0,Y21,P31+Y21) -> 0 | Z31: =IF(Q31=0,Z21,Q31+Z21) -> 0 | AA31: =IF(R31=" ",AA21,AA21+R31) -> 0 | AC31: =IF(T31=" ",AC21,T31+AC21) -> 0 | AD31: =IF(G31="SSP",H31,0) -> 0 | AE31: =IF(G31="SMP",H31,0) -> 0 | AF31: =IF(G31="SPP",H31,0) -> 0 | AG31: =IF(G31="SAP",H31,0) -> 0
B32: =IF(E32=" "," ",IF(Employee!F$50>E$29," ",IF(Employee!F$52<E$29," ",Employee!D$56))) | E32: =IF(Employee!D$54="m"," ",IF(Employee!F$50>E$29," ",IF(Employee!F$52<E$29," ",Employee!D$55))) | F32: =IF(E32=" "," ",IF(Employee!F$50>E$29," ",IF(Employee!F$52<E$29," ",Employee!D$41))) | H32: =IF(T$29="Y",H22,0) -> 0 | I32: =IF(T$29="Y",I22,0) -> 0 | J32: =IF(T$29="Y",J22,0) -> 0 | K32: =IF(T$29="Y",K22,I32*J32) -> 0 | L32: =IF(T$29="Y",L22,0) -> 0 | M32: =IF(E32=" "," ",IF(T$29="Y",M22,IF((H32+K32+L32)>0,H32+K32+L32," "))) | N32: 0 | O32: 0 | P32: 0 | Q32: 0 | R32: =IF(M32=" "," ",IF(M32=0," ",M32-SUM(N32:Q32))) | T32: 0 | V32: =IF(Employee!H$60=E$29,Employee!D$60+SUM(M32)+V22,SUM(M32)+V22) -> 0 | W32: =IF(Employee!H$60=E$29,Employee!D$61+SUM(N32)+W22,SUM(N32)+W22) -> 0 | X32: =IF(O32=" ",X22,O32+X22) -> 0 | Y32: =IF(P32=0,Y22,P32+Y22) -> 0 | Z32: =IF(Q32=0,Z22,Q32+Z22) -> 0 | AA32: =IF(R32=" ",AA22,AA22+R32) -> 0 | AC32: =IF(T32=" ",AC22,T32+AC22) -> 0 | AD32: =IF(G32="SSP",H32,0) -> 0 | AE32: =IF(G32="SMP",H32,0) -> 0 | AF32: =IF(G32="SPP",H32,0) -> 0 | AG32: =IF(G32="SAP",H32,0) -> 0
B33: =IF(E33=" "," ",IF(Employee!F$76>E$29," ",IF(Employee!F$78<E$29," ",Employee!D$82))) | E33: =IF(Employee!D$80="m"," ",IF(Employee!F$76>E$29," ",IF(Employee!F$78<E$29," ",Employee!D$81))) | F33: =IF(E33=" "," ",IF(Employee!F$76>E$29," ",IF(Employee!F$78<E$29," ",Employee!D$67))) | H33: =IF(T$29="Y",H23,0) -> 0 | I33: =IF(T$29="Y",I23,0) -> 0 | J33: =IF(T$29="Y",J23,0) -> 0 | K33: =IF(T$29="Y",K23,I33*J33) -> 0 | L33: =IF(T$29="Y",L23,0) -> 0 | M33: =IF(E33=" "," ",IF(T$29="Y",M23,IF((H33+K33+L33)>0,H33+K33+L33," "))) | N33: 0 | O33: 0 | P33: 0 | Q33: 0 | R33: =IF(M33=" "," ",IF(M33=0," ",M33-SUM(N33:Q33))) | T33: 0 | V33: =IF(Employee!H$86=E$29,Employee!D$86+SUM(M33)+V23,SUM(M33)+V23) -> 0 | W33: =IF(Employee!H$86=E$29,Employee!D$87+SUM(N33)+W23,SUM(N33)+W23) -> 0 | X33: =IF(O33=" ",X23,O33+X23) -> 0 | Y33: =IF(P33=0,Y23,P33+Y23) -> 0 | Z33: =IF(Q33=0,Z23,Q33+Z23) -> 0 | AA33: =IF(R33=" ",AA23,AA23+R33) -> 0 | AC33: =IF(T33=" ",AC23,T33+AC23) -> 0 | AD33: =IF(G33="SSP",H33,0) -> 0 | AE33: =IF(G33="SMP",H33,0) -> 0 | AF33: =IF(G33="SPP",H33,0) -> 0 | AG33: =IF(G33="SAP",H33,0) -> 0
B34: =IF(E34=" "," ",IF(Employee!F$102>E$29," ",IF(Employee!F$104<E$29," ",Employee!D$108))) | E34: =IF(Employee!D$106="m"," ",IF(Employee!F$102>E$29," ",IF(Employee!F$104<E$29," ",Employee!D$107))) | F34: =IF(E34=" "," ",IF(Employee!F$102>E$29," ",IF(Employee!F$104<E$29," ",Employee!D$93))) | H34: =IF(T$29="Y",H24,0) -> 0 | I34: =IF(T$29="Y",I24,0) -> 0 | J34: =IF(T$29="Y",J24,0) -> 0 | K34: =IF(T$29="Y",K24,I34*J34) -> 0 | L34: =IF(T$29="Y",L24,0) -> 0 | M34: =IF(E34=" "," ",IF(T$29="Y",M24,IF((H34+K34+L34)>0,H34+K34+L34," "))) | N34: 0 | O34: 0 | P34: 0 | Q34: 0 | R34: =IF(M34=" "," ",IF(M34=0," ",M34-SUM(N34:Q34))) | T34: 0 | V34: =IF(Employee!H$112=E$29,Employee!D$112+SUM(M34)+V24,SUM(M34)+V24) -> 0 | W34: =IF(Employee!H$112=E$29,Employee!D$113+SUM(N34)+W24,SUM(N34)+W24) -> 0 | X34: =IF(O34=" ",X24,O34+X24) -> 0 | Y34: =IF(P34=0,Y24,P34+Y24) -> 0 | Z34: =IF(Q34=0,Z24,Q34+Z24) -> 0 | AA34: =IF(R34=" ",AA24,AA24+R34) -> 0 | AC34: =IF(T34=" ",AC24,T34+AC24) -> 0 | AD34: =IF(G34="SSP",H34,0) -> 0 | AE34: =IF(G34="SMP",H34,0) -> 0 | AF34: =IF(G34="SPP",H34,0) -> 0 | AG34: =IF(G34="SAP",H34,0) -> 0
B35: =IF(E35=" "," ",IF(Employee!F$128>E$29," ",IF(Employee!F$130<E$29," ",Employee!D$134))) | E35: =IF(Employee!D$132="m"," ",IF(Employee!F$128>E$29," ",IF(Employee!F$130<E$29," ",Employee!D$133))) | F35: =IF(E35=" "," ",IF(Employee!F$128>E$29," ",IF(Employee!F$130<E$29," ",Employee!D$119))) | H35: =IF(T$29="Y",H25,0) -> 0 | I35: =IF(T$29="Y",I25,0) -> 0 | J35: =IF(T$29="Y",J25,0) -> 0 | K35: =IF(T$29="Y",K25,I35*J35) -> 0 | L35: =IF(T$29="Y",L25,0) -> 0 | M35: =IF(E35=" "," ",IF(T$29="Y",M25,IF((H35+K35+L35)>0,H35+K35+L35," "))) | N35: 0 | O35: 0 | P35: 0 | Q35: 0 | R35: =IF(M35=" "," ",IF(M35=0," ",M35-SUM(N35:Q35))) | T35: 0 | V35: =IF(Employee!H$138=E$29,Employee!D$138+SUM(M35)+V25,SUM(M35)+V25) -> 0 | W35: =IF(Employee!H$138=E$29,Employee!D$139+SUM(N35)+W25,SUM(N35)+W25) -> 0 | X35: =IF(O35=" ",X25,O35+X25) -> 0 | Y35: =IF(P35=0,Y25,P35+Y25) -> 0 | Z35: =IF(Q35=0,Z25,Q35+Z25) -> 0 | AA35: =IF(R35=" ",AA25,AA25+R35) -> 0 | AC35: =IF(T35=" ",AC25,T35+AC25) -> 0 | AD35: =IF(G35="SSP",H35,0) -> 0 | AE35: =IF(G35="SMP",H35,0) -> 0 | AF35: =IF(G35="SPP",H35,0) -> 0 | AG35: =IF(G35="SAP",H35,0) -> 0
F36: Payroll Total | M36: =SUM(M31:M35) -> 0 | N36: =SUM(N31:N35) -> 0 | O36: =SUM(O31:O35) -> 0 | P36: =SUM(P31:P35) -> 0 | Q36: =SUM(Q31:Q35) -> 0 | R36: =SUM(R31:R35) -> 0 | T36: =SUM(T31:T35) -> 0
B38: WEEKLY PAYROLL | O38: Date Wages paid
B39: Week number | E39: 17 | H39: Date Wages paid | K39: =M29+1 -> 45863 | L39: - | M39: =K39+6 -> 45869 | O39: One Click to repeat previous week Enter Y
B41: =IF(E41=" "," ",IF(Employee!F$24>E$39," ",IF(Employee!F$26<E$39," ",Employee!D$30))) | E41: =IF(Employee!D$28="m"," ",IF(Employee!F$24>E$39," ",IF(Employee!F$26<E$39," ",Employee!D$29))) | F41: =IF(E41=" "," ",IF(Employee!F$24>E$39," ",IF(Employee!F$26<E$39," ",Employee!D$15))) | H41: =IF(T$39="Y",H31,0) -> 0 | I41: =IF(T$39="Y",I31,0) -> 0 | J41: =IF(T$39="Y",J31,0) -> 0 | K41: =IF(T$39="Y",K31,I41*J41) -> 0 | L41: =IF(T$39="Y",L31,0) -> 0 | M41: =IF(E41=" "," ",IF(T$39="Y",M31,IF((H41+K41+L41)>0,H41+K41+L41," "))) | N41: 0 | O41: 0 | P41: 0 | Q41: 0 | R41: =IF(M41=" "," ",IF(M41=0," ",M41-SUM(N41:Q41))) | T41: 0 | V41: =IF(Employee!H$34=E$39,Employee!D$34+SUM(M41)+V31,SUM(M41)+V31) -> 0 | W41: =IF(Employee!H$34=E$39,Employee!D$35+SUM(N41)+W31,SUM(N41)+W31) -> 0 | X41: =IF(O41=" ",X31,O41+X31) -> 0 | Y41: =IF(P41=0,Y31,P41+Y31) -> 0 | Z41: =IF(Q41=0,Z31,Q41+Z31) -> 0 | AA41: =IF(R41=" ",AA31,AA31+R41) -> 0 | AC41: =IF(T41=" ",AC31,T41+AC31) -> 0 | AD41: =IF(G41="SSP",H41,0) -> 0 | AE41: =IF(G41="SMP",H41,0) -> 0 | AF41: =IF(G41="SPP",H41,0) -> 0 | AG41: =IF(G41="SAP",H41,0) -> 0
B42: =IF(E42=" "," ",IF(Employee!F$50>E$39," ",IF(Employee!F$52<E$39," ",Employee!D$56))) | E42: =IF(Employee!D$54="m"," ",IF(Employee!F$50>E$39," ",IF(Employee!F$52<E$39," ",Employee!D$55))) | F42: =IF(E42=" "," ",IF(Employee!F$50>E$39," ",IF(Employee!F$52<E$39," ",Employee!D$41))) | H42: =IF(T$39="Y",H32,0) -> 0 | I42: =IF(T$39="Y",I32,0) -> 0 | J42: =IF(T$39="Y",J32,0) -> 0 | K42: =IF(T$39="Y",K32,I42*J42) -> 0 | L42: =IF(T$39="Y",L32,0) -> 0 | M42: =IF(E42=" "," ",IF(T$39="Y",M32,IF((H42+K42+L42)>0,H42+K42+L42," "))) | N42: 0 | O42: 0 | P42: 0 | Q42: 0 | R42: =IF(M42=" "," ",IF(M42=0," ",M42-SUM(N42:Q42))) | T42: 0 | V42: =IF(Employee!H$60=E$39,Employee!D$60+SUM(M42)+V32,SUM(M42)+V32) -> 0 | W42: =IF(Employee!H$60=E$39,Employee!D$61+SUM(N42)+W32,SUM(N42)+W32) -> 0 | X42: =IF(O42=" ",X32,O42+X32) -> 0 | Y42: =IF(P42=0,Y32,P42+Y32) -> 0 | Z42: =IF(Q42=0,Z32,Q42+Z32) -> 0 | AA42: =IF(R42=" ",AA32,AA32+R42) -> 0 | AC42: =IF(T42=" ",AC32,T42+AC32) -> 0 | AD42: =IF(G42="SSP",H42,0) -> 0 | AE42: =IF(G42="SMP",H42,0) -> 0 | AF42: =IF(G42="SPP",H42,0) -> 0 | AG42: =IF(G42="SAP",H42,0) -> 0
B43: =IF(E43=" "," ",IF(Employee!F$76>E$39," ",IF(Employee!F$78<E$39," ",Employee!D$82))) | E43: =IF(Employee!D$80="m"," ",IF(Employee!F$76>E$39," ",IF(Employee!F$78<E$39," ",Employee!D$81))) | F43: =IF(E43=" "," ",IF(Employee!F$76>E$39," ",IF(Employee!F$78<E$39," ",Employee!D$67))) | H43: =IF(T$39="Y",H33,0) -> 0 | I43: =IF(T$39="Y",I33,0) -> 0 | J43: =IF(T$39="Y",J33,0) -> 0 | K43: =IF(T$39="Y",K33,I43*J43) -> 0 | L43: =IF(T$39="Y",L33,0) -> 0 | M43: =IF(E43=" "," ",IF(T$39="Y",M33,IF((H43+K43+L43)>0,H43+K43+L43," "))) | N43: 0 | O43: 0 | P43: 0 | Q43: 0 | R43: =IF(M43=" "," ",IF(M43=0," ",M43-SUM(N43:Q43))) | T43: 0 | V43: =IF(Employee!H$86=E$39,Employee!D$86+SUM(M43)+V33,SUM(M43)+V33) -> 0 | W43: =IF(Employee!H$86=E$39,Employee!D$87+SUM(N43)+W33,SUM(N43)+W33) -> 0 | X43: =IF(O43=" ",X33,O43+X33) -> 0 | Y43: =IF(P43=0,Y33,P43+Y33) -> 0 | Z43: =IF(Q43=0,Z33,Q43+Z33) -> 0 | AA43: =IF(R43=" ",AA33,AA33+R43) -> 0 | AC43: =IF(T43=" ",AC33,T43+AC33) -> 0 | AD43: =IF(G43="SSP",H43,0) -> 0 | AE43: =IF(G43="SMP",H43,0) -> 0 | AF43: =IF(G43="SPP",H43,0) -> 0 | AG43: =IF(G43="SAP",H43,0) -> 0
B44: =IF(E44=" "," ",IF(Employee!F$102>E$39," ",IF(Employee!F$104<E$39," ",Employee!D$108))) | E44: =IF(Employee!D$106="m"," ",IF(Employee!F$102>E$39," ",IF(Employee!F$104<E$39," ",Employee!D$107))) | F44: =IF(E44=" "," ",IF(Employee!F$102>E$39," ",IF(Employee!F$104<E$39," ",Employee!D$93))) | H44: =IF(T$39="Y",H34,0) -> 0 | I44: =IF(T$39="Y",I34,0) -> 0 | J44: =IF(T$39="Y",J34,0) -> 0 | K44: =IF(T$39="Y",K34,I44*J44) -> 0 | L44: =IF(T$39="Y",L34,0) -> 0 | M44: =IF(E44=" "," ",IF(T$39="Y",M34,IF((H44+K44+L44)>0,H44+K44+L44," "))) | N44: 0 | O44: 0 | P44: 0 | Q44: 0 | R44: =IF(M44=" "," ",IF(M44=0," ",M44-SUM(N44:Q44))) | T44: 0 | V44: =IF(Employee!H$112=E$39,Employee!D$112+SUM(M44)+V34,SUM(M44)+V34) -> 0 | W44: =IF(Employee!H$112=E$39,Employee!D$113+SUM(N44)+W34,SUM(N44)+W34) -> 0 | X44: =IF(O44=" ",X34,O44+X34) -> 0 | Y44: =IF(P44=0,Y34,P44+Y34) -> 0 | Z44: =IF(Q44=0,Z34,Q44+Z34) -> 0 | AA44: =IF(R44=" ",AA34,AA34+R44) -> 0 | AC44: =IF(T44=" ",AC34,T44+AC34) -> 0 | AD44: =IF(G44="SSP",H44,0) -> 0 | AE44: =IF(G44="SMP",H44,0) -> 0 | AF44: =IF(G44="SPP",H44,0) -> 0 | AG44: =IF(G44="SAP",H44,0) -> 0
B45: =IF(E45=" "," ",IF(Employee!F$128>E$39," ",IF(Employee!F$130<E$39," ",Employee!D$134))) | E45: =IF(Employee!D$132="m"," ",IF(Employee!F$128>E$39," ",IF(Employee!F$130<E$39," ",Employee!D$133))) | F45: =IF(E45=" "," ",IF(Employee!F$128>E$39," ",IF(Employee!F$130<E$39," ",Employee!D$119))) | H45: =IF(T$39="Y",H35,0) -> 0 | I45: =IF(T$39="Y",I35,0) -> 0 | J45: =IF(T$39="Y",J35,0) -> 0 | K45: =IF(T$39="Y",K35,I45*J45) -> 0 | L45: =IF(T$39="Y",L35,0) -> 0 | M45: =IF(E45=" "," ",IF(T$39="Y",M35,IF((H45+K45+L45)>0,H45+K45+L45," "))) | N45: 0 | O45: 0 | P45: 0 | Q45: 0 | R45: =IF(M45=" "," ",IF(M45=0," ",M45-SUM(N45:Q45))) | T45: 0 | V45: =IF(Employee!H$138=E$39,Employee!D$138+SUM(M45)+V35,SUM(M45)+V35) -> 0 | W45: =IF(Employee!H$138=E$39,Employee!D$139+SUM(N45)+W35,SUM(N45)+W35) -> 0 | X45: =IF(O45=" ",X35,O45+X35) -> 0 | Y45: =IF(P45=0,Y35,P45+Y35) -> 0 | Z45: =IF(Q45=0,Z35,Q45+Z35) -> 0 | AA45: =IF(R45=" ",AA35,AA35+R45) -> 0 | AC45: =IF(T45=" ",AC35,T45+AC35) -> 0 | AD45: =IF(G45="SSP",H45,0) -> 0 | AE45: =IF(G45="SMP",H45,0) -> 0 | AF45: =IF(G45="SPP",H45,0) -> 0 | AG45: =IF(G45="SAP",H45,0) -> 0
F46: Payroll Total | M46: =SUM(M41:M45) -> 0 | N46: =SUM(N41:N45) -> 0 | O46: =SUM(O41:O45) -> 0 | P46: =SUM(P41:P45) -> 0 | Q46: =SUM(Q41:Q45) -> 0 | R46: =SUM(R41:R45) -> 0 | T46: 0
B48: MONTHLY PAYROLL | O48: Date Wages paid
B49: Month number | E49: 4 | H49: Date Wages paid | K49: =DATE(2024,9,1) -> 45536 | L49: - | M49: =DATE(2024,9,30) -> 45565 | O49: One Click to repeat previous month Enter Y
B51: =IF(E51=" "," ",IF(Employee!F$24>E$49," ",IF(Employee!F$26<E$49," ",Employee!D$30))) | E51: =IF(Employee!D$28="w"," ",IF(Employee!F$24>E$49," ",IF(Employee!F$26<E$49," ",Employee!D$29))) | F51: =IF(E51=" "," ",IF(Employee!F$24>E$49," ",IF(Employee!F$26<E$49," ",Employee!D$15))) | H51: =IF(T$49="Y",Aug!H61,0) -> 0 | I51: =IF(T$49="Y",Aug!I61,0) -> 0 | J51: =IF(T$49="Y",Aug!J61,0) -> 0 | K51: =IF(T$49="Y",Aug!K61,I51*J51) -> 0 | L51: =IF(T$49="Y",Aug!L61,0) -> 0 | M51: =IF(E51=" "," ",IF(T$49="Y",Aug!M61,IF((H51+K51+L51)>0,H51+K51+L51," "))) | N51: 0 | O51: 0 | P51: 0 | Q51: 0 | R51: =IF(M51=" "," ",IF(M51=0," ",M51-SUM(N51:Q51))) | T51: 0 | V51: =IF(Employee!H$35=E$49,Employee!D$34+SUM(M51)+Aug!V61,SUM(M51)+Aug!V61) -> 0 | W51: =IF(Employee!H$35=E$49,Employee!D$35+SUM(N51)+Aug!W61,SUM(N51)+Aug!W61) -> 0 | X51: =IF(O51=" ",Aug!X61,O51+Aug!X61) -> 0 | Y51: =IF(P51=" ",Aug!Y61,P51+Aug!Y61) -> 0 | Z51: =IF(Q51=" ",Aug!Z61,Q51+Aug!Z61) -> 0 | AA51: =IF(R51=" ",Aug!AA61,R51+Aug!AA61) -> 0 | AC51: =IF(T51=" ",Aug!AC61,T51+Aug!AC61) -> 0 | AD51: =IF(G51="SSP",H51,0) -> 0 | AE51: =IF(G51="SMP",H51,0) -> 0 | AF51: =IF(G51="SPP",H51,0) -> 0 | AG51: =IF(G51="SAP",H51,0) -> 0
B52: =IF(E52=" "," ",IF(Employee!F$50>E$49," ",IF(Employee!F$52<E$49," ",Employee!D$56))) | E52: =IF(Employee!D$54="w"," ",IF(Employee!F$50>E$49," ",IF(Employee!F$52<E$49," ",Employee!D$55))) | F52: =IF(E52=" "," ",IF(Employee!F$50>E$49," ",IF(Employee!F$52<E$49," ",Employee!D$41))) | H52: =IF(T$49="Y",Aug!H62,0) -> 0 | I52: =IF(T$49="Y",Aug!I62,0) -> 0 | J52: =IF(T$49="Y",Aug!J62,0) -> 0 | K52: =IF(T$49="Y",Aug!K62,I52*J52) -> 0 | L52: =IF(T$49="Y",Aug!L62,0) -> 0 | M52: =IF(E52=" "," ",IF(T$49="Y",Aug!M62,IF((H52+K52+L52)>0,H52+K52+L52," "))) | N52: 0 | O52: 0 | P52: 0 | Q52: 0 | R52: =IF(M52=" "," ",IF(M52=0," ",M52-SUM(N52:Q52))) | T52: 0 | V52: =IF(Employee!H$61=E$49,Employee!D$60+SUM(M52)+Aug!V62,SUM(M52)+Aug!V62) -> 0 | W52: =IF(Employee!H$61=E$49,Employee!D$61+SUM(N52)+Aug!W62,SUM(N52)+Aug!W62) -> 0 | X52: =IF(O52=" ",Aug!X62,O52+Aug!X62) -> 0 | Y52: =IF(P52=" ",Aug!Y62,P52+Aug!Y62) -> 0 | Z52: =IF(Q52=" ",Aug!Z62,Q52+Aug!Z62) -> 0 | AA52: =IF(R52=" ",Aug!AA62,R52+Aug!AA62) -> 0 | AC52: =IF(T52=" ",Aug!AC62,T52+Aug!AC62) -> 0 | AD52: =IF(G52="SSP",H52,0) -> 0 | AE52: =IF(G52="SMP",H52,0) -> 0 | AF52: =IF(G52="SPP",H52,0) -> 0 | AG52: =IF(G52="SAP",H52,0) -> 0
B53: =IF(E53=" "," ",IF(Employee!F$76>E$49," ",IF(Employee!F$78<E$49," ",Employee!D$82))) | E53: =IF(Employee!D$80="w"," ",IF(Employee!F$76>E$49," ",IF(Employee!F$78<E$49," ",Employee!D$81))) | F53: =IF(E53=" "," ",IF(Employee!F$76>E$49," ",IF(Employee!F$78<E$49," ",Employee!D$67))) | H53: =IF(T$49="Y",Aug!H63,0) -> 0 | I53: =IF(T$49="Y",Aug!I63,0) -> 0 | J53: =IF(T$49="Y",Aug!J63,0) -> 0 | K53: =IF(T$49="Y",Aug!K63,I53*J53) -> 0 | L53: =IF(T$49="Y",Aug!L63,0) -> 0 | M53: =IF(E53=" "," ",IF(T$49="Y",Aug!M63,IF((H53+K53+L53)>0,H53+K53+L53," "))) | N53: 0 | O53: 0 | P53: 0 | Q53: 0 | R53: =IF(M53=" "," ",IF(M53=0," ",M53-SUM(N53:Q53))) | T53: 0 | V53: =IF(Employee!H$87=E$49,Employee!D$86+SUM(M53)+Aug!V63,SUM(M53)+Aug!V63) -> 0 | W53: =IF(Employee!H$87=E$49,Employee!D$87+SUM(N53)+Aug!W63,SUM(N53)+Aug!W63) -> 0 | X53: =IF(O53=" ",Aug!X63,O53+Aug!X63) -> 0 | Y53: =IF(P53=" ",Aug!Y63,P53+Aug!Y63) -> 0 | Z53: =IF(Q53=" ",Aug!Z63,Q53+Aug!Z63) -> 0 | AA53: =IF(R53=" ",Aug!AA63,R53+Aug!AA63) -> 0 | AC53: =IF(T53=" ",Aug!AC63,T53+Aug!AC63) -> 0 | AD53: =IF(G53="SSP",H53,0) -> 0 | AE53: =IF(G53="SMP",H53,0) -> 0 | AF53: =IF(G53="SPP",H53,0) -> 0 | AG53: =IF(G53="SAP",H53,0) -> 0
B54: =IF(E54=" "," ",IF(Employee!F$102>E$49," ",IF(Employee!F$104<E$49," ",Employee!D$108))) | E54: =IF(Employee!D$106="w"," ",IF(Employee!F$102>E$49," ",IF(Employee!F$104<E$49," ",Employee!D$107))) | F54: =IF(E54=" "," ",IF(Employee!F$102>E$49," ",IF(Employee!F$104<E$49," ",Employee!D$93))) | H54: =IF(T$49="Y",Aug!H64,0) -> 0 | I54: =IF(T$49="Y",Aug!I64,0) -> 0 | J54: =IF(T$49="Y",Aug!J64,0) -> 0 | K54: =IF(T$49="Y",Aug!K64,I54*J54) -> 0 | L54: =IF(T$49="Y",Aug!L64,0) -> 0 | M54: =IF(E54=" "," ",IF(T$49="Y",Aug!M64,IF((H54+K54+L54)>0,H54+K54+L54," "))) | N54: 0 | O54: 0 | P54: 0 | Q54: 0 | R54: =IF(M54=" "," ",IF(M54=0," ",M54-SUM(N54:Q54))) | T54: 0 | V54: =IF(Employee!H$113=E$49,Employee!D$112+SUM(M54)+Aug!V64,SUM(M54)+Aug!V64) -> 0 | W54: =IF(Employee!H$113=E$49,Employee!D$113+SUM(N54)+Aug!W64,SUM(N54)+Aug!W64) -> 0 | X54: =IF(O54=" ",Aug!X64,O54+Aug!X64) -> 0 | Y54: =IF(P54=" ",Aug!Y64,P54+Aug!Y64) -> 0 | Z54: =IF(Q54=" ",Aug!Z64,Q54+Aug!Z64) -> 0 | AA54: =IF(R54=" ",Aug!AA64,R54+Aug!AA64) -> 0 | AC54: =IF(T54=" ",Aug!AC64,T54+Aug!AC64) -> 0 | AD54: =IF(G54="SSP",H54,0) -> 0 | AE54: =IF(G54="SMP",H54,0) -> 0 | AF54: =IF(G54="SPP",H54,0) -> 0 | AG54: =IF(G54="SAP",H54,0) -> 0
B55: =IF(E55=" "," ",IF(Employee!F$128>E$49," ",IF(Employee!F$130<E$49," ",Employee!D$134))) | E55: =IF(Employee!D$132="w"," ",IF(Employee!F$128>E$49," ",IF(Employee!F$130<E$49," ",Employee!D$133))) | F55: =IF(E55=" "," ",IF(Employee!F$128>E$49," ",IF(Employee!F$130<E$49," ",Employee!D$119))) | H55: =IF(T$49="Y",Aug!H65,0) -> 0 | I55: =IF(T$49="Y",Aug!I65,0) -> 0 | J55: =IF(T$49="Y",Aug!J65,0) -> 0 | K55: =IF(T$49="Y",Aug!K65,I55*J55) -> 0 | L55: =IF(T$49="Y",Aug!L65,0) -> 0 | M55: =IF(E55=" "," ",IF(T$49="Y",Aug!M65,IF((H55+K55+L55)>0,H55+K55+L55," "))) | N55: 0 | O55: 0 | P55: 0 | Q55: 0 | R55: =IF(M55=" "," ",IF(M55=0," ",M55-SUM(N55:Q55))) | T55: 0 | V55: =IF(Employee!H$139=E$49,Employee!D$138+SUM(M55)+Aug!V65,SUM(M55)+Aug!V65) -> 0 | W55: =IF(Employee!H$139=E$49,Employee!D$139+SUM(N55)+Aug!W65,SUM(N55)+Aug!W65) -> 0 | X55: =IF(O55=" ",Aug!X65,O55+Aug!X65) -> 0 | Y55: =IF(P55=" ",Aug!Y65,P55+Aug!Y65) -> 0 | Z55: =IF(Q55=" ",Aug!Z65,Q55+Aug!Z65) -> 0 | AA55: =IF(R55=" ",Aug!AA65,R55+Aug!AA65) -> 0 | AC55: =IF(T55=" ",Aug!AC65,T55+Aug!AC65) -> 0 | AD55: =IF(G55="SSP",H55,0) -> 0 | AE55: =IF(G55="SMP",H55,0) -> 0 | AF55: =IF(G55="SPP",H55,0) -> 0 | AG55: =IF(G55="SAP",H55,0) -> 0
F56: Payroll Total | M56: =SUM(M51:M55) -> 0 | N56: =SUM(N51:N55) -> 0 | O56: =SUM(O51:O55) -> 0 | P56: =SUM(P51:P55) -> 0 | Q56: =SUM(Q51:Q55) -> 0 | R56: =SUM(R51:R55) -> 0 | T56: =SUM(T51:T55) -> 0
AD58: =SUM(AD21:AD56) -> 0 | AE58: =SUM(AE21:AE56) -> 0 | AF58: =SUM(AF21:AF56) -> 0 | AG58: =SUM(AG21:AG56) -> 0
F59: Directors | M59: Directors Wages Limited Companies Only
F60: =IF(B51="D",Employee!D15," ") | M60: =IF(B51="D",M51," ") | N60: =IF(B51="D",N51," ") | O60: =IF(B51="D",O51," ") | P60: =IF(B51="D",P51," ") | Q60: =IF(B51="D",Q51," ") | R60: =IF(B51="D",R51," ") | T60: =IF(B51="D",T51," ") | AD60: =IF((AD58-(O1+T1)*0.13)>0,AD58-(Q1+T1)*0.13,0) -> 0 | AE60: =AE58 -> 0 | AF60: =AF58 -> 0 | AG60: =AG58 -> 0
F61: =IF(B52="D",Employee!D41," ") | M61: =IF(B52="D",M52," ") | N61: =IF(B52="D",N52," ") | O61: =IF(B52="D",O52," ") | P61: =IF(B52="D",P52," ") | Q61: =IF(B52="D",Q52," ") | R61: =IF(B52="D",R52," ") | T61: =IF(B52="D",T52," ")
F62: =IF(B53="D",Employee!D67," ") | M62: =IF(B53="D",M53," ") | N62: =IF(B53="D",N53," ") | O62: =IF(B53="D",O53," ") | P62: =IF(B53="D",P53," ") | Q62: =IF(B53="D",Q53," ") | R62: =IF(B53="D",R53," ") | T62: =IF(B53="D",T53," ") | AE62: =AE60*0.045 -> 0 | AF62: =AF60*0.045 -> 0 | AG62: =AG60*0.045 -> 0
F63: =IF(B54="D",Employee!D93," ") | M63: =IF(B54="D",M54," ") | N63: =IF(B54="D",N54," ") | O63: =IF(B54="D",O54," ") | P63: =IF(B54="D",P54," ") | Q63: =IF(B54="D",Q54," ") | R63: =IF(B54="D",R54," ") | T63: =IF(B54="D",T54," ")
F64: =IF(B55="D",Employee!D119," ") | M64: =IF(B55="D",M55," ") | N64: =IF(B55="D",N55," ") | O64: =IF(B55="D",O55," ") | P64: =IF(B55="D",P55," ") | Q64: =IF(B55="D",Q55," ") | R64: =IF(B55="D",R55," ") | T64: =IF(B55="D",T55," ")
F65: Director Totals | M65: =SUM(M60:M64) -> 0 | N65: =SUM(N60:N64) -> 0 | O65: =SUM(O60:O64) -> 0 | P65: =SUM(P60:P64) -> 0 | Q65: =SUM(Q60:Q64) -> 0 | R65: =SUM(R60:R64) -> 0 | T65: =SUM(T60:T64) -> 0 | AD65: =AD60+Aug!AD75 -> 0 | AE65: =AE60+Aug!AE75 -> 0 | AF65: =AF60+Aug!AF75 -> 0 | AG65: =AG60+Aug!AG75 -> 0
AE67: =AE62+Aug!AE77 -> 0 | AF67: =AF62+Aug!AF77 -> 0 | AG67: =AG62+Aug!AG77 -> 0

Sheet Oct
B1: www.diyaccounting.co.uk | G1: =SUM(AD60:AG60)+SUM(AE62:AG62) -> 0 | I1: Monthly Totals | M1: =M16+M26+M36+M46+M56 -> 0 | N1: =N16+N26+N36+N46+N56 -> 0 | O1: =O16+O26+O36+O46+O56 -> 0 | P1: =P16+P26+P36+P46+P56 -> 0 | Q1: =Q16+Q26+Q36+Q46+Q56 -> 0 | R1: =R16+R26+R36+R46+R56 -> 0 | T1: =T16+T26+T36+T46+T56 -> 0 | V1: YEAR TO DATE | AD1: Statutory Payments & NIC Recovered
I2: Sub Totals Directors | M2: =M65 -> 0 | N2: =N65 -> 0 | O2: =O65 -> 0 | P2: =P65 -> 0 | Q2: =Q65 -> 0 | R2: =R65 -> 0 | S2: =S65 -> 0 | T2: =T65 -> 0
B3: Dir Ref | C3: NIC Table | D3: Tax Code | E3: Pay No | F3: Employee Name | G3: SSP | H3: =Jun!H3:H6 -> Statutory Pay | I3: =Jun!I3:I6 -> Basic hours | J3: =Jun!J3:J6 -> Hourly rate | K3: =Jun!K3:K6 -> Basic wages | L3: =Jun!L3:L6 -> Overtime Bonus Gratuities | M3: =Jun!M3:M6 -> GROSS WAGES | N3: =Jun!N3:N6 -> Income Tax | O3: =Jun!O3:O6 -> Employees National Insurance | ... R3: =Jun!R3:R6 -> NET PAY | T3: =Jun!T3:T6 -> Employers National Insurance | V3: Gross Wages | W3: Income Tax | X3: Employees National Insurance | Y3: Student Loan deductions | Z3: Other Deductions | AA3: Net Pay | AC3: Employers National Insurance | AD3: Statutory Sick Pay Recovered | AE3: Statutory Maternity Pay Recovered | AF3: Statutory Paternity Pay Recovered | AG3: Statutory Adoption Pay Recovered
G4: SMP
G5: SPP
G6: SAP
B8: WEEKLY PAYROLL | O8: Date Wages paid
B9: Week number | E9: 18 | H9: Date Wages paid | K9: =Admin!B119 -> 45870 | L9: - | M9: =K9+6 -> 45876 | O9: One Click to repeat previous week Enter Y
B11: =IF(E11=" "," ",IF(Employee!F$24>E$9," ",IF(Employee!F$26<E$9," ",Employee!D$30))) | E11: =IF(Employee!D$28="m"," ",IF(Employee!F$24>E$9," ",IF(Employee!F$26<E$9," ",Employee!D$29))) | F11: =IF(E11=" "," ",IF(Employee!F$24>E$9," ",IF(Employee!F$26<E$9," ",Employee!D$15))) | H11: =IF(T$9="Y",Sep!H41,0) -> 0 | I11: =IF(T$9="Y",Sep!I41,0) -> 0 | J11: =IF(T$9="Y",Sep!J41,0) -> 0 | K11: 0 | L11: =IF(T$9="Y",Sep!L41,0) -> 0 | M11: =IF(E11=" "," ",IF(T$9="Y",Sep!M41,IF((H11+K11+L11)>0,H11+K11+L11," "))) | N11: 0 | O11: 0 | P11: 0 | Q11: 0 | R11: =IF(M11=" "," ",IF(M11=0," ",M11-SUM(N11:Q11))) | T11: 0 | V11: =IF(Employee!H$34=E$9,Employee!D$34+SUM(M11)+Sep!V41,SUM(M11)+Sep!V41) -> 0 | W11: =IF(Employee!H$34=E$9,Employee!D$35+SUM(N11)+Sep!W41,SUM(N11)+Sep!W41) -> 0 | X11: =IF(O11=" ",Sep!X41,O11+Sep!X41) -> 0 | Y11: =IF(P11=" ",Sep!Y41,P11+Sep!Y41) -> 0 | Z11: =IF(Q11=" ",Sep!Z41,Q11+Sep!Z41) -> 0 | AA11: =IF(R11=" ",Sep!AA41,R11+Sep!AA41) -> 0 | AC11: =IF(T11=" ",Sep!AC41,T11+Sep!AC41) -> 0 | AD11: =IF(G11="SSP",H11,0) -> 0 | AE11: =IF(G11="SMP",H11,0) -> 0 | AF11: =IF(G11="SPP",H11,0) -> 0 | AG11: =IF(G11="SAP",H11,0) -> 0
B12: =IF(E12=" "," ",IF(Employee!F$50>E$9," ",IF(Employee!F$52<E$9," ",Employee!D$56))) | E12: =IF(Employee!D$54="m"," ",IF(Employee!F$50>E$9," ",IF(Employee!F$52<E$9," ",Employee!D$55))) | F12: =IF(E12=" "," ",IF(Employee!F$50>E$9," ",IF(Employee!F$52<E$9," ",Employee!D$41))) | H12: =IF(T$9="Y",Sep!H41,0) -> 0 | I12: =IF(T$9="Y",Sep!I41,0) -> 0 | J12: =IF(T$9="Y",Sep!J41,0) -> 0 | K12: =IF(T$9="Y",Sep!K41,I12*J12) -> 0 | L12: =IF(T$9="Y",Sep!L41,0) -> 0 | M12: =IF(E12=" "," ",IF(T$9="Y",Sep!M41,IF((H12+K12+L12)>0,H12+K12+L12," "))) | N12: 0 | O12: 0 | P12: 0 | Q12: 0 | R12: =IF(M12=" "," ",IF(M12=0," ",M12-SUM(N12:Q12))) | T12: 0 | V12: =IF(Employee!H$60=E$9,Employee!D$60+SUM(M12)+Sep!V42,SUM(M12)+Sep!V42) -> 0 | W12: =IF(Employee!H$60=E$9,Employee!D$61+SUM(N12)+Sep!W42,SUM(N12)+Sep!W42) -> 0 | X12: =IF(O12=" ",Sep!X42,O12+Sep!X42) -> 0 | Y12: =IF(P12=" ",Sep!Y42,P12+Sep!Y42) -> 0 | Z12: =IF(Q12=" ",Sep!Z42,Q12+Sep!Z42) -> 0 | AA12: =IF(R12=" ",Sep!AA42,R12+Sep!AA42) -> 0 | AC12: =IF(T12=" ",Sep!AC42,T12+Sep!AC42) -> 0 | AD12: =IF(G12="SSP",H12,0) -> 0 | AE12: =IF(G12="SMP",H12,0) -> 0 | AF12: =IF(G12="SPP",H12,0) -> 0 | AG12: =IF(G12="SAP",H12,0) -> 0
B13: =IF(E13=" "," ",IF(Employee!F$76>E$9," ",IF(Employee!F$78<E$9," ",Employee!D$82))) | E13: =IF(Employee!D$80="m"," ",IF(Employee!F$76>E$9," ",IF(Employee!F$78<E$9," ",Employee!D$81))) | F13: =IF(E13=" "," ",IF(Employee!F$76>E$9," ",IF(Employee!F$78<E$9," ",Employee!D$67))) | H13: =IF(T$9="Y",Sep!H41,0) -> 0 | I13: =IF(T$9="Y",Sep!I41,0) -> 0 | J13: =IF(T$9="Y",Sep!J41,0) -> 0 | K13: =IF(T$9="Y",Sep!K41,I13*J13) -> 0 | L13: =IF(T$9="Y",Sep!L41,0) -> 0 | M13: =IF(E13=" "," ",IF(T$9="Y",Sep!M41,IF((H13+K13+L13)>0,H13+K13+L13," "))) | N13: 0 | O13: 0 | P13: 0 | Q13: 0 | R13: =IF(M13=" "," ",IF(M13=0," ",M13-SUM(N13:Q13))) | T13: 0 | V13: =IF(Employee!H$86=E$9,Employee!D$86+SUM(M13)+Sep!V43,SUM(M13)+Sep!V43) -> 0 | W13: =IF(Employee!H$86=E$9,Employee!D$87+SUM(N13)+Sep!W43,SUM(N13)+Sep!W43) -> 0 | X13: =IF(O13=" ",Sep!X43,O13+Sep!X43) -> 0 | Y13: =IF(P13=" ",Sep!Y43,P13+Sep!Y43) -> 0 | Z13: =IF(Q13=" ",Sep!Z43,Q13+Sep!Z43) -> 0 | AA13: =IF(R13=" ",Sep!AA43,R13+Sep!AA43) -> 0 | AC13: =IF(T13=" ",Sep!AC43,T13+Sep!AC43) -> 0 | AD13: =IF(G13="SSP",H13,0) -> 0 | AE13: =IF(G13="SMP",H13,0) -> 0 | AF13: =IF(G13="SPP",H13,0) -> 0 | AG13: =IF(G13="SAP",H13,0) -> 0
B14: =IF(E14=" "," ",IF(Employee!F$102>E$9," ",IF(Employee!F$104<E$9," ",Employee!D$108))) | E14: =IF(Employee!D$106="m"," ",IF(Employee!F$102>E$9," ",IF(Employee!F$104<E$9," ",Employee!D$107))) | F14: =IF(E14=" "," ",IF(Employee!F$102>E$9," ",IF(Employee!F$104<E$9," ",Employee!D$93))) | H14: =IF(T$9="Y",Sep!H41,0) -> 0 | I14: =IF(T$9="Y",Sep!I41,0) -> 0 | J14: =IF(T$9="Y",Sep!J41,0) -> 0 | K14: =IF(T$9="Y",Sep!K41,I14*J14) -> 0 | L14: =IF(T$9="Y",Sep!L41,0) -> 0 | M14: =IF(E14=" "," ",IF(T$9="Y",Sep!M41,IF((H14+K14+L14)>0,H14+K14+L14," "))) | N14: 0 | O14: 0 | P14: 0 | Q14: 0 | R14: =IF(M14=" "," ",IF(M14=0," ",M14-SUM(N14:Q14))) | T14: 0 | V14: =IF(Employee!H$112=E$9,Employee!D$112+SUM(M14)+Sep!V44,SUM(M14)+Sep!V44) -> 0 | W14: =IF(Employee!H$112=E$9,Employee!D$113+SUM(N14)+Sep!W44,SUM(N14)+Sep!W44) -> 0 | X14: =IF(O14=" ",Sep!X44,O14+Sep!X44) -> 0 | Y14: =IF(P14=" ",Sep!Y44,P14+Sep!Y44) -> 0 | Z14: =IF(Q14=" ",Sep!Z44,Q14+Sep!Z44) -> 0 | AA14: =IF(R14=" ",Sep!AA44,R14+Sep!AA44) -> 0 | AC14: =IF(T14=" ",Sep!AC44,T14+Sep!AC44) -> 0 | AD14: =IF(G14="SSP",H14,0) -> 0 | AE14: =IF(G14="SMP",H14,0) -> 0 | AF14: =IF(G14="SPP",H14,0) -> 0 | AG14: =IF(G14="SAP",H14,0) -> 0
B15: =IF(E15=" "," ",IF(Employee!F$128>E$9," ",IF(Employee!F$130<E$9," ",Employee!D$134))) | E15: =IF(Employee!D$132="m"," ",IF(Employee!F$128>E$9," ",IF(Employee!F$130<E$9," ",Employee!D$133))) | F15: =IF(E15=" "," ",IF(Employee!F$128>E$9," ",IF(Employee!F$130<E$9," ",Employee!D$119))) | H15: =IF(T$9="Y",Sep!H41,0) -> 0 | I15: =IF(T$9="Y",Sep!I41,0) -> 0 | J15: =IF(T$9="Y",Sep!J41,0) -> 0 | K15: =IF(T$9="Y",Sep!K41,I15*J15) -> 0 | L15: =IF(T$9="Y",Sep!L41,0) -> 0 | M15: =IF(E15=" "," ",IF(T$9="Y",Sep!M41,IF((H15+K15+L15)>0,H15+K15+L15," "))) | N15: 0 | O15: 0 | P15: 0 | Q15: 0 | R15: =IF(M15=" "," ",IF(M15=0," ",M15-SUM(N15:Q15))) | T15: 0 | V15: =IF(Employee!H$138=E$9,Employee!D$138+SUM(M15)+Sep!V45,SUM(M15)+Sep!V45) -> 0 | W15: =IF(Employee!H$138=E$9,Employee!D$139+SUM(N15)+Sep!W45,SUM(N15)+Sep!W45) -> 0 | X15: =IF(O15=" ",Sep!X45,O15+Sep!X45) -> 0 | Y15: =IF(P15=" ",Sep!Y45,P15+Sep!Y45) -> 0 | Z15: =IF(Q15=" ",Sep!Z45,Q15+Sep!Z45) -> 0 | AA15: =IF(R15=" ",Sep!AA45,R15+Sep!AA45) -> 0 | AC15: =IF(T15=" ",Sep!AC45,T15+Sep!AC45) -> 0 | AD15: =IF(G15="SSP",H15,0) -> 0 | AE15: =IF(G15="SMP",H15,0) -> 0 | AF15: =IF(G15="SPP",H15,0) -> 0 | AG15: =IF(G15="SAP",H15,0) -> 0
F16: Payroll Total | M16: =SUM(M11:M15) -> 0 | N16: =SUM(N11:N15) -> 0 | O16: =SUM(O11:O15) -> 0 | P16: =SUM(P11:P15) -> 0 | Q16: =SUM(Q11:Q15) -> 0 | R16: =SUM(R11:R15) -> 0 | T16: =SUM(T11:T15) -> 0
B18: WEEKLY PAYROLL | O18: Date Wages paid
B19: Week number | E19: 19 | H19: Date Wages paid | K19: =M9+1 -> 45877 | L19: - | M19: =K19+6 -> 45883 | O19: One Click to repeat previous week Enter Y
B21: =IF(E21=" "," ",IF(Employee!F$24>E$19," ",IF(Employee!F$26<E$19," ",Employee!D$30))) | E21: =IF(Employee!D$28="m"," ",IF(Employee!F$24>E$19," ",IF(Employee!F$26<E$19," ",Employee!D$29))) | F21: =IF(E21=" "," ",IF(Employee!F$24>E$19," ",IF(Employee!F$26<E$19," ",Employee!D$15))) | H21: =IF(T$19="Y",H11,0) -> 0 | I21: =IF(T$19="Y",I11,0) -> 0 | J21: =IF(T$19="Y",J11,0) -> 0 | K21: =IF(T$19="Y",K11,I21*J21) -> 0 | L21: =IF(T$19="Y",L11,0) -> 0 | M21: =IF(E21=" "," ",IF(T$19="Y",M11,IF((H21+K21+L21)>0,H21+K21+L21," "))) | N21: 0 | O21: 0 | P21: 0 | Q21: 0 | R21: =IF(M21=" "," ",IF(M21=0," ",M21-SUM(N21:Q21))) | T21: 0 | V21: =IF(Employee!H$34=E$19,Employee!D$34+SUM(M21)+V11,SUM(M21)+V11) -> 0 | W21: =IF(Employee!H$34=E$19,Employee!D$35+SUM(N21)+W11,SUM(N21)+W11) -> 0 | X21: =IF(O21=" ",X11,O21+X11) -> 0 | Y21: =IF(P21=0,Y11,P21+Y11) -> 0 | Z21: =IF(Q21=0,Z11,Q21+Z11) -> 0 | AA21: =IF(R21=" ",AA11,AA11+R21) -> 0 | AC21: =IF(T21=" ",AC11,T21+AC11) -> 0 | AD21: =IF(G21="SSP",H21,0) -> 0 | AE21: =IF(G21="SMP",H21,0) -> 0 | AF21: =IF(G21="SPP",H21,0) -> 0 | AG21: =IF(G21="SAP",H21,0) -> 0
B22: =IF(E22=" "," ",IF(Employee!F$50>E$19," ",IF(Employee!F$52<E$19," ",Employee!D$56))) | E22: =IF(Employee!D$54="m"," ",IF(Employee!F$50>E$19," ",IF(Employee!F$52<E$19," ",Employee!D$55))) | F22: =IF(E22=" "," ",IF(Employee!F$50>E$19," ",IF(Employee!F$52<E$19," ",Employee!D$41))) | H22: =IF(T$19="Y",H12,0) -> 0 | I22: =IF(T$19="Y",I12,0) -> 0 | J22: =IF(T$19="Y",J12,0) -> 0 | K22: =IF(T$19="Y",K12,I22*J22) -> 0 | L22: =IF(T$19="Y",L12,0) -> 0 | M22: =IF(E22=" "," ",IF(T$19="Y",M12,IF((H22+K22+L22)>0,H22+K22+L22," "))) | N22: 0 | O22: 0 | P22: 0 | Q22: 0 | R22: =IF(M22=" "," ",IF(M22=0," ",M22-SUM(N22:Q22))) | T22: 0 | V22: =IF(Employee!H$60=E$19,Employee!D$60+SUM(M22)+V12,SUM(M22)+V12) -> 0 | W22: =IF(Employee!H$60=E$19,Employee!D$61+SUM(N22)+W12,SUM(N22)+W12) -> 0 | X22: =IF(O22=" ",X12,O22+X12) -> 0 | Y22: =IF(P22=0,Y12,P22+Y12) -> 0 | Z22: =IF(Q22=0,Z12,Q22+Z12) -> 0 | AA22: =IF(R22=" ",AA12,AA12+R22) -> 0 | AC22: =IF(T22=" ",AC12,T22+AC12) -> 0 | AD22: =IF(G22="SSP",H22,0) -> 0 | AE22: =IF(G22="SMP",H22,0) -> 0 | AF22: =IF(G22="SPP",H22,0) -> 0 | AG22: =IF(G22="SAP",H22,0) -> 0
B23: =IF(E23=" "," ",IF(Employee!F$76>E$19," ",IF(Employee!F$78<E$19," ",Employee!D$82))) | E23: =IF(Employee!D$80="m"," ",IF(Employee!F$76>E$19," ",IF(Employee!F$78<E$19," ",Employee!D$81))) | F23: =IF(E23=" "," ",IF(Employee!F$76>E$19," ",IF(Employee!F$78<E$19," ",Employee!D$67))) | H23: =IF(T$19="Y",H13,0) -> 0 | I23: =IF(T$19="Y",I13,0) -> 0 | J23: =IF(T$19="Y",J13,0) -> 0 | K23: =IF(T$19="Y",K13,I23*J23) -> 0 | L23: =IF(T$19="Y",L13,0) -> 0 | M23: =IF(E23=" "," ",IF(T$19="Y",M13,IF((H23+K23+L23)>0,H23+K23+L23," "))) | N23: 0 | O23: 0 | P23: 0 | Q23: 0 | R23: =IF(M23=" "," ",IF(M23=0," ",M23-SUM(N23:Q23))) | T23: 0 | V23: =IF(Employee!H$86=E$19,Employee!D$86+SUM(M23)+V13,SUM(M23)+V13) -> 0 | W23: =IF(Employee!H$86=E$19,Employee!D$87+SUM(N23)+W13,SUM(N23)+W13) -> 0 | X23: =IF(O23=" ",X13,O23+X13) -> 0 | Y23: =IF(P23=0,Y13,P23+Y13) -> 0 | Z23: =IF(Q23=0,Z13,Q23+Z13) -> 0 | AA23: =IF(R23=" ",AA13,AA13+R23) -> 0 | AC23: =IF(T23=" ",AC13,T23+AC13) -> 0 | AD23: =IF(G23="SSP",H23,0) -> 0 | AE23: =IF(G23="SMP",H23,0) -> 0 | AF23: =IF(G23="SPP",H23,0) -> 0 | AG23: =IF(G23="SAP",H23,0) -> 0
B24: =IF(E24=" "," ",IF(Employee!F$102>E$19," ",IF(Employee!F$104<E$19," ",Employee!D$108))) | E24: =IF(Employee!D$106="m"," ",IF(Employee!F$102>E$19," ",IF(Employee!F$104<E$19," ",Employee!D$107))) | F24: =IF(E24=" "," ",IF(Employee!F$102>E$19," ",IF(Employee!F$104<E$19," ",Employee!D$93))) | H24: =IF(T$19="Y",H14,0) -> 0 | I24: =IF(T$19="Y",I14,0) -> 0 | J24: =IF(T$19="Y",J14,0) -> 0 | K24: =IF(T$19="Y",K14,I24*J24) -> 0 | L24: =IF(T$19="Y",L14,0) -> 0 | M24: =IF(E24=" "," ",IF(T$19="Y",M14,IF((H24+K24+L24)>0,H24+K24+L24," "))) | N24: 0 | O24: 0 | P24: 0 | Q24: 0 | R24: =IF(M24=" "," ",IF(M24=0," ",M24-SUM(N24:Q24))) | T24: 0 | V24: =IF(Employee!H$112=E$19,Employee!D$112+SUM(M24)+V14,SUM(M24)+V14) -> 0 | W24: =IF(Employee!H$112=E$19,Employee!D$113+SUM(N24)+W14,SUM(N24)+W14) -> 0 | X24: =IF(O24=" ",X14,O24+X14) -> 0 | Y24: =IF(P24=0,Y14,P24+Y14) -> 0 | Z24: =IF(Q24=0,Z14,Q24+Z14) -> 0 | AA24: =IF(R24=" ",AA14,AA14+R24) -> 0 | AC24: =IF(T24=" ",AC14,T24+AC14) -> 0 | AD24: =IF(G24="SSP",H24,0) -> 0 | AE24: =IF(G24="SMP",H24,0) -> 0 | AF24: =IF(G24="SPP",H24,0) -> 0 | AG24: =IF(G24="SAP",H24,0) -> 0
B25: =IF(E25=" "," ",IF(Employee!F$128>E$19," ",IF(Employee!F$130<E$19," ",Employee!D$134))) | E25: =IF(Employee!D$132="m"," ",IF(Employee!F$128>E$19," ",IF(Employee!F$130<E$19," ",Employee!D$133))) | F25: =IF(E25=" "," ",IF(Employee!F$128>E$19," ",IF(Employee!F$130<E$19," ",Employee!D$119))) | H25: =IF(T$19="Y",H15,0) -> 0 | I25: =IF(T$19="Y",I15,0) -> 0 | J25: =IF(T$19="Y",J15,0) -> 0 | K25: =IF(T$19="Y",K15,I25*J25) -> 0 | L25: =IF(T$19="Y",L15,0) -> 0 | M25: =IF(E25=" "," ",IF(T$19="Y",M15,IF((H25+K25+L25)>0,H25+K25+L25," "))) | N25: 0 | O25: 0 | P25: 0 | Q25: 0 | R25: =IF(M25=" "," ",IF(M25=0," ",M25-SUM(N25:Q25))) | T25: 0 | V25: =IF(Employee!H$138=E$19,Employee!D$138+SUM(M25)+V15,SUM(M25)+V15) -> 0 | W25: =IF(Employee!H$138=E$19,Employee!D$139+SUM(N25)+W15,SUM(N25)+W15) -> 0 | X25: =IF(O25=" ",X15,O25+X15) -> 0 | Y25: =IF(P25=0,Y15,P25+Y15) -> 0 | Z25: =IF(Q25=0,Z15,Q25+Z15) -> 0 | AA25: =IF(R25=" ",AA15,AA15+R25) -> 0 | AC25: =IF(T25=" ",AC15,T25+AC15) -> 0 | AD25: =IF(G25="SSP",H25,0) -> 0 | AE25: =IF(G25="SMP",H25,0) -> 0 | AF25: =IF(G25="SPP",H25,0) -> 0 | AG25: =IF(G25="SAP",H25,0) -> 0
F26: Payroll Total | M26: =SUM(M21:M25) -> 0 | N26: =SUM(N21:N25) -> 0 | O26: =SUM(O21:O25) -> 0 | P26: =SUM(P21:P25) -> 0 | Q26: =SUM(Q21:Q25) -> 0 | R26: =SUM(R21:R25) -> 0 | T26: =SUM(T21:T25) -> 0
B28: WEEKLY PAYROLL | O28: Date Wages paid
B29: Week number | E29: 20 | H29: Date Wages paid | K29: =M19+1 -> 45884 | L29: - | M29: =K29+6 -> 45890 | O29: One Click to repeat previous week Enter Y
B31: =IF(E31=" "," ",IF(Employee!F$24>E$29," ",IF(Employee!F$26<E$29," ",Employee!D$30))) | E31: =IF(Employee!D$28="m"," ",IF(Employee!F$24>E$29," ",IF(Employee!F$26<E$29," ",Employee!D$29))) | F31: =IF(E31=" "," ",IF(Employee!F$24>E$29," ",IF(Employee!F$26<E$29," ",Employee!D$15))) | H31: =IF(T$29="Y",H21,0) -> 0 | I31: =IF(T$29="Y",I21,0) -> 0 | J31: =IF(T$29="Y",J21,0) -> 0 | K31: =IF(T$29="Y",K21,I31*J31) -> 0 | L31: =IF(T$29="Y",L21,0) -> 0 | M31: =IF(E31=" "," ",IF(T$29="Y",M21,IF((H31+K31+L31)>0,H31+K31+L31," "))) | N31: 0 | O31: 0 | P31: 0 | Q31: 0 | R31: =IF(M31=" "," ",IF(M31=0," ",M31-SUM(N31:Q31))) | T31: 0 | V31: =IF(Employee!H$34=E$29,Employee!D$34+SUM(M31)+V21,SUM(M31)+V21) -> 0 | W31: =IF(Employee!H$34=E$29,Employee!D$35+SUM(N31)+W21,SUM(N31)+W21) -> 0 | X31: =IF(O31=" ",X21,O31+X21) -> 0 | Y31: =IF(P31=0,Y21,P31+Y21) -> 0 | Z31: =IF(Q31=0,Z21,Q31+Z21) -> 0 | AA31: =IF(R31=" ",AA21,AA21+R31) -> 0 | AC31: =IF(T31=" ",AC21,T31+AC21) -> 0 | AD31: =IF(G31="SSP",H31,0) -> 0 | AE31: =IF(G31="SMP",H31,0) -> 0 | AF31: =IF(G31="SPP",H31,0) -> 0 | AG31: =IF(G31="SAP",H31,0) -> 0
B32: =IF(E32=" "," ",IF(Employee!F$50>E$29," ",IF(Employee!F$52<E$29," ",Employee!D$56))) | E32: =IF(Employee!D$54="m"," ",IF(Employee!F$50>E$29," ",IF(Employee!F$52<E$29," ",Employee!D$55))) | F32: =IF(E32=" "," ",IF(Employee!F$50>E$29," ",IF(Employee!F$52<E$29," ",Employee!D$41))) | H32: =IF(T$29="Y",H22,0) -> 0 | I32: =IF(T$29="Y",I22,0) -> 0 | J32: =IF(T$29="Y",J22,0) -> 0 | K32: =IF(T$29="Y",K22,I32*J32) -> 0 | L32: =IF(T$29="Y",L22,0) -> 0 | M32: =IF(E32=" "," ",IF(T$29="Y",M22,IF((H32+K32+L32)>0,H32+K32+L32," "))) | N32: 0 | O32: 0 | P32: 0 | Q32: 0 | R32: =IF(M32=" "," ",IF(M32=0," ",M32-SUM(N32:Q32))) | T32: 0 | V32: =IF(Employee!H$60=E$29,Employee!D$60+SUM(M32)+V22,SUM(M32)+V22) -> 0 | W32: =IF(Employee!H$60=E$29,Employee!D$61+SUM(N32)+W22,SUM(N32)+W22) -> 0 | X32: =IF(O32=" ",X22,O32+X22) -> 0 | Y32: =IF(P32=0,Y22,P32+Y22) -> 0 | Z32: =IF(Q32=0,Z22,Q32+Z22) -> 0 | AA32: =IF(R32=" ",AA22,AA22+R32) -> 0 | AC32: =IF(T32=" ",AC22,T32+AC22) -> 0 | AD32: =IF(G32="SSP",H32,0) -> 0 | AE32: =IF(G32="SMP",H32,0) -> 0 | AF32: =IF(G32="SPP",H32,0) -> 0 | AG32: =IF(G32="SAP",H32,0) -> 0
B33: =IF(E33=" "," ",IF(Employee!F$76>E$29," ",IF(Employee!F$78<E$29," ",Employee!D$82))) | E33: =IF(Employee!D$80="m"," ",IF(Employee!F$76>E$29," ",IF(Employee!F$78<E$29," ",Employee!D$81))) | F33: =IF(E33=" "," ",IF(Employee!F$76>E$29," ",IF(Employee!F$78<E$29," ",Employee!D$67))) | H33: =IF(T$29="Y",H23,0) -> 0 | I33: =IF(T$29="Y",I23,0) -> 0 | J33: =IF(T$29="Y",J23,0) -> 0 | K33: =IF(T$29="Y",K23,I33*J33) -> 0 | L33: =IF(T$29="Y",L23,0) -> 0 | M33: =IF(E33=" "," ",IF(T$29="Y",M23,IF((H33+K33+L33)>0,H33+K33+L33," "))) | N33: 0 | O33: 0 | P33: 0 | Q33: 0 | R33: =IF(M33=" "," ",IF(M33=0," ",M33-SUM(N33:Q33))) | T33: 0 | V33: =IF(Employee!H$86=E$29,Employee!D$86+SUM(M33)+V23,SUM(M33)+V23) -> 0 | W33: =IF(Employee!H$86=E$29,Employee!D$87+SUM(N33)+W23,SUM(N33)+W23) -> 0 | X33: =IF(O33=" ",X23,O33+X23) -> 0 | Y33: =IF(P33=0,Y23,P33+Y23) -> 0 | Z33: =IF(Q33=0,Z23,Q33+Z23) -> 0 | AA33: =IF(R33=" ",AA23,AA23+R33) -> 0 | AC33: =IF(T33=" ",AC23,T33+AC23) -> 0 | AD33: =IF(G33="SSP",H33,0) -> 0 | AE33: =IF(G33="SMP",H33,0) -> 0 | AF33: =IF(G33="SPP",H33,0) -> 0 | AG33: =IF(G33="SAP",H33,0) -> 0
B34: =IF(E34=" "," ",IF(Employee!F$102>E$29," ",IF(Employee!F$104<E$29," ",Employee!D$108))) | E34: =IF(Employee!D$106="m"," ",IF(Employee!F$102>E$29," ",IF(Employee!F$104<E$29," ",Employee!D$107))) | F34: =IF(E34=" "," ",IF(Employee!F$102>E$29," ",IF(Employee!F$104<E$29," ",Employee!D$93))) | H34: =IF(T$29="Y",H24,0) -> 0 | I34: =IF(T$29="Y",I24,0) -> 0 | J34: =IF(T$29="Y",J24,0) -> 0 | K34: =IF(T$29="Y",K24,I34*J34) -> 0 | L34: =IF(T$29="Y",L24,0) -> 0 | M34: =IF(E34=" "," ",IF(T$29="Y",M24,IF((H34+K34+L34)>0,H34+K34+L34," "))) | N34: 0 | O34: 0 | P34: 0 | Q34: 0 | R34: =IF(M34=" "," ",IF(M34=0," ",M34-SUM(N34:Q34))) | T34: 0 | V34: =IF(Employee!H$112=E$29,Employee!D$112+SUM(M34)+V24,SUM(M34)+V24) -> 0 | W34: =IF(Employee!H$112=E$29,Employee!D$113+SUM(N34)+W24,SUM(N34)+W24) -> 0 | X34: =IF(O34=" ",X24,O34+X24) -> 0 | Y34: =IF(P34=0,Y24,P34+Y24) -> 0 | Z34: =IF(Q34=0,Z24,Q34+Z24) -> 0 | AA34: =IF(R34=" ",AA24,AA24+R34) -> 0 | AC34: =IF(T34=" ",AC24,T34+AC24) -> 0 | AD34: =IF(G34="SSP",H34,0) -> 0 | AE34: =IF(G34="SMP",H34,0) -> 0 | AF34: =IF(G34="SPP",H34,0) -> 0 | AG34: =IF(G34="SAP",H34,0) -> 0
B35: =IF(E35=" "," ",IF(Employee!F$128>E$29," ",IF(Employee!F$130<E$29," ",Employee!D$134))) | E35: =IF(Employee!D$132="m"," ",IF(Employee!F$128>E$29," ",IF(Employee!F$130<E$29," ",Employee!D$133))) | F35: =IF(E35=" "," ",IF(Employee!F$128>E$29," ",IF(Employee!F$130<E$29," ",Employee!D$119))) | H35: =IF(T$29="Y",H25,0) -> 0 | I35: =IF(T$29="Y",I25,0) -> 0 | J35: =IF(T$29="Y",J25,0) -> 0 | K35: =IF(T$29="Y",K25,I35*J35) -> 0 | L35: =IF(T$29="Y",L25,0) -> 0 | M35: =IF(E35=" "," ",IF(T$29="Y",M25,IF((H35+K35+L35)>0,H35+K35+L35," "))) | N35: 0 | O35: 0 | P35: 0 | Q35: 0 | R35: =IF(M35=" "," ",IF(M35=0," ",M35-SUM(N35:Q35))) | T35: 0 | V35: =IF(Employee!H$138=E$29,Employee!D$138+SUM(M35)+V25,SUM(M35)+V25) -> 0 | W35: =IF(Employee!H$138=E$29,Employee!D$139+SUM(N35)+W25,SUM(N35)+W25) -> 0 | X35: =IF(O35=" ",X25,O35+X25) -> 0 | Y35: =IF(P35=0,Y25,P35+Y25) -> 0 | Z35: =IF(Q35=0,Z25,Q35+Z25) -> 0 | AA35: =IF(R35=" ",AA25,AA25+R35) -> 0 | AC35: =IF(T35=" ",AC25,T35+AC25) -> 0 | AD35: =IF(G35="SSP",H35,0) -> 0 | AE35: =IF(G35="SMP",H35,0) -> 0 | AF35: =IF(G35="SPP",H35,0) -> 0 | AG35: =IF(G35="SAP",H35,0) -> 0
F36: Payroll Total | M36: =SUM(M31:M35) -> 0 | N36: =SUM(N31:N35) -> 0 | O36: =SUM(O31:O35) -> 0 | P36: =SUM(P31:P35) -> 0 | Q36: =SUM(Q31:Q35) -> 0 | R36: =SUM(R31:R35) -> 0 | T36: =SUM(T31:T35) -> 0
B38: WEEKLY PAYROLL | O38: Date Wages paid
B39: Week number | E39: 21 | H39: Date Wages paid | K39: =M29+1 -> 45891 | L39: - | M39: =K39+6 -> 45897 | O39: One Click to repeat previous week Enter Y
B41: =IF(E41=" "," ",IF(Employee!F$24>E$39," ",IF(Employee!F$26<E$39," ",Employee!D$30))) | E41: =IF(Employee!D$28="m"," ",IF(Employee!F$24>E$39," ",IF(Employee!F$26<E$39," ",Employee!D$29))) | F41: =IF(E41=" "," ",IF(Employee!F$24>E$39," ",IF(Employee!F$26<E$39," ",Employee!D$15))) | H41: =IF(T$39="Y",H31,0) -> 0 | I41: =IF(T$39="Y",I31,0) -> 0 | J41: =IF(T$39="Y",J31,0) -> 0 | K41: =IF(T$39="Y",K31,I41*J41) -> 0 | L41: =IF(T$39="Y",L31,0) -> 0 | M41: =IF(E41=" "," ",IF(T$39="Y",M31,IF((H41+K41+L41)>0,H41+K41+L41," "))) | N41: 0 | O41: 0 | P41: 0 | Q41: 0 | R41: =IF(M41=" "," ",IF(M41=0," ",M41-SUM(N41:Q41))) | T41: 0 | V41: =IF(Employee!H$34=E$39,Employee!D$34+SUM(M41)+V31,SUM(M41)+V31) -> 0 | W41: =IF(Employee!H$34=E$39,Employee!D$35+SUM(N41)+W31,SUM(N41)+W31) -> 0 | X41: =IF(O41=" ",X31,O41+X31) -> 0 | Y41: =IF(P41=0,Y31,P41+Y31) -> 0 | Z41: =IF(Q41=0,Z31,Q41+Z31) -> 0 | AA41: =IF(R41=" ",AA31,AA31+R41) -> 0 | AC41: =IF(T41=" ",AC31,T41+AC31) -> 0 | AD41: =IF(G41="SSP",H41,0) -> 0 | AE41: =IF(G41="SMP",H41,0) -> 0 | AF41: =IF(G41="SPP",H41,0) -> 0 | AG41: =IF(G41="SAP",H41,0) -> 0
B42: =IF(E42=" "," ",IF(Employee!F$50>E$39," ",IF(Employee!F$52<E$39," ",Employee!D$56))) | E42: =IF(Employee!D$54="m"," ",IF(Employee!F$50>E$39," ",IF(Employee!F$52<E$39," ",Employee!D$55))) | F42: =IF(E42=" "," ",IF(Employee!F$50>E$39," ",IF(Employee!F$52<E$39," ",Employee!D$41))) | H42: =IF(T$39="Y",H32,0) -> 0 | I42: =IF(T$39="Y",I32,0) -> 0 | J42: =IF(T$39="Y",J32,0) -> 0 | K42: =IF(T$39="Y",K32,I42*J42) -> 0 | L42: =IF(T$39="Y",L32,0) -> 0 | M42: =IF(E42=" "," ",IF(T$39="Y",M32,IF((H42+K42+L42)>0,H42+K42+L42," "))) | N42: 0 | O42: 0 | P42: 0 | Q42: 0 | R42: =IF(M42=" "," ",IF(M42=0," ",M42-SUM(N42:Q42))) | T42: 0 | V42: =IF(Employee!H$60=E$39,Employee!D$60+SUM(M42)+V32,SUM(M42)+V32) -> 0 | W42: =IF(Employee!H$60=E$39,Employee!D$61+SUM(N42)+W32,SUM(N42)+W32) -> 0 | X42: =IF(O42=" ",X32,O42+X32) -> 0 | Y42: =IF(P42=0,Y32,P42+Y32) -> 0 | Z42: =IF(Q42=0,Z32,Q42+Z32) -> 0 | AA42: =IF(R42=" ",AA32,AA32+R42) -> 0 | AC42: =IF(T42=" ",AC32,T42+AC32) -> 0 | AD42: =IF(G42="SSP",H42,0) -> 0 | AE42: =IF(G42="SMP",H42,0) -> 0 | AF42: =IF(G42="SPP",H42,0) -> 0 | AG42: =IF(G42="SAP",H42,0) -> 0
B43: =IF(E43=" "," ",IF(Employee!F$76>E$39," ",IF(Employee!F$78<E$39," ",Employee!D$82))) | E43: =IF(Employee!D$80="m"," ",IF(Employee!F$76>E$39," ",IF(Employee!F$78<E$39," ",Employee!D$81))) | F43: =IF(E43=" "," ",IF(Employee!F$76>E$39," ",IF(Employee!F$78<E$39," ",Employee!D$67))) | H43: =IF(T$39="Y",H33,0) -> 0 | I43: =IF(T$39="Y",I33,0) -> 0 | J43: =IF(T$39="Y",J33,0) -> 0 | K43: =IF(T$39="Y",K33,I43*J43) -> 0 | L43: =IF(T$39="Y",L33,0) -> 0 | M43: =IF(E43=" "," ",IF(T$39="Y",M33,IF((H43+K43+L43)>0,H43+K43+L43," "))) | N43: 0 | O43: 0 | P43: 0 | Q43: 0 | R43: =IF(M43=" "," ",IF(M43=0," ",M43-SUM(N43:Q43))) | T43: 0 | V43: =IF(Employee!H$86=E$39,Employee!D$86+SUM(M43)+V33,SUM(M43)+V33) -> 0 | W43: =IF(Employee!H$86=E$39,Employee!D$87+SUM(N43)+W33,SUM(N43)+W33) -> 0 | X43: =IF(O43=" ",X33,O43+X33) -> 0 | Y43: =IF(P43=0,Y33,P43+Y33) -> 0 | Z43: =IF(Q43=0,Z33,Q43+Z33) -> 0 | AA43: =IF(R43=" ",AA33,AA33+R43) -> 0 | AC43: =IF(T43=" ",AC33,T43+AC33) -> 0 | AD43: =IF(G43="SSP",H43,0) -> 0 | AE43: =IF(G43="SMP",H43,0) -> 0 | AF43: =IF(G43="SPP",H43,0) -> 0 | AG43: =IF(G43="SAP",H43,0) -> 0
B44: =IF(E44=" "," ",IF(Employee!F$102>E$39," ",IF(Employee!F$104<E$39," ",Employee!D$108))) | E44: =IF(Employee!D$106="m"," ",IF(Employee!F$102>E$39," ",IF(Employee!F$104<E$39," ",Employee!D$107))) | F44: =IF(E44=" "," ",IF(Employee!F$102>E$39," ",IF(Employee!F$104<E$39," ",Employee!D$93))) | H44: =IF(T$39="Y",H34,0) -> 0 | I44: =IF(T$39="Y",I34,0) -> 0 | J44: =IF(T$39="Y",J34,0) -> 0 | K44: =IF(T$39="Y",K34,I44*J44) -> 0 | L44: =IF(T$39="Y",L34,0) -> 0 | M44: =IF(E44=" "," ",IF(T$39="Y",M34,IF((H44+K44+L44)>0,H44+K44+L44," "))) | N44: 0 | O44: 0 | P44: 0 | Q44: 0 | R44: =IF(M44=" "," ",IF(M44=0," ",M44-SUM(N44:Q44))) | T44: 0 | V44: =IF(Employee!H$112=E$39,Employee!D$112+SUM(M44)+V34,SUM(M44)+V34) -> 0 | W44: =IF(Employee!H$112=E$39,Employee!D$113+SUM(N44)+W34,SUM(N44)+W34) -> 0 | X44: =IF(O44=" ",X34,O44+X34) -> 0 | Y44: =IF(P44=0,Y34,P44+Y34) -> 0 | Z44: =IF(Q44=0,Z34,Q44+Z34) -> 0 | AA44: =IF(R44=" ",AA34,AA34+R44) -> 0 | AC44: =IF(T44=" ",AC34,T44+AC34) -> 0 | AD44: =IF(G44="SSP",H44,0) -> 0 | AE44: =IF(G44="SMP",H44,0) -> 0 | AF44: =IF(G44="SPP",H44,0) -> 0 | AG44: =IF(G44="SAP",H44,0) -> 0
B45: =IF(E45=" "," ",IF(Employee!F$128>E$39," ",IF(Employee!F$130<E$39," ",Employee!D$134))) | E45: =IF(Employee!D$132="m"," ",IF(Employee!F$128>E$39," ",IF(Employee!F$130<E$39," ",Employee!D$133))) | F45: =IF(E45=" "," ",IF(Employee!F$128>E$39," ",IF(Employee!F$130<E$39," ",Employee!D$119))) | H45: =IF(T$39="Y",H35,0) -> 0 | I45: =IF(T$39="Y",I35,0) -> 0 | J45: =IF(T$39="Y",J35,0) -> 0 | K45: =IF(T$39="Y",K35,I45*J45) -> 0 | L45: =IF(T$39="Y",L35,0) -> 0 | M45: =IF(E45=" "," ",IF(T$39="Y",M35,IF((H45+K45+L45)>0,H45+K45+L45," "))) | N45: 0 | O45: 0 | P45: 0 | Q45: 0 | R45: =IF(M45=" "," ",IF(M45=0," ",M45-SUM(N45:Q45))) | T45: 0 | V45: =IF(Employee!H$138=E$39,Employee!D$138+SUM(M45)+V35,SUM(M45)+V35) -> 0 | W45: =IF(Employee!H$138=E$39,Employee!D$139+SUM(N45)+W35,SUM(N45)+W35) -> 0 | X45: =IF(O45=" ",X35,O45+X35) -> 0 | Y45: =IF(P45=0,Y35,P45+Y35) -> 0 | Z45: =IF(Q45=0,Z35,Q45+Z35) -> 0 | AA45: =IF(R45=" ",AA35,AA35+R45) -> 0 | AC45: =IF(T45=" ",AC35,T45+AC35) -> 0 | AD45: =IF(G45="SSP",H45,0) -> 0 | AE45: =IF(G45="SMP",H45,0) -> 0 | AF45: =IF(G45="SPP",H45,0) -> 0 | AG45: =IF(G45="SAP",H45,0) -> 0
F46: Payroll Total | M46: =SUM(M41:M45) -> 0 | N46: =SUM(N41:N45) -> 0 | O46: =SUM(O41:O45) -> 0 | P46: =SUM(P41:P45) -> 0 | Q46: =SUM(Q41:Q45) -> 0 | R46: =SUM(R41:R45) -> 0 | T46: =SUM(T41:T45) -> 0
B48: MONTHLY PAYROLL | O48: Date Wages paid
B49: Month number | E49: 5 | H49: Date Wages paid | K49: =DATE(2024,10,1) -> 45566 | L49: - | M49: =DATE(2024,10,31) -> 45596 | O49: One Click to repeat previous month Enter Y
B51: =IF(E51=" "," ",IF(Employee!F$24>E$49," ",IF(Employee!F$26<E$49," ",Employee!D$30))) | E51: =IF(Employee!D$28="w"," ",IF(Employee!F$24>E$49," ",IF(Employee!F$26<E$49," ",Employee!D$29))) | F51: =IF(E51=" "," ",IF(Employee!F$24>E$49," ",IF(Employee!F$26<E$49," ",Employee!D$15))) | H51: =IF(T$49="Y",Sep!H51,0) -> 0 | I51: =IF(T$49="Y",Sep!I51,0) -> 0 | J51: =IF(T$49="Y",Sep!J51,0) -> 0 | K51: =IF(T$49="Y",Sep!K51,I51*J51) -> 0 | L51: =IF(T$49="Y",Sep!L51,0) -> 0 | M51: =IF(E51=" "," ",IF(T$49="Y",Sep!M51,IF((H51+K51+L51)>0,H51+K51+L51," "))) | N51: 0 | O51: 0 | P51: 0 | Q51: 0 | R51: =IF(M51=" "," ",IF(M51=0," ",M51-SUM(N51:Q51))) | T51: 0 | V51: =IF(Employee!H$35=E$49,Employee!D$34+SUM(M51)+Sep!V51,SUM(M51)+Sep!V51) -> 0 | W51: =IF(Employee!H$35=E$49,Employee!D$35+SUM(N51)+Sep!W51,SUM(N51)+Sep!W51) -> 0 | X51: =IF(O51=" ",Sep!X51,O51+Sep!X51) -> 0 | Y51: =IF(P51=" ",Sep!Y51,P51+Sep!Y51) -> 0 | Z51: =IF(Q51=" ",Sep!Z51,Q51+Sep!Z51) -> 0 | AA51: =IF(R51=" ",Sep!AA51,R51+Sep!AA51) -> 0 | AC51: =IF(T51=" ",Sep!AC51,T51+Sep!AC51) -> 0 | AD51: =IF(G51="SSP",H51,0) -> 0 | AE51: =IF(G51="SMP",H51,0) -> 0 | AF51: =IF(G51="SPP",H51,0) -> 0 | AG51: =IF(G51="SAP",H51,0) -> 0
B52: =IF(E52=" "," ",IF(Employee!F$50>E$49," ",IF(Employee!F$52<E$49," ",Employee!D$56))) | E52: =IF(Employee!D$54="w"," ",IF(Employee!F$50>E$49," ",IF(Employee!F$52<E$49," ",Employee!D$55))) | F52: =IF(E52=" "," ",IF(Employee!F$50>E$49," ",IF(Employee!F$52<E$49," ",Employee!D$41))) | H52: =IF(T$49="Y",Sep!H52,0) -> 0 | I52: =IF(T$49="Y",Sep!I52,0) -> 0 | J52: =IF(T$49="Y",Sep!J52,0) -> 0 | K52: =IF(T$49="Y",Sep!K52,I52*J52) -> 0 | L52: =IF(T$49="Y",Sep!L52,0) -> 0 | M52: =IF(E52=" "," ",IF(T$49="Y",Sep!M52,IF((H52+K52+L52)>0,H52+K52+L52," "))) | N52: 0 | O52: 0 | P52: 0 | Q52: 0 | R52: =IF(M52=" "," ",IF(M52=0," ",M52-SUM(N52:Q52))) | T52: 0 | V52: =IF(Employee!H$61=E$49,Employee!D$60+SUM(M52)+Sep!V52,SUM(M52)+Sep!V52) -> 0 | W52: =IF(Employee!H$61=E$49,Employee!D$61+SUM(N52)+Sep!W52,SUM(N52)+Sep!W52) -> 0 | X52: =IF(O52=" ",Sep!X52,O52+Sep!X52) -> 0 | Y52: =IF(P52=" ",Sep!Y52,P52+Sep!Y52) -> 0 | Z52: =IF(Q52=" ",Sep!Z52,Q52+Sep!Z52) -> 0 | AA52: =IF(R52=" ",Sep!AA52,R52+Sep!AA52) -> 0 | AC52: =IF(T52=" ",Sep!AC52,T52+Sep!AC52) -> 0 | AD52: =IF(G52="SSP",H52,0) -> 0 | AE52: =IF(G52="SMP",H52,0) -> 0 | AF52: =IF(G52="SPP",H52,0) -> 0 | AG52: =IF(G52="SAP",H52,0) -> 0
B53: =IF(E53=" "," ",IF(Employee!F$76>E$49," ",IF(Employee!F$78<E$49," ",Employee!D$82))) | E53: =IF(Employee!D$80="w"," ",IF(Employee!F$76>E$49," ",IF(Employee!F$78<E$49," ",Employee!D$81))) | F53: =IF(E53=" "," ",IF(Employee!F$76>E$49," ",IF(Employee!F$78<E$49," ",Employee!D$67))) | H53: =IF(T$49="Y",Sep!H53,0) -> 0 | I53: =IF(T$49="Y",Sep!I53,0) -> 0 | J53: =IF(T$49="Y",Sep!J53,0) -> 0 | K53: =IF(T$49="Y",Sep!K53,I53*J53) -> 0 | L53: =IF(T$49="Y",Sep!L53,0) -> 0 | M53: =IF(E53=" "," ",IF(T$49="Y",Sep!M53,IF((H53+K53+L53)>0,H53+K53+L53," "))) | N53: 0 | O53: 0 | P53: 0 | Q53: 0 | R53: =IF(M53=" "," ",IF(M53=0," ",M53-SUM(N53:Q53))) | T53: 0 | V53: =IF(Employee!H$87=E$49,Employee!D$86+SUM(M53)+Sep!V53,SUM(M53)+Sep!V53) -> 0 | W53: =IF(Employee!H$87=E$49,Employee!D$87+SUM(N53)+Sep!W53,SUM(N53)+Sep!W53) -> 0 | X53: =IF(O53=" ",Sep!X53,O53+Sep!X53) -> 0 | Y53: =IF(P53=" ",Sep!Y53,P53+Sep!Y53) -> 0 | Z53: =IF(Q53=" ",Sep!Z53,Q53+Sep!Z53) -> 0 | AA53: =IF(R53=" ",Sep!AA53,R53+Sep!AA53) -> 0 | AC53: =IF(T53=" ",Sep!AC53,T53+Sep!AC53) -> 0 | AD53: =IF(G53="SSP",H53,0) -> 0 | AE53: =IF(G53="SMP",H53,0) -> 0 | AF53: =IF(G53="SPP",H53,0) -> 0 | AG53: =IF(G53="SAP",H53,0) -> 0
B54: =IF(E54=" "," ",IF(Employee!F$102>E$49," ",IF(Employee!F$104<E$49," ",Employee!D$108))) | E54: =IF(Employee!D$106="w"," ",IF(Employee!F$102>E$49," ",IF(Employee!F$104<E$49," ",Employee!D$107))) | F54: =IF(E54=" "," ",IF(Employee!F$102>E$49," ",IF(Employee!F$104<E$49," ",Employee!D$93))) | H54: =IF(T$49="Y",Sep!H54,0) -> 0 | I54: =IF(T$49="Y",Sep!I54,0) -> 0 | J54: =IF(T$49="Y",Sep!J54,0) -> 0 | K54: =IF(T$49="Y",Sep!K54,I54*J54) -> 0 | L54: =IF(T$49="Y",Sep!L54,0) -> 0 | M54: =IF(E54=" "," ",IF(T$49="Y",Sep!M54,IF((H54+K54+L54)>0,H54+K54+L54," "))) | N54: 0 | O54: 0 | P54: 0 | Q54: 0 | R54: =IF(M54=" "," ",IF(M54=0," ",M54-SUM(N54:Q54))) | T54: 0 | V54: =IF(Employee!H$113=E$49,Employee!D$112+SUM(M54)+Sep!V54,SUM(M54)+Sep!V54) -> 0 | W54: =IF(Employee!H$113=E$49,Employee!D$113+SUM(N54)+Sep!W54,SUM(N54)+Sep!W54) -> 0 | X54: =IF(O54=" ",Sep!X54,O54+Sep!X54) -> 0 | Y54: =IF(P54=" ",Sep!Y54,P54+Sep!Y54) -> 0 | Z54: =IF(Q54=" ",Sep!Z54,Q54+Sep!Z54) -> 0 | AA54: =IF(R54=" ",Sep!AA54,R54+Sep!AA54) -> 0 | AC54: =IF(T54=" ",Sep!AC54,T54+Sep!AC54) -> 0 | AD54: =IF(G54="SSP",H54,0) -> 0 | AE54: =IF(G54="SMP",H54,0) -> 0 | AF54: =IF(G54="SPP",H54,0) -> 0 | AG54: =IF(G54="SAP",H54,0) -> 0
B55: =IF(E55=" "," ",IF(Employee!F$128>E$49," ",IF(Employee!F$130<E$49," ",Employee!D$134))) | E55: =IF(Employee!D$132="w"," ",IF(Employee!F$128>E$49," ",IF(Employee!F$130<E$49," ",Employee!D$133))) | F55: =IF(E55=" "," ",IF(Employee!F$128>E$49," ",IF(Employee!F$130<E$49," ",Employee!D$119))) | H55: =IF(T$49="Y",Sep!H55,0) -> 0 | I55: =IF(T$49="Y",Sep!I55,0) -> 0 | J55: =IF(T$49="Y",Sep!J55,0) -> 0 | K55: =IF(T$49="Y",Sep!K55,I55*J55) -> 0 | L55: =IF(T$49="Y",Sep!L55,0) -> 0 | M55: =IF(E55=" "," ",IF(T$49="Y",Sep!M55,IF((H55+K55+L55)>0,H55+K55+L55," "))) | N55: 0 | O55: 0 | P55: 0 | Q55: 0 | R55: =IF(M55=" "," ",IF(M55=0," ",M55-SUM(N55:Q55))) | T55: 0 | V55: =IF(Employee!H$139=E$49,Employee!D$138+SUM(M55)+Sep!V55,SUM(M55)+Sep!V55) -> 0 | W55: =IF(Employee!H$139=E$49,Employee!D$139+SUM(N55)+Sep!W55,SUM(N55)+Sep!W55) -> 0 | X55: =IF(O55=" ",Sep!X55,O55+Sep!X55) -> 0 | Y55: =IF(P55=" ",Sep!Y55,P55+Sep!Y55) -> 0 | Z55: =IF(Q55=" ",Sep!Z55,Q55+Sep!Z55) -> 0 | AA55: =IF(R55=" ",Sep!AA55,R55+Sep!AA55) -> 0 | AC55: =IF(T55=" ",Sep!AC55,T55+Sep!AC55) -> 0 | AD55: =IF(G55="SSP",H55,0) -> 0 | AE55: =IF(G55="SMP",H55,0) -> 0 | AF55: =IF(G55="SPP",H55,0) -> 0 | AG55: =IF(G55="SAP",H55,0) -> 0
F56: Payroll Total | M56: =SUM(M51:M55) -> 0 | N56: =SUM(N51:N55) -> 0 | O56: =SUM(O51:O55) -> 0 | P56: =SUM(P51:P55) -> 0 | Q56: =SUM(Q51:Q55) -> 0 | R56: =SUM(R51:R55) -> 0 | T56: =SUM(T51:T55) -> 0
AD58: =SUM(AD11:AD56) -> 0 | AE58: =SUM(AE11:AE56) -> 0 | AF58: =SUM(AF11:AF56) -> 0 | AG58: =SUM(AG11:AG56) -> 0
F59: Directors | M59: Directors Wages Limited Companies Only
F60: =IF(B51="D",Employee!D15," ") | M60: =IF(B51="D",M51," ") | N60: =IF(B51="D",N51," ") | O60: =IF(B51="D",O51," ") | P60: =IF(B51="D",P51," ") | Q60: =IF(B51="D",Q51," ") | R60: =IF(B51="D",R51," ") | T60: =IF(B51="D",T51," ") | AD60: =IF((AD58-(O1+T1)*0.13)>0,AD58-(Q1+T1)*0.13,0) -> 0 | AE60: =AE58 -> 0 | AF60: =AF58 -> 0 | AG60: =AG58 -> 0
F61: =IF(B52="D",Employee!D41," ") | M61: =IF(B52="D",M52," ") | N61: =IF(B52="D",N52," ") | O61: =IF(B52="D",O52," ") | P61: =IF(B52="D",P52," ") | Q61: =IF(B52="D",Q52," ") | R61: =IF(B52="D",R52," ") | T61: =IF(B52="D",T52," ")
F62: =IF(B53="D",Employee!D67," ") | M62: =IF(B53="D",M53," ") | N62: =IF(B53="D",N53," ") | O62: =IF(B53="D",O53," ") | P62: =IF(B53="D",P53," ") | Q62: =IF(B53="D",Q53," ") | R62: =IF(B53="D",R53," ") | T62: =IF(B53="D",T53," ") | AE62: =AE60*0.045 -> 0 | AF62: =AF60*0.045 -> 0 | AG62: =AG60*0.045 -> 0
F63: =IF(B54="D",Employee!D93," ") | M63: =IF(B54="D",M54," ") | N63: =IF(B54="D",N54," ") | O63: =IF(B54="D",O54," ") | P63: =IF(B54="D",P54," ") | Q63: =IF(B54="D",Q54," ") | R63: =IF(B54="D",R54," ") | T63: =IF(B54="D",T54," ")
F64: =IF(B55="D",Employee!D119," ") | M64: =IF(B55="D",M55," ") | N64: =IF(B55="D",N55," ") | O64: =IF(B55="D",O55," ") | P64: =IF(B55="D",P55," ") | Q64: =IF(B55="D",Q55," ") | R64: =IF(B55="D",R55," ") | T64: =IF(B55="D",T55," ")
F65: Director Totals | M65: =SUM(M60:M64) -> 0 | N65: =SUM(N60:N64) -> 0 | O65: =SUM(O60:O64) -> 0 | P65: =SUM(P60:P64) -> 0 | Q65: =SUM(Q60:Q64) -> 0 | R65: =SUM(R60:R64) -> 0 | T65: =SUM(T60:T64) -> 0 | AD65: =AD60+Sep!AD65 -> 0 | AE65: =AE60+Sep!AE65 -> 0 | AF65: =AF60+Sep!AF65 -> 0 | AG65: =AG60+Sep!AG65 -> 0
AE67: =AE62+Sep!AE67 -> 0 | AF67: =AF62+Sep!AF67 -> 0 | AG67: =AG62+Sep!AG67 -> 0

Sheet Nov
B1: www.diyaccounting.co.uk | G1: =SUM(AD70:AG70)+SUM(AE72:AG72) -> 0 | I1: Monthly Totals | M1: =M16+M26+M36+M46+M56+M66 -> 0 | N1: =N16+N26+N36+N46+N56+N66 -> 0 | O1: =O16+O26+O36+O46+O56+O66 -> 0 | P1: =P16+P26+P36+P46+P56+P66 -> 0 | Q1: =Q16+Q26+Q36+Q46+Q56+Q66 -> 0 | R1: =R16+R26+R36+R46+R56+R66 -> 0 | T1: =T16+T26+T36+T46+T56+T66 -> 0 | V1: YEAR TO DATE | AD1: Statutory Payments & NIC Recovered
I2: Sub Totals Directors | M2: =M75 -> 0 | N2: =N75 -> 0 | O2: =O75 -> 0 | P2: =P75 -> 0 | Q2: =Q75 -> 0 | R2: =R75 -> 0 | S2: =S65 -> 0 | T2: =T75 -> 0
B3: Dir Ref | C3: NIC Table | D3: Tax Code | E3: Pay No | F3: Employee Name | G3: SSP | H3: =Jun!H3:H6 -> Statutory Pay | I3: =Jun!I3:I6 -> Basic hours | J3: =Jun!J3:J6 -> Hourly rate | K3: =Jun!K3:K6 -> Basic wages | L3: =Jun!L3:L6 -> Overtime Bonus Gratuities | M3: =Jun!M3:M6 -> GROSS WAGES | N3: =Jun!N3:N6 -> Income Tax | O3: =Jun!O3:O6 -> Employees National Insurance | ... R3: =Jun!R3:R6 -> NET PAY | T3: =Jun!T3:T6 -> Employers National Insurance | V3: Gross Wages | W3: Income Tax | X3: Employees National Insurance | Y3: Student Loan deductions | Z3: Other Deductions | AA3: Net Pay | AC3: Employers National Insurance | AD3: Statutory Sick Pay Recovered | AE3: Statutory Maternity Pay Recovered | AF3: Statutory Paternity Pay Recovered | AG3: Statutory Adoption Pay Recovered
G4: SMP
G5: SPP
G6: SAP
B8: WEEKLY PAYROLL | O8: Date Wages paid
B9: Week number | E9: 22 | H9: Date Wages paid | K9: =Oct!M39+1 -> 45898 | L9: - | M9: =K9+6 -> 45904 | O9: One Click to repeat previous week Enter Y
B11: =IF(E11=" "," ",IF(Employee!F$24>E$9," ",IF(Employee!F$26<E$9," ",Employee!D$30))) | E11: =IF(Employee!D$28="m"," ",IF(Employee!F$24>E$9," ",IF(Employee!F$26<E$9," ",Employee!D$29))) | F11: =IF(E11=" "," ",IF(Employee!F$24>E$9," ",IF(Employee!F$26<E$9," ",Employee!D$15))) | H11: =IF(T$9="Y",Oct!H41,0) -> 0 | I11: =IF(T$9="Y",Oct!I41,0) -> 0 | J11: =IF(T$9="Y",Oct!J41,0) -> 0 | K11: =IF(T$9="Y",Oct!K41,I11*J11) -> 0 | L11: =IF(T$9="Y",Oct!L41,0) -> 0 | M11: =IF(E11=" "," ",IF(T$9="Y",Oct!M41,IF((H11+K11+L11)>0,H11+K11+L11," "))) | N11: 0 | O11: 0 | P11: 0 | Q11: 0 | R11: =IF(M11=" "," ",IF(M11=0," ",M11-SUM(N11:Q11))) | T11: 0 | V11: =IF(Employee!H$34=E$9,Employee!D$34+SUM(M11)+Oct!V41,SUM(M11)+Oct!V41) -> 0 | W11: =IF(Employee!H$34=E$9,Employee!D$35+SUM(N11)+Oct!W41,SUM(N11)+Oct!W41) -> 0 | X11: =IF(O11=" ",Oct!X41,O11+Oct!X41) -> 0 | Y11: =IF(P11=" ",Oct!Y41,P11+Oct!Y41) -> 0 | Z11: =IF(Q11=" ",Oct!Z41,Q11+Oct!Z41) -> 0 | AA11: =IF(R11=" ",Oct!AA41,R11+Oct!AA41) -> 0 | AC11: =IF(T11=" ",Oct!AC41,T11+Oct!AC41) -> 0 | AD11: =IF(G11="SSP",H11,0) -> 0 | AE11: =IF(G11="SMP",H11,0) -> 0 | AF11: =IF(G11="SPP",H11,0) -> 0 | AG11: =IF(G11="SAP",H11,0) -> 0
B12: =IF(E12=" "," ",IF(Employee!F$50>E$9," ",IF(Employee!F$52<E$9," ",Employee!D$56))) | E12: =IF(Employee!D$54="m"," ",IF(Employee!F$50>E$9," ",IF(Employee!F$52<E$9," ",Employee!D$55))) | F12: =IF(E12=" "," ",IF(Employee!F$50>E$9," ",IF(Employee!F$52<E$9," ",Employee!D$41))) | H12: =IF(T$9="Y",Oct!H42,0) -> 0 | I12: =IF(T$9="Y",Oct!I42,0) -> 0 | J12: =IF(T$9="Y",Oct!J42,0) -> 0 | K12: =IF(T$9="Y",Oct!K42,I12*J12) -> 0 | L12: =IF(T$9="Y",Oct!L42,0) -> 0 | M12: =IF(E12=" "," ",IF(T$9="Y",Oct!M42,IF((H12+K12+L12)>0,H12+K12+L12," "))) | N12: 0 | O12: 0 | P12: 0 | Q12: 0 | R12: =IF(M12=" "," ",IF(M12=0," ",M12-SUM(N12:Q12))) | T12: 0 | V12: =IF(Employee!H$60=E$9,Employee!D$60+SUM(M12)+Oct!V42,SUM(M12)+Oct!V42) -> 0 | W12: =IF(Employee!H$60=E$9,Employee!D$61+SUM(N12)+Oct!W42,SUM(N12)+Oct!W42) -> 0 | X12: =IF(O12=" ",Oct!X42,O12+Oct!X42) -> 0 | Y12: =IF(P12=" ",Oct!Y42,P12+Oct!Y42) -> 0 | Z12: =IF(Q12=" ",Oct!Z42,Q12+Oct!Z42) -> 0 | AA12: =IF(R12=" ",Oct!AA42,R12+Oct!AA42) -> 0 | AC12: =IF(T12=" ",Oct!AC42,T12+Oct!AC42) -> 0 | AD12: =IF(G12="SSP",H12,0) -> 0 | AE12: =IF(G12="SMP",H12,0) -> 0 | AF12: =IF(G12="SPP",H12,0) -> 0 | AG12: =IF(G12="SAP",H12,0) -> 0
B13: =IF(E13=" "," ",IF(Employee!F$76>E$9," ",IF(Employee!F$78<E$9," ",Employee!D$82))) | E13: =IF(Employee!D$80="m"," ",IF(Employee!F$76>E$9," ",IF(Employee!F$78<E$9," ",Employee!D$81))) | F13: =IF(E13=" "," ",IF(Employee!F$76>E$9," ",IF(Employee!F$78<E$9," ",Employee!D$67))) | H13: =IF(T$9="Y",Oct!H43,0) -> 0 | I13: =IF(T$9="Y",Oct!I43,0) -> 0 | J13: =IF(T$9="Y",Oct!J43,0) -> 0 | K13: =IF(T$9="Y",Oct!K43,I13*J13) -> 0 | L13: =IF(T$9="Y",Oct!L43,0) -> 0 | M13: =IF(E13=" "," ",IF(T$9="Y",Oct!M43,IF((H13+K13+L13)>0,H13+K13+L13," "))) | N13: 0 | O13: 0 | P13: 0 | Q13: 0 | R13: =IF(M13=" "," ",IF(M13=0," ",M13-SUM(N13:Q13))) | T13: 0 | V13: =IF(Employee!H$86=E$9,Employee!D$86+SUM(M13)+Oct!V43,SUM(M13)+Oct!V43) -> 0 | W13: =IF(Employee!H$86=E$9,Employee!D$87+SUM(N13)+Oct!W43,SUM(N13)+Oct!W43) -> 0 | X13: =IF(O13=" ",Oct!X43,O13+Oct!X43) -> 0 | Y13: =IF(P13=" ",Oct!Y43,P13+Oct!Y43) -> 0 | Z13: =IF(Q13=" ",Oct!Z43,Q13+Oct!Z43) -> 0 | AA13: =IF(R13=" ",Oct!AA43,R13+Oct!AA43) -> 0 | AC13: =IF(T13=" ",Oct!AC43,T13+Oct!AC43) -> 0 | AD13: =IF(G13="SSP",H13,0) -> 0 | AE13: =IF(G13="SMP",H13,0) -> 0 | AF13: =IF(G13="SPP",H13,0) -> 0 | AG13: =IF(G13="SAP",H13,0) -> 0
B14: =IF(E14=" "," ",IF(Employee!F$102>E$9," ",IF(Employee!F$104<E$9," ",Employee!D$108))) | E14: =IF(Employee!D$106="m"," ",IF(Employee!F$102>E$9," ",IF(Employee!F$104<E$9," ",Employee!D$107))) | F14: =IF(E14=" "," ",IF(Employee!F$102>E$9," ",IF(Employee!F$104<E$9," ",Employee!D$93))) | H14: =IF(T$9="Y",Oct!H44,0) -> 0 | I14: =IF(T$9="Y",Oct!I44,0) -> 0 | J14: =IF(T$9="Y",Oct!J44,0) -> 0 | K14: =IF(T$9="Y",Oct!K44,I14*J14) -> 0 | L14: =IF(T$9="Y",Oct!L44,0) -> 0 | M14: =IF(E14=" "," ",IF(T$9="Y",Oct!M44,IF((H14+K14+L14)>0,H14+K14+L14," "))) | N14: 0 | O14: 0 | P14: 0 | Q14: 0 | R14: =IF(M14=" "," ",IF(M14=0," ",M14-SUM(N14:Q14))) | T14: 0 | V14: =IF(Employee!H$112=E$9,Employee!D$112+SUM(M14)+Oct!V44,SUM(M14)+Oct!V44) -> 0 | W14: =IF(Employee!H$112=E$9,Employee!D$113+SUM(N14)+Oct!W44,SUM(N14)+Oct!W44) -> 0 | X14: =IF(O14=" ",Oct!X44,O14+Oct!X44) -> 0 | Y14: =IF(P14=" ",Oct!Y44,P14+Oct!Y44) -> 0 | Z14: =IF(Q14=" ",Oct!Z44,Q14+Oct!Z44) -> 0 | AA14: =IF(R14=" ",Oct!AA44,R14+Oct!AA44) -> 0 | AC14: =IF(T14=" ",Oct!AC44,T14+Oct!AC44) -> 0 | AD14: =IF(G14="SSP",H14,0) -> 0 | AE14: =IF(G14="SMP",H14,0) -> 0 | AF14: =IF(G14="SPP",H14,0) -> 0 | AG14: =IF(G14="SAP",H14,0) -> 0
B15: =IF(E15=" "," ",IF(Employee!F$128>E$9," ",IF(Employee!F$130<E$9," ",Employee!D$134))) | E15: =IF(Employee!D$132="m"," ",IF(Employee!F$128>E$9," ",IF(Employee!F$130<E$9," ",Employee!D$133))) | F15: =IF(E15=" "," ",IF(Employee!F$128>E$9," ",IF(Employee!F$130<E$9," ",Employee!D$119))) | H15: =IF(T$9="Y",Oct!H45,0) -> 0 | I15: =IF(T$9="Y",Oct!I45,0) -> 0 | J15: =IF(T$9="Y",Oct!J45,0) -> 0 | K15: =IF(T$9="Y",Oct!K45,I15*J15) -> 0 | L15: =IF(T$9="Y",Oct!L45,0) -> 0 | M15: =IF(E15=" "," ",IF(T$9="Y",Oct!M45,IF((H15+K15+L15)>0,H15+K15+L15," "))) | N15: 0 | O15: 0 | P15: 0 | Q15: 0 | R15: =IF(M15=" "," ",IF(M15=0," ",M15-SUM(N15:Q15))) | T15: 0 | V15: =IF(Employee!H$138=E$9,Employee!D$138+SUM(M15)+Oct!V45,SUM(M15)+Oct!V45) -> 0 | W15: =IF(Employee!H$138=E$9,Employee!D$139+SUM(N15)+Oct!W45,SUM(N15)+Oct!W45) -> 0 | X15: =IF(O15=" ",Oct!X45,O15+Oct!X45) -> 0 | Y15: =IF(P15=" ",Oct!Y45,P15+Oct!Y45) -> 0 | Z15: =IF(Q15=" ",Oct!Z45,Q15+Oct!Z45) -> 0 | AA15: =IF(R15=" ",Oct!AA45,R15+Oct!AA45) -> 0 | AC15: =IF(T15=" ",Oct!AC45,T15+Oct!AC45) -> 0 | AD15: =IF(G15="SSP",H15,0) -> 0 | AE15: =IF(G15="SMP",H15,0) -> 0 | AF15: =IF(G15="SPP",H15,0) -> 0 | AG15: =IF(G15="SAP",H15,0) -> 0
F16: Payroll Total | M16: =SUM(M11:M15) -> 0 | N16: =SUM(N11:N15) -> 0 | O16: =SUM(O11:O15) -> 0 | P16: =SUM(P11:P15) -> 0 | Q16: =SUM(Q11:Q15) -> 0 | R16: =SUM(R11:R15) -> 0 | T16: =SUM(T11:T15) -> 0
B18: WEEKLY PAYROLL | O18: Date Wages paid
B19: Week number | E19: 23 | H19: Date Wages paid | K19: =M9+1 -> 45905 | L19: - | M19: =K19+6 -> 45911 | O19: One Click to repeat previous week Enter Y
B21: =IF(E21=" "," ",IF(Employee!F$24>E$19," ",IF(Employee!F$26<E$19," ",Employee!D$30))) | E21: =IF(Employee!D$28="m"," ",IF(Employee!F$24>E$19," ",IF(Employee!F$26<E$19," ",Employee!D$29))) | F21: =IF(E21=" "," ",IF(Employee!F$24>E$19," ",IF(Employee!F$26<E$19," ",Employee!D$15))) | H21: =IF(T$19="Y",H11,0) -> 0 | I21: =IF(T$19="Y",I11,0) -> 0 | J21: =IF(T$19="Y",J11,0) -> 0 | K21: =IF(T$19="Y",K11,I21*J21) -> 0 | L21: =IF(T$19="Y",L11,0) -> 0 | M21: =IF(E21=" "," ",IF(T$19="Y",M11,IF((H21+K21+L21)>0,H21+K21+L21," "))) | N21: 0 | O21: 0 | P21: 0 | Q21: 0 | R21: =IF(M21=" "," ",IF(M21=0," ",M21-SUM(N21:Q21))) | T21: 0 | V21: =IF(Employee!H$34=E$19,Employee!D$34+SUM(M21)+V11,SUM(M21)+V11) -> 0 | W21: =IF(Employee!H$34=E$19,Employee!D$35+SUM(N21)+W11,SUM(N21)+W11) -> 0 | X21: =IF(O21=" ",X11,O21+X11) -> 0 | Y21: =IF(P21=0,Y11,P21+Y11) -> 0 | Z21: =IF(Q21=0,Z11,Q21+Z11) -> 0 | AA21: =IF(R21=" ",AA11,AA11+R21) -> 0 | AC21: =IF(T21=" ",AC11,T21+AC11) -> 0 | AD21: =IF(G21="SSP",H21,0) -> 0 | AE21: =IF(G21="SMP",H21,0) -> 0 | AF21: =IF(G21="SPP",H21,0) -> 0 | AG21: =IF(G21="SAP",H21,0) -> 0
B22: =IF(E22=" "," ",IF(Employee!F$50>E$19," ",IF(Employee!F$52<E$19," ",Employee!D$56))) | E22: =IF(Employee!D$54="m"," ",IF(Employee!F$50>E$19," ",IF(Employee!F$52<E$19," ",Employee!D$55))) | F22: =IF(E22=" "," ",IF(Employee!F$50>E$19," ",IF(Employee!F$52<E$19," ",Employee!D$41))) | H22: =IF(T$19="Y",H12,0) -> 0 | I22: =IF(T$19="Y",I12,0) -> 0 | J22: =IF(T$19="Y",J12,0) -> 0 | K22: =IF(T$19="Y",K12,I22*J22) -> 0 | L22: =IF(T$19="Y",L12,0) -> 0 | M22: =IF(E22=" "," ",IF(T$19="Y",M12,IF((H22+K22+L22)>0,H22+K22+L22," "))) | N22: 0 | O22: 0 | P22: 0 | Q22: 0 | R22: =IF(M22=" "," ",IF(M22=0," ",M22-SUM(N22:Q22))) | T22: 0 | V22: =IF(Employee!H$60=E$19,Employee!D$60+SUM(M22)+V12,SUM(M22)+V12) -> 0 | W22: =IF(Employee!H$60=E$19,Employee!D$61+SUM(N22)+W12,SUM(N22)+W12) -> 0 | X22: =IF(O22=" ",X12,O22+X12) -> 0 | Y22: =IF(P22=0,Y12,P22+Y12) -> 0 | Z22: =IF(Q22=0,Z12,Q22+Z12) -> 0 | AA22: =IF(R22=" ",AA12,AA12+R22) -> 0 | AC22: =IF(T22=" ",AC12,T22+AC12) -> 0 | AD22: =IF(G22="SSP",H22,0) -> 0 | AE22: =IF(G22="SMP",H22,0) -> 0 | AF22: =IF(G22="SPP",H22,0) -> 0 | AG22: =IF(G22="SAP",H22,0) -> 0
B23: =IF(E23=" "," ",IF(Employee!F$76>E$19," ",IF(Employee!F$78<E$19," ",Employee!D$82))) | E23: =IF(Employee!D$80="m"," ",IF(Employee!F$76>E$19," ",IF(Employee!F$78<E$19," ",Employee!D$81))) | F23: =IF(E23=" "," ",IF(Employee!F$76>E$19," ",IF(Employee!F$78<E$19," ",Employee!D$67))) | H23: =IF(T$19="Y",H13,0) -> 0 | I23: =IF(T$19="Y",I13,0) -> 0 | J23: =IF(T$19="Y",J13,0) -> 0 | K23: =IF(T$19="Y",K13,I23*J23) -> 0 | L23: =IF(T$19="Y",L13,0) -> 0 | M23: =IF(E23=" "," ",IF(T$19="Y",M13,IF((H23+K23+L23)>0,H23+K23+L23," "))) | N23: 0 | O23: 0 | P23: 0 | Q23: 0 | R23: =IF(M23=" "," ",IF(M23=0," ",M23-SUM(N23:Q23))) | T23: 0 | V23: =IF(Employee!H$86=E$19,Employee!D$86+SUM(M23)+V13,SUM(M23)+V13) -> 0 | W23: =IF(Employee!H$86=E$19,Employee!D$87+SUM(N23)+W13,SUM(N23)+W13) -> 0 | X23: =IF(O23=" ",X13,O23+X13) -> 0 | Y23: =IF(P23=0,Y13,P23+Y13) -> 0 | Z23: =IF(Q23=0,Z13,Q23+Z13) -> 0 | AA23: =IF(R23=" ",AA13,AA13+R23) -> 0 | AC23: =IF(T23=" ",AC13,T23+AC13) -> 0 | AD23: =IF(G23="SSP",H23,0) -> 0 | AE23: =IF(G23="SMP",H23,0) -> 0 | AF23: =IF(G23="SPP",H23,0) -> 0 | AG23: =IF(G23="SAP",H23,0) -> 0
B24: =IF(E24=" "," ",IF(Employee!F$102>E$19," ",IF(Employee!F$104<E$19," ",Employee!D$108))) | E24: =IF(Employee!D$106="m"," ",IF(Employee!F$102>E$19," ",IF(Employee!F$104<E$19," ",Employee!D$107))) | F24: =IF(E24=" "," ",IF(Employee!F$102>E$19," ",IF(Employee!F$104<E$19," ",Employee!D$93))) | H24: =IF(T$19="Y",H14,0) -> 0 | I24: =IF(T$19="Y",I14,0) -> 0 | J24: =IF(T$19="Y",J14,0) -> 0 | K24: =IF(T$19="Y",K14,I24*J24) -> 0 | L24: =IF(T$19="Y",L14,0) -> 0 | M24: =IF(E24=" "," ",IF(T$19="Y",M14,IF((H24+K24+L24)>0,H24+K24+L24," "))) | N24: 0 | O24: 0 | P24: 0 | Q24: 0 | R24: =IF(M24=" "," ",IF(M24=0," ",M24-SUM(N24:Q24))) | T24: 0 | V24: =IF(Employee!H$112=E$19,Employee!D$112+SUM(M24)+V14,SUM(M24)+V14) -> 0 | W24: =IF(Employee!H$112=E$19,Employee!D$113+SUM(N24)+W14,SUM(N24)+W14) -> 0 | X24: =IF(O24=" ",X14,O24+X14) -> 0 | Y24: =IF(P24=0,Y14,P24+Y14) -> 0 | Z24: =IF(Q24=0,Z14,Q24+Z14) -> 0 | AA24: =IF(R24=" ",AA14,AA14+R24) -> 0 | AC24: =IF(T24=" ",AC14,T24+AC14) -> 0 | AD24: =IF(G24="SSP",H24,0) -> 0 | AE24: =IF(G24="SMP",H24,0) -> 0 | AF24: =IF(G24="SPP",H24,0) -> 0 | AG24: =IF(G24="SAP",H24,0) -> 0
B25: =IF(E25=" "," ",IF(Employee!F$128>E$19," ",IF(Employee!F$130<E$19," ",Employee!D$134))) | E25: =IF(Employee!D$132="m"," ",IF(Employee!F$128>E$19," ",IF(Employee!F$130<E$19," ",Employee!D$133))) | F25: =IF(E25=" "," ",IF(Employee!F$128>E$19," ",IF(Employee!F$130<E$19," ",Employee!D$119))) | H25: =IF(T$19="Y",H15,0) -> 0 | I25: =IF(T$19="Y",I15,0) -> 0 | J25: =IF(T$19="Y",J15,0) -> 0 | K25: =IF(T$19="Y",K15,I25*J25) -> 0 | L25: =IF(T$19="Y",L15,0) -> 0 | M25: =IF(E25=" "," ",IF(T$19="Y",M15,IF((H25+K25+L25)>0,H25+K25+L25," "))) | N25: 0 | O25: 0 | P25: 0 | Q25: 0 | R25: =IF(M25=" "," ",IF(M25=0," ",M25-SUM(N25:Q25))) | T25: 0 | V25: =IF(Employee!H$138=E$19,Employee!D$138+SUM(M25)+V15,SUM(M25)+V15) -> 0 | W25: =IF(Employee!H$138=E$19,Employee!D$139+SUM(N25)+W15,SUM(N25)+W15) -> 0 | X25: =IF(O25=" ",X15,O25+X15) -> 0 | Y25: =IF(P25=0,Y15,P25+Y15) -> 0 | Z25: =IF(Q25=0,Z15,Q25+Z15) -> 0 | AA25: =IF(R25=" ",AA15,AA15+R25) -> 0 | AC25: =IF(T25=" ",AC15,T25+AC15) -> 0 | AD25: =IF(G25="SSP",H25,0) -> 0 | AE25: =IF(G25="SMP",H25,0) -> 0 | AF25: =IF(G25="SPP",H25,0) -> 0 | AG25: =IF(G25="SAP",H25,0) -> 0
F26: Payroll Total | M26: =SUM(M21:M25) -> 0 | N26: =SUM(N21:N25) -> 0 | O26: =SUM(O21:O25) -> 0 | P26: =SUM(P21:P25) -> 0 | Q26: =SUM(Q21:Q25) -> 0 | R26: =SUM(R21:R25) -> 0 | T26: =SUM(T21:T25) -> 0
B28: WEEKLY PAYROLL | O28: Date Wages paid
B29: Week number | E29: 24 | H29: Date Wages paid | K29: =M19+1 -> 45912 | L29: - | M29: =K29+6 -> 45918 | O29: One Click to repeat previous week Enter Y
B31: =IF(E31=" "," ",IF(Employee!F$24>E$29," ",IF(Employee!F$26<E$29," ",Employee!D$30))) | E31: =IF(Employee!D$28="m"," ",IF(Employee!F$24>E$29," ",IF(Employee!F$26<E$29," ",Employee!D$29))) | F31: =IF(E31=" "," ",IF(Employee!F$24>E$29," ",IF(Employee!F$26<E$29," ",Employee!D$15))) | H31: =IF(T$29="Y",H21,0) -> 0 | I31: =IF(T$29="Y",I21,0) -> 0 | J31: =IF(T$29="Y",J21,0) -> 0 | K31: =IF(T$29="Y",K21,I31*J31) -> 0 | L31: =IF(T$29="Y",L21,0) -> 0 | M31: =IF(E31=" "," ",IF(T$29="Y",M21,IF((H31+K31+L31)>0,H31+K31+L31," "))) | N31: 0 | O31: 0 | P31: 0 | Q31: 0 | R31: =IF(M31=" "," ",IF(M31=0," ",M31-SUM(N31:Q31))) | T31: 0 | V31: =IF(Employee!H$34=E$29,Employee!D$34+SUM(M31)+V21,SUM(M31)+V21) -> 0 | W31: =IF(Employee!H$34=E$29,Employee!D$35+SUM(N31)+W21,SUM(N31)+W21) -> 0 | X31: =IF(O31=" ",X21,O31+X21) -> 0 | Y31: =IF(P31=0,Y21,P31+Y21) -> 0 | Z31: =IF(Q31=0,Z21,Q31+Z21) -> 0 | AA31: =IF(R31=" ",AA21,AA21+R31) -> 0 | AC31: =IF(T31=" ",AC21,T31+AC21) -> 0 | AD31: =IF(G31="SSP",H31,0) -> 0 | AE31: =IF(G31="SMP",H31,0) -> 0 | AF31: =IF(G31="SPP",H31,0) -> 0 | AG31: =IF(G31="SAP",H31,0) -> 0
B32: =IF(E32=" "," ",IF(Employee!F$50>E$29," ",IF(Employee!F$52<E$29," ",Employee!D$56))) | E32: =IF(Employee!D$54="m"," ",IF(Employee!F$50>E$29," ",IF(Employee!F$52<E$29," ",Employee!D$55))) | F32: =IF(E32=" "," ",IF(Employee!F$50>E$29," ",IF(Employee!F$52<E$29," ",Employee!D$41))) | H32: =IF(T$29="Y",H22,0) -> 0 | I32: =IF(T$29="Y",I22,0) -> 0 | J32: =IF(T$29="Y",J22,0) -> 0 | K32: =IF(T$29="Y",K22,I32*J32) -> 0 | L32: =IF(T$29="Y",L22,0) -> 0 | M32: =IF(E32=" "," ",IF(T$29="Y",M22,IF((H32+K32+L32)>0,H32+K32+L32," "))) | N32: 0 | O32: 0 | P32: 0 | Q32: 0 | R32: =IF(M32=" "," ",IF(M32=0," ",M32-SUM(N32:Q32))) | T32: 0 | V32: =IF(Employee!H$60=E$29,Employee!D$60+SUM(M32)+V22,SUM(M32)+V22) -> 0 | W32: =IF(Employee!H$60=E$29,Employee!D$61+SUM(N32)+W22,SUM(N32)+W22) -> 0 | X32: =IF(O32=" ",X22,O32+X22) -> 0 | Y32: =IF(P32=0,Y22,P32+Y22) -> 0 | Z32: =IF(Q32=0,Z22,Q32+Z22) -> 0 | AA32: =IF(R32=" ",AA22,AA22+R32) -> 0 | AC32: =IF(T32=" ",AC22,T32+AC22) -> 0 | AD32: =IF(G32="SSP",H32,0) -> 0 | AE32: =IF(G32="SMP",H32,0) -> 0 | AF32: =IF(G32="SPP",H32,0) -> 0 | AG32: =IF(G32="SAP",H32,0) -> 0
B33: =IF(E33=" "," ",IF(Employee!F$76>E$29," ",IF(Employee!F$78<E$29," ",Employee!D$82))) | E33: =IF(Employee!D$80="m"," ",IF(Employee!F$76>E$29," ",IF(Employee!F$78<E$29," ",Employee!D$81))) | F33: =IF(E33=" "," ",IF(Employee!F$76>E$29," ",IF(Employee!F$78<E$29," ",Employee!D$67))) | H33: =IF(T$29="Y",H23,0) -> 0 | I33: =IF(T$29="Y",I23,0) -> 0 | J33: =IF(T$29="Y",J23,0) -> 0 | K33: =IF(T$29="Y",K23,I33*J33) -> 0 | L33: =IF(T$29="Y",L23,0) -> 0 | M33: =IF(E33=" "," ",IF(T$29="Y",M23,IF((H33+K33+L33)>0,H33+K33+L33," "))) | N33: 0 | O33: 0 | P33: 0 | Q33: 0 | R33: =IF(M33=" "," ",IF(M33=0," ",M33-SUM(N33:Q33))) | T33: 0 | V33: =IF(Employee!H$86=E$29,Employee!D$86+SUM(M33)+V23,SUM(M33)+V23) -> 0 | W33: =IF(Employee!H$86=E$29,Employee!D$87+SUM(N33)+W23,SUM(N33)+W23) -> 0 | X33: =IF(O33=" ",X23,O33+X23) -> 0 | Y33: =IF(P33=0,Y23,P33+Y23) -> 0 | Z33: =IF(Q33=0,Z23,Q33+Z23) -> 0 | AA33: =IF(R33=" ",AA23,AA23+R33) -> 0 | AC33: =IF(T33=" ",AC23,T33+AC23) -> 0 | AD33: =IF(G33="SSP",H33,0) -> 0 | AE33: =IF(G33="SMP",H33,0) -> 0 | AF33: =IF(G33="SPP",H33,0) -> 0 | AG33: =IF(G33="SAP",H33,0) -> 0
B34: =IF(E34=" "," ",IF(Employee!F$102>E$29," ",IF(Employee!F$104<E$29," ",Employee!D$108))) | E34: =IF(Employee!D$106="m"," ",IF(Employee!F$102>E$29," ",IF(Employee!F$104<E$29," ",Employee!D$107))) | F34: =IF(E34=" "," ",IF(Employee!F$102>E$29," ",IF(Employee!F$104<E$29," ",Employee!D$93))) | H34: =IF(T$29="Y",H24,0) -> 0 | I34: =IF(T$29="Y",I24,0) -> 0 | J34: =IF(T$29="Y",J24,0) -> 0 | K34: =IF(T$29="Y",K24,I34*J34) -> 0 | L34: =IF(T$29="Y",L24,0) -> 0 | M34: =IF(E34=" "," ",IF(T$29="Y",M24,IF((H34+K34+L34)>0,H34+K34+L34," "))) | N34: 0 | O34: 0 | P34: 0 | Q34: 0 | R34: =IF(M34=" "," ",IF(M34=0," ",M34-SUM(N34:Q34))) | T34: 0 | V34: =IF(Employee!H$112=E$29,Employee!D$112+SUM(M34)+V24,SUM(M34)+V24) -> 0 | W34: =IF(Employee!H$112=E$29,Employee!D$113+SUM(N34)+W24,SUM(N34)+W24) -> 0 | X34: =IF(O34=" ",X24,O34+X24) -> 0 | Y34: =IF(P34=0,Y24,P34+Y24) -> 0 | Z34: =IF(Q34=0,Z24,Q34+Z24) -> 0 | AA34: =IF(R34=" ",AA24,AA24+R34) -> 0 | AC34: =IF(T34=" ",AC24,T34+AC24) -> 0 | AD34: =IF(G34="SSP",H34,0) -> 0 | AE34: =IF(G34="SMP",H34,0) -> 0 | AF34: =IF(G34="SPP",H34,0) -> 0 | AG34: =IF(G34="SAP",H34,0) -> 0
B35: =IF(E35=" "," ",IF(Employee!F$128>E$29," ",IF(Employee!F$130<E$29," ",Employee!D$134))) | E35: =IF(Employee!D$132="m"," ",IF(Employee!F$128>E$29," ",IF(Employee!F$130<E$29," ",Employee!D$133))) | F35: =IF(E35=" "," ",IF(Employee!F$128>E$29," ",IF(Employee!F$130<E$29," ",Employee!D$119))) | H35: =IF(T$29="Y",H25,0) -> 0 | I35: =IF(T$29="Y",I25,0) -> 0 | J35: =IF(T$29="Y",J25,0) -> 0 | K35: =IF(T$29="Y",K25,I35*J35) -> 0 | L35: =IF(T$29="Y",L25,0) -> 0 | M35: =IF(E35=" "," ",IF(T$29="Y",M25,IF((H35+K35+L35)>0,H35+K35+L35," "))) | N35: 0 | O35: 0 | P35: 0 | Q35: 0 | R35: =IF(M35=" "," ",IF(M35=0," ",M35-SUM(N35:Q35))) | T35: 0 | V35: =IF(Employee!H$138=E$29,Employee!D$138+SUM(M35)+V25,SUM(M35)+V25) -> 0 | W35: =IF(Employee!H$138=E$29,Employee!D$139+SUM(N35)+W25,SUM(N35)+W25) -> 0 | X35: =IF(O35=" ",X25,O35+X25) -> 0 | Y35: =IF(P35=0,Y25,P35+Y25) -> 0 | Z35: =IF(Q35=0,Z25,Q35+Z25) -> 0 | AA35: =IF(R35=" ",AA25,AA25+R35) -> 0 | AC35: =IF(T35=" ",AC25,T35+AC25) -> 0 | AD35: =IF(G35="SSP",H35,0) -> 0 | AE35: =IF(G35="SMP",H35,0) -> 0 | AF35: =IF(G35="SPP",H35,0) -> 0 | AG35: =IF(G35="SAP",H35,0) -> 0
F36: Payroll Total | M36: =SUM(M31:M35) -> 0 | N36: =SUM(N31:N35) -> 0 | O36: =SUM(O31:O35) -> 0 | P36: =SUM(P31:P35) -> 0 | Q36: =SUM(Q31:Q35) -> 0 | R36: =SUM(R31:R35) -> 0 | T36: =SUM(T31:T35) -> 0
B38: WEEKLY PAYROLL | O38: Date Wages paid
B39: Week number | E39: 25 | H39: Date Wages paid | K39: =M29+1 -> 45919 | L39: - | M39: =K39+6 -> 45925 | O39: One Click to repeat previous week Enter Y
