Workbook

Sheet VATQtr1
B2: Value Added Tax Return | K2: =Vatinterface!B6 -> 45777
E3: Copy values in boxes to your Vat return | K3: =Vatinterface!B7 -> 45808
B4: To calculate vat payable 1.Click Cell G5 Vat Period 2.Click down arrow 3.Select Vat quarter end date | K4: =Vatinterface!B8 -> 45838
E5: VAT Period ends | G5: 44530 | K5: =Vatinterface!B9 -> 45869
K6: =Vatinterface!B10 -> 45900
E7: Due date: | G7: =LOOKUP(G$5,Vatinterface!B1:B20,Vatinterface!C1:C20) -> 45869 | K7: =Vatinterface!B11 -> 45930
K8: =Vatinterface!B12 -> 45961
B9: VAT due on sales | F9: 1 | G9: =LOOKUP(G$5,Vatinterface!B1:B20,Vatinterface!G1:G20) -> 0 | K9: =Vatinterface!B13 -> 45991
K10: =Vatinterface!B14 -> 46022
B11: VAT due on purchases from other EU states | F11: 2 | G11: 0 | K11: =Vatinterface!B15 -> 46053
K12: =Vatinterface!B16 -> 46081
B13: VAT due on sales | F13: 3 | G13: =G9+G11 -> 0 | K13: =Vatinterface!B17 -> 46112
K14: =Vatinterface!B18 -> 46142
B15: VAT reclaimed on purchases | F15: 4 | G15: =LOOKUP(G$5,Vatinterface!B1:B20,Vatinterface!K1:K20) -> 0 | K15: =Vatinterface!B19 -> 46173
B17: =IF(G17>0,"Net VAT to be PAID to Customs","Net VAT to be RECLIAMED from Customs") -> Net VAT to be RECLIAMED from Customs | F17: 5 | G17: =G13-G15 -> 0
B19: =IF(LOOKUP(G$5,Vatinterface!B1:B20,Vatinterface!M1:M20)>0,"FLAT RATE SCHEME APPLIED"," ") | E19: =IF(LOOKUP(G$5,Vatinterface!B1:B20,Vatinterface!M1:M20)>0,LOOKUP(G$5,Vatinterface!B1:B20,Vatinterface!M1:M20)," ")
B21: =IF(LOOKUP(G$5,Vatinterface!B1:B20,Vatinterface!M1:M20)>0,"Total value of sales including VAT","Total value of sales excluding VAT") -> Total value of sales excluding VAT | F21: 6 | G21: =IF(LOOKUP(G$5,Vatinterface!B1:B20,Vatinterface!M1:M20)>0,(LOOKUP(G$5,Vatinterface!B1:B20,Vatinterface!E1:E20)+LOOKUP(G$5,Vatinterface!B1:B20,Vatinterface!G1:G20)),LOOKUP(G$5,Vatinterface!B1:B20,Vatinterface!E1:E20)) -> 0
B23: Total value of purchases excluding VAT | F23: 7 | G23: =LOOKUP(G$5,Vatinterface!B1:B20,Vatinterface!I1:I20) -> 0
A25: Note: | B25: Box 2 is set to zero, any amounts due should be calculated and inserted manually
B26: If goods are bought or sold to other EU states boxes 8 & 9 on the return will require completion
A28: Vat returns must be received by HM Revenue & Customs on or before the due date to avoid surcharges
A29: Make cheques payable to "H M Revenue & Customs" and write your VAT registration number on the back
A30: Quote your VAT registration number as a reference if paying direct by bank
A31: Account Name: HMRC VAT: Account No: 11963155 Sort Code: 08 32 00
F34: box8 | G34: 0
F36: box9 | G36: 0

Sheet VATQtr2
B2: Value Added Tax Return | K2: =Vatinterface!B6 -> 45777
E3: Copy values in boxes to your Vat return | K3: =Vatinterface!B7 -> 45808
B4: To calculate vat payable 1.Click Cell G5 Vat Period 2.Click down arrow 3.Select Vat quarter end date | K4: =Vatinterface!B8 -> 45838
E5: VAT Period ends | G5: 44620 | K5: =Vatinterface!B9 -> 45869
K6: =Vatinterface!B10 -> 45900
E7: Due date: | G7: =LOOKUP(G$5,Vatinterface!B1:B20,Vatinterface!C1:C20) -> 45961 | K7: =Vatinterface!B11 -> 45930
K8: =Vatinterface!B12 -> 45961
B9: VAT due on sales | F9: 1 | G9: =LOOKUP(G$5,Vatinterface!B1:B20,Vatinterface!G1:G20) -> 0 | K9: =Vatinterface!B13 -> 45991
K10: =Vatinterface!B14 -> 46022
B11: VAT due on purchases from other EU states | F11: 2 | G11: 0 | K11: =Vatinterface!B15 -> 46053
K12: =Vatinterface!B16 -> 46081
B13: VAT due on sales | F13: 3 | G13: =G9+G11 -> 0 | K13: =Vatinterface!B17 -> 46112
K14: =Vatinterface!B18 -> 46142
B15: VAT reclaimed on purchases | F15: 4 | G15: =LOOKUP(G$5,Vatinterface!B1:B20,Vatinterface!K1:K20) -> 0 | K15: =Vatinterface!B19 -> 46173
B17: =IF(G17>0,"Net VAT to be PAID to Customs","Net VAT to be RECLIAMED from Customs") -> Net VAT to be RECLIAMED from Customs | F17: 5 | G17: =G13-G15 -> 0
B19: =IF(LOOKUP(G$5,Vatinterface!B1:B20,Vatinterface!M1:M20)>0,"FLAT RATE SCHEME APPLIED"," ") | E19: =IF(LOOKUP(G$5,Vatinterface!B1:B20,Vatinterface!M1:M20)>0,LOOKUP(G$5,Vatinterface!B1:B20,Vatinterface!M1:M20)," ")
B21: =IF(LOOKUP(G$5,Vatinterface!B1:B20,Vatinterface!M1:M20)>0,"Total value of sales including VAT","Total value of sales excluding VAT") -> Total value of sales excluding VAT | F21: 6 | G21: =IF(LOOKUP(G$5,Vatinterface!B1:B20,Vatinterface!M1:M20)>0,(LOOKUP(G$5,Vatinterface!B1:B20,Vatinterface!E1:E20)+LOOKUP(G$5,Vatinterface!B1:B20,Vatinterface!G1:G20)),LOOKUP(G$5,Vatinterface!B1:B20,Vatinterface!E1:E20)) -> 0
B23: Total value of purchases excluding VAT | F23: 7 | G23: =LOOKUP(G$5,Vatinterface!B1:B20,Vatinterface!I1:I20) -> 0
A25: Note: | B25: Box 2 is set to zero, any amounts due should be calculated and inserted manually
B26: If goods are bought or sold to other EU states boxes 8 & 9 on the return will require completion
A28: Vat returns must be received by HM Revenue & Customs on or before the due date to avoid surcharges
A29: Make cheques payable to "H M Revenue & Customs" and write your VAT registration number on the back
A30: Quote your VAT registration number as a reference if paying direct by bank
A31: Account Name: HMRC VAT: Account No: 11963155 Sort Code: 08 32 00
F34: box8 | G34: 0
F36: box9 | G36: 0

Sheet VATQtr3
B2: Value Added Tax Return | K2: =Vatinterface!B6 -> 45777
E3: Copy values in boxes to your Vat return | K3: =Vatinterface!B7 -> 45808
B4: To calculate vat payable 1.Click Cell G5 Vat Period 2.Click down arrow 3.Select Vat quarter end date | K4: =Vatinterface!B8 -> 45838
E5: VAT Period ends | G5: 44712 | K5: =Vatinterface!B9 -> 45869
K6: =Vatinterface!B10 -> 45900
E7: Due date: | G7: =LOOKUP(G$5,Vatinterface!B1:B20,Vatinterface!C1:C20) -> 46053 | K7: =Vatinterface!B11 -> 45930
K8: =Vatinterface!B12 -> 45961
B9: VAT due on sales | F9: 1 | G9: =LOOKUP(G$5,Vatinterface!B1:B20,Vatinterface!G1:G20) -> 0 | K9: =Vatinterface!B13 -> 45991
K10: =Vatinterface!B14 -> 46022
B11: VAT due on purchases from other EU states | F11: 2 | G11: 0 | K11: =Vatinterface!B15 -> 46053
K12: =Vatinterface!B16 -> 46081
B13: VAT due on sales | F13: 3 | G13: =G9+G11 -> 0 | K13: =Vatinterface!B17 -> 46112
K14: =Vatinterface!B18 -> 46142
B15: VAT reclaimed on purchases | F15: 4 | G15: =LOOKUP(G$5,Vatinterface!B1:B20,Vatinterface!K1:K20) -> 0 | K15: =Vatinterface!B19 -> 46173
B17: =IF(G17>0,"Net VAT to be PAID to Customs","Net VAT to be RECLIAMED from Customs") -> Net VAT to be RECLIAMED from Customs | F17: 5 | G17: =G13-G15 -> 0
B19: =IF(LOOKUP(G$5,Vatinterface!B1:B20,Vatinterface!M1:M20)>0,"FLAT RATE SCHEME APPLIED"," ") | E19: =IF(LOOKUP(G$5,Vatinterface!B1:B20,Vatinterface!M1:M20)>0,LOOKUP(G$5,Vatinterface!B1:B20,Vatinterface!M1:M20)," ")
B21: =IF(LOOKUP(G$5,Vatinterface!B1:B20,Vatinterface!M1:M20)>0,"Total value of sales including VAT","Total value of sales excluding VAT") -> Total value of sales excluding VAT | F21: 6 | G21: =IF(LOOKUP(G$5,Vatinterface!B1:B20,Vatinterface!M1:M20)>0,(LOOKUP(G$5,Vatinterface!B1:B20,Vatinterface!E1:E20)+LOOKUP(G$5,Vatinterface!B1:B20,Vatinterface!G1:G20)),LOOKUP(G$5,Vatinterface!B1:B20,Vatinterface!E1:E20)) -> 0
B23: Total value of purchases excluding VAT | F23: 7 | G23: =LOOKUP(G$5,Vatinterface!B1:B20,Vatinterface!I1:I20) -> 0
A25: Note: | B25: Box 2 is set to zero, any amounts due should be calculated and inserted manually
B26: If goods are bought or sold to other EU states boxes 8 & 9 on the return will require completion
A28: Vat returns must be received by HM Revenue & Customs on or before the due date to avoid surcharges
A29: Make cheques payable to "H M Revenue & Customs" and write your VAT registration number on the back
A30: Quote your VAT registration number as a reference if paying direct by bank
A31: Account Name: HMRC VAT: Account No: 11963155 Sort Code: 08 32 00
F34: box8 | G34: 0
F36: box9 | G36: 0

Sheet VATQtr4
B2: Value Added Tax Return | K2: =Vatinterface!B6 -> 45777
E3: Copy values in boxes to your Vat return | K3: =Vatinterface!B7 -> 45808
B4: To calculate vat payable 1.Click Cell G5 Vat Period 2.Click down arrow 3.Select Vat quarter end date | K4: =Vatinterface!B8 -> 45838
E5: VAT Period ends | G5: 44804 | K5: =Vatinterface!B9 -> 45869
K6: =Vatinterface!B10 -> 45900
E7: Due date: | G7: =LOOKUP(G$5,Vatinterface!B1:B20,Vatinterface!C1:C20) -> 46142 | K7: =Vatinterface!B11 -> 45930
K8: =Vatinterface!B12 -> 45961
B9: VAT due on sales | F9: 1 | G9: =LOOKUP(G$5,Vatinterface!B1:B20,Vatinterface!G1:G20) -> 0 | K9: =Vatinterface!B13 -> 45991
K10: =Vatinterface!B14 -> 46022
B11: VAT due on purchases from other EU states | F11: 2 | G11: 0 | K11: =Vatinterface!B15 -> 46053
K12: =Vatinterface!B16 -> 46081
B13: VAT due on sales | F13: 3 | G13: =G9+G11 -> 0 | K13: =Vatinterface!B17 -> 46112
K14: =Vatinterface!B18 -> 46142
B15: VAT reclaimed on purchases | F15: 4 | G15: =LOOKUP(G$5,Vatinterface!B1:B20,Vatinterface!K1:K20) -> 0 | K15: =Vatinterface!B19 -> 46173
B17: =IF(G17>0,"Net VAT to be PAID to Customs","Net VAT to be RECLIAMED from Customs") -> Net VAT to be RECLIAMED from Customs | F17: 5 | G17: =G13-G15 -> 0
B19: =IF(LOOKUP(G$5,Vatinterface!B1:B20,Vatinterface!M1:M20)>0,"FLAT RATE SCHEME APPLIED"," ") | E19: =IF(LOOKUP(G$5,Vatinterface!B1:B20,Vatinterface!M1:M20)>0,LOOKUP(G$5,Vatinterface!B1:B20,Vatinterface!M1:M20)," ")
B21: =IF(LOOKUP(G$5,Vatinterface!B1:B20,Vatinterface!M1:M20)>0,"Total value of sales including VAT","Total value of sales excluding VAT") -> Total value of sales excluding VAT | F21: 6 | G21: =IF(LOOKUP(G$5,Vatinterface!B1:B20,Vatinterface!M1:M20)>0,(LOOKUP(G$5,Vatinterface!B1:B20,Vatinterface!E1:E20)+LOOKUP(G$5,Vatinterface!B1:B20,Vatinterface!G1:G20)),LOOKUP(G$5,Vatinterface!B1:B20,Vatinterface!E1:E20)) -> 0
B23: Total value of purchases excluding VAT | F23: 7 | G23: =LOOKUP(G$5,Vatinterface!B1:B20,Vatinterface!I1:I20) -> 0
A25: Note: | B25: Box 2 is set to zero, any amounts due should be calculated and inserted manually
B26: If goods are bought or sold to other EU states boxes 8 & 9 on the return will require completion
A28: Vat returns must be received by HM Revenue & Customs on or before the due date to avoid surcharges
A29: Make cheques payable to "H M Revenue & Customs" and write your VAT registration number on the back
A30: Quote your VAT registration number as a reference if paying direct by bank
A31: Account Name: HMRC VAT: Account No: 11963155 Sort Code: 08 32 00
F34: box8 | G34: 0
F36: box9 | G36: 0

Sheet VATQtr5
B2: Value Added Tax Return | K2: =Vatinterface!B6 -> 45777
E3: Copy values in boxes to your Vat return | K3: =Vatinterface!B7 -> 45808
B4: To calculate vat payable 1.Click Cell G5 Vat Period 2.Click down arrow 3.Select Vat quarter end date | K4: =Vatinterface!B8 -> 45838
E5: VAT Period ends | G5: 44834 | K5: =Vatinterface!B9 -> 45869
K6: =Vatinterface!B10 -> 45900
E7: Due date: | G7: =LOOKUP(G$5,Vatinterface!B1:B20,Vatinterface!C1:C20) -> 46173 | K7: =Vatinterface!B11 -> 45930
K8: =Vatinterface!B12 -> 45961
B9: VAT due on sales | F9: 1 | G9: =LOOKUP(G$5,Vatinterface!B1:B20,Vatinterface!G1:G20) -> 0 | K9: =Vatinterface!B13 -> 45991
K10: =Vatinterface!B14 -> 46022
B11: VAT due on purchases from other EU states | F11: 2 | G11: 0 | K11: =Vatinterface!B15 -> 46053
K12: =Vatinterface!B16 -> 46081
B13: VAT due on sales | F13: 3 | G13: =G9+G11 -> 0 | K13: =Vatinterface!B17 -> 46112
K14: =Vatinterface!B18 -> 46142
B15: VAT reclaimed on purchases | F15: 4 | G15: =LOOKUP(G$5,Vatinterface!B1:B20,Vatinterface!K1:K20) -> 0 | K15: =Vatinterface!B19 -> 46173
B17: =IF(G17>0,"Net VAT to be PAID to Customs","Net VAT to be RECLIAMED from Customs") -> Net VAT to be RECLIAMED from Customs | F17: 5 | G17: =G13-G15 -> 0
B19: =IF(LOOKUP(G$5,Vatinterface!B1:B20,Vatinterface!M1:M20)>0,"FLAT RATE SCHEME APPLIED"," ") | E19: =IF(LOOKUP(G$5,Vatinterface!B1:B20,Vatinterface!M1:M20)>0,LOOKUP(G$5,Vatinterface!B1:B20,Vatinterface!M1:M20)," ")
B21: =IF(LOOKUP(G$5,Vatinterface!B1:B20,Vatinterface!M1:M20)>0,"Total value of sales including VAT","Total value of sales excluding VAT") -> Total value of sales excluding VAT | F21: 6 | G21: =IF(LOOKUP(G$5,Vatinterface!B1:B20,Vatinterface!M1:M20)>0,(LOOKUP(G$5,Vatinterface!B1:B20,Vatinterface!E1:E20)+LOOKUP(G$5,Vatinterface!B1:B20,Vatinterface!G1:G20)),LOOKUP(G$5,Vatinterface!B1:B20,Vatinterface!E1:E20)) -> 0
B23: Total value of purchases excluding VAT | F23: 7 | G23: =LOOKUP(G$5,Vatinterface!B1:B20,Vatinterface!I1:I20) -> 0
A25: Note: | B25: Box 2 is set to zero, any amounts due should be calculated and inserted manually
B26: If goods are bought or sold to other EU states boxes 8 & 9 on the return will require completion
A28: Vat returns must be received by HM Revenue & Customs on or before the due date to avoid surcharges
A29: Make cheques payable to "H M Revenue & Customs" and write your VAT registration number on the back
A30: Quote your VAT registration number as a reference if paying direct by bank
A31: Account Name: HMRC VAT: Account No: 11963155 Sort Code: 08 32 00
F34: box8 | G34: 0
F36: box9 | G36: 0

Sheet Vatinterface
B2: Vat Period End | C2: Final Date for Vat Payment | D2: Month Sales | E2: Quarter Sales Net of Vat | F2: Month Vat Output | G2: Quarter Vat Due Sales | H2: Month Purchases | I2: Quarter Purchases Net of vat | J2: Month Vat Input | K2: Quarter Vat Reclaimed Purchases | M2: Flat rate Scheme Applied
B4: =[1]Admin!$B$16 -> 45716 | C4: =B5 -> 45747 | D4: =S02Y1!$H$1 -> 0 | F4: =S02Y1!$G$1 -> 0 | H4: =P02Y1!$H$1 -> 0 | J4: =P02Y1!$G$1 -> 0 | M4: =IF([2]Jul!$G$4>0,[2]Jul!$G$4,0) -> 0
B5: =[1]Admin!$B$18 -> 45747 | C5: =B6 -> 45777 | D5: =S03Y1!$H$1 -> 0 | F5: =S03Y1!$G$1 -> 0 | H5: =P03Y1!$H$1 -> 0 | J5: =P03Y1!$G$1 -> 0 | M5: =IF([2]Jul!$G$4>0,[2]Jul!$G$4,0) -> 0
B6: =[1]Admin!$B$20 -> 45777 | C6: =B7 -> 45808 | D6: =[2]Jul!$H$1 -> 0 | E6: =SUM(D4:D6) -> 0 | F6: =[2]Jul!$G$1 -> 0 | G6: =SUM(F4:F6) -> 0 | H6: =[3]Jul!$H$1 -> 0 | I6: =SUM(H4:H6) -> 0 | J6: =[3]Jul!$G$1 -> 0 | K6: =SUM(J4:J6) -> 0 | M6: =IF([2]Jul!$G$4>0,[2]Jul!$G$4,0) -> 0
B7: =[1]Admin!$B$22 -> 45808 | C7: =B8 -> 45838 | D7: =[2]Aug!$H$1 -> 0 | E7: =SUM(D5:D7) -> 0 | F7: =[2]Aug!$G$1 -> 0 | G7: =SUM(F5:F7) -> 0 | H7: =[3]Aug!$H$1 -> 0 | I7: =SUM(H5:H7) -> 0 | J7: =[3]Aug!$G$1 -> 0 | K7: =SUM(J5:J7) -> 0 | M7: =IF([2]Aug!$G$4>0,[2]Aug!$G$4,0) -> 0
B8: =[1]Admin!$B$24 -> 45838 | C8: =B9 -> 45869 | D8: =[2]Apr!$H$1 -> 0 | E8: =SUM(D6:D8) -> 0 | F8: =[2]Apr!$G$1 -> 0 | G8: =SUM(F6:F8) -> 0 | H8: =[3]Apr!$H$1 -> 0 | I8: =SUM(H6:H8) -> 0 | J8: =[3]Apr!$G$1 -> 0 | K8: =SUM(J6:J8) -> 0 | M8: =IF([2]Jul!$G$4>0,[2]Jul!$G$4,0) -> 0
B9: =[1]Admin!$B$26 -> 45869 | C9: =B10 -> 45900 | D9: =[2]May!$H$1 -> 0 | E9: =SUM(D7:D9) -> 0 | F9: =[2]May!$G$1 -> 0 | G9: =SUM(F7:F9) -> 0 | H9: =[3]May!$H$1 -> 0 | I9: =SUM(H7:H9) -> 0 | J9: =[3]May!$G$1 -> 0 | K9: =SUM(J7:J9) -> 0 | M9: =IF([2]Aug!$G$4>0,[2]Aug!$G$4,0) -> 0
B10: =[1]Admin!$B$28 -> 45900 | C10: =B11 -> 45930 | D10: =[2]Jun!$H$1 -> 0 | E10: =SUM(D8:D10) -> 0 | F10: =[2]Jun!$G$1 -> 0 | G10: =SUM(F8:F10) -> 0 | H10: =[3]Jun!$H$1 -> 0 | I10: =SUM(H8:H10) -> 0 | J10: =[3]Jun!$G$1 -> 0 | K10: =SUM(J8:J10) -> 0 | M10: =IF([2]Aug!$G$4>0,[2]Aug!$G$4,0) -> 0
B11: =[1]Admin!$B$30 -> 45930 | C11: =B12 -> 45961 | D11: =[2]Jul!$H$1 -> 0 | E11: =SUM(D9:D11) -> 0 | F11: =[2]Jul!$G$1 -> 0 | G11: =SUM(F9:F11) -> 0 | H11: =[3]Jul!$H$1 -> 0 | I11: =SUM(H9:H11) -> 0 | J11: =[3]Jul!$G$1 -> 0 | K11: =SUM(J9:J11) -> 0 | M11: =IF([2]Apr!$G$4>0,[2]Apr!$G$4,0) -> 0
B12: =[1]Admin!$B$32 -> 45961 | C12: =B13 -> 45991 | D12: =[2]Aug!$H$1 -> 0 | E12: =SUM(D10:D12) -> 0 | F12: =[2]Aug!$G$1 -> 0 | G12: =SUM(F10:F12) -> 0 | H12: =[3]Aug!$H$1 -> 0 | I12: =SUM(H10:H12) -> 0 | J12: =[3]Aug!$G$1 -> 0 | K12: =SUM(J10:J12) -> 0 | M12: =IF([2]Apr!$G$4>0,[2]Apr!$G$4,0) -> 0
B13: =[1]Admin!$B$34 -> 45991 | C13: =B14 -> 46022 | D13: =[2]Apr!$H$1 -> 0 | E13: =SUM(D11:D13) -> 0 | F13: =[2]Apr!$G$1 -> 0 | G13: =SUM(F11:F13) -> 0 | H13: =[3]Apr!$H$1 -> 0 | I13: =SUM(H11:H13) -> 0 | J13: =[3]Apr!$G$1 -> 0 | K13: =SUM(J11:J13) -> 0 | M13: =IF([2]Jun!$G$4>0,[2]Jun!$G$4,0) -> 0
B14: =[1]Admin!$B$36 -> 46022 | C14: =B15 -> 46053 | D14: =[2]May!$H$1 -> 0 | E14: =SUM(D12:D14) -> 0 | F14: =[2]May!$G$1 -> 0 | G14: =SUM(F12:F14) -> 0 | H14: =[3]May!$H$1 -> 0 | I14: =SUM(H12:H14) -> 0 | J14: =[3]May!$G$1 -> 0 | K14: =SUM(J12:J14) -> 0 | M14: =IF([2]Jun!$G$4>0,[2]Jun!$G$4,0) -> 0
B15: =[1]Admin!$B$38 -> 46053 | C15: =B16 -> 46081 | D15: =[2]Jun!$H$1 -> 0 | E15: =SUM(D13:D15) -> 0 | F15: =[2]Jun!$G$1 -> 0 | G15: =SUM(F13:F15) -> 0 | H15: =[3]Jun!$H$1 -> 0 | I15: =SUM(H13:H15) -> 0 | J15: =[3]Jun!$G$1 -> 0 | K15: =SUM(J13:J15) -> 0 | M15: =IF([2]Apr!$G$4>0,[2]Apr!$G$4,0) -> 0
B16: =[1]Admin!$B$40 -> 46081 | C16: =B17 -> 46112 | D16: =[2]Jul!$H$1 -> 0 | E16: =SUM(D14:D16) -> 0 | F16: =[2]Jul!$G$1 -> 0 | G16: =SUM(F14:F16) -> 0 | H16: =[3]Jul!$H$1 -> 0 | I16: =SUM(H14:H16) -> 0 | J16: =[3]Jul!$G$1 -> 0 | K16: =SUM(J14:J16) -> 0 | M16: =IF([2]Apr!$G$4>0,[2]Apr!$G$4,0) -> 0
B17: =[1]Admin!$B$42 -> 46112 | C17: =B18 -> 46142 | D17: =[2]Aug!$H$1 -> 0 | E17: =SUM(D15:D17) -> 0 | F17: =[2]Aug!$G$1 -> 0 | G17: =SUM(F15:F17) -> 0 | H17: =[3]Aug!$H$1 -> 0 | I17: =SUM(H15:H17) -> 0 | J17: =[3]Aug!$G$1 -> 0 | K17: =SUM(J15:J17) -> 0 | M17: =IF([2]Aug!$G$4>0,[2]Aug!$G$4,0) -> 0
B18: =[1]Admin!$B$44 -> 46142 | C18: =B19 -> 46173 | D18: =S04Y2!$H$1 -> 0 | E18: =SUM(D16:D18) -> 0 | F18: =S04Y2!$G$1 -> 0 | G18: =SUM(F16:F18) -> 0 | H18: =P04Y2!$H$1 -> 0 | I18: =SUM(H16:H18) -> 0 | J18: =P04Y2!$G$1 -> 0 | K18: =SUM(J16:J18) -> 0 | M18: =IF([2]Aug!$G$4>0,[2]Aug!$G$4,0) -> 0
B19: =[1]Admin!$B$46 -> 46173 | C19: =[1]Admin!$B$38 -> 46203 | D19: =S05Y2!$H$1 -> 0 | E19: =SUM(D17:D19) -> 0 | F19: =S05Y2!$G$1 -> 0 | G19: =SUM(F17:F19) -> 0 | H19: =P05Y2!$H$1 -> 0 | I19: =SUM(H17:H19) -> 0 | J19: =P05Y2!$G$1 -> 0 | K19: =SUM(J17:J19) -> 0 | M19: =IF([2]Aug!$G$4>0,[2]Aug!$G$4,0) -> 0

Sheet S02Y1
A1: USE FOR VAT PERIODS OUTSIDE FINANCIAL YEAR | D1: Total for Month | F1: =SUM(F5:F500) -> 0 | G1: =SUM(G5:G500) -> 0 | H1: =SUM(H5:H500) -> 0
A2: Sales Date | B2: Customer Name | C2: Sales Invoice Number or reference | D2: Sales Description | F2: Sales Value including Vat | G2: =[2]OpeningDebtors!$G$2 -> 20 | H2: Sales Net of Vat
G3: Vat Output
G4: =[2]OpeningDebtors!$G$4 -> 0
G5: =IF(G$4>0,(IF(F5<>0,F5*G$4/100," ")),IF(F5<>0,F5*G$2/(100+G$2)," ")) | H5: =IF((F5<>0),F5-G5," ")
G6: =IF(G$4>0,(IF(F6<>0,F6*G$4/100," ")),IF(F6<>0,F6*G$2/(100+G$2)," ")) | H6: =IF((F6<>0),F6-G6," ")
G7: =IF(G$4>0,(IF(F7<>0,F7*G$4/100," ")),IF(F7<>0,F7*G$2/(100+G$2)," ")) | H7: =IF((F7<>0),F7-G7," ")
G8: =IF(G$4>0,(IF(F8<>0,F8*G$4/100," ")),IF(F8<>0,F8*G$2/(100+G$2)," ")) | H8: =IF((F8<>0),F8-G8," ")
G9: =IF(G$4>0,(IF(F9<>0,F9*G$4/100," ")),IF(F9<>0,F9*G$2/(100+G$2)," ")) | H9: =IF((F9<>0),F9-G9," ")
G10: =IF(G$4>0,(IF(F10<>0,F10*G$4/100," ")),IF(F10<>0,F10*G$2/(100+G$2)," ")) | H10: =IF((F10<>0),F10-G10," ")
G11: =IF(G$4>0,(IF(F11<>0,F11*G$4/100," ")),IF(F11<>0,F11*G$2/(100+G$2)," ")) | H11: =IF((F11<>0),F11-G11," ")
G12: =IF(G$4>0,(IF(F12<>0,F12*G$4/100," ")),IF(F12<>0,F12*G$2/(100+G$2)," ")) | H12: =IF((F12<>0),F12-G12," ")
G13: =IF(G$4>0,(IF(F13<>0,F13*G$4/100," ")),IF(F13<>0,F13*G$2/(100+G$2)," ")) | H13: =IF((F13<>0),F13-G13," ")
G14: =IF(G$4>0,(IF(F14<>0,F14*G$4/100," ")),IF(F14<>0,F14*G$2/(100+G$2)," ")) | H14: =IF((F14<>0),F14-G14," ")
G15: =IF(G$4>0,(IF(F15<>0,F15*G$4/100," ")),IF(F15<>0,F15*G$2/(100+G$2)," ")) | H15: =IF((F15<>0),F15-G15," ")
G16: =IF(G$4>0,(IF(F16<>0,F16*G$4/100," ")),IF(F16<>0,F16*G$2/(100+G$2)," ")) | H16: =IF((F16<>0),F16-G16," ")
... G200: =IF(G$4>0,(IF(F200<>0,F200*G$4/100," ")),IF(F200<>0,F200*G$2/(100+G$2)," ")) | H200: =IF((F200<>0),F200-G200," ")
A201: Entries below this row are not included in Row 1 Totals

Sheet S03Y1
A1: USE FOR VAT PERIODS OUTSIDE FINANCIAL YEAR | D1: Total for Month | F1: =SUM(F5:F500) -> 0 | G1: =SUM(G5:G500) -> 0 | H1: =SUM(H5:H500) -> 0
A2: Sales Date | B2: Customer Name | C2: Sales Invoice Number or reference | D2: Sales Description | F2: Sales Value including Vat | G2: =[2]OpeningDebtors!$G$2 -> 20 | H2: Sales Net of Vat
G3: Vat Output
G4: =[2]OpeningDebtors!$G$4 -> 0
G5: =IF(G$4>0,(IF(F5<>0,F5*G$4/100," ")),IF(F5<>0,F5*G$2/(100+G$2)," ")) | H5: =IF((F5<>0),F5-G5," ")
G6: =IF(G$4>0,(IF(F6<>0,F6*G$4/100," ")),IF(F6<>0,F6*G$2/(100+G$2)," ")) | H6: =IF((F6<>0),F6-G6," ")
G7: =IF(G$4>0,(IF(F7<>0,F7*G$4/100," ")),IF(F7<>0,F7*G$2/(100+G$2)," ")) | H7: =IF((F7<>0),F7-G7," ")
G8: =IF(G$4>0,(IF(F8<>0,F8*G$4/100," ")),IF(F8<>0,F8*G$2/(100+G$2)," ")) | H8: =IF((F8<>0),F8-G8," ")
G9: =IF(G$4>0,(IF(F9<>0,F9*G$4/100," ")),IF(F9<>0,F9*G$2/(100+G$2)," ")) | H9: =IF((F9<>0),F9-G9," ")
G10: =IF(G$4>0,(IF(F10<>0,F10*G$4/100," ")),IF(F10<>0,F10*G$2/(100+G$2)," ")) | H10: =IF((F10<>0),F10-G10," ")
G11: =IF(G$4>0,(IF(F11<>0,F11*G$4/100," ")),IF(F11<>0,F11*G$2/(100+G$2)," ")) | H11: =IF((F11<>0),F11-G11," ")
G12: =IF(G$4>0,(IF(F12<>0,F12*G$4/100," ")),IF(F12<>0,F12*G$2/(100+G$2)," ")) | H12: =IF((F12<>0),F12-G12," ")
G13: =IF(G$4>0,(IF(F13<>0,F13*G$4/100," ")),IF(F13<>0,F13*G$2/(100+G$2)," ")) | H13: =IF((F13<>0),F13-G13," ")
G14: =IF(G$4>0,(IF(F14<>0,F14*G$4/100," ")),IF(F14<>0,F14*G$2/(100+G$2)," ")) | H14: =IF((F14<>0),F14-G14," ")
G15: =IF(G$4>0,(IF(F15<>0,F15*G$4/100," ")),IF(F15<>0,F15*G$2/(100+G$2)," ")) | H15: =IF((F15<>0),F15-G15," ")
G16: =IF(G$4>0,(IF(F16<>0,F16*G$4/100," ")),IF(F16<>0,F16*G$2/(100+G$2)," ")) | H16: =IF((F16<>0),F16-G16," ")
... G200: =IF(G$4>0,(IF(F200<>0,F200*G$4/100," ")),IF(F200<>0,F200*G$2/(100+G$2)," ")) | H200: =IF((F200<>0),F200-G200," ")
A201: Entries below this row are not included in Row 1 Totals

Sheet S04Y2
A1: USE FOR VAT PERIODS OUTSIDE FINANCIAL YEAR | D1: Total for Month | F1: =SUM(F5:F500) -> 0 | G1: =SUM(G5:G500) -> 0 | H1: =SUM(H5:H500) -> 0
A2: Sales Date | B2: Customer Name | C2: Sales Invoice Number or reference | D2: Sales Description | F2: Sales Value including Vat | G2: =[2]ClosingDebtors!$G$2 -> 20 | H2: Sales Net of Vat
G3: Vat Output
G4: =[2]ClosingDebtors!$G$4 -> 0
G5: =IF(G$4>0,(IF(F5<>0,F5*G$4/100," ")),IF(F5<>0,F5*G$2/(100+G$2)," ")) | H5: =IF((F5<>0),F5-G5," ")
G6: =IF(G$4>0,(IF(F6<>0,F6*G$4/100," ")),IF(F6<>0,F6*G$2/(100+G$2)," ")) | H6: =IF((F6<>0),F6-G6," ")
G7: =IF(G$4>0,(IF(F7<>0,F7*G$4/100," ")),IF(F7<>0,F7*G$2/(100+G$2)," ")) | H7: =IF((F7<>0),F7-G7," ")
G8: =IF(G$4>0,(IF(F8<>0,F8*G$4/100," ")),IF(F8<>0,F8*G$2/(100+G$2)," ")) | H8: =IF((F8<>0),F8-G8," ")
G9: =IF(G$4>0,(IF(F9<>0,F9*G$4/100," ")),IF(F9<>0,F9*G$2/(100+G$2)," ")) | H9: =IF((F9<>0),F9-G9," ")
G10: =IF(G$4>0,(IF(F10<>0,F10*G$4/100," ")),IF(F10<>0,F10*G$2/(100+G$2)," ")) | H10: =IF((F10<>0),F10-G10," ")
G11: =IF(G$4>0,(IF(F11<>0,F11*G$4/100," ")),IF(F11<>0,F11*G$2/(100+G$2)," ")) | H11: =IF((F11<>0),F11-G11," ")
G12: =IF(G$4>0,(IF(F12<>0,F12*G$4/100," ")),IF(F12<>0,F12*G$2/(100+G$2)," ")) | H12: =IF((F12<>0),F12-G12," ")
G13: =IF(G$4>0,(IF(F13<>0,F13*G$4/100," ")),IF(F13<>0,F13*G$2/(100+G$2)," ")) | H13: =IF((F13<>0),F13-G13," ")
G14: =IF(G$4>0,(IF(F14<>0,F14*G$4/100," ")),IF(F14<>0,F14*G$2/(100+G$2)," ")) | H14: =IF((F14<>0),F14-G14," ")
G15: =IF(G$4>0,(IF(F15<>0,F15*G$4/100," ")),IF(F15<>0,F15*G$2/(100+G$2)," ")) | H15: =IF((F15<>0),F15-G15," ")
G16: =IF(G$4>0,(IF(F16<>0,F16*G$4/100," ")),IF(F16<>0,F16*G$2/(100+G$2)," ")) | H16: =IF((F16<>0),F16-G16," ")
... G200: =IF(G$4>0,(IF(F200<>0,F200*G$4/100," ")),IF(F200<>0,F200*G$2/(100+G$2)," ")) | H200: =IF((F200<>0),F200-G200," ")
A201: Entries below this row are not included in Row 1 Totals

Sheet S05Y2
A1: USE FOR VAT PERIODS OUTSIDE FINANCIAL YEAR | D1: Total for Month | F1: =SUM(F5:F500) -> 0 | G1: =SUM(G5:G500) -> 0 | H1: =SUM(H5:H500) -> 0
A2: Sales Date | B2: Customer Name | C2: Sales Invoice Number or reference | D2: Sales Description | F2: Sales Value including Vat | G2: =[2]ClosingDebtors!$G$2 -> 20 | H2: Sales Net of Vat
G3: Vat Output
G4: =[2]ClosingDebtors!$G$4 -> 0
G5: =IF(G$4>0,(IF(F5<>0,F5*G$4/100," ")),IF(F5<>0,F5*G$2/(100+G$2)," ")) | H5: =IF((F5<>0),F5-G5," ")
G6: =IF(G$4>0,(IF(F6<>0,F6*G$4/100," ")),IF(F6<>0,F6*G$2/(100+G$2)," ")) | H6: =IF((F6<>0),F6-G6," ")
G7: =IF(G$4>0,(IF(F7<>0,F7*G$4/100," ")),IF(F7<>0,F7*G$2/(100+G$2)," ")) | H7: =IF((F7<>0),F7-G7," ")
G8: =IF(G$4>0,(IF(F8<>0,F8*G$4/100," ")),IF(F8<>0,F8*G$2/(100+G$2)," ")) | H8: =IF((F8<>0),F8-G8," ")
G9: =IF(G$4>0,(IF(F9<>0,F9*G$4/100," ")),IF(F9<>0,F9*G$2/(100+G$2)," ")) | H9: =IF((F9<>0),F9-G9," ")
G10: =IF(G$4>0,(IF(F10<>0,F10*G$4/100," ")),IF(F10<>0,F10*G$2/(100+G$2)," ")) | H10: =IF((F10<>0),F10-G10," ")
G11: =IF(G$4>0,(IF(F11<>0,F11*G$4/100," ")),IF(F11<>0,F11*G$2/(100+G$2)," ")) | H11: =IF((F11<>0),F11-G11," ")
G12: =IF(G$4>0,(IF(F12<>0,F12*G$4/100," ")),IF(F12<>0,F12*G$2/(100+G$2)," ")) | H12: =IF((F12<>0),F12-G12," ")
G13: =IF(G$4>0,(IF(F13<>0,F13*G$4/100," ")),IF(F13<>0,F13*G$2/(100+G$2)," ")) | H13: =IF((F13<>0),F13-G13," ")
G14: =IF(G$4>0,(IF(F14<>0,F14*G$4/100," ")),IF(F14<>0,F14*G$2/(100+G$2)," ")) | H14: =IF((F14<>0),F14-G14," ")
G15: =IF(G$4>0,(IF(F15<>0,F15*G$4/100," ")),IF(F15<>0,F15*G$2/(100+G$2)," ")) | H15: =IF((F15<>0),F15-G15," ")
G16: =IF(G$4>0,(IF(F16<>0,F16*G$4/100," ")),IF(F16<>0,F16*G$2/(100+G$2)," ")) | H16: =IF((F16<>0),F16-G16," ")
... G200: =IF(G$4>0,(IF(F200<>0,F200*G$4/100," ")),IF(F200<>0,F200*G$2/(100+G$2)," ")) | H200: =IF((F200<>0),F200-G200," ")
A201: Entries below this row are not included in Row 1 Totals

Sheet P02Y1
A1: USE FOR VAT PERIODS OUTSIDE FINANCIAL YEAR | D1: Total for Month | F1: =SUM(F5:F200) -> 0 | G1: =SUM(G5:G200) -> 0 | H1: =SUM(H5:H200) -> 0
A2: Purchase Date | B2: =IF((H1-SUM(O1:AK1)<>0),"COMPLETE EXPENSE ANALYSIS by inserting expense letter in col F","Supplier") -> Supplier | C2: Purchase Invoice Number or Reference | D2: Purchase Description | F2: Total Purchase Value incl Vat | G2: =[3]OpeningCreditors!$G$2 -> 20 | H2: Purchases Net of Vat
G3: Vat Input
G5: =IF(F5<>0,F5*G$2/(100+G$2)," ") | H5: =IF((F5<>0),F5-G5," ")
G6: =IF(F6<>0,F6*G$2/(100+G$2)," ") | H6: =IF((F6<>0),F6-G6," ")
G7: =IF(F7<>0,F7*G$2/(100+G$2)," ") | H7: =IF((F7<>0),F7-G7," ")
G8: =IF(F8<>0,F8*G$2/(100+G$2)," ") | H8: =IF((F8<>0),F8-G8," ")
G9: =IF(F9<>0,F9*G$2/(100+G$2)," ") | H9: =IF((F9<>0),F9-G9," ")
G10: =IF(F10<>0,F10*G$2/(100+G$2)," ") | H10: =IF((F10<>0),F10-G10," ")
G11: =IF(F11<>0,F11*G$2/(100+G$2)," ") | H11: =IF((F11<>0),F11-G11," ")
G12: =IF(F12<>0,F12*G$2/(100+G$2)," ") | H12: =IF((F12<>0),F12-G12," ")
G13: =IF(F13<>0,F13*G$2/(100+G$2)," ") | H13: =IF((F13<>0),F13-G13," ")
G14: =IF(F14<>0,F14*G$2/(100+G$2)," ") | H14: =IF((F14<>0),F14-G14," ")
G15: =IF(G$4="X"," ",IF(F15<>0,F15*G$2/(100+G$2)," ")) | H15: =IF((F15<>0),F15-G15," ")
G16: =IF(G$4="X"," ",IF(F16<>0,F16*G$2/(100+G$2)," ")) | H16: =IF((F16<>0),F16-G16," ")
G17: =IF(G$4="X"," ",IF(F17<>0,F17*G$2/(100+G$2)," ")) | H17: =IF((F17<>0),F17-G17," ")
G18: =IF(G$4="X"," ",IF(F18<>0,F18*G$2/(100+G$2)," ")) | H18: =IF((F18<>0),F18-G18," ")
G19: =IF(G$4="X"," ",IF(F19<>0,F19*G$2/(100+G$2)," ")) | H19: =IF((F19<>0),F19-G19," ")
G20: =IF(G$4="X"," ",IF(F20<>0,F20*G$2/(100+G$2)," ")) | H20: =IF((F20<>0),F20-G20," ")
G21: =IF(G$4="X"," ",IF(F21<>0,F21*G$2/(100+G$2)," ")) | H21: =IF((F21<>0),F21-G21," ")
G22: =IF(G$4="X"," ",IF(F22<>0,F22*G$2/(100+G$2)," ")) | H22: =IF((F22<>0),F22-G22," ")
G23: =IF(G$4="X"," ",IF(F23<>0,F23*G$2/(100+G$2)," ")) | H23: =IF((F23<>0),F23-G23," ")
G24: =IF(G$4="X"," ",IF(F24<>0,F24*G$2/(100+G$2)," ")) | H24: =IF((F24<>0),F24-G24," ")
G25: =IF(G$4="X"," ",IF(F25<>0,F25*G$2/(100+G$2)," ")) | H25: =IF((F25<>0),F25-G25," ")
G26: =IF(G$4="X"," ",IF(F26<>0,F26*G$2/(100+G$2)," ")) | H26: =IF((F26<>0),F26-G26," ")
... G200: =IF(G$4="X"," ",IF(F200<>0,F200*G$2/(100+G$2)," ")) | H200: =IF((F200<>0),F200-G200," ")
A201: Entries below this row are not included in Row 1 Totals | G201: =IF(F201<>0,F201*#REF!/(100+#REF!)," ")

Sheet P03Y1
A1: USE FOR VAT PERIODS OUTSIDE FINANCIAL YEAR | D1: Total for Month | F1: =SUM(F5:F200) -> 0 | G1: =SUM(G5:G200) -> 0 | H1: =SUM(H5:H200) -> 0
A2: Purchase Date | B2: =IF((H1-SUM(O1:AK1)<>0),"COMPLETE EXPENSE ANALYSIS by inserting expense letter in col F","Supplier") -> Supplier | C2: Purchase Invoice Number or Reference | D2: Purchase Description | F2: Total Purchase Value incl Vat | G2: =[3]OpeningCreditors!$G$2 -> 20 | H2: Purchases Net of Vat
G3: Vat Input
G5: =IF(F5<>0,F5*G$2/(100+G$2)," ") | H5: =IF((F5<>0),F5-G5," ")
G6: =IF(F6<>0,F6*G$2/(100+G$2)," ") | H6: =IF((F6<>0),F6-G6," ")
G7: =IF(F7<>0,F7*G$2/(100+G$2)," ") | H7: =IF((F7<>0),F7-G7," ")
G8: =IF(F8<>0,F8*G$2/(100+G$2)," ") | H8: =IF((F8<>0),F8-G8," ")
G9: =IF(F9<>0,F9*G$2/(100+G$2)," ") | H9: =IF((F9<>0),F9-G9," ")
G10: =IF(F10<>0,F10*G$2/(100+G$2)," ") | H10: =IF((F10<>0),F10-G10," ")
G11: =IF(F11<>0,F11*G$2/(100+G$2)," ") | H11: =IF((F11<>0),F11-G11," ")
G12: =IF(F12<>0,F12*G$2/(100+G$2)," ") | H12: =IF((F12<>0),F12-G12," ")
G13: =IF(F13<>0,F13*G$2/(100+G$2)," ") | H13: =IF((F13<>0),F13-G13," ")
G14: =IF(F14<>0,F14*G$2/(100+G$2)," ") | H14: =IF((F14<>0),F14-G14," ")
G15: =IF(G$4="X"," ",IF(F15<>0,F15*G$2/(100+G$2)," ")) | H15: =IF((F15<>0),F15-G15," ")
G16: =IF(G$4="X"," ",IF(F16<>0,F16*G$2/(100+G$2)," ")) | H16: =IF((F16<>0),F16-G16," ")
G17: =IF(G$4="X"," ",IF(F17<>0,F17*G$2/(100+G$2)," ")) | H17: =IF((F17<>0),F17-G17," ")
G18: =IF(G$4="X"," ",IF(F18<>0,F18*G$2/(100+G$2)," ")) | H18: =IF((F18<>0),F18-G18," ")
G19: =IF(G$4="X"," ",IF(F19<>0,F19*G$2/(100+G$2)," ")) | H19: =IF((F19<>0),F19-G19," ")
G20: =IF(G$4="X"," ",IF(F20<>0,F20*G$2/(100+G$2)," ")) | H20: =IF((F20<>0),F20-G20," ")
G21: =IF(G$4="X"," ",IF(F21<>0,F21*G$2/(100+G$2)," ")) | H21: =IF((F21<>0),F21-G21," ")
G22: =IF(G$4="X"," ",IF(F22<>0,F22*G$2/(100+G$2)," ")) | H22: =IF((F22<>0),F22-G22," ")
G23: =IF(G$4="X"," ",IF(F23<>0,F23*G$2/(100+G$2)," ")) | H23: =IF((F23<>0),F23-G23," ")
G24: =IF(G$4="X"," ",IF(F24<>0,F24*G$2/(100+G$2)," ")) | H24: =IF((F24<>0),F24-G24," ")
G25: =IF(G$4="X"," ",IF(F25<>0,F25*G$2/(100+G$2)," ")) | H25: =IF((F25<>0),F25-G25," ")
G26: =IF(G$4="X"," ",IF(F26<>0,F26*G$2/(100+G$2)," ")) | H26: =IF((F26<>0),F26-G26," ")
... G200: =IF(G$4="X"," ",IF(F200<>0,F200*G$2/(100+G$2)," ")) | H200: =IF((F200<>0),F200-G200," ")
A201: Entries below this row are not included in Row 1 Totals | G201: =IF(F201<>0,F201*#REF!/(100+#REF!)," ")

Sheet P04Y2
A1: USE FOR VAT PERIODS OUTSIDE FINANCIAL YEAR | D1: Total for Month | F1: =SUM(F5:F200) -> 0 | G1: =SUM(G5:G200) -> 0 | H1: =SUM(H5:H200) -> 0
A2: Purchase Date | B2: =IF((H1-SUM(O1:AK1)<>0),"COMPLETE EXPENSE ANALYSIS by inserting expense letter in col F","Supplier") -> Supplier | C2: Purchase Invoice Number or Reference | D2: Purchase Description | F2: Total Purchase Value incl Vat | G2: =[3]ClosingCreditors!$G$2 -> 20 | H2: Purchases Net of Vat
G3: Vat Input
G5: =IF(F5<>0,F5*G$2/(100+G$2)," ") | H5: =IF((F5<>0),F5-G5," ")
G6: =IF(F6<>0,F6*G$2/(100+G$2)," ") | H6: =IF((F6<>0),F6-G6," ")
G7: =IF(F7<>0,F7*G$2/(100+G$2)," ") | H7: =IF((F7<>0),F7-G7," ")
G8: =IF(F8<>0,F8*G$2/(100+G$2)," ") | H8: =IF((F8<>0),F8-G8," ")
G9: =IF(F9<>0,F9*G$2/(100+G$2)," ") | H9: =IF((F9<>0),F9-G9," ")
G10: =IF(F10<>0,F10*G$2/(100+G$2)," ") | H10: =IF((F10<>0),F10-G10," ")
G11: =IF(F11<>0,F11*G$2/(100+G$2)," ") | H11: =IF((F11<>0),F11-G11," ")
G12: =IF(F12<>0,F12*G$2/(100+G$2)," ") | H12: =IF((F12<>0),F12-G12," ")
G13: =IF(F13<>0,F13*G$2/(100+G$2)," ") | H13: =IF((F13<>0),F13-G13," ")
G14: =IF(F14<>0,F14*G$2/(100+G$2)," ") | H14: =IF((F14<>0),F14-G14," ")
G15: =IF(G$4="X"," ",IF(F15<>0,F15*G$2/(100+G$2)," ")) | H15: =IF((F15<>0),F15-G15," ")
G16: =IF(G$4="X"," ",IF(F16<>0,F16*G$2/(100+G$2)," ")) | H16: =IF((F16<>0),F16-G16," ")
G17: =IF(G$4="X"," ",IF(F17<>0,F17*G$2/(100+G$2)," ")) | H17: =IF((F17<>0),F17-G17," ")
G18: =IF(G$4="X"," ",IF(F18<>0,F18*G$2/(100+G$2)," ")) | H18: =IF((F18<>0),F18-G18," ")
G19: =IF(G$4="X"," ",IF(F19<>0,F19*G$2/(100+G$2)," ")) | H19: =IF((F19<>0),F19-G19," ")
G20: =IF(G$4="X"," ",IF(F20<>0,F20*G$2/(100+G$2)," ")) | H20: =IF((F20<>0),F20-G20," ")
G21: =IF(G$4="X"," ",IF(F21<>0,F21*G$2/(100+G$2)," ")) | H21: =IF((F21<>0),F21-G21," ")
G22: =IF(G$4="X"," ",IF(F22<>0,F22*G$2/(100+G$2)," ")) | H22: =IF((F22<>0),F22-G22," ")
G23: =IF(G$4="X"," ",IF(F23<>0,F23*G$2/(100+G$2)," ")) | H23: =IF((F23<>0),F23-G23," ")
G24: =IF(G$4="X"," ",IF(F24<>0,F24*G$2/(100+G$2)," ")) | H24: =IF((F24<>0),F24-G24," ")
G25: =IF(G$4="X"," ",IF(F25<>0,F25*G$2/(100+G$2)," ")) | H25: =IF((F25<>0),F25-G25," ")
G26: =IF(G$4="X"," ",IF(F26<>0,F26*G$2/(100+G$2)," ")) | H26: =IF((F26<>0),F26-G26," ")
... G200: =IF(G$4="X"," ",IF(F200<>0,F200*G$2/(100+G$2)," ")) | H200: =IF((F200<>0),F200-G200," ")
A201: Entries below this row are not included in Row 1 Totals | G201: =IF(F201<>0,F201*#REF!/(100+#REF!)," ")

Sheet P05Y2
A1: USE FOR VAT PERIODS OUTSIDE FINANCIAL YEAR | D1: Total for Month | F1: =SUM(F5:F200) -> 0 | G1: =SUM(G5:G200) -> 0 | H1: =SUM(H5:H200) -> 0
A2: Purchase Date | B2: =IF((H1-SUM(O1:AK1)<>0),"COMPLETE EXPENSE ANALYSIS by inserting expense letter in col F","Supplier") -> Supplier | C2: Purchase Invoice Number or Reference | D2: Purchase Description | F2: Total Purchase Value incl Vat | G2: =[3]ClosingCreditors!$G$2 -> 20 | H2: Purchases Net of Vat
G3: Vat Input
G5: =IF(F5<>0,F5*G$2/(100+G$2)," ") | H5: =IF((F5<>0),F5-G5," ")
G6: =IF(F6<>0,F6*G$2/(100+G$2)," ") | H6: =IF((F6<>0),F6-G6," ")
G7: =IF(F7<>0,F7*G$2/(100+G$2)," ") | H7: =IF((F7<>0),F7-G7," ")
G8: =IF(F8<>0,F8*G$2/(100+G$2)," ") | H8: =IF((F8<>0),F8-G8," ")
G9: =IF(F9<>0,F9*G$2/(100+G$2)," ") | H9: =IF((F9<>0),F9-G9," ")
G10: =IF(F10<>0,F10*G$2/(100+G$2)," ") | H10: =IF((F10<>0),F10-G10," ")
G11: =IF(F11<>0,F11*G$2/(100+G$2)," ") | H11: =IF((F11<>0),F11-G11," ")
G12: =IF(F12<>0,F12*G$2/(100+G$2)," ") | H12: =IF((F12<>0),F12-G12," ")
G13: =IF(F13<>0,F13*G$2/(100+G$2)," ") | H13: =IF((F13<>0),F13-G13," ")
G14: =IF(F14<>0,F14*G$2/(100+G$2)," ") | H14: =IF((F14<>0),F14-G14," ")
G15: =IF(G$4="X"," ",IF(F15<>0,F15*G$2/(100+G$2)," ")) | H15: =IF((F15<>0),F15-G15," ")
G16: =IF(G$4="X"," ",IF(F16<>0,F16*G$2/(100+G$2)," ")) | H16: =IF((F16<>0),F16-G16," ")
G17: =IF(G$4="X"," ",IF(F17<>0,F17*G$2/(100+G$2)," ")) | H17: =IF((F17<>0),F17-G17," ")
G18: =IF(G$4="X"," ",IF(F18<>0,F18*G$2/(100+G$2)," ")) | H18: =IF((F18<>0),F18-G18," ")
G19: =IF(G$4="X"," ",IF(F19<>0,F19*G$2/(100+G$2)," ")) | H19: =IF((F19<>0),F19-G19," ")
G20: =IF(G$4="X"," ",IF(F20<>0,F20*G$2/(100+G$2)," ")) | H20: =IF((F20<>0),F20-G20," ")
G21: =IF(G$4="X"," ",IF(F21<>0,F21*G$2/(100+G$2)," ")) | H21: =IF((F21<>0),F21-G21," ")
G22: =IF(G$4="X"," ",IF(F22<>0,F22*G$2/(100+G$2)," ")) | H22: =IF((F22<>0),F22-G22," ")
G23: =IF(G$4="X"," ",IF(F23<>0,F23*G$2/(100+G$2)," ")) | H23: =IF((F23<>0),F23-G23," ")
G24: =IF(G$4="X"," ",IF(F24<>0,F24*G$2/(100+G$2)," ")) | H24: =IF((F24<>0),F24-G24," ")
G25: =IF(G$4="X"," ",IF(F25<>0,F25*G$2/(100+G$2)," ")) | H25: =IF((F25<>0),F25-G25," ")
G26: =IF(G$4="X"," ",IF(F26<>0,F26*G$2/(100+G$2)," ")) | H26: =IF((F26<>0),F26-G26," ")
... G200: =IF(G$4="X"," ",IF(F200<>0,F200*G$2/(100+G$2)," ")) | H200: =IF((F200<>0),F200-G200," ")
A201: Entries below this row are not included in Row 1 Totals | G201: =IF(F201<>0,F201*#REF!/(100+#REF!)," ")
