Workbook

Sheet OpenAccounts
C2: Company Name (including Limited) | J2: Registered Office Address | O2: Tax Reference per CT603 Notice
C3: Company registration number
C4: Telephone number (including STD Code)
C5: First Director's Name | O5: Loss brought forward
C6: Second Director's Name | L6: Postcode | O6: Franked investment income
C8: The principal activity of the company is | K8: If bank interest received Gross e.g. Co-op Enter X
C10: PREVIOUS YEAR BALANCE SHEET | E10: OPENING BALANCE SHEET | G10: Fixed Asset Original Cost | M10: Fixed Asset Accumulated Depreciation
B11: AUDIT CHECK | G11: Land & Buildings | H11: Plant & Machinery | I11: Fixtures & Fittings | J11: Computer Technology | K11: Motor Vehicles | M11: Land & Buildings | N11: Plant & Machinery | O11: Fixtures & Fittings | P11: Computer Technology | Q11: Motor Vehicles
C12: Fixed Assets
B13: =E13-G13-H13-I13-J13-K13+M13+N13+O13+P13+Q13 -> 0 | C13: Tangible assets (note 1)
C14: Current Assets
C15: Stock at cost
C16: Trade Debtors
G17: Current Account | H17: Savings Account | I17: Credit Card Account | J17: Cash Account
B18: =E18-G18-H18-I18-J18 -> 0 | C18: Cash and Bank Balances | K18: Enter all bank balances on this row. Enter accounts overdrawn as negative amounts.
C19: Current Liabilities
C20: Trade Creditors
C21: Net wages due
C22: Wage deductions due
C23: Dividends due
C24: Corporation Tax
G25: HMRC Paye | H25: HMRC Vat | I25: HMRC CIS
B26: =E26-G26-H26-I26 -> 0 | C26: Taxation and Social Security
C28: Long Term Debtors (3-5 years)
C29: Other Creditors
C30: Directors Loan Account
C31: Long Term Creditors (over 1 year)
C32: Capital and Reserves
C33: Called up share capital
C34: Retained Profit and Loss account
C35: Capital Reserves
C37: ACCURACY CHECK | E37: =E13+E15+E16+E18-E20-E21-E22-E23-E24-E26+E28-E30-E31-E33-E34-E35 -> 0
C41: PREVIOUS YEAR PROFIT & LOSS ACCOUNT
C43: Sales Turnover
C44: Investment Grants received
C45: Sales Turnover | G45: =SUM(E43:E44) -> 0
C46: Opening Stock
C47: Purchases
C48: Less Closing Stock | E48: =IF(COUNT(E43:E47,E49:E76,E80:E85)=0,0,E15) -> 0
C49: Sub contractors
C50: Cost of Sales | G50: =E46+E47-E48+E49 -> 0
C52: Gross Profit | G52: =G45-G50 -> 0
C53: Administrative Expenses
C54: Wages and Salaries
C55: Directors Wages
C56: National Insurance
C57: Premises Rent & Rates
C58: Premises Light & Heating
C59: Distribution Transport Costs
C60: Equipment Tools & Plant Hire
C61: Repairs & Maintenance
C62: Consumable Materials
C63: Advertising & Promotion
C64: Telephone Postage & Stationery
... C76: Depreciation
C77: Administrative Expenses | G77: =SUM(E54:E76) -> 0
C79: Operating Profit | G79: =G52-G77 -> 0
C80: Other Income
C81: Profit (Loss) before Tax | G81: =G79+E80 -> 0
C82: Corporation tax
C83: Profit (Loss) after Tax | G83: =G81-E82 -> 0
C84: Dividends
C85: Retained Profit (Loss) for the year | G85: =G83-E84 -> 0
B88: Copyright (C) 2006-2026 DIY Accounting Limited
B89: Licensed under the PolyForm Internal Use License 1.0.0 with an additional grant for accountants. Free to use, source available: https://spreadsheets.diyaccounting.co.uk

Sheet TrialBalance
B1: www.diyaccounting.co.uk | C1: Acct Code Letter | D1: =Admin!B9 -> 45748 | F1: =Admin!B10 -> 45777 | O1: =F1 -> 45777 | Q1: =Admin!B12 -> 45808 | Z1: =Q1 -> 45808 | AB1: =Admin!B14 -> 45838 | AK1: =AB1 -> 45838 | AM1: =Admin!B16 -> 45869 | AV1: =AM1 -> 45869 | AX1: =Admin!B18 -> 45900 | BG1: =AX1 -> 45900 | BI1: =Admin!B20 -> 45930 | BR1: =BI1 -> 45930 | BT1: =Admin!B22 -> 45961 | CC1: =BT1 -> 45961 | CE1: =Admin!B24 -> 45991 | CN1: =CE1 -> 45991 | CP1: =Admin!B26 -> 46022 | CY1: =CP1 -> 46022 | DA1: =Admin!B28 -> 46053 | DJ1: =DA1 -> 46053 | DL1: =Admin!B30 -> 46081 | DU1: =DL1 -> 46081 | DW1: =Admin!B32 -> 46112 | EF1: =DW1 -> 46112 | EH1: Year End Accounting | EJ1: =EF1 -> 46112
B2: AUTOMATED TRIAL BALANCE | D2: Opening Balances | F2: Sales | G2: Purchases | H2: Bank Current | I2: Bank Savings | J2: Credit Card | K2: Cash Account | L2: Wages | M2: Monthly Accrual | O2: Closing Balances | Q2: Sales | R2: Purchases | S2: Bank Current | T2: Bank Savings | U2: Credit Card | V2: Cash Account | W2: Wages | X2: Monthly Accrual | Z2: Closing Balances | AB2: Sales | AC2: Purchases | AD2: Bank Current | AE2: Bank Savings | AF2: Credit Card | AG2: Cash Account | AH2: Wages | AI2: Monthly Accrual | AK2: Closing Balances | AM2: Sales | AN2: Purchases | AO2: Bank Current | AP2: Bank Savings | AQ2: Credit Card | AR2: Cash Account | AS2: Wages | AT2: Monthly Accrual | AV2: Closing Balances | AX2: Sales | AY2: Purchases | AZ2: Bank Current | BA2: Bank Savings | BB2: Credit Card | BC2: Cash Account | BD2: Wages | BE2: Monthly Accrual | BG2: Closing Balances | BI2: Sales | BJ2: Purchases | BK2: Bank Current | BL2: Bank Savings | BM2: Credit Card | BN2: Cash Account | BO2: Wages | BP2: Monthly Accrual | BR2: Closing Balances | BT2: Sales | BU2: Purchases | BV2: Bank Current | BW2: Bank Savings | BX2: Credit Card | BY2: Cash Account | BZ2: Wages | CA2: Monthly Accrual | CC2: Closing Balances | CE2: Sales | CF2: Purchases | CG2: Bank Current | CH2: Bank Savings | CI2: Credit Card | CJ2: Cash Account | CK2: Wages | CL2: Monthly Accrual | CN2: Closing Balances | CP2: Sales | CQ2: Purchases | CR2: Bank Current | CS2: Bank Savings | CT2: Credit Card | CU2: Cash Account | CV2: Wages | CW2: Monthly Accrual | CY2: Closing Balances | DA2: Sales | DB2: Purchases | DC2: Bank Current | DD2: Bank Savings | DE2: Credit Card | DF2: Cash Account | DG2: Wages | DH2: Monthly Accrual | DJ2: Closing Balances | DL2: Sales | DM2: Purchases | DN2: Bank Current | DO2: Bank Savings | DP2: Credit Card | DQ2: Cash Account | DR2: Wages | DS2: Monthly Accrual | DU2: Closing Balances | DW2: Sales | DX2: Purchases | DY2: Bank Current | DZ2: Bank Savings | EA2: Credit Card | EB2: Cash Account | EC2: Wages | ED2: Monthly Accrual | EF2: Closing Balances | EJ2: FINAL Balances
B4: BALANCE SHEET ITEMS
B5: FIXED ASSETS
B6: Fixed Asset Land & Property | C6: FL | D6: =OpenAccounts!G13 -> 0 | O6: =SUM(D6:N6) -> 0 | Z6: =SUM(O6:Y6) -> 0 | AK6: =SUM(Z6:AJ6) -> 0 | AV6: =SUM(AK6:AU6) -> 0 | BG6: =SUM(AV6:BF6) -> 0 | BR6: =SUM(BG6:BQ6) -> 0 | CC6: =SUM(BR6:CB6) -> 0 | CN6: =SUM(CC6:CM6) -> 0 | CY6: =SUM(CN6:CX6) -> 0 | DJ6: =SUM(CY6:DI6) -> 0 | DU6: =SUM(DJ6:DT6) -> 0 | EF6: =SUM(DU6:EE6) -> 0 | EH6: =[1]Schedule!$E$64-([1]Schedule!$W$11+[1]Schedule!$W$64) -> 0 | EJ6: =SUM(EF6:EH6) -> 0
B7: Fixed Asset Plant & Machinery | C7: FP | D7: =OpenAccounts!H13 -> 0 | O7: =SUM(D7:N7) -> 0 | Z7: =SUM(O7:Y7) -> 0 | AK7: =SUM(Z7:AJ7) -> 0 | AV7: =SUM(AK7:AU7) -> 0 | BG7: =SUM(AV7:BF7) -> 0 | BR7: =SUM(BG7:BQ7) -> 0 | CC7: =SUM(BR7:CB7) -> 0 | CN7: =SUM(CC7:CM7) -> 0 | CY7: =SUM(CN7:CX7) -> 0 | DJ7: =SUM(CY7:DI7) -> 0 | DU7: =SUM(DJ7:DT7) -> 0 | EF7: =SUM(DU7:EE7) -> 0 | EH7: =[1]Schedule!$E$75-([1]Schedule!$W$22+[1]Schedule!$W$75) -> 0 | EJ7: =SUM(EF7:EH7) -> 0
B8: Fixed Asset Fixtures & Fittings | C8: FF | D8: =OpenAccounts!I13 -> 0 | O8: =SUM(D8:N8) -> 0 | Z8: =SUM(O8:Y8) -> 0 | AK8: =SUM(Z8:AJ8) -> 0 | AV8: =SUM(AK8:AU8) -> 0 | BG8: =SUM(AV8:BF8) -> 0 | BR8: =SUM(BG8:BQ8) -> 0 | CC8: =SUM(BR8:CB8) -> 0 | CN8: =SUM(CC8:CM8) -> 0 | CY8: =SUM(CN8:CX8) -> 0 | DJ8: =SUM(CY8:DI8) -> 0 | DU8: =SUM(DJ8:DT8) -> 0 | EF8: =SUM(DU8:EE8) -> 0 | EH8: =[1]Schedule!$E$83-([1]Schedule!$W$30+[1]Schedule!$W$83) -> 0 | EJ8: =SUM(EF8:EH8) -> 0
B9: Fixed Asset Computers | C9: FC | D9: =OpenAccounts!J13 -> 0 | O9: =SUM(D9:N9) -> 0 | Z9: =SUM(O9:Y9) -> 0 | AK9: =SUM(Z9:AJ9) -> 0 | AV9: =SUM(AK9:AU9) -> 0 | BG9: =SUM(AV9:BF9) -> 0 | BR9: =SUM(BG9:BQ9) -> 0 | CC9: =SUM(BR9:CB9) -> 0 | CN9: =SUM(CC9:CM9) -> 0 | CY9: =SUM(CN9:CX9) -> 0 | DJ9: =SUM(CY9:DI9) -> 0 | DU9: =SUM(DJ9:DT9) -> 0 | EF9: =SUM(DU9:EE9) -> 0 | EH9: =[1]Schedule!$E$94-([1]Schedule!$W$41+[1]Schedule!$W$94) -> 0 | EJ9: =SUM(EF9:EH9) -> 0
B10: Fixed Asset Motor Vehicles | C10: FM | D10: =OpenAccounts!K13 -> 0 | O10: =SUM(D10:N10) -> 0 | Z10: =SUM(O10:Y10) -> 0 | AK10: =SUM(Z10:AJ10) -> 0 | AV10: =SUM(AK10:AU10) -> 0 | BG10: =SUM(AV10:BF10) -> 0 | BR10: =SUM(BG10:BQ10) -> 0 | CC10: =SUM(BR10:CB10) -> 0 | CN10: =SUM(CC10:CM10) -> 0 | CY10: =SUM(CN10:CX10) -> 0 | DJ10: =SUM(CY10:DI10) -> 0 | DU10: =SUM(DJ10:DT10) -> 0 | EF10: =SUM(DU10:EE10) -> 0 | EH10: =[1]Schedule!$E$108-([1]Schedule!$W$55+[1]Schedule!$W$108) -> 0 | EJ10: =SUM(EF10:EH10) -> 0
B11: Accumulated Depreciation Land & Property | D11: =-OpenAccounts!M13 -> 0 | M11: =-([1]Schedule!$I$11+[1]Schedule!$I$64)/12 -> 0 | O11: =SUM(D11:N11) -> 0 | X11: =-([1]Schedule!$I$11+[1]Schedule!$I$64)/12 -> 0 | Z11: =SUM(O11:Y11) -> 0 | AI11: =-([1]Schedule!$I$11+[1]Schedule!$I$64)/12 -> 0 | AK11: =SUM(Z11:AJ11) -> 0 | AT11: =-([1]Schedule!$I$11+[1]Schedule!$I$64)/12 -> 0 | AV11: =SUM(AK11:AU11) -> 0 | BE11: =-([1]Schedule!$I$11+[1]Schedule!$I$64)/12 -> 0 | BG11: =SUM(AV11:BF11) -> 0 | BP11: =-([1]Schedule!$I$11+[1]Schedule!$I$64)/12 -> 0 | BR11: =SUM(BG11:BQ11) -> 0 | CA11: =-([1]Schedule!$I$11+[1]Schedule!$I$64)/12 -> 0 | CC11: =SUM(BR11:CB11) -> 0 | CL11: =-([1]Schedule!$I$11+[1]Schedule!$I$64)/12 -> 0 | CN11: =SUM(CC11:CM11) -> 0 | CW11: =-([1]Schedule!$I$11+[1]Schedule!$I$64)/12 -> 0 | CY11: =SUM(CN11:CX11) -> 0 | DH11: =-([1]Schedule!$I$11+[1]Schedule!$I$64)/12 -> 0 | DJ11: =SUM(CY11:DI11) -> 0 | DS11: =-([1]Schedule!$I$11+[1]Schedule!$I$64)/12 -> 0 | DU11: =SUM(DJ11:DT11) -> 0 | ED11: =-([1]Schedule!$I$11+[1]Schedule!$I$64)/12 -> 0 | EF11: =SUM(DU11:EE11) -> 0 | EH11: =[1]Schedule!$X$11+[1]Schedule!$X$64 -> 0 | EJ11: =SUM(EF11:EH11) -> 0
B12: Accumulated Depreciation Plant & Machinery | D12: =-OpenAccounts!N13 -> 0 | M12: =-([1]Schedule!$I$22+[1]Schedule!$I$75)/12 -> 0 | O12: =SUM(D12:N12) -> 0 | X12: =-([1]Schedule!$I$22+[1]Schedule!$I$75)/12 -> 0 | Z12: =SUM(O12:Y12) -> 0 | AI12: =-([1]Schedule!$I$22+[1]Schedule!$I$75)/12 -> 0 | AK12: =SUM(Z12:AJ12) -> 0 | AT12: =-([1]Schedule!$I$22+[1]Schedule!$I$75)/12 -> 0 | AV12: =SUM(AK12:AU12) -> 0 | BE12: =-([1]Schedule!$I$22+[1]Schedule!$I$75)/12 -> 0 | BG12: =SUM(AV12:BF12) -> 0 | BP12: =-([1]Schedule!$I$22+[1]Schedule!$I$75)/12 -> 0 | BR12: =SUM(BG12:BQ12) -> 0 | CA12: =-([1]Schedule!$I$22+[1]Schedule!$I$75)/12 -> 0 | CC12: =SUM(BR12:CB12) -> 0 | CL12: =-([1]Schedule!$I$22+[1]Schedule!$I$75)/12 -> 0 | CN12: =SUM(CC12:CM12) -> 0 | CW12: =-([1]Schedule!$I$22+[1]Schedule!$I$75)/12 -> 0 | CY12: =SUM(CN12:CX12) -> 0 | DH12: =-([1]Schedule!$I$22+[1]Schedule!$I$75)/12 -> 0 | DJ12: =SUM(CY12:DI12) -> 0 | DS12: =-([1]Schedule!$I$22+[1]Schedule!$I$75)/12 -> 0 | DU12: =SUM(DJ12:DT12) -> 0 | ED12: =-([1]Schedule!$I$22+[1]Schedule!$I$75)/12 -> 0 | EF12: =SUM(DU12:EE12) -> 0 | EH12: =[1]Schedule!$X$22+[1]Schedule!$X$75 -> 0 | EJ12: =SUM(EF12:EH12) -> 0
B13: Accumulated Depreciation Fixtures & Fittings | D13: =-OpenAccounts!O13 -> 0 | M13: =-([1]Schedule!$I$30+[1]Schedule!$I$83)/12 -> 0 | O13: =SUM(D13:N13) -> 0 | X13: =-([1]Schedule!$I$30+[1]Schedule!$I$83)/12 -> 0 | Z13: =SUM(O13:Y13) -> 0 | AI13: =-([1]Schedule!$I$30+[1]Schedule!$I$83)/12 -> 0 | AK13: =SUM(Z13:AJ13) -> 0 | AT13: =-([1]Schedule!$I$30+[1]Schedule!$I$83)/12 -> 0 | AV13: =SUM(AK13:AU13) -> 0 | BE13: =-([1]Schedule!$I$30+[1]Schedule!$I$83)/12 -> 0 | BG13: =SUM(AV13:BF13) -> 0 | BP13: =-([1]Schedule!$I$30+[1]Schedule!$I$83)/12 -> 0 | BR13: =SUM(BG13:BQ13) -> 0 | CA13: =-([1]Schedule!$I$30+[1]Schedule!$I$83)/12 -> 0 | CC13: =SUM(BR13:CB13) -> 0 | CL13: =-([1]Schedule!$I$30+[1]Schedule!$I$83)/12 -> 0 | CN13: =SUM(CC13:CM13) -> 0 | CW13: =-([1]Schedule!$I$30+[1]Schedule!$I$83)/12 -> 0 | CY13: =SUM(CN13:CX13) -> 0 | DH13: =-([1]Schedule!$I$30+[1]Schedule!$I$83)/12 -> 0 | DJ13: =SUM(CY13:DI13) -> 0 | DS13: =-([1]Schedule!$I$30+[1]Schedule!$I$83)/12 -> 0 | DU13: =SUM(DJ13:DT13) -> 0 | ED13: =-([1]Schedule!$I$30+[1]Schedule!$I$83)/12 -> 0 | EF13: =SUM(DU13:EE13) -> 0 | EH13: =[1]Schedule!$X$30+[1]Schedule!$X$83 -> 0 | EJ13: =SUM(EF13:EH13) -> 0
B14: Accumulated Depreciation Computers | D14: =-OpenAccounts!P13 -> 0 | M14: =-([1]Schedule!$I$41+[1]Schedule!$I$94)/12 -> 0 | O14: =SUM(D14:N14) -> 0 | X14: =-([1]Schedule!$I$41+[1]Schedule!$I$94)/12 -> 0 | Z14: =SUM(O14:Y14) -> 0 | AI14: =-([1]Schedule!$I$41+[1]Schedule!$I$94)/12 -> 0 | AK14: =SUM(Z14:AJ14) -> 0 | AT14: =-([1]Schedule!$I$41+[1]Schedule!$I$94)/12 -> 0 | AV14: =SUM(AK14:AU14) -> 0 | BE14: =-([1]Schedule!$I$41+[1]Schedule!$I$94)/12 -> 0 | BG14: =SUM(AV14:BF14) -> 0 | BP14: =-([1]Schedule!$I$41+[1]Schedule!$I$94)/12 -> 0 | BR14: =SUM(BG14:BQ14) -> 0 | CA14: =-([1]Schedule!$I$41+[1]Schedule!$I$94)/12 -> 0 | CC14: =SUM(BR14:CB14) -> 0 | CL14: =-([1]Schedule!$I$41+[1]Schedule!$I$94)/12 -> 0 | CN14: =SUM(CC14:CM14) -> 0 | CW14: =-([1]Schedule!$I$41+[1]Schedule!$I$94)/12 -> 0 | CY14: =SUM(CN14:CX14) -> 0 | DH14: =-([1]Schedule!$I$41+[1]Schedule!$I$94)/12 -> 0 | DJ14: =SUM(CY14:DI14) -> 0 | DS14: =-([1]Schedule!$I$41+[1]Schedule!$I$94)/12 -> 0 | DU14: =SUM(DJ14:DT14) -> 0 | ED14: =-([1]Schedule!$I$41+[1]Schedule!$I$94)/12 -> 0 | EF14: =SUM(DU14:EE14) -> 0 | EH14: =[1]Schedule!$X$41+[1]Schedule!$X$94 -> 0 | EJ14: =SUM(EF14:EH14) -> 0
B15: Accumulated Depreciation Motor Vehicles | D15: =-OpenAccounts!Q13 -> 0 | M15: =-([1]Schedule!$I$55+[1]Schedule!$I$108)/12 -> 0 | O15: =SUM(D15:N15) -> 0 | X15: =-([1]Schedule!$I$55+[1]Schedule!$I$108)/12 -> 0 | Z15: =SUM(O15:Y15) -> 0 | AI15: =-([1]Schedule!$I$55+[1]Schedule!$I$108)/12 -> 0 | AK15: =SUM(Z15:AJ15) -> 0 | AT15: =-([1]Schedule!$I$55+[1]Schedule!$I$108)/12 -> 0 | AV15: =SUM(AK15:AU15) -> 0 | BE15: =-([1]Schedule!$I$55+[1]Schedule!$I$108)/12 -> 0 | BG15: =SUM(AV15:BF15) -> 0 | BP15: =-([1]Schedule!$I$55+[1]Schedule!$I$108)/12 -> 0 | BR15: =SUM(BG15:BQ15) -> 0 | CA15: =-([1]Schedule!$I$55+[1]Schedule!$I$108)/12 -> 0 | CC15: =SUM(BR15:CB15) -> 0 | CL15: =-([1]Schedule!$I$55+[1]Schedule!$I$108)/12 -> 0 | CN15: =SUM(CC15:CM15) -> 0 | CW15: =-([1]Schedule!$I$55+[1]Schedule!$I$108)/12 -> 0 | CY15: =SUM(CN15:CX15) -> 0 | DH15: =-([1]Schedule!$I$55+[1]Schedule!$I$108)/12 -> 0 | DJ15: =SUM(CY15:DI15) -> 0 | DS15: =-([1]Schedule!$I$55+[1]Schedule!$I$108)/12 -> 0 | DU15: =SUM(DJ15:DT15) -> 0 | ED15: =-([1]Schedule!$I$55+[1]Schedule!$I$108)/12 -> 0 | EF15: =SUM(DU15:EE15) -> 0 | EH15: =[1]Schedule!$X$55+[1]Schedule!$X$108 -> 0 | EJ15: =SUM(EF15:EH15) -> 0
B16: Fixed Asset Additions accrued | G16: =[2]Apr!$AI$1 -> 0 | O16: =SUM(D16:N16) -> 0 | R16: =[2]May!$AI$1 -> 0 | Z16: =SUM(O16:Y16) -> 0 | AC16: =[2]Jun!$AI$1 -> 0 | AK16: =SUM(Z16:AJ16) -> 0 | AN16: =[2]Jul!$AI$1 -> 0 | AV16: =SUM(AK16:AU16) -> 0 | AY16: =[2]Aug!$AI$1 -> 0 | BG16: =SUM(AV16:BF16) -> 0 | BJ16: =[2]Sep!$AI$1 -> 0 | BR16: =SUM(BG16:BQ16) -> 0 | BU16: =[2]Oct!$AI$1 -> 0 | CC16: =SUM(BR16:CB16) -> 0 | CF16: =[2]Nov!$AI$1 -> 0 | CN16: =SUM(CC16:CM16) -> 0 | CQ16: =[2]Dec!$AI$1 -> 0 | CY16: =SUM(CN16:CX16) -> 0 | DB16: =[2]Jan!$AI$1 -> 0 | DJ16: =SUM(CY16:DI16) -> 0 | DM16: =[2]Feb!$AI$1 -> 0 | DU16: =SUM(DJ16:DT16) -> 0 | DX16: =[2]Mar!$AI$1 -> 0 | EF16: =SUM(DU16:EE16) -> 0 | EH16: =-[1]Schedule!$E$110 -> 0 | EJ16: =SUM(EF16:EH16) -> 0
B17: Fixed Asset Disposal Value accrued | C17: FS | F17: =-[3]Apr!$U$1 -> 0 | M17: =-(([1]Schedule!$W$1-[1]Schedule!$X$1-[1]Schedule!$V$1)/12) -> 0 | O17: =SUM(D17:N17) -> 0 | Q17: =-[3]May!$U$1 -> 0 | X17: =-(([1]Schedule!$W$1-[1]Schedule!$X$1-[1]Schedule!$V$1)/12) -> 0 | Z17: =SUM(O17:Y17) -> 0 | AB17: =-[3]Jun!$U$1 -> 0 | AI17: =-(([1]Schedule!$W$1-[1]Schedule!$X$1-[1]Schedule!$V$1)/12) -> 0 | AK17: =SUM(Z17:AJ17) -> 0 | AM17: =-[3]Jul!$U$1 -> 0 | AT17: =-(([1]Schedule!$W$1-[1]Schedule!$X$1-[1]Schedule!$V$1)/12) -> 0 | AV17: =SUM(AK17:AU17) -> 0 | AX17: =-[3]Aug!$U$1 -> 0 | BE17: =-(([1]Schedule!$W$1-[1]Schedule!$X$1-[1]Schedule!$V$1)/12) -> 0 | BG17: =SUM(AV17:BF17) -> 0 | BI17: =-[3]Sep!$U$1 -> 0 | BP17: =-(([1]Schedule!$W$1-[1]Schedule!$X$1-[1]Schedule!$V$1)/12) -> 0 | BR17: =SUM(BG17:BQ17) -> 0 | BT17: =-[3]Oct!$U$1 -> 0 | CA17: =-(([1]Schedule!$W$1-[1]Schedule!$X$1-[1]Schedule!$V$1)/12) -> 0 | CC17: =SUM(BR17:CB17) -> 0 | CE17: =-[3]Nov!$U$1 -> 0 | CL17: =-(([1]Schedule!$W$1-[1]Schedule!$X$1-[1]Schedule!$V$1)/12) -> 0 | CN17: =SUM(CC17:CM17) -> 0 | CP17: =-[3]Dec!$U$1 -> 0 | CW17: =-(([1]Schedule!$W$1-[1]Schedule!$X$1-[1]Schedule!$V$1)/12) -> 0 | CY17: =SUM(CN17:CX17) -> 0 | DA17: =-[3]Jan!$U$1 -> 0 | DH17: =-(([1]Schedule!$W$1-[1]Schedule!$X$1-[1]Schedule!$V$1)/12) -> 0 | DJ17: =SUM(CY17:DI17) -> 0 | DL17: =-[3]Feb!$U$1 -> 0 | DS17: =-(([1]Schedule!$W$1-[1]Schedule!$X$1-[1]Schedule!$V$1)/12) -> 0 | DU17: =SUM(DJ17:DT17) -> 0 | DW17: =-[3]Mar!$U$1 -> 0 | ED17: =-(([1]Schedule!$W$1-[1]Schedule!$X$1-[1]Schedule!$V$1)/12) -> 0 | EF17: =SUM(DU17:EE17) -> 0 | EH17: =[1]Schedule!$W$1-[1]Schedule!$X$1 -> 0 | EJ17: =SUM(EF17:EH17) -> 0
B18: CURRENT ASSETS
B19: Stock | D19: =OpenAccounts!E15 -> 0 | M19: =Stock!$F$8-Stock!$L$8-Stock!$R$8-Stock!$X$8+Stock!$Z$8 -> 0 | O19: =SUM(D19:N19) -> 0 | X19: =Stock!$F$10-Stock!$L$10-Stock!$R$10-Stock!$X$10+Stock!$Z$10 -> 0 | Z19: =SUM(O19:Y19) -> 0 | AI19: =Stock!$F$12-Stock!$L$12-Stock!$R$12-Stock!$X$12+Stock!$Z$12 -> 0 | AK19: =SUM(Z19:AJ19) -> 0 | AT19: =Stock!$F$14-Stock!$L$14-Stock!$R$14-Stock!$X$14+Stock!$Z$14 -> 0 | AV19: =SUM(AK19:AU19) -> 0 | BE19: =Stock!$F$16-Stock!$L$16-Stock!$R$16-Stock!$X$16+Stock!$Z$16 -> 0 | BG19: =SUM(AV19:BF19) -> 0 | BP19: =Stock!$F$18-Stock!$L$18-Stock!$R$18-Stock!$X$18+Stock!$Z$18 -> 0 | BR19: =SUM(BG19:BQ19) -> 0 | CA19: =Stock!$F$20-Stock!$L$20-Stock!$R$20-Stock!$X$20+Stock!$Z$20 -> 0 | CC19: =SUM(BR19:CB19) -> 0 | CL19: =Stock!$F$22-Stock!$L$22-Stock!$R$22-Stock!$X$22+Stock!$Z$22 -> 0 | CN19: =SUM(CC19:CM19) -> 0 | CW19: =Stock!$F$24-Stock!$L$24-Stock!$R$24-Stock!$X$24+Stock!$Z$24 -> 0 | CY19: =SUM(CN19:CX19) -> 0 | DH19: =Stock!$F$26-Stock!$L$26-Stock!$R$26-Stock!$X$26+Stock!$Z$26 -> 0 | DJ19: =SUM(CY19:DI19) -> 0 | DS19: =Stock!$F$28-Stock!$L$28-Stock!$R$28-Stock!$X$28+Stock!$Z$28 -> 0 | DU19: =SUM(DJ19:DT19) -> 0 | ED19: =Stock!$F$30-Stock!$L$30-Stock!$R$30-Stock!$X$30+Stock!$Z$30 -> 0 | EF19: =SUM(DU19:EE19) -> 0 | EJ19: =SUM(EF19:EH19) -> 0
B20: Trade Debtors | C20: DR | D20: =OpenAccounts!E16 -> 0 | F20: =[3]Apr!$F$1-[3]Apr!$V$1 -> 0 | H20: =-[4]Apr!$J$1 -> 0 | I20: =-[5]Apr!$J$1 -> 0 | J20: =-[6]Apr!$J$1 -> 0 | K20: =-[7]Apr!$J$1 -> 0 | O20: =SUM(D20:N20) -> 0 | Q20: =[3]May!$F$1-[3]May!$V$1 -> 0 | S20: =-[4]May!$J$1 -> 0 | T20: =-[5]May!$J$1 -> 0 | U20: =-[6]May!$J$1 -> 0 | V20: =-[7]May!$J$1 -> 0 | Z20: =SUM(O20:Y20) -> 0 | AB20: =[3]Jun!$F$1-[3]Jun!$V$1 -> 0 | AD20: =-[4]Jun!$J$1 -> 0 | AE20: =-[5]Jun!$J$1 -> 0 | AF20: =-[6]Jun!$J$1 -> 0 | AG20: =-[7]Jun!$J$1 -> 0 | AK20: =SUM(Z20:AJ20) -> 0 | AM20: =[3]Jul!$F$1-[3]Jul!$V$1 -> 0 | AO20: =-[4]Jul!$J$1 -> 0 | AP20: =-[5]Jul!$J$1 -> 0 | AQ20: =-[6]Jul!$J$1 -> 0 | AR20: =-[7]Jul!$J$1 -> 0 | AV20: =SUM(AK20:AU20) -> 0 | AX20: =[3]Aug!$F$1-[3]Aug!$V$1 -> 0 | AZ20: =-[4]Aug!$J$1 -> 0 | BA20: =-[5]Aug!$J$1 -> 0 | BB20: =-[6]Aug!$J$1 -> 0 | BC20: =-[7]Aug!$J$1 -> 0 | BG20: =SUM(AV20:BF20) -> 0 | BI20: =[3]Sep!$F$1-[3]Sep!$V$1 -> 0 | BK20: =-[4]Sep!$J$1 -> 0 | BL20: =-[5]Sep!$J$1 -> 0 | BM20: =-[6]Sep!$J$1 -> 0 | BN20: =-[7]Sep!$J$1 -> 0 | BR20: =SUM(BG20:BQ20) -> 0 | BT20: =[3]Oct!$F$1-[3]Oct!$V$1 -> 0 | BV20: =-[4]Oct!$J$1 -> 0 | BW20: =-[5]Oct!$J$1 -> 0 | BX20: =-[6]Oct!$J$1 -> 0 | BY20: =-[7]Oct!$J$1 -> 0 | CC20: =SUM(BR20:CB20) -> 0 | CE20: =[3]Nov!$F$1-[3]Nov!$V$1 -> 0 | CG20: =-[4]Nov!$J$1 -> 0 | CH20: =-[5]Nov!$J$1 -> 0 | CI20: =-[6]Nov!$J$1 -> 0 | CJ20: =-[7]Nov!$J$1 -> 0 | CN20: =SUM(CC20:CM20) -> 0 | CP20: =[3]Dec!$F$1-[3]Dec!$V$1 -> 0 | CR20: =-[4]Dec!$J$1 -> 0 | CS20: =-[5]Dec!$J$1 -> 0 | CT20: =-[6]Dec!$J$1 -> 0 | CU20: =-[7]Dec!$J$1 -> 0 | CY20: =SUM(CN20:CX20) -> 0 | DA20: =[3]Jan!$F$1-[3]Jan!$V$1 -> 0 | DC20: =-[4]Jan!$J$1 -> 0 | DD20: =-[5]Jan!$J$1 -> 0 | DE20: =-[6]Jan!$J$1 -> 0 | DF20: =-[7]Jan!$J$1 -> 0 | DJ20: =SUM(CY20:DI20) -> 0 | DL20: =[3]Feb!$F$1-[3]Feb!$V$1 -> 0 | DN20: =-[4]Feb!$J$1 -> 0 | DO20: =-[5]Feb!$J$1 -> 0 | DP20: =-[6]Feb!$J$1 -> 0 | DQ20: =-[7]Feb!$J$1 -> 0 | DU20: =SUM(DJ20:DT20) -> 0 | DW20: =[3]Mar!$F$1-[3]Mar!$V$1 -> 0 | DY20: =-[4]Mar!$J$1 -> 0 | DZ20: =-[5]Mar!$J$1 -> 0 | EA20: =-[6]Mar!$J$1 -> 0 | EB20: =-[7]Mar!$J$1 -> 0 | EF20: =SUM(DU20:EE20) -> 0 | EJ20: =SUM(EF20:EH20) -> 0
B21: Cash & Bank Receipts
B22: Bank Current Account | C22: BB | D22: =OpenAccounts!G18 -> 0 | H22: =[4]Apr!$F$1-[4]Apr!$X$1 -> 0 | O22: =SUM(D22:N22) -> 0 | S22: =[4]May!$F$1-[4]May!$X$1 -> 0 | Z22: =SUM(O22:Y22) -> 0 | AD22: =[4]Jun!$F$1-[4]Jun!$X$1 -> 0 | AK22: =SUM(Z22:AJ22) -> 0 | AO22: =[4]Jul!$F$1-[4]Jul!$X$1 -> 0 | AV22: =SUM(AK22:AU22) -> 0 | AZ22: =[4]Aug!$F$1-[4]Aug!$X$1 -> 0 | BG22: =SUM(AV22:BF22) -> 0 | BK22: =[4]Sep!$F$1-[4]Sep!$X$1 -> 0 | BR22: =SUM(BG22:BQ22) -> 0 | BV22: =[4]Oct!$F$1-[4]Oct!$X$1 -> 0 | CC22: =SUM(BR22:CB22) -> 0 | CG22: =[4]Nov!$F$1-[4]Nov!$X$1 -> 0 | CN22: =SUM(CC22:CM22) -> 0 | CR22: =[4]Dec!$F$1-[4]Dec!$X$1 -> 0 | CY22: =SUM(CN22:CX22) -> 0 | DC22: =[4]Jan!$F$1-[4]Jan!$X$1 -> 0 | DJ22: =SUM(CY22:DI22) -> 0 | DN22: =[4]Feb!$F$1-[4]Feb!$X$1 -> 0 | DU22: =SUM(DJ22:DT22) -> 0 | DY22: =[4]Mar!$F$1-[4]Mar!$X$1 -> 0 | EF22: =SUM(DU22:EE22) -> 0 | EJ22: =SUM(EF22:EH22) -> 0
B23: Bank Savings Account | C23: BS | D23: =OpenAccounts!H18 -> 0 | I23: =[5]Apr!$F$1-[5]Apr!$X$1 -> 0 | O23: =SUM(D23:N23) -> 0 | T23: =[5]May!$F$1-[5]May!$X$1 -> 0 | Z23: =SUM(O23:Y23) -> 0 | AE23: =[5]Jun!$F$1-[5]Jun!$X$1 -> 0 | AK23: =SUM(Z23:AJ23) -> 0 | AP23: =[5]Jul!$F$1-[5]Jul!$X$1 -> 0 | AV23: =SUM(AK23:AU23) -> 0 | BA23: =[5]Aug!$F$1-[5]Aug!$X$1 -> 0 | BG23: =SUM(AV23:BF23) -> 0 | BL23: =[5]Sep!$F$1-[5]Sep!$X$1 -> 0 | BR23: =SUM(BG23:BQ23) -> 0 | BW23: =[5]Oct!$F$1-[5]Oct!$X$1 -> 0 | CC23: =SUM(BR23:CB23) -> 0 | CH23: =[5]Nov!$F$1-[5]Nov!$X$1 -> 0 | CN23: =SUM(CC23:CM23) -> 0 | CS23: =[5]Dec!$F$1-[5]Dec!$X$1 -> 0 | CY23: =SUM(CN23:CX23) -> 0 | DD23: =[5]Jan!$F$1-[5]Jan!$X$1 -> 0 | DJ23: =SUM(CY23:DI23) -> 0 | DO23: =[5]Feb!$F$1-[5]Feb!$X$1 -> 0 | DU23: =SUM(DJ23:DT23) -> 0 | DZ23: =[5]Mar!$F$1-[5]Mar!$X$1 -> 0 | EF23: =SUM(DU23:EE23) -> 0 | EJ23: =SUM(EF23:EH23) -> 0
B24: Credit Card Account | C24: BD | D24: =OpenAccounts!I18 -> 0 | J24: =[6]Apr!$F$1-[6]Apr!$X$1 -> 0 | O24: =SUM(D24:N24) -> 0 | U24: =[6]May!$F$1-[6]May!$X$1 -> 0 | Z24: =SUM(O24:Y24) -> 0 | AF24: =[6]Jun!$F$1-[6]Jun!$X$1 -> 0 | AK24: =SUM(Z24:AJ24) -> 0 | AQ24: =[6]Jul!$F$1-[6]Jul!$X$1 -> 0 | AV24: =SUM(AK24:AU24) -> 0 | BB24: =[6]Aug!$F$1-[6]Aug!$X$1 -> 0 | BG24: =SUM(AV24:BF24) -> 0 | BM24: =[6]Sep!$F$1-[6]Sep!$X$1 -> 0 | BR24: =SUM(BG24:BQ24) -> 0 | BX24: =[6]Oct!$F$1-[6]Oct!$X$1 -> 0 | CC24: =SUM(BR24:CB24) -> 0 | CI24: =[6]Nov!$F$1-[6]Nov!$X$1 -> 0 | CN24: =SUM(CC24:CM24) -> 0 | CT24: =[6]Dec!$F$1-[6]Dec!$X$1 -> 0 | CY24: =SUM(CN24:CX24) -> 0 | DE24: =[6]Jan!$F$1-[6]Jan!$X$1 -> 0 | DJ24: =SUM(CY24:DI24) -> 0 | DP24: =[6]Feb!$F$1-[6]Feb!$X$1 -> 0 | DU24: =SUM(DJ24:DT24) -> 0 | EA24: =[6]Mar!$F$1-[6]Mar!$X$1 -> 0 | EF24: =SUM(DU24:EE24) -> 0 | EJ24: =SUM(EF24:EH24) -> 0
B25: Cash Account | C25: BC | D25: =OpenAccounts!J18 -> 0 | K25: =[7]Apr!$F$1-[7]Apr!$U$1 -> 0 | O25: =SUM(D25:N25) -> 0 | V25: =[7]May!$F$1-[7]May!$U$1 -> 0 | Z25: =SUM(O25:Y25) -> 0 | AG25: =[7]Jun!$F$1-[7]Jun!$U$1 -> 0 | AK25: =SUM(Z25:AJ25) -> 0 | AR25: =[7]Jul!$F$1-[7]Jul!$U$1 -> 0 | AV25: =SUM(AK25:AU25) -> 0 | BC25: =[7]Aug!$F$1-[7]Aug!$U$1 -> 0 | BG25: =SUM(AV25:BF25) -> 0 | BN25: =[7]Sep!$F$1-[7]Sep!$U$1 -> 0 | BR25: =SUM(BG25:BQ25) -> 0 | BY25: =[7]Oct!$F$1-[7]Oct!$U$1 -> 0 | CC25: =SUM(BR25:CB25) -> 0 | CJ25: =[7]Nov!$F$1-[7]Nov!$U$1 -> 0 | CN25: =SUM(CC25:CM25) -> 0 | CU25: =[7]Dec!$F$1-[7]Dec!$U$1 -> 0 | CY25: =SUM(CN25:CX25) -> 0 | DF25: =[7]Jan!$F$1-[7]Jan!$U$1 -> 0 | DJ25: =SUM(CY25:DI25) -> 0 | DQ25: =[7]Feb!$F$1-[7]Feb!$U$1 -> 0 | DU25: =SUM(DJ25:DT25) -> 0 | EB25: =[7]Mar!$F$1-[7]Mar!$U$1 -> 0 | EF25: =SUM(DU25:EE25) -> 0 | EH25: =[8]Boardmeeting!$E$6 -> 0 | EJ25: =SUM(EF25:EH25) -> 0
B26: Intra Cash & Bank Transfers | D26: 0 | H26: =-[4]Apr!$G$1-[4]Apr!$H$1-[4]Apr!$I$1+[4]Apr!$Y$1+[4]Apr!$Z$1+[4]Apr!$AA$1 -> 0 | I26: =-[5]Apr!$G$1-[5]Apr!$H$1-[5]Apr!$I$1+[5]Apr!$Y$1+[5]Apr!$Z$1+[5]Apr!$AA$1 -> 0 | J26: =-[6]Apr!$G$1-[6]Apr!$H$1-[6]Apr!$I$1+[6]Apr!$Y$1+[6]Apr!$Z$1+[6]Apr!$AA$1 -> 0 | K26: =-[7]Apr!$G$1-[7]Apr!$H$1-[7]Apr!$I$1+[7]Apr!$V$1+[7]Apr!$W$1+[7]Apr!$X$1 -> 0 | O26: =SUM(D26:N26) -> 0 | S26: =-[4]May!$G$1-[4]May!$H$1-[4]May!$I$1+[4]May!$Y$1+[4]May!$Z$1+[4]May!$AA$1 -> 0 | T26: =-[5]May!$G$1-[5]May!$H$1-[5]May!$I$1+[5]May!$Y$1+[5]May!$Z$1+[5]May!$AA$1 -> 0 | U26: =-[6]May!$G$1-[6]May!$H$1-[6]May!$I$1+[6]May!$Y$1+[6]May!$Z$1+[6]May!$AA$1 -> 0 | V26: =-[7]May!$G$1-[7]May!$H$1-[7]May!$I$1+[7]May!$V$1+[7]May!$W$1+[7]May!$X$1 -> 0 | Z26: =SUM(O26:Y26) -> 0 | AD26: =-[4]Jun!$G$1-[4]Jun!$H$1-[4]Jun!$I$1+[4]Jun!$Y$1+[4]Jun!$Z$1+[4]Jun!$AA$1 -> 0 | AE26: =-[5]Jun!$G$1-[5]Jun!$H$1-[5]Jun!$I$1+[5]Jun!$Y$1+[5]Jun!$Z$1+[5]Jun!$AA$1 -> 0 | AF26: =-[6]Jun!$G$1-[6]Jun!$H$1-[6]Jun!$I$1+[6]Jun!$Y$1+[6]Jun!$Z$1+[6]Jun!$AA$1 -> 0 | AG26: =-[7]Jun!$G$1-[7]Jun!$H$1-[7]Jun!$I$1+[7]Jun!$V$1+[7]Jun!$W$1+[7]Jun!$X$1 -> 0 | AK26: =SUM(Z26:AJ26) -> 0 | AO26: =-[4]Jul!$G$1-[4]Jul!$H$1-[4]Jul!$I$1+[4]Jul!$Y$1+[4]Jul!$Z$1+[4]Jul!$AA$1 -> 0 | AP26: =-[5]Jul!$G$1-[5]Jul!$H$1-[5]Jul!$I$1+[5]Jul!$Y$1+[5]Jul!$Z$1+[5]Jul!$AA$1 -> 0 | AQ26: =-[6]Jul!$G$1-[6]Jul!$H$1-[6]Jul!$I$1+[6]Jul!$Y$1+[6]Jul!$Z$1+[6]Jul!$AA$1 -> 0 | AR26: =-[7]Jul!$G$1-[7]Jul!$H$1-[7]Jul!$I$1+[7]Jul!$V$1+[7]Jul!$W$1+[7]Jul!$X$1 -> 0 | AV26: =SUM(AK26:AU26) -> 0 | AZ26: =-[4]Aug!$G$1-[4]Aug!$H$1-[4]Aug!$I$1+[4]Aug!$Y$1+[4]Aug!$Z$1+[4]Aug!$AA$1 -> 0 | BA26: =-[5]Aug!$G$1-[5]Aug!$H$1-[5]Aug!$I$1+[5]Aug!$Y$1+[5]Aug!$Z$1+[5]Aug!$AA$1 -> 0 | BB26: =-[6]Aug!$G$1-[6]Aug!$H$1-[6]Aug!$I$1+[6]Aug!$Y$1+[6]Aug!$Z$1+[6]Aug!$AA$1 -> 0 | BC26: =-[7]Aug!$G$1-[7]Aug!$H$1-[7]Aug!$I$1+[7]Aug!$V$1+[7]Aug!$W$1+[7]Aug!$X$1 -> 0 | BG26: =SUM(AV26:BF26) -> 0 | BK26: =-[4]Sep!$G$1-[4]Sep!$H$1-[4]Sep!$I$1+[4]Sep!$Y$1+[4]Sep!$Z$1+[4]Sep!$AA$1 -> 0 | BL26: =-[5]Sep!$G$1-[5]Sep!$H$1-[5]Sep!$I$1+[5]Sep!$Y$1+[5]Sep!$Z$1+[5]Sep!$AA$1 -> 0 | BM26: =-[6]Sep!$G$1-[6]Sep!$H$1-[6]Sep!$I$1+[6]Sep!$Y$1+[6]Sep!$Z$1+[6]Sep!$AA$1 -> 0 | BN26: =-[7]Sep!$G$1-[7]Sep!$H$1-[7]Sep!$I$1+[7]Sep!$V$1+[7]Sep!$W$1+[7]Sep!$X$1 -> 0 | BR26: =SUM(BG26:BQ26) -> 0 | BV26: =-[4]Oct!$G$1-[4]Oct!$H$1-[4]Oct!$I$1+[4]Oct!$Y$1+[4]Oct!$Z$1+[4]Oct!$AA$1 -> 0 | BW26: =-[5]Oct!$G$1-[5]Oct!$H$1-[5]Oct!$I$1+[5]Oct!$Y$1+[5]Oct!$Z$1+[5]Oct!$AA$1 -> 0 | BX26: =-[6]Oct!$G$1-[6]Oct!$H$1-[6]Oct!$I$1+[6]Oct!$Y$1+[6]Oct!$Z$1+[6]Oct!$AA$1 -> 0 | BY26: =-[7]Oct!$G$1-[7]Oct!$H$1-[7]Oct!$I$1+[7]Oct!$V$1+[7]Oct!$W$1+[7]Oct!$X$1 -> 0 | CC26: =SUM(BR26:CB26) -> 0 | CG26: =-[4]Nov!$G$1-[4]Nov!$H$1-[4]Nov!$I$1+[4]Nov!$Y$1+[4]Nov!$Z$1+[4]Nov!$AA$1 -> 0 | CH26: =-[5]Nov!$G$1-[5]Nov!$H$1-[5]Nov!$I$1+[5]Nov!$Y$1+[5]Nov!$Z$1+[5]Nov!$AA$1 -> 0 | CI26: =-[6]Nov!$G$1-[6]Nov!$H$1-[6]Nov!$I$1+[6]Nov!$Y$1+[6]Nov!$Z$1+[6]Nov!$AA$1 -> 0 | CJ26: =-[7]Nov!$G$1-[7]Nov!$H$1-[7]Nov!$I$1+[7]Nov!$V$1+[7]Nov!$W$1+[7]Nov!$X$1 -> 0 | CN26: =SUM(CC26:CM26) -> 0 | CR26: =-[4]Dec!$G$1-[4]Dec!$H$1-[4]Dec!$I$1+[4]Dec!$Y$1+[4]Dec!$Z$1+[4]Dec!$AA$1 -> 0 | CS26: =-[5]Dec!$G$1-[5]Dec!$H$1-[5]Dec!$I$1+[5]Dec!$Y$1+[5]Dec!$Z$1+[5]Dec!$AA$1 -> 0 | CT26: =-[6]Dec!$G$1-[6]Dec!$H$1-[6]Dec!$I$1+[6]Dec!$Y$1+[6]Dec!$Z$1+[6]Dec!$AA$1 -> 0 | CU26: =-[7]Dec!$G$1-[7]Dec!$H$1-[7]Dec!$I$1+[7]Dec!$V$1+[7]Dec!$W$1+[7]Dec!$X$1 -> 0 | CY26: =SUM(CN26:CX26) -> 0 | DC26: =-[4]Jan!$G$1-[4]Jan!$H$1-[4]Jan!$I$1+[4]Jan!$Y$1+[4]Jan!$Z$1+[4]Jan!$AA$1 -> 0 | DD26: =-[5]Jan!$G$1-[5]Jan!$H$1-[5]Jan!$I$1+[5]Jan!$Y$1+[5]Jan!$Z$1+[5]Jan!$AA$1 -> 0 | DE26: =-[6]Jan!$G$1-[6]Jan!$H$1-[6]Jan!$I$1+[6]Jan!$Y$1+[6]Jan!$Z$1+[6]Jan!$AA$1 -> 0 | DF26: =-[7]Jan!$G$1-[7]Jan!$H$1-[7]Jan!$I$1+[7]Jan!$V$1+[7]Jan!$W$1+[7]Jan!$X$1 -> 0 | DJ26: =SUM(CY26:DI26) -> 0 | DN26: =-[4]Feb!$G$1-[4]Feb!$H$1-[4]Feb!$I$1+[4]Feb!$Y$1+[4]Feb!$Z$1+[4]Feb!$AA$1 -> 0 | DO26: =-[5]Feb!$G$1-[5]Feb!$H$1-[5]Feb!$I$1+[5]Feb!$Y$1+[5]Feb!$Z$1+[5]Feb!$AA$1 -> 0 | DP26: =-[6]Feb!$G$1-[6]Feb!$H$1-[6]Feb!$I$1+[6]Feb!$Y$1+[6]Feb!$Z$1+[6]Feb!$AA$1 -> 0 | DQ26: =-[7]Feb!$G$1-[7]Feb!$H$1-[7]Feb!$I$1+[7]Feb!$V$1+[7]Feb!$W$1+[7]Feb!$X$1 -> 0 | DU26: =SUM(DJ26:DT26) -> 0 | DY26: =-[4]Mar!$G$1-[4]Mar!$H$1-[4]Mar!$I$1+[4]Mar!$Y$1+[4]Mar!$Z$1+[4]Mar!$AA$1 -> 0 | DZ26: =-[5]Mar!$G$1-[5]Mar!$H$1-[5]Mar!$I$1+[5]Mar!$Y$1+[5]Mar!$Z$1+[5]Mar!$AA$1 -> 0 | EA26: =-[6]Mar!$G$1-[6]Mar!$H$1-[6]Mar!$I$1+[6]Mar!$Y$1+[6]Mar!$Z$1+[6]Mar!$AA$1 -> 0 | EB26: =-[7]Mar!$G$1-[7]Mar!$H$1-[7]Mar!$I$1+[7]Mar!$V$1+[7]Mar!$W$1+[7]Mar!$X$1 -> 0 | EF26: =SUM(DU26:EE26) -> 0 | EJ26: =SUM(EF26:EH26) -> 0
B27: CURRENT LIABILITIES
B28: Trade Creditors | C28: CR | D28: =-OpenAccounts!E20 -> 0 | G28: =-[2]Apr!$F$1+[2]Apr!$AK$1 -> 0 | H28: =[4]Apr!$AB$1 -> 0 | I28: =[5]Apr!$AB$1 -> 0 | J28: =[6]Apr!$AB$1 -> 0 | K28: =[7]Apr!$Y$1 -> 0 | O28: =SUM(D28:N28) -> 0 | R28: =-[2]May!$F$1+[2]May!$AK$1 -> 0 | S28: =[4]May!$AB$1 -> 0 | T28: =[5]May!$AB$1 -> 0 | U28: =[6]May!$AB$1 -> 0 | V28: =[7]May!$Y$1 -> 0 | Z28: =SUM(O28:Y28) -> 0 | AC28: =-[2]Jun!$F$1+[2]Jun!$AK$1 -> 0 | AD28: =[4]Jun!$AB$1 -> 0 | AE28: =[5]Jun!$AB$1 -> 0 | AF28: =[6]Jun!$AB$1 -> 0 | AG28: =[7]Jun!$Y$1 -> 0 | AK28: =SUM(Z28:AJ28) -> 0 | AN28: =-[2]Jul!$F$1+[2]Jul!$AK$1 -> 0 | AO28: =[4]Jul!$AB$1 -> 0 | AP28: =[5]Jul!$AB$1 -> 0 | AQ28: =[6]Jul!$AB$1 -> 0 | AR28: =[7]Jul!$Y$1 -> 0 | AV28: =SUM(AK28:AU28) -> 0 | AY28: =-[2]Aug!$F$1+[2]Aug!$AK$1 -> 0 | AZ28: =[4]Aug!$AB$1 -> 0 | BA28: =[5]Aug!$AB$1 -> 0 | BB28: =[6]Aug!$AB$1 -> 0 | BC28: =[7]Aug!$Y$1 -> 0 | BG28: =SUM(AV28:BF28) -> 0 | BJ28: =-[2]Sep!$F$1+[2]Sep!$AK$1 -> 0 | BK28: =[4]Sep!$AB$1 -> 0 | BL28: =[5]Sep!$AB$1 -> 0 | BM28: =[6]Sep!$AB$1 -> 0 | BN28: =[7]Sep!$Y$1 -> 0 | BR28: =SUM(BG28:BQ28) -> 0 | BU28: =-[2]Oct!$F$1+[2]Oct!$AK$1 -> 0 | BV28: =[4]Oct!$AB$1 -> 0 | BW28: =[5]Oct!$AB$1 -> 0 | BX28: =[6]Oct!$AB$1 -> 0 | BY28: =[7]Oct!$Y$1 -> 0 | CC28: =SUM(BR28:CB28) -> 0 | CF28: =-[2]Nov!$F$1+[2]Nov!$AK$1 -> 0 | CG28: =[4]Nov!$AB$1 -> 0 | CH28: =[5]Nov!$AB$1 -> 0 | CI28: =[6]Nov!$AB$1 -> 0 | CJ28: =[7]Nov!$Y$1 -> 0 | CN28: =SUM(CC28:CM28) -> 0 | CQ28: =-[2]Dec!$F$1+[2]Dec!$AK$1 -> 0 | CR28: =[4]Dec!$AB$1 -> 0 | CS28: =[5]Dec!$AB$1 -> 0 | CT28: =[6]Dec!$AB$1 -> 0 | CU28: =[7]Dec!$Y$1 -> 0 | CY28: =SUM(CN28:CX28) -> 0 | DB28: =-[2]Jan!$F$1+[2]Jan!$AK$1 -> 0 | DC28: =[4]Jan!$AB$1 -> 0 | DD28: =[5]Jan!$AB$1 -> 0 | DE28: =[6]Jan!$AB$1 -> 0 | DF28: =[7]Jan!$Y$1 -> 0 | DJ28: =SUM(CY28:DI28) -> 0 | DM28: =-[2]Feb!$F$1+[2]Feb!$AK$1 -> 0 | DN28: =[4]Feb!$AB$1 -> 0 | DO28: =[5]Feb!$AB$1 -> 0 | DP28: =[6]Feb!$AB$1 -> 0 | DQ28: =[7]Feb!$Y$1 -> 0 | DU28: =SUM(DJ28:DT28) -> 0 | DX28: =-[2]Mar!$F$1+[2]Mar!$AK$1 -> 0 | DY28: =[4]Mar!$AB$1 -> 0 | DZ28: =[5]Mar!$AB$1 -> 0 | EA28: =[6]Mar!$AB$1 -> 0 | EB28: =[7]Mar!$Y$1 -> 0 | EF28: =SUM(DU28:EE28) -> 0 | EH28: =[1]HPfinance!$E$2 -> 0 | EJ28: =SUM(EF28:EH28) -> 0
B29: Net Wages Creditor | D29: =-OpenAccounts!E21 -> 0 | H29: =[4]Apr!$AC$1 -> 0 | I29: =[5]Apr!$AC$1 -> 0 | J29: =[6]Apr!$AC$1 -> 0 | K29: =[7]Apr!$Z$1 -> 0 | L29: =-WagesInterface!G4-WagesInterface!G17 -> 0 | O29: =SUM(D29:N29) -> 0 | S29: =[4]May!$AC$1 -> 0 | T29: =[5]May!$AC$1 -> 0 | U29: =[6]May!$AC$1 -> 0 | V29: =[7]May!$Z$1 -> 0 | W29: =-WagesInterface!G5-WagesInterface!G18 -> 0 | Z29: =SUM(O29:Y29) -> 0 | AD29: =[4]Jun!$AC$1 -> 0 | AE29: =[5]Jun!$AC$1 -> 0 | AF29: =[6]Jun!$AC$1 -> 0 | AG29: =[7]Jun!$Z$1 -> 0 | AH29: =-WagesInterface!G6-WagesInterface!G19 -> 0 | AK29: =SUM(Z29:AJ29) -> 0 | AO29: =[4]Jul!$AC$1 -> 0 | AP29: =[5]Jul!$AC$1 -> 0 | AQ29: =[6]Jul!$AC$1 -> 0 | AR29: =[7]Jul!$Z$1 -> 0 | AS29: =-WagesInterface!G7-WagesInterface!G20 -> 0 | AV29: =SUM(AK29:AU29) -> 0 | AZ29: =[4]Aug!$AC$1 -> 0 | BA29: =[5]Aug!$AC$1 -> 0 | BB29: =[6]Aug!$AC$1 -> 0 | BC29: =[7]Aug!$Z$1 -> 0 | BD29: =-WagesInterface!G8-WagesInterface!G21 -> 0 | BG29: =SUM(AV29:BF29) -> 0 | BK29: =[4]Sep!$AC$1 -> 0 | BL29: =[5]Sep!$AC$1 -> 0 | BM29: =[6]Sep!$AC$1 -> 0 | BN29: =[7]Sep!$Z$1 -> 0 | BO29: =-WagesInterface!G9-WagesInterface!G22 -> 0 | BR29: =SUM(BG29:BQ29) -> 0 | BV29: =[4]Oct!$AC$1 -> 0 | BW29: =[5]Oct!$AC$1 -> 0 | BX29: =[6]Oct!$AC$1 -> 0 | BY29: =[7]Oct!$Z$1 -> 0 | BZ29: =-WagesInterface!G10-WagesInterface!G23 -> 0 | CC29: =SUM(BR29:CB29) -> 0 | CG29: =[4]Nov!$AC$1 -> 0 | CH29: =[5]Nov!$AC$1 -> 0 | CI29: =[6]Nov!$AC$1 -> 0 | CJ29: =[7]Nov!$Z$1 -> 0 | CK29: =-WagesInterface!G11-WagesInterface!G24 -> 0 | CN29: =SUM(CC29:CM29) -> 0 | CR29: =[4]Dec!$AC$1 -> 0 | CS29: =[5]Dec!$AC$1 -> 0 | CT29: =[6]Dec!$AC$1 -> 0 | CU29: =[7]Dec!$Z$1 -> 0 | CV29: =-WagesInterface!G12-WagesInterface!G25 -> 0 | CY29: =SUM(CN29:CX29) -> 0 | DC29: =[4]Jan!$AC$1 -> 0 | DD29: =[5]Jan!$AC$1 -> 0 | DE29: =[6]Jan!$AC$1 -> 0 | DF29: =[7]Jan!$Z$1 -> 0 | DG29: =-WagesInterface!G13-WagesInterface!G26 -> 0 | DJ29: =SUM(CY29:DI29) -> 0 | DN29: =[4]Feb!$AC$1 -> 0 | DO29: =[5]Feb!$AC$1 -> 0 | DP29: =[6]Feb!$AC$1 -> 0 | DQ29: =[7]Feb!$Z$1 -> 0 | DR29: =-WagesInterface!G14-WagesInterface!G27 -> 0 | DU29: =SUM(DJ29:DT29) -> 0 | DY29: =[4]Mar!$AC$1 -> 0 | DZ29: =[5]Mar!$AC$1 -> 0 | EA29: =[6]Mar!$AC$1 -> 0 | EB29: =[7]Mar!$Z$1 -> 0 | EC29: =-WagesInterface!G15-WagesInterface!G28 -> 0 | EF29: =SUM(DU29:EE29) -> 0 | EJ29: =SUM(EF29:EH29) -> 0
B30: Other Deductions from wages | D30: =-OpenAccounts!E22 -> 0 | L30: =-WagesInterface!F4-WagesInterface!F17 -> 0 | O30: =SUM(D30:N30) -> 0 | W30: =-WagesInterface!F5-WagesInterface!F18 -> 0 | Z30: =SUM(O30:Y30) -> 0 | AH30: =-WagesInterface!F6-WagesInterface!F19 -> 0 | AK30: =SUM(Z30:AJ30) -> 0 | AS30: =-WagesInterface!F7-WagesInterface!F20 -> 0 | AV30: =SUM(AK30:AU30) -> 0 | BD30: =-WagesInterface!F8-WagesInterface!F21 -> 0 | BG30: =SUM(AV30:BF30) -> 0 | BO30: =-WagesInterface!F9-WagesInterface!F22 -> 0 | BR30: =SUM(BG30:BQ30) -> 0 | BZ30: =-WagesInterface!F10-WagesInterface!F23 -> 0 | CC30: =SUM(BR30:CB30) -> 0 | CK30: =-WagesInterface!F11-WagesInterface!F24 -> 0 | CN30: =SUM(CC30:CM30) -> 0 | CV30: =-WagesInterface!F12-WagesInterface!F25 -> 0 | CY30: =SUM(CN30:CX30) -> 0 | DG30: =-WagesInterface!F13-WagesInterface!F26 -> 0 | DJ30: =SUM(CY30:DI30) -> 0 | DR30: =-WagesInterface!F14-WagesInterface!F27 -> 0 | DU30: =SUM(DJ30:DT30) -> 0 | EC30: =-WagesInterface!F15-WagesInterface!F28 -> 0 | EF30: =SUM(DU30:EE30) -> 0 | EJ30: =SUM(EF30:EH30) -> 0
B31: Dividends Creditor | C31: DV | D31: =-OpenAccounts!E23 -> 0 | H31: =[4]Apr!$AL$1 -> 0 | I31: =[5]Apr!$AL$1 -> 0 | J31: =[6]Apr!$AL$1 -> 0 | K31: =[7]Apr!$AI$1 -> 0 | O31: =SUM(D31:N31) -> 0 | S31: =[4]May!$AL$1 -> 0 | T31: =[5]May!$AL$1 -> 0 | U31: =[6]May!$AL$1 -> 0 | V31: =[7]May!$AI$1 -> 0 | Z31: =SUM(O31:Y31) -> 0 | AD31: =[4]Jun!$AL$1 -> 0 | AE31: =[5]Jun!$AL$1 -> 0 | AF31: =[6]Jun!$AL$1 -> 0 | AG31: =[7]Jun!$AI$1 -> 0 | AK31: =SUM(Z31:AJ31) -> 0 | AO31: =[4]Jul!$AL$1 -> 0 | AP31: =[5]Jul!$AL$1 -> 0 | AQ31: =[6]Jul!$AL$1 -> 0 | AR31: =[7]Jul!$AI$1 -> 0 | AV31: =SUM(AK31:AU31) -> 0 | AZ31: =[4]Aug!$AL$1 -> 0 | BA31: =[5]Aug!$AL$1 -> 0 | BB31: =[6]Aug!$AL$1 -> 0 | BC31: =[7]Aug!$AI$1 -> 0 | BG31: =SUM(AV31:BF31) -> 0 | BK31: =[4]Sep!$AL$1 -> 0 | BL31: =[5]Sep!$AL$1 -> 0 | BM31: =[6]Sep!$AL$1 -> 0 | BN31: =[7]Sep!$AI$1 -> 0 | BR31: =SUM(BG31:BQ31) -> 0 | BV31: =[4]Oct!$AL$1 -> 0 | BW31: =[5]Oct!$AL$1 -> 0 | BX31: =[6]Oct!$AL$1 -> 0 | BY31: =[7]Oct!$AI$1 -> 0 | CC31: =SUM(BR31:CB31) -> 0 | CG31: =[4]Nov!$AL$1 -> 0 | CH31: =[5]Nov!$AL$1 -> 0 | CI31: =[6]Nov!$AL$1 -> 0 | CJ31: =[7]Nov!$AI$1 -> 0 | CN31: =SUM(CC31:CM31) -> 0 | CR31: =[4]Dec!$AL$1 -> 0 | CS31: =[5]Dec!$AL$1 -> 0 | CT31: =[6]Dec!$AL$1 -> 0 | CU31: =[7]Dec!$AI$1 -> 0 | CY31: =SUM(CN31:CX31) -> 0 | DC31: =[4]Jan!$AL$1 -> 0 | DD31: =[5]Jan!$AL$1 -> 0 | DE31: =[6]Jan!$AL$1 -> 0 | DF31: =[7]Jan!$AI$1 -> 0 | DJ31: =SUM(CY31:DI31) -> 0 | DN31: =[4]Feb!$AL$1 -> 0 | DO31: =[5]Feb!$AL$1 -> 0 | DP31: =[6]Feb!$AL$1 -> 0 | DQ31: =[7]Feb!$AI$1 -> 0 | DU31: =SUM(DJ31:DT31) -> 0 | DY31: =[4]Mar!$AL$1 -> 0 | DZ31: =[5]Mar!$AL$1 -> 0 | EA31: =[6]Mar!$AL$1 -> 0 | EB31: =[7]Mar!$AI$1 -> 0 | EF31: =SUM(DU31:EE31) -> 0 | EH31: =-[8]Boardmeeting!$E$4 -> 0 | EJ31: =SUM(EF31:EH31) -> 0
B32: Creditor HMRC CIS | C32: RC | D32: =-OpenAccounts!I26 -> 0 | F32: =[3]Apr!$V$1 -> 0 | G32: =-[2]Apr!$AK$1 -> 0 | H32: =-[4]Apr!$O$1+[4]Apr!$AJ$1 -> 0 | I32: =-[5]Apr!$O$1+[5]Apr!$AJ$1 -> 0 | J32: =-[6]Apr!$O$1+[6]Apr!$AJ$1 -> 0 | K32: =[7]Apr!$AG$1 -> 0 | O32: =SUM(D32:N32) -> 0 | Q32: =[3]May!$V$1 -> 0 | R32: =-[2]May!$AK$1 -> 0 | S32: =-[4]May!$O$1+[4]May!$AJ$1 -> 0 | T32: =-[5]May!$O$1+[5]May!$AJ$1 -> 0 | U32: =-[6]May!$O$1+[6]May!$AJ$1 -> 0 | V32: =[7]May!$AG$1 -> 0 | Z32: =SUM(O32:Y32) -> 0 | AB32: =[3]Jun!$V$1 -> 0 | AC32: =-[2]Jun!$AK$1 -> 0 | AD32: =-[4]Jun!$O$1+[4]Jun!$AJ$1 -> 0 | AE32: =-[5]Jun!$O$1+[5]Jun!$AJ$1 -> 0 | AF32: =-[6]Jun!$O$1+[6]Jun!$AJ$1 -> 0 | AG32: =[7]Jun!$AG$1 -> 0 | AK32: =SUM(Z32:AJ32) -> 0 | AM32: =[3]Jul!$V$1 -> 0 | AN32: =-[2]Jul!$AK$1 -> 0 | AO32: =-[4]Jul!$O$1+[4]Jul!$AJ$1 -> 0 | AP32: =-[5]Jul!$O$1+[5]Jul!$AJ$1 -> 0 | AQ32: =-[6]Jul!$O$1+[6]Jul!$AJ$1 -> 0 | AR32: =[7]Jul!$AG$1 -> 0 | AV32: =SUM(AK32:AU32) -> 0 | AX32: =[3]Aug!$V$1 -> 0 | AY32: =-[2]Aug!$AK$1 -> 0 | AZ32: =-[4]Aug!$O$1+[4]Aug!$AJ$1 -> 0 | BA32: =-[5]Aug!$O$1+[5]Aug!$AJ$1 -> 0 | BB32: =-[6]Aug!$O$1+[6]Aug!$AJ$1 -> 0 | BC32: =[7]Aug!$AG$1 -> 0 | BG32: =SUM(AV32:BF32) -> 0 | BI32: =[3]Sep!$V$1 -> 0 | BJ32: =-[2]Sep!$AK$1 -> 0 | BK32: =-[4]Sep!$O$1+[4]Sep!$AJ$1 -> 0 | BL32: =-[5]Sep!$O$1+[5]Sep!$AJ$1 -> 0 | BM32: =-[6]Sep!$O$1+[6]Sep!$AJ$1 -> 0 | BN32: =[7]Sep!$AG$1 -> 0 | BR32: =SUM(BG32:BQ32) -> 0 | BT32: =[3]Oct!$V$1 -> 0 | BU32: =-[2]Oct!$AK$1 -> 0 | BV32: =-[4]Oct!$O$1+[4]Oct!$AJ$1 -> 0 | BW32: =-[5]Oct!$O$1+[5]Oct!$AJ$1 -> 0 | BX32: =-[6]Oct!$O$1+[6]Oct!$AJ$1 -> 0 | BY32: =[7]Oct!$AG$1 -> 0 | CC32: =SUM(BR32:CB32) -> 0 | CE32: =[3]Nov!$V$1 -> 0 | CF32: =-[2]Nov!$AK$1 -> 0 | CG32: =-[4]Nov!$O$1+[4]Nov!$AJ$1 -> 0 | CH32: =-[5]Nov!$O$1+[5]Nov!$AJ$1 -> 0 | CI32: =-[6]Nov!$O$1+[6]Nov!$AJ$1 -> 0 | CJ32: =[7]Nov!$AG$1 -> 0 | CN32: =SUM(CC32:CM32) -> 0 | CP32: =[3]Dec!$V$1 -> 0 | CQ32: =-[2]Dec!$AK$1 -> 0 | CR32: =-[4]Dec!$O$1+[4]Dec!$AJ$1 -> 0 | CS32: =-[5]Dec!$O$1+[5]Dec!$AJ$1 -> 0 | CT32: =-[6]Dec!$O$1+[6]Dec!$AJ$1 -> 0 | CU32: =[7]Dec!$AG$1 -> 0 | CY32: =SUM(CN32:CX32) -> 0 | DA32: =[3]Jan!$V$1 -> 0 | DB32: =-[2]Jan!$AK$1 -> 0 | DC32: =-[4]Jan!$O$1+[4]Jan!$AJ$1 -> 0 | DD32: =-[5]Jan!$O$1+[5]Jan!$AJ$1 -> 0 | DE32: =-[6]Jan!$O$1+[6]Jan!$AJ$1 -> 0 | DF32: =[7]Jan!$AG$1 -> 0 | DJ32: =SUM(CY32:DI32) -> 0 | DL32: =[3]Feb!$V$1 -> 0 | DM32: =-[2]Feb!$AK$1 -> 0 | DN32: =-[4]Feb!$O$1+[4]Feb!$AJ$1 -> 0 | DO32: =-[5]Feb!$O$1+[5]Feb!$AJ$1 -> 0 | DP32: =-[6]Feb!$O$1+[6]Feb!$AJ$1 -> 0 | DQ32: =[7]Feb!$AG$1 -> 0 | DU32: =SUM(DJ32:DT32) -> 0 | DW32: =[3]Mar!$V$1 -> 0 | DX32: =-[2]Mar!$AK$1 -> 0 | DY32: =-[4]Mar!$O$1+[4]Mar!$AJ$1 -> 0 | DZ32: =-[5]Mar!$O$1+[5]Mar!$AJ$1 -> 0 | EA32: =-[6]Mar!$O$1+[6]Mar!$AJ$1 -> 0 | EB32: =[7]Mar!$AG$1 -> 0 | EF32: =SUM(DU32:EE32) -> 0 | EJ32: =SUM(EF32:EH32) -> 0
B33: Creditor HMRC Vat | C33: RV | D33: =-OpenAccounts!H26 -> 0 | F33: =-[3]Apr!$G$1 -> 0 | G33: =[2]Apr!$G$1 -> 0 | H33: =-[4]Apr!$N$1+[4]Apr!$AI$1 -> 0 | I33: =-[5]Apr!$N$1+[5]Apr!$AI$1 -> 0 | J33: =-[6]Apr!$N$1+[6]Apr!$AI$1 -> 0 | K33: =[7]Apr!$AF$1 -> 0 | O33: =SUM(D33:N33) -> 0 | Q33: =-[3]May!$G$1 -> 0 | R33: =[2]May!$G$1 -> 0 | S33: =-[4]May!$N$1+[4]May!$AI$1 -> 0 | T33: =-[5]May!$N$1+[5]May!$AI$1 -> 0 | U33: =-[6]May!$N$1+[6]May!$AI$1 -> 0 | V33: =[7]May!$AF$1 -> 0 | Z33: =SUM(O33:Y33) -> 0 | AB33: =-[3]Jun!$G$1 -> 0 | AC33: =[2]Jun!$G$1 -> 0 | AD33: =-[4]Jun!$N$1+[4]Jun!$AI$1 -> 0 | AE33: =-[5]Jun!$N$1+[5]Jun!$AI$1 -> 0 | AF33: =-[6]Jun!$N$1+[6]Jun!$AI$1 -> 0 | AG33: =[7]Jun!$AF$1 -> 0 | AK33: =SUM(Z33:AJ33) -> 0 | AM33: =-[3]Jul!$G$1 -> 0 | AN33: =[2]Jul!$G$1 -> 0 | AO33: =-[4]Jul!$N$1+[4]Jul!$AI$1 -> 0 | AP33: =-[5]Jul!$N$1+[5]Jul!$AI$1 -> 0 | AQ33: =-[6]Jul!$N$1+[6]Jul!$AI$1 -> 0 | AR33: =[7]Jul!$AF$1 -> 0 | AV33: =SUM(AK33:AU33) -> 0 | AX33: =-[3]Aug!$G$1 -> 0 | AY33: =[2]Aug!$G$1 -> 0 | AZ33: =-[4]Aug!$N$1+[4]Aug!$AI$1 -> 0 | BA33: =-[5]Aug!$N$1+[5]Aug!$AI$1 -> 0 | BB33: =-[6]Aug!$N$1+[6]Aug!$AI$1 -> 0 | BC33: =[7]Aug!$AF$1 -> 0 | BG33: =SUM(AV33:BF33) -> 0 | BI33: =-[3]Sep!$G$1 -> 0 | BJ33: =[2]Sep!$G$1 -> 0 | BK33: =-[4]Sep!$N$1+[4]Sep!$AI$1 -> 0 | BL33: =-[5]Sep!$N$1+[5]Sep!$AI$1 -> 0 | BM33: =-[6]Sep!$N$1+[6]Sep!$AI$1 -> 0 | BN33: =[7]Sep!$AF$1 -> 0 | BR33: =SUM(BG33:BQ33) -> 0 | BT33: =-[3]Oct!$G$1 -> 0 | BU33: =[2]Oct!$G$1 -> 0 | BV33: =-[4]Oct!$N$1+[4]Oct!$AI$1 -> 0 | BW33: =-[5]Oct!$N$1+[5]Oct!$AI$1 -> 0 | BX33: =-[6]Oct!$N$1+[6]Oct!$AI$1 -> 0 | BY33: =[7]Oct!$AF$1 -> 0 | CC33: =SUM(BR33:CB33) -> 0 | CE33: =-[3]Nov!$G$1 -> 0 | CF33: =[2]Nov!$G$1 -> 0 | CG33: =-[4]Nov!$N$1+[4]Nov!$AI$1 -> 0 | CH33: =-[5]Nov!$N$1+[5]Nov!$AI$1 -> 0 | CI33: =-[6]Nov!$N$1+[6]Nov!$AI$1 -> 0 | CJ33: =[7]Nov!$AF$1 -> 0 | CN33: =SUM(CC33:CM33) -> 0 | CP33: =-[3]Dec!$G$1 -> 0 | CQ33: =[2]Dec!$G$1 -> 0 | CR33: =-[4]Dec!$N$1+[4]Dec!$AI$1 -> 0 | CS33: =-[5]Dec!$N$1+[5]Dec!$AI$1 -> 0 | CT33: =-[6]Dec!$N$1+[6]Dec!$AI$1 -> 0 | CU33: =[7]Dec!$AF$1 -> 0 | CY33: =SUM(CN33:CX33) -> 0 | DA33: =-[3]Jan!$G$1 -> 0 | DB33: =[2]Jan!$G$1 -> 0 | DC33: =-[4]Jan!$N$1+[4]Jan!$AI$1 -> 0 | DD33: =-[5]Jan!$N$1+[5]Jan!$AI$1 -> 0 | DE33: =-[6]Jan!$N$1+[6]Jan!$AI$1 -> 0 | DF33: =[7]Jan!$AF$1 -> 0 | DJ33: =SUM(CY33:DI33) -> 0 | DL33: =-[3]Feb!$G$1 -> 0 | DM33: =[2]Feb!$G$1 -> 0 | DN33: =-[4]Feb!$N$1+[4]Feb!$AI$1 -> 0 | DO33: =-[5]Feb!$N$1+[5]Feb!$AI$1 -> 0 | DP33: =-[6]Feb!$N$1+[6]Feb!$AI$1 -> 0 | DQ33: =[7]Feb!$AF$1 -> 0 | DU33: =SUM(DJ33:DT33) -> 0 | DW33: =-[3]Mar!$G$1 -> 0 | DX33: =[2]Mar!$G$1 -> 0 | DY33: =-[4]Mar!$N$1+[4]Mar!$AI$1 -> 0 | DZ33: =-[5]Mar!$N$1+[5]Mar!$AI$1 -> 0 | EA33: =-[6]Mar!$N$1+[6]Mar!$AI$1 -> 0 | EB33: =[7]Mar!$AF$1 -> 0 | EF33: =SUM(DU33:EE33) -> 0 | EJ33: =SUM(EF33:EH33) -> 0
B34: Creditor HMRC Paye | C34: RP | D34: =-OpenAccounts!G26 -> 0 | H34: =[4]Apr!$AH$1 -> 0 | I34: =[5]Apr!$AH$1 -> 0 | J34: =[6]Apr!$AH$1 -> 0 | K34: =[7]Apr!$AE$1 -> 0 | L34: =-(WagesInterface!D4+WagesInterface!E4+WagesInterface!H4)-(WagesInterface!D17+WagesInterface!E17+WagesInterface!H17)+(WagesInterface!I4+WagesInterface!I17) -> 0 | O34: =SUM(D34:N34) -> 0 | S34: =[4]May!$AH$1 -> 0 | T34: =[5]May!$AH$1 -> 0 | U34: =[6]May!$AH$1 -> 0 | V34: =[7]May!$AE$1 -> 0 | W34: =-(WagesInterface!D5+WagesInterface!E5+WagesInterface!H5)-(WagesInterface!D18+WagesInterface!E18+WagesInterface!H18)+(WagesInterface!I5+WagesInterface!I18) -> 0 | Z34: =SUM(O34:Y34) -> 0 | AD34: =[4]Jun!$AH$1 -> 0 | AE34: =[5]Jun!$AH$1 -> 0 | AF34: =[6]Jun!$AH$1 -> 0 | AG34: =[7]Jun!$AE$1 -> 0 | AH34: =-(WagesInterface!D6+WagesInterface!E6+WagesInterface!H6)-(WagesInterface!D19+WagesInterface!E19+WagesInterface!H19)+(WagesInterface!I6+WagesInterface!I19) -> 0 | AK34: =SUM(Z34:AJ34) -> 0 | AO34: =[4]Jul!$AH$1 -> 0 | AP34: =[5]Jul!$AH$1 -> 0 | AQ34: =[6]Jul!$AH$1 -> 0 | AR34: =[7]Jul!$AE$1 -> 0 | AS34: =-(WagesInterface!D7+WagesInterface!E7+WagesInterface!H7)-(WagesInterface!D20+WagesInterface!E20+WagesInterface!H20)+(WagesInterface!I7+WagesInterface!I20) -> 0 | AV34: =SUM(AK34:AU34) -> 0 | AZ34: =[4]Aug!$AH$1 -> 0 | BA34: =[5]Aug!$AH$1 -> 0 | BB34: =[6]Aug!$AH$1 -> 0 | BC34: =[7]Aug!$AE$1 -> 0 | BD34: =-(WagesInterface!D8+WagesInterface!E8+WagesInterface!H8)-(WagesInterface!D21+WagesInterface!E21+WagesInterface!H21)+(WagesInterface!I8+WagesInterface!I21) -> 0 | BG34: =SUM(AV34:BF34) -> 0 | BK34: =[4]Sep!$AH$1 -> 0 | BL34: =[5]Sep!$AH$1 -> 0 | BM34: =[6]Sep!$AH$1 -> 0 | BN34: =[7]Sep!$AE$1 -> 0 | BO34: =-(WagesInterface!D9+WagesInterface!E9+WagesInterface!H9)-(WagesInterface!D22+WagesInterface!E22+WagesInterface!H22)+(WagesInterface!I9+WagesInterface!I22) -> 0 | BR34: =SUM(BG34:BQ34) -> 0 | BV34: =[4]Oct!$AH$1 -> 0 | BW34: =[5]Oct!$AH$1 -> 0 | BX34: =[6]Oct!$AH$1 -> 0 | BY34: =[7]Oct!$AE$1 -> 0 | BZ34: =-(WagesInterface!D10+WagesInterface!E10+WagesInterface!H10)-(WagesInterface!D23+WagesInterface!E23+WagesInterface!H23)+(WagesInterface!I10+WagesInterface!I23) -> 0 | CC34: =SUM(BR34:CB34) -> 0 | CG34: =[4]Nov!$AH$1 -> 0 | CH34: =[5]Nov!$AH$1 -> 0 | CI34: =[6]Nov!$AH$1 -> 0 | CJ34: =[7]Nov!$AE$1 -> 0 | CK34: =-(WagesInterface!D11+WagesInterface!E11+WagesInterface!H11)-(WagesInterface!D24+WagesInterface!E24+WagesInterface!H24)+(WagesInterface!I11+WagesInterface!I24) -> 0 | CN34: =SUM(CC34:CM34) -> 0 | CR34: =[4]Dec!$AH$1 -> 0 | CS34: =[5]Dec!$AH$1 -> 0 | CT34: =[6]Dec!$AH$1 -> 0 | CU34: =[7]Dec!$AE$1 -> 0 | CV34: =-(WagesInterface!D12+WagesInterface!E12+WagesInterface!H12)-(WagesInterface!D25+WagesInterface!E25+WagesInterface!H25)+(WagesInterface!I12+WagesInterface!I25) -> 0 | CY34: =SUM(CN34:CX34) -> 0 | DC34: =[4]Jan!$AH$1 -> 0 | DD34: =[5]Jan!$AH$1 -> 0 | DE34: =[6]Jan!$AH$1 -> 0 | DF34: =[7]Jan!$AE$1 -> 0 | DG34: =-(WagesInterface!D13+WagesInterface!E13+WagesInterface!H13)-(WagesInterface!D26+WagesInterface!E26+WagesInterface!H26)+(WagesInterface!I13+WagesInterface!I26) -> 0 | DJ34: =SUM(CY34:DI34) -> 0 | DN34: =[4]Feb!$AH$1 -> 0 | DO34: =[5]Feb!$AH$1 -> 0 | DP34: =[6]Feb!$AH$1 -> 0 | DQ34: =[7]Feb!$AE$1 -> 0 | DR34: =-(WagesInterface!D14+WagesInterface!E14+WagesInterface!H14)-(WagesInterface!D27+WagesInterface!E27+WagesInterface!H27)+(WagesInterface!I14+WagesInterface!I27) -> 0 | DU34: =SUM(DJ34:DT34) -> 0 | DY34: =[4]Mar!$AH$1 -> 0 | DZ34: =[5]Mar!$AH$1 -> 0 | EA34: =[6]Mar!$AH$1 -> 0 | EB34: =[7]Mar!$AE$1 -> 0 | EC34: =-(WagesInterface!D15+WagesInterface!E15+WagesInterface!H15)-(WagesInterface!D28+WagesInterface!E28+WagesInterface!H28)+(WagesInterface!I15+WagesInterface!I28) -> 0 | EF34: =SUM(DU34:EE34) -> 0 | EJ34: =SUM(EF34:EH34) -> 0
B35: Creditor HMRC Corporation Tax | C35: RT | D35: =-OpenAccounts!E24 -> 0 | H35: =[4]Apr!$AK$1 -> 0 | I35: =[5]Apr!$AK$1 -> 0 | J35: =[6]Apr!$AK$1 -> 0 | K35: =[7]Apr!$AH$1 -> 0 | O35: =SUM(D35:N35) -> 0 | S35: =[4]May!$AK$1 -> 0 | T35: =[5]May!$AK$1 -> 0 | U35: =[6]May!$AK$1 -> 0 | V35: =[7]May!$AH$1 -> 0 | Z35: =SUM(O35:Y35) -> 0 | AD35: =[4]Jun!$AK$1 -> 0 | AE35: =[5]Jun!$AK$1 -> 0 | AF35: =[6]Jun!$AK$1 -> 0 | AG35: =[7]Jun!$AH$1 -> 0 | AK35: =SUM(Z35:AJ35) -> 0 | AO35: =[4]Jul!$AK$1 -> 0 | AP35: =[5]Jul!$AK$1 -> 0 | AQ35: =[6]Jul!$AK$1 -> 0 | AR35: =[7]Jul!$AH$1 -> 0 | AV35: =SUM(AK35:AU35) -> 0 | AZ35: =[4]Aug!$AK$1 -> 0 | BA35: =[5]Aug!$AK$1 -> 0 | BB35: =[6]Aug!$AK$1 -> 0 | BC35: =[7]Aug!$AH$1 -> 0 | BG35: =SUM(AV35:BF35) -> 0 | BK35: =[4]Sep!$AK$1 -> 0 | BL35: =[5]Sep!$AK$1 -> 0 | BM35: =[6]Sep!$AK$1 -> 0 | BN35: =[7]Sep!$AH$1 -> 0 | BR35: =SUM(BG35:BQ35) -> 0 | BV35: =[4]Oct!$AK$1 -> 0 | BW35: =[5]Oct!$AK$1 -> 0 | BX35: =[6]Oct!$AK$1 -> 0 | BY35: =[7]Oct!$AH$1 -> 0 | CC35: =SUM(BR35:CB35) -> 0 | CG35: =[4]Nov!$AK$1 -> 0 | CH35: =[5]Nov!$AK$1 -> 0 | CI35: =[6]Nov!$AK$1 -> 0 | CJ35: =[7]Nov!$AH$1 -> 0 | CN35: =SUM(CC35:CM35) -> 0 | CR35: =[4]Dec!$AK$1 -> 0 | CS35: =[5]Dec!$AK$1 -> 0 | CT35: =[6]Dec!$AK$1 -> 0 | CU35: =[7]Dec!$AH$1 -> 0 | CY35: =SUM(CN35:CX35) -> 0 | DC35: =[4]Jan!$AK$1 -> 0 | DD35: =[5]Jan!$AK$1 -> 0 | DE35: =[6]Jan!$AK$1 -> 0 | DF35: =[7]Jan!$AH$1 -> 0 | DJ35: =SUM(CY35:DI35) -> 0 | DN35: =[4]Feb!$AK$1 -> 0 | DO35: =[5]Feb!$AK$1 -> 0 | DP35: =[6]Feb!$AK$1 -> 0 | DQ35: =[7]Feb!$AH$1 -> 0 | DU35: =SUM(DJ35:DT35) -> 0 | DY35: =[4]Mar!$AK$1 -> 0 | DZ35: =[5]Mar!$AK$1 -> 0 | EA35: =[6]Mar!$AK$1 -> 0 | EB35: =[7]Mar!$AH$1 -> 0 | ED35: =-CorporationTax!K35 -> 0 | EF35: =SUM(DU35:EE35) -> 0 | EH35: =-EH58 -> 0 | EJ35: =SUM(EF35:EH35) -> 0
B36: OTHER ASSETS
B37: Debtor Long Term (repayable 3 - 5 years) | C37: LDR | D37: =OpenAccounts!E28 -> 0 | H37: =-[4]Apr!$L$1+[4]Apr!$AF$1 -> 0 | I37: =-[5]Apr!$L$1+[5]Apr!$AF$1 -> 0 | J37: =-[6]Apr!$L$1+[6]Apr!$AF$1 -> 0 | K37: =-[7]Apr!$L$1+[7]Apr!$AC$1 -> 0 | O37: =SUM(D37:N37) -> 0 | S37: =-[4]May!$L$1+[4]May!$AF$1 -> 0 | T37: =-[5]May!$L$1+[5]May!$AF$1 -> 0 | U37: =-[6]May!$L$1+[6]May!$AF$1 -> 0 | V37: =-[7]May!$L$1+[7]May!$AC$1 -> 0 | Z37: =SUM(O37:Y37) -> 0 | AD37: =-[4]Jun!$L$1+[4]Jun!$AF$1 -> 0 | AE37: =-[5]Jun!$L$1+[5]Jun!$AF$1 -> 0 | AF37: =-[6]Jun!$L$1+[6]Jun!$AF$1 -> 0 | AG37: =-[7]Jun!$L$1+[7]Jun!$AC$1 -> 0 | AK37: =SUM(Z37:AJ37) -> 0 | AO37: =-[4]Jul!$L$1+[4]Jul!$AF$1 -> 0 | AP37: =-[5]Jul!$L$1+[5]Jul!$AF$1 -> 0 | AQ37: =-[6]Jul!$L$1+[6]Jul!$AF$1 -> 0 | AR37: =-[7]Jul!$L$1+[7]Jul!$AC$1 -> 0 | AV37: =SUM(AK37:AU37) -> 0 | AZ37: =-[4]Aug!$L$1+[4]Aug!$AF$1 -> 0 | BA37: =-[5]Aug!$L$1+[5]Aug!$AF$1 -> 0 | BB37: =-[6]Aug!$L$1+[6]Aug!$AF$1 -> 0 | BC37: =-[7]Aug!$L$1+[7]Aug!$AC$1 -> 0 | BG37: =SUM(AV37:BF37) -> 0 | BK37: =-[4]Sep!$L$1+[4]Sep!$AF$1 -> 0 | BL37: =-[5]Sep!$L$1+[5]Sep!$AF$1 -> 0 | BM37: =-[6]Sep!$L$1+[6]Sep!$AF$1 -> 0 | BN37: =-[7]Sep!$L$1+[7]Sep!$AC$1 -> 0 | BR37: =SUM(BG37:BQ37) -> 0 | BV37: =-[4]Oct!$L$1+[4]Oct!$AF$1 -> 0 | BW37: =-[5]Oct!$L$1+[5]Oct!$AF$1 -> 0 | BX37: =-[6]Oct!$L$1+[6]Oct!$AF$1 -> 0 | BY37: =-[7]Oct!$L$1+[7]Oct!$AC$1 -> 0 | CC37: =SUM(BR37:CB37) -> 0 | CG37: =-[4]Nov!$L$1+[4]Nov!$AF$1 -> 0 | CH37: =-[5]Nov!$L$1+[5]Nov!$AF$1 -> 0 | CI37: =-[6]Nov!$L$1+[6]Nov!$AF$1 -> 0 | CJ37: =-[7]Nov!$L$1+[7]Nov!$AC$1 -> 0 | CN37: =SUM(CC37:CM37) -> 0 | CR37: =-[4]Dec!$L$1+[4]Dec!$AF$1 -> 0 | CS37: =-[5]Dec!$L$1+[5]Dec!$AF$1 -> 0 | CT37: =-[6]Dec!$L$1+[6]Dec!$AF$1 -> 0 | CU37: =-[7]Dec!$L$1+[7]Dec!$AC$1 -> 0 | CY37: =SUM(CN37:CX37) -> 0 | DC37: =-[4]Jan!$L$1+[4]Jan!$AF$1 -> 0 | DD37: =-[5]Jan!$L$1+[5]Jan!$AF$1 -> 0 | DE37: =-[6]Jan!$L$1+[6]Jan!$AF$1 -> 0 | DF37: =-[7]Jan!$L$1+[7]Jan!$AC$1 -> 0 | DJ37: =SUM(CY37:DI37) -> 0 | DN37: =-[4]Feb!$L$1+[4]Feb!$AF$1 -> 0 | DO37: =-[5]Feb!$L$1+[5]Feb!$AF$1 -> 0 | DP37: =-[6]Feb!$L$1+[6]Feb!$AF$1 -> 0 | DQ37: =-[7]Feb!$L$1+[7]Feb!$AC$1 -> 0 | DU37: =SUM(DJ37:DT37) -> 0 | DY37: =-[4]Mar!$L$1+[4]Mar!$AF$1 -> 0 | DZ37: =-[5]Mar!$L$1+[5]Mar!$AF$1 -> 0 | EA37: =-[6]Mar!$L$1+[6]Mar!$AF$1 -> 0 | EB37: =-[7]Mar!$L$1+[7]Mar!$AC$1 -> 0 | EF37: =SUM(DU37:EE37) -> 0 | EJ37: =SUM(EF37:EH37) -> 0
B38: OTHER CREDITORS
B39: Directors Loan Account | C39: DL | D39: =-OpenAccounts!E30 -> 0 | H39: =-[4]Apr!$P$1+[4]Apr!$AM$1 -> 0 | I39: =-[5]Apr!$P$1+[5]Apr!$AM$1 -> 0 | J39: =-[6]Apr!$P$1+[6]Apr!$AM$1 -> 0 | K39: =-[7]Apr!$N$1+[7]Apr!$AJ$1 -> 0 | O39: =SUM(D39:N39) -> 0 | S39: =-[4]May!$P$1+[4]May!$AM$1 -> 0 | T39: =-[5]May!$P$1+[5]May!$AM$1 -> 0 | U39: =-[6]May!$P$1+[6]May!$AM$1 -> 0 | V39: =-[7]May!$N$1+[7]May!$AJ$1 -> 0 | Z39: =SUM(O39:Y39) -> 0 | AD39: =-[4]Jun!$P$1+[4]Jun!$AM$1 -> 0 | AE39: =-[5]Jun!$P$1+[5]Jun!$AM$1 -> 0 | AF39: =-[6]Jun!$P$1+[6]Jun!$AM$1 -> 0 | AG39: =-[7]Jun!$N$1+[7]Jun!$AJ$1 -> 0 | AK39: =SUM(Z39:AJ39) -> 0 | AO39: =-[4]Jul!$P$1+[4]Jul!$AM$1 -> 0 | AP39: =-[5]Jul!$P$1+[5]Jul!$AM$1 -> 0 | AQ39: =-[6]Jul!$P$1+[6]Jul!$AM$1 -> 0 | AR39: =-[7]Jul!$N$1+[7]Jul!$AJ$1 -> 0 | AV39: =SUM(AK39:AU39) -> 0 | AZ39: =-[4]Aug!$P$1+[4]Aug!$AM$1 -> 0 | BA39: =-[5]Aug!$P$1+[5]Aug!$AM$1 -> 0 | BB39: =-[6]Aug!$P$1+[6]Aug!$AM$1 -> 0 | BC39: =-[7]Aug!$N$1+[7]Aug!$AJ$1 -> 0 | BG39: =SUM(AV39:BF39) -> 0 | BK39: =-[4]Sep!$P$1+[4]Sep!$AM$1 -> 0 | BL39: =-[5]Sep!$P$1+[5]Sep!$AM$1 -> 0 | BM39: =-[6]Sep!$P$1+[6]Sep!$AM$1 -> 0 | BN39: =-[7]Sep!$N$1+[7]Sep!$AJ$1 -> 0 | BR39: =SUM(BG39:BQ39) -> 0 | BV39: =-[4]Oct!$P$1+[4]Oct!$AM$1 -> 0 | BW39: =-[5]Oct!$P$1+[5]Oct!$AM$1 -> 0 | BX39: =-[6]Oct!$P$1+[6]Oct!$AM$1 -> 0 | BY39: =-[7]Oct!$N$1+[7]Oct!$AJ$1 -> 0 | CC39: =SUM(BR39:CB39) -> 0 | CG39: =-[4]Nov!$P$1+[4]Nov!$AM$1 -> 0 | CH39: =-[5]Nov!$P$1+[5]Nov!$AM$1 -> 0 | CI39: =-[6]Nov!$P$1+[6]Nov!$AM$1 -> 0 | CJ39: =-[7]Nov!$N$1+[7]Nov!$AJ$1 -> 0 | CN39: =SUM(CC39:CM39) -> 0 | CR39: =-[4]Dec!$P$1+[4]Dec!$AM$1 -> 0 | CS39: =-[5]Dec!$P$1+[5]Dec!$AM$1 -> 0 | CT39: =-[6]Dec!$P$1+[6]Dec!$AM$1 -> 0 | CU39: =-[7]Dec!$N$1+[7]Dec!$AJ$1 -> 0 | CY39: =SUM(CN39:CX39) -> 0 | DC39: =-[4]Jan!$P$1+[4]Jan!$AM$1 -> 0 | DD39: =-[5]Jan!$P$1+[5]Jan!$AM$1 -> 0 | DE39: =-[6]Jan!$P$1+[6]Jan!$AM$1 -> 0 | DF39: =-[7]Jan!$N$1+[7]Jan!$AJ$1 -> 0 | DJ39: =SUM(CY39:DI39) -> 0 | DN39: =-[4]Feb!$P$1+[4]Feb!$AM$1 -> 0 | DO39: =-[5]Feb!$P$1+[5]Feb!$AM$1 -> 0 | DP39: =-[6]Feb!$P$1+[6]Feb!$AM$1 -> 0 | DQ39: =-[7]Feb!$N$1+[7]Feb!$AJ$1 -> 0 | DU39: =SUM(DJ39:DT39) -> 0 | DY39: =-[4]Mar!$P$1+[4]Mar!$AM$1 -> 0 | DZ39: =-[5]Mar!$P$1+[5]Mar!$AM$1 -> 0 | EA39: =-[6]Mar!$P$1+[6]Mar!$AM$1 -> 0 | EB39: =-[7]Mar!$N$1+[7]Mar!$AJ$1 -> 0 | EF39: =SUM(DU39:EE39) -> 0 | EJ39: =SUM(EF39:EH39) -> 0
B40: Creditor Long Term (falling due after 1 year) | C40: LCR | D40: =-OpenAccounts!E31 -> 0 | H40: =-[4]Apr!$M$1+[4]Apr!$AG$1 -> 0 | I40: =-[5]Apr!$M$1+[5]Apr!$AG$1 -> 0 | J40: =-[6]Apr!$M$1+[6]Apr!$AG$1 -> 0 | K40: =-[7]Apr!$M$1+[7]Apr!$AD$1 -> 0 | O40: =SUM(D40:N40) -> 0 | S40: =-[4]May!$M$1+[4]May!$AG$1 -> 0 | T40: =-[5]May!$M$1+[5]May!$AG$1 -> 0 | U40: =-[6]May!$M$1+[6]May!$AG$1 -> 0 | V40: =-[7]May!$M$1+[7]May!$AD$1 -> 0 | Z40: =SUM(O40:Y40) -> 0 | AD40: =-[4]Jun!$M$1+[4]Jun!$AG$1 -> 0 | AE40: =-[5]Jun!$M$1+[5]Jun!$AG$1 -> 0 | AF40: =-[6]Jun!$M$1+[6]Jun!$AG$1 -> 0 | AG40: =-[7]Jun!$M$1+[7]Jun!$AD$1 -> 0 | AK40: =SUM(Z40:AJ40) -> 0 | AO40: =-[4]Jul!$M$1+[4]Jul!$AG$1 -> 0 | AP40: =-[5]Jul!$M$1+[5]Jul!$AG$1 -> 0 | AQ40: =-[6]Jul!$M$1+[6]Jul!$AG$1 -> 0 | AR40: =-[7]Jul!$M$1+[7]Jul!$AD$1 -> 0 | AV40: =SUM(AK40:AU40) -> 0 | AZ40: =-[4]Aug!$M$1+[4]Aug!$AG$1 -> 0 | BA40: =-[5]Aug!$M$1+[5]Aug!$AG$1 -> 0 | BB40: =-[6]Aug!$M$1+[6]Aug!$AG$1 -> 0 | BC40: =-[7]Aug!$M$1+[7]Aug!$AD$1 -> 0 | BG40: =SUM(AV40:BF40) -> 0 | BK40: =-[4]Sep!$M$1+[4]Sep!$AG$1 -> 0 | BL40: =-[5]Sep!$M$1+[5]Sep!$AG$1 -> 0 | BM40: =-[6]Sep!$M$1+[6]Sep!$AG$1 -> 0 | BN40: =-[7]Sep!$M$1+[7]Sep!$AD$1 -> 0 | BR40: =SUM(BG40:BQ40) -> 0 | BV40: =-[4]Oct!$M$1+[4]Oct!$AG$1 -> 0 | BW40: =-[5]Oct!$M$1+[5]Oct!$AG$1 -> 0 | BX40: =-[6]Oct!$M$1+[6]Oct!$AG$1 -> 0 | BY40: =-[7]Oct!$M$1+[7]Oct!$AD$1 -> 0 | CC40: =SUM(BR40:CB40) -> 0 | CG40: =-[4]Nov!$M$1+[4]Nov!$AG$1 -> 0 | CH40: =-[5]Nov!$M$1+[5]Nov!$AG$1 -> 0 | CI40: =-[6]Nov!$M$1+[6]Nov!$AG$1 -> 0 | CJ40: =-[7]Nov!$M$1+[7]Nov!$AD$1 -> 0 | CN40: =SUM(CC40:CM40) -> 0 | CR40: =-[4]Dec!$M$1+[4]Dec!$AG$1 -> 0 | CS40: =-[5]Dec!$M$1+[5]Dec!$AG$1 -> 0 | CT40: =-[6]Dec!$M$1+[6]Dec!$AG$1 -> 0 | CU40: =-[7]Dec!$M$1+[7]Dec!$AD$1 -> 0 | CY40: =SUM(CN40:CX40) -> 0 | DC40: =-[4]Jan!$M$1+[4]Jan!$AG$1 -> 0 | DD40: =-[5]Jan!$M$1+[5]Jan!$AG$1 -> 0 | DE40: =-[6]Jan!$M$1+[6]Jan!$AG$1 -> 0 | DF40: =-[7]Jan!$M$1+[7]Jan!$AD$1 -> 0 | DJ40: =SUM(CY40:DI40) -> 0 | DN40: =-[4]Feb!$M$1+[4]Feb!$AG$1 -> 0 | DO40: =-[5]Feb!$M$1+[5]Feb!$AG$1 -> 0 | DP40: =-[6]Feb!$M$1+[6]Feb!$AG$1 -> 0 | DQ40: =-[7]Feb!$M$1+[7]Feb!$AD$1 -> 0 | DU40: =SUM(DJ40:DT40) -> 0 | DY40: =-[4]Mar!$M$1+[4]Mar!$AG$1 -> 0 | DZ40: =-[5]Mar!$M$1+[5]Mar!$AG$1 -> 0 | EA40: =-[6]Mar!$M$1+[6]Mar!$AG$1 -> 0 | EB40: =-[7]Mar!$M$1+[7]Mar!$AD$1 -> 0 | EF40: =SUM(DU40:EE40) -> 0 | EH40: =-[1]HPfinance!$E$2 -> 0 | EJ40: =SUM(EF40:EH40) -> 0
B41: CAPITAL & RESERVES
B42: Share Capital | D42: =-OpenAccounts!E33 -> 0 | O42: =SUM(D42:N42) -> 0 | Z42: =SUM(O42:Y42) -> 0 | AK42: =SUM(Z42:AJ42) -> 0 | AV42: =SUM(AK42:AU42) -> 0 | BG42: =SUM(AV42:BF42) -> 0 | BR42: =SUM(BG42:BQ42) -> 0 | CC42: =SUM(BR42:CB42) -> 0 | CN42: =SUM(CC42:CM42) -> 0 | CY42: =SUM(CN42:CX42) -> 0 | DJ42: =SUM(CY42:DI42) -> 0 | DU42: =SUM(DJ42:DT42) -> 0 | EF42: =SUM(DU42:EE42) -> 0 | EH42: =-[8]Boardmeeting!$E$6 -> 0 | EJ42: =SUM(EF42:EH42) -> 0
B43: Revenue Reserve Profit & Loss Account | D43: =-OpenAccounts!E34 -> 0 | O43: =SUM(D43:N43) -> 0 | Z43: =SUM(O43:Y43) -> 0 | AK43: =SUM(Z43:AJ43) -> 0 | AV43: =SUM(AK43:AU43) -> 0 | BG43: =SUM(AV43:BF43) -> 0 | BR43: =SUM(BG43:BQ43) -> 0 | CC43: =SUM(BR43:CB43) -> 0 | CN43: =SUM(CC43:CM43) -> 0 | CY43: =SUM(CN43:CX43) -> 0 | DJ43: =SUM(CY43:DI43) -> 0 | DU43: =SUM(DJ43:DT43) -> 0 | EF43: =SUM(DU43:EE43) -> 0 | EH43: =-'PubP&L'!F54 -> 0 | EJ43: =SUM(EF43:EH43) -> 0
B44: Capital Reserve | D44: =-OpenAccounts!E35 -> 0 | O44: =SUM(D44:N44) -> 0 | Z44: =SUM(O44:Y44) -> 0 | AK44: =SUM(Z44:AJ44) -> 0 | AV44: =SUM(AK44:AU44) -> 0 | BG44: =SUM(AV44:BF44) -> 0 | BR44: =SUM(BG44:BQ44) -> 0 | CC44: =SUM(BR44:CB44) -> 0 | CN44: =SUM(CC44:CM44) -> 0 | CY44: =SUM(CN44:CX44) -> 0 | DJ44: =SUM(CY44:DI44) -> 0 | DU44: =SUM(DJ44:DT44) -> 0 | EF44: =SUM(DU44:EE44) -> 0 | EJ44: =SUM(EF44:EH44) -> 0
B46: PROFIT DISTRIBUTION
B47: Corporation Tax Payable | O47: =SUM(D47:N47) -> 0 | Z47: =SUM(O47:Y47) -> 0 | AK47: =SUM(Z47:AJ47) -> 0 | AV47: =SUM(AK47:AU47) -> 0 | BG47: =SUM(AV47:BF47) -> 0 | BR47: =SUM(BG47:BQ47) -> 0 | CC47: =SUM(BR47:CB47) -> 0 | CN47: =SUM(CC47:CM47) -> 0 | CY47: =SUM(CN47:CX47) -> 0 | DJ47: =SUM(CY47:DI47) -> 0 | DU47: =SUM(DJ47:DT47) -> 0 | ED47: =CorporationTax!K35 -> 0 | EF47: =SUM(DU47:EE47) -> 0 | EJ47: =SUM(EF47:EH47) -> 0
B48: Dividends | C48: DV | O48: =SUM(D48:N48) -> 0 | Z48: =SUM(O48:Y48) -> 0 | AK48: =SUM(Z48:AJ48) -> 0 | AV48: =SUM(AK48:AU48) -> 0 | BG48: =SUM(AV48:BF48) -> 0 | BR48: =SUM(BG48:BQ48) -> 0 | CC48: =SUM(BR48:CB48) -> 0 | CN48: =SUM(CC48:CM48) -> 0 | CY48: =SUM(CN48:CX48) -> 0 | DJ48: =SUM(CY48:DI48) -> 0 | DU48: =SUM(DJ48:DT48) -> 0 | EF48: =SUM(DU48:EE48) -> 0 | EH48: =[8]Boardmeeting!$E$4 -> 0 | EJ48: =SUM(EF48:EH48) -> 0
B49: Profit & Loss Retained | O49: =SUM(D49:N49) -> 0 | Z49: =SUM(O49:Y49) -> 0 | AK49: =SUM(Z49:AJ49) -> 0 | AV49: =SUM(AK49:AU49) -> 0 | BG49: =SUM(AV49:BF49) -> 0 | BR49: =SUM(BG49:BQ49) -> 0 | CC49: =SUM(BR49:CB49) -> 0 | CN49: =SUM(CC49:CM49) -> 0 | CY49: =SUM(CN49:CX49) -> 0 | DJ49: =SUM(CY49:DI49) -> 0 | DU49: =SUM(DJ49:DT49) -> 0 | EF49: =SUM(DU49:EE49) -> 0 | EH49: ='PubP&L'!F54 -> 0 | EJ49: =SUM(EF49:EH49) -> 0
B51: PROFIT & LOSS ACCOUNT
B52: INCOME
B53: Sales Product A | C53: A | F53: =-[3]Apr!$O$1 -> 0 | O53: =SUM(D53:N53) -> 0 | Q53: =-[3]May!$O$1 -> 0 | Z53: =SUM(O53:Y53) -> 0 | AB53: =-[3]Jun!$O$1 -> 0 | AK53: =SUM(Z53:AJ53) -> 0 | AM53: =-[3]Jul!$O$1 -> 0 | AV53: =SUM(AK53:AU53) -> 0 | AX53: =-[3]Aug!$O$1 -> 0 | BG53: =SUM(AV53:BF53) -> 0 | BI53: =-[3]Sep!$O$1 -> 0 | BR53: =SUM(BG53:BQ53) -> 0 | BT53: =-[3]Oct!$O$1 -> 0 | CC53: =SUM(BR53:CB53) -> 0 | CE53: =-[3]Nov!$O$1 -> 0 | CN53: =SUM(CC53:CM53) -> 0 | CP53: =-[3]Dec!$O$1 -> 0 | CY53: =SUM(CN53:CX53) -> 0 | DA53: =-[3]Jan!$O$1 -> 0 | DJ53: =SUM(CY53:DI53) -> 0 | DL53: =-[3]Feb!$O$1 -> 0 | DU53: =SUM(DJ53:DT53) -> 0 | DW53: =-[3]Mar!$O$1 -> 0 | EF53: =SUM(DU53:EE53) -> 0 | EJ53: =SUM(EF53:EH53) -> 0
B54: Sales Product B | C54: B | F54: =-[3]Apr!$P$1 -> 0 | O54: =SUM(D54:N54) -> 0 | Q54: =-[3]May!$P$1 -> 0 | Z54: =SUM(O54:Y54) -> 0 | AB54: =-[3]Jun!$P$1 -> 0 | AK54: =SUM(Z54:AJ54) -> 0 | AM54: =-[3]Jul!$P$1 -> 0 | AV54: =SUM(AK54:AU54) -> 0 | AX54: =-[3]Aug!$P$1 -> 0 | BG54: =SUM(AV54:BF54) -> 0 | BI54: =-[3]Sep!$P$1 -> 0 | BR54: =SUM(BG54:BQ54) -> 0 | BT54: =-[3]Oct!$P$1 -> 0 | CC54: =SUM(BR54:CB54) -> 0 | CE54: =-[3]Nov!$P$1 -> 0 | CN54: =SUM(CC54:CM54) -> 0 | CP54: =-[3]Dec!$P$1 -> 0 | CY54: =SUM(CN54:CX54) -> 0 | DA54: =-[3]Jan!$P$1 -> 0 | DJ54: =SUM(CY54:DI54) -> 0 | DL54: =-[3]Feb!$P$1 -> 0 | DU54: =SUM(DJ54:DT54) -> 0 | DW54: =-[3]Mar!$P$1 -> 0 | EF54: =SUM(DU54:EE54) -> 0 | EJ54: =SUM(EF54:EH54) -> 0
B55: Sales Product C | C55: C | F55: =-[3]Apr!$Q$1 -> 0 | O55: =SUM(D55:N55) -> 0 | Q55: =-[3]May!$Q$1 -> 0 | Z55: =SUM(O55:Y55) -> 0 | AB55: =-[3]Jun!$Q$1 -> 0 | AK55: =SUM(Z55:AJ55) -> 0 | AM55: =-[3]Jul!$Q$1 -> 0 | AV55: =SUM(AK55:AU55) -> 0 | AX55: =-[3]Aug!$Q$1 -> 0 | BG55: =SUM(AV55:BF55) -> 0 | BI55: =-[3]Sep!$Q$1 -> 0 | BR55: =SUM(BG55:BQ55) -> 0 | BT55: =-[3]Oct!$Q$1 -> 0 | CC55: =SUM(BR55:CB55) -> 0 | CE55: =-[3]Nov!$Q$1 -> 0 | CN55: =SUM(CC55:CM55) -> 0 | CP55: =-[3]Dec!$Q$1 -> 0 | CY55: =SUM(CN55:CX55) -> 0 | DA55: =-[3]Jan!$Q$1 -> 0 | DJ55: =SUM(CY55:DI55) -> 0 | DL55: =-[3]Feb!$Q$1 -> 0 | DU55: =SUM(DJ55:DT55) -> 0 | DW55: =-[3]Mar!$Q$1 -> 0 | EF55: =SUM(DU55:EE55) -> 0 | EJ55: =SUM(EF55:EH55) -> 0
B56: Other Income | C56: D | F56: =-[3]Apr!$R$1 -> 0 | O56: =SUM(D56:N56) -> 0 | Q56: =-[3]May!$R$1 -> 0 | Z56: =SUM(O56:Y56) -> 0 | AB56: =-[3]Jun!$R$1 -> 0 | AK56: =SUM(Z56:AJ56) -> 0 | AM56: =-[3]Jul!$R$1 -> 0 | AV56: =SUM(AK56:AU56) -> 0 | AX56: =-[3]Aug!$R$1 -> 0 | BG56: =SUM(AV56:BF56) -> 0 | BI56: =-[3]Sep!$R$1 -> 0 | BR56: =SUM(BG56:BQ56) -> 0 | BT56: =-[3]Oct!$R$1 -> 0 | CC56: =SUM(BR56:CB56) -> 0 | CE56: =-[3]Nov!$R$1 -> 0 | CN56: =SUM(CC56:CM56) -> 0 | CP56: =-[3]Dec!$R$1 -> 0 | CY56: =SUM(CN56:CX56) -> 0 | DA56: =-[3]Jan!$R$1 -> 0 | DJ56: =SUM(CY56:DI56) -> 0 | DL56: =-[3]Feb!$R$1 -> 0 | DU56: =SUM(DJ56:DT56) -> 0 | DW56: =-[3]Mar!$R$1 -> 0 | EF56: =SUM(DU56:EE56) -> 0 | EJ56: =SUM(EF56:EH56) -> 0
B57: Investment Grants Received | C57: G | F57: =-[3]Apr!$S$1 -> 0 | O57: =SUM(D57:N57) -> 0 | Q57: =-[3]May!$S$1 -> 0 | Z57: =SUM(O57:Y57) -> 0 | AB57: =-[3]Jun!$S$1 -> 0 | AK57: =SUM(Z57:AJ57) -> 0 | AM57: =-[3]Jul!$S$1 -> 0 | AV57: =SUM(AK57:AU57) -> 0 | AX57: =-[3]Aug!$S$1 -> 0 | BG57: =SUM(AV57:BF57) -> 0 | BI57: =-[3]Sep!$S$1 -> 0 | BR57: =SUM(BG57:BQ57) -> 0 | BT57: =-[3]Oct!$S$1 -> 0 | CC57: =SUM(BR57:CB57) -> 0 | CE57: =-[3]Nov!$S$1 -> 0 | CN57: =SUM(CC57:CM57) -> 0 | CP57: =-[3]Dec!$S$1 -> 0 | CY57: =SUM(CN57:CX57) -> 0 | DA57: =-[3]Jan!$S$1 -> 0 | DJ57: =SUM(CY57:DI57) -> 0 | DL57: =-[3]Feb!$S$1 -> 0 | DU57: =SUM(DJ57:DT57) -> 0 | DW57: =-[3]Mar!$S$1 -> 0 | EF57: =SUM(DU57:EE57) -> 0 | EJ57: =SUM(EF57:EH57) -> 0
B58: Interest Received | C58: K | H58: =-[4]Apr!$K$1 -> 0 | I58: =-[5]Apr!$K$1 -> 0 | J58: =-[6]Apr!$K$1 -> 0 | K58: =-[7]Apr!$K$1 -> 0 | O58: =SUM(D58:N58) -> 0 | S58: =-[4]May!$K$1 -> 0 | T58: =-[5]May!$K$1 -> 0 | U58: =-[6]May!$K$1 -> 0 | V58: =-[7]May!$K$1 -> 0 | Z58: =SUM(O58:Y58) -> 0 | AD58: =-[4]Jun!$K$1 -> 0 | AE58: =-[5]Jun!$K$1 -> 0 | AF58: =-[6]Jun!$K$1 -> 0 | AG58: =-[7]Jun!$K$1 -> 0 | AK58: =SUM(Z58:AJ58) -> 0 | AO58: =-[4]Jul!$K$1 -> 0 | AP58: =-[5]Jul!$K$1 -> 0 | AQ58: =-[6]Jul!$K$1 -> 0 | AR58: =-[7]Jul!$K$1 -> 0 | AV58: =SUM(AK58:AU58) -> 0 | AZ58: =-[4]Aug!$K$1 -> 0 | BA58: =-[5]Aug!$K$1 -> 0 | BB58: =-[6]Aug!$K$1 -> 0 | BC58: =-[7]Aug!$K$1 -> 0 | BG58: =SUM(AV58:BF58) -> 0 | BK58: =-[4]Sep!$K$1 -> 0 | BL58: =-[5]Sep!$K$1 -> 0 | BM58: =-[6]Sep!$K$1 -> 0 | BN58: =-[7]Sep!$K$1 -> 0 | BR58: =SUM(BG58:BQ58) -> 0 | BV58: =-[4]Oct!$K$1 -> 0 | BW58: =-[5]Oct!$K$1 -> 0 | BX58: =-[6]Oct!$K$1 -> 0 | BY58: =-[7]Oct!$K$1 -> 0 | CC58: =SUM(BR58:CB58) -> 0 | CG58: =-[4]Nov!$K$1 -> 0 | CH58: =-[5]Nov!$K$1 -> 0 | CI58: =-[6]Nov!$K$1 -> 0 | CJ58: =-[7]Nov!$K$1 -> 0 | CN58: =SUM(CC58:CM58) -> 0 | CR58: =-[4]Dec!$K$1 -> 0 | CS58: =-[5]Dec!$K$1 -> 0 | CT58: =-[6]Dec!$K$1 -> 0 | CU58: =-[7]Dec!$K$1 -> 0 | CY58: =SUM(CN58:CX58) -> 0 | DC58: =-[4]Jan!$K$1 -> 0 | DD58: =-[5]Jan!$K$1 -> 0 | DE58: =-[6]Jan!$K$1 -> 0 | DF58: =-[7]Jan!$K$1 -> 0 | DJ58: =SUM(CY58:DI58) -> 0 | DN58: =-[4]Feb!$K$1 -> 0 | DO58: =-[5]Feb!$K$1 -> 0 | DP58: =-[6]Feb!$K$1 -> 0 | DQ58: =-[7]Feb!$K$1 -> 0 | DU58: =SUM(DJ58:DT58) -> 0 | DY58: =-[4]Mar!$K$1 -> 0 | DZ58: =-[5]Mar!$K$1 -> 0 | EA58: =-[6]Mar!$K$1 -> 0 | EB58: =-[7]Mar!$K$1 -> 0 | EF58: =SUM(DU58:EE58) -> 0 | EH58: =ROUND(IF(OpenAccounts!P8="X",0,EF58/((100-Admin!P7)/100)-EF58),2) -> 0 | EJ58: =SUM(EF58:EH58) -> 0
B59: COST OF SALES
B60: Purchases Stock Materials | C60: S | G60: =[2]Apr!$O$1 -> 0 | M60: =-(Stock!$F$8-Stock!$L$8-Stock!$R$8-Stock!$X$8+Stock!$Z$8) -> 0 | O60: =SUM(D60:N60) -> 0 | R60: =[2]May!$O$1 -> 0 | X60: =-(Stock!$F$10-Stock!$L$10-Stock!$R$10-Stock!$X$10+Stock!$Z$10) -> 0 | Z60: =SUM(O60:Y60) -> 0 | AC60: =[2]Jun!$O$1 -> 0 | AI60: =-(Stock!$F$12-Stock!$L$12-Stock!$R$12-Stock!$X$12+Stock!$Z$12) -> 0 | AK60: =SUM(Z60:AJ60) -> 0 | AN60: =[2]Jul!$O$1 -> 0 | AT60: =-(Stock!$F$14-Stock!$L$14-Stock!$R$14-Stock!$X$14+Stock!$Z$14) -> 0 | AV60: =SUM(AK60:AU60) -> 0 | AY60: =[2]Aug!$O$1 -> 0 | BE60: =-(Stock!$F$16-Stock!$L$16-Stock!$R$16-Stock!$X$16+Stock!$Z$16) -> 0 | BG60: =SUM(AV60:BF60) -> 0 | BJ60: =[2]Sep!$O$1 -> 0 | BP60: =-(Stock!$F$18-Stock!$L$18-Stock!$R$18-Stock!$X$18+Stock!$Z$18) -> 0 | BR60: =SUM(BG60:BQ60) -> 0 | BU60: =[2]Oct!$O$1 -> 0 | CA60: =-(Stock!$F$20-Stock!$L$20-Stock!$R$20-Stock!$X$20+Stock!$Z$20) -> 0 | CC60: =SUM(BR60:CB60) -> 0 | CF60: =[2]Nov!$O$1 -> 0 | CL60: =-(Stock!$F$22-Stock!$L$22-Stock!$R$22-Stock!$X$22+Stock!$Z$22) -> 0 | CN60: =SUM(CC60:CM60) -> 0 | CQ60: =[2]Dec!$O$1 -> 0 | CW60: =-(Stock!$F$24-Stock!$L$24-Stock!$R$24-Stock!$X$24+Stock!$Z$24) -> 0 | CY60: =SUM(CN60:CX60) -> 0 | DB60: =[2]Jan!$O$1 -> 0 | DH60: =-(Stock!$F$26-Stock!$L$26-Stock!$R$26-Stock!$X$26+Stock!$Z$26) -> 0 | DJ60: =SUM(CY60:DI60) -> 0 | DM60: =[2]Feb!$O$1 -> 0 | DS60: =-(Stock!$F$28-Stock!$L$28-Stock!$R$28-Stock!$X$28+Stock!$Z$28) -> 0 | DU60: =SUM(DJ60:DT60) -> 0 | DX60: =[2]Mar!$O$1 -> 0 | ED60: =-(Stock!$F$30-Stock!$L$30-Stock!$R$30-Stock!$X$30+Stock!$Z$30) -> 0 | EF60: =SUM(DU60:EE60) -> 0 | EJ60: =SUM(EF60:EH60) -> 0
B61: Purchases Sub Contractors | C61: C | G61: =[2]Apr!$P$1 -> 0 | O61: =SUM(D61:N61) -> 0 | R61: =[2]May!$P$1 -> 0 | Z61: =SUM(O61:Y61) -> 0 | AC61: =[2]Jun!$P$1 -> 0 | AK61: =SUM(Z61:AJ61) -> 0 | AN61: =[2]Jul!$P$1 -> 0 | AV61: =SUM(AK61:AU61) -> 0 | AY61: =[2]Aug!$P$1 -> 0 | BG61: =SUM(AV61:BF61) -> 0 | BJ61: =[2]Sep!$P$1 -> 0 | BR61: =SUM(BG61:BQ61) -> 0 | BU61: =[2]Oct!$P$1 -> 0 | CC61: =SUM(BR61:CB61) -> 0 | CF61: =[2]Nov!$P$1 -> 0 | CN61: =SUM(CC61:CM61) -> 0 | CQ61: =[2]Dec!$P$1 -> 0 | CY61: =SUM(CN61:CX61) -> 0 | DB61: =[2]Jan!$P$1 -> 0 | DJ61: =SUM(CY61:DI61) -> 0 | DM61: =[2]Feb!$P$1 -> 0 | DU61: =SUM(DJ61:DT61) -> 0 | DX61: =[2]Mar!$P$1 -> 0 | EF61: =SUM(DU61:EE61) -> 0 | EJ61: =SUM(EF61:EH61) -> 0
B62: Purchases Other Direct Costs | C62: O | G62: =[2]Apr!$Q$1 -> 0 | O62: =SUM(D62:N62) -> 0 | R62: =[2]May!$Q$1 -> 0 | Z62: =SUM(O62:Y62) -> 0 | AC62: =[2]Jun!$Q$1 -> 0 | AK62: =SUM(Z62:AJ62) -> 0 | AN62: =[2]Jul!$Q$1 -> 0 | AV62: =SUM(AK62:AU62) -> 0 | AY62: =[2]Aug!$Q$1 -> 0 | BG62: =SUM(AV62:BF62) -> 0 | BJ62: =[2]Sep!$Q$1 -> 0 | BR62: =SUM(BG62:BQ62) -> 0 | BU62: =[2]Oct!$Q$1 -> 0 | CC62: =SUM(BR62:CB62) -> 0 | CF62: =[2]Nov!$Q$1 -> 0 | CN62: =SUM(CC62:CM62) -> 0 | CQ62: =[2]Dec!$Q$1 -> 0 | CY62: =SUM(CN62:CX62) -> 0 | DB62: =[2]Jan!$Q$1 -> 0 | DJ62: =SUM(CY62:DI62) -> 0 | DM62: =[2]Feb!$Q$1 -> 0 | DU62: =SUM(DJ62:DT62) -> 0 | DX62: =[2]Mar!$Q$1 -> 0 | EF62: =SUM(DU62:EE62) -> 0 | EJ62: =SUM(EF62:EH62) -> 0
B63: EXPENSES
B64: Paye Net Wages | C64: W | L64: =WagesInterface!C4-WagesInterface!I4 -> 0 | O64: =SUM(D64:N64) -> 0 | W64: =WagesInterface!C5-WagesInterface!I5 -> 0 | Z64: =SUM(O64:Y64) -> 0 | AH64: =WagesInterface!C6-WagesInterface!I6 -> 0 | AK64: =SUM(Z64:AJ64) -> 0 | AS64: =WagesInterface!C7-WagesInterface!I7 -> 0 | AV64: =SUM(AK64:AU64) -> 0 | BD64: =WagesInterface!C8-WagesInterface!I8 -> 0 | BG64: =SUM(AV64:BF64) -> 0 | BO64: =WagesInterface!C9-WagesInterface!I9 -> 0 | BR64: =SUM(BG64:BQ64) -> 0 | BZ64: =WagesInterface!C10-WagesInterface!I10 -> 0 | CC64: =SUM(BR64:CB64) -> 0 | CK64: =WagesInterface!C11-WagesInterface!I11 -> 0 | CN64: =SUM(CC64:CM64) -> 0 | CV64: =WagesInterface!C12-WagesInterface!I12 -> 0 | CY64: =SUM(CN64:CX64) -> 0 | DG64: =WagesInterface!C13-WagesInterface!I13 -> 0 | DJ64: =SUM(CY64:DI64) -> 0 | DR64: =WagesInterface!C14-WagesInterface!I14 -> 0 | DU64: =SUM(DJ64:DT64) -> 0 | EC64: =WagesInterface!C15-WagesInterface!I15 -> 0 | EF64: =SUM(DU64:EE64) -> 0 | EJ64: =SUM(EF64:EH64) -> 0
B65: Non Paye Casual Employee Wages | C65: E | G65: =[2]Apr!$S$1 -> 0 | O65: =SUM(D65:N65) -> 0 | R65: =[2]May!$S$1 -> 0 | Z65: =SUM(O65:Y65) -> 0 | AC65: =[2]Jun!$S$1 -> 0 | AK65: =SUM(Z65:AJ65) -> 0 | AN65: =[2]Jul!$S$1 -> 0 | AV65: =SUM(AK65:AU65) -> 0 | AY65: =[2]Aug!$S$1 -> 0 | BG65: =SUM(AV65:BF65) -> 0 | BJ65: =[2]Sep!$S$1 -> 0 | BR65: =SUM(BG65:BQ65) -> 0 | BU65: =[2]Oct!$S$1 -> 0 | CC65: =SUM(BR65:CB65) -> 0 | CF65: =[2]Nov!$S$1 -> 0 | CN65: =SUM(CC65:CM65) -> 0 | CQ65: =[2]Dec!$S$1 -> 0 | CY65: =SUM(CN65:CX65) -> 0 | DB65: =[2]Jan!$S$1 -> 0 | DJ65: =SUM(CY65:DI65) -> 0 | DM65: =[2]Feb!$S$1 -> 0 | DU65: =SUM(DJ65:DT65) -> 0 | DX65: =[2]Mar!$S$1 -> 0 | EF65: =SUM(DU65:EE65) -> 0 | EJ65: =SUM(EF65:EH65) -> 0
B66: Directors Wages | C66: D | G66: =[2]Apr!$R$1 -> 0 | L66: =WagesInterface!C17-WagesInterface!I17 -> 0 | O66: =SUM(D66:N66) -> 0 | R66: =[2]May!$R$1 -> 0 | W66: =WagesInterface!C18-WagesInterface!I18 -> 0 | Z66: =SUM(O66:Y66) -> 0 | AC66: =[2]Jun!$R$1 -> 0 | AH66: =WagesInterface!C19-WagesInterface!I19 -> 0 | AK66: =SUM(Z66:AJ66) -> 0 | AN66: =[2]Jul!$R$1 -> 0 | AS66: =WagesInterface!C20-WagesInterface!I20 -> 0 | AV66: =SUM(AK66:AU66) -> 0 | AY66: =[2]Aug!$R$1 -> 0 | BD66: =WagesInterface!C21-WagesInterface!I21 -> 0 | BG66: =SUM(AV66:BF66) -> 0 | BJ66: =[2]Sep!$R$1 -> 0 | BO66: =WagesInterface!C22-WagesInterface!I22 -> 0 | BR66: =SUM(BG66:BQ66) -> 0 | BU66: =[2]Oct!$R$1 -> 0 | BZ66: =WagesInterface!C23-WagesInterface!I23 -> 0 | CC66: =SUM(BR66:CB66) -> 0 | CF66: =[2]Nov!$R$1 -> 0 | CK66: =WagesInterface!C24-WagesInterface!I24 -> 0 | CN66: =SUM(CC66:CM66) -> 0 | CQ66: =[2]Dec!$R$1 -> 0 | CV66: =WagesInterface!C25-WagesInterface!I25 -> 0 | CY66: =SUM(CN66:CX66) -> 0 | DB66: =[2]Jan!$R$1 -> 0 | DG66: =WagesInterface!C26-WagesInterface!I26 -> 0 | DJ66: =SUM(CY66:DI66) -> 0 | DM66: =[2]Feb!$R$1 -> 0 | DR66: =WagesInterface!C27-WagesInterface!I27 -> 0 | DU66: =SUM(DJ66:DT66) -> 0 | DX66: =[2]Mar!$R$1 -> 0 | EC66: =WagesInterface!C28-WagesInterface!I28 -> 0 | EF66: =SUM(DU66:EE66) -> 0 | EJ66: =SUM(EF66:EH66) -> 0
B67: Employers National Insurance | L67: =WagesInterface!H4+WagesInterface!H17 -> 0 | O67: =SUM(D67:N67) -> 0 | W67: =WagesInterface!H5+WagesInterface!H18 -> 0 | Z67: =SUM(O67:Y67) -> 0 | AH67: =WagesInterface!H6+WagesInterface!H19 -> 0 | AK67: =SUM(Z67:AJ67) -> 0 | AS67: =WagesInterface!H7+WagesInterface!H20 -> 0 | AV67: =SUM(AK67:AU67) -> 0 | BD67: =WagesInterface!H8+WagesInterface!H21 -> 0 | BG67: =SUM(AV67:BF67) -> 0 | BO67: =WagesInterface!H9+WagesInterface!H22 -> 0 | BR67: =SUM(BG67:BQ67) -> 0 | BZ67: =WagesInterface!H10+WagesInterface!H23 -> 0 | CC67: =SUM(BR67:CB67) -> 0 | CK67: =WagesInterface!H11+WagesInterface!H24 -> 0 | CN67: =SUM(CC67:CM67) -> 0 | CV67: =WagesInterface!H12+WagesInterface!H25 -> 0 | CY67: =SUM(CN67:CX67) -> 0 | DG67: =WagesInterface!H13+WagesInterface!H26 -> 0 | DJ67: =SUM(CY67:DI67) -> 0 | DR67: =WagesInterface!H14+WagesInterface!H27 -> 0 | DU67: =SUM(DJ67:DT67) -> 0 | EC67: =WagesInterface!H15+WagesInterface!H28 -> 0 | EF67: =SUM(DU67:EE67) -> 0 | EJ67: =SUM(EF67:EH67) -> 0
B68: Premises Rent & Rates | C68: R | G68: =[2]Apr!$T$1 -> 0 | O68: =SUM(D68:N68) -> 0 | R68: =[2]May!$T$1 -> 0 | Z68: =SUM(O68:Y68) -> 0 | AC68: =[2]Jun!$T$1 -> 0 | AK68: =SUM(Z68:AJ68) -> 0 | AN68: =[2]Jul!$T$1 -> 0 | AV68: =SUM(AK68:AU68) -> 0 | AY68: =[2]Aug!$T$1 -> 0 | BG68: =SUM(AV68:BF68) -> 0 | BJ68: =[2]Sep!$T$1 -> 0 | BR68: =SUM(BG68:BQ68) -> 0 | BU68: =[2]Oct!$T$1 -> 0 | CC68: =SUM(BR68:CB68) -> 0 | CF68: =[2]Nov!$T$1 -> 0 | CN68: =SUM(CC68:CM68) -> 0 | CQ68: =[2]Dec!$T$1 -> 0 | CY68: =SUM(CN68:CX68) -> 0 | DB68: =[2]Jan!$T$1 -> 0 | DJ68: =SUM(CY68:DI68) -> 0 | DM68: =[2]Feb!$T$1 -> 0 | DU68: =SUM(DJ68:DT68) -> 0 | DX68: =[2]Mar!$T$1 -> 0 | EF68: =SUM(DU68:EE68) -> 0 | EJ68: =SUM(EF68:EH68) -> 0
B69: Premises Light & Heating | C69: P | G69: =[2]Apr!$U$1 -> 0 | O69: =SUM(D69:N69) -> 0 | R69: =[2]May!$U$1 -> 0 | Z69: =SUM(O69:Y69) -> 0 | AC69: =[2]Jun!$U$1 -> 0 | AK69: =SUM(Z69:AJ69) -> 0 | AN69: =[2]Jul!$U$1 -> 0 | AV69: =SUM(AK69:AU69) -> 0 | AY69: =[2]Aug!$U$1 -> 0 | BG69: =SUM(AV69:BF69) -> 0 | BJ69: =[2]Sep!$U$1 -> 0 | BR69: =SUM(BG69:BQ69) -> 0 | BU69: =[2]Oct!$U$1 -> 0 | CC69: =SUM(BR69:CB69) -> 0 | CF69: =[2]Nov!$U$1 -> 0 | CN69: =SUM(CC69:CM69) -> 0 | CQ69: =[2]Dec!$U$1 -> 0 | CY69: =SUM(CN69:CX69) -> 0 | DB69: =[2]Jan!$U$1 -> 0 | DJ69: =SUM(CY69:DI69) -> 0 | DM69: =[2]Feb!$U$1 -> 0 | DU69: =SUM(DJ69:DT69) -> 0 | DX69: =[2]Mar!$U$1 -> 0 | EF69: =SUM(DU69:EE69) -> 0 | EJ69: =SUM(EF69:EH69) -> 0
B70: Distribution Transport Costs | C70: T | G70: =[2]Apr!$V$1 -> 0 | O70: =SUM(D70:N70) -> 0 | R70: =[2]May!$V$1 -> 0 | Z70: =SUM(O70:Y70) -> 0 | AC70: =[2]Jun!$V$1 -> 0 | AK70: =SUM(Z70:AJ70) -> 0 | AN70: =[2]Jul!$V$1 -> 0 | AV70: =SUM(AK70:AU70) -> 0 | AY70: =[2]Aug!$V$1 -> 0 | BG70: =SUM(AV70:BF70) -> 0 | BJ70: =[2]Sep!$V$1 -> 0 | BR70: =SUM(BG70:BQ70) -> 0 | BU70: =[2]Oct!$V$1 -> 0 | CC70: =SUM(BR70:CB70) -> 0 | CF70: =[2]Nov!$V$1 -> 0 | CN70: =SUM(CC70:CM70) -> 0 | CQ70: =[2]Dec!$V$1 -> 0 | CY70: =SUM(CN70:CX70) -> 0 | DB70: =[2]Jan!$V$1 -> 0 | DJ70: =SUM(CY70:DI70) -> 0 | DM70: =[2]Feb!$V$1 -> 0 | DU70: =SUM(DJ70:DT70) -> 0 | DX70: =[2]Mar!$V$1 -> 0 | EF70: =SUM(DU70:EE70) -> 0 | EJ70: =SUM(EF70:EH70) -> 0
B71: Equipment Tools & Plant Hire | C71: Q | G71: =[2]Apr!$W$1 -> 0 | O71: =SUM(D71:N71) -> 0 | R71: =[2]May!$W$1 -> 0 | Z71: =SUM(O71:Y71) -> 0 | AC71: =[2]Jun!$W$1 -> 0 | AK71: =SUM(Z71:AJ71) -> 0 | AN71: =[2]Jul!$W$1 -> 0 | AV71: =SUM(AK71:AU71) -> 0 | AY71: =[2]Aug!$W$1 -> 0 | BG71: =SUM(AV71:BF71) -> 0 | BJ71: =[2]Sep!$W$1 -> 0 | BR71: =SUM(BG71:BQ71) -> 0 | BU71: =[2]Oct!$W$1 -> 0 | CC71: =SUM(BR71:CB71) -> 0 | CF71: =[2]Nov!$W$1 -> 0 | CN71: =SUM(CC71:CM71) -> 0 | CQ71: =[2]Dec!$W$1 -> 0 | CY71: =SUM(CN71:CX71) -> 0 | DB71: =[2]Jan!$W$1 -> 0 | DJ71: =SUM(CY71:DI71) -> 0 | DM71: =[2]Feb!$W$1 -> 0 | DU71: =SUM(DJ71:DT71) -> 0 | DX71: =[2]Mar!$W$1 -> 0 | EF71: =SUM(DU71:EE71) -> 0 | EJ71: =SUM(EF71:EH71) -> 0
B72: Repairs & Maintenance | C72: M | G72: =[2]Apr!$X$1 -> 0 | O72: =SUM(D72:N72) -> 0 | R72: =[2]May!$X$1 -> 0 | Z72: =SUM(O72:Y72) -> 0 | AC72: =[2]Jun!$X$1 -> 0 | AK72: =SUM(Z72:AJ72) -> 0 | AN72: =[2]Jul!$X$1 -> 0 | AV72: =SUM(AK72:AU72) -> 0 | AY72: =[2]Aug!$X$1 -> 0 | BG72: =SUM(AV72:BF72) -> 0 | BJ72: =[2]Sep!$X$1 -> 0 | BR72: =SUM(BG72:BQ72) -> 0 | BU72: =[2]Oct!$X$1 -> 0 | CC72: =SUM(BR72:CB72) -> 0 | CF72: =[2]Nov!$X$1 -> 0 | CN72: =SUM(CC72:CM72) -> 0 | CQ72: =[2]Dec!$X$1 -> 0 | CY72: =SUM(CN72:CX72) -> 0 | DB72: =[2]Jan!$X$1 -> 0 | DJ72: =SUM(CY72:DI72) -> 0 | DM72: =[2]Feb!$X$1 -> 0 | DU72: =SUM(DJ72:DT72) -> 0 | DX72: =[2]Mar!$X$1 -> 0 | EF72: =SUM(DU72:EE72) -> 0 | EJ72: =SUM(EF72:EH72) -> 0
B73: Consumable Materials | C73: U | G73: =[2]Apr!$Y$1 -> 0 | O73: =SUM(D73:N73) -> 0 | R73: =[2]May!$Y$1 -> 0 | Z73: =SUM(O73:Y73) -> 0 | AC73: =[2]Jun!$Y$1 -> 0 | AK73: =SUM(Z73:AJ73) -> 0 | AN73: =[2]Jul!$Y$1 -> 0 | AV73: =SUM(AK73:AU73) -> 0 | AY73: =[2]Aug!$Y$1 -> 0 | BG73: =SUM(AV73:BF73) -> 0 | BJ73: =[2]Sep!$Y$1 -> 0 | BR73: =SUM(BG73:BQ73) -> 0 | BU73: =[2]Oct!$Y$1 -> 0 | CC73: =SUM(BR73:CB73) -> 0 | CF73: =[2]Nov!$Y$1 -> 0 | CN73: =SUM(CC73:CM73) -> 0 | CQ73: =[2]Dec!$Y$1 -> 0 | CY73: =SUM(CN73:CX73) -> 0 | DB73: =[2]Jan!$Y$1 -> 0 | DJ73: =SUM(CY73:DI73) -> 0 | DM73: =[2]Feb!$Y$1 -> 0 | DU73: =SUM(DJ73:DT73) -> 0 | DX73: =[2]Mar!$Y$1 -> 0 | EF73: =SUM(DU73:EE73) -> 0 | EJ73: =SUM(EF73:EH73) -> 0
B74: Advertising & Promotion | C74: A | G74: =[2]Apr!$Z$1 -> 0 | O74: =SUM(D74:N74) -> 0 | R74: =[2]May!$Z$1 -> 0 | Z74: =SUM(O74:Y74) -> 0 | AC74: =[2]Jun!$Z$1 -> 0 | AK74: =SUM(Z74:AJ74) -> 0 | AN74: =[2]Jul!$Z$1 -> 0 | AV74: =SUM(AK74:AU74) -> 0 | AY74: =[2]Aug!$Z$1 -> 0 | BG74: =SUM(AV74:BF74) -> 0 | BJ74: =[2]Sep!$Z$1 -> 0 | BR74: =SUM(BG74:BQ74) -> 0 | BU74: =[2]Oct!$Z$1 -> 0 | CC74: =SUM(BR74:CB74) -> 0 | CF74: =[2]Nov!$Z$1 -> 0 | CN74: =SUM(CC74:CM74) -> 0 | CQ74: =[2]Dec!$Z$1 -> 0 | CY74: =SUM(CN74:CX74) -> 0 | DB74: =[2]Jan!$Z$1 -> 0 | DJ74: =SUM(CY74:DI74) -> 0 | DM74: =[2]Feb!$Z$1 -> 0 | DU74: =SUM(DJ74:DT74) -> 0 | DX74: =[2]Mar!$Z$1 -> 0 | EF74: =SUM(DU74:EE74) -> 0 | EJ74: =SUM(EF74:EH74) -> 0
B75: Telephone Postage & Stationery | C75: G | G75: =[2]Apr!$AA$1 -> 0 | O75: =SUM(D75:N75) -> 0 | R75: =[2]May!$AA$1 -> 0 | Z75: =SUM(O75:Y75) -> 0 | AC75: =[2]Jun!$AA$1 -> 0 | AK75: =SUM(Z75:AJ75) -> 0 | AN75: =[2]Jul!$AA$1 -> 0 | AV75: =SUM(AK75:AU75) -> 0 | AY75: =[2]Aug!$AA$1 -> 0 | BG75: =SUM(AV75:BF75) -> 0 | BJ75: =[2]Sep!$AA$1 -> 0 | BR75: =SUM(BG75:BQ75) -> 0 | BU75: =[2]Oct!$AA$1 -> 0 | CC75: =SUM(BR75:CB75) -> 0 | CF75: =[2]Nov!$AA$1 -> 0 | CN75: =SUM(CC75:CM75) -> 0 | CQ75: =[2]Dec!$AA$1 -> 0 | CY75: =SUM(CN75:CX75) -> 0 | DB75: =[2]Jan!$AA$1 -> 0 | DJ75: =SUM(CY75:DI75) -> 0 | DM75: =[2]Feb!$AA$1 -> 0 | DU75: =SUM(DJ75:DT75) -> 0 | DX75: =[2]Mar!$AA$1 -> 0 | EF75: =SUM(DU75:EE75) -> 0 | EJ75: =SUM(EF75:EH75) -> 0
B76: Travel & Hotel Expenses | C76: H | G76: =[2]Apr!$AB$1 -> 0 | O76: =SUM(D76:N76) -> 0 | R76: =[2]May!$AB$1 -> 0 | Z76: =SUM(O76:Y76) -> 0 | AC76: =[2]Jun!$AB$1 -> 0 | AK76: =SUM(Z76:AJ76) -> 0 | AN76: =[2]Jul!$AB$1 -> 0 | AV76: =SUM(AK76:AU76) -> 0 | AY76: =[2]Aug!$AB$1 -> 0 | BG76: =SUM(AV76:BF76) -> 0 | BJ76: =[2]Sep!$AB$1 -> 0 | BR76: =SUM(BG76:BQ76) -> 0 | BU76: =[2]Oct!$AB$1 -> 0 | CC76: =SUM(BR76:CB76) -> 0 | CF76: =[2]Nov!$AB$1 -> 0 | CN76: =SUM(CC76:CM76) -> 0 | CQ76: =[2]Dec!$AB$1 -> 0 | CY76: =SUM(CN76:CX76) -> 0 | DB76: =[2]Jan!$AB$1 -> 0 | DJ76: =SUM(CY76:DI76) -> 0 | DM76: =[2]Feb!$AB$1 -> 0 | DU76: =SUM(DJ76:DT76) -> 0 | DX76: =[2]Mar!$AB$1 -> 0 | EF76: =SUM(DU76:EE76) -> 0 | EJ76: =SUM(EF76:EH76) -> 0
B77: Motor Vehicle Expenses | C77: V | G77: =[2]Apr!$AC$1 -> 0 | O77: =SUM(D77:N77) -> 0 | R77: =[2]May!$AC$1 -> 0 | Z77: =SUM(O77:Y77) -> 0 | AC77: =[2]Jun!$AC$1 -> 0 | AK77: =SUM(Z77:AJ77) -> 0 | AN77: =[2]Jul!$AC$1 -> 0 | AV77: =SUM(AK77:AU77) -> 0 | AY77: =[2]Aug!$AC$1 -> 0 | BG77: =SUM(AV77:BF77) -> 0 | BJ77: =[2]Sep!$AC$1 -> 0 | BR77: =SUM(BG77:BQ77) -> 0 | BU77: =[2]Oct!$AC$1 -> 0 | CC77: =SUM(BR77:CB77) -> 0 | CF77: =[2]Nov!$AC$1 -> 0 | CN77: =SUM(CC77:CM77) -> 0 | CQ77: =[2]Dec!$AC$1 -> 0 | CY77: =SUM(CN77:CX77) -> 0 | DB77: =[2]Jan!$AC$1 -> 0 | DJ77: =SUM(CY77:DI77) -> 0 | DM77: =[2]Feb!$AC$1 -> 0 | DU77: =SUM(DJ77:DT77) -> 0 | DX77: =[2]Mar!$AC$1 -> 0 | EF77: =SUM(DU77:EE77) -> 0 | EJ77: =SUM(EF77:EH77) -> 0
B78: Insurance Costs | C78: N | G78: =[2]Apr!$AD$1 -> 0 | O78: =SUM(D78:N78) -> 0 | R78: =[2]May!$AD$1 -> 0 | Z78: =SUM(O78:Y78) -> 0 | AC78: =[2]Jun!$AD$1 -> 0 | AK78: =SUM(Z78:AJ78) -> 0 | AN78: =[2]Jul!$AD$1 -> 0 | AV78: =SUM(AK78:AU78) -> 0 | AY78: =[2]Aug!$AD$1 -> 0 | BG78: =SUM(AV78:BF78) -> 0 | BJ78: =[2]Sep!$AD$1 -> 0 | BR78: =SUM(BG78:BQ78) -> 0 | BU78: =[2]Oct!$AD$1 -> 0 | CC78: =SUM(BR78:CB78) -> 0 | CF78: =[2]Nov!$AD$1 -> 0 | CN78: =SUM(CC78:CM78) -> 0 | CQ78: =[2]Dec!$AD$1 -> 0 | CY78: =SUM(CN78:CX78) -> 0 | DB78: =[2]Jan!$AD$1 -> 0 | DJ78: =SUM(CY78:DI78) -> 0 | DM78: =[2]Feb!$AD$1 -> 0 | DU78: =SUM(DJ78:DT78) -> 0 | DX78: =[2]Mar!$AD$1 -> 0 | EF78: =SUM(DU78:EE78) -> 0 | EJ78: =SUM(EF78:EH78) -> 0
B79: Leasing Charges | C79: F | G79: =[2]Apr!$AE$1 -> 0 | O79: =SUM(D79:N79) -> 0 | R79: =[2]May!$AE$1 -> 0 | Z79: =SUM(O79:Y79) -> 0 | AC79: =[2]Jun!$AE$1 -> 0 | AK79: =SUM(Z79:AJ79) -> 0 | AN79: =[2]Jul!$AE$1 -> 0 | AV79: =SUM(AK79:AU79) -> 0 | AY79: =[2]Aug!$AE$1 -> 0 | BG79: =SUM(AV79:BF79) -> 0 | BJ79: =[2]Sep!$AE$1 -> 0 | BR79: =SUM(BG79:BQ79) -> 0 | BU79: =[2]Oct!$AE$1 -> 0 | CC79: =SUM(BR79:CB79) -> 0 | CF79: =[2]Nov!$AE$1 -> 0 | CN79: =SUM(CC79:CM79) -> 0 | CQ79: =[2]Dec!$AE$1 -> 0 | CY79: =SUM(CN79:CX79) -> 0 | DB79: =[2]Jan!$AE$1 -> 0 | DJ79: =SUM(CY79:DI79) -> 0 | DM79: =[2]Feb!$AE$1 -> 0 | DU79: =SUM(DJ79:DT79) -> 0 | DX79: =[2]Mar!$AE$1 -> 0 | EF79: =SUM(DU79:EE79) -> 0 | EJ79: =SUM(EF79:EH79) -> 0
B80: Legal & Professional Fees | C80: L | G80: =[2]Apr!$AF$1 -> 0 | O80: =SUM(D80:N80) -> 0 | R80: =[2]May!$AF$1 -> 0 | Z80: =SUM(O80:Y80) -> 0 | AC80: =[2]Jun!$AF$1 -> 0 | AK80: =SUM(Z80:AJ80) -> 0 | AN80: =[2]Jul!$AF$1 -> 0 | AV80: =SUM(AK80:AU80) -> 0 | AY80: =[2]Aug!$AF$1 -> 0 | BG80: =SUM(AV80:BF80) -> 0 | BJ80: =[2]Sep!$AF$1 -> 0 | BR80: =SUM(BG80:BQ80) -> 0 | BU80: =[2]Oct!$AF$1 -> 0 | CC80: =SUM(BR80:CB80) -> 0 | CF80: =[2]Nov!$AF$1 -> 0 | CN80: =SUM(CC80:CM80) -> 0 | CQ80: =[2]Dec!$AF$1 -> 0 | CY80: =SUM(CN80:CX80) -> 0 | DB80: =[2]Jan!$AF$1 -> 0 | DJ80: =SUM(CY80:DI80) -> 0 | DM80: =[2]Feb!$AF$1 -> 0 | DU80: =SUM(DJ80:DT80) -> 0 | DX80: =[2]Mar!$AF$1 -> 0 | EF80: =SUM(DU80:EE80) -> 0 | EJ80: =SUM(EF80:EH80) -> 0
B81: Bad Debts written off | C81: O | F81: =-[3]Apr!$T$1 -> 0 | O81: =SUM(D81:N81) -> 0 | Q81: =-[3]May!$T$1 -> 0 | Z81: =SUM(O81:Y81) -> 0 | AB81: =-[3]Jun!$T$1 -> 0 | AK81: =SUM(Z81:AJ81) -> 0 | AM81: =-[3]Jul!$T$1 -> 0 | AV81: =SUM(AK81:AU81) -> 0 | AX81: =-[3]Aug!$T$1 -> 0 | BG81: =SUM(AV81:BF81) -> 0 | BI81: =-[3]Sep!$T$1 -> 0 | BR81: =SUM(BG81:BQ81) -> 0 | BT81: =-[3]Oct!$T$1 -> 0 | CC81: =SUM(BR81:CB81) -> 0 | CE81: =-[3]Nov!$T$1 -> 0 | CN81: =SUM(CC81:CM81) -> 0 | CP81: =-[3]Dec!$T$1 -> 0 | CY81: =SUM(CN81:CX81) -> 0 | DA81: =-[3]Jan!$T$1 -> 0 | DJ81: =SUM(CY81:DI81) -> 0 | DL81: =-[3]Feb!$T$1 -> 0 | DU81: =SUM(DJ81:DT81) -> 0 | DW81: =-[3]Mar!$T$1 -> 0 | EF81: =SUM(DU81:EE81) -> 0 | EJ81: =SUM(EF81:EH81) -> 0
B82: Bank Interest Paid | C82: J | H82: =[4]Apr!$AE$1 -> 0 | I82: =[5]Apr!$AE$1 -> 0 | J82: =[6]Apr!$AE$1 -> 0 | K82: =[7]Apr!$AB$1 -> 0 | O82: =SUM(D82:N82) -> 0 | S82: =[4]May!$AE$1 -> 0 | T82: =[5]May!$AE$1 -> 0 | U82: =[6]May!$AE$1 -> 0 | V82: =[7]May!$AB$1 -> 0 | Z82: =SUM(O82:Y82) -> 0 | AD82: =[4]Jun!$AE$1 -> 0 | AE82: =[5]Jun!$AE$1 -> 0 | AF82: =[6]Jun!$AE$1 -> 0 | AG82: =[7]Jun!$AB$1 -> 0 | AK82: =SUM(Z82:AJ82) -> 0 | AO82: =[4]Jul!$AE$1 -> 0 | AP82: =[5]Jul!$AE$1 -> 0 | AQ82: =[6]Jul!$AE$1 -> 0 | AR82: =[7]Jul!$AB$1 -> 0 | AV82: =SUM(AK82:AU82) -> 0 | AZ82: =[4]Aug!$AE$1 -> 0 | BA82: =[5]Aug!$AE$1 -> 0 | BB82: =[6]Aug!$AE$1 -> 0 | BC82: =[7]Aug!$AB$1 -> 0 | BG82: =SUM(AV82:BF82) -> 0 | BK82: =[4]Sep!$AE$1 -> 0 | BL82: =[5]Sep!$AE$1 -> 0 | BM82: =[6]Sep!$AE$1 -> 0 | BN82: =[7]Sep!$AB$1 -> 0 | BR82: =SUM(BG82:BQ82) -> 0 | BV82: =[4]Oct!$AE$1 -> 0 | BW82: =[5]Oct!$AE$1 -> 0 | BX82: =[6]Oct!$AE$1 -> 0 | BY82: =[7]Oct!$AB$1 -> 0 | CC82: =SUM(BR82:CB82) -> 0 | CG82: =[4]Nov!$AE$1 -> 0 | CH82: =[5]Nov!$AE$1 -> 0 | CI82: =[6]Nov!$AE$1 -> 0 | CJ82: =[7]Nov!$AB$1 -> 0 | CN82: =SUM(CC82:CM82) -> 0 | CR82: =[4]Dec!$AE$1 -> 0 | CS82: =[5]Dec!$AE$1 -> 0 | CT82: =[6]Dec!$AE$1 -> 0 | CU82: =[7]Dec!$AB$1 -> 0 | CY82: =SUM(CN82:CX82) -> 0 | DC82: =[4]Jan!$AE$1 -> 0 | DD82: =[5]Jan!$AE$1 -> 0 | DE82: =[6]Jan!$AE$1 -> 0 | DF82: =[7]Jan!$AB$1 -> 0 | DJ82: =SUM(CY82:DI82) -> 0 | DN82: =[4]Feb!$AE$1 -> 0 | DO82: =[5]Feb!$AE$1 -> 0 | DP82: =[6]Feb!$AE$1 -> 0 | DQ82: =[7]Feb!$AB$1 -> 0 | DU82: =SUM(DJ82:DT82) -> 0 | DY82: =[4]Mar!$AE$1 -> 0 | DZ82: =[5]Mar!$AE$1 -> 0 | EA82: =[6]Mar!$AE$1 -> 0 | EB82: =[7]Mar!$AB$1 -> 0 | EF82: =SUM(DU82:EE82) -> 0 | EJ82: =SUM(EF82:EH82) -> 0
B83: Bank Charges | C83: B | H83: =[4]Apr!$AD$1 -> 0 | I83: =[5]Apr!$AD$1 -> 0 | J83: =[6]Apr!$AD$1 -> 0 | K83: =[7]Apr!$AA$1 -> 0 | O83: =SUM(D83:N83) -> 0 | S83: =[4]May!$AD$1 -> 0 | T83: =[5]May!$AD$1 -> 0 | U83: =[6]May!$AD$1 -> 0 | V83: =[7]May!$AA$1 -> 0 | Z83: =SUM(O83:Y83) -> 0 | AD83: =[4]Jun!$AD$1 -> 0 | AE83: =[5]Jun!$AD$1 -> 0 | AF83: =[6]Jun!$AD$1 -> 0 | AG83: =[7]Jun!$AA$1 -> 0 | AK83: =SUM(Z83:AJ83) -> 0 | AO83: =[4]Jul!$AD$1 -> 0 | AP83: =[5]Jul!$AD$1 -> 0 | AQ83: =[6]Jul!$AD$1 -> 0 | AR83: =[7]Jul!$AA$1 -> 0 | AV83: =SUM(AK83:AU83) -> 0 | AZ83: =[4]Aug!$AD$1 -> 0 | BA83: =[5]Aug!$AD$1 -> 0 | BB83: =[6]Aug!$AD$1 -> 0 | BC83: =[7]Aug!$AA$1 -> 0 | BG83: =SUM(AV83:BF83) -> 0 | BK83: =[4]Sep!$AD$1 -> 0 | BL83: =[5]Sep!$AD$1 -> 0 | BM83: =[6]Sep!$AD$1 -> 0 | BN83: =[7]Sep!$AA$1 -> 0 | BR83: =SUM(BG83:BQ83) -> 0 | BV83: =[4]Oct!$AD$1 -> 0 | BW83: =[5]Oct!$AD$1 -> 0 | BX83: =[6]Oct!$AD$1 -> 0 | BY83: =[7]Oct!$AA$1 -> 0 | CC83: =SUM(BR83:CB83) -> 0 | CG83: =[4]Nov!$AD$1 -> 0 | CH83: =[5]Nov!$AD$1 -> 0 | CI83: =[6]Nov!$AD$1 -> 0 | CJ83: =[7]Nov!$AA$1 -> 0 | CN83: =SUM(CC83:CM83) -> 0 | CR83: =[4]Dec!$AD$1 -> 0 | CS83: =[5]Dec!$AD$1 -> 0 | CT83: =[6]Dec!$AD$1 -> 0 | CU83: =[7]Dec!$AA$1 -> 0 | CY83: =SUM(CN83:CX83) -> 0 | DC83: =[4]Jan!$AD$1 -> 0 | DD83: =[5]Jan!$AD$1 -> 0 | DE83: =[6]Jan!$AD$1 -> 0 | DF83: =[7]Jan!$AA$1 -> 0 | DJ83: =SUM(CY83:DI83) -> 0 | DN83: =[4]Feb!$AD$1 -> 0 | DO83: =[5]Feb!$AD$1 -> 0 | DP83: =[6]Feb!$AD$1 -> 0 | DQ83: =[7]Feb!$AA$1 -> 0 | DU83: =SUM(DJ83:DT83) -> 0 | DY83: =[4]Mar!$AD$1 -> 0 | DZ83: =[5]Mar!$AD$1 -> 0 | EA83: =[6]Mar!$AD$1 -> 0 | EB83: =[7]Mar!$AA$1 -> 0 | EF83: =SUM(DU83:EE83) -> 0 | EJ83: =SUM(EF83:EH83) -> 0
B84: Charitable Donations | C84: Y | G84: =[2]Apr!$AG$1 -> 0 | O84: =SUM(D84:N84) -> 0 | R84: =[2]May!$AG$1 -> 0 | Z84: =SUM(O84:Y84) -> 0 | AC84: =[2]Jun!$AG$1 -> 0 | AK84: =SUM(Z84:AJ84) -> 0 | AN84: =[2]Jul!$AG$1 -> 0 | AV84: =SUM(AK84:AU84) -> 0 | AY84: =[2]Aug!$AG$1 -> 0 | BG84: =SUM(AV84:BF84) -> 0 | BJ84: =[2]Sep!$AG$1 -> 0 | BR84: =SUM(BG84:BQ84) -> 0 | BU84: =[2]Oct!$AG$1 -> 0 | CC84: =SUM(BR84:CB84) -> 0 | CF84: =[2]Nov!$AG$1 -> 0 | CN84: =SUM(CC84:CM84) -> 0 | CQ84: =[2]Dec!$AG$1 -> 0 | CY84: =SUM(CN84:CX84) -> 0 | DB84: =[2]Jan!$AG$1 -> 0 | DJ84: =SUM(CY84:DI84) -> 0 | DM84: =[2]Feb!$AG$1 -> 0 | DU84: =SUM(DJ84:DT84) -> 0 | DX84: =[2]Mar!$AG$1 -> 0 | EF84: =SUM(DU84:EE84) -> 0 | EJ84: =SUM(EF84:EH84) -> 0
B85: Goodwill written off | C85: Z | G85: =[2]Apr!$AH$1 -> 0 | O85: =SUM(D85:N85) -> 0 | R85: =[2]May!$AH$1 -> 0 | Z85: =SUM(O85:Y85) -> 0 | AC85: =[2]Jun!$AH$1 -> 0 | AK85: =SUM(Z85:AJ85) -> 0 | AN85: =[2]Jul!$AH$1 -> 0 | AV85: =SUM(AK85:AU85) -> 0 | AY85: =[2]Aug!$AH$1 -> 0 | BG85: =SUM(AV85:BF85) -> 0 | BJ85: =[2]Sep!$AH$1 -> 0 | BR85: =SUM(BG85:BQ85) -> 0 | BU85: =[2]Oct!$AH$1 -> 0 | CC85: =SUM(BR85:CB85) -> 0 | CF85: =[2]Nov!$AH$1 -> 0 | CN85: =SUM(CC85:CM85) -> 0 | CQ85: =[2]Dec!$AH$1 -> 0 | CY85: =SUM(CN85:CX85) -> 0 | DB85: =[2]Jan!$AH$1 -> 0 | DJ85: =SUM(CY85:DI85) -> 0 | DM85: =[2]Feb!$AH$1 -> 0 | DU85: =SUM(DJ85:DT85) -> 0 | DX85: =[2]Mar!$AH$1 -> 0 | EF85: =SUM(DU85:EE85) -> 0 | EJ85: =SUM(EF85:EH85) -> 0
B86: Loss on disposal of assets | M86: =([1]Schedule!$W$1-[1]Schedule!$X$1-[1]Schedule!$V$1)/12 -> 0 | O86: =SUM(D86:N86) -> 0 | X86: =([1]Schedule!$W$1-[1]Schedule!$X$1-[1]Schedule!$V$1)/12 -> 0 | Z86: =SUM(O86:Y86) -> 0 | AI86: =([1]Schedule!$W$1-[1]Schedule!$X$1-[1]Schedule!$V$1)/12 -> 0 | AK86: =SUM(Z86:AJ86) -> 0 | AT86: =([1]Schedule!$W$1-[1]Schedule!$X$1-[1]Schedule!$V$1)/12 -> 0 | AV86: =SUM(AK86:AU86) -> 0 | BE86: =([1]Schedule!$W$1-[1]Schedule!$X$1-[1]Schedule!$V$1)/12 -> 0 | BG86: =SUM(AV86:BF86) -> 0 | BP86: =([1]Schedule!$W$1-[1]Schedule!$X$1-[1]Schedule!$V$1)/12 -> 0 | BR86: =SUM(BG86:BQ86) -> 0 | CA86: =([1]Schedule!$W$1-[1]Schedule!$X$1-[1]Schedule!$V$1)/12 -> 0 | CC86: =SUM(BR86:CB86) -> 0 | CL86: =([1]Schedule!$W$1-[1]Schedule!$X$1-[1]Schedule!$V$1)/12 -> 0 | CN86: =SUM(CC86:CM86) -> 0 | CW86: =([1]Schedule!$W$1-[1]Schedule!$X$1-[1]Schedule!$V$1)/12 -> 0 | CY86: =SUM(CN86:CX86) -> 0 | DH86: =([1]Schedule!$W$1-[1]Schedule!$X$1-[1]Schedule!$V$1)/12 -> 0 | DJ86: =SUM(CY86:DI86) -> 0 | DS86: =([1]Schedule!$W$1-[1]Schedule!$X$1-[1]Schedule!$V$1)/12 -> 0 | DU86: =SUM(DJ86:DT86) -> 0 | ED86: =([1]Schedule!$W$1-[1]Schedule!$X$1-[1]Schedule!$V$1)/12 -> 0 | EF86: =SUM(DU86:EE86) -> 0 | EJ86: =SUM(EF86:EH86) -> 0
B87: Depreciation | M87: =[1]Schedule!$I$1/12 -> 0 | O87: =SUM(D87:N87) -> 0 | X87: =[1]Schedule!$I$1/12 -> 0 | Z87: =SUM(O87:Y87) -> 0 | AI87: =[1]Schedule!$I$1/12 -> 0 | AK87: =SUM(Z87:AJ87) -> 0 | AT87: =[1]Schedule!$I$1/12 -> 0 | AV87: =SUM(AK87:AU87) -> 0 | BE87: =[1]Schedule!$I$1/12 -> 0 | BG87: =SUM(AV87:BF87) -> 0 | BP87: =[1]Schedule!$I$1/12 -> 0 | BR87: =SUM(BG87:BQ87) -> 0 | CA87: =[1]Schedule!$I$1/12 -> 0 | CC87: =SUM(BR87:CB87) -> 0 | CL87: =[1]Schedule!$I$1/12 -> 0 | CN87: =SUM(CC87:CM87) -> 0 | CW87: =[1]Schedule!$I$1/12 -> 0 | CY87: =SUM(CN87:CX87) -> 0 | DH87: =[1]Schedule!$I$1/12 -> 0 | DJ87: =SUM(CY87:DI87) -> 0 | DS87: =[1]Schedule!$I$1/12 -> 0 | DU87: =SUM(DJ87:DT87) -> 0 | ED87: =[1]Schedule!$I$1/12 -> 0 | EF87: =SUM(DU87:EE87) -> 0 | EJ87: =SUM(EF87:EH87) -> 0
B88: Bank Contra Items Received | C88: X | H88: =-[4]Apr!$Q$1 -> 0 | I88: =-[5]Apr!$Q$1 -> 0 | J88: =-[6]Apr!$Q$1 -> 0 | O88: =SUM(D88:N88) -> 0 | S88: =-[4]May!$Q$1 -> 0 | T88: =-[5]May!$Q$1 -> 0 | U88: =-[6]May!$Q$1 -> 0 | Z88: =SUM(O88:Y88) -> 0 | AD88: =-[4]Jun!$Q$1 -> 0 | AE88: =-[5]Jun!$Q$1 -> 0 | AF88: =-[6]Jun!$Q$1 -> 0 | AK88: =SUM(Z88:AJ88) -> 0 | AO88: =-[4]Jul!$Q$1 -> 0 | AP88: =-[5]Jul!$Q$1 -> 0 | AQ88: =-[6]Jul!$Q$1 -> 0 | AV88: =SUM(AK88:AU88) -> 0 | AZ88: =-[4]Aug!$Q$1 -> 0 | BA88: =-[5]Aug!$Q$1 -> 0 | BB88: =-[6]Aug!$Q$1 -> 0 | BG88: =SUM(AV88:BF88) -> 0 | BK88: =-[4]Sep!$Q$1 -> 0 | BL88: =-[5]Sep!$Q$1 -> 0 | BM88: =-[6]Sep!$Q$1 -> 0 | BR88: =SUM(BG88:BQ88) -> 0 | BV88: =-[4]Oct!$Q$1 -> 0 | BW88: =-[5]Oct!$Q$1 -> 0 | BX88: =-[6]Oct!$Q$1 -> 0 | CC88: =SUM(BR88:CB88) -> 0 | CG88: =-[4]Nov!$Q$1 -> 0 | CH88: =-[5]Nov!$Q$1 -> 0 | CI88: =-[6]Nov!$Q$1 -> 0 | CN88: =SUM(CC88:CM88) -> 0 | CR88: =-[4]Dec!$Q$1 -> 0 | CS88: =-[5]Dec!$Q$1 -> 0 | CT88: =-[6]Dec!$Q$1 -> 0 | CY88: =SUM(CN88:CX88) -> 0 | DC88: =-[4]Jan!$Q$1 -> 0 | DD88: =-[5]Jan!$Q$1 -> 0 | DE88: =-[6]Jan!$Q$1 -> 0 | DJ88: =SUM(CY88:DI88) -> 0 | DN88: =-[4]Feb!$Q$1 -> 0 | DO88: =-[5]Feb!$Q$1 -> 0 | DP88: =-[6]Feb!$Q$1 -> 0 | DU88: =SUM(DJ88:DT88) -> 0 | DY88: =-[4]Mar!$Q$1 -> 0 | DZ88: =-[5]Mar!$Q$1 -> 0 | EA88: =-[6]Mar!$Q$1 -> 0 | EF88: =SUM(DU88:EE88) -> 0 | EJ88: =SUM(EF88:EH88) -> 0
B89: Bank Contra Items Paid | C89: X | H89: =[4]Apr!$AN$1 -> 0 | I89: =[5]Apr!$AN$1 -> 0 | J89: =[6]Apr!$AN$1 -> 0 | O89: =SUM(D89:N89) -> 0 | S89: =[4]May!$AN$1 -> 0 | T89: =[5]May!$AN$1 -> 0 | U89: =[6]May!$AN$1 -> 0 | Z89: =SUM(O89:Y89) -> 0 | AD89: =[4]Jun!$AN$1 -> 0 | AE89: =[5]Jun!$AN$1 -> 0 | AF89: =[6]Jun!$AN$1 -> 0 | AK89: =SUM(Z89:AJ89) -> 0 | AO89: =[4]Jul!$AN$1 -> 0 | AP89: =[5]Jul!$AN$1 -> 0 | AQ89: =[6]Jul!$AN$1 -> 0 | AV89: =SUM(AK89:AU89) -> 0 | AZ89: =[4]Aug!$AN$1 -> 0 | BA89: =[5]Aug!$AN$1 -> 0 | BB89: =[6]Aug!$AN$1 -> 0 | BG89: =SUM(AV89:BF89) -> 0 | BK89: =[4]Sep!$AN$1 -> 0 | BL89: =[5]Sep!$AN$1 -> 0 | BM89: =[6]Sep!$AN$1 -> 0 | BR89: =SUM(BG89:BQ89) -> 0 | BV89: =[4]Oct!$AN$1 -> 0 | BW89: =[5]Oct!$AN$1 -> 0 | BX89: =[6]Oct!$AN$1 -> 0 | CC89: =SUM(BR89:CB89) -> 0 | CG89: =[4]Nov!$AN$1 -> 0 | CH89: =[5]Nov!$AN$1 -> 0 | CI89: =[6]Nov!$AN$1 -> 0 | CN89: =SUM(CC89:CM89) -> 0 | CR89: =[4]Dec!$AN$1 -> 0 | CS89: =[5]Dec!$AN$1 -> 0 | CT89: =[6]Dec!$AN$1 -> 0 | CY89: =SUM(CN89:CX89) -> 0 | DC89: =[4]Jan!$AN$1 -> 0 | DD89: =[5]Jan!$AN$1 -> 0 | DE89: =[6]Jan!$AN$1 -> 0 | DJ89: =SUM(CY89:DI89) -> 0 | DN89: =[4]Feb!$AN$1 -> 0 | DO89: =[5]Feb!$AN$1 -> 0 | DP89: =[6]Feb!$AN$1 -> 0 | DU89: =SUM(DJ89:DT89) -> 0 | DY89: =[4]Mar!$AN$1 -> 0 | DZ89: =[5]Mar!$AN$1 -> 0 | EA89: =[6]Mar!$AN$1 -> 0 | EF89: =SUM(DU89:EE89) -> 0 | EJ89: =SUM(EF89:EH89) -> 0
B90: Business Entertainment | C90: E | G90: =[2]Apr!$AJ$1 -> 0 | O90: =SUM(D90:N90) -> 0 | R90: =[2]May!$AJ$1 -> 0 | Z90: =SUM(O90:Y90) -> 0 | AC90: =[2]Jun!$AJ$1 -> 0 | AK90: =SUM(Z90:AJ90) -> 0 | AN90: =[2]Jul!$AJ$1 -> 0 | AV90: =SUM(AK90:AU90) -> 0 | AY90: =[2]Aug!$AJ$1 -> 0 | BG90: =SUM(AV90:BF90) -> 0 | BJ90: =[2]Sep!$AJ$1 -> 0 | BR90: =SUM(BG90:BQ90) -> 0 | BU90: =[2]Oct!$AJ$1 -> 0 | CC90: =SUM(BR90:CB90) -> 0 | CF90: =[2]Nov!$AJ$1 -> 0 | CN90: =SUM(CC90:CM90) -> 0 | CQ90: =[2]Dec!$AJ$1 -> 0 | CY90: =SUM(CN90:CX90) -> 0 | DB90: =[2]Jan!$AJ$1 -> 0 | DJ90: =SUM(CY90:DI90) -> 0 | DM90: =[2]Feb!$AJ$1 -> 0 | DU90: =SUM(DJ90:DT90) -> 0 | DX90: =[2]Mar!$AJ$1 -> 0 | EF90: =SUM(DU90:EE90) -> 0 | EJ90: =SUM(EF90:EH90) -> 0
B91: AUDIT ACCURACY CHECK | D91: =SUM(D4:D90) -> 0 | F91: =SUM(F4:F90) -> 0 | G91: =SUM(G4:G90) -> 0 | H91: =SUM(H4:H90) -> 0 | I91: =SUM(I4:I90) -> 0 | J91: =SUM(J4:J90) -> 0 | K91: =SUM(K4:K90) -> 0 | L91: =SUM(L4:L90) -> 0 | M91: =SUM(M4:M90) -> 0 | O91: =SUM(O4:O90) -> 0 | Q91: =SUM(Q4:Q90) -> 0 | R91: =SUM(R4:R90) -> 0 | S91: =SUM(S4:S90) -> 0 | T91: =SUM(T4:T90) -> 0 | U91: =SUM(U4:U90) -> 0 | V91: =SUM(V4:V90) -> 0 | W91: =SUM(W4:W90) -> 0 | X91: =SUM(X4:X90) -> 0 | Z91: =SUM(Z4:Z90) -> 0 | AB91: =SUM(AB4:AB90) -> 0 | AC91: =SUM(AC4:AC90) -> 0 | AD91: =SUM(AD4:AD90) -> 0 | AE91: =SUM(AE4:AE90) -> 0 | AF91: =SUM(AF4:AF90) -> 0 | AG91: =SUM(AG4:AG90) -> 0 | AH91: =SUM(AH4:AH90) -> 0 | AI91: =SUM(AI4:AI90) -> 0 | AK91: =SUM(AK4:AK90) -> 0 | AM91: =SUM(AM4:AM90) -> 0 | AN91: =SUM(AN4:AN90) -> 0 | AO91: =SUM(AO4:AO90) -> 0 | AP91: =SUM(AP4:AP90) -> 0 | AQ91: =SUM(AQ4:AQ90) -> 0 | AR91: =SUM(AR4:AR90) -> 0 | AS91: =SUM(AS4:AS90) -> 0 | AT91: =SUM(AT4:AT90) -> 0 | AV91: =SUM(AV4:AV90) -> 0 | AX91: =SUM(AX4:AX90) -> 0 | AY91: =SUM(AY4:AY90) -> 0 | AZ91: =SUM(AZ4:AZ90) -> 0 | BA91: =SUM(BA4:BA90) -> 0 | BB91: =SUM(BB4:BB90) -> 0 | BC91: =SUM(BC4:BC90) -> 0 | BD91: =SUM(BD4:BD90) -> 0 | BE91: =SUM(BE4:BE90) -> 0 | BG91: =SUM(BG4:BG90) -> 0 | BI91: =SUM(BI4:BI90) -> 0 | BJ91: =SUM(BJ4:BJ90) -> 0 | BK91: =SUM(BK4:BK90) -> 0 | BL91: =SUM(BL4:BL90) -> 0 | BM91: =SUM(BM4:BM90) -> 0 | BN91: =SUM(BN4:BN90) -> 0 | BO91: =SUM(BO4:BO90) -> 0 | BP91: =SUM(BP4:BP90) -> 0 | BR91: =SUM(BR4:BR90) -> 0 | BT91: =SUM(BT4:BT90) -> 0 | BU91: =SUM(BU4:BU90) -> 0 | BV91: =SUM(BV4:BV90) -> 0 | BW91: =SUM(BW4:BW90) -> 0 | BX91: =SUM(BX4:BX90) -> 0 | BY91: =SUM(BY4:BY90) -> 0 | BZ91: =SUM(BZ4:BZ90) -> 0 | CA91: =SUM(CA4:CA90) -> 0 | CC91: =SUM(CC4:CC90) -> 0 | CE91: =SUM(CE4:CE90) -> 0 | CF91: =SUM(CF4:CF90) -> 0 | CG91: =SUM(CG4:CG90) -> 0 | CH91: =SUM(CH4:CH90) -> 0 | CI91: =SUM(CI4:CI90) -> 0 | CJ91: =SUM(CJ4:CJ90) -> 0 | CK91: =SUM(CK4:CK90) -> 0 | CL91: =SUM(CL4:CL90) -> 0 | CN91: =SUM(CN4:CN90) -> 0 | CP91: =SUM(CP4:CP90) -> 0 | CQ91: =SUM(CQ4:CQ90) -> 0 | CR91: =SUM(CR4:CR90) -> 0 | CS91: =SUM(CS4:CS90) -> 0 | CT91: =SUM(CT4:CT90) -> 0 | CU91: =SUM(CU4:CU90) -> 0 | CV91: =SUM(CV4:CV90) -> 0 | CW91: =SUM(CW4:CW90) -> 0 | CY91: =SUM(CY4:CY90) -> 0 | DA91: =SUM(DA4:DA90) -> 0 | DB91: =SUM(DB4:DB90) -> 0 | DC91: =SUM(DC4:DC90) -> 0 | DD91: =SUM(DD4:DD90) -> 0 | DE91: =SUM(DE4:DE90) -> 0 | DF91: =SUM(DF4:DF90) -> 0 | DG91: =SUM(DG4:DG90) -> 0 | DH91: =SUM(DH4:DH90) -> 0 | DJ91: =SUM(DJ4:DJ90) -> 0 | DL91: =SUM(DL4:DL90) -> 0 | DM91: =SUM(DM4:DM90) -> 0 | DN91: =SUM(DN4:DN90) -> 0 | DO91: =SUM(DO4:DO90) -> 0 | DP91: =SUM(DP4:DP90) -> 0 | DQ91: =SUM(DQ4:DQ90) -> 0 | DR91: =SUM(DR4:DR90) -> 0 | DS91: =SUM(DS4:DS90) -> 0 | DU91: =SUM(DU4:DU90) -> 0 | DW91: =SUM(DW4:DW90) -> 0 | DX91: =SUM(DX4:DX90) -> 0 | DY91: =SUM(DY4:DY90) -> 0 | DZ91: =SUM(DZ4:DZ90) -> 0 | EA91: =SUM(EA4:EA90) -> 0 | EB91: =SUM(EB4:EB90) -> 0 | EC91: =SUM(EC4:EC90) -> 0 | ED91: =SUM(ED4:ED90) -> 0 | EF91: =SUM(EF4:EF90) -> 0 | EH91: =SUM(EH4:EH90) -> 0 | EJ91: =SUM(EJ4:EJ90) -> 0

Sheet MnthP&L
A1: Monthly Management Accounts Profit and Loss Account | B1: Total Year to | C1: =Admin!B10 -> 45777 | D1: =Admin!B12 -> 45808 | E1: =Admin!B14 -> 45838 | F1: =Admin!B16 -> 45869 | G1: =Admin!B18 -> 45900 | H1: =Admin!B20 -> 45930 | I1: =Admin!B22 -> 45961 | J1: =Admin!B24 -> 45991 | K1: =Admin!B26 -> 46022 | L1: =Admin!B28 -> 46053 | M1: =Admin!B30 -> 46081 | N1: =Admin!B32 -> 46112
B2: =Admin!B32 -> 46112
B3: £ | C3: £ | D3: £ | E3: £ | F3: £ | G3: £ | H3: £ | I3: £ | J3: £ | K3: £ | L3: £ | M3: £ | N3: £
A4: Sales Product A | B4: =SUM(C4:N4) -> 0 | C4: =-TrialBalance!O53-0 -> 0 | D4: =-TrialBalance!Z53-C4 -> 0 | E4: =-TrialBalance!AK53-SUM(C4:D4) -> 0 | F4: =-TrialBalance!AV53-SUM(C4:E4) -> 0 | G4: =-TrialBalance!BG53-SUM(C4:F4) -> 0 | H4: =-TrialBalance!BR53-SUM(C4:G4) -> 0 | I4: =-TrialBalance!CC53-SUM(C4:H4) -> 0 | J4: =-TrialBalance!CN53-SUM(C4:I4) -> 0 | K4: =-TrialBalance!CY53-SUM(C4:J4) -> 0 | L4: =-TrialBalance!DJ53-SUM(C4:K4) -> 0 | M4: =-TrialBalance!DU53-SUM(C4:L4) -> 0 | N4: =-TrialBalance!EF53-SUM(C4:M4) -> 0
A5: Sales Product B | B5: =SUM(C5:N5) -> 0 | C5: =-TrialBalance!O54-0 -> 0 | D5: =-TrialBalance!Z54-C5 -> 0 | E5: =-TrialBalance!AK54-SUM(C5:D5) -> 0 | F5: =-TrialBalance!AV54-SUM(C5:E5) -> 0 | G5: =-TrialBalance!BG54-SUM(C5:F5) -> 0 | H5: =-TrialBalance!BR54-SUM(C5:G5) -> 0 | I5: =-TrialBalance!CC54-SUM(C5:H5) -> 0 | J5: =-TrialBalance!CN54-SUM(C5:I5) -> 0 | K5: =-TrialBalance!CY54-SUM(C5:J5) -> 0 | L5: =-TrialBalance!DJ54-SUM(C5:K5) -> 0 | M5: =-TrialBalance!DU54-SUM(C5:L5) -> 0 | N5: =-TrialBalance!EF54-SUM(C5:M5) -> 0
A6: Sales Product C | B6: =SUM(C6:N6) -> 0 | C6: =-TrialBalance!O55-0 -> 0 | D6: =-TrialBalance!Z55-C6 -> 0 | E6: =-TrialBalance!AK55-SUM(C6:D6) -> 0 | F6: =-TrialBalance!AV55-SUM(C6:E6) -> 0 | G6: =-TrialBalance!BG55-SUM(C6:F6) -> 0 | H6: =-TrialBalance!BR55-SUM(C6:G6) -> 0 | I6: =-TrialBalance!CC55-SUM(C6:H6) -> 0 | J6: =-TrialBalance!CN55-SUM(C6:I6) -> 0 | K6: =-TrialBalance!CY55-SUM(C6:J6) -> 0 | L6: =-TrialBalance!DJ55-SUM(C6:K6) -> 0 | M6: =-TrialBalance!DU55-SUM(C6:L6) -> 0 | N6: =-TrialBalance!EF55-SUM(C6:M6) -> 0
A7: Other Income | B7: =SUM(C7:N7) -> 0 | C7: =-TrialBalance!O56 -> 0 | D7: =-TrialBalance!Z56-C7 -> 0 | E7: =-TrialBalance!AK56-SUM(C7:D7) -> 0 | F7: =-TrialBalance!AV56-SUM(C7:E7) -> 0 | G7: =-TrialBalance!BG56-SUM(C7:F7) -> 0 | H7: =-TrialBalance!BR56-SUM(C7:G7) -> 0 | I7: =-TrialBalance!CC56-SUM(C7:H7) -> 0 | J7: =-TrialBalance!CN56-SUM(C7:I7) -> 0 | K7: =-TrialBalance!CY56-SUM(C7:J7) -> 0 | L7: =-TrialBalance!DJ56-SUM(C7:K7) -> 0 | M7: =-TrialBalance!DU56-SUM(C7:L7) -> 0 | N7: =-TrialBalance!EF56-SUM(C7:M7) -> 0
A8: Investment Grants received | B8: =SUM(C8:N8) -> 0 | C8: =-TrialBalance!O57 -> 0 | D8: =-TrialBalance!Z57-C8 -> 0 | E8: =-TrialBalance!AK57-SUM(C8:D8) -> 0 | F8: =-TrialBalance!AV57-SUM(C8:E8) -> 0 | G8: =-TrialBalance!BG57-SUM(C8:F8) -> 0 | H8: =-TrialBalance!BR57-SUM(C8:G8) -> 0 | I8: =-TrialBalance!CC57-SUM(C8:H8) -> 0 | J8: =-TrialBalance!CN57-SUM(C8:I8) -> 0 | K8: =-TrialBalance!CY57-SUM(C8:J8) -> 0 | L8: =-TrialBalance!DJ57-SUM(C8:K8) -> 0 | M8: =-TrialBalance!DU57-SUM(C8:L8) -> 0 | N8: =-TrialBalance!EF57-SUM(C8:M8) -> 0
A9: Sales Turnover | B9: =SUM(B4:B8) -> 0 | C9: =SUM(C4:C8) -> 0 | D9: =SUM(D4:D8) -> 0 | E9: =SUM(E4:E8) -> 0 | F9: =SUM(F4:F8) -> 0 | G9: =SUM(G4:G8) -> 0 | H9: =SUM(H4:H8) -> 0 | I9: =SUM(I4:I8) -> 0 | ... N9: =SUM(N4:N8) -> 0
A10: Cost of Sales
A11: Purchases | B11: =SUM(C11:N11) -> 0 | C11: =TrialBalance!O60-0 -> 0 | D11: =TrialBalance!Z60-C11 -> 0 | E11: =TrialBalance!AK60-SUM(C11:D11) -> 0 | F11: =TrialBalance!AV60-SUM(C11:E11) -> 0 | G11: =TrialBalance!BG60-SUM(C11:F11) -> 0 | H11: =TrialBalance!BR60-SUM(C11:G11) -> 0 | I11: =TrialBalance!CC60-SUM(C11:H11) -> 0 | J11: =TrialBalance!CN60-SUM(C11:I11) -> 0 | K11: =TrialBalance!CY60-SUM(C11:J11) -> 0 | L11: =TrialBalance!DJ60-SUM(C11:K11) -> 0 | M11: =TrialBalance!DU60-SUM(C11:L11) -> 0 | N11: =TrialBalance!EF60-SUM(C11:M11) -> 0
A12: Sub contractors | B12: =SUM(C12:N12) -> 0 | C12: =TrialBalance!O61-0 -> 0 | D12: =TrialBalance!Z61-C12 -> 0 | E12: =TrialBalance!AK61-SUM(C12:D12) -> 0 | F12: =TrialBalance!AV61-SUM(C12:E12) -> 0 | G12: =TrialBalance!BG61-SUM(C12:F12) -> 0 | H12: =TrialBalance!BR61-SUM(C12:G12) -> 0 | I12: =TrialBalance!CC61-SUM(C12:H12) -> 0 | J12: =TrialBalance!CN61-SUM(C12:I12) -> 0 | K12: =TrialBalance!CY61-SUM(C12:J12) -> 0 | L12: =TrialBalance!DJ61-SUM(C12:K12) -> 0 | M12: =TrialBalance!DU61-SUM(C12:L12) -> 0 | N12: =TrialBalance!EF61-SUM(C12:M12) -> 0
A13: Other Direct Cost of Sales | B13: =SUM(C13:N13) -> 0 | C13: =TrialBalance!O62-0 -> 0 | D13: =TrialBalance!Z62-C13 -> 0 | E13: =TrialBalance!AK62-SUM(C13:D13) -> 0 | F13: =TrialBalance!AV62-SUM(C13:E13) -> 0 | G13: =TrialBalance!BG62-SUM(C13:F13) -> 0 | H13: =TrialBalance!BR62-SUM(C13:G13) -> 0 | I13: =TrialBalance!CC62-SUM(C13:H13) -> 0 | J13: =TrialBalance!CN62-SUM(C13:I13) -> 0 | K13: =TrialBalance!CY62-SUM(C13:J13) -> 0 | L13: =TrialBalance!DJ62-SUM(C13:K13) -> 0 | M13: =TrialBalance!DU62-SUM(C13:L13) -> 0 | N13: =TrialBalance!EF62-SUM(C13:M13) -> 0
A14: Cost of Sales | B14: =SUM(B11:B13) -> 0 | C14: =SUM(C11:C13) -> 0 | D14: =SUM(D11:D13) -> 0 | E14: =SUM(E11:E13) -> 0 | F14: =SUM(F11:F13) -> 0 | G14: =SUM(G11:G13) -> 0 | H14: =SUM(H11:H13) -> 0 | I14: =SUM(I11:I13) -> 0 | ... N14: =SUM(N11:N13) -> 0
A16: Gross Profit | B16: =B9-B14 -> 0 | C16: =C9-C14 -> 0 | D16: =D9-D14 -> 0 | E16: =E9-E14 -> 0 | F16: =F9-F14 -> 0 | G16: =G9-G14 -> 0 | H16: =H9-H14 -> 0 | I16: =I9-I14 -> 0 | ... N16: =N9-N14 -> 0
A17: Administrative Expenses
A18: Wages and Salaries | B18: =SUM(C18:N18) -> 0 | C18: =TrialBalance!O64+TrialBalance!O65-0 -> 0 | D18: =TrialBalance!Z64+TrialBalance!Z65-C18 -> 0 | E18: =TrialBalance!AK64+TrialBalance!AK65-SUM(C18:D18) -> 0 | F18: =TrialBalance!AV64+TrialBalance!AV65-SUM(C18:E18) -> 0 | G18: =TrialBalance!BG64+TrialBalance!BG65-SUM(C18:F18) -> 0 | H18: =TrialBalance!BR64+TrialBalance!BR65-SUM(C18:G18) -> 0 | I18: =TrialBalance!CC64+TrialBalance!CC65-SUM(C18:H18) -> 0 | J18: =TrialBalance!CN64+TrialBalance!CN65-SUM(C18:I18) -> 0 | K18: =TrialBalance!CY64+TrialBalance!CY65-SUM(C18:J18) -> 0 | L18: =TrialBalance!DJ64+TrialBalance!DJ65-SUM(C18:K18) -> 0 | M18: =TrialBalance!DU64+TrialBalance!DU65-SUM(C18:L18) -> 0 | N18: =TrialBalance!EF64+TrialBalance!EF65-SUM(C18:M18) -> 0
A19: Directors Wages | B19: =SUM(C19:N19) -> 0 | C19: =TrialBalance!O66-0 -> 0 | D19: =TrialBalance!Z66-C19 -> 0 | E19: =TrialBalance!AK66-SUM(C19:D19) -> 0 | F19: =TrialBalance!AV66-SUM(C19:E19) -> 0 | G19: =TrialBalance!BG66-SUM(C19:F19) -> 0 | H19: =TrialBalance!BR66-SUM(C19:G19) -> 0 | I19: =TrialBalance!CC66-SUM(C19:H19) -> 0 | J19: =TrialBalance!CN66-SUM(C19:I19) -> 0 | K19: =TrialBalance!CY66-SUM(C19:J19) -> 0 | L19: =TrialBalance!DJ66-SUM(C19:K19) -> 0 | M19: =TrialBalance!DU66-SUM(C19:L19) -> 0 | N19: =TrialBalance!EF66-SUM(C19:M19) -> 0
A20: Employers National Insurance | B20: =SUM(C20:N20) -> 0 | C20: =TrialBalance!O67-0 -> 0 | D20: =TrialBalance!Z67-C20 -> 0 | E20: =TrialBalance!AK67-SUM(C20:D20) -> 0 | F20: =TrialBalance!AV67-SUM(C20:E20) -> 0 | G20: =TrialBalance!BG67-SUM(C20:F20) -> 0 | H20: =TrialBalance!BR67-SUM(C20:G20) -> 0 | I20: =TrialBalance!CC67-SUM(C20:H20) -> 0 | J20: =TrialBalance!CN67-SUM(C20:I20) -> 0 | K20: =TrialBalance!CY67-SUM(C20:J20) -> 0 | L20: =TrialBalance!DJ67-SUM(C20:K20) -> 0 | M20: =TrialBalance!DU67-SUM(C20:L20) -> 0 | N20: =TrialBalance!EF67-SUM(C20:M20) -> 0
A21: Premises Rent & Rates | B21: =SUM(C21:N21) -> 0 | C21: =TrialBalance!O68-0 -> 0 | D21: =TrialBalance!Z68-C21 -> 0 | E21: =TrialBalance!AK68-SUM(C21:D21) -> 0 | F21: =TrialBalance!AV68-SUM(C21:E21) -> 0 | G21: =TrialBalance!BG68-SUM(C21:F21) -> 0 | H21: =TrialBalance!BR68-SUM(C21:G21) -> 0 | I21: =TrialBalance!CC68-SUM(C21:H21) -> 0 | J21: =TrialBalance!CN68-SUM(C21:I21) -> 0 | K21: =TrialBalance!CY68-SUM(C21:J21) -> 0 | L21: =TrialBalance!DJ68-SUM(C21:K21) -> 0 | M21: =TrialBalance!DU68-SUM(C21:L21) -> 0 | N21: =TrialBalance!EF68-SUM(C21:M21) -> 0
A22: Premises Light & Heating | B22: =SUM(C22:N22) -> 0 | C22: =TrialBalance!O69-0 -> 0 | D22: =TrialBalance!Z69-C22 -> 0 | E22: =TrialBalance!AK69-SUM(C22:D22) -> 0 | F22: =TrialBalance!AV69-SUM(C22:E22) -> 0 | G22: =TrialBalance!BG69-SUM(C22:F22) -> 0 | H22: =TrialBalance!BR69-SUM(C22:G22) -> 0 | I22: =TrialBalance!CC69-SUM(C22:H22) -> 0 | J22: =TrialBalance!CN69-SUM(C22:I22) -> 0 | K22: =TrialBalance!CY69-SUM(C22:J22) -> 0 | L22: =TrialBalance!DJ69-SUM(C22:K22) -> 0 | M22: =TrialBalance!DU69-SUM(C22:L22) -> 0 | N22: =TrialBalance!EF69-SUM(C22:M22) -> 0
A23: Distribution Transport Costs | B23: =SUM(C23:N23) -> 0 | C23: =TrialBalance!O70-0 -> 0 | D23: =TrialBalance!Z70-C23 -> 0 | E23: =TrialBalance!AK70-SUM(C23:D23) -> 0 | F23: =TrialBalance!AV70-SUM(C23:E23) -> 0 | G23: =TrialBalance!BG70-SUM(C23:F23) -> 0 | H23: =TrialBalance!BR70-SUM(C23:G23) -> 0 | I23: =TrialBalance!CC70-SUM(C23:H23) -> 0 | J23: =TrialBalance!CN70-SUM(C23:I23) -> 0 | K23: =TrialBalance!CY70-SUM(C23:J23) -> 0 | L23: =TrialBalance!DJ70-SUM(C23:K23) -> 0 | M23: =TrialBalance!DU70-SUM(C23:L23) -> 0 | N23: =TrialBalance!EF70-SUM(C23:M23) -> 0
A24: Equipment Tools & Plant Hire | B24: =SUM(C24:N24) -> 0 | C24: =TrialBalance!O71-0 -> 0 | D24: =TrialBalance!Z71-C24 -> 0 | E24: =TrialBalance!AK71-SUM(C24:D24) -> 0 | F24: =TrialBalance!AV71-SUM(C24:E24) -> 0 | G24: =TrialBalance!BG71-SUM(C24:F24) -> 0 | H24: =TrialBalance!BR71-SUM(C24:G24) -> 0 | I24: =TrialBalance!CC71-SUM(C24:H24) -> 0 | J24: =TrialBalance!CN71-SUM(C24:I24) -> 0 | K24: =TrialBalance!CY71-SUM(C24:J24) -> 0 | L24: =TrialBalance!DJ71-SUM(C24:K24) -> 0 | M24: =TrialBalance!DU71-SUM(C24:L24) -> 0 | N24: =TrialBalance!EF71-SUM(C24:M24) -> 0
A25: Repairs & Maintenance | B25: =SUM(C25:N25) -> 0 | C25: =TrialBalance!O72-0 -> 0 | D25: =TrialBalance!Z72-C25 -> 0 | E25: =TrialBalance!AK72-SUM(C25:D25) -> 0 | F25: =TrialBalance!AV72-SUM(C25:E25) -> 0 | G25: =TrialBalance!BG72-SUM(C25:F25) -> 0 | H25: =TrialBalance!BR72-SUM(C25:G25) -> 0 | I25: =TrialBalance!CC72-SUM(C25:H25) -> 0 | J25: =TrialBalance!CN72-SUM(C25:I25) -> 0 | K25: =TrialBalance!CY72-SUM(C25:J25) -> 0 | L25: =TrialBalance!DJ72-SUM(C25:K25) -> 0 | M25: =TrialBalance!DU72-SUM(C25:L25) -> 0 | N25: =TrialBalance!EF72-SUM(C25:M25) -> 0
A26: Consumable Materials | B26: =SUM(C26:N26) -> 0 | C26: =TrialBalance!O73-0 -> 0 | D26: =TrialBalance!Z73-C26 -> 0 | E26: =TrialBalance!AK73-SUM(C26:D26) -> 0 | F26: =TrialBalance!AV73-SUM(C26:E26) -> 0 | G26: =TrialBalance!BG73-SUM(C26:F26) -> 0 | H26: =TrialBalance!BR73-SUM(C26:G26) -> 0 | I26: =TrialBalance!CC73-SUM(C26:H26) -> 0 | J26: =TrialBalance!CN73-SUM(C26:I26) -> 0 | K26: =TrialBalance!CY73-SUM(C26:J26) -> 0 | L26: =TrialBalance!DJ73-SUM(C26:K26) -> 0 | M26: =TrialBalance!DU73-SUM(C26:L26) -> 0 | N26: =TrialBalance!EF73-SUM(C26:M26) -> 0
A27: Advertising, Promotion & Entertainment | B27: =SUM(C27:N27) -> 0 | C27: =TrialBalance!O74+TrialBalance!O90-0 -> 0 | D27: =TrialBalance!Z74+TrialBalance!Z90-C27 -> 0 | E27: =TrialBalance!AK74+TrialBalance!AK90-SUM(C27:D27) -> 0 | F27: =TrialBalance!AV74+TrialBalance!AV90-SUM(C27:E27) -> 0 | G27: =TrialBalance!BG74+TrialBalance!BG90-SUM(C27:F27) -> 0 | H27: =TrialBalance!BR74+TrialBalance!BR90-SUM(C27:G27) -> 0 | I27: =TrialBalance!CC74+TrialBalance!CC90-SUM(C27:H27) -> 0 | J27: =TrialBalance!CN74+TrialBalance!CN90-SUM(C27:I27) -> 0 | K27: =TrialBalance!CY74+TrialBalance!CY90-SUM(C27:J27) -> 0 | L27: =TrialBalance!DJ74+TrialBalance!DJ90-SUM(C27:K27) -> 0 | M27: =TrialBalance!DU74+TrialBalance!DU90-SUM(C27:L27) -> 0 | N27: =TrialBalance!EF74+TrialBalance!EF90-SUM(C27:M27) -> 0
A28: Telephone Postage & Stationery | B28: =SUM(C28:N28) -> 0 | C28: =TrialBalance!O75-0 -> 0 | D28: =TrialBalance!Z75-C28 -> 0 | E28: =TrialBalance!AK75-SUM(C28:D28) -> 0 | F28: =TrialBalance!AV75-SUM(C28:E28) -> 0 | G28: =TrialBalance!BG75-SUM(C28:F28) -> 0 | H28: =TrialBalance!BR75-SUM(C28:G28) -> 0 | I28: =TrialBalance!CC75-SUM(C28:H28) -> 0 | J28: =TrialBalance!CN75-SUM(C28:I28) -> 0 | K28: =TrialBalance!CY75-SUM(C28:J28) -> 0 | L28: =TrialBalance!DJ75-SUM(C28:K28) -> 0 | M28: =TrialBalance!DU75-SUM(C28:L28) -> 0 | N28: =TrialBalance!EF75-SUM(C28:M28) -> 0
A29: Travel & Hotel Expenses | B29: =SUM(C29:N29) -> 0 | C29: =TrialBalance!O76-0 -> 0 | D29: =TrialBalance!Z76-C29 -> 0 | E29: =TrialBalance!AK76-SUM(C29:D29) -> 0 | F29: =TrialBalance!AV76-SUM(C29:E29) -> 0 | G29: =TrialBalance!BG76-SUM(C29:F29) -> 0 | H29: =TrialBalance!BR76-SUM(C29:G29) -> 0 | I29: =TrialBalance!CC76-SUM(C29:H29) -> 0 | J29: =TrialBalance!CN76-SUM(C29:I29) -> 0 | K29: =TrialBalance!CY76-SUM(C29:J29) -> 0 | L29: =TrialBalance!DJ76-SUM(C29:K29) -> 0 | M29: =TrialBalance!DU76-SUM(C29:L29) -> 0 | N29: =TrialBalance!EF76-SUM(C29:M29) -> 0
A30: Motor Vehicle Expenses | B30: =SUM(C30:N30) -> 0 | C30: =TrialBalance!O77-0 -> 0 | D30: =TrialBalance!Z77-C30 -> 0 | E30: =TrialBalance!AK77-SUM(C30:D30) -> 0 | F30: =TrialBalance!AV77-SUM(C30:E30) -> 0 | G30: =TrialBalance!BG77-SUM(C30:F30) -> 0 | H30: =TrialBalance!BR77-SUM(C30:G30) -> 0 | I30: =TrialBalance!CC77-SUM(C30:H30) -> 0 | J30: =TrialBalance!CN77-SUM(C30:I30) -> 0 | K30: =TrialBalance!CY77-SUM(C30:J30) -> 0 | L30: =TrialBalance!DJ77-SUM(C30:K30) -> 0 | M30: =TrialBalance!DU77-SUM(C30:L30) -> 0 | N30: =TrialBalance!EF77-SUM(C30:M30) -> 0
A31: Insurance Costs | B31: =SUM(C31:N31) -> 0 | C31: =TrialBalance!O78-0 -> 0 | D31: =TrialBalance!Z78-C31 -> 0 | E31: =TrialBalance!AK78-SUM(C31:D31) -> 0 | F31: =TrialBalance!AV78-SUM(C31:E31) -> 0 | G31: =TrialBalance!BG78-SUM(C31:F31) -> 0 | H31: =TrialBalance!BR78-SUM(C31:G31) -> 0 | I31: =TrialBalance!CC78-SUM(C31:H31) -> 0 | J31: =TrialBalance!CN78-SUM(C31:I31) -> 0 | K31: =TrialBalance!CY78-SUM(C31:J31) -> 0 | L31: =TrialBalance!DJ78-SUM(C31:K31) -> 0 | M31: =TrialBalance!DU78-SUM(C31:L31) -> 0 | N31: =TrialBalance!EF78-SUM(C31:M31) -> 0
A32: Leasing Charges | B32: =SUM(C32:N32) -> 0 | C32: =TrialBalance!O79-0 -> 0 | D32: =TrialBalance!Z79-C32 -> 0 | E32: =TrialBalance!AK79-SUM(C32:D32) -> 0 | F32: =TrialBalance!AV79-SUM(C32:E32) -> 0 | G32: =TrialBalance!BG79-SUM(C32:F32) -> 0 | H32: =TrialBalance!BR79-SUM(C32:G32) -> 0 | I32: =TrialBalance!CC79-SUM(C32:H32) -> 0 | J32: =TrialBalance!CN79-SUM(C32:I32) -> 0 | K32: =TrialBalance!CY79-SUM(C32:J32) -> 0 | L32: =TrialBalance!DJ79-SUM(C32:K32) -> 0 | M32: =TrialBalance!DU79-SUM(C32:L32) -> 0 | N32: =TrialBalance!EF79-SUM(C32:M32) -> 0
A33: Legal & Professional Fees | B33: =SUM(C33:N33) -> 0 | C33: =TrialBalance!O80-0 -> 0 | D33: =TrialBalance!Z80-C33 -> 0 | E33: =TrialBalance!AK80-SUM(C33:D33) -> 0 | F33: =TrialBalance!AV80-SUM(C33:E33) -> 0 | G33: =TrialBalance!BG80-SUM(C33:F33) -> 0 | H33: =TrialBalance!BR80-SUM(C33:G33) -> 0 | I33: =TrialBalance!CC80-SUM(C33:H33) -> 0 | J33: =TrialBalance!CN80-SUM(C33:I33) -> 0 | K33: =TrialBalance!CY80-SUM(C33:J33) -> 0 | L33: =TrialBalance!DJ80-SUM(C33:K33) -> 0 | M33: =TrialBalance!DU80-SUM(C33:L33) -> 0 | N33: =TrialBalance!EF80-SUM(C33:M33) -> 0
A34: Bad Debts written off | B34: =SUM(C34:N34) -> 0 | C34: =TrialBalance!O81-0 -> 0 | D34: =TrialBalance!Z81-C34 -> 0 | E34: =TrialBalance!AK81-SUM(C34:D34) -> 0 | F34: =TrialBalance!AV81-SUM(C34:E34) -> 0 | G34: =TrialBalance!BG81-SUM(C34:F34) -> 0 | H34: =TrialBalance!BR81-SUM(C34:G34) -> 0 | I34: =TrialBalance!CC81-SUM(C34:H34) -> 0 | J34: =TrialBalance!CN81-SUM(C34:I34) -> 0 | K34: =TrialBalance!CY81-SUM(C34:J34) -> 0 | L34: =TrialBalance!DJ81-SUM(C34:K34) -> 0 | M34: =TrialBalance!DU81-SUM(C34:L34) -> 0 | N34: =TrialBalance!EF81-SUM(C34:M34) -> 0
A35: Bank Interest Paid | B35: =SUM(C35:N35) -> 0 | C35: =TrialBalance!O82-0 -> 0 | D35: =TrialBalance!Z82-C35 -> 0 | E35: =TrialBalance!AK82-SUM(C35:D35) -> 0 | F35: =TrialBalance!AV82-SUM(C35:E35) -> 0 | G35: =TrialBalance!BG82-SUM(C35:F35) -> 0 | H35: =TrialBalance!BR82-SUM(C35:G35) -> 0 | I35: =TrialBalance!CC82-SUM(C35:H35) -> 0 | J35: =TrialBalance!CN82-SUM(C35:I35) -> 0 | K35: =TrialBalance!CY82-SUM(C35:J35) -> 0 | L35: =TrialBalance!DJ82-SUM(C35:K35) -> 0 | M35: =TrialBalance!DU82-SUM(C35:L35) -> 0 | N35: =TrialBalance!EF82-SUM(C35:M35) -> 0
A36: Bank Charges | B36: =SUM(C36:N36) -> 0 | C36: =TrialBalance!O83+TrialBalance!O88+TrialBalance!O89-0 -> 0 | D36: =TrialBalance!Z83+TrialBalance!Z88+TrialBalance!Z89-C36 -> 0 | E36: =TrialBalance!AK83+TrialBalance!AK88+TrialBalance!AK89-SUM(C36:D36) -> 0 | F36: =TrialBalance!AV83+TrialBalance!AV88+TrialBalance!AV89-SUM(C36:E36) -> 0 | G36: =TrialBalance!BG83+TrialBalance!BG88+TrialBalance!BG89-SUM(C36:F36) -> 0 | H36: =TrialBalance!BR83+TrialBalance!BR88+TrialBalance!BR89-SUM(C36:G36) -> 0 | I36: =TrialBalance!CC83+TrialBalance!CC88+TrialBalance!CC89-SUM(C36:H36) -> 0 | J36: =TrialBalance!CN83+TrialBalance!CN88+TrialBalance!CN89-SUM(C36:I36) -> 0 | K36: =TrialBalance!CY83+TrialBalance!CY88+TrialBalance!CY89-SUM(C36:J36) -> 0 | L36: =TrialBalance!DJ83+TrialBalance!DJ88+TrialBalance!DJ89-SUM(C36:K36) -> 0 | M36: =TrialBalance!DU83+TrialBalance!DU88+TrialBalance!DU89-SUM(C36:L36) -> 0 | N36: =TrialBalance!EF83+TrialBalance!EF88+TrialBalance!EF89-SUM(C36:M36) -> 0
A37: Charitable Donations | B37: =SUM(C37:N37) -> 0 | C37: =TrialBalance!O84-0 -> 0 | D37: =TrialBalance!Z84-C37 -> 0 | E37: =TrialBalance!AK84-SUM(C37:D37) -> 0 | F37: =TrialBalance!AV84-SUM(C37:E37) -> 0 | G37: =TrialBalance!BG84-SUM(C37:F37) -> 0 | H37: =TrialBalance!BR84-SUM(C37:G37) -> 0 | I37: =TrialBalance!CC84-SUM(C37:H37) -> 0 | J37: =TrialBalance!CN84-SUM(C37:I37) -> 0 | K37: =TrialBalance!CY84-SUM(C37:J37) -> 0 | L37: =TrialBalance!DJ84-SUM(C37:K37) -> 0 | M37: =TrialBalance!DU84-SUM(C37:L37) -> 0 | N37: =TrialBalance!EF84-SUM(C37:M37) -> 0
A38: Goodwill written off | B38: =SUM(C38:N38) -> 0 | C38: =TrialBalance!O85-0 -> 0 | D38: =TrialBalance!Z85-C38 -> 0 | E38: =TrialBalance!AK85-SUM(C38:D38) -> 0 | F38: =TrialBalance!AV85-SUM(C38:E38) -> 0 | G38: =TrialBalance!BG85-SUM(C38:F38) -> 0 | H38: =TrialBalance!BR85-SUM(C38:G38) -> 0 | I38: =TrialBalance!CC85-SUM(C38:H38) -> 0 | J38: =TrialBalance!CN85-SUM(C38:I38) -> 0 | K38: =TrialBalance!CY85-SUM(C38:J38) -> 0 | L38: =TrialBalance!DJ85-SUM(C38:K38) -> 0 | M38: =TrialBalance!DU85-SUM(C38:L38) -> 0 | N38: =TrialBalance!EF85-SUM(C38:M38) -> 0
A39: Loss on disposal of assets | B39: =SUM(C39:N39) -> 0 | C39: =TrialBalance!O86-0 -> 0 | D39: =TrialBalance!Z86-C39 -> 0 | E39: =TrialBalance!AK86-SUM(C39:D39) -> 0 | F39: =TrialBalance!AV86-SUM(C39:E39) -> 0 | G39: =TrialBalance!BG86-SUM(C39:F39) -> 0 | H39: =TrialBalance!BR86-SUM(C39:G39) -> 0 | I39: =TrialBalance!CC86-SUM(C39:H39) -> 0 | J39: =TrialBalance!CN86-SUM(C39:I39) -> 0 | K39: =TrialBalance!CY86-SUM(C39:J39) -> 0 | L39: =TrialBalance!DJ86-SUM(C39:K39) -> 0 | M39: =TrialBalance!DU86-SUM(C39:L39) -> 0 | N39: =TrialBalance!EF86-SUM(C39:M39) -> 0
A40: Depreciation | B40: =SUM(C40:N40) -> 0 | C40: =TrialBalance!O87-0 -> 0 | D40: =TrialBalance!Z87-C40 -> 0 | E40: =TrialBalance!AK87-SUM(C40:D40) -> 0 | F40: =TrialBalance!AV87-SUM(C40:E40) -> 0 | G40: =TrialBalance!BG87-SUM(C40:F40) -> 0 | H40: =TrialBalance!BR87-SUM(C40:G40) -> 0 | I40: =TrialBalance!CC87-SUM(C40:H40) -> 0 | J40: =TrialBalance!CN87-SUM(C40:I40) -> 0 | K40: =TrialBalance!CY87-SUM(C40:J40) -> 0 | L40: =TrialBalance!DJ87-SUM(C40:K40) -> 0 | M40: =TrialBalance!DU87-SUM(C40:L40) -> 0 | N40: =TrialBalance!EF87-SUM(C40:M40) -> 0
A41: Administrative Expenses | B41: =SUM(B18:B40) -> 0 | C41: =SUM(C18:C40) -> 0 | D41: =SUM(D18:D40) -> 0 | E41: =SUM(E18:E40) -> 0 | F41: =SUM(F18:F40) -> 0 | G41: =SUM(G18:G40) -> 0 | H41: =SUM(H18:H40) -> 0 | I41: =SUM(I18:I40) -> 0 | ... N41: =SUM(N18:N40) -> 0
A43: Operating Profit | B43: =B16-B41 -> 0 | C43: =C16-C41 -> 0 | D43: =D16-D41 -> 0 | E43: =E16-E41 -> 0 | F43: =F16-F41 -> 0 | G43: =G16-G41 -> 0 | H43: =H16-H41 -> 0 | I43: =I16-I41 -> 0 | ... N43: =N16-N41 -> 0
A44: Interest received | B44: =SUM(C44:N44) -> 0 | C44: =-(TrialBalance!O58-0) -> 0 | D44: =-TrialBalance!Z58-C44 -> 0 | E44: =-TrialBalance!AK58-SUM(C44:D44) -> 0 | F44: =-TrialBalance!AV58-SUM(C44:E44) -> 0 | G44: =-TrialBalance!BG58-SUM(C44:F44) -> 0 | H44: =-TrialBalance!BR58-SUM(C44:G44) -> 0 | I44: =-TrialBalance!CC58-SUM(C44:H44) -> 0 | J44: =-TrialBalance!CN58-SUM(C44:I44) -> 0 | K44: =-TrialBalance!CY58-SUM(C44:J44) -> 0 | L44: =-TrialBalance!DJ58-SUM(C44:K44) -> 0 | M44: =-TrialBalance!DU58-SUM(C44:L44) -> 0 | N44: =-TrialBalance!EF58-SUM(C44:M44) -> 0
A45: Profit (Loss) before Tax | B45: =B43+B44 -> 0 | C45: =C43+C44 -> 0 | D45: =D43+D44 -> 0 | E45: =E43+E44 -> 0 | F45: =F43+F44 -> 0 | G45: =G43+G44 -> 0 | H45: =H43+H44 -> 0 | I45: =I43+I44 -> 0 | ... N45: =N43+N44 -> 0

Sheet PubP&L
C2: Profit and Loss Account
C3: for the year ended | D3: =Admin!B32 -> 46477
A5: =Admin!B8 -> 45747 | E5: =D3 -> 46477
A6: £ | B6: £ | E6: £ | F6: £
B7: =OpenAccounts!E43 -> 0 | C7: Sales Turnover | F7: =-(TrialBalance!EJ53+TrialBalance!EJ54+TrialBalance!EJ55+TrialBalance!EJ56) -> 0
B8: =OpenAccounts!E44 -> 0 | C8: Investment Grants received | F8: =-(TrialBalance!EJ57) -> 0
B9: =SUM(B7:B8) -> 0 | C9: Sales Turnover | F9: =SUM(F7:F8) -> 0
C11: Cost of Sales
A12: =OpenAccounts!E46 -> 0 | C12: Opening Stock at | D12: =Admin!B9 -> 45748 | E12: =TrialBalance!D19 -> 0
A13: =OpenAccounts!E47 -> 0 | C13: Purchases | E13: =F14-E12+E14 -> 0
A14: =OpenAccounts!E48 -> 0 | B14: =A12+A13-A14 -> 0 | C14: Less Closing Stock at | D14: =D3 -> 46112 | E14: =TrialBalance!EJ19 -> 0 | F14: =TrialBalance!EJ60+TrialBalance!EJ62 -> 0
B15: =OpenAccounts!E49 -> 0 | C15: Sub contractors | F15: =TrialBalance!EJ61 -> 0
B16: =SUM(B14:B15) -> 0 | C16: Cost of Sales | F16: =SUM(F14:F15) -> 0
B18: =B9-B16 -> 0 | C18: Gross Profit | F18: =F9-F16 -> 0
C20: Administrative Expenses
A21: =OpenAccounts!E54 -> 0 | C21: Wages and Salaries | E21: =TrialBalance!EJ64+TrialBalance!EJ65 -> 0
A22: =OpenAccounts!E55 -> 0 | C22: Directors Wages | E22: =TrialBalance!EJ66 -> 0
A23: =OpenAccounts!E56 -> 0 | C23: National Insurance | E23: =TrialBalance!EJ67 -> 0
A24: =OpenAccounts!E57 -> 0 | C24: Premises Rent & Rates | E24: =TrialBalance!EJ68 -> 0
A25: =OpenAccounts!E58 -> 0 | C25: Premises Light & Heating | E25: =TrialBalance!EJ69 -> 0
A26: =OpenAccounts!E59 -> 0 | C26: Distribution Transport Costs | E26: =TrialBalance!EJ70 -> 0
A27: =OpenAccounts!E60 -> 0 | C27: Equipment Tools & Plant Hire | E27: =TrialBalance!EJ71 -> 0
A28: =OpenAccounts!E61 -> 0 | C28: Repairs & Maintenance | E28: =TrialBalance!EJ72 -> 0
A29: =OpenAccounts!E62 -> 0 | C29: Consumable Materials | E29: =TrialBalance!EJ73 -> 0
A30: =OpenAccounts!E63 -> 0 | C30: Advertising, Promotion & Entertainment | E30: =TrialBalance!EJ74+TrialBalance!EJ90 -> 0
A31: =OpenAccounts!E64 -> 0 | C31: Telephone Postage & Stationery | E31: =TrialBalance!EJ75 -> 0
A32: =OpenAccounts!E65 -> 0 | C32: Travel & Hotel Expenses | E32: =TrialBalance!EJ76 -> 0
A33: =OpenAccounts!E66 -> 0 | C33: Motor Vehicle Expenses | E33: =TrialBalance!EJ77 -> 0
A34: =OpenAccounts!E67 -> 0 | C34: Insurance Costs | E34: =TrialBalance!EJ78 -> 0
A35: =OpenAccounts!E68 -> 0 | C35: Leasing Charges | E35: =TrialBalance!EJ79 -> 0
A36: =OpenAccounts!E69 -> 0 | C36: Legal & Professional Fees | E36: =TrialBalance!EJ80 -> 0
A37: =OpenAccounts!E70 -> 0 | C37: Bad Debts written off | E37: =TrialBalance!EJ81 -> 0
A38: =OpenAccounts!E71 -> 0 | C38: Bank Interest Paid | E38: =TrialBalance!EJ82 -> 0
A39: =OpenAccounts!E72 -> 0 | C39: Bank Charges | E39: =TrialBalance!EJ83+TrialBalance!EJ88+TrialBalance!EJ89 -> 0
A40: =OpenAccounts!E73 -> 0 | C40: Charitable Donations | E40: =TrialBalance!EJ84 -> 0
A41: =OpenAccounts!E74 -> 0 | C41: Goodwill written off | E41: =TrialBalance!EJ85 -> 0
A42: =OpenAccounts!E75 -> 0 | C42: Loss on disposal of assets | E42: =TrialBalance!EJ86 -> 0
A43: =OpenAccounts!E76 -> 0 | C43: Depreciation | E43: =TrialBalance!EJ87 -> 0
B44: =SUM(A21:A43) -> 0 | C44: Administrative Expenses | F44: =SUM(E21:E43) -> 0
B46: =B18-B44 -> 0 | C46: Operating Profit | F46: =F18-F44 -> 0
B48: =OpenAccounts!E80 -> 0 | C48: Other Income | F48: =-TrialBalance!EJ58 -> 0
B49: =B46+B48 -> 0 | C49: Profit (Loss) before Tax | F49: =F46+F48 -> 0
B50: =OpenAccounts!E82 -> 0 | C50: Corporation tax | F50: =TrialBalance!EJ47 -> 0
B51: =B49-B50 -> 0 | C51: Profit (Loss) after Tax | F51: =F49-F50 -> 0
B52: =OpenAccounts!E84 -> 0 | C52: Dividends | F52: =TrialBalance!EJ48 -> 0
A54: £ | B54: =B51-B52 -> 0 | C54: Retained Profit (Loss) for the year | E54: £ | F54: =F51-F52 -> 0

Sheet PubBalSht
C1: Balance Sheet
C2: as at | D2: ='PubP&L'!D3 -> 46477
A3: ='PubP&L'!A5 -> 45747 | E3: ='PubP&L'!E5 -> 46112
A4: £ | B4: £ | E4: £ | F4: £
B6: =SUM(TrialBalance!D6:D17) -> 0 | C6: Fixed Assets | F6: =SUM(TrialBalance!EJ6:EJ17) -> 0
C7: Tangible assets (note 1)
C9: Current Assets
A10: =TrialBalance!D19 -> 0 | C10: Stock at cost | E10: =TrialBalance!EJ19 -> 0
A11: =TrialBalance!D20 -> 0 | C11: Trade Debtors | E11: =TrialBalance!EJ20 -> 0
A12: =IF(SUM(TrialBalance!D22:D24)>0,SUM(TrialBalance!D22:D24)+TrialBalance!D25,TrialBalance!D25) -> 0 | C12: Cash at bank and in hand | E12: =IF(SUM(TrialBalance!EJ22:EJ24)>0,SUM(TrialBalance!EJ22:EJ24)+TrialBalance!EJ25+TrialBalance!EJ26,TrialBalance!EJ25) -> 0
A13: =SUM(A10:A12) -> 0 | C13: Current Assets | E13: =SUM(E10:E12) -> 0
C15: Current Liabilities (due within one year)
A16: =-SUM(TrialBalance!D28:D31) -> 0 | C16: Trade Creditors | E16: =-SUM(TrialBalance!EJ28:EJ31) -> 0
A17: =-TrialBalance!D35 -> 0 | C17: Corporation Tax | E17: =-TrialBalance!EJ35 -> 0
A18: =-SUM(TrialBalance!D32:D34) -> 0 | C18: Taxation and Social Security | E18: =-SUM(TrialBalance!EJ32:EJ34) -> 0
A19: =IF(SUM(TrialBalance!D22:D24)<0,-SUM(TrialBalance!D22:D24),0) -> 0 | C19: Bank Overdraft | E19: =IF(SUM(TrialBalance!EJ22:EJ24)<0,-SUM(TrialBalance!EJ22:EJ24),0) -> 0
A20: =SUM(A16:A19) -> 0 | C20: Current Liabilities | E20: =SUM(E16:E19) -> 0
B22: =A13-A20 -> 0 | C22: Net Current Assets | F22: =E13-E20 -> 0
B24: =TrialBalance!D37 -> 0 | C24: Long Term Debtor (repayable within 3 - 5 years) | F24: =TrialBalance!EJ37 -> 0
B26: =SUM(B6:B25) -> 0 | C26: Total assets less current liabilities | F26: =SUM(F6:F25) -> 0
C28: Other Creditors
A29: =-TrialBalance!D39 -> 0 | C29: Directors Loan Account | E29: =-TrialBalance!EJ39 -> 0
A30: =-TrialBalance!D40 -> 0 | C30: Creditors (falling due after more than one year) | E30: =-TrialBalance!EJ40 -> 0
B31: =SUM(A29:A30) -> 0 | F31: =SUM(E29:E30) -> 0
A33: £ | B33: =B26-B31 -> 0 | C33: Net Assets | E33: £ | F33: =F26-F31 -> 0
C35: Capital and Reserves
B36: =-TrialBalance!D42 -> 0 | C36: Called up share capital 2 ordinary shares of £1.00 each | F36: =-TrialBalance!EJ42 -> 0
B37: =-TrialBalance!D43 -> 0 | C37: Retained Profit and Loss account | F37: =-TrialBalance!EJ43 -> 0
B38: =-TrialBalance!D44 -> 0 | C38: Capital Reserves | F38: =-TrialBalance!EJ44 -> 0
A39: £ | B39: =SUM(B36:B38) -> 0 | C39: Shareholders' Funds | E39: £ | F39: =SUM(F36:F38) -> 0
A41: For year end | B41: =D2 -> 46112 | C41: the company was entitled to exemption from audit under section 477 of the
A42: Companies Act 2006 relating to small companies.
A43: Directors' responsibilities:
A44: a) The members have not required the company to obtain an audit of its accounts for the year in question in accordance
A45: with section 476, of the Companies Act 2006
A46: b) The directors acknowledge their responsibilities for complying with the requirements of the Act with respect to
A47: accounting records and the preparation of accounts under the Companies Act 2006.
A48: c) The company directors acknowledge their responsibility for preparing accounts which give a "true and fair view" of
A49: the state of affairs of the company and of its profit or loss for the year
A50: d) The accounts have been delivered in accordance with the provisions applicable to companies subject to the
A51: small companies regime.
A52: e) The accounts have been prepared in accordance with the special provisions of the Companies Act relating to small
A53: companies
A55: Director's Signature
A56: Name of Director | C56: =OpenAccounts!E5 -> 0
A57: Date Signed | C57: =TODAY() -> 45751
A59: Company Number | C59: =OpenAccounts!E3 -> 0
A60: Registered Office | C60: =OpenAccounts!J3 -> 0
C61: =OpenAccounts!J4 -> 0
C62: =OpenAccounts!J5 -> 0
C63: =OpenAccounts!J6 -> 0

Sheet PubNotes
A1: Notes to the accounts
A3: 1. Tangible Assets
B4: Land and Buildings | C4: Plant and Machinery | D4: Fixtures & Fittings | E4: Computer Equipment | F4: Motor Vehicles | G4: Total Tangible Assets
B6: £ | C6: £ | D6: £ | E6: £ | F6: £ | G6: £
A7: Original Cost
A8: =Admin!B9 -> 45748 | B8: =IF([1]Schedule!$E$11>0,[1]Schedule!$E$11,0) -> 0 | C8: =IF([1]Schedule!$E$22>0,[1]Schedule!$E$22,0) -> 0 | D8: =IF([1]Schedule!$E$30>0,[1]Schedule!$E$30,0) -> 0 | E8: =IF([1]Schedule!$E$41>0,[1]Schedule!$E$41,0) -> 0 | F8: =IF([1]Schedule!$E$55>0,[1]Schedule!$E$55,0) -> 0 | G8: =SUM(B8:F8) -> 0
A9: Additions | B9: =IF([1]Schedule!$E$64>0,[1]Schedule!$E$64,0) -> 0 | C9: =IF([1]Schedule!$E$75>0,[1]Schedule!$E$75,0) -> 0 | D9: =IF([1]Schedule!$E$83>0,[1]Schedule!$E$83,0) -> 0 | E9: =IF([1]Schedule!$E$94>0,[1]Schedule!$E$94,0) -> 0 | F9: =IF([1]Schedule!$E$108>0,[1]Schedule!$E$108,0) -> 0 | G9: =SUM(B9:F9) -> 0
A10: Disposals | B10: =IF(([1]Schedule!$W$11+[1]Schedule!$W$64)>0,[1]Schedule!$W$11+[1]Schedule!$W$64,0) -> 0 | C10: =IF(([1]Schedule!$W$22+[1]Schedule!$W$75)>0,[1]Schedule!$W$22+[1]Schedule!$W$75,0) -> 0 | D10: =IF(([1]Schedule!$W$30+[1]Schedule!$W$83)>0,[1]Schedule!$W$30+[1]Schedule!$W$83,0) -> 0 | E10: =IF(([1]Schedule!$W$41+[1]Schedule!$W$94)>0,[1]Schedule!$W$41+[1]Schedule!$W$94,0) -> 0 | F10: =IF(([1]Schedule!$W$55+[1]Schedule!$W$108)>0,[1]Schedule!$W$55+[1]Schedule!$W$108,0) -> 0 | G10: =SUM(B10:F10) -> 0
A11: ='PubP&L'!D3 -> 46477 | B11: =B8+B9-B10 -> 0 | C11: =C8+C9-C10 -> 0 | D11: =D8+D9-D10 -> 0 | E11: =E8+E9-E10 -> 0 | F11: =F8+F9-F10 -> 0 | G11: =G8+G9-G10 -> 0
A13: Depreciation
A14: =A8 -> 45748 | B14: =IF([1]Schedule!$F$11>0,[1]Schedule!$F$11,0) -> 0 | C14: =IF([1]Schedule!$F$22>0,[1]Schedule!$F$22,0) -> 0 | D14: =IF([1]Schedule!$F$30>0,[1]Schedule!$F$30,0) -> 0 | E14: =IF([1]Schedule!$F$41>0,[1]Schedule!$F$41,0) -> 0 | F14: =IF([1]Schedule!$F$55>0,[1]Schedule!$F$55,0) -> 0 | G14: =SUM(B14:F14) -> 0
A15: Charge for the year | B15: =IF(([1]Schedule!$I$11+[1]Schedule!$I$64)>0,[1]Schedule!$I$11+[1]Schedule!$I$64,0) -> 0 | C15: =IF(([1]Schedule!$I$22+[1]Schedule!$I$75)>0,[1]Schedule!$I$22+[1]Schedule!$I$75,0) -> 0 | D15: =IF(([1]Schedule!$I$30+[1]Schedule!$I$83)>0,[1]Schedule!$I$30+[1]Schedule!$I$83,0) -> 0 | E15: =IF(([1]Schedule!$I$41+[1]Schedule!$I$94)>0,[1]Schedule!$I$41+[1]Schedule!$I$94,0) -> 0 | F15: =IF(([1]Schedule!$I$55+[1]Schedule!$I$108)>0,[1]Schedule!$I$55+[1]Schedule!$I$108,0) -> 0 | G15: =SUM(B15:F15) -> 0
A16: On Disposals | B16: =IF(([1]Schedule!$X$11+[1]Schedule!$X$64)>0,[1]Schedule!$X$11+[1]Schedule!$X$64,0) -> 0 | C16: =IF(([1]Schedule!$X$22+[1]Schedule!$X$75)>0,[1]Schedule!$X$22+[1]Schedule!$X$75,0) -> 0 | D16: =IF(([1]Schedule!$X$30+[1]Schedule!$X$83)>0,[1]Schedule!$X$30+[1]Schedule!$X$83,0) -> 0 | E16: =IF(([1]Schedule!$X$41+[1]Schedule!$X$94)>0,[1]Schedule!$X$41+[1]Schedule!$X$94,0) -> 0 | F16: =IF(([1]Schedule!$X$55+[1]Schedule!$X$108)>0,[1]Schedule!$X$55+[1]Schedule!$X$108,0) -> 0 | G16: =SUM(B16:F16) -> 0
A17: =A11 -> 46112 | B17: =B14-B16+B15 -> 0 | C17: =C14-C16+C15 -> 0 | D17: =D14-D16+D15 -> 0 | E17: =E14-E16+E15 -> 0 | F17: =F14-F16+F15 -> 0 | G17: =SUM(B17:F17) -> 0
A19: Net Book Value
A20: =A11 -> 46112 | B20: =B11-B17 -> 0 | C20: =C11-C17 -> 0 | D20: =D11-D17 -> 0 | E20: =E11-E17 -> 0 | F20: =F11-F17 -> 0 | G20: =G11-G17 -> 0
A23: Fixed assets are included at purchase cost
A24: Depreciation is calculated to write off the cost of tangible assets by equal instalments
A25: over their estimated useful lives at the following rates:
A27: Land & Buildings | B27: =[1]Schedule!$H$7 -> 0 | C27: per annum
A28: Plant & Equipment | B28: =[1]Schedule!$H$13 -> 0.1 | C28: per annum
A29: Fixtures & Fittings | B29: =[1]Schedule!$H$24 -> 0.2 | C29: per annum
A30: Computer Software | B30: =[1]Schedule!$H$32 -> 0.33 | C30: per annum
A31: Motor Vehicles | B31: =[1]Schedule!$H$43 -> 0.25 | C31: per annum
A34: 2. Directors emoluments
A35: Aggregate emoluments paid to the company directors | D35: =TrialBalance!EJ66 -> 0
A37: 3. Dividends Declared
A38: Gross dividend declared for the year ended | D38: ='PubP&L'!D3 -> 46112 | F38: =[8]Boardmeeting!$E$4 -> 0
A40: 4. Corporation Tax
A41: Corporation tax for the year to | B41: ='PubP&L'!D3 -> 46112 | D41: =CorporationTax!K35 -> 0

Sheet Report
A12: =OpenAccounts!E2 -> 0
A20: ANNUAL FINANCIAL REPORT
A22: For the year ended | F22: =PubBalSht!D2 -> 46477
B46: =OpenAccounts!J3 -> 0
B47: =OpenAccounts!J4 -> 0
B48: =OpenAccounts!J5 -> 0
B49: =OpenAccounts!J6 -> 0
B50: Tel No. | C50: =OpenAccounts!E4 -> 0 | F50: Company registration number | I50: =OpenAccounts!E3 -> 0
A56: =OpenAccounts!E2 -> 0
D60: CLIENT CERTIFICATE
B62: I/We certify that to the best of my/our knowledge and belief, the
B63: accounts produced together with explanations given to my/our
B64: accountant constitute a true and correct record of all the
B65: transactions of my/our business for the year ended | F65: ='PubP&L'!E5 -> 46112
B66: and confirm that the attached accounts have my/our approval
B69: Signature
B71: DIRECTOR | D71: =OpenAccounts!E5 -> 0
B74: Dated | D74: =TODAY() -> 45751
A78: =OpenAccounts!E2 -> 0
B79: Directors’ Report for the 12 months to | G79: ='PubP&L'!E5 -> 46112
A81: The directors submit their annual report and the financial accounts of the company for the
A82: 12 months ended | C82: ='PubP&L'!E5 -> 46112
A84: The principal activity of the company is | E84: =OpenAccounts!E8 -> 0
A86: Business Review
A87: Sales turnover in the year under review was | E87: ='PubP&L'!F9 -> 0 | F87: compared with | H87: ='PubP&L'!B9 -> 0 | I87: last year.
A88: Sales turnover reflected the continued demand for the company's products and services
A89: Trading margins were | D89: =IF('PubP&L'!F9>0,'PubP&L'!F18/'PubP&L'!F9," ") | E89: compared with the previous year | I89: =IF('PubP&L'!B9>0,'PubP&L'!B18/'PubP&L'!B9," ")
A90: reflecting market conditions experienced during the financial year.
A92: Dividends Declared
A93: Based upon retained earnings and the current years' financial result the board of directors
A94: declared a dividend payment of | D94: =[8]Boardmeeting!$E$4 -> 0 | E94: ensuring sufficient funds being retained for next year
A95: The total number of £1 ordinary shares issued at the end of the financial year was | I95: =[8]RegisterofMembers!$G$1 -> 0
A96: Shareholders entitled to dividend payment in proportion to number of ordinary shares issued were
A97: =IF([8]RegisterofMembers!$A$3>0,[8]RegisterofMembers!$A$3," ") | D97: Number of shares held | F97: =[8]RegisterofMembers!$G$3 -> 0 | G97: as at | H97: ='PubP&L'!E5 -> 46112
A98: =IF([8]RegisterofMembers!$A$4>0,[8]RegisterofMembers!$A$4," ") | D98: Number of shares held | F98: =[8]RegisterofMembers!$G$4 -> 0 | G98: as at | H98: ='PubP&L'!E5 -> 46112
A100: Financial Control
A101: The directors acknowledge responsibility for the company’s system of internal financial control
A102: and believe the established systems including the computerization of the company’s financial
A103: accounts are appropriate to the business. No material losses or contingencies have arisen
A104: during the 12 months trading period that would require disclosure by the directors.
A106: Having formed an opinion at the time of approving these accounts it is the directors intention
A107: to continue to support the company financially, the profits earned and retained within the
A108: company being sufficient to ensure the company has adequate resources to continue
A109: existing trading policies and the directors have adopted a going concern basis in preparing the
A110: accounts.
A112: It is the view of the directors that the accounts presented represent a true and fair view
A113: of the state of affairs of the company and result for the 12 months to | H113: ='PubP&L'!E5 -> 46112
A114: Suitable accounting policies have been established and applied consistently and disclose
A115: with reasonable accuracy the financial position of the company.
D118: Signed by
B119: =OpenAccounts!E5 -> 0 | D119: Director | F119: Date: | G119: =TODAY() -> 45751

Sheet CorporationTax
B2: =IF(OpenAccounts!E2>0,OpenAccounts!E2," ") | E2: Corporation Tax Computation | K2: Tax Calculation
I3: £ | K3: £
B5: Operating profit before tax for the 12 months | E5: =Admin!L6 -> 46113 | G5: to | H5: =Admin!N7 -> 46477 | K5: ='PubP&L'!F46 -> 0
C7: Add back goodwill written off | I7: =IF(TrialBalance!EJ85>0,TrialBalance!EJ85," ")
C8: Add back depreciation charged during the year | I8: =IF(TrialBalance!EJ87>0,TrialBalance!EJ87," ")
C9: Add back business entertainment | I9: =IF(TrialBalance!EJ90>0,TrialBalance!EJ90," ")
C10: Add back depreciation, goodwill and business entertainment | K10: =SUM(I6:I9) -> 0
B12: Operational profit chargeable to corporation tax | K12: =K5+K10 -> 0
B14: Deduct Capital Allowances
B15: Annual Investment Allowances plant & equipment bought | E15: =E5 -> 45748 | F15: =H5 -> 46477 | G15: =Admin!G5 -> 100 | I15: =IF(K79>0,K79,0) -> 0 | K15: See Note 1
B16: Writing Down Allowance cars bought between | E16: =E5 -> 45748 | F16: =H5 -> 46477 | G16: =Admin!G6 -> 18 | I16: =IF(K91>0,K91,0) -> 0 | K16: See Note 2
B17: Writing Down Allowance assets purchased prior to | E17: =E5 -> 45748 | G17: =Admin!G6 -> 18 | I17: =IF(K99>0,K99,0) -> 0 | K17: See Note 3
B18: Balancing charges on assets disposed of between | E18: =E5 -> 45748 | F18: =H5 -> 46477 | I18: =IF(K102<>0,-K102,0) -> 0 | K18: See Note 4
C20: Deduct Capital Allowances | K20: =SUM(I14:I19) -> 0
B22: Trading and professional profit after deducting capital allowances | K22: =K12-K20 -> 0
B24: Add gross bank interest received | K24: =-TrialBalance!EJ58 -> 0
B26: Deduct losses brought forward from previous years | K26: =OpenAccounts!Q5 -> 0
B28: Amount chargeable to Corporation Tax for the year to | E28: =H5 -> 46477 | K28: =K22+K24-K26 -> 0
B29: Add franked investment income (exempt distributions received) | K29: =OpenAccounts!Q6 -> 0
B30: Augmented profits, which the marginal relief limits are tested against | K30: =K28+K29 -> 0
A31: Days | B31: Tax Calculation | C31: From | D31: To | E31: Tax Year | F31: Taxable | G31: % | I31: Corp Tax
A33: =D33-C33+1 -> 365 | B33: Corporation Tax | C33: =Admin!L6 -> 45748 | D33: =Admin!N6 -> 46112 | E33: =Admin!K6 -> 2026 | F33: =IF(K28>0,K28*A33/A35,0) -> 0 | G33: =IF(K30*A33/A35<=Admin!$T$6*A33/A35/(1+Admin!$P$14),Admin!P6,Admin!$R$6) -> 19 | I33: =J33-L33 -> 0 | J33: =F33*G33/100 -> 0 | L33: =IF(AND(K30*A33/A35>Admin!$T$6*A33/A35/(1+Admin!$P$14),K30*A33/A35<Admin!$U$6*A33/A35/(1+Admin!$P$14)),(Admin!$U$6*A33/A35/(1+Admin!$P$14)-K30*A33/A35)*F33/(K30*A33/A35)*Admin!$S$6,0) -> 0
A34: =MAX(0,D34-C34+1) -> 0 | B34: Corporation Tax | C34: =Admin!L7 -> 46113 | D34: =Admin!N7 -> 46477 | E34: =Admin!K7 -> 2027 | F34: =IF(K28>0,K28*A34/A35,0) -> 0 | G34: =IF(K30*A34/A35<=Admin!$T$7*A34/A35/(1+Admin!$P$14),Admin!P7,Admin!$R$7) -> 19 | I34: =J34-L34 -> 0 | J34: =F34*G34/100 -> 0 | L34: =IF(AND(K30*A34/A35>Admin!$T$7*A34/A35/(1+Admin!$P$14),K30*A34/A35<Admin!$U$7*A34/A35/(1+Admin!$P$14)),(Admin!$U$7*A34/A35/(1+Admin!$P$14)-K30*A34/A35)*F34/(K30*A34/A35)*Admin!$S$7,0) -> 0
A35: =D34-C33+1 -> 365 | C35: Corporation Tax chargeable | K35: =ROUND(SUM(I33:I34),2) -> 0
C37: Deduct Income tax deducted from gross bank interest | K37: =TrialBalance!EH35 -> 0
C39: TAX OUTSTANDING | K39: =K35-K37 -> 0
B44: CAPITAL ALLOWANCES DEDUCTED
F45: Capital Expenditure | I45: Annual Investment Allowances
A46: Note 1 | B46: Annual Investment Allowances
F47: £ | I47: £
B48: Expenditure on Plant & Machinery between | D48: =E5 -> 45748 | E48: =H5 -> 46477
A49: =IF([1]Schedule!$E$67>0,[1]Schedule!$B$67," ") | B49: =IF([1]Schedule!$E$67>0,[1]Schedule!$C$67," ") | F49: =IF([1]Schedule!$E$67>0,[1]Schedule!$E$67," ") | I49: =IF([1]Schedule!$E$67>0,[1]Schedule!$Q$67," ")
A50: =IF([1]Schedule!$E$68>0,[1]Schedule!$B$68," ") | B50: =IF([1]Schedule!$E$68>0,[1]Schedule!$C$68," ") | F50: =IF([1]Schedule!$E$68>0,[1]Schedule!$E$68," ") | I50: =IF([1]Schedule!$E$68>0,[1]Schedule!$Q$68," ")
A51: =IF([1]Schedule!$E$69>0,[1]Schedule!$B$69," ") | B51: =IF([1]Schedule!$E$69>0,[1]Schedule!$C$69," ") | F51: =IF([1]Schedule!$E$69>0,[1]Schedule!$E$69," ") | I51: =IF([1]Schedule!$E$69>0,[1]Schedule!$Q$69," ")
A52: =IF([1]Schedule!$E$70>0,[1]Schedule!$B$70," ") | B52: =IF([1]Schedule!$E$70>0,[1]Schedule!$C$70," ") | F52: =IF([1]Schedule!$E$70>0,[1]Schedule!$E$70," ") | I52: =IF([1]Schedule!$E$70>0,[1]Schedule!$Q$70," ")
A53: =IF([1]Schedule!$E$71>0,[1]Schedule!$B$71," ") | B53: =IF([1]Schedule!$E$71>0,[1]Schedule!$C$71," ") | F53: =IF([1]Schedule!$E$71>0,[1]Schedule!$E$71," ") | I53: =IF([1]Schedule!$E$71>0,[1]Schedule!$Q$71," ")
A54: =IF([1]Schedule!$E$72>0,[1]Schedule!$B$72," ") | B54: =IF([1]Schedule!$E$72>0,[1]Schedule!$C$72," ") | F54: =IF([1]Schedule!$E$72>0,[1]Schedule!$E$72," ") | I54: =IF([1]Schedule!$E$72>0,[1]Schedule!$Q$72," ")
A55: =IF([1]Schedule!$E$73>0,[1]Schedule!$B$73," ") | B55: =IF([1]Schedule!$E$73>0,[1]Schedule!$C$73," ") | F55: =IF([1]Schedule!$E$73>0,[1]Schedule!$E$73," ") | I55: =IF([1]Schedule!$E$73>0,[1]Schedule!$Q$73," ")
A56: =IF([1]Schedule!$E$74>0,[1]Schedule!$B$74," ") | B56: =IF([1]Schedule!$E$74>0,[1]Schedule!$C$74," ") | F56: =IF([1]Schedule!$E$74>0,[1]Schedule!$E$74," ") | I56: =IF([1]Schedule!$E$74>0,[1]Schedule!$Q$74," ")
B57: Expenditure on Fixtures & Fittings between | D57: =E5 -> 45748 | E57: =H5 -> 46477
A58: =IF([1]Schedule!$E$78>0,[1]Schedule!$B$78," ") | B58: =IF([1]Schedule!$E$78>0,[1]Schedule!$C$78," ") | F58: =IF([1]Schedule!$E$78>0,[1]Schedule!$E$78," ") | I58: =IF([1]Schedule!$E$78>0,[1]Schedule!$Q$78," ")
A59: =IF([1]Schedule!$E$79>0,[1]Schedule!$B$79," ") | B59: =IF([1]Schedule!$E$79>0,[1]Schedule!$C$79," ") | F59: =IF([1]Schedule!$E$79>0,[1]Schedule!$E$79," ") | I59: =IF([1]Schedule!$E$79>0,[1]Schedule!$Q$79," ")
A60: =IF([1]Schedule!$E$80>0,[1]Schedule!$B$80," ") | B60: =IF([1]Schedule!$E$80>0,[1]Schedule!$C$80," ") | F60: =IF([1]Schedule!$E$80>0,[1]Schedule!$E$80," ") | I60: =IF([1]Schedule!$E$80>0,[1]Schedule!$Q$80," ")
A61: =IF([1]Schedule!$E$81>0,[1]Schedule!$B$81," ") | B61: =IF([1]Schedule!$E$81>0,[1]Schedule!$C$81," ") | F61: =IF([1]Schedule!$E$81>0,[1]Schedule!$E$81," ") | I61: =IF([1]Schedule!$E$81>0,[1]Schedule!$Q$81," ")
A62: =IF([1]Schedule!$E$82>0,[1]Schedule!$B$82," ") | B62: =IF([1]Schedule!$E$82>0,[1]Schedule!$C$82," ") | F62: =IF([1]Schedule!$E$82>0,[1]Schedule!$E$82," ") | I62: =IF([1]Schedule!$E$82>0,[1]Schedule!$Q$82," ")
A63: Expenditure on Computer Equipment between | D63: =E5 -> 45748 | E63: =H5 -> 46477
A64: =IF([1]Schedule!$E$86>0,[1]Schedule!$B$86," ") | B64: =IF([1]Schedule!$E$86>0,[1]Schedule!$C$86," ") | F64: =IF([1]Schedule!$E$86>0,[1]Schedule!$E$86," ") | I64: =IF([1]Schedule!$E$86>0,[1]Schedule!$Q$86," ")
A65: =IF([1]Schedule!$E$87>0,[1]Schedule!$B$87," ") | B65: =IF([1]Schedule!$E$87>0,[1]Schedule!$C$87," ") | F65: =IF([1]Schedule!$E$87>0,[1]Schedule!$E$87," ") | I65: =IF([1]Schedule!$E$87>0,[1]Schedule!$Q$87," ")
A66: =IF([1]Schedule!$E$88>0,[1]Schedule!$B$88," ") | B66: =IF([1]Schedule!$E$88>0,[1]Schedule!$C$88," ") | F66: =IF([1]Schedule!$E$88>0,[1]Schedule!$E$88," ") | I66: =IF([1]Schedule!$E$88>0,[1]Schedule!$Q$88," ")
A67: =IF([1]Schedule!$E$89>0,[1]Schedule!$B$89," ") | B67: =IF([1]Schedule!$E$89>0,[1]Schedule!$C$89," ") | F67: =IF([1]Schedule!$E$89>0,[1]Schedule!$E$89," ") | I67: =IF([1]Schedule!$E$89>0,[1]Schedule!$Q$89," ")
A68: =IF([1]Schedule!$E$90>0,[1]Schedule!$B$90," ") | B68: =IF([1]Schedule!$E$90>0,[1]Schedule!$C$90," ") | F68: =IF([1]Schedule!$E$90>0,[1]Schedule!$E$90," ") | I68: =IF([1]Schedule!$E$90>0,[1]Schedule!$Q$90," ")
A69: =IF([1]Schedule!$E$91>0,[1]Schedule!$B$91," ") | B69: =IF([1]Schedule!$E$91>0,[1]Schedule!$C$91," ") | F69: =IF([1]Schedule!$E$91>0,[1]Schedule!$E$91," ") | I69: =IF([1]Schedule!$E$91>0,[1]Schedule!$Q$91," ")
A70: =IF([1]Schedule!$E$92>0,[1]Schedule!$B$92," ") | B70: =IF([1]Schedule!$E$92>0,[1]Schedule!$C$92," ") | F70: =IF([1]Schedule!$E$92>0,[1]Schedule!$E$92," ") | I70: =IF([1]Schedule!$E$92>0,[1]Schedule!$Q$92," ")
A71: =IF([1]Schedule!$E$93>0,[1]Schedule!$B$93," ") | B71: =IF([1]Schedule!$E$93>0,[1]Schedule!$C$93," ") | F71: =IF([1]Schedule!$E$93>0,[1]Schedule!$E$93," ") | I71: =IF([1]Schedule!$E$93>0,[1]Schedule!$Q$93," ")
B72: Expenditure on Vans & Lorries between | D72: =E5 -> 45748 | E72: =H5 -> 46477
A73: =IF([1]Schedule!$E$103>0,[1]Schedule!$B$103," ") | B73: =IF([1]Schedule!$E$103>0,[1]Schedule!$C$103," ") | F73: =IF([1]Schedule!$E$103>0,[1]Schedule!$E$103," ") | I73: =IF([1]Schedule!$E$103>0,[1]Schedule!$Q$103," ")
A74: =IF([1]Schedule!$E$104>0,[1]Schedule!$B$104," ") | B74: =IF([1]Schedule!$E$104>0,[1]Schedule!$C$104," ") | F74: =IF([1]Schedule!$E$104>0,[1]Schedule!$E$104," ") | I74: =IF([1]Schedule!$E$104>0,[1]Schedule!$Q$104," ")
A75: =IF([1]Schedule!$E$105>0,[1]Schedule!$B$105," ") | B75: =IF([1]Schedule!$E$105>0,[1]Schedule!$C$105," ") | F75: =IF([1]Schedule!$E$105>0,[1]Schedule!$E$105," ") | I75: =IF([1]Schedule!$E$105>0,[1]Schedule!$Q$105," ")
A76: =IF([1]Schedule!$E$106>0,[1]Schedule!$B$106," ") | B76: =IF([1]Schedule!$E$106>0,[1]Schedule!$C$106," ") | F76: =IF([1]Schedule!$E$106>0,[1]Schedule!$E$106," ") | I76: =IF([1]Schedule!$E$106>0,[1]Schedule!$Q$106," ")
A77: =IF([1]Schedule!$E$107>0,[1]Schedule!$B$107," ") | B77: =IF([1]Schedule!$E$107>0,[1]Schedule!$C$107," ") | F77: =IF([1]Schedule!$E$107>0,[1]Schedule!$E$107," ") | I77: =IF([1]Schedule!$E$107>0,[1]Schedule!$Q$107," ")
B79: Total Capital Expenditure between | D79: =E5 -> 45748 | E79: =H5 -> 46477 | F79: =SUM(F48:F78) -> 0 | I79: =SUM(I48:I78) -> 0 | K79: =I79 -> 0
F81: Capital Expenditure | I81: Writing Down Allowances
B82: WRITING DOWN ALLOWANCES
F83: £ | I83: £
A84: Note 2 | B84: Expenditure on Cars between | D84: =E5 -> 45748 | E84: =H5 -> 46477
A85: =IF([1]Schedule!$E$97>0,[1]Schedule!$B$97," ") | B85: =IF([1]Schedule!$E$97>0,[1]Schedule!$C$97," ") | F85: =IF([1]Schedule!$E$97>0,[1]Schedule!$E$97," ") | I85: =IF([1]Schedule!$E$97>0,[1]Schedule!$R$97," ")
A86: =IF([1]Schedule!$E$98>0,[1]Schedule!$B$98," ") | B86: =IF([1]Schedule!$E$98>0,[1]Schedule!$C$98," ") | F86: =IF([1]Schedule!$E$98>0,[1]Schedule!$E$98," ") | I86: =IF([1]Schedule!$E$98>0,[1]Schedule!$R$98," ")
A87: =IF([1]Schedule!$E$99>0,[1]Schedule!$B$99," ") | B87: =IF([1]Schedule!$E$99>0,[1]Schedule!$C$99," ") | F87: =IF([1]Schedule!$E$99>0,[1]Schedule!$E$99," ") | I87: =IF([1]Schedule!$E$99>0,[1]Schedule!$R$99," ")
A88: =IF([1]Schedule!$E$100>0,[1]Schedule!$B$100," ") | B88: =IF([1]Schedule!$E$100>0,[1]Schedule!$C$100," ") | F88: =IF([1]Schedule!$E$100>0,[1]Schedule!$E$100," ") | I88: =IF([1]Schedule!$E$100>0,[1]Schedule!$R$100," ")
A89: =IF([1]Schedule!$E$101>0,[1]Schedule!$B$101," ") | B89: =IF([1]Schedule!$E$101>0,[1]Schedule!$C$101," ") | F89: =IF([1]Schedule!$E$101>0,[1]Schedule!$E$101," ") | I89: =IF([1]Schedule!$E$101>0,[1]Schedule!$R$101," ")
B91: Writing Down Allowance on Cars bought | D91: =E5 -> 45748 | E91: =H5 -> 46477 | F91: at 20% restricted to £3,000 | K91: =SUM(I84:I90) -> 0
A93: Note 3 | B93: Writing Down Allowance on Assets purchased prior to | E93: =E5 -> 45748 | F93: =Admin!G6/100 -> 0.18
B94: Plant & Machinery purchased prior to | D94: =E5 -> 45748 | I94: =IF([1]Schedule!$R$22>0,[1]Schedule!$R$22," ")
B95: Fixtures & Fittings purchased prior to | D95: =E5 -> 45748 | I95: =IF([1]Schedule!$R$30>0,[1]Schedule!$R$30," ")
B96: Computer Equipment purchased prior to | D96: =E5 -> 45748 | I96: =IF([1]Schedule!$R$41>0,[1]Schedule!$R$41," ")
B97: Motor Vehicles purchased prior to | D97: =E5 -> 45748 | I97: =IF([1]Schedule!$R$55>0,[1]Schedule!$R$55," ")
B99: Writing Down Allowance on Assets purchased prior to | E99: =E5 -> 45748 | F99: =F93 -> 0.18 | K99: =SUM(I93:I98) -> 0
I101: =IF([1]Schedule!$W$1>0,[1]Schedule!$Z$1-[1]Schedule!$Y$1," ")
A102: Note 4 | B102: Balancing charges on assets disposed of between | E102: =E5 -> 45748 | F102: =H5 -> 46477 | K102: =SUM(I100:I101) -> 0
B104: TOTAL CAPITAL ALLOWANCES DEDUCTED FROM OPERATING PROFIT | K104: =K79+K99+K91-K102 -> 0

Sheet CT600
F1: Print and Copy figures to official HM Revenue & Customs CT600 form
AO3: Page 1
C4: HM Revenue & Customs | X4: Company - Short Tax Return form
X6: CT600 (Short) (2008) Version 2
X7: for accounting periods ending on or after 1 July 1999
A9: Your company tax return
B10: If the revenue send the company a Notice to deliver a company tax return (form CT603) it has to comply by the filing
B11: date, or the revenue charge a penalty, even if there is no tax to pay. A return includes a company tax return form, any
B12: Supplementary Pages, accounts, computations and any relevant information.
B13: In this the right form for the company? Read the advice on pages 3 to 6 of the Company tax return guide before you start.
B14: The forms in the CT600 series set out the information we need and provide a standard format for calculations.
B15: Use the Guide which contains general information you may need and box by box advice to help complete the return form.
A17: Company information
B18: Company name
B19: =IF(OpenAccounts!$E$2>0,OpenAccounts!E2," ")
B20: Company registration number | U20: Tax Reference as shown on the CT603 | AL20: Type of company
B21: =IF(OpenAccounts!$E$3>0,OpenAccounts!E3," ") | U21: =IF(OpenAccounts!$O$3>0,OpenAccounts!O3," ") | Y21: =IF(OpenAccounts!$P$3>0,OpenAccounts!P3," ") | AE21: =IF(OpenAccounts!$Q$3>0,OpenAccounts!Q3," ")
B22: Registered office address
B23: =IF(OpenAccounts!$J$3>0,OpenAccounts!J3," ")
B24: =IF(OpenAccounts!$J$4>0,OpenAccounts!J4," ")
B25: =IF(OpenAccounts!$J$5>0,OpenAccounts!J5," ")
B26: =IF(OpenAccounts!$J$6>0,OpenAccounts!J6," ") | AE26: Postcode | AK26: =IF(OpenAccounts!$N$6>0,OpenAccounts!N6," ")
A29: About this return
B31: This is the above company's return for the period | Z31: Accounts
B32: from (dd / mm / yyyy) | M32: to (dd / mm / yyyy) | Z32: I attach accounts and computations
B33: =Admin!L6 -> 46113 | M33: =Admin!N7 -> 46477
Z34: for the period to which this return relates | AQ34: X
B35: Put an 'X' in the appropriate box(es) below
Z36: for a different period
B37: A repayment is due for this return period
B39: A repayment is due for an earlier period | Z39: If you are not attaching accounts and
Z40: computations, say why not
B41: Making more than one return for the
B42: company now
B44: This return contains estimated figures
B46: Company part of a group that is not small
Z48: Supplementary Pages
B49: Disclosure of tax avoidance schemes | Z49: If you are enclosing any Supplementary Pages put
Z50: an 'X' in the appropriate box(es)
B51: Notice of disclosure avoidance schemes
Z52: Loans to participation by close companies,
Z53: form CT600A
B54: Transfer pricing
Z55: Charities and Community Amateur Sports
B56: Compensating adjustment claimed | Z56: Clubs (CASCs) form CT600E
B58: Company qualifies for SME exemption | Z58: Disclosure of tax avoidance schemes,
Z59: form CT600J
A62: Page 2
A63: Company tax calculation
A64: Turnover
A65: 111
B66: 1 | C66: Total turnover from trade or profession | AI66: 1 | AJ66: £ | AK66: ='PubP&L'!F9 -> 0
A68: Income
B70: 3 | C70: Trading and professional profits | W70: 3 | Y70: £ | Z70: =IF(CorporationTax!K22>0,CorporationTax!K22," ")
B72: 4 | C72: Trading losses brought forward claimed against profits | W72: 4 | Y72: £ | Z72: =IF(OpenAccounts!Q5>0,OpenAccounts!Q5," ")
AH73: box 3 minus box 4
B74: 5 | C74: Net trading and professional profits | AH74: 5 | AI74: £ | AJ74: =SUM(Z69:AF70)-SUM(Z72:AF73) -> 0
B75: 6 | C75: Bank, building society or other interest, and profits and
C76: gains from ono-trading loan relationships | AH76: 6 | AI76: £ | AJ76: =IF(-TrialBalance!EJ58>0,-TrialBalance!EJ58," ")
B78: 11 | C78: Income from UK land and buildings | AH78: 11 | AI78: £
B80: 12 | C80: Annual profits and gains not falling under any other heading | AH80: 14 | AI80: £
A82: Chargeable gains
B84: 16 | C84: Gross chargeable gains | W84: 16 | Y84: £
B86: 17 | C86: Allowable losses including losses brought forward | W86: 17 | Y86: £
AH87: box 16 minus box 17
B88: 18 | C88: Net chargeable gains | AH88: 18 | AI88: £
AH91: sum of boxes 5.6.11.14.& 18
B92: 21 | C92: Profits before other deductions and reliefs | AH92: 21 | AI92: £ | AJ92: =IF(AJ74>0,AJ74+SUM(AJ76:AJ80)+AJ88,0) -> 0
A94: Deductions and Reliefs
B96: 24 | C96: Management expenses under S75 ICTA 1988 | W96: 24 | Y96: £
B98: 30 | C98: Trading losses of this or a later accounting period | W98: 30 | Y98: £
C99: under S383A ICTA 1988
B101: 31 | C101: Put an 'X' in box 31 if amounts carried back from later | W101: 31
C102: accounting periods are included in box 30
B104: 32 | C104: Non-trade capital allowances | W104: 32 | Y104: £
B106: 35 | C106: Charges paid | W106: 35 | Y106: £
AH109: box 21 minus boxes 24,30.32 and 35
B110: 37 | C110: Profits chargeable to corporation tax | AH110: 37 | AI110: £ | AJ110: =AJ92-Z96-Z98-Z104-Z106 -> 0
A112: Tax calculation
B114: 38 | C114: Franked investment income | W114: 38 | Y114: £ | Z114: =CorporationTax!K29 -> 0
B116: 39 | C116: Number or associated companies in this period | W116: 39 | Y116: 0
C117: or
B118: 40 | C118: Associated companies in the first financial year | W118: 40 | Y118: =Admin!$P$14 -> 0
B120: 41 | C120: Associated companies in the second financial year | W120: 41 | Y120: =IF(CorporationTax!A34>0,Admin!$P$14," ")
B122: 42 | C122: Put an 'X' in box 22 if the company claims to be charged at the starting rate or the | AH122: 42 | AI122: X
C123: small companies' rate on any part of its profits, or is claiming marginal rate relief
B124: Enter how much profits has to be charged and at what rate of tax
B125: Financial year (yyyy) | L125: Amount of profit | Y125: Rate of tax | AH125: Tax
B126: 43 | C126: =CorporationTax!E33 -> 2026 | L126: 44 | M126: £ | N126: =CorporationTax!F33 -> 0 | Y126: 45 | AA126: =CorporationTax!G33 -> 19 | AH126: 46 | AI126: £ | AJ126: =CorporationTax!J33 -> 0 | AQ126: p
B128: 53 | C128: =IF(CorporationTax!A34>0,CorporationTax!E34," ") | L128: 54 | M128: £ | N128: =IF(CorporationTax!A34>0,CorporationTax!F34," ") | Y128: 55 | AA128: =IF(CorporationTax!A34>0,CorporationTax!G34," ") | AH128: 56 | AI128: £ | AJ128: =CorporationTax!J34 -> 0 | AQ128: p
AH130: total of boxes 46 & 56
B131: 61 | C131: Corporation tax | AH131: 63 | AI131: £ | AJ131: =AJ126+AJ128 -> 0 | AQ131: p
B133: 64 | C133: Marginal rate relief | V133: 64 | W133: £ | Y133: =CorporationTax!L33+CorporationTax!L34 -> 0 | AE133: p
B135: 65 | C135: Corporation tax net of marginal rate relief | V135: 65 | W135: £ | Y135: =CorporationTax!K35 -> 0 | AE135: p
B137: 66 | C137: Underlying rate of corporation tax | V137: 66 | W137: =IF(Y135>0,Y135*100/AJ110," ") | AA137: %
B139: 67 | C139: Profits matched with non-corporate distribution | V139: 67
B141: 68 | C141: Tax at non-corporate distribution rate | V141: 68 | W141: £ | AE141: p
B143: 69 | C143: Tax at underlying rate on remaining profits | V143: 69 | W143: £ | AE143: p
AH144: see note for box 70 in CT600 Guide
B145: 70 | C145: Corporation tax chargeable | AH145: 70 | AI145: £ | AJ145: =Y135 -> 0 | AQ145: p
...

Sheet WagesInterface
B2: Month | C2: Gross Wages paid | D2: Income Tax deducted | E2: Employees National Insurance deducted | F2: Other Deductions | G2: Net Wages Paid | H2: Employers National Insurance | I2: Recoverable Statutory Payments | K2: WAGES INTERFACE
B3: EMPLOYEES
B4: =Admin!B10 -> 45777 | C4: =[9]Apr!$M$1-C17 -> 0 | D4: =[9]Apr!$N$1-D17 -> 0 | E4: =[9]Apr!$O$1-E17 -> 0 | F4: =[9]Apr!$P$1+[9]Apr!$Q$1-F17 -> 0 | G4: =C4-SUM(D4:F4) -> 0 | H4: =[9]Apr!$T$1-H17 -> 0 | I4: =[9]Apr!$G$1 -> 0 | K4: 1. If you are using a DIY Accounting payroll package then no action is required for the pay periods during which that payroll package is relevant April to March each year.
B5: =Admin!B12 -> 45808 | C5: =[9]May!$M$1-C18 -> 0 | D5: =[9]May!$N$1-D18 -> 0 | E5: =[9]May!$O$1-E18 -> 0 | F5: =[9]May!$P$1+[9]May!$Q$1-F18 -> 0 | G5: =C5-SUM(D5:F5) -> 0 | H5: =[9]May!$T$1-H18 -> 0 | I5: =[9]May!$G$1 -> 0
B6: =Admin!B14 -> 45838 | C6: =[9]Jun!$M$1-C19 -> 0 | D6: =[9]Jun!$N$1-D19 -> 0 | E6: =[9]Jun!$O$1-E19 -> 0 | F6: =[9]Jun!$P$1+[9]Jun!$Q$1-F19 -> 0 | G6: =C6-SUM(D6:F6) -> 0 | H6: =[9]Jun!$T$1-H19 -> 0 | I6: =[9]Jun!$G$1 -> 0
B7: =Admin!B16 -> 45869 | C7: =[9]Jul!$M$1-C20 -> 0 | D7: =[9]Jul!$N$1-D20 -> 0 | E7: =[9]Jul!$O$1-E20 -> 0 | F7: =[9]Jul!$P$1+[9]Jul!$Q$1-F20 -> 0 | G7: =C7-SUM(D7:F7) -> 0 | H7: =[9]Jul!$T$1-H20 -> 0 | I7: =[9]Jul!$G$1 -> 0
B8: =Admin!B18 -> 45900 | C8: =[9]Aug!$M$1-C21 -> 0 | D8: =[9]Aug!$N$1-D21 -> 0 | E8: =[9]Aug!$O$1-E21 -> 0 | F8: =[9]Aug!$P$1+[9]Aug!$Q$1-F21 -> 0 | G8: =C8-SUM(D8:F8) -> 0 | H8: =[9]Aug!$T$1-H21 -> 0 | I8: =[9]Aug!$G$1 -> 0 | K8: 2. For Pay periods outside the financial tax year and non DIY Accounting Payroll users enter monthly figures manually
B9: =Admin!B20 -> 45930 | C9: =[9]Sep!$M$1-C22 -> 0 | D9: =[9]Sep!$N$1-D22 -> 0 | E9: =[9]Sep!$O$1-E22 -> 0 | F9: =[9]Sep!$P$1+[9]Sep!$Q$1-F22 -> 0 | G9: =C9-SUM(D9:F9) -> 0 | H9: =[9]Sep!$T$1-H22 -> 0 | I9: =[9]Sep!$G$1 -> 0
B10: =Admin!B22 -> 45961 | C10: =[9]Oct!$M$1-C23 -> 0 | D10: =[9]Oct!$N$1-D23 -> 0 | E10: =[9]Oct!$O$1-E23 -> 0 | F10: =[9]Oct!$P$1+[9]Oct!$Q$1-F23 -> 0 | G10: =C10-SUM(D10:F10) -> 0 | H10: =[9]Oct!$T$1-H23 -> 0 | I10: =[9]Oct!$G$1 -> 0
B11: =Admin!B24 -> 45991 | C11: =[9]Nov!$M$1-C24 -> 0 | D11: =[9]Nov!$N$1-D24 -> 0 | E11: =[9]Nov!$O$1-E24 -> 0 | F11: =[9]Nov!$P$1+[9]Nov!$Q$1-F24 -> 0 | G11: =C11-SUM(D11:F11) -> 0 | H11: =[9]Nov!$T$1-H24 -> 0 | I11: =[9]Nov!$G$1 -> 0
B12: =Admin!B26 -> 46022 | C12: =[9]Dec!$M$1-C25 -> 0 | D12: =[9]Dec!$N$1-D25 -> 0 | E12: =[9]Dec!$O$1-E25 -> 0 | F12: =[9]Dec!$P$1+[9]Dec!$Q$1-F25 -> 0 | G12: =C12-SUM(D12:F12) -> 0 | H12: =[9]Dec!$T$1-H25 -> 0 | I12: =[9]Dec!$G$1 -> 0 | K12: 3. Non DIY Accounting Payroll employers should overwrite the formulae with the actual monthly payroll totals
B13: =Admin!B28 -> 46053 | C13: =[9]Jan!$M$1-C26 -> 0 | D13: =[9]Jan!$N$1-D26 -> 0 | E13: =[9]Jan!$O$1-E26 -> 0 | F13: =[9]Jan!$P$1+[9]Jan!$Q$1-F26 -> 0 | G13: =C13-SUM(D13:F13) -> 0 | H13: =[9]Jan!$T$1-H26 -> 0 | I13: =[9]Jan!$G$1 -> 0
B14: =Admin!B30 -> 46081 | C14: =[9]Feb!$M$1-C27 -> 0 | D14: =[9]Feb!$N$1-D27 -> 0 | E14: =[9]Feb!$O$1-E27 -> 0 | F14: =[9]Feb!$P$1+[9]Feb!$Q$1-F27 -> 0 | G14: =C14-SUM(D14:F14) -> 0 | H14: =[9]Feb!$T$1-H27 -> 0 | I14: =[9]Feb!$G$1 -> 0
B15: =Admin!B32 -> 46112 | C15: =[9]Mar!$M$1-C28 -> 0 | D15: =[9]Mar!$N$1-D28 -> 0 | E15: =[9]Mar!$O$1-E28 -> 0 | F15: =[9]Mar!$P$1+[9]Mar!$Q$1-F28 -> 0 | G15: =C15-SUM(D15:F15) -> 0 | H15: =[9]Mar!$T$1-H28 -> 0 | I15: =[9]Mar!$G$1 -> 0
B16: DIRECTORS
B17: =B4 -> 45777 | C17: =[9]Apr!$M$2 -> 0 | D17: =[9]Apr!$N$2 -> 0 | E17: =[9]Apr!$O$2 -> 0 | F17: =[9]Apr!$P$2+[9]Apr!$Q$2 -> 0 | G17: =C17-SUM(D17:F17) -> 0 | H17: =[9]Apr!$T$2 -> 0 | K17: 4.. Enter wages payments to directors in this section to separately identify payments in the profit and loss account
B18: =B5 -> 45808 | C18: =[9]May!$M$2 -> 0 | D18: =[9]May!$N$2 -> 0 | E18: =[9]May!$O$2 -> 0 | F18: =[9]May!$P$2+[9]May!$Q$2 -> 0 | G18: =C18-SUM(D18:F18) -> 0 | H18: =[9]May!$T$2 -> 0
B19: =B6 -> 45838 | C19: =[9]Jun!$M$2 -> 0 | D19: =[9]Jun!$N$2 -> 0 | E19: =[9]Jun!$O$2 -> 0 | F19: =[9]Jun!$P$2+[9]Jun!$Q$2 -> 0 | G19: =C19-SUM(D19:F19) -> 0 | H19: =[9]Jun!$T$2 -> 0
B20: =B7 -> 45869 | C20: =[9]Jul!$M$2 -> 0 | D20: =[9]Jul!$N$2 -> 0 | E20: =[9]Jul!$O$2 -> 0 | F20: =[9]Jul!$P$2+[9]Jul!$Q$2 -> 0 | G20: =C20-SUM(D20:F20) -> 0 | H20: =[9]Jul!$T$2 -> 0
B21: =B8 -> 45900 | C21: =[9]Aug!$M$2 -> 0 | D21: =[9]Aug!$N$2 -> 0 | E21: =[9]Aug!$O$2 -> 0 | F21: =[9]Aug!$P$2+[9]Aug!$Q$2 -> 0 | G21: =C21-SUM(D21:F21) -> 0 | H21: =[9]Aug!$T$2 -> 0
B22: =B9 -> 45930 | C22: =[9]Sep!$M$2 -> 0 | D22: =[9]Sep!$N$2 -> 0 | E22: =[9]Sep!$O$2 -> 0 | F22: =[9]Sep!$P$2+[9]Sep!$Q$2 -> 0 | G22: =C22-SUM(D22:F22) -> 0 | H22: =[9]Sep!$T$2 -> 0
B23: =B10 -> 45961 | C23: =[9]Oct!$M$2 -> 0 | D23: =[9]Oct!$N$2 -> 0 | E23: =[9]Oct!$O$2 -> 0 | F23: =[9]Oct!$P$2+[9]Oct!$Q$2 -> 0 | G23: =C23-SUM(D23:F23) -> 0 | H23: =[9]Oct!$T$2 -> 0
B24: =B11 -> 45991 | C24: =[9]Nov!$M$2 -> 0 | D24: =[9]Nov!$N$2 -> 0 | E24: =[9]Nov!$O$2 -> 0 | F24: =[9]Nov!$P$2+[9]Nov!$Q$2 -> 0 | G24: =C24-SUM(D24:F24) -> 0 | H24: =[9]Nov!$T$2 -> 0
B25: =B12 -> 46022 | C25: =[9]Dec!$M$2 -> 0 | D25: =[9]Dec!$N$2 -> 0 | E25: =[9]Dec!$O$2 -> 0 | F25: =[9]Dec!$P$2+[9]Dec!$Q$2 -> 0 | G25: =C25-SUM(D25:F25) -> 0 | H25: =[9]Dec!$T$2 -> 0
B26: =B13 -> 46053 | C26: =[9]Jan!$M$2 -> 0 | D26: =[9]Jan!$N$2 -> 0 | E26: =[9]Jan!$O$2 -> 0 | F26: =[9]Jan!$P$2+[9]Jan!$Q$2 -> 0 | G26: =C26-SUM(D26:F26) -> 0 | H26: =[9]Jan!$T$2 -> 0
B27: =B14 -> 46081 | C27: =[9]Feb!$M$2 -> 0 | D27: =[9]Feb!$N$2 -> 0 | E27: =[9]Feb!$O$2 -> 0 | F27: =[9]Feb!$P$2+[9]Feb!$Q$2 -> 0 | G27: =C27-SUM(D27:F27) -> 0 | H27: =[9]Feb!$T$2 -> 0
B28: =B15 -> 46112 | C28: =[9]Mar!$M$2 -> 0 | D28: =[9]Mar!$N$2 -> 0 | E28: =[9]Mar!$O$2 -> 0 | F28: =[9]Mar!$P$2+[9]Mar!$Q$2 -> 0 | G28: =C28-SUM(D28:F28) -> 0 | H28: =[9]Mar!$T$2 -> 0

Sheet Stock
H1: Calculation Of Stock Sold | N1: Calculation Of Stock Sold | T1: Calculation Of Stock Sold
B2: Date | D2: Calculated Stock value | F2: Direct Material BOUGHT | H2: Stock % Prod A | J2: Net Sales Product A | L2: Direct Material SOLD | N2: Stock % Prod B | P2: Net Sales Product B | R2: Direct Material SOLD | T2: Stock % Prod C | V2: Net Sales Product C | X2: Direct Material SOLD | Z2: Stock Loss Adjustment | AB2: ACTUAL STOCK VALUE | AD2: Stock Control User Notes
AD3: 1. Enter the average percentage stock value in cell H4. This is the average % of direct materials included in the net sales value of each product type. The table will repeat this same % for each month unless a new percentage is entered in a specific month which will then overwrite the originally % entered for that and the remaining months
B4: Enter % to change % materials sold | H4: 0 | N4: 0 | T4: 0
B6: =Admin!B9 -> 45748 | D6: =OpenAccounts!$E$15 -> 0 | AB6: =OpenAccounts!$E$15 -> 0
B8: =Admin!B10 -> 45777 | D8: =D6+F8-L8-R8-X8+Z6 -> 0 | F8: =IF((H$4+N$4+T$4)=0,0,[2]Apr!O$1) -> 0 | H8: =H4 -> 0 | J8: =[3]Apr!$O$1 -> 0 | L8: =J8*H8 -> 0 | N8: =N4 -> 0 | P8: =[3]Apr!$P$1 -> 0 | R8: =P8*N8 -> 0 | T8: =T4 -> 0 | V8: =[3]Apr!$Q$1 -> 0 | X8: =V8*T8 -> 0 | Z8: =IF(AB8<>D8,AB8-D8,0) -> 0 | AB8: =AB6+F8-L8-R8-X8 -> 0
B10: =Admin!B12 -> 45808 | D10: =D8+F10-L10-R10-X10+Z8 -> 0 | F10: =IF((H$4+N$4+T$4)=0,0,[2]May!O$1) -> 0 | H10: =H8 -> 0 | J10: =[3]May!$O$1 -> 0 | L10: =J10*H10 -> 0 | N10: =N8 -> 0 | P10: =[3]May!$P$1 -> 0 | R10: =P10*N10 -> 0 | T10: =T8 -> 0 | V10: =[3]May!$Q$1 -> 0 | X10: =V10*T10 -> 0 | Z10: =IF(AB10<>D10,AB10-D10,0) -> 0 | AB10: =AB8+F10-L10-R10-X10 -> 0
AD11: 2. Optional: manually calculate the % of direct materials included in net sales value and enter this percentage in Column H against each month
B12: =Admin!B14 -> 45838 | D12: =D10+F12-L12-R12-X12+Z10 -> 0 | F12: =IF((H$4+N$4+T$4)=0,0,[2]Jun!O$1) -> 0 | H12: =H10 -> 0 | J12: =[3]Jun!$O$1 -> 0 | L12: =J12*H12 -> 0 | N12: =N10 -> 0 | P12: =[3]Jun!$P$1 -> 0 | R12: =P12*N12 -> 0 | T12: =T10 -> 0 | V12: =[3]Jun!$Q$1 -> 0 | X12: =V12*T12 -> 0 | Z12: =IF(AB12<>D12,AB12-D12,0) -> 0 | AB12: =AB10+F12-L12-R12-X12 -> 0
B14: =Admin!B16 -> 45869 | D14: =D12+F14-L14-R14-X14+Z12 -> 0 | F14: =IF((H$4+N$4+T$4)=0,0,[2]Jul!O$1) -> 0 | H14: =H12 -> 0 | J14: =[3]Jul!$O$1 -> 0 | L14: =J14*H14 -> 0 | N14: =N12 -> 0 | P14: =[3]Jul!$P$1 -> 0 | R14: =P14*N14 -> 0 | T14: =T12 -> 0 | V14: =[3]Jul!$Q$1 -> 0 | X14: =V14*T14 -> 0 | Z14: =IF(AB14<>D14,AB14-D14,0) -> 0 | AB14: =AB12+F14-L14-R14-X14 -> 0
AD15: 3. Column F automatically collects the value of direct material purchased from the monthly purchases worksheet
B16: =Admin!B18 -> 45900 | D16: =D14+F16-L16-R16-X16+Z14 -> 0 | F16: =IF((H$4+N$4+T$4)=0,0,[2]Aug!O$1) -> 0 | H16: =H14 -> 0 | J16: =[3]Aug!$O$1 -> 0 | L16: =J16*H16 -> 0 | N16: =N14 -> 0 | P16: =[3]Aug!$P$1 -> 0 | R16: =P16*N16 -> 0 | T16: =T14 -> 0 | V16: =[3]Aug!$Q$1 -> 0 | X16: =V16*T16 -> 0 | Z16: =IF(AB16<>D16,AB16-D16,0) -> 0 | AB16: =AB14+F16-L16-R16-X16 -> 0
B18: =Admin!B20 -> 45930 | D18: =D16+F18-L18-R18-X18+Z16 -> 0 | F18: =IF((H$4+N$4+T$4)=0,0,[2]Sep!O$1) -> 0 | H18: =H16 -> 0 | J18: =[3]Sep!$O$1 -> 0 | L18: =J18*H18 -> 0 | N18: =N16 -> 0 | P18: =[3]Sep!$P$1 -> 0 | R18: =P18*N18 -> 0 | T18: =T16 -> 0 | V18: =[3]Sep!$Q$1 -> 0 | X18: =V18*T18 -> 0 | Z18: =IF(AB18<>D18,AB18-D18,0) -> 0 | AB18: =AB16+F18-L18-R18-X18 -> 0
AD19: 4. Column L automatically calculates the value of direct materials sold by applying the stock sales % to the net sales value from the sales worksheet
B20: =Admin!B22 -> 45961 | D20: =D18+F20-L20-R20-X20+Z18 -> 0 | F20: =IF((H$4+N$4+T$4)=0,0,[2]Oct!O$1) -> 0 | H20: =H18 -> 0 | J20: =[3]Oct!$O$1 -> 0 | L20: =J20*H20 -> 0 | N20: =N18 -> 0 | P20: =[3]Oct!$P$1 -> 0 | R20: =P20*N20 -> 0 | T20: =T18 -> 0 | V20: =[3]Oct!$Q$1 -> 0 | X20: =V20*T20 -> 0 | Z20: =IF(AB20<>D20,AB20-D20,0) -> 0 | AB20: =AB18+F20-L20-R20-X20 -> 0
B22: =Admin!B24 -> 45991 | D22: =D20+F22-L22-R22-X22+Z20 -> 0 | F22: =IF((H$4+N$4+T$4)=0,0,[2]Nov!O$1) -> 0 | H22: =H20 -> 0 | J22: =[3]Nov!$O$1 -> 0 | L22: =J22*H22 -> 0 | N22: =N20 -> 0 | P22: =[3]Nov!$P$1 -> 0 | R22: =P22*N22 -> 0 | T22: =T20 -> 0 | V22: =[3]Nov!$Q$1 -> 0 | X22: =V22*T22 -> 0 | Z22: =IF(AB22<>D22,AB22-D22,0) -> 0 | AB22: =AB20+F22-L22-R22-X22 -> 0
AD23: 5. Optional: At the end of each month conduct a physical stock check and value the items counted at cost price. Enter this actual physical value in column P at the appropriate month end date
B24: =Admin!B26 -> 46022 | D24: =D22+F24-L24-R24-X24+Z22 -> 0 | F24: =IF((H$4+N$4+T$4)=0,0,[2]Dec!O$1) -> 0 | H24: =H22 -> 0 | J24: =[3]Dec!$O$1 -> 0 | L24: =J24*H24 -> 0 | N24: =N22 -> 0 | P24: =[3]Dec!$P$1 -> 0 | R24: =P24*N24 -> 0 | T24: =T22 -> 0 | V24: =[3]Dec!$Q$1 -> 0 | X24: =V24*T24 -> 0 | Z24: =IF(AB24<>D24,AB24-D24,0) -> 0 | AB24: =AB22+F24-L24-R24-X24 -> 0
B26: =Admin!B28 -> 46053 | D26: =D24+F26-L26-R26-X26+Z24 -> 0 | F26: =IF((H$4+N$4+T$4)=0,0,[2]Jan!O$1) -> 0 | H26: =H24 -> 0 | J26: =[3]Jan!$O$1 -> 0 | L26: =J26*H26 -> 0 | N26: =N24 -> 0 | P26: =[3]Jan!$P$1 -> 0 | R26: =P26*N26 -> 0 | T26: =T24 -> 0 | V26: =[3]Jan!$Q$1 -> 0 | X26: =V26*T26 -> 0 | Z26: =IF(AB26<>D26,AB26-D26,0) -> 0 | AB26: =AB24+F26-L26-R26-X26 -> 0
B28: =Admin!B30 -> 46081 | D28: =D26+F28-L28-R28-X28+Z26 -> 0 | F28: =IF((H$4+N$4+T$4)=0,0,[2]Feb!O$1) -> 0 | H28: =H26 -> 0 | J28: =[3]Feb!$O$1 -> 0 | L28: =J28*H28 -> 0 | N28: =N26 -> 0 | P28: =[3]Feb!$P$1 -> 0 | R28: =P28*N28 -> 0 | T28: =T26 -> 0 | V28: =[3]Feb!$Q$1 -> 0 | X28: =V28*T28 -> 0 | Z28: =IF(AB28<>D28,AB28-D28,0) -> 0 | AB28: =AB26+F28-L28-R28-X28 -> 0 | AD28: 6. If the % of stock sold in net sales is correct then Column Z should be zero unless stock has been lost.. Investigate significant Stock Loss Adjustments
B30: =Admin!B32 -> 46112 | D30: =D28+F30-L30-R30-X30+Z28 -> 0 | F30: =IF((H$4+N$4+T$4)=0,0,[2]Mar!O$1) -> 0 | H30: =H28 -> 0 | J30: =[3]Mar!$O$1 -> 0 | L30: =J30*H30 -> 0 | N30: =N28 -> 0 | P30: =[3]Mar!$P$1 -> 0 | R30: =P30*N30 -> 0 | T30: =T28 -> 0 | V30: =[3]Mar!$Q$1 -> 0 | X30: =V30*T30 -> 0 | Z30: =IF(AB30<>D30,AB30-D30,0) -> 0 | AB30: =AB28+F30-L30-R30-X30 -> 0

Sheet Admin
B1: Dates
B2: =DATE(YEAR(B4),MONTH(B4),1)-1 -> 46022
B3: =DATE(YEAR(B4),MONTH(B4),1) -> 46023 | D3: Capital Tax Allowances | G3: =TEXT(YEAR(F21)-1,"0") & "-" & TEXT(YEAR(F21)-2000,"0") -> 2025-26 | K3: Corporation Tax Rates | N3: =G3 -> 2025-26
B4: =DATE(YEAR(B6),MONTH(B6),1)-1 -> 46053 | F4: Year to | G4: %
B5: =DATE(YEAR(B6),MONTH(B6),1) -> 46054 | D5: Annual Investment Allowance | F5: =B8 -> 45747 | G5: 100 | P5: (Small profits rate) | R5: (Main rate %) | S5: (Relief fraction) | T5: (Relief lower limit) | U5: (Relief upper limit)
B6: =DATE(YEAR(B8),MONTH(B8),1)-1 -> 46081 | D6: Writing down allowance | F6: =B8 -> 45747 | G6: 14 | I6: Corporation Tax | K6: =YEAR(L6)-IF(MONTH(L6)<4,1,0) -> 2026 | L6: =B9 -> 46113 | N6: =MIN(IF(DATE(YEAR(L6),3,31)>=L6,DATE(YEAR(L6),3,31),DATE(YEAR(L6)+1,3,31)),F21) -> 46477 | P6: 19 | Q6: % | R6: 25 | S6: 0.015 | T6: 50000 | U6: 250000
B7: =DATE(YEAR(B8),MONTH(B8),1) -> 46082 | D7: Annual Investment Allowance | F7: =B32 -> 46112 | G7: 100 | I7: Corporation Tax | K7: =YEAR(L7)-IF(MONTH(L7)<4,1,0) -> 2027 | L7: =N6+1 -> 46478 | N7: =F21 -> 46477 | P7: 19 | Q7: % | R7: 25 | S7: 0.015 | T7: 50000 | U7: 250000
B8: =DATE(YEAR(B10),MONTH(B10),1)-1 -> 46112 | D8: Writing down allowance | F8: =B32 -> 46112 | G8: 14
B9: =DATE(YEAR(B10),MONTH(B10),1) -> 46113 | L9: Date | N9: Number
B10: =DATE(YEAR(B12),MONTH(B12),1)-1 -> 46142 | D10: Allowances restricted on Motor vehicles | L10: =B8 -> 45747 | M10: = | N10: =B8 -> 45747
B11: =DATE(YEAR(B12),MONTH(B12),1) -> 46143 | L11: =B32 -> 46112 | M11: = | N11: =B32 -> 46112
B12: =DATE(YEAR(B14),MONTH(B14),1)-1 -> 46173
B13: =DATE(YEAR(B14),MONTH(B14),1) -> 46174 | D13: Depreciation Rates Applied | G13: %
B14: =DATE(YEAR(B16),MONTH(B16),1)-1 -> 46203 | I14: Mileage Allowances | N14: Miles | O14: p per mile
B15: =DATE(YEAR(B16),MONTH(B16),1) -> 46204 | D15: Land & Property | G15: 0
B16: =DATE(YEAR(B18),MONTH(B18),1)-1 -> 46234 | D16: Plant & Machinery | G16: 0.1 | I16: Higher rate allowance up to | N16: 10000 | O16: 0.55
B17: =DATE(YEAR(B18),MONTH(B18),1) -> 46235 | D17: Fixtures & Fittings | G17: 0.2 | I17: Lower rate allowance over | N17: 10001 | O17: 0.25
B18: =DATE(YEAR(B20),MONTH(B20),1)-1 -> 46265 | D18: Computer Equipment | G18: 0.33
B19: =DATE(YEAR(B20),MONTH(B20),1) -> 46266 | D19: Motor Vehicles | G19: 0.25 | I19: Standard Vat Rate | M19: 20 | N19: =B9 -> 45748 | O19: =B26 -> 46022
B20: =DATE(YEAR(B22),MONTH(B22),1)-1 -> 46295
B21: =DATE(YEAR(B22),MONTH(B22),1) -> 46296 | D21: Year to | F21: 46477 | I21: Standard Vat Rate | M21: 20 | N21: =B27 -> 46023
B22: =DATE(YEAR(B24),MONTH(B24),1)-1 -> 46326
B23: =DATE(YEAR(B24),MONTH(B24),1) -> 46327
B24: =DATE(YEAR(B26),MONTH(B26),1)-1 -> 46356
B25: =DATE(YEAR(B26),MONTH(B26),1) -> 46357
B26: =DATE(YEAR(B28),MONTH(B28),1)-1 -> 46387
B27: =DATE(YEAR(B28),MONTH(B28),1) -> 46388
B28: =DATE(YEAR(B30),MONTH(B30),1)-1 -> 46418
B29: =DATE(YEAR(B30),MONTH(B30),1) -> 46419
B30: =DATE(YEAR(B32),MONTH(B32),1)-1 -> 46446
B31: =DATE(YEAR(B32),MONTH(B32),1) -> 46447
B32: =F21 -> 46477
B33: =DATE(YEAR(B34),MONTH(B34),1) -> 46478
B34: =DATE(IF(MONTH(B32)<11,YEAR(B32),YEAR(B32)+1),IF(MONTH(B32)<11,MONTH(B32)+2,IF(MONTH(B32)=11,1,2)),1)-1 -> 46507
B35: =DATE(YEAR(B36),MONTH(B36),1) -> 46508
B36: =DATE(IF(MONTH(B34)<11,YEAR(B34),YEAR(B34)+1),IF(MONTH(B34)<11,MONTH(B34)+2,IF(MONTH(B34)=11,1,2)),1)-1 -> 46538
B37: =DATE(YEAR(B38),MONTH(B38),1) -> 46539
B38: =DATE(IF(MONTH(B36)<11,YEAR(B36),YEAR(B36)+1),IF(MONTH(B36)<11,MONTH(B36)+2,IF(MONTH(B36)=11,1,2)),1)-1 -> 46568
B39: =DATE(YEAR(B40),MONTH(B40),1) -> 46569
B40: =DATE(IF(MONTH(B38)<11,YEAR(B38),YEAR(B38)+1),IF(MONTH(B38)<11,MONTH(B38)+2,IF(MONTH(B38)=11,1,2)),1)-1 -> 46599
B41: =DATE(YEAR(B42),MONTH(B42),1) -> 46600
B42: =DATE(IF(MONTH(B40)<11,YEAR(B40),YEAR(B40)+1),IF(MONTH(B40)<11,MONTH(B40)+2,IF(MONTH(B40)=11,1,2)),1)-1 -> 46630
B43: =DATE(YEAR(B44),MONTH(B44),1) -> 46631
B44: =DATE(IF(MONTH(B42)<11,YEAR(B42),YEAR(B42)+1),IF(MONTH(B42)<11,MONTH(B42)+2,IF(MONTH(B42)=11,1,2)),1)-1 -> 46660
B45: =DATE(YEAR(B46),MONTH(B46),1) -> 46661
B46: =DATE(IF(MONTH(B44)<11,YEAR(B44),YEAR(B44)+1),IF(MONTH(B44)<11,MONTH(B44)+2,IF(MONTH(B44)=11,1,2)),1)-1 -> 46691
B47: =DATE(YEAR(B48),MONTH(B48),1) -> 46692
B48: =DATE(IF(MONTH(B46)<11,YEAR(B46),YEAR(B46)+1),IF(MONTH(B46)<11,MONTH(B46)+2,IF(MONTH(B46)=11,1,2)),1)-1 -> 46721
B49: =DATE(YEAR(B50),MONTH(B50),1) -> 46722
B50: =DATE(IF(MONTH(B48)<11,YEAR(B48),YEAR(B48)+1),IF(MONTH(B48)<11,MONTH(B48)+2,IF(MONTH(B48)=11,1,2)),1)-1 -> 46752
B51: =DATE(YEAR(B52),MONTH(B52),1) -> 46753
B52: =DATE(IF(MONTH(B50)<11,YEAR(B50),YEAR(B50)+1),IF(MONTH(B50)<11,MONTH(B50)+2,IF(MONTH(B50)=11,1,2)),1)-1 -> 46783
B53: =DATE(YEAR(B54),MONTH(B54),1) -> 46784
B54: =DATE(IF(MONTH(B52)<11,YEAR(B52),YEAR(B52)+1),IF(MONTH(B52)<11,MONTH(B52)+2,IF(MONTH(B52)=11,1,2)),1)-1 -> 46812
B55: =DATE(YEAR(B56),MONTH(B56),1) -> 46813
B56: =DATE(IF(MONTH(B54)<11,YEAR(B54),YEAR(B54)+1),IF(MONTH(B54)<11,MONTH(B54)+2,IF(MONTH(B54)=11,1,2)),1)-1 -> 46843
